code size: 80
code size: 9
code size: 25
code size: 532
code size: 7
code size: 15
code size: 23
code size: 82
code size: 17
code size: 3
code size: 51
code size: 89
code size: 18
; This file has been disassembled using luadec 2.0.2 by sztupy (http://winmo.sztupy.hu)
; Command line was: -dis M:\git repos\warframe-lua-disassembled\lua\Lotus\Interface\CephalonFragmentMessage.luac 

; Name:            
; Defined at line: 0
; #Upvalues:       0
; #Parameters:     0
; Is_vararg:       2
; Max Stack Size:  27

  1 [-]: GETGLOBAL R0 K0        ; R0 := 0x329BDC44
  2 [-]: LOADK     R1 K1        ; R1 := "EE.Interface.Utilities"
  3 [-]: CALL      R0 2 2       ; R0 := R0(R1)
  4 [-]: GETGLOBAL R1 K0        ; R1 := 0x329BDC44
  5 [-]: LOADK     R2 K2        ; R2 := "Lotus.Interface.LotusUtilities"
  6 [-]: CALL      R1 2 2       ; R1 := R1(R2)
  7 [-]: LOADNIL   R2 R3        ; R2 := R3 := nil
  8 [-]: MOVE      R4 R0        ; R4 := R0
  9 [-]: LOADK     R5 K3        ; R5 := 0
 10 [-]: LOADK     R6 K3        ; R6 := 0
 11 [-]: LOADNIL   R7 R7        ; R7 := nil
 12 [-]: MOVE      R8 R0        ; R8 := R0
 13 [-]: LOADK     R9 K3        ; R9 := 0
 14 [-]: LOADK     R10 K4       ; R10 := 8305377
 15 [-]: LOADK     R11 K5       ; R11 := 12638695
 16 [-]: LOADK     R12 K6       ; R12 := 14253793
 17 [-]: LOADK     R13 K7       ; R13 := 16503548
 18 [-]: LOADK     R14 K8       ; R14 := 1273751
 19 [-]: LOADK     R15 K8       ; R15 := 1273751
 20 [-]: LOADK     R16 K9       ; R16 := 15061656
 21 [-]: LOADK     R17 K10      ; R17 := 2236962
 22 [-]: LOADK     R18 K11      ; R18 := 7405584
 23 [-]: LOADK     R19 K12      ; R19 := 16777215
 24 [-]: LOADK     R20 K13      ; R20 := 12495206
 25 [-]: GETGLOBAL R21 K14      ; R21 := 0xB5A59043
 26 [-]: LOADK     R22 K15      ; R22 := 162
 27 [-]: LOADK     R23 K3       ; R23 := 0
 28 [-]: LOADK     R24 K16      ; R24 := 46
 29 [-]: CALL      R21 4 2      ; R21 := R21(R22,R23,R24)
 30 [-]: LOADK     R22 K17      ; R22 := 16709593
 31 [-]: CLOSURE   R23 0        ; R23 := closure(Function #1)
 32 [-]: MOVE      R0 R4        ; R0 := R4
 33 [-]: MOVE      R0 R3        ; R0 := R3
 34 [-]: CLOSURE   R24 1        ; R24 := closure(Function #2)
 35 [-]: MOVE      R0 R5        ; R0 := R5
 36 [-]: MOVE      R0 R6        ; R0 := R6
 37 [-]: MOVE      R0 R8        ; R0 := R8
 38 [-]: MOVE      R0 R0        ; R0 := R0
 39 [-]: CLOSURE   R25 2        ; R25 := closure(Function #3)
 40 [-]: MOVE      R0 R10       ; R0 := R10
 41 [-]: MOVE      R0 R11       ; R0 := R11
 42 [-]: MOVE      R0 R12       ; R0 := R12
 43 [-]: MOVE      R0 R13       ; R0 := R13
 44 [-]: MOVE      R0 R14       ; R0 := R14
 45 [-]: MOVE      R0 R15       ; R0 := R15
 46 [-]: MOVE      R0 R16       ; R0 := R16
 47 [-]: MOVE      R0 R22       ; R0 := R22
 48 [-]: MOVE      R0 R20       ; R0 := R20
 49 [-]: MOVE      R0 R6        ; R0 := R6
 50 [-]: MOVE      R0 R5        ; R0 := R5
 51 [-]: MOVE      R0 R24       ; R0 := R24
 52 [-]: MOVE      R0 R7        ; R0 := R7
 53 [-]: MOVE      R0 R0        ; R0 := R0
 54 [-]: MOVE      R0 R21       ; R0 := R21
 55 [-]: MOVE      R0 R17       ; R0 := R17
 56 [-]: MOVE      R0 R18       ; R0 := R18
 57 [-]: MOVE      R0 R19       ; R0 := R19
 58 [-]: MOVE      R0 R2        ; R0 := R2
 59 [-]: MOVE      R0 R1        ; R0 := R1
 60 [-]: MOVE      R0 R23       ; R0 := R23
 61 [-]: CLOSURE   R26 3        ; R26 := closure(Function #4)
 62 [-]: MOVE      R0 R2        ; R0 := R2
 63 [-]: MOVE      R0 R7        ; R0 := R7
 64 [-]: SETGLOBAL R26 K18      ; Initialize := R26
 65 [-]: SETGLOBAL R26 K19      ; 0x62648036 := R26
 66 [-]: CLOSURE   R26 4        ; R26 := closure(Function #5)
 67 [-]: MOVE      R0 R4        ; R0 := R4
 68 [-]: MOVE      R0 R3        ; R0 := R3
 69 [-]: MOVE      R0 R25       ; R0 := R25
 70 [-]: MOVE      R0 R7        ; R0 := R7
 71 [-]: MOVE      R0 R5        ; R0 := R5
 72 [-]: MOVE      R0 R8        ; R0 := R8
 73 [-]: MOVE      R0 R9        ; R0 := R9
 74 [-]: SETGLOBAL R26 K20      ; Update := R26
 75 [-]: SETGLOBAL R26 K21      ; 0x8C7099E9 := R26
 76 [-]: CLOSURE   R26 5        ; R26 := closure(Function #6)
 77 [-]: MOVE      R0 R3        ; R0 := R3
 78 [-]: SETGLOBAL R26 K22      ; ShowScanStatus := R26
 79 [-]: SETGLOBAL R26 K23      ; 0x2EE7CE90 := R26
 80 [-]: RETURN    R0 1         ; return 


; Function #1:
;
; Name:            
; Defined at line: 43
; #Upvalues:       2
; #Parameters:     0
; Is_vararg:       0
; Max Stack Size:  2

  1 [-]: MOVE      R0 R0        ; R0 := R0
  2 [-]: MOVE      R0 R0        ; R0 := R0
  3 [-]: GETUPVAL  R0 U1        ; R0 := U1
  4 [-]: EQ        0 R0 K0      ; if R0 ~= nil then PC := 9
  5 [-]: JMP       9            ; PC := 9
  6 [-]: GETGLOBAL R0 K1        ; R0 := mMovie
  7 [-]: SELF      R0 R0 K2     ; R1 := R0; R0 := R0["0xA58BB96C"]
  8 [-]: CALL      R0 2 1       ; R0(R1)
  9 [-]: RETURN    R0 1         ; return 


; Function #2:
;
; Name:            
; Defined at line: 50
; #Upvalues:       4
; #Parameters:     1
; Is_vararg:       0
; Max Stack Size:  10

  1 [-]: GETUPVAL  R1 U0        ; R1 := U0
  2 [-]: GETUPVAL  R2 U1        ; R2 := U1
  3 [-]: SUB       R1 R1 R2     ; R1 := R1 - R2
  4 [-]: MUL       R1 R1 R0     ; R1 := R1 * R0
  5 [-]: GETUPVAL  R2 U1        ; R2 := U1
  6 [-]: ADD       R1 R1 R2     ; R1 := R1 + R2
  7 [-]: DIV       R1 R1 K0     ; R1 := R1 / 100
  8 [-]: LE        0 K1 R1      ; if 1 > R1 then PC := 16
  9 [-]: JMP       16           ; PC := 16
 10 [-]: MOVE      R2 R1        ; R2 := R1
 11 [-]: MOVE      R2 R2        ; R2 := R2
 12 [-]: GETUPVAL  R2 U3        ; R2 := U3
 13 [-]: GETTABLE  R2 R2 K2     ; R2 := R2["0x25992394"]
 14 [-]: GETGLOBAL R3 K3        ; R3 := nemesisHintFullSound
 15 [-]: CALL      R2 2 1       ; R2(R3)
 16 [-]: GETGLOBAL R2 K4        ; R2 := mMovie
 17 [-]: SELF      R2 R2 K5     ; R3 := R2; R2 := R2["0x302AAB2F"]
 18 [-]: LOADK     R4 K6        ; R4 := "Message.Icon.HintProgress"
 19 [-]: LOADK     R5 K7        ; R5 := "AlphaTestThreshold"
 20 [-]: MOVE      R6 R1        ; R6 := R1
 21 [-]: LOADK     R7 K8        ; R7 := 0
 22 [-]: LOADK     R8 K8        ; R8 := 0
 23 [-]: LOADK     R9 K8        ; R9 := 0
 24 [-]: CALL      R2 8 1       ; R2(R3,R4,R5,R6,R7,R8,R9)
 25 [-]: RETURN    R0 1         ; return 


; Function #3:
;
; Name:            
; Defined at line: 59
; #Upvalues:       21
; #Parameters:     4
; Is_vararg:       0
; Max Stack Size:  35

  1 [-]: LOADK     R4 K0        ; R4 := 1.5
  2 [-]: GETGLOBAL R5 K1        ; R5 := string
  3 [-]: GETTABLE  R5 R5 K2     ; R5 := R5["0x639C642A"]
  4 [-]: MOVE      R6 R0        ; R6 := R0
  5 [-]: CALL      R5 2 2       ; R5 := R5(R6)
  6 [-]: MOVE      R0 R5        ; R0 := R5
  7 [-]: GETUPVAL  R5 U0        ; R5 := U0
  8 [-]: MOVE      R6 R0        ; R6 := R0
  9 [-]: LOADK     R7 K3        ; R7 := 100
 10 [-]: LOADK     R8 K4        ; R8 := 2.5599999427795
 11 [-]: GETUPVAL  R9 U1        ; R9 := U1
 12 [-]: LOADK     R10 K5       ; R10 := "Lore"
 13 [-]: EQ        0 R3 K6      ; if R3 ~= "SONG" then PC := 19
 14 [-]: JMP       19           ; PC := 19
 15 [-]: GETUPVAL  R5 U2        ; R5 := U2
 16 [-]: GETUPVAL  R9 U3        ; R9 := U3
 17 [-]: LOADK     R10 K7       ; R10 := "Song"
 18 [-]: JMP       41           ; PC := 41
 19 [-]: EQ        0 R3 K8      ; if R3 ~= "FIGHTER" then PC := 25
 20 [-]: JMP       25           ; PC := 25
 21 [-]: GETUPVAL  R5 U4        ; R5 := U4
 22 [-]: GETUPVAL  R9 U5        ; R9 := U5
 23 [-]: LOADK     R10 K9       ; R10 := "Arcade"
 24 [-]: JMP       41           ; PC := 41
 25 [-]: EQ        0 R3 K10     ; if R3 ~= "NEMESIS" then PC := 30
 26 [-]: JMP       30           ; PC := 30
 27 [-]: GETUPVAL  R5 U6        ; R5 := U6
 28 [-]: LOADK     R10 K11      ; R10 := "NemesisPickup"
 29 [-]: JMP       41           ; PC := 41
 30 [-]: EQ        0 R3 K12     ; if R3 ~= "NEMESIS_HINT" then PC := 35
 31 [-]: JMP       35           ; PC := 35
 32 [-]: LOADK     R10 K13      ; R10 := "NemesisHint"
 33 [-]: MOVE      R6 R1        ; R6 := R1
 34 [-]: JMP       41           ; PC := 41
 35 [-]: EQ        0 R3 K14     ; if R3 ~= "PARTIAL_NEMESIS_HINT" then PC := 41
 36 [-]: JMP       41           ; PC := 41
 37 [-]: LOADK     R10 K15      ; R10 := "PartialNemesisHint"
 38 [-]: MOVE      R6 R1        ; R6 := R1
 39 [-]: LOADK     R7 K16       ; R7 := 75
 40 [-]: LOADK     R8 K17       ; R8 := 1.9199999570847
 41 [-]: GETGLOBAL R11 K18      ; R11 := 0x8C64AFA9
 42 [-]: GETGLOBAL R12 K19      ; R12 := mMovie
 43 [-]: LOADK     R13 K20      ; R13 := "Message.gotoAndStop"
 44 [-]: MOVE      R14 R10      ; R14 := R10
 45 [-]: CALL      R11 4 1      ; R11(R12,R13,R14)
 46 [-]: LOADK     R11 K21      ; R11 := 20
 47 [-]: TEST      R6 0         ; if not R6 then PC := 345
 48 [-]: JMP       345          ; PC := 345
 49 [-]: GETGLOBAL R12 K19      ; R12 := mMovie
 50 [-]: SELF      R12 R12 K22  ; R13 := R12; R12 := R12["0x880196A7"]
 51 [-]: LOADK     R14 K23      ; R14 := "Message"
 52 [-]: LOADK     R15 K24      ; R15 := "Hint"
 53 [-]: LOADK     R16 K25      ; R16 := "_color"
 54 [-]: GETUPVAL  R17 U7       ; R17 := U7
 55 [-]: CALL      R12 6 1      ; R12(R13,R14,R15,R16,R17)
 56 [-]: GETGLOBAL R12 K19      ; R12 := mMovie
 57 [-]: SELF      R12 R12 K22  ; R13 := R12; R12 := R12["0x880196A7"]
 58 [-]: LOADK     R14 K23      ; R14 := "Message"
 59 [-]: LOADK     R15 K26      ; R15 := "Lines"
 60 [-]: LOADK     R16 K25      ; R16 := "_color"
 61 [-]: GETUPVAL  R17 U8       ; R17 := U8
 62 [-]: CALL      R12 6 1      ; R12(R13,R14,R15,R16,R17)
 63 [-]: GETGLOBAL R12 K19      ; R12 := mMovie
 64 [-]: SELF      R12 R12 K22  ; R13 := R12; R12 := R12["0x880196A7"]
 65 [-]: LOADK     R14 K27      ; R14 := "Message.Icon"
 66 [-]: LOADK     R15 K28      ; R15 := "Icon"
 67 [-]: LOADK     R16 K25      ; R16 := "_color"
 68 [-]: GETUPVAL  R17 U7       ; R17 := U7
 69 [-]: CALL      R12 6 1      ; R12(R13,R14,R15,R16,R17)
 70 [-]: GETGLOBAL R12 K19      ; R12 := mMovie
 71 [-]: SELF      R12 R12 K22  ; R13 := R12; R12 := R12["0x880196A7"]
 72 [-]: LOADK     R14 K27      ; R14 := "Message.Icon"
 73 [-]: LOADK     R15 K29      ; R15 := "HintProgress"
 74 [-]: LOADK     R16 K25      ; R16 := "_color"
 75 [-]: GETUPVAL  R17 U7       ; R17 := U7
 76 [-]: CALL      R12 6 1      ; R12(R13,R14,R15,R16,R17)
 77 [-]: GETGLOBAL R12 K19      ; R12 := mMovie
 78 [-]: SELF      R12 R12 K22  ; R13 := R12; R12 := R12["0x880196A7"]
 79 [-]: LOADK     R14 K27      ; R14 := "Message.Icon"
 80 [-]: LOADK     R15 K30      ; R15 := "Hint2"
 81 [-]: LOADK     R16 K25      ; R16 := "_color"
 82 [-]: GETUPVAL  R17 U7       ; R17 := U7
 83 [-]: CALL      R12 6 1      ; R12(R13,R14,R15,R16,R17)
 84 [-]: GETGLOBAL R12 K19      ; R12 := mMovie
 85 [-]: SELF      R12 R12 K22  ; R13 := R12; R12 := R12["0x880196A7"]
 86 [-]: LOADK     R14 K27      ; R14 := "Message.Icon"
 87 [-]: LOADK     R15 K31      ; R15 := "Hint3"
 88 [-]: LOADK     R16 K25      ; R16 := "_color"
 89 [-]: GETUPVAL  R17 U7       ; R17 := U7
 90 [-]: CALL      R12 6 1      ; R12(R13,R14,R15,R16,R17)
 91 [-]: GETGLOBAL R12 K19      ; R12 := mMovie
 92 [-]: SELF      R12 R12 K22  ; R13 := R12; R12 := R12["0x880196A7"]
 93 [-]: LOADK     R14 K23      ; R14 := "Message"
 94 [-]: LOADK     R15 K28      ; R15 := "Icon"
 95 [-]: LOADK     R16 K32      ; R16 := "_alpha"
 96 [-]: LOADK     R17 K33      ; R17 := 0
 97 [-]: CALL      R12 6 1      ; R12(R13,R14,R15,R16,R17)
 98 [-]: GETGLOBAL R12 K19      ; R12 := mMovie
 99 [-]: SELF      R12 R12 K22  ; R13 := R12; R12 := R12["0x880196A7"]
100 [-]: LOADK     R14 K23      ; R14 := "Message"
101 [-]: LOADK     R15 K28      ; R15 := "Icon"
102 [-]: LOADK     R16 K34      ; R16 := "_xscale"
103 [-]: LOADK     R17 K35      ; R17 := 1
104 [-]: CALL      R12 6 1      ; R12(R13,R14,R15,R16,R17)
105 [-]: GETGLOBAL R12 K19      ; R12 := mMovie
106 [-]: SELF      R12 R12 K22  ; R13 := R12; R12 := R12["0x880196A7"]
107 [-]: LOADK     R14 K23      ; R14 := "Message"
108 [-]: LOADK     R15 K28      ; R15 := "Icon"
109 [-]: LOADK     R16 K36      ; R16 := "_yscale"
110 [-]: LOADK     R17 K35      ; R17 := 1
111 [-]: CALL      R12 6 1      ; R12(R13,R14,R15,R16,R17)
112 [-]: GETGLOBAL R12 K19      ; R12 := mMovie
113 [-]: SELF      R12 R12 K22  ; R13 := R12; R12 := R12["0x880196A7"]
114 [-]: LOADK     R14 K23      ; R14 := "Message"
115 [-]: LOADK     R15 K37      ; R15 := "CloudTop"
116 [-]: LOADK     R16 K32      ; R16 := "_alpha"
117 [-]: MOVE      R17 R7       ; R17 := R7
118 [-]: CALL      R12 6 1      ; R12(R13,R14,R15,R16,R17)
119 [-]: GETGLOBAL R12 K19      ; R12 := mMovie
120 [-]: SELF      R12 R12 K22  ; R13 := R12; R12 := R12["0x880196A7"]
121 [-]: LOADK     R14 K23      ; R14 := "Message"
122 [-]: LOADK     R15 K38      ; R15 := "CloudBottom"
123 [-]: LOADK     R16 K32      ; R16 := "_alpha"
124 [-]: MOVE      R17 R7       ; R17 := R7
125 [-]: CALL      R12 6 1      ; R12(R13,R14,R15,R16,R17)
126 [-]: GETGLOBAL R12 K19      ; R12 := mMovie
127 [-]: SELF      R12 R12 K22  ; R13 := R12; R12 := R12["0x880196A7"]
128 [-]: LOADK     R14 K23      ; R14 := "Message"
129 [-]: LOADK     R15 K39      ; R15 := "CloudDots"
130 [-]: LOADK     R16 K32      ; R16 := "_alpha"
131 [-]: MOVE      R17 R7       ; R17 := R7
132 [-]: CALL      R12 6 1      ; R12(R13,R14,R15,R16,R17)
133 [-]: GETGLOBAL R12 K19      ; R12 := mMovie
134 [-]: SELF      R12 R12 K40  ; R13 := R12; R12 := R12["0x7E1F26D7"]
135 [-]: LOADK     R14 K41      ; R14 := "Message.CloudTop"
136 [-]: GETGLOBAL R15 K42      ; R15 := smokeMaterial
137 [-]: CALL      R12 4 1      ; R12(R13,R14,R15)
138 [-]: GETGLOBAL R12 K19      ; R12 := mMovie
139 [-]: SELF      R12 R12 K40  ; R13 := R12; R12 := R12["0x7E1F26D7"]
140 [-]: LOADK     R14 K43      ; R14 := "Message.CloudBottom"
141 [-]: GETGLOBAL R15 K42      ; R15 := smokeMaterial
142 [-]: CALL      R12 4 1      ; R12(R13,R14,R15)
143 [-]: GETGLOBAL R12 K19      ; R12 := mMovie
144 [-]: SELF      R12 R12 K40  ; R13 := R12; R12 := R12["0x7E1F26D7"]
145 [-]: LOADK     R14 K44      ; R14 := "Message.CloudDots"
146 [-]: GETGLOBAL R15 K45      ; R15 := kuvaMaterial
147 [-]: CALL      R12 4 1      ; R12(R13,R14,R15)
148 [-]: LOADK     R12 K3       ; R12 := 100
149 [-]: LE        1 K3 R1      ; if 100 <= R1 then PC := 152
150 [-]: JMP       152          ; PC := 152
151 [-]: MOVE      R13 R0       ; R13 := R0
152 [-]: MOVE      R13 R1       ; R13 := R1
153 [-]: LT        1 K46 R1     ; if 200 < R1 then PC := 156
154 [-]: JMP       156          ; PC := 156
155 [-]: MOVE      R14 R0       ; R14 := R0
156 [-]: MOVE      R14 R1       ; R14 := R1
157 [-]: LT        1 K47 R1     ; if 300 < R1 then PC := 160
158 [-]: JMP       160          ; PC := 160
159 [-]: MOVE      R15 R0       ; R15 := R0
160 [-]: MOVE      R15 R1       ; R15 := R1
161 [-]: GETGLOBAL R16 K19      ; R16 := mMovie
162 [-]: SELF      R16 R16 K22  ; R17 := R16; R16 := R16["0x880196A7"]
163 [-]: LOADK     R18 K27      ; R18 := "Message.Icon"
164 [-]: LOADK     R19 K29      ; R19 := "HintProgress"
165 [-]: LOADK     R20 K48      ; R20 := "_visible"
166 [-]: MOVE      R21 R13      ; R21 := R13
167 [-]: CALL      R16 6 1      ; R16(R17,R18,R19,R20,R21)
168 [-]: GETGLOBAL R16 K19      ; R16 := mMovie
169 [-]: SELF      R16 R16 K22  ; R17 := R16; R16 := R16["0x880196A7"]
170 [-]: LOADK     R18 K27      ; R18 := "Message.Icon"
171 [-]: LOADK     R19 K30      ; R19 := "Hint2"
172 [-]: LOADK     R20 K48      ; R20 := "_visible"
173 [-]: TESTSET   R21 R13 0    ; if not R13 then PC := 176 else R21 := R13
174 [-]: JMP       176          ; PC := 176
175 [-]: MOVE      R21 R14      ; R21 := R14
176 [-]: CALL      R16 6 1      ; R16(R17,R18,R19,R20,R21)
177 [-]: GETGLOBAL R16 K19      ; R16 := mMovie
178 [-]: SELF      R16 R16 K22  ; R17 := R16; R16 := R16["0x880196A7"]
179 [-]: LOADK     R18 K27      ; R18 := "Message.Icon"
180 [-]: LOADK     R19 K31      ; R19 := "Hint3"
181 [-]: LOADK     R20 K48      ; R20 := "_visible"
182 [-]: TESTSET   R21 R13 0    ; if not R13 then PC := 185 else R21 := R13
183 [-]: JMP       185          ; PC := 185
184 [-]: MOVE      R21 R15      ; R21 := R15
185 [-]: CALL      R16 6 1      ; R16(R17,R18,R19,R20,R21)
186 [-]: TEST      R13 0        ; if not R13 then PC := 233
187 [-]: JMP       233          ; PC := 233
188 [-]: LOADK     R12 K49      ; R12 := 60
189 [-]: MOVE      R2 R9        ; R2 := R9
190 [-]: MOD       R16 R1 K3    ; R16 := R1 % 100
191 [-]: MOVE      R16 R10      ; R16 := R10
192 [-]: GETUPVAL  R16 U10      ; R16 := U10
193 [-]: GETUPVAL  R17 U9       ; R17 := U9
194 [-]: LT        0 R16 R17    ; if R16 >= R17 then PC := 198
195 [-]: JMP       198          ; PC := 198
196 [-]: LOADK     R16 K3       ; R16 := 100
197 [-]: MOVE      R16 R10      ; R16 := R10
198 [-]: GETGLOBAL R16 K19      ; R16 := mMovie
199 [-]: SELF      R16 R16 K50  ; R17 := R16; R16 := R16["0x17028E8F"]
200 [-]: LOADK     R18 K51      ; R18 := "Message.Title.text"
201 [-]: MOVE      R19 R0       ; R19 := R0
202 [-]: CALL      R16 4 1      ; R16(R17,R18,R19)
203 [-]: GETGLOBAL R16 K19      ; R16 := mMovie
204 [-]: SELF      R16 R16 K22  ; R17 := R16; R16 := R16["0x880196A7"]
205 [-]: LOADK     R18 K23      ; R18 := "Message"
206 [-]: LOADK     R19 K24      ; R19 := "Hint"
207 [-]: LOADK     R20 K52      ; R20 := "text"
208 [-]: LOADK     R21 K53      ; R21 := ""
209 [-]: CALL      R16 6 1      ; R16(R17,R18,R19,R20,R21)
210 [-]: GETGLOBAL R16 K19      ; R16 := mMovie
211 [-]: SELF      R16 R16 K40  ; R17 := R16; R16 := R16["0x7E1F26D7"]
212 [-]: LOADK     R18 K54      ; R18 := "Message.Icon.HintProgress"
213 [-]: GETGLOBAL R19 K55      ; R19 := radialProgressMaterial
214 [-]: CALL      R16 4 1      ; R16(R17,R18,R19)
215 [-]: GETGLOBAL R16 K19      ; R16 := mMovie
216 [-]: SELF      R16 R16 K56  ; R17 := R16; R16 := R16["0x4443A5E7"]
217 [-]: LOADK     R18 K57      ; R18 := "Message.Icon.Icon"
218 [-]: GETGLOBAL R19 K58      ; R19 := lichIconsPartial
219 [-]: GETGLOBAL R20 K59      ; R20 := lichIconMaterial
220 [-]: CALL      R16 5 1      ; R16(R17,R18,R19,R20)
221 [-]: GETGLOBAL R16 K19      ; R16 := mMovie
222 [-]: SELF      R16 R16 K60  ; R17 := R16; R16 := R16["0xE953BC1F"]
223 [-]: LOADK     R18 K57      ; R18 := "Message.Icon.Icon"
224 [-]: GETGLOBAL R19 K61      ; R19 := 0xEC274B1A
225 [-]: LOADK     R20 K62      ; R20 := "DetailMap"
226 [-]: CALL      R19 2 2      ; R19 := R19(R20)
227 [-]: GETGLOBAL R20 K63      ; R20 := lichIconsPartialGlow
228 [-]: CALL      R16 5 1      ; R16(R17,R18,R19,R20)
229 [-]: GETUPVAL  R16 U11      ; R16 := U11
230 [-]: LOADK     R17 K33      ; R17 := 0
231 [-]: CALL      R16 2 1      ; R16(R17)
232 [-]: JMP       282          ; PC := 282
233 [-]: GETGLOBAL R16 K64      ; R16 := 0x6374FD98
234 [-]: MOVE      R17 R1       ; R17 := R1
235 [-]: LOADK     R18 K35      ; R18 := 1
236 [-]: GETGLOBAL R19 K65      ; R19 := lichIcons
237 [-]: LEN       R19 R19      ; R19 := # R19
238 [-]: CALL      R16 4 2      ; R16 := R16(R17,R18,R19)
239 [-]: MOVE      R1 R16       ; R1 := R16
240 [-]: GETGLOBAL R16 K19      ; R16 := mMovie
241 [-]: SELF      R16 R16 K50  ; R17 := R16; R16 := R16["0x17028E8F"]
242 [-]: LOADK     R18 K51      ; R18 := "Message.Title.text"
243 [-]: MOVE      R19 R0       ; R19 := R0
244 [-]: CALL      R16 4 1      ; R16(R17,R18,R19)
245 [-]: GETGLOBAL R16 K19      ; R16 := mMovie
246 [-]: SELF      R16 R16 K50  ; R17 := R16; R16 := R16["0x17028E8F"]
247 [-]: LOADK     R18 K66      ; R18 := "Message.Hint.text"
248 [-]: GETGLOBAL R19 K67      ; R19 := lichIconLoc
249 [-]: GETTABLE  R19 R19 R1   ; R19 := R19[R1]
250 [-]: SELF      R19 R19 K68  ; R20 := R19; R19 := R19["0x5EC7A3D2"]
251 [-]: CALL      R19 2 0      ; R19,... := R19(R20)
252 [-]: CALL      R16 0 1      ; R16(R17,...)
253 [-]: GETGLOBAL R16 K19      ; R16 := mMovie
254 [-]: SELF      R16 R16 K56  ; R17 := R16; R16 := R16["0x4443A5E7"]
255 [-]: LOADK     R18 K57      ; R18 := "Message.Icon.Icon"
256 [-]: GETGLOBAL R19 K65      ; R19 := lichIcons
257 [-]: GETTABLE  R19 R19 R1   ; R19 := R19[R1]
258 [-]: GETGLOBAL R20 K59      ; R20 := lichIconMaterial
259 [-]: CALL      R16 5 1      ; R16(R17,R18,R19,R20)
260 [-]: GETGLOBAL R16 K19      ; R16 := mMovie
261 [-]: SELF      R16 R16 K60  ; R17 := R16; R16 := R16["0xE953BC1F"]
262 [-]: LOADK     R18 K57      ; R18 := "Message.Icon.Icon"
263 [-]: GETGLOBAL R19 K61      ; R19 := 0xEC274B1A
264 [-]: LOADK     R20 K62      ; R20 := "DetailMap"
265 [-]: CALL      R19 2 2      ; R19 := R19(R20)
266 [-]: GETGLOBAL R20 K69      ; R20 := lichIconGlows
267 [-]: GETTABLE  R20 R20 R1   ; R20 := R20[R1]
268 [-]: CALL      R16 5 1      ; R16(R17,R18,R19,R20)
269 [-]: GETGLOBAL R16 K70      ; R16 := 0x400E7765
270 [-]: GETGLOBAL R17 K71      ; R17 := lichIconSounds
271 [-]: GETTABLE  R17 R17 R1   ; R17 := R17[R1]
272 [-]: CALL      R16 2 2      ; R16 := R16(R17)
273 [-]: TEST      R16 1        ; if R16 then PC := 282
274 [-]: JMP       282          ; PC := 282
275 [-]: GETUPVAL  R16 U12      ; R16 := U12
276 [-]: SELF      R16 R16 K72  ; R17 := R16; R16 := R16["0x61494587"]
277 [-]: ADD       R18 R4 K35   ; R18 := R4 + 1
278 [-]: CLOSURE   R19 0        ; R19 := closure(Function #3.1)
279 [-]: GETUPVAL  R0 U13       ; R0 := U13
280 [-]: MOVE      R0 R1        ; R0 := R1
281 [-]: CALL      R16 4 1      ; R16(R17,R18,R19)
282 [-]: GETGLOBAL R16 K73      ; R16 := 0x52E17A90
283 [-]: GETGLOBAL R17 K19      ; R17 := mMovie
284 [-]: LOADK     R18 K27      ; R18 := "Message.Icon"
285 [-]: GETGLOBAL R19 K74      ; R19 := UISys
286 [-]: GETTABLE  R19 R19 K75  ; R19 := R19["FlashInstance_EASE_OUT_BACK"]
287 [-]: NEWTABLE  R20 3 0      ; R20 := {}
288 [-]: LOADK     R21 K32      ; R21 := "_alpha"
289 [-]: LOADK     R22 K34      ; R22 := "_xscale"
290 [-]: LOADK     R23 K36      ; R23 := "_yscale"
291 [-]: SETLIST   R20 3 1      ; R20[(1-1)*FPF+i] := R(20+i), 1 <= i <= 3
292 [-]: NEWTABLE  R21 3 0      ; R21 := {}
293 [-]: MOVE      R22 R12      ; R22 := R12
294 [-]: MUL       R23 K3 R8    ; R23 := 100 * R8
295 [-]: MUL       R24 K3 R8    ; R24 := 100 * R8
296 [-]: SETLIST   R21 3 1      ; R21[(1-1)*FPF+i] := R(21+i), 1 <= i <= 3
297 [-]: LOADK     R22 K76      ; R22 := 0.40000000596046
298 [-]: ADD       R23 R4 K77   ; R23 := R4 + 0.75
299 [-]: CLOSURE   R24 1        ; R24 := closure(Function #3.2)
300 [-]: GETUPVAL  R0 U11       ; R0 := U11
301 [-]: CALL      R16 9 1      ; R16(R17,R18,R19,R20,R21,R22,R23,R24)
302 [-]: GETGLOBAL R16 K19      ; R16 := mMovie
303 [-]: SELF      R16 R16 K40  ; R17 := R16; R16 := R16["0x7E1F26D7"]
304 [-]: LOADK     R18 K78      ; R18 := "Message.Lines"
305 [-]: GETGLOBAL R19 K79      ; R19 := visibleRangeMaterial
306 [-]: CALL      R16 4 1      ; R16(R17,R18,R19)
307 [-]: GETGLOBAL R16 K19      ; R16 := mMovie
308 [-]: SELF      R16 R16 K80  ; R17 := R16; R16 := R16["0x302AAB2F"]
309 [-]: LOADK     R18 K78      ; R18 := "Message.Lines"
310 [-]: LOADK     R19 K81      ; R19 := "VisibilitySize"
311 [-]: LOADK     R20 K82      ; R20 := 0.059999998658895
312 [-]: LOADK     R21 K33      ; R21 := 0
313 [-]: LOADK     R22 K33      ; R22 := 0
314 [-]: LOADK     R23 K33      ; R23 := 0
315 [-]: CALL      R16 8 1      ; R16(R17,R18,R19,R20,R21,R22,R23)
316 [-]: GETGLOBAL R16 K19      ; R16 := mMovie
317 [-]: SELF      R16 R16 K80  ; R17 := R16; R16 := R16["0x302AAB2F"]
318 [-]: LOADK     R18 K78      ; R18 := "Message.Lines"
319 [-]: LOADK     R19 K83      ; R19 := "VisibilityFadeSize"
320 [-]: LOADK     R20 K84      ; R20 := 0.10000000149012
321 [-]: LOADK     R21 K33      ; R21 := 0
322 [-]: LOADK     R22 K33      ; R22 := 0
323 [-]: LOADK     R23 K33      ; R23 := 0
324 [-]: CALL      R16 8 1      ; R16(R17,R18,R19,R20,R21,R22,R23)
325 [-]: GETGLOBAL R16 K19      ; R16 := mMovie
326 [-]: SELF      R16 R16 K80  ; R17 := R16; R16 := R16["0x302AAB2F"]
327 [-]: LOADK     R18 K57      ; R18 := "Message.Icon.Icon"
328 [-]: LOADK     R19 K85      ; R19 := "DetailMapTint"
329 [-]: GETUPVAL  R20 U14      ; R20 := U14
330 [-]: GETTABLE  R20 R20 K86  ; R20 := R20["red"]
331 [-]: DIV       R20 R20 K87  ; R20 := R20 / 255
332 [-]: GETUPVAL  R21 U14      ; R21 := U14
333 [-]: GETTABLE  R21 R21 K88  ; R21 := R21["green"]
334 [-]: DIV       R21 R21 K87  ; R21 := R21 / 255
335 [-]: GETUPVAL  R22 U14      ; R22 := U14
336 [-]: GETTABLE  R22 R22 K89  ; R22 := R22["blue"]
337 [-]: DIV       R22 R22 K87  ; R22 := R22 / 255
338 [-]: LOADK     R23 K77      ; R23 := 0.75
339 [-]: CALL      R16 8 1      ; R16(R17,R18,R19,R20,R21,R22,R23)
340 [-]: GETUPVAL  R16 U13      ; R16 := U13
341 [-]: GETTABLE  R16 R16 K90  ; R16 := R16["0x25992394"]
342 [-]: GETGLOBAL R17 K91      ; R17 := nemesisTransitionInSound
343 [-]: CALL      R16 2 1      ; R16(R17)
344 [-]: JMP       416          ; PC := 416
345 [-]: EQ        0 R3 K10     ; if R3 ~= "NEMESIS" then PC := 354
346 [-]: JMP       354          ; PC := 354
347 [-]: LOADK     R11 K92      ; R11 := 30
348 [-]: GETGLOBAL R16 K19      ; R16 := mMovie
349 [-]: SELF      R16 R16 K50  ; R17 := R16; R16 := R16["0x17028E8F"]
350 [-]: LOADK     R18 K51      ; R18 := "Message.Title.text"
351 [-]: MOVE      R19 R0       ; R19 := R0
352 [-]: CALL      R16 4 1      ; R16(R17,R18,R19)
353 [-]: JMP       416          ; PC := 416
354 [-]: GETGLOBAL R16 K19      ; R16 := mMovie
355 [-]: SELF      R16 R16 K22  ; R17 := R16; R16 := R16["0x880196A7"]
356 [-]: LOADK     R18 K23      ; R18 := "Message"
357 [-]: LOADK     R19 K93      ; R19 := "Flare"
358 [-]: LOADK     R20 K25      ; R20 := "_color"
359 [-]: MOVE      R21 R5       ; R21 := R5
360 [-]: CALL      R16 6 1      ; R16(R17,R18,R19,R20,R21)
361 [-]: GETGLOBAL R16 K19      ; R16 := mMovie
362 [-]: SELF      R16 R16 K22  ; R17 := R16; R16 := R16["0x880196A7"]
363 [-]: LOADK     R18 K23      ; R18 := "Message"
364 [-]: LOADK     R19 K94      ; R19 := "Title"
365 [-]: LOADK     R20 K25      ; R20 := "_color"
366 [-]: MOVE      R21 R9       ; R21 := R9
367 [-]: CALL      R16 6 1      ; R16(R17,R18,R19,R20,R21)
368 [-]: GETGLOBAL R16 K19      ; R16 := mMovie
369 [-]: SELF      R16 R16 K22  ; R17 := R16; R16 := R16["0x880196A7"]
370 [-]: LOADK     R18 K95      ; R18 := "Message.Progress"
371 [-]: LOADK     R19 K96      ; R19 := "Notch1"
372 [-]: LOADK     R20 K25      ; R20 := "_color"
373 [-]: MOVE      R21 R9       ; R21 := R9
374 [-]: CALL      R16 6 1      ; R16(R17,R18,R19,R20,R21)
375 [-]: EQ        0 R1 R2      ; if R1 ~= R2 then PC := 405
376 [-]: JMP       405          ; PC := 405
377 [-]: EQ        0 R3 K6      ; if R3 ~= "SONG" then PC := 387
378 [-]: JMP       387          ; PC := 387
379 [-]: GETGLOBAL R16 K19      ; R16 := mMovie
380 [-]: SELF      R16 R16 K50  ; R17 := R16; R16 := R16["0x17028E8F"]
381 [-]: LOADK     R18 K51      ; R18 := "Message.Title.text"
382 [-]: LOADK     R19 K97      ; R19 := "/Lotus/Language/Menu/SongFragmentComplete"
383 [-]: NEWTABLE  R20 0 1      ; R20 := {}
384 [-]: SETTABLE  R20 K98 R0   ; R20["TARGET"] := R0
385 [-]: CALL      R16 5 1      ; R16(R17,R18,R19,R20)
386 [-]: JMP       412          ; PC := 412
387 [-]: EQ        0 R3 K8      ; if R3 ~= "FIGHTER" then PC := 397
388 [-]: JMP       397          ; PC := 397
389 [-]: GETGLOBAL R16 K19      ; R16 := mMovie
390 [-]: SELF      R16 R16 K50  ; R17 := R16; R16 := R16["0x17028E8F"]
391 [-]: LOADK     R18 K51      ; R18 := "Message.Title.text"
392 [-]: LOADK     R19 K97      ; R19 := "/Lotus/Language/Menu/SongFragmentComplete"
393 [-]: NEWTABLE  R20 0 1      ; R20 := {}
394 [-]: SETTABLE  R20 K98 R0   ; R20["TARGET"] := R0
395 [-]: CALL      R16 5 1      ; R16(R17,R18,R19,R20)
396 [-]: JMP       412          ; PC := 412
397 [-]: GETGLOBAL R16 K19      ; R16 := mMovie
398 [-]: SELF      R16 R16 K50  ; R17 := R16; R16 := R16["0x17028E8F"]
399 [-]: LOADK     R18 K51      ; R18 := "Message.Title.text"
400 [-]: LOADK     R19 K99      ; R19 := "/Lotus/Language/Menu/CephalonFragmentComplete"
401 [-]: NEWTABLE  R20 0 1      ; R20 := {}
402 [-]: SETTABLE  R20 K98 R0   ; R20["TARGET"] := R0
403 [-]: CALL      R16 5 1      ; R16(R17,R18,R19,R20)
404 [-]: JMP       412          ; PC := 412
405 [-]: GETGLOBAL R16 K19      ; R16 := mMovie
406 [-]: SELF      R16 R16 K50  ; R17 := R16; R16 := R16["0x17028E8F"]
407 [-]: LOADK     R18 K51      ; R18 := "Message.Title.text"
408 [-]: LOADK     R19 K100     ; R19 := "/Lotus/Language/Menu/CephalonFragmentFound"
409 [-]: NEWTABLE  R20 0 1      ; R20 := {}
410 [-]: SETTABLE  R20 K98 R0   ; R20["TARGET"] := R0
411 [-]: CALL      R16 5 1      ; R16(R17,R18,R19,R20)
412 [-]: GETUPVAL  R16 U13      ; R16 := U13
413 [-]: GETTABLE  R16 R16 K90  ; R16 := R16["0x25992394"]
414 [-]: GETGLOBAL R17 K101     ; R17 := transitionInSound
415 [-]: CALL      R16 2 1      ; R16(R17)
416 [-]: TEST      R6 1         ; if R6 then PC := 507
417 [-]: JMP       507          ; PC := 507
418 [-]: LOADK     R16 K35      ; R16 := 1
419 [-]: MOVE      R17 R2       ; R17 := R2
420 [-]: LOADK     R18 K35      ; R18 := 1
421 [-]: FORPREP   R16 506      ; R16 -= R18; PC := 506
422 [-]: LOADK     R20 K102     ; R20 := "Message.Progress.Notch"
423 [-]: MOVE      R21 R19      ; R21 := R19
424 [-]: CONCAT    R20 R20 R21  ; R20 := R20 .. R21
425 [-]: GETGLOBAL R21 K19      ; R21 := mMovie
426 [-]: SELF      R21 R21 K103 ; R22 := R21; R21 := R21["0x6B7B470B"]
427 [-]: MOVE      R23 R20      ; R23 := R20
428 [-]: CALL      R21 3 2      ; R21 := R21(R22,R23)
429 [-]: GETGLOBAL R22 K70      ; R22 := 0x400E7765
430 [-]: MOVE      R23 R21      ; R23 := R21
431 [-]: CALL      R22 2 2      ; R22 := R22(R23)
432 [-]: TEST      R22 1        ; if R22 then PC := 439
433 [-]: JMP       439          ; PC := 439
434 [-]: GETGLOBAL R22 K104     ; R22 := 0x9FAED6BC
435 [-]: MOVE      R23 R21      ; R23 := R21
436 [-]: CALL      R22 2 2      ; R22 := R22(R23)
437 [-]: EQ        0 R22 K105   ; if R22 ~= "undefined" then PC := 447
438 [-]: JMP       447          ; PC := 447
439 [-]: GETGLOBAL R22 K18      ; R22 := 0x8C64AFA9
440 [-]: GETGLOBAL R23 K19      ; R23 := mMovie
441 [-]: LOADK     R24 K106     ; R24 := "Message.Progress.Notch1.duplicateMovieClip"
442 [-]: LOADK     R25 K107     ; R25 := "Notch"
443 [-]: MOVE      R26 R19      ; R26 := R19
444 [-]: CONCAT    R25 R25 R26  ; R25 := R25 .. R26
445 [-]: ADD       R26 K108 R19 ; R26 := 1000 + R19
446 [-]: CALL      R22 5 1      ; R22(R23,R24,R25,R26)
447 [-]: SUB       R22 R2 K35   ; R22 := R2 - 1
448 [-]: MUL       R22 R22 R11  ; R22 := R22 * R11
449 [-]: MUL       R22 R22 K109 ; R22 := R22 * 0.5
450 [-]: UNM       R22 R22      ; R22 := - R22
451 [-]: SUB       R23 R19 K35  ; R23 := R19 - 1
452 [-]: MUL       R23 R23 R11  ; R23 := R23 * R11
453 [-]: ADD       R23 R22 R23  ; R23 := R22 + R23
454 [-]: GETGLOBAL R24 K19      ; R24 := mMovie
455 [-]: SELF      R24 R24 K110 ; R25 := R24; R24 := R24["0x1C19D966"]
456 [-]: MOVE      R26 R20      ; R26 := R20
457 [-]: LOADK     R27 K111     ; R27 := "_x"
458 [-]: MOVE      R28 R23      ; R28 := R23
459 [-]: CALL      R24 5 1      ; R24(R25,R26,R27,R28)
460 [-]: LE        1 R19 R1     ; if R19 <= R1 then PC := 463
461 [-]: JMP       463          ; PC := 463
462 [-]: MOVE      R24 R0       ; R24 := R0
463 [-]: MOVE      R24 R1       ; R24 := R1
464 [-]: GETGLOBAL R25 K19      ; R25 := mMovie
465 [-]: SELF      R25 R25 K22  ; R26 := R25; R25 := R25["0x880196A7"]
466 [-]: MOVE      R27 R20      ; R27 := R20
467 [-]: LOADK     R28 K112     ; R28 := "Front"
468 [-]: LOADK     R29 K48      ; R29 := "_visible"
469 [-]: MOVE      R30 R24      ; R30 := R24
470 [-]: CALL      R25 6 1      ; R25(R26,R27,R28,R29,R30)
471 [-]: EQ        0 R3 K10     ; if R3 ~= "NEMESIS" then PC := 506
472 [-]: JMP       506          ; PC := 506
473 [-]: GETGLOBAL R25 K19      ; R25 := mMovie
474 [-]: SELF      R25 R25 K22  ; R26 := R25; R25 := R25["0x880196A7"]
475 [-]: MOVE      R27 R20      ; R27 := R20
476 [-]: LOADK     R28 K112     ; R28 := "Front"
477 [-]: LOADK     R29 K25      ; R29 := "_color"
478 [-]: MOVE      R30 R5       ; R30 := R5
479 [-]: CALL      R25 6 1      ; R25(R26,R27,R28,R29,R30)
480 [-]: GETGLOBAL R25 K19      ; R25 := mMovie
481 [-]: SELF      R25 R25 K22  ; R26 := R25; R25 := R25["0x880196A7"]
482 [-]: MOVE      R27 R20      ; R27 := R20
483 [-]: LOADK     R28 K113     ; R28 := "Back"
484 [-]: LOADK     R29 K25      ; R29 := "_color"
485 [-]: GETUPVAL  R30 U15      ; R30 := U15
486 [-]: CALL      R25 6 1      ; R25(R26,R27,R28,R29,R30)
487 [-]: GETGLOBAL R25 K19      ; R25 := mMovie
488 [-]: SELF      R25 R25 K22  ; R26 := R25; R25 := R25["0x880196A7"]
489 [-]: MOVE      R27 R20      ; R27 := R20
490 [-]: LOADK     R28 K114     ; R28 := "Glow"
491 [-]: LOADK     R29 K25      ; R29 := "_color"
492 [-]: TEST      R24 0        ; if not R24 then PC := 497
493 [-]: JMP       497          ; PC := 497
494 [-]: GETUPVAL  R30 U16      ; R30 := U16
495 [-]: TEST      R30 1        ; if R30 then PC := 498
496 [-]: JMP       498          ; PC := 498
497 [-]: GETUPVAL  R30 U17      ; R30 := U17
498 [-]: CALL      R25 6 1      ; R25(R26,R27,R28,R29,R30)
499 [-]: GETGLOBAL R25 K19      ; R25 := mMovie
500 [-]: SELF      R25 R25 K22  ; R26 := R25; R25 := R25["0x880196A7"]
501 [-]: MOVE      R27 R20      ; R27 := R20
502 [-]: LOADK     R28 K114     ; R28 := "Glow"
503 [-]: LOADK     R29 K48      ; R29 := "_visible"
504 [-]: MOVE      R30 R24      ; R30 := R24
505 [-]: CALL      R25 6 1      ; R25(R26,R27,R28,R29,R30)
506 [-]: FORLOOP   R16 422      ; R16 += R18; if R16 <= R17 then begin PC := 422; R19 := R16 end
507 [-]: CLOSURE   R25 2        ; R25 := closure(Function #3.3)
508 [-]: MOVE      R0 R3        ; R0 := R3
509 [-]: GETUPVAL  R0 U18       ; R0 := U18
510 [-]: GETGLOBAL R26 K73      ; R26 := 0x52E17A90
511 [-]: GETGLOBAL R27 K19      ; R27 := mMovie
512 [-]: LOADK     R28 K115     ; R28 := "_root"
513 [-]: GETGLOBAL R29 K74      ; R29 := UISys
514 [-]: GETTABLE  R29 R29 K116 ; R29 := R29["FlashInstance_EASE_OUT"]
515 [-]: NEWTABLE  R30 1 0      ; R30 := {}
516 [-]: LOADK     R31 K32      ; R31 := "_alpha"
517 [-]: SETLIST   R30 1 1      ; R30[(1-1)*FPF+i] := R(30+i), 1 <= i <= 1
518 [-]: NEWTABLE  R31 1 0      ; R31 := {}
519 [-]: LOADK     R32 K3       ; R32 := 100
520 [-]: SETLIST   R31 1 1      ; R31[(1-1)*FPF+i] := R(31+i), 1 <= i <= 1
521 [-]: MOVE      R32 R4       ; R32 := R4
522 [-]: LOADK     R33 K33      ; R33 := 0
523 [-]: CLOSURE   R34 3        ; R34 := closure(Function #3.4)
524 [-]: GETUPVAL  R0 U19       ; R0 := U19
525 [-]: GETUPVAL  R0 U14       ; R0 := U14
526 [-]: MOVE      R0 R6        ; R0 := R6
527 [-]: MOVE      R0 R25       ; R0 := R25
528 [-]: GETUPVAL  R0 U20       ; R0 := U20
529 [-]: CALL      R26 9 1      ; R26(R27,R28,R29,R30,R31,R32,R33,R34)
530 [-]: MOVE      R26 R1       ; R26 := R1
531 [-]: RETURN    R26 2        ; return R26
532 [-]: RETURN    R0 1         ; return 


; Function #3.1:
;
; Name:            
; Defined at line: 141
; #Upvalues:       2
; #Parameters:     0
; Is_vararg:       0
; Max Stack Size:  3

  1 [-]: GETUPVAL  R0 U0        ; R0 := U0
  2 [-]: GETTABLE  R0 R0 K0     ; R0 := R0["0x25992394"]
  3 [-]: GETGLOBAL R1 K1        ; R1 := lichIconSounds
  4 [-]: GETUPVAL  R2 U1        ; R2 := U1
  5 [-]: GETTABLE  R1 R1 R2     ; R1 := R1[R2]
  6 [-]: CALL      R0 2 1       ; R0(R1)
  7 [-]: RETURN    R0 1         ; return 


; Function #3.2:
;
; Name:            
; Defined at line: 148
; #Upvalues:       1
; #Parameters:     0
; Is_vararg:       0
; Max Stack Size:  8

  1 [-]: GETGLOBAL R0 K0        ; R0 := 0x52E17A90
  2 [-]: GETGLOBAL R1 K1        ; R1 := mMovie
  3 [-]: LOADK     R2 K2        ; R2 := "_root"
  4 [-]: GETGLOBAL R3 K3        ; R3 := UISys
  5 [-]: GETTABLE  R3 R3 K4     ; R3 := R3["FlashInstance_EASE_OUT"]
  6 [-]: NEWTABLE  R4 1 0       ; R4 := {}
  7 [-]: GETUPVAL  R5 U0        ; R5 := U0
  8 [-]: SETLIST   R4 1 1       ; R4[(1-1)*FPF+i] := R(4+i), 1 <= i <= 1
  9 [-]: NEWTABLE  R5 1 0       ; R5 := {}
 10 [-]: LOADK     R6 K5        ; R6 := 1
 11 [-]: SETLIST   R5 1 1       ; R5[(1-1)*FPF+i] := R(5+i), 1 <= i <= 1
 12 [-]: LOADK     R6 K6        ; R6 := 2
 13 [-]: LOADK     R7 K7        ; R7 := 0.5
 14 [-]: CALL      R0 8 1       ; R0(R1,R2,R3,R4,R5,R6,R7)
 15 [-]: RETURN    R0 1         ; return 


; Function #3.3:
;
; Name:            
; Defined at line: 203
; #Upvalues:       2
; #Parameters:     1
; Is_vararg:       0
; Max Stack Size:  7

  1 [-]: GETUPVAL  R1 U0        ; R1 := U0
  2 [-]: EQ        1 R1 K0      ; if R1 == "NEMESIS" then PC := 6
  3 [-]: JMP       6            ; PC := 6
  4 [-]: SUB       R1 K1 R0     ; R1 := 1 - R0
  5 [-]: MUL       R0 R1 K2     ; R0 := R1 * 50
  6 [-]: GETGLOBAL R1 K3        ; R1 := mMovie
  7 [-]: SELF      R1 R1 K4     ; R2 := R1; R1 := R1["0x880196A7"]
  8 [-]: LOADK     R3 K5        ; R3 := "Message"
  9 [-]: LOADK     R4 K6        ; R4 := "Icon"
 10 [-]: LOADK     R5 K7        ; R5 := "_y"
 11 [-]: GETUPVAL  R6 U1        ; R6 := U1
 12 [-]: ADD       R6 R6 R0     ; R6 := R6 + R0
 13 [-]: CALL      R1 6 1       ; R1(R2,R3,R4,R5,R6)
 14 [-]: GETGLOBAL R1 K3        ; R1 := mMovie
 15 [-]: SELF      R1 R1 K4     ; R2 := R1; R1 := R1["0x880196A7"]
 16 [-]: LOADK     R3 K5        ; R3 := "Message"
 17 [-]: LOADK     R4 K8        ; R4 := "Decoration"
 18 [-]: LOADK     R5 K7        ; R5 := "_y"
 19 [-]: GETUPVAL  R6 U1        ; R6 := U1
 20 [-]: ADD       R6 R6 K9     ; R6 := R6 + 30
 21 [-]: ADD       R6 R6 R0     ; R6 := R6 + R0
 22 [-]: CALL      R1 6 1       ; R1(R2,R3,R4,R5,R6)
 23 [-]: RETURN    R0 1         ; return 


; Function #3.4:
;
; Name:            
; Defined at line: 212
; #Upvalues:       5
; #Parameters:     0
; Is_vararg:       0
; Max Stack Size:  12

  1 [-]: MOVE      R0 R0        ; R0 := R0
  2 [-]: TEST      R0 0         ; if not R0 then PC := 35
  3 [-]: JMP       35           ; PC := 35
  4 [-]: GETUPVAL  R0 U0        ; R0 := U0
  5 [-]: GETTABLE  R0 R0 K0     ; R0 := R0["0x69B983D"]
  6 [-]: GETGLOBAL R1 K1        ; R1 := mMovie
  7 [-]: LOADK     R2 K2        ; R2 := "Message.Icon"
  8 [-]: CALL      R0 3 3       ; R0,R1 := R0(R1,R2)
  9 [-]: GETUPVAL  R2 U0        ; R2 := U0
 10 [-]: GETTABLE  R2 R2 K3     ; R2 := R2["0xBB2F7661"]
 11 [-]: GETGLOBAL R3 K1        ; R3 := mMovie
 12 [-]: GETGLOBAL R4 K4        ; R4 := upgradeFx
 13 [-]: MOVE      R5 R0        ; R5 := R0
 14 [-]: ADD       R6 R1 K5     ; R6 := R1 + 68
 15 [-]: GETGLOBAL R7 K6        ; R7 := gBackgroundRegion
 16 [-]: CALL      R2 6 2       ; R2 := R2(R3,R4,R5,R6,R7)
 17 [-]: SELF      R3 R2 K7     ; R4 := R2; R3 := R2["0x8B598ED4"]
 18 [-]: GETGLOBAL R5 K8        ; R5 := gParticleSysType
 19 [-]: CALL      R3 3 2       ; R3 := R3(R4,R5)
 20 [-]: TEST      R3 0         ; if not R3 then PC := 27
 21 [-]: JMP       27           ; PC := 27
 22 [-]: SELF      R3 R2 K9     ; R4 := R2; R3 := R2["0x408A179A"]
 23 [-]: GETUPVAL  R5 U1        ; R5 := U1
 24 [-]: GETUPVAL  R6 U1        ; R6 := U1
 25 [-]: CALL      R3 4 1       ; R3(R4,R5,R6)
 26 [-]: JMP       35           ; PC := 35
 27 [-]: SELF      R3 R2 K7     ; R4 := R2; R3 := R2["0x8B598ED4"]
 28 [-]: GETGLOBAL R5 K10       ; R5 := gLensFlareType
 29 [-]: CALL      R3 3 2       ; R3 := R3(R4,R5)
 30 [-]: TEST      R3 0         ; if not R3 then PC := 35
 31 [-]: JMP       35           ; PC := 35
 32 [-]: SELF      R3 R2 K11    ; R4 := R2; R3 := R2["0xA20F64C0"]
 33 [-]: GETUPVAL  R5 U1        ; R5 := U1
 34 [-]: CALL      R3 3 1       ; R3(R4,R5)
 35 [-]: GETUPVAL  R3 U2        ; R3 := U2
 36 [-]: TEST      R3 1         ; if R3 then PC := 52
 37 [-]: JMP       52           ; PC := 52
 38 [-]: GETGLOBAL R3 K12       ; R3 := 0x52E17A90
 39 [-]: GETGLOBAL R4 K1        ; R4 := mMovie
 40 [-]: LOADK     R5 K2        ; R5 := "Message.Icon"
 41 [-]: GETGLOBAL R6 K13       ; R6 := UISys
 42 [-]: GETTABLE  R6 R6 K14    ; R6 := R6["FlashInstance_EASE_OUT"]
 43 [-]: NEWTABLE  R7 1 0       ; R7 := {}
 44 [-]: GETUPVAL  R8 U3        ; R8 := U3
 45 [-]: SETLIST   R7 1 1       ; R7[(1-1)*FPF+i] := R(7+i), 1 <= i <= 1
 46 [-]: NEWTABLE  R8 1 0       ; R8 := {}
 47 [-]: LOADK     R9 K15       ; R9 := 1
 48 [-]: SETLIST   R8 1 1       ; R8[(1-1)*FPF+i] := R(8+i), 1 <= i <= 1
 49 [-]: LOADK     R9 K16       ; R9 := 8
 50 [-]: LOADK     R10 K17      ; R10 := 0
 51 [-]: CALL      R3 8 1       ; R3(R4,R5,R6,R7,R8,R9,R10)
 52 [-]: GETGLOBAL R3 K12       ; R3 := 0x52E17A90
 53 [-]: GETGLOBAL R4 K1        ; R4 := mMovie
 54 [-]: LOADK     R5 K18       ; R5 := "Message.Decoration"
 55 [-]: GETGLOBAL R6 K13       ; R6 := UISys
 56 [-]: GETTABLE  R6 R6 K14    ; R6 := R6["FlashInstance_EASE_OUT"]
 57 [-]: NEWTABLE  R7 1 0       ; R7 := {}
 58 [-]: LOADK     R8 K19       ; R8 := "_alpha"
 59 [-]: SETLIST   R7 1 1       ; R7[(1-1)*FPF+i] := R(7+i), 1 <= i <= 1
 60 [-]: NEWTABLE  R8 1 0       ; R8 := {}
 61 [-]: LOADK     R9 K20       ; R9 := 100
 62 [-]: SETLIST   R8 1 1       ; R8[(1-1)*FPF+i] := R(8+i), 1 <= i <= 1
 63 [-]: LOADK     R9 K16       ; R9 := 8
 64 [-]: LOADK     R10 K17      ; R10 := 0
 65 [-]: CALL      R3 8 1       ; R3(R4,R5,R6,R7,R8,R9,R10)
 66 [-]: GETGLOBAL R3 K12       ; R3 := 0x52E17A90
 67 [-]: GETGLOBAL R4 K1        ; R4 := mMovie
 68 [-]: LOADK     R5 K21       ; R5 := "Message"
 69 [-]: GETGLOBAL R6 K13       ; R6 := UISys
 70 [-]: GETTABLE  R6 R6 K22    ; R6 := R6["FlashInstance_LINEAR"]
 71 [-]: NEWTABLE  R7 1 0       ; R7 := {}
 72 [-]: LOADK     R8 K19       ; R8 := "_alpha"
 73 [-]: SETLIST   R7 1 1       ; R7[(1-1)*FPF+i] := R(7+i), 1 <= i <= 1
 74 [-]: NEWTABLE  R8 1 0       ; R8 := {}
 75 [-]: LOADK     R9 K20       ; R9 := 100
 76 [-]: SETLIST   R8 1 1       ; R8[(1-1)*FPF+i] := R(8+i), 1 <= i <= 1
 77 [-]: LOADK     R9 K23       ; R9 := 1.5
 78 [-]: LOADK     R10 K17      ; R10 := 0
 79 [-]: CLOSURE   R11 0        ; R11 := closure(Function #3.4.1)
 80 [-]: GETUPVAL  R0 U4        ; R0 := U4
 81 [-]: CALL      R3 9 1       ; R3(R4,R5,R6,R7,R8,R9,R10,R11)
 82 [-]: RETURN    R0 1         ; return 


; Function #3.4.1:
;
; Name:            
; Defined at line: 231
; #Upvalues:       1
; #Parameters:     0
; Is_vararg:       0
; Max Stack Size:  9

  1 [-]: GETGLOBAL R0 K0        ; R0 := 0x52E17A90
  2 [-]: GETGLOBAL R1 K1        ; R1 := mMovie
  3 [-]: LOADK     R2 K2        ; R2 := "Message"
  4 [-]: GETGLOBAL R3 K3        ; R3 := UISys
  5 [-]: GETTABLE  R3 R3 K4     ; R3 := R3["FlashInstance_LINEAR"]
  6 [-]: NEWTABLE  R4 1 0       ; R4 := {}
  7 [-]: LOADK     R5 K5        ; R5 := "_alpha"
  8 [-]: SETLIST   R4 1 1       ; R4[(1-1)*FPF+i] := R(4+i), 1 <= i <= 1
  9 [-]: NEWTABLE  R5 1 0       ; R5 := {}
 10 [-]: LOADK     R6 K6        ; R6 := 0
 11 [-]: SETLIST   R5 1 1       ; R5[(1-1)*FPF+i] := R(5+i), 1 <= i <= 1
 12 [-]: LOADK     R6 K7        ; R6 := 1
 13 [-]: LOADK     R7 K8        ; R7 := 5
 14 [-]: CLOSURE   R8 0         ; R8 := closure(Function #3.4.1.1)
 15 [-]: GETUPVAL  R0 U0        ; R0 := U0
 16 [-]: CALL      R0 9 1       ; R0(R1,R2,R3,R4,R5,R6,R7,R8)
 17 [-]: RETURN    R0 1         ; return 


; Function #3.4.1.1:
;
; Name:            
; Defined at line: 233
; #Upvalues:       1
; #Parameters:     0
; Is_vararg:       0
; Max Stack Size:  2

  1 [-]: GETUPVAL  R0 U0        ; R0 := U0
  2 [-]: CALL      R0 1 1       ; R0()
  3 [-]: RETURN    R0 1         ; return 


; Function #4:
;
; Name:            
; Defined at line: 241
; #Upvalues:       2
; #Parameters:     0
; Is_vararg:       0
; Max Stack Size:  6

  1 [-]: GETUPVAL  R0 U0        ; R0 := U0
  2 [-]: EQ        0 R0 K0      ; if R0 ~= nil then PC := 12
  3 [-]: JMP       12           ; PC := 12
  4 [-]: GETGLOBAL R0 K1        ; R0 := 0xF595ADDE
  5 [-]: GETGLOBAL R1 K2        ; R1 := mMovie
  6 [-]: SELF      R1 R1 K3     ; R2 := R1; R1 := R1["0x6B7B470B"]
  7 [-]: LOADK     R3 K4        ; R3 := "Message.Icon"
  8 [-]: LOADK     R4 K5        ; R4 := "_y"
  9 [-]: CALL      R1 4 0       ; R1,... := R1(R2,R3,R4)
 10 [-]: CALL      R0 0 2       ; R0 := R0(R1,...)
 11 [-]: MOVE      R0 R0        ; R0 := R0
 12 [-]: GETGLOBAL R0 K2        ; R0 := mMovie
 13 [-]: SELF      R0 R0 K6     ; R1 := R0; R0 := R0["0x1C19D966"]
 14 [-]: LOADK     R2 K7        ; R2 := "Message"
 15 [-]: LOADK     R3 K8        ; R3 := "_alpha"
 16 [-]: LOADK     R4 K9        ; R4 := 0
 17 [-]: CALL      R0 5 1       ; R0(R1,R2,R3,R4)
 18 [-]: GETGLOBAL R0 K2        ; R0 := mMovie
 19 [-]: SELF      R0 R0 K10    ; R1 := R0; R0 := R0["0x880196A7"]
 20 [-]: LOADK     R2 K7        ; R2 := "Message"
 21 [-]: LOADK     R3 K11       ; R3 := "Icon"
 22 [-]: LOADK     R4 K5        ; R4 := "_y"
 23 [-]: GETUPVAL  R5 U0        ; R5 := U0
 24 [-]: ADD       R5 R5 K12    ; R5 := R5 + 50
 25 [-]: CALL      R0 6 1       ; R0(R1,R2,R3,R4,R5)
 26 [-]: GETGLOBAL R0 K2        ; R0 := mMovie
 27 [-]: SELF      R0 R0 K10    ; R1 := R0; R0 := R0["0x880196A7"]
 28 [-]: LOADK     R2 K7        ; R2 := "Message"
 29 [-]: LOADK     R3 K11       ; R3 := "Icon"
 30 [-]: LOADK     R4 K8        ; R4 := "_alpha"
 31 [-]: LOADK     R5 K13       ; R5 := 100
 32 [-]: CALL      R0 6 1       ; R0(R1,R2,R3,R4,R5)
 33 [-]: GETGLOBAL R0 K2        ; R0 := mMovie
 34 [-]: SELF      R0 R0 K10    ; R1 := R0; R0 := R0["0x880196A7"]
 35 [-]: LOADK     R2 K7        ; R2 := "Message"
 36 [-]: LOADK     R3 K14       ; R3 := "Decoration"
 37 [-]: LOADK     R4 K8        ; R4 := "_alpha"
 38 [-]: LOADK     R5 K15       ; R5 := 30
 39 [-]: CALL      R0 6 1       ; R0(R1,R2,R3,R4,R5)
 40 [-]: GETGLOBAL R0 K2        ; R0 := mMovie
 41 [-]: SELF      R0 R0 K16    ; R1 := R0; R0 := R0["0x7E1F26D7"]
 42 [-]: LOADK     R2 K17       ; R2 := "Message.Icon.Chroma"
 43 [-]: GETGLOBAL R3 K18       ; R3 := flareMaterial
 44 [-]: CALL      R0 4 1       ; R0(R1,R2,R3)
 45 [-]: GETGLOBAL R0 K19       ; R0 := 0x329BDC44
 46 [-]: LOADK     R1 K20       ; R1 := "Lotus.Interface.Libs.TimerMgr"
 47 [-]: CALL      R0 2 2       ; R0 := R0(R1)
 48 [-]: GETTABLE  R1 R0 K21    ; R1 := R0["0xC2A7FAC0"]
 49 [-]: CALL      R1 1 2       ; R1 := R1()
 50 [-]: MOVE      R1 R1        ; R1 := R1
 51 [-]: RETURN    R0 1         ; return 


; Function #5:
;
; Name:            
; Defined at line: 260
; #Upvalues:       7
; #Parameters:     0
; Is_vararg:       0
; Max Stack Size:  11

  1 [-]: GETUPVAL  R0 U0        ; R0 := U0
  2 [-]: TEST      R0 1         ; if R0 then PC := 38
  3 [-]: JMP       38           ; PC := 38
  4 [-]: GETUPVAL  R0 U1        ; R0 := U1
  5 [-]: EQ        1 R0 K0      ; if R0 == nil then PC := 38
  6 [-]: JMP       38           ; PC := 38
  7 [-]: GETUPVAL  R0 U2        ; R0 := U2
  8 [-]: GETUPVAL  R1 U1        ; R1 := U1
  9 [-]: GETTABLE  R1 R1 K1     ; R1 := R1[1]
 10 [-]: GETTABLE  R1 R1 K2     ; R1 := R1["TargetName"]
 11 [-]: GETGLOBAL R2 K3        ; R2 := 0xF595ADDE
 12 [-]: GETUPVAL  R3 U1        ; R3 := U1
 13 [-]: GETTABLE  R3 R3 K1     ; R3 := R3[1]
 14 [-]: GETTABLE  R3 R3 K4     ; R3 := R3["ScanCount"]
 15 [-]: CALL      R2 2 2       ; R2 := R2(R3)
 16 [-]: GETGLOBAL R3 K3        ; R3 := 0xF595ADDE
 17 [-]: GETUPVAL  R4 U1        ; R4 := U1
 18 [-]: GETTABLE  R4 R4 K1     ; R4 := R4[1]
 19 [-]: GETTABLE  R4 R4 K5     ; R4 := R4["ScansRequired"]
 20 [-]: CALL      R3 2 2       ; R3 := R3(R4)
 21 [-]: GETUPVAL  R4 U1        ; R4 := U1
 22 [-]: GETTABLE  R4 R4 K1     ; R4 := R4[1]
 23 [-]: GETTABLE  R4 R4 K6     ; R4 := R4["MsgType"]
 24 [-]: CALL      R0 5 1       ; R0(R1,R2,R3,R4)
 25 [-]: GETGLOBAL R0 K7        ; R0 := table
 26 [-]: GETTABLE  R0 R0 K8     ; R0 := R0["0xCDB1FD5E"]
 27 [-]: GETUPVAL  R1 U1        ; R1 := U1
 28 [-]: LOADK     R2 K1        ; R2 := 1
 29 [-]: CALL      R0 3 1       ; R0(R1,R2)
 30 [-]: GETUPVAL  R0 U1        ; R0 := U1
 31 [-]: LEN       R0 R0        ; R0 := # R0
 32 [-]: EQ        0 R0 K9      ; if R0 ~= 0 then PC := 36
 33 [-]: JMP       36           ; PC := 36
 34 [-]: LOADNIL   R0 R0        ; R0 := nil
 35 [-]: MOVE      R0 R1        ; R0 := R1
 36 [-]: MOVE      R0 R1        ; R0 := R1
 37 [-]: MOVE      R0 R0        ; R0 := R0
 38 [-]: GETGLOBAL R0 K10       ; R0 := 0x6306558E
 39 [-]: CALL      R0 1 2       ; R0 := R0()
 40 [-]: GETGLOBAL R1 K11       ; R1 := mMovie
 41 [-]: SELF      R1 R1 K12    ; R2 := R1; R1 := R1["0x80D6B1A"]
 42 [-]: MOVE      R3 R0        ; R3 := R0
 43 [-]: CALL      R1 3 1       ; R1(R2,R3)
 44 [-]: GETGLOBAL R1 K13       ; R1 := 0x400E7765
 45 [-]: GETUPVAL  R2 U3        ; R2 := U3
 46 [-]: CALL      R1 2 2       ; R1 := R1(R2)
 47 [-]: TEST      R1 1         ; if R1 then PC := 53
 48 [-]: JMP       53           ; PC := 53
 49 [-]: GETUPVAL  R1 U3        ; R1 := U3
 50 [-]: SELF      R1 R1 K14    ; R2 := R1; R1 := R1["0x8C7099E9"]
 51 [-]: MOVE      R3 R0        ; R3 := R0
 52 [-]: CALL      R1 3 1       ; R1(R2,R3)
 53 [-]: GETUPVAL  R1 U4        ; R1 := U4
 54 [-]: LE        0 K15 R1     ; if 100 > R1 then PC := 89
 55 [-]: JMP       89           ; PC := 89
 56 [-]: GETUPVAL  R1 U5        ; R1 := U5
 57 [-]: TEST      R1 0         ; if not R1 then PC := 89
 58 [-]: JMP       89           ; PC := 89
 59 [-]: GETGLOBAL R1 K16       ; R1 := math
 60 [-]: GETTABLE  R1 R1 K17    ; R1 := R1["0xF93F7CC8"]
 61 [-]: GETGLOBAL R2 K16       ; R2 := math
 62 [-]: GETTABLE  R2 R2 K18    ; R2 := R2["0xBB3F1476"]
 63 [-]: GETGLOBAL R3 K19       ; R3 := 0xA1FD035F
 64 [-]: GETUPVAL  R4 U6        ; R4 := U6
 65 [-]: CALL      R3 2 2       ; R3 := R3(R4)
 66 [-]: MUL       R3 R3 K1     ; R3 := R3 * 1
 67 [-]: GETGLOBAL R4 K16       ; R4 := math
 68 [-]: GETTABLE  R4 R4 K20    ; R4 := R4["pi"]
 69 [-]: MUL       R3 R3 R4     ; R3 := R3 * R4
 70 [-]: CALL      R2 2 0       ; R2,... := R2(R3)
 71 [-]: CALL      R1 0 2       ; R1 := R1(R2,...)
 72 [-]: SUB       R1 K1 R1     ; R1 := 1 - R1
 73 [-]: GETGLOBAL R2 K11       ; R2 := mMovie
 74 [-]: SELF      R2 R2 K21    ; R3 := R2; R2 := R2["0x880196A7"]
 75 [-]: LOADK     R4 K22       ; R4 := "Message"
 76 [-]: LOADK     R5 K23       ; R5 := "Icon"
 77 [-]: LOADK     R6 K24       ; R6 := "_alpha"
 78 [-]: GETGLOBAL R7 K25       ; R7 := 0x93034B55
 79 [-]: LOADK     R8 K26       ; R8 := 30
 80 [-]: LOADK     R9 K15       ; R9 := 100
 81 [-]: MOVE      R10 R1       ; R10 := R1
 82 [-]: CALL      R7 4 0       ; R7,... := R7(R8,R9,R10)
 83 [-]: CALL      R2 0 1       ; R2(R3,...)
 84 [-]: GETUPVAL  R2 U6        ; R2 := U6
 85 [-]: GETGLOBAL R3 K27       ; R3 := 0x4CDEF9FF
 86 [-]: CALL      R3 1 2       ; R3 := R3()
 87 [-]: ADD       R2 R2 R3     ; R2 := R2 + R3
 88 [-]: MOVE      R2 R6        ; R2 := R6
 89 [-]: RETURN    R0 1         ; return 


; Function #6:
;
; Name:            
; Defined at line: 284
; #Upvalues:       1
; #Parameters:     5
; Is_vararg:       0
; Max Stack Size:  8

  1 [-]: GETUPVAL  R5 U0        ; R5 := U0
  2 [-]: EQ        0 R5 K0      ; if R5 ~= nil then PC := 6
  3 [-]: JMP       6            ; PC := 6
  4 [-]: NEWTABLE  R5 0 0       ; R5 := {}
  5 [-]: MOVE      R5 R0        ; R5 := R0
  6 [-]: GETGLOBAL R5 K1        ; R5 := table
  7 [-]: GETTABLE  R5 R5 K2     ; R5 := R5["0xE6450C9D"]
  8 [-]: GETUPVAL  R6 U0        ; R6 := U0
  9 [-]: NEWTABLE  R7 0 5       ; R7 := {}
 10 [-]: SETTABLE  R7 K3 R0     ; R7["TargetName"] := R0
 11 [-]: SETTABLE  R7 K4 R1     ; R7["ScanCount"] := R1
 12 [-]: SETTABLE  R7 K5 R2     ; R7["ScansRequired"] := R2
 13 [-]: SETTABLE  R7 K6 R3     ; R7["IsDaily"] := R3
 14 [-]: SETTABLE  R7 K7 R4     ; R7["MsgType"] := R4
 15 [-]: CALL      R5 3 1       ; R5(R6,R7)
 16 [-]: MOVE      R5 R1        ; R5 := R1
 17 [-]: RETURN    R5 2         ; return R5
 18 [-]: RETURN    R0 1         ; return 


