code size: 127
code size: 11
code size: 3
code size: 219
code size: 338
code size: 20
code size: 20
code size: 246
code size: 440
code size: 26
code size: 72
code size: 22
code size: 33
code size: 5
code size: 8
code size: 1
code size: 9
code size: 9
code size: 7
code size: 4
code size: 4
code size: 7
code size: 4
code size: 4
code size: 8
code size: 28
code size: 8
code size: 3
code size: 8
; This file has been disassembled using luadec 2.0.2 by sztupy (http://winmo.sztupy.hu)
; Command line was: -dis M:\git repos\warframe-lua-disassembled\B.Font.cache_extracted\Lotus\Interface\JunctionTasks.luac 

; Name:            
; Defined at line: 0
; #Upvalues:       0
; #Parameters:     0
; Is_vararg:       2
; Max Stack Size:  24

  1 [-]: GETGLOBAL R0 K0        ; R0 := 0x329BDC44
  2 [-]: LOADK     R1 K1        ; R1 := "Lotus.Interface.CardUtilitiesRedux"
  3 [-]: CALL      R0 2 2       ; R0 := R0(R1)
  4 [-]: GETGLOBAL R1 K0        ; R1 := 0x329BDC44
  5 [-]: LOADK     R2 K2        ; R2 := "Lotus.Interface.LotusUtilities"
  6 [-]: CALL      R1 2 2       ; R1 := R1(R2)
  7 [-]: GETGLOBAL R2 K0        ; R2 := 0x329BDC44
  8 [-]: LOADK     R3 K3        ; R3 := "EE.Interface.Utilities"
  9 [-]: CALL      R2 2 2       ; R2 := R2(R3)
 10 [-]: LOADK     R3 K4        ; R3 := 3
 11 [-]: MOVE      R4 R0        ; R4 := R0
 12 [-]: LOADNIL   R5 R6        ; R5 := R6 := nil
 13 [-]: MOVE      R7 R0        ; R7 := R0
 14 [-]: LOADK     R8 K5        ; R8 := 0
 15 [-]: LOADK     R9 K6        ; R9 := -1
 16 [-]: NEWTABLE  R10 0 0      ; R10 := {}
 17 [-]: LOADK     R11 K5       ; R11 := 0
 18 [-]: LOADNIL   R12 R12      ; R12 := nil
 19 [-]: MOVE      R13 R0       ; R13 := R0
 20 [-]: CLOSURE   R14 0        ; R14 := closure(Function #1)
 21 [-]: CLOSURE   R15 1        ; R15 := closure(Function #2)
 22 [-]: MOVE      R0 R14       ; R0 := R14
 23 [-]: SETGLOBAL R15 K7       ; Close := R15
 24 [-]: SETGLOBAL R15 K8       ; 0xA58BB96C := R15
 25 [-]: CLOSURE   R15 2        ; R15 := closure(Function #3)
 26 [-]: MOVE      R0 R2        ; R0 := R2
 27 [-]: MOVE      R0 R12       ; R0 := R12
 28 [-]: MOVE      R0 R6        ; R0 := R6
 29 [-]: MOVE      R0 R11       ; R0 := R11
 30 [-]: CLOSURE   R16 3        ; R16 := closure(Function #4)
 31 [-]: MOVE      R0 R9        ; R0 := R9
 32 [-]: MOVE      R0 R10       ; R0 := R10
 33 [-]: MOVE      R0 R0        ; R0 := R0
 34 [-]: MOVE      R0 R2        ; R0 := R2
 35 [-]: MOVE      R0 R12       ; R0 := R12
 36 [-]: MOVE      R0 R11       ; R0 := R11
 37 [-]: MOVE      R0 R8        ; R0 := R8
 38 [-]: MOVE      R0 R3        ; R0 := R3
 39 [-]: CLOSURE   R17 4        ; R17 := closure(Function #5)
 40 [-]: MOVE      R0 R5        ; R0 := R5
 41 [-]: MOVE      R0 R1        ; R0 := R1
 42 [-]: MOVE      R0 R10       ; R0 := R10
 43 [-]: MOVE      R0 R2        ; R0 := R2
 44 [-]: MOVE      R0 R12       ; R0 := R12
 45 [-]: MOVE      R0 R16       ; R0 := R16
 46 [-]: MOVE      R0 R6        ; R0 := R6
 47 [-]: MOVE      R0 R7        ; R0 := R7
 48 [-]: MOVE      R0 R11       ; R0 := R11
 49 [-]: CLOSURE   R18 5        ; R18 := closure(Function #6)
 50 [-]: MOVE      R0 R2        ; R0 := R2
 51 [-]: MOVE      R0 R13       ; R0 := R13
 52 [-]: CLOSURE   R19 6        ; R19 := closure(Function #7)
 53 [-]: MOVE      R0 R5        ; R0 := R5
 54 [-]: MOVE      R0 R1        ; R0 := R1
 55 [-]: MOVE      R0 R2        ; R0 := R2
 56 [-]: MOVE      R0 R15       ; R0 := R15
 57 [-]: MOVE      R0 R17       ; R0 := R17
 58 [-]: MOVE      R0 R18       ; R0 := R18
 59 [-]: SETGLOBAL R19 K9       ; Initialize := R19
 60 [-]: SETGLOBAL R19 K10      ; 0x62648036 := R19
 61 [-]: CLOSURE   R19 7        ; R19 := closure(Function #8)
 62 [-]: MOVE      R0 R8        ; R0 := R8
 63 [-]: MOVE      R0 R3        ; R0 := R3
 64 [-]: MOVE      R0 R16       ; R0 := R16
 65 [-]: SETGLOBAL R19 K11      ; Update := R19
 66 [-]: SETGLOBAL R19 K12      ; 0x8C7099E9 := R19
 67 [-]: CLOSURE   R19 8        ; R19 := closure(Function #9)
 68 [-]: MOVE      R0 R4        ; R0 := R4
 69 [-]: MOVE      R0 R14       ; R0 := R14
 70 [-]: CLOSURE   R20 9        ; R20 := closure(Function #10)
 71 [-]: MOVE      R0 R2        ; R0 := R2
 72 [-]: MOVE      R0 R19       ; R0 := R19
 73 [-]: CLOSURE   R21 10       ; R21 := closure(Function #11)
 74 [-]: SETGLOBAL R21 K13      ; OpenJunctionTasksList := R21
 75 [-]: SETGLOBAL R21 K14      ; 0x76149B30 := R21
 76 [-]: CLOSURE   R21 11       ; R21 := closure(Function #12)
 77 [-]: CLOSURE   R22 12       ; R22 := closure(Function #13)
 78 [-]: CLOSURE   R23 13       ; R23 := closure(Function #14)
 79 [-]: MOVE      R0 R4        ; R0 := R4
 80 [-]: MOVE      R0 R16       ; R0 := R16
 81 [-]: SETGLOBAL R23 K15      ; RightCyclerPressed := R23
 82 [-]: SETGLOBAL R23 K16      ; 0xD241D52C := R23
 83 [-]: CLOSURE   R23 14       ; R23 := closure(Function #15)
 84 [-]: MOVE      R0 R21       ; R0 := R21
 85 [-]: SETGLOBAL R23 K17      ; RightCyclerFocused := R23
 86 [-]: SETGLOBAL R23 K18      ; 0x499F2353 := R23
 87 [-]: CLOSURE   R23 15       ; R23 := closure(Function #16)
 88 [-]: MOVE      R0 R22       ; R0 := R22
 89 [-]: SETGLOBAL R23 K19      ; RightCyclerUnfocused := R23
 90 [-]: SETGLOBAL R23 K20      ; 0x20E26483 := R23
 91 [-]: CLOSURE   R23 16       ; R23 := closure(Function #17)
 92 [-]: MOVE      R0 R4        ; R0 := R4
 93 [-]: MOVE      R0 R16       ; R0 := R16
 94 [-]: SETGLOBAL R23 K21      ; LeftCyclerPressed := R23
 95 [-]: SETGLOBAL R23 K22      ; 0x8358CBE0 := R23
 96 [-]: CLOSURE   R23 17       ; R23 := closure(Function #18)
 97 [-]: MOVE      R0 R21       ; R0 := R21
 98 [-]: SETGLOBAL R23 K23      ; LeftCyclerFocused := R23
 99 [-]: SETGLOBAL R23 K24      ; 0xEA17E29C := R23
100 [-]: CLOSURE   R23 18       ; R23 := closure(Function #19)
101 [-]: MOVE      R0 R22       ; R0 := R22
102 [-]: SETGLOBAL R23 K25      ; LeftCyclerUnfocused := R23
103 [-]: SETGLOBAL R23 K26      ; 0xEC471675 := R23
104 [-]: CLOSURE   R23 19       ; R23 := closure(Function #20)
105 [-]: MOVE      R0 R4        ; R0 := R4
106 [-]: MOVE      R0 R20       ; R0 := R20
107 [-]: SETGLOBAL R23 K27      ; onKeyUp_MENU_CANCEL := R23
108 [-]: SETGLOBAL R23 K28      ; 0xD853E536 := R23
109 [-]: CLOSURE   R23 20       ; R23 := closure(Function #21)
110 [-]: MOVE      R0 R12       ; R0 := R12
111 [-]: SETGLOBAL R23 K29      ; SetTrigger := R23
112 [-]: SETGLOBAL R23 K30      ; 0x3F956A34 := R23
113 [-]: CLOSURE   R23 21       ; R23 := closure(Function #22)
114 [-]: MOVE      R0 R13       ; R0 := R13
115 [-]: MOVE      R0 R18       ; R0 := R18
116 [-]: SETGLOBAL R23 K31      ; SetRightAligned := R23
117 [-]: SETGLOBAL R23 K32      ; 0xCB617B74 := R23
118 [-]: CLOSURE   R23 22       ; R23 := closure(Function #23)
119 [-]: MOVE      R0 R18       ; R0 := R18
120 [-]: SETGLOBAL R23 K33      ; onViewportSizeChanged := R23
121 [-]: SETGLOBAL R23 K34      ; 0x3A900427 := R23
122 [-]: CLOSURE   R23 23       ; R23 := closure(Function #24)
123 [-]: MOVE      R0 R6        ; R0 := R6
124 [-]: MOVE      R0 R17       ; R0 := R17
125 [-]: SETGLOBAL R23 K35      ; OnWorldStateChanged := R23
126 [-]: SETGLOBAL R23 K36      ; 0xECDF5016 := R23
127 [-]: RETURN    R0 1         ; return 


; Function #1:
;
; Name:            
; Defined at line: 28
; #Upvalues:       0
; #Parameters:     0
; Is_vararg:       0
; Max Stack Size:  2

  1 [-]: GETGLOBAL R0 K0        ; R0 := _T
  2 [-]: SETTABLE  R0 K1 K2     ; R0["JunctionTasksRelayReconstruction"] := nil
  3 [-]: GETGLOBAL R0 K3        ; R0 := 0x400E7765
  4 [-]: GETGLOBAL R1 K4        ; R1 := mMovie
  5 [-]: CALL      R0 2 2       ; R0 := R0(R1)
  6 [-]: TEST      R0 1         ; if R0 then PC := 11
  7 [-]: JMP       11           ; PC := 11
  8 [-]: GETGLOBAL R0 K4        ; R0 := mMovie
  9 [-]: SELF      R0 R0 K5     ; R1 := R0; R0 := R0["0xA58BB96C"]
 10 [-]: CALL      R0 2 1       ; R0(R1)
 11 [-]: RETURN    R0 1         ; return 


; Function #2:
;
; Name:            
; Defined at line: 36
; #Upvalues:       1
; #Parameters:     0
; Is_vararg:       0
; Max Stack Size:  2

  1 [-]: GETUPVAL  R0 U0        ; R0 := U0
  2 [-]: CALL      R0 1 1       ; R0()
  3 [-]: RETURN    R0 1         ; return 


; Function #3:
;
; Name:            
; Defined at line: 40
; #Upvalues:       4
; #Parameters:     0
; Is_vararg:       0
; Max Stack Size:  12

  1 [-]: GETGLOBAL R0 K0        ; R0 := _G
  2 [-]: GETTABLE  R0 R0 K1     ; R0 := R0["UIMaterial_RectangleNoDepth"]
  3 [-]: LOADK     R1 K2        ; R1 := 0.5
  4 [-]: GETUPVAL  R2 U0        ; R2 := U0
  5 [-]: GETTABLE  R2 R2 K3     ; R2 := R2["0x97B78441"]
  6 [-]: LOADK     R3 K4        ; R3 := 2832446
  7 [-]: CALL      R2 2 2       ; R2 := R2(R3)
  8 [-]: GETGLOBAL R3 K5        ; R3 := 0x400E7765
  9 [-]: GETUPVAL  R4 U1        ; R4 := U1
 10 [-]: CALL      R3 2 2       ; R3 := R3(R4)
 11 [-]: TEST      R3 1         ; if R3 then PC := 15
 12 [-]: JMP       15           ; PC := 15
 13 [-]: GETGLOBAL R3 K0        ; R3 := _G
 14 [-]: GETTABLE  R0 R3 K6     ; R0 := R3["UIMaterial_Rectangle"]
 15 [-]: GETGLOBAL R3 K7        ; R3 := mMovie
 16 [-]: SELF      R3 R3 K8     ; R4 := R3; R3 := R3["0x7E1F26D7"]
 17 [-]: LOADK     R5 K9        ; R5 := "Junction.TitleBg"
 18 [-]: MOVE      R6 R0        ; R6 := R0
 19 [-]: CALL      R3 4 1       ; R3(R4,R5,R6)
 20 [-]: GETGLOBAL R3 K7        ; R3 := mMovie
 21 [-]: SELF      R3 R3 K10    ; R4 := R3; R3 := R3["0x302AAB2F"]
 22 [-]: LOADK     R5 K9        ; R5 := "Junction.TitleBg"
 23 [-]: LOADK     R6 K11       ; R6 := "RectInnerColor"
 24 [-]: GETTABLE  R7 R2 K12    ; R7 := R2["r"]
 25 [-]: GETTABLE  R8 R2 K13    ; R8 := R2["g"]
 26 [-]: GETTABLE  R9 R2 K14    ; R9 := R2["b"]
 27 [-]: MOVE      R10 R1       ; R10 := R1
 28 [-]: CALL      R3 8 1       ; R3(R4,R5,R6,R7,R8,R9,R10)
 29 [-]: GETGLOBAL R3 K7        ; R3 := mMovie
 30 [-]: SELF      R3 R3 K10    ; R4 := R3; R3 := R3["0x302AAB2F"]
 31 [-]: LOADK     R5 K9        ; R5 := "Junction.TitleBg"
 32 [-]: LOADK     R6 K15       ; R6 := "RectEdgeColor"
 33 [-]: GETGLOBAL R7 K0        ; R7 := _G
 34 [-]: GETTABLE  R7 R7 K16    ; R7 := R7["UIColorObject_White"]
 35 [-]: GETTABLE  R7 R7 K12    ; R7 := R7["r"]
 36 [-]: GETGLOBAL R8 K0        ; R8 := _G
 37 [-]: GETTABLE  R8 R8 K16    ; R8 := R8["UIColorObject_White"]
 38 [-]: GETTABLE  R8 R8 K13    ; R8 := R8["g"]
 39 [-]: GETGLOBAL R9 K0        ; R9 := _G
 40 [-]: GETTABLE  R9 R9 K16    ; R9 := R9["UIColorObject_White"]
 41 [-]: GETTABLE  R9 R9 K14    ; R9 := R9["b"]
 42 [-]: LOADK     R10 K17      ; R10 := 0.20000000298023
 43 [-]: CALL      R3 8 1       ; R3(R4,R5,R6,R7,R8,R9,R10)
 44 [-]: GETGLOBAL R3 K18       ; R3 := 0x329BDC44
 45 [-]: LOADK     R4 K19       ; R4 := "EE.Interface.Components.List"
 46 [-]: CALL      R3 2 2       ; R3 := R3(R4)
 47 [-]: GETTABLE  R4 R3 K20    ; R4 := R3["0xB40DEC3F"]
 48 [-]: GETGLOBAL R5 K7        ; R5 := mMovie
 49 [-]: LOADK     R6 K21       ; R6 := "Junction.MissionTasks.MissionTaskList.MissionTask"
 50 [-]: CALL      R4 3 2       ; R4 := R4(R5,R6)
 51 [-]: MOVE      R4 R2        ; R4 := R2
 52 [-]: GETUPVAL  R4 U2        ; R4 := U2
 53 [-]: SETTABLE  R4 K22 K23   ; R4["mVisibleElements"] := 6
 54 [-]: GETUPVAL  R4 U2        ; R4 := U2
 55 [-]: GETGLOBAL R5 K25       ; R5 := 0xF595ADDE
 56 [-]: GETGLOBAL R6 K7        ; R6 := mMovie
 57 [-]: SELF      R6 R6 K26    ; R7 := R6; R6 := R6["0x6B7B470B"]
 58 [-]: LOADK     R8 K27       ; R8 := "Junction.MissionTasks.MissionTaskList.MissionTask.DescBg"
 59 [-]: LOADK     R9 K28       ; R9 := "_height"
 60 [-]: CALL      R6 4 0       ; R6,... := R6(R7,R8,R9)
 61 [-]: CALL      R5 0 2       ; R5 := R5(R6,...)
 62 [-]: SETTABLE  R4 K24 R5    ; R4["mOriginalBgHeight"] := R5
 63 [-]: GETUPVAL  R4 U2        ; R4 := U2
 64 [-]: GETGLOBAL R5 K25       ; R5 := 0xF595ADDE
 65 [-]: GETGLOBAL R6 K7        ; R6 := mMovie
 66 [-]: SELF      R6 R6 K26    ; R7 := R6; R6 := R6["0x6B7B470B"]
 67 [-]: LOADK     R8 K27       ; R8 := "Junction.MissionTasks.MissionTaskList.MissionTask.DescBg"
 68 [-]: LOADK     R9 K30       ; R9 := "_width"
 69 [-]: CALL      R6 4 0       ; R6,... := R6(R7,R8,R9)
 70 [-]: CALL      R5 0 2       ; R5 := R5(R6,...)
 71 [-]: SETTABLE  R4 K29 R5    ; R4["mOriginalBgWidth"] := R5
 72 [-]: GETUPVAL  R4 U2        ; R4 := U2
 73 [-]: GETGLOBAL R5 K25       ; R5 := 0xF595ADDE
 74 [-]: GETGLOBAL R6 K7        ; R6 := mMovie
 75 [-]: SELF      R6 R6 K26    ; R7 := R6; R6 := R6["0x6B7B470B"]
 76 [-]: LOADK     R8 K32       ; R8 := "Junction.MissionTasks.MissionTaskList.MissionTask.Desc"
 77 [-]: LOADK     R9 K33       ; R9 := "_y"
 78 [-]: CALL      R6 4 0       ; R6,... := R6(R7,R8,R9)
 79 [-]: CALL      R5 0 2       ; R5 := R5(R6,...)
 80 [-]: SETTABLE  R4 K31 R5    ; R4["mOriginalDescYPos"] := R5
 81 [-]: GETUPVAL  R4 U2        ; R4 := U2
 82 [-]: GETGLOBAL R5 K25       ; R5 := 0xF595ADDE
 83 [-]: GETGLOBAL R6 K7        ; R6 := mMovie
 84 [-]: SELF      R6 R6 K26    ; R7 := R6; R6 := R6["0x6B7B470B"]
 85 [-]: LOADK     R8 K35       ; R8 := "Junction.MissionTasks.MissionTaskList.MissionTask.Status"
 86 [-]: LOADK     R9 K33       ; R9 := "_y"
 87 [-]: CALL      R6 4 0       ; R6,... := R6(R7,R8,R9)
 88 [-]: CALL      R5 0 2       ; R5 := R5(R6,...)
 89 [-]: SETTABLE  R4 K34 R5    ; R4["mOriginalStatusYPos"] := R5
 90 [-]: GETUPVAL  R4 U2        ; R4 := U2
 91 [-]: GETGLOBAL R5 K25       ; R5 := 0xF595ADDE
 92 [-]: GETGLOBAL R6 K7        ; R6 := mMovie
 93 [-]: SELF      R6 R6 K26    ; R7 := R6; R6 := R6["0x6B7B470B"]
 94 [-]: LOADK     R8 K37       ; R8 := "Junction.MissionTasks.MissionTaskList.MissionTask.Progress"
 95 [-]: LOADK     R9 K33       ; R9 := "_y"
 96 [-]: CALL      R6 4 0       ; R6,... := R6(R7,R8,R9)
 97 [-]: CALL      R5 0 2       ; R5 := R5(R6,...)
 98 [-]: SETTABLE  R4 K36 R5    ; R4["mOriginalProgressYPos"] := R5
 99 [-]: GETUPVAL  R4 U2        ; R4 := U2
100 [-]: GETGLOBAL R5 K25       ; R5 := 0xF595ADDE
101 [-]: GETGLOBAL R6 K7        ; R6 := mMovie
102 [-]: SELF      R6 R6 K26    ; R7 := R6; R6 := R6["0x6B7B470B"]
103 [-]: LOADK     R8 K39       ; R8 := "Junction.MissionTasks.MissionTaskList"
104 [-]: LOADK     R9 K33       ; R9 := "_y"
105 [-]: CALL      R6 4 0       ; R6,... := R6(R7,R8,R9)
106 [-]: CALL      R5 0 2       ; R5 := R5(R6,...)
107 [-]: SETTABLE  R4 K38 R5    ; R4["mOriginalListYPos"] := R5
108 [-]: GETUPVAL  R4 U2        ; R4 := U2
109 [-]: SETTABLE  R4 K40 K41   ; R4["mBgGrowthPerLine"] := 21
110 [-]: GETUPVAL  R4 U2        ; R4 := U2
111 [-]: SETTABLE  R4 K42 K43   ; R4["mLineThreshold"] := 3
112 [-]: GETUPVAL  R4 U2        ; R4 := U2
113 [-]: SETTABLE  R4 K44 K45   ; R4["mForcedVerticalSeparation"] := 80
114 [-]: GETUPVAL  R4 U2        ; R4 := U2
115 [-]: CLOSURE   R5 0         ; R5 := closure(Function #3.1)
116 [-]: MOVE      R0 R0        ; R0 := R0
117 [-]: MOVE      R0 R2        ; R0 := R2
118 [-]: MOVE      R0 R1        ; R0 := R1
119 [-]: GETUPVAL  R0 U0        ; R0 := U0
120 [-]: SETTABLE  R4 K46 R5    ; R4["mElementDrawCallback"] := R5
121 [-]: GETUPVAL  R4 U2        ; R4 := U2
122 [-]: CLOSURE   R5 1         ; R5 := closure(Function #3.2)
123 [-]: SETTABLE  R4 K47 R5    ; R4["GetHeight"] := R5
124 [-]: GETUPVAL  R4 U2        ; R4 := U2
125 [-]: CLOSURE   R5 2         ; R5 := closure(Function #3.3)
126 [-]: SETTABLE  R4 K48 R5    ; R4["CalculateY"] := R5
127 [-]: GETGLOBAL R4 K25       ; R4 := 0xF595ADDE
128 [-]: GETGLOBAL R5 K7        ; R5 := mMovie
129 [-]: SELF      R5 R5 K26    ; R6 := R5; R5 := R5["0x6B7B470B"]
130 [-]: LOADK     R7 K49       ; R7 := "Junction.MissionTasks.Rewards.Bg"
131 [-]: LOADK     R8 K28       ; R8 := "_height"
132 [-]: CALL      R5 4 0       ; R5,... := R5(R6,R7,R8)
133 [-]: CALL      R4 0 2       ; R4 := R4(R5,...)
134 [-]: MOVE      R4 R3        ; R4 := R3
135 [-]: GETGLOBAL R4 K7        ; R4 := mMovie
136 [-]: SELF      R4 R4 K8     ; R5 := R4; R4 := R4["0x7E1F26D7"]
137 [-]: LOADK     R6 K49       ; R6 := "Junction.MissionTasks.Rewards.Bg"
138 [-]: MOVE      R7 R0        ; R7 := R0
139 [-]: CALL      R4 4 1       ; R4(R5,R6,R7)
140 [-]: GETGLOBAL R4 K7        ; R4 := mMovie
141 [-]: SELF      R4 R4 K10    ; R5 := R4; R4 := R4["0x302AAB2F"]
142 [-]: LOADK     R6 K49       ; R6 := "Junction.MissionTasks.Rewards.Bg"
143 [-]: LOADK     R7 K11       ; R7 := "RectInnerColor"
144 [-]: GETTABLE  R8 R2 K12    ; R8 := R2["r"]
145 [-]: GETTABLE  R9 R2 K13    ; R9 := R2["g"]
146 [-]: GETTABLE  R10 R2 K14   ; R10 := R2["b"]
147 [-]: MOVE      R11 R1       ; R11 := R1
148 [-]: CALL      R4 8 1       ; R4(R5,R6,R7,R8,R9,R10,R11)
149 [-]: GETGLOBAL R4 K7        ; R4 := mMovie
150 [-]: SELF      R4 R4 K10    ; R5 := R4; R4 := R4["0x302AAB2F"]
151 [-]: LOADK     R6 K49       ; R6 := "Junction.MissionTasks.Rewards.Bg"
152 [-]: LOADK     R7 K15       ; R7 := "RectEdgeColor"
153 [-]: GETGLOBAL R8 K0        ; R8 := _G
154 [-]: GETTABLE  R8 R8 K16    ; R8 := R8["UIColorObject_White"]
155 [-]: GETTABLE  R8 R8 K12    ; R8 := R8["r"]
156 [-]: GETGLOBAL R9 K0        ; R9 := _G
157 [-]: GETTABLE  R9 R9 K16    ; R9 := R9["UIColorObject_White"]
158 [-]: GETTABLE  R9 R9 K13    ; R9 := R9["g"]
159 [-]: GETGLOBAL R10 K0       ; R10 := _G
160 [-]: GETTABLE  R10 R10 K16  ; R10 := R10["UIColorObject_White"]
161 [-]: GETTABLE  R10 R10 K14  ; R10 := R10["b"]
162 [-]: LOADK     R11 K17      ; R11 := 0.20000000298023
163 [-]: CALL      R4 8 1       ; R4(R5,R6,R7,R8,R9,R10,R11)
164 [-]: GETGLOBAL R4 K7        ; R4 := mMovie
165 [-]: SELF      R4 R4 K50    ; R5 := R4; R4 := R4["0x26581636"]
166 [-]: LOADK     R6 K51       ; R6 := "Junction.MissionTasks.Rewards.ImageBg"
167 [-]: GETGLOBAL R7 K52       ; R7 := 0x2C00D429
168 [-]: LOADK     R8 K53       ; R8 := "/Lotus/Interface/Icons/Store/BlueprintOverlay.png"
169 [-]: CALL      R7 2 0       ; R7,... := R7(R8)
170 [-]: CALL      R4 0 1       ; R4(R5,...)
171 [-]: GETGLOBAL R4 K7        ; R4 := mMovie
172 [-]: SELF      R4 R4 K54    ; R5 := R4; R4 := R4["0x1C19D966"]
173 [-]: LOADK     R6 K55       ; R6 := "Junction.MissionTasks.Rewards.Right.Label"
174 [-]: LOADK     R7 K56       ; R7 := "text"
175 [-]: LOADK     R8 K57       ; R8 := ">>"
176 [-]: CALL      R4 5 1       ; R4(R5,R6,R7,R8)
177 [-]: GETGLOBAL R4 K7        ; R4 := mMovie
178 [-]: SELF      R4 R4 K54    ; R5 := R4; R4 := R4["0x1C19D966"]
179 [-]: LOADK     R6 K58       ; R6 := "Junction.MissionTasks.Rewards.Left.Label"
180 [-]: LOADK     R7 K56       ; R7 := "text"
181 [-]: LOADK     R8 K57       ; R8 := ">>"
182 [-]: CALL      R4 5 1       ; R4(R5,R6,R7,R8)
183 [-]: GETGLOBAL R4 K7        ; R4 := mMovie
184 [-]: SELF      R4 R4 K54    ; R5 := R4; R4 := R4["0x1C19D966"]
185 [-]: LOADK     R6 K59       ; R6 := "Junction.MissionTasks.Rewards.Right"
186 [-]: LOADK     R7 K60       ; R7 := "SelectCallback"
187 [-]: LOADK     R8 K61       ; R8 := "RightCyclerPressed"
188 [-]: CALL      R4 5 1       ; R4(R5,R6,R7,R8)
189 [-]: GETGLOBAL R4 K7        ; R4 := mMovie
190 [-]: SELF      R4 R4 K54    ; R5 := R4; R4 := R4["0x1C19D966"]
191 [-]: LOADK     R6 K59       ; R6 := "Junction.MissionTasks.Rewards.Right"
192 [-]: LOADK     R7 K62       ; R7 := "RollOverCallback"
193 [-]: LOADK     R8 K63       ; R8 := "RightCyclerFocused"
194 [-]: CALL      R4 5 1       ; R4(R5,R6,R7,R8)
195 [-]: GETGLOBAL R4 K7        ; R4 := mMovie
196 [-]: SELF      R4 R4 K54    ; R5 := R4; R4 := R4["0x1C19D966"]
197 [-]: LOADK     R6 K59       ; R6 := "Junction.MissionTasks.Rewards.Right"
198 [-]: LOADK     R7 K64       ; R7 := "RollOutCallback"
199 [-]: LOADK     R8 K65       ; R8 := "RightCyclerUnfocused"
200 [-]: CALL      R4 5 1       ; R4(R5,R6,R7,R8)
201 [-]: GETGLOBAL R4 K7        ; R4 := mMovie
202 [-]: SELF      R4 R4 K54    ; R5 := R4; R4 := R4["0x1C19D966"]
203 [-]: LOADK     R6 K66       ; R6 := "Junction.MissionTasks.Rewards.Left"
204 [-]: LOADK     R7 K60       ; R7 := "SelectCallback"
205 [-]: LOADK     R8 K67       ; R8 := "LeftCyclerPressed"
206 [-]: CALL      R4 5 1       ; R4(R5,R6,R7,R8)
207 [-]: GETGLOBAL R4 K7        ; R4 := mMovie
208 [-]: SELF      R4 R4 K54    ; R5 := R4; R4 := R4["0x1C19D966"]
209 [-]: LOADK     R6 K66       ; R6 := "Junction.MissionTasks.Rewards.Left"
210 [-]: LOADK     R7 K62       ; R7 := "RollOverCallback"
211 [-]: LOADK     R8 K68       ; R8 := "LeftCyclerFocused"
212 [-]: CALL      R4 5 1       ; R4(R5,R6,R7,R8)
213 [-]: GETGLOBAL R4 K7        ; R4 := mMovie
214 [-]: SELF      R4 R4 K54    ; R5 := R4; R4 := R4["0x1C19D966"]
215 [-]: LOADK     R6 K66       ; R6 := "Junction.MissionTasks.Rewards.Left"
216 [-]: LOADK     R7 K64       ; R7 := "RollOutCallback"
217 [-]: LOADK     R8 K69       ; R8 := "LeftCyclerUnfocused"
218 [-]: CALL      R4 5 1       ; R4(R5,R6,R7,R8)
219 [-]: RETURN    R0 1         ; return 


; Function #3.1:
;
; Name:            
; Defined at line: 67
; #Upvalues:       4
; #Parameters:     1
; Is_vararg:       0
; Max Stack Size:  18

  1 [-]: GETTABLE  R1 R0 K0     ; R1 := R0["mClipName"]
  2 [-]: EQ        0 R1 K1      ; if R1 ~= nil then PC := 5
  3 [-]: JMP       5            ; PC := 5
  4 [-]: RETURN    R0 1         ; return 
  5 [-]: GETGLOBAL R1 K2        ; R1 := mMovie
  6 [-]: SELF      R1 R1 K3     ; R2 := R1; R1 := R1["0x7E1F26D7"]
  7 [-]: GETTABLE  R3 R0 K0     ; R3 := R0["mClipName"]
  8 [-]: LOADK     R4 K4        ; R4 := ".DescBg"
  9 [-]: CONCAT    R3 R3 R4     ; R3 := R3 .. R4
 10 [-]: GETUPVAL  R4 U0        ; R4 := U0
 11 [-]: CALL      R1 4 1       ; R1(R2,R3,R4)
 12 [-]: GETGLOBAL R1 K2        ; R1 := mMovie
 13 [-]: SELF      R1 R1 K5     ; R2 := R1; R1 := R1["0x302AAB2F"]
 14 [-]: GETTABLE  R3 R0 K0     ; R3 := R0["mClipName"]
 15 [-]: LOADK     R4 K4        ; R4 := ".DescBg"
 16 [-]: CONCAT    R3 R3 R4     ; R3 := R3 .. R4
 17 [-]: LOADK     R4 K6        ; R4 := "RectInnerColor"
 18 [-]: GETUPVAL  R5 U1        ; R5 := U1
 19 [-]: GETTABLE  R5 R5 K7     ; R5 := R5["r"]
 20 [-]: GETUPVAL  R6 U1        ; R6 := U1
 21 [-]: GETTABLE  R6 R6 K8     ; R6 := R6["g"]
 22 [-]: GETUPVAL  R7 U1        ; R7 := U1
 23 [-]: GETTABLE  R7 R7 K9     ; R7 := R7["b"]
 24 [-]: GETUPVAL  R8 U2        ; R8 := U2
 25 [-]: CALL      R1 8 1       ; R1(R2,R3,R4,R5,R6,R7,R8)
 26 [-]: GETGLOBAL R1 K2        ; R1 := mMovie
 27 [-]: SELF      R1 R1 K5     ; R2 := R1; R1 := R1["0x302AAB2F"]
 28 [-]: GETTABLE  R3 R0 K0     ; R3 := R0["mClipName"]
 29 [-]: LOADK     R4 K4        ; R4 := ".DescBg"
 30 [-]: CONCAT    R3 R3 R4     ; R3 := R3 .. R4
 31 [-]: LOADK     R4 K10       ; R4 := "RectEdgeColor"
 32 [-]: GETGLOBAL R5 K11       ; R5 := _G
 33 [-]: GETTABLE  R5 R5 K12    ; R5 := R5["UIColorObject_White"]
 34 [-]: GETTABLE  R5 R5 K7     ; R5 := R5["r"]
 35 [-]: GETGLOBAL R6 K11       ; R6 := _G
 36 [-]: GETTABLE  R6 R6 K12    ; R6 := R6["UIColorObject_White"]
 37 [-]: GETTABLE  R6 R6 K8     ; R6 := R6["g"]
 38 [-]: GETGLOBAL R7 K11       ; R7 := _G
 39 [-]: GETTABLE  R7 R7 K12    ; R7 := R7["UIColorObject_White"]
 40 [-]: GETTABLE  R7 R7 K9     ; R7 := R7["b"]
 41 [-]: LOADK     R8 K13       ; R8 := 0.20000000298023
 42 [-]: CALL      R1 8 1       ; R1(R2,R3,R4,R5,R6,R7,R8)
 43 [-]: GETGLOBAL R1 K2        ; R1 := mMovie
 44 [-]: SELF      R1 R1 K3     ; R2 := R1; R1 := R1["0x7E1F26D7"]
 45 [-]: GETTABLE  R3 R0 K0     ; R3 := R0["mClipName"]
 46 [-]: LOADK     R4 K14       ; R4 := ".StatusBg"
 47 [-]: CONCAT    R3 R3 R4     ; R3 := R3 .. R4
 48 [-]: GETUPVAL  R4 U0        ; R4 := U0
 49 [-]: CALL      R1 4 1       ; R1(R2,R3,R4)
 50 [-]: GETGLOBAL R1 K2        ; R1 := mMovie
 51 [-]: SELF      R1 R1 K5     ; R2 := R1; R1 := R1["0x302AAB2F"]
 52 [-]: GETTABLE  R3 R0 K0     ; R3 := R0["mClipName"]
 53 [-]: LOADK     R4 K14       ; R4 := ".StatusBg"
 54 [-]: CONCAT    R3 R3 R4     ; R3 := R3 .. R4
 55 [-]: LOADK     R4 K6        ; R4 := "RectInnerColor"
 56 [-]: GETUPVAL  R5 U1        ; R5 := U1
 57 [-]: GETTABLE  R5 R5 K7     ; R5 := R5["r"]
 58 [-]: GETUPVAL  R6 U1        ; R6 := U1
 59 [-]: GETTABLE  R6 R6 K8     ; R6 := R6["g"]
 60 [-]: GETUPVAL  R7 U1        ; R7 := U1
 61 [-]: GETTABLE  R7 R7 K9     ; R7 := R7["b"]
 62 [-]: GETUPVAL  R8 U2        ; R8 := U2
 63 [-]: CALL      R1 8 1       ; R1(R2,R3,R4,R5,R6,R7,R8)
 64 [-]: GETGLOBAL R1 K2        ; R1 := mMovie
 65 [-]: SELF      R1 R1 K5     ; R2 := R1; R1 := R1["0x302AAB2F"]
 66 [-]: GETTABLE  R3 R0 K0     ; R3 := R0["mClipName"]
 67 [-]: LOADK     R4 K14       ; R4 := ".StatusBg"
 68 [-]: CONCAT    R3 R3 R4     ; R3 := R3 .. R4
 69 [-]: LOADK     R4 K10       ; R4 := "RectEdgeColor"
 70 [-]: GETGLOBAL R5 K11       ; R5 := _G
 71 [-]: GETTABLE  R5 R5 K12    ; R5 := R5["UIColorObject_White"]
 72 [-]: GETTABLE  R5 R5 K7     ; R5 := R5["r"]
 73 [-]: GETGLOBAL R6 K11       ; R6 := _G
 74 [-]: GETTABLE  R6 R6 K12    ; R6 := R6["UIColorObject_White"]
 75 [-]: GETTABLE  R6 R6 K8     ; R6 := R6["g"]
 76 [-]: GETGLOBAL R7 K11       ; R7 := _G
 77 [-]: GETTABLE  R7 R7 K12    ; R7 := R7["UIColorObject_White"]
 78 [-]: GETTABLE  R7 R7 K9     ; R7 := R7["b"]
 79 [-]: LOADK     R8 K13       ; R8 := 0.20000000298023
 80 [-]: CALL      R1 8 1       ; R1(R2,R3,R4,R5,R6,R7,R8)
 81 [-]: GETGLOBAL R1 K2        ; R1 := mMovie
 82 [-]: SELF      R1 R1 K15    ; R2 := R1; R1 := R1["0x5DB0BD4"]
 83 [-]: GETTABLE  R3 R0 K16    ; R3 := R0["Desc"]
 84 [-]: MOVE      R4 R1        ; R4 := R1
 85 [-]: CALL      R1 4 2       ; R1 := R1(R2,R3,R4)
 86 [-]: LOADK     R2 K17       ; R2 := ""
 87 [-]: GETGLOBAL R3 K2        ; R3 := mMovie
 88 [-]: SELF      R3 R3 K15    ; R4 := R3; R3 := R3["0x5DB0BD4"]
 89 [-]: GETTABLE  R5 R0 K18    ; R5 := R0["Hint"]
 90 [-]: MOVE      R6 R1        ; R6 := R1
 91 [-]: NEWTABLE  R7 0 2       ; R7 := {}
 92 [-]: SETTABLE  R7 K19 K20   ; R7["COLOR"] := "<font color=\"#48B8FF\">"
 93 [-]: SETTABLE  R7 K21 K22   ; R7["NO_COLOR"] := "</font>"
 94 [-]: CALL      R3 5 2       ; R3 := R3(R4,R5,R6,R7)
 95 [-]: LEN       R4 R3        ; R4 := # R3
 96 [-]: LT        0 K23 R4     ; if 0 >= R4 then PC := 110
 97 [-]: JMP       110          ; PC := 110
 98 [-]: GETGLOBAL R4 K24       ; R4 := string
 99 [-]: GETTABLE  R4 R4 K25    ; R4 := R4["0x7B782033"]
100 [-]: MOVE      R5 R3        ; R5 := R3
101 [-]: LOADK     R6 K26       ; R6 := 1
102 [-]: LOADK     R7 K26       ; R7 := 1
103 [-]: CALL      R4 4 2       ; R4 := R4(R5,R6,R7)
104 [-]: EQ        1 R4 K27     ; if R4 == "/" then PC := 110
105 [-]: JMP       110          ; PC := 110
106 [-]: LOADK     R4 K28       ; R4 := "<br><br>"
107 [-]: MOVE      R5 R3        ; R5 := R3
108 [-]: CONCAT    R2 R4 R5     ; R2 := R4 .. R5
109 [-]: JMP       116          ; PC := 116
110 [-]: MOVE      R4 R0        ; R4 := R0
111 [-]: TEST      R4 0         ; if not R4 then PC := 116
112 [-]: JMP       116          ; PC := 116
113 [-]: LOADK     R4 K29       ; R4 := "<br><br><font color=\"#FF0000\">[DEV MODE]</font><br>"
114 [-]: MOVE      R5 R3        ; R5 := R3
115 [-]: CONCAT    R2 R4 R5     ; R2 := R4 .. R5
116 [-]: GETGLOBAL R4 K2        ; R4 := mMovie
117 [-]: SELF      R4 R4 K30    ; R5 := R4; R4 := R4["0x880196A7"]
118 [-]: GETTABLE  R6 R0 K0     ; R6 := R0["mClipName"]
119 [-]: LOADK     R7 K16       ; R7 := "Desc"
120 [-]: LOADK     R8 K31       ; R8 := "text"
121 [-]: LOADK     R9 K32       ; R9 := "<p><font color=\"#FFFFFF\">"
122 [-]: MOVE      R10 R1       ; R10 := R1
123 [-]: MOVE      R11 R2       ; R11 := R2
124 [-]: LOADK     R12 K33      ; R12 := "</font></p>"
125 [-]: CONCAT    R9 R9 R12    ; R9 := R9 .. R10 .. R11 .. R12
126 [-]: CALL      R4 6 1       ; R4(R5,R6,R7,R8,R9)
127 [-]: GETGLOBAL R4 K34       ; R4 := 0xF595ADDE
128 [-]: GETGLOBAL R5 K2        ; R5 := mMovie
129 [-]: SELF      R5 R5 K35    ; R6 := R5; R5 := R5["0x6B7B470B"]
130 [-]: GETTABLE  R7 R0 K0     ; R7 := R0["mClipName"]
131 [-]: LOADK     R8 K36       ; R8 := ".Desc"
132 [-]: CONCAT    R7 R7 R8     ; R7 := R7 .. R8
133 [-]: LOADK     R8 K37       ; R8 := "textHeight"
134 [-]: CALL      R5 4 0       ; R5,... := R5(R6,R7,R8)
135 [-]: CALL      R4 0 2       ; R4 := R4(R5,...)
136 [-]: GETGLOBAL R5 K38       ; R5 := math
137 [-]: GETTABLE  R5 R5 K39    ; R5 := R5["0x8B011038"]
138 [-]: MOVE      R6 R4        ; R6 := R4
139 [-]: LOADK     R7 K40       ; R7 := 50
140 [-]: CALL      R5 3 2       ; R5 := R5(R6,R7)
141 [-]: ADD       R5 R5 K41    ; R5 := R5 + 30
142 [-]: GETGLOBAL R6 K2        ; R6 := mMovie
143 [-]: SELF      R6 R6 K30    ; R7 := R6; R6 := R6["0x880196A7"]
144 [-]: GETTABLE  R8 R0 K0     ; R8 := R0["mClipName"]
145 [-]: LOADK     R9 K16       ; R9 := "Desc"
146 [-]: LOADK     R10 K42      ; R10 := "_y"
147 [-]: DIV       R11 R5 K43   ; R11 := R5 / 2
148 [-]: DIV       R12 R4 K43   ; R12 := R4 / 2
149 [-]: SUB       R11 R11 R12  ; R11 := R11 - R12
150 [-]: SUB       R11 R11 K44  ; R11 := R11 - 4
151 [-]: CALL      R6 6 1       ; R6(R7,R8,R9,R10,R11)
152 [-]: GETGLOBAL R6 K2        ; R6 := mMovie
153 [-]: SELF      R6 R6 K30    ; R7 := R6; R6 := R6["0x880196A7"]
154 [-]: GETTABLE  R8 R0 K0     ; R8 := R0["mClipName"]
155 [-]: LOADK     R9 K45       ; R9 := "DescBg"
156 [-]: LOADK     R10 K46      ; R10 := "_height"
157 [-]: MOVE      R11 R5       ; R11 := R5
158 [-]: CALL      R6 6 1       ; R6(R7,R8,R9,R10,R11)
159 [-]: GETGLOBAL R6 K2        ; R6 := mMovie
160 [-]: SELF      R6 R6 K30    ; R7 := R6; R6 := R6["0x880196A7"]
161 [-]: GETTABLE  R8 R0 K0     ; R8 := R0["mClipName"]
162 [-]: LOADK     R9 K47       ; R9 := "DescBlurer"
163 [-]: LOADK     R10 K46      ; R10 := "_height"
164 [-]: SUB       R11 R5 K26   ; R11 := R5 - 1
165 [-]: CALL      R6 6 1       ; R6(R7,R8,R9,R10,R11)
166 [-]: GETGLOBAL R6 K2        ; R6 := mMovie
167 [-]: SELF      R6 R6 K30    ; R7 := R6; R6 := R6["0x880196A7"]
168 [-]: GETTABLE  R8 R0 K0     ; R8 := R0["mClipName"]
169 [-]: LOADK     R9 K48       ; R9 := "StatusBg"
170 [-]: LOADK     R10 K46      ; R10 := "_height"
171 [-]: MOVE      R11 R5       ; R11 := R5
172 [-]: CALL      R6 6 1       ; R6(R7,R8,R9,R10,R11)
173 [-]: GETGLOBAL R6 K2        ; R6 := mMovie
174 [-]: SELF      R6 R6 K30    ; R7 := R6; R6 := R6["0x880196A7"]
175 [-]: GETTABLE  R8 R0 K0     ; R8 := R0["mClipName"]
176 [-]: LOADK     R9 K49       ; R9 := "StatusBlurer"
177 [-]: LOADK     R10 K46      ; R10 := "_height"
178 [-]: SUB       R11 R5 K26   ; R11 := R5 - 1
179 [-]: CALL      R6 6 1       ; R6(R7,R8,R9,R10,R11)
180 [-]: GETGLOBAL R6 K2        ; R6 := mMovie
181 [-]: SELF      R6 R6 K30    ; R7 := R6; R6 := R6["0x880196A7"]
182 [-]: GETTABLE  R8 R0 K0     ; R8 := R0["mClipName"]
183 [-]: LOADK     R9 K50       ; R9 := "ProgBarBg"
184 [-]: LOADK     R10 K46      ; R10 := "_height"
185 [-]: SUB       R11 R5 K44   ; R11 := R5 - 4
186 [-]: CALL      R6 6 1       ; R6(R7,R8,R9,R10,R11)
187 [-]: GETGLOBAL R6 K2        ; R6 := mMovie
188 [-]: SELF      R6 R6 K30    ; R7 := R6; R6 := R6["0x880196A7"]
189 [-]: GETTABLE  R8 R0 K0     ; R8 := R0["mClipName"]
190 [-]: LOADK     R9 K51       ; R9 := "ProgBarFill"
191 [-]: LOADK     R10 K46      ; R10 := "_height"
192 [-]: SUB       R11 R5 K44   ; R11 := R5 - 4
193 [-]: CALL      R6 6 1       ; R6(R7,R8,R9,R10,R11)
194 [-]: GETGLOBAL R6 K2        ; R6 := mMovie
195 [-]: SELF      R6 R6 K30    ; R7 := R6; R6 := R6["0x880196A7"]
196 [-]: GETTABLE  R8 R0 K0     ; R8 := R0["mClipName"]
197 [-]: LOADK     R9 K51       ; R9 := "ProgBarFill"
198 [-]: LOADK     R10 K42      ; R10 := "_y"
199 [-]: GETGLOBAL R11 K34      ; R11 := 0xF595ADDE
200 [-]: GETGLOBAL R12 K2       ; R12 := mMovie
201 [-]: SELF      R12 R12 K35  ; R13 := R12; R12 := R12["0x6B7B470B"]
202 [-]: GETTABLE  R14 R0 K0    ; R14 := R0["mClipName"]
203 [-]: LOADK     R15 K52      ; R15 := ".ProgBarBg"
204 [-]: CONCAT    R14 R14 R15  ; R14 := R14 .. R15
205 [-]: LOADK     R15 K42      ; R15 := "_y"
206 [-]: CALL      R12 4 0      ; R12,... := R12(R13,R14,R15)
207 [-]: CALL      R11 0 2      ; R11 := R11(R12,...)
208 [-]: SUB       R12 R5 K44   ; R12 := R5 - 4
209 [-]: ADD       R11 R11 R12  ; R11 := R11 + R12
210 [-]: CALL      R6 6 1       ; R6(R7,R8,R9,R10,R11)
211 [-]: GETGLOBAL R6 K2        ; R6 := mMovie
212 [-]: SELF      R6 R6 K30    ; R7 := R6; R6 := R6["0x880196A7"]
213 [-]: GETTABLE  R8 R0 K0     ; R8 := R0["mClipName"]
214 [-]: LOADK     R9 K47       ; R9 := "DescBlurer"
215 [-]: LOADK     R10 K53      ; R10 := "_visible"
216 [-]: MOVE      R11 R1       ; R11 := R1
217 [-]: CALL      R6 6 1       ; R6(R7,R8,R9,R10,R11)
218 [-]: GETGLOBAL R6 K2        ; R6 := mMovie
219 [-]: SELF      R6 R6 K30    ; R7 := R6; R6 := R6["0x880196A7"]
220 [-]: GETTABLE  R8 R0 K0     ; R8 := R0["mClipName"]
221 [-]: LOADK     R9 K49       ; R9 := "StatusBlurer"
222 [-]: LOADK     R10 K53      ; R10 := "_visible"
223 [-]: MOVE      R11 R1       ; R11 := R1
224 [-]: CALL      R6 6 1       ; R6(R7,R8,R9,R10,R11)
225 [-]: GETGLOBAL R6 K2        ; R6 := mMovie
226 [-]: SELF      R6 R6 K30    ; R7 := R6; R6 := R6["0x880196A7"]
227 [-]: GETTABLE  R8 R0 K0     ; R8 := R0["mClipName"]
228 [-]: LOADK     R9 K50       ; R9 := "ProgBarBg"
229 [-]: LOADK     R10 K54      ; R10 := "_color"
230 [-]: GETGLOBAL R11 K11      ; R11 := _G
231 [-]: GETTABLE  R11 R11 K55  ; R11 := R11["UIColor_Black"]
232 [-]: CALL      R6 6 1       ; R6(R7,R8,R9,R10,R11)
233 [-]: GETGLOBAL R6 K2        ; R6 := mMovie
234 [-]: SELF      R6 R6 K30    ; R7 := R6; R6 := R6["0x880196A7"]
235 [-]: GETTABLE  R8 R0 K0     ; R8 := R0["mClipName"]
236 [-]: LOADK     R9 K50       ; R9 := "ProgBarBg"
237 [-]: LOADK     R10 K56      ; R10 := "_alpha"
238 [-]: LOADK     R11 K57      ; R11 := 75
239 [-]: CALL      R6 6 1       ; R6(R7,R8,R9,R10,R11)
240 [-]: GETUPVAL  R6 U3        ; R6 := U3
241 [-]: GETTABLE  R6 R6 K58    ; R6 := R6["0xF81722A2"]
242 [-]: GETTABLE  R7 R0 K59    ; R7 := R0["Completed"]
243 [-]: GETTABLE  R8 R0 K60    ; R8 := R0["RequiredCount"]
244 [-]: GETTABLE  R9 R0 K61    ; R9 := R0["Progress"]
245 [-]: CALL      R6 4 2       ; R6 := R6(R7,R8,R9)
246 [-]: LOADK     R7 K62       ; R7 := 9278873
247 [-]: LOADK     R8 K63       ; R8 := "NotStarted"
248 [-]: GETGLOBAL R9 K2        ; R9 := mMovie
249 [-]: SELF      R9 R9 K30    ; R10 := R9; R9 := R9["0x880196A7"]
250 [-]: GETTABLE  R11 R0 K0    ; R11 := R0["mClipName"]
251 [-]: LOADK     R12 K51      ; R12 := "ProgBarFill"
252 [-]: LOADK     R13 K53      ; R13 := "_visible"
253 [-]: LT        1 K23 R6     ; if 0 < R6 then PC := 256
254 [-]: JMP       256          ; PC := 256
255 [-]: MOVE      R14 R0       ; R14 := R0
256 [-]: MOVE      R14 R1       ; R14 := R1
257 [-]: CALL      R9 6 1       ; R9(R10,R11,R12,R13,R14)
258 [-]: LT        0 K23 R6     ; if 0 >= R6 then PC := 300
259 [-]: JMP       300          ; PC := 300
260 [-]: GETUPVAL  R9 U3        ; R9 := U3
261 [-]: GETTABLE  R9 R9 K58    ; R9 := R9["0xF81722A2"]
262 [-]: GETTABLE  R10 R0 K60   ; R10 := R0["RequiredCount"]
263 [-]: EQ        1 R6 R10     ; if R6 == R10 then PC := 266
264 [-]: JMP       266          ; PC := 266
265 [-]: MOVE      R10 R0       ; R10 := R0
266 [-]: MOVE      R10 R1       ; R10 := R1
267 [-]: LOADK     R11 K59      ; R11 := "Completed"
268 [-]: LOADK     R12 K64      ; R12 := "InProgress"
269 [-]: CALL      R9 4 2       ; R9 := R9(R10,R11,R12)
270 [-]: MOVE      R8 R9        ; R8 := R9
271 [-]: GETUPVAL  R9 U3        ; R9 := U3
272 [-]: GETTABLE  R9 R9 K58    ; R9 := R9["0xF81722A2"]
273 [-]: GETTABLE  R10 R0 K60   ; R10 := R0["RequiredCount"]
274 [-]: EQ        1 R6 R10     ; if R6 == R10 then PC := 277
275 [-]: JMP       277          ; PC := 277
276 [-]: MOVE      R10 R0       ; R10 := R0
277 [-]: MOVE      R10 R1       ; R10 := R1
278 [-]: LOADK     R11 K65      ; R11 := 5815460
279 [-]: LOADK     R12 K66      ; R12 := 4765951
280 [-]: CALL      R9 4 2       ; R9 := R9(R10,R11,R12)
281 [-]: MOVE      R7 R9        ; R7 := R9
282 [-]: GETGLOBAL R9 K34       ; R9 := 0xF595ADDE
283 [-]: GETGLOBAL R10 K2       ; R10 := mMovie
284 [-]: SELF      R10 R10 K35  ; R11 := R10; R10 := R10["0x6B7B470B"]
285 [-]: GETTABLE  R12 R0 K0    ; R12 := R0["mClipName"]
286 [-]: LOADK     R13 K52      ; R13 := ".ProgBarBg"
287 [-]: CONCAT    R12 R12 R13  ; R12 := R12 .. R13
288 [-]: LOADK     R13 K46      ; R13 := "_height"
289 [-]: CALL      R10 4 0      ; R10,... := R10(R11,R12,R13)
290 [-]: CALL      R9 0 2       ; R9 := R9(R10,...)
291 [-]: GETGLOBAL R10 K2       ; R10 := mMovie
292 [-]: SELF      R10 R10 K30  ; R11 := R10; R10 := R10["0x880196A7"]
293 [-]: GETTABLE  R12 R0 K0    ; R12 := R0["mClipName"]
294 [-]: LOADK     R13 K51      ; R13 := "ProgBarFill"
295 [-]: LOADK     R14 K46      ; R14 := "_height"
296 [-]: GETTABLE  R15 R0 K60   ; R15 := R0["RequiredCount"]
297 [-]: DIV       R15 R6 R15   ; R15 := R6 / R15
298 [-]: MUL       R15 R9 R15   ; R15 := R9 * R15
299 [-]: CALL      R10 6 1      ; R10(R11,R12,R13,R14,R15)
300 [-]: GETGLOBAL R10 K67      ; R10 := 0x8C64AFA9
301 [-]: GETGLOBAL R11 K2       ; R11 := mMovie
302 [-]: GETTABLE  R12 R0 K0    ; R12 := R0["mClipName"]
303 [-]: LOADK     R13 K68      ; R13 := ".Status.gotoAndStop"
304 [-]: CONCAT    R12 R12 R13  ; R12 := R12 .. R13
305 [-]: MOVE      R13 R8       ; R13 := R8
306 [-]: CALL      R10 4 1      ; R10(R11,R12,R13)
307 [-]: GETGLOBAL R10 K2       ; R10 := mMovie
308 [-]: SELF      R10 R10 K30  ; R11 := R10; R10 := R10["0x880196A7"]
309 [-]: GETTABLE  R12 R0 K0    ; R12 := R0["mClipName"]
310 [-]: LOADK     R13 K61      ; R13 := "Progress"
311 [-]: LOADK     R14 K31      ; R14 := "text"
312 [-]: MOVE      R15 R6       ; R15 := R6
313 [-]: LOADK     R16 K69      ; R16 := " / "
314 [-]: GETTABLE  R17 R0 K60   ; R17 := R0["RequiredCount"]
315 [-]: CONCAT    R15 R15 R17  ; R15 := R15 .. R16 .. R17
316 [-]: CALL      R10 6 1      ; R10(R11,R12,R13,R14,R15)
317 [-]: GETGLOBAL R10 K2       ; R10 := mMovie
318 [-]: SELF      R10 R10 K30  ; R11 := R10; R10 := R10["0x880196A7"]
319 [-]: GETTABLE  R12 R0 K0    ; R12 := R0["mClipName"]
320 [-]: LOADK     R13 K70      ; R13 := "Status"
321 [-]: LOADK     R14 K54      ; R14 := "_color"
322 [-]: MOVE      R15 R7       ; R15 := R7
323 [-]: CALL      R10 6 1      ; R10(R11,R12,R13,R14,R15)
324 [-]: GETGLOBAL R10 K2       ; R10 := mMovie
325 [-]: SELF      R10 R10 K30  ; R11 := R10; R10 := R10["0x880196A7"]
326 [-]: GETTABLE  R12 R0 K0    ; R12 := R0["mClipName"]
327 [-]: LOADK     R13 K61      ; R13 := "Progress"
328 [-]: LOADK     R14 K71      ; R14 := "textColor"
329 [-]: MOVE      R15 R7       ; R15 := R7
330 [-]: CALL      R10 6 1      ; R10(R11,R12,R13,R14,R15)
331 [-]: GETGLOBAL R10 K2       ; R10 := mMovie
332 [-]: SELF      R10 R10 K30  ; R11 := R10; R10 := R10["0x880196A7"]
333 [-]: GETTABLE  R12 R0 K0    ; R12 := R0["mClipName"]
334 [-]: LOADK     R13 K51      ; R13 := "ProgBarFill"
335 [-]: LOADK     R14 K54      ; R14 := "_color"
336 [-]: MOVE      R15 R7       ; R15 := R7
337 [-]: CALL      R10 6 1      ; R10(R11,R12,R13,R14,R15)
338 [-]: RETURN    R0 1         ; return 


; Function #3.2:
;
; Name:            
; Defined at line: 125
; #Upvalues:       0
; #Parameters:     2
; Is_vararg:       0
; Max Stack Size:  13

  1 [-]: LOADK     R2 K0        ; R2 := 0
  2 [-]: LOADK     R3 K1        ; R3 := 1
  3 [-]: GETTABLE  R4 R0 K2     ; R4 := R0["mElements"]
  4 [-]: LEN       R4 R4        ; R4 := # R4
  5 [-]: LOADK     R5 K1        ; R5 := 1
  6 [-]: FORPREP   R3 18        ; R3 -= R5; PC := 18
  7 [-]: GETTABLE  R7 R0 K2     ; R7 := R0["mElements"]
  8 [-]: GETTABLE  R7 R7 R6     ; R7 := R7[R6]
  9 [-]: GETGLOBAL R8 K3        ; R8 := 0xF595ADDE
 10 [-]: GETTABLE  R9 R0 K4     ; R9 := R0["mMovie"]
 11 [-]: SELF      R9 R9 K5     ; R10 := R9; R9 := R9["0x6B7B470B"]
 12 [-]: GETTABLE  R11 R7 K6    ; R11 := R7["mClipName"]
 13 [-]: LOADK     R12 K7       ; R12 := "_height"
 14 [-]: CALL      R9 4 0       ; R9,... := R9(R10,R11,R12)
 15 [-]: CALL      R8 0 2       ; R8 := R8(R9,...)
 16 [-]: ADD       R8 R2 R8     ; R8 := R2 + R8
 17 [-]: ADD       R2 R8 K1     ; R2 := R8 + 1
 18 [-]: FORLOOP   R3 7         ; R3 += R5; if R3 <= R4 then begin PC := 7; R6 := R3 end
 19 [-]: RETURN    R2 2         ; return R2
 20 [-]: RETURN    R0 1         ; return 


; Function #3.3:
;
; Name:            
; Defined at line: 136
; #Upvalues:       0
; #Parameters:     2
; Is_vararg:       0
; Max Stack Size:  12

  1 [-]: GETTABLE  R2 R0 K0     ; R2 := R0["mInitialY"]
  2 [-]: LOADK     R3 K1        ; R3 := 1
  3 [-]: GETTABLE  R4 R1 K2     ; R4 := R1["Id"]
  4 [-]: SUB       R4 R4 K1     ; R4 := R4 - 1
  5 [-]: LOADK     R5 K1        ; R5 := 1
  6 [-]: FORPREP   R3 18        ; R3 -= R5; PC := 18
  7 [-]: GETGLOBAL R7 K3        ; R7 := 0xF595ADDE
  8 [-]: GETTABLE  R8 R0 K4     ; R8 := R0["mMovie"]
  9 [-]: SELF      R8 R8 K5     ; R9 := R8; R8 := R8["0x6B7B470B"]
 10 [-]: GETTABLE  R10 R0 K6    ; R10 := R0["mElements"]
 11 [-]: GETTABLE  R10 R10 R6   ; R10 := R10[R6]
 12 [-]: GETTABLE  R10 R10 K7   ; R10 := R10["mClipName"]
 13 [-]: LOADK     R11 K8       ; R11 := "_height"
 14 [-]: CALL      R8 4 0       ; R8,... := R8(R9,R10,R11)
 15 [-]: CALL      R7 0 2       ; R7 := R7(R8,...)
 16 [-]: ADD       R7 R2 R7     ; R7 := R2 + R7
 17 [-]: ADD       R2 R7 K1     ; R2 := R7 + 1
 18 [-]: FORLOOP   R3 7         ; R3 += R5; if R3 <= R4 then begin PC := 7; R6 := R3 end
 19 [-]: RETURN    R2 2         ; return R2
 20 [-]: RETURN    R0 1         ; return 


; Function #4:
;
; Name:            
; Defined at line: 161
; #Upvalues:       8
; #Parameters:     1
; Is_vararg:       0
; Max Stack Size:  16

  1 [-]: EQ        0 R0 K0      ; if R0 ~= nil then PC := 6
  2 [-]: JMP       6            ; PC := 6
  3 [-]: LOADK     R1 K1        ; R1 := 1
  4 [-]: MOVE      R1 R0        ; R1 := R0
  5 [-]: JMP       23           ; PC := 23
  6 [-]: GETUPVAL  R1 U0        ; R1 := U0
  7 [-]: ADD       R1 R1 R0     ; R1 := R1 + R0
  8 [-]: MOVE      R1 R0        ; R1 := R0
  9 [-]: GETUPVAL  R1 U0        ; R1 := U0
 10 [-]: EQ        0 R1 K2      ; if R1 ~= 0 then PC := 16
 11 [-]: JMP       16           ; PC := 16
 12 [-]: GETUPVAL  R1 U1        ; R1 := U1
 13 [-]: LEN       R1 R1        ; R1 := # R1
 14 [-]: MOVE      R1 R0        ; R1 := R0
 15 [-]: JMP       23           ; PC := 23
 16 [-]: GETUPVAL  R1 U0        ; R1 := U0
 17 [-]: GETUPVAL  R2 U1        ; R2 := U1
 18 [-]: LEN       R2 R2        ; R2 := # R2
 19 [-]: LT        0 R2 R1      ; if R2 >= R1 then PC := 23
 20 [-]: JMP       23           ; PC := 23
 21 [-]: LOADK     R1 K1        ; R1 := 1
 22 [-]: MOVE      R1 R0        ; R1 := R0
 23 [-]: GETUPVAL  R1 U1        ; R1 := U1
 24 [-]: GETUPVAL  R2 U0        ; R2 := U0
 25 [-]: GETTABLE  R1 R1 R2     ; R1 := R1[R2]
 26 [-]: EQ        0 R1 K0      ; if R1 ~= nil then PC := 29
 27 [-]: JMP       29           ; PC := 29
 28 [-]: RETURN    R0 1         ; return 
 29 [-]: GETGLOBAL R1 K3        ; R1 := mMovie
 30 [-]: SELF      R1 R1 K4     ; R2 := R1; R1 := R1["0x1C19D966"]
 31 [-]: LOADK     R3 K5        ; R3 := "Junction.MissionTasks.Rewards.Name"
 32 [-]: LOADK     R4 K6        ; R4 := "_visible"
 33 [-]: GETUPVAL  R5 U1        ; R5 := U1
 34 [-]: GETUPVAL  R6 U0        ; R6 := U0
 35 [-]: GETTABLE  R5 R5 R6     ; R5 := R5[R6]
 36 [-]: GETTABLE  R5 R5 K7     ; R5 := R5["IsMod"]
 37 [-]: MOVE      R5 R5        ; R5 := R5
 38 [-]: CALL      R1 5 1       ; R1(R2,R3,R4,R5)
 39 [-]: GETUPVAL  R1 U1        ; R1 := U1
 40 [-]: GETUPVAL  R2 U0        ; R2 := U0
 41 [-]: GETTABLE  R1 R1 R2     ; R1 := R1[R2]
 42 [-]: GETTABLE  R1 R1 K7     ; R1 := R1["IsMod"]
 43 [-]: TEST      R1 1         ; if R1 then PC := 61
 44 [-]: JMP       61           ; PC := 61
 45 [-]: GETGLOBAL R1 K3        ; R1 := mMovie
 46 [-]: SELF      R1 R1 K8     ; R2 := R1; R1 := R1["0x17028E8F"]
 47 [-]: LOADK     R3 K9        ; R3 := "Junction.MissionTasks.Rewards.Name.text"
 48 [-]: LOADK     R4 K10       ; R4 := "/Lotus/Language/Junction/RewardTitle"
 49 [-]: NEWTABLE  R5 0 3       ; R5 := {}
 50 [-]: GETUPVAL  R6 U0        ; R6 := U0
 51 [-]: SETTABLE  R5 K11 R6    ; R5["X"] := R6
 52 [-]: GETUPVAL  R6 U1        ; R6 := U1
 53 [-]: LEN       R6 R6        ; R6 := # R6
 54 [-]: SETTABLE  R5 K12 R6    ; R5["Y"] := R6
 55 [-]: GETUPVAL  R6 U1        ; R6 := U1
 56 [-]: GETUPVAL  R7 U0        ; R7 := U0
 57 [-]: GETTABLE  R6 R6 R7     ; R6 := R6[R7]
 58 [-]: GETTABLE  R6 R6 K14    ; R6 := R6["Desc"]
 59 [-]: SETTABLE  R5 K13 R6    ; R5["REWARD"] := R6
 60 [-]: CALL      R1 5 1       ; R1(R2,R3,R4,R5)
 61 [-]: GETGLOBAL R1 K3        ; R1 := mMovie
 62 [-]: SELF      R1 R1 K4     ; R2 := R1; R1 := R1["0x1C19D966"]
 63 [-]: LOADK     R3 K15       ; R3 := "Junction.MissionTasks.Rewards.Mod"
 64 [-]: LOADK     R4 K6        ; R4 := "_visible"
 65 [-]: GETUPVAL  R5 U1        ; R5 := U1
 66 [-]: GETUPVAL  R6 U0        ; R6 := U0
 67 [-]: GETTABLE  R5 R5 R6     ; R5 := R5[R6]
 68 [-]: GETTABLE  R5 R5 K7     ; R5 := R5["IsMod"]
 69 [-]: CALL      R1 5 1       ; R1(R2,R3,R4,R5)
 70 [-]: GETGLOBAL R1 K3        ; R1 := mMovie
 71 [-]: SELF      R1 R1 K4     ; R2 := R1; R1 := R1["0x1C19D966"]
 72 [-]: LOADK     R3 K16       ; R3 := "Junction.MissionTasks.Rewards.Image"
 73 [-]: LOADK     R4 K6        ; R4 := "_visible"
 74 [-]: GETUPVAL  R5 U1        ; R5 := U1
 75 [-]: GETUPVAL  R6 U0        ; R6 := U0
 76 [-]: GETTABLE  R5 R5 R6     ; R5 := R5[R6]
 77 [-]: GETTABLE  R5 R5 K7     ; R5 := R5["IsMod"]
 78 [-]: MOVE      R5 R5        ; R5 := R5
 79 [-]: CALL      R1 5 1       ; R1(R2,R3,R4,R5)
 80 [-]: GETGLOBAL R1 K3        ; R1 := mMovie
 81 [-]: SELF      R1 R1 K4     ; R2 := R1; R1 := R1["0x1C19D966"]
 82 [-]: LOADK     R3 K17       ; R3 := "Junction.MissionTasks.Rewards.ImageBg"
 83 [-]: LOADK     R4 K6        ; R4 := "_visible"
 84 [-]: GETUPVAL  R5 U1        ; R5 := U1
 85 [-]: GETUPVAL  R6 U0        ; R6 := U0
 86 [-]: GETTABLE  R5 R5 R6     ; R5 := R5[R6]
 87 [-]: GETTABLE  R5 R5 K7     ; R5 := R5["IsMod"]
 88 [-]: TEST      R5 1         ; if R5 then PC := 95
 89 [-]: JMP       95           ; PC := 95
 90 [-]: GETUPVAL  R5 U1        ; R5 := U1
 91 [-]: GETUPVAL  R6 U0        ; R6 := U0
 92 [-]: GETTABLE  R5 R5 R6     ; R5 := R5[R6]
 93 [-]: GETTABLE  R5 R5 K18    ; R5 := R5["IsRecipe"]
 94 [-]: JMP       97           ; PC := 97
 95 [-]: MOVE      R5 R0        ; R5 := R0
 96 [-]: MOVE      R5 R1        ; R5 := R1
 97 [-]: CALL      R1 5 1       ; R1(R2,R3,R4,R5)
 98 [-]: GETUPVAL  R1 U1        ; R1 := U1
 99 [-]: GETUPVAL  R2 U0        ; R2 := U0
100 [-]: GETTABLE  R1 R1 R2     ; R1 := R1[R2]
101 [-]: GETTABLE  R1 R1 K7     ; R1 := R1["IsMod"]
102 [-]: TEST      R1 0         ; if not R1 then PC := 156
103 [-]: JMP       156          ; PC := 156
104 [-]: NEWTABLE  R1 0 7       ; R1 := {}
105 [-]: GETUPVAL  R2 U1        ; R2 := U1
106 [-]: GETUPVAL  R3 U0        ; R3 := U0
107 [-]: GETTABLE  R2 R2 R3     ; R2 := R2[R3]
108 [-]: GETTABLE  R2 R2 K20    ; R2 := R2["ItemType"]
109 [-]: SETTABLE  R1 K19 R2    ; R1["mItemType"] := R2
110 [-]: GETGLOBAL R2 K22       ; R2 := 0x7C282057
111 [-]: GETUPVAL  R3 U1        ; R3 := U1
112 [-]: GETUPVAL  R4 U0        ; R4 := U0
113 [-]: GETTABLE  R3 R3 R4     ; R3 := R3[R4]
114 [-]: GETTABLE  R3 R3 K20    ; R3 := R3["ItemType"]
115 [-]: CALL      R2 2 2       ; R2 := R2(R3)
116 [-]: SETTABLE  R1 K21 R2    ; R1["mInstance"] := R2
117 [-]: SETTABLE  R1 K23 K1    ; R1["mItemCount"] := 1
118 [-]: NEWTABLE  R2 0 1       ; R2 := {}
119 [-]: SETTABLE  R2 K25 K26   ; R2["Id"] := ""
120 [-]: SETTABLE  R1 K24 R2    ; R1["mItemId"] := R2
121 [-]: SETTABLE  R1 K27 K26   ; R1["mUpgradeFingerprint"] := ""
122 [-]: SETTABLE  R1 K28 K2    ; R1["mSlot"] := 0
123 [-]: SETTABLE  R1 K29 K0    ; R1["mPolarity"] := nil
124 [-]: GETUPVAL  R2 U2        ; R2 := U2
125 [-]: GETTABLE  R2 R2 K30    ; R2 := R2["0x8383A1DC"]
126 [-]: MOVE      R3 R1        ; R3 := R1
127 [-]: LOADK     R4 K1        ; R4 := 1
128 [-]: CALL      R2 3 2       ; R2 := R2(R3,R4)
129 [-]: NEWTABLE  R3 0 3       ; R3 := {}
130 [-]: SETTABLE  R3 K31 K15   ; R3["mClipName"] := "Junction.MissionTasks.Rewards.Mod"
131 [-]: SETTABLE  R3 K32 R2    ; R3["Card"] := R2
132 [-]: SETTABLE  R3 K29 K2    ; R3["mPolarity"] := 0
133 [-]: GETUPVAL  R4 U2        ; R4 := U2
134 [-]: GETTABLE  R4 R4 K33    ; R4 := R4["0xA7A7B88"]
135 [-]: MOVE      R5 R3        ; R5 := R3
136 [-]: CALL      R4 2 1       ; R4(R5)
137 [-]: GETUPVAL  R4 U2        ; R4 := U2
138 [-]: GETTABLE  R4 R4 K34    ; R4 := R4["0x697262FB"]
139 [-]: MOVE      R5 R3        ; R5 := R3
140 [-]: GETTABLE  R6 R3 K31    ; R6 := R3["mClipName"]
141 [-]: LOADK     R7 K35       ; R7 := ".Card"
142 [-]: CONCAT    R6 R6 R7     ; R6 := R6 .. R7
143 [-]: MOVE      R7 R0        ; R7 := R0
144 [-]: LOADK     R8 K2        ; R8 := 0
145 [-]: LOADNIL   R9 R11       ; R9 := R10 := R11 := nil
146 [-]: GETUPVAL  R12 U3       ; R12 := U3
147 [-]: GETTABLE  R12 R12 K36  ; R12 := R12["0xF81722A2"]
148 [-]: GETGLOBAL R13 K37      ; R13 := 0x400E7765
149 [-]: GETUPVAL  R14 U4       ; R14 := U4
150 [-]: CALL      R13 2 2      ; R13 := R13(R14)
151 [-]: LOADK     R14 K38      ; R14 := 2
152 [-]: LOADK     R15 K1       ; R15 := 1
153 [-]: CALL      R12 4 0      ; R12,... := R12(R13,R14,R15)
154 [-]: CALL      R4 0 1       ; R4(R5,...)
155 [-]: JMP       178          ; PC := 178
156 [-]: GETUPVAL  R4 U1        ; R4 := U1
157 [-]: GETUPVAL  R5 U0        ; R5 := U0
158 [-]: GETTABLE  R4 R4 R5     ; R4 := R4[R5]
159 [-]: GETTABLE  R4 R4 K39    ; R4 := R4["Icon"]
160 [-]: GETGLOBAL R5 K40       ; R5 := _G
161 [-]: GETTABLE  R5 R5 K41    ; R5 := R5["UITexture_CreditsIcon"]
162 [-]: EQ        0 R4 R5      ; if R4 ~= R5 then PC := 170
163 [-]: JMP       170          ; PC := 170
164 [-]: GETUPVAL  R4 U1        ; R4 := U1
165 [-]: GETUPVAL  R5 U0        ; R5 := U0
166 [-]: GETTABLE  R4 R4 R5     ; R4 := R4[R5]
167 [-]: GETGLOBAL R5 K40       ; R5 := _G
168 [-]: GETTABLE  R5 R5 K42    ; R5 := R5["UITexture_CreditsStoreItemIcon"]
169 [-]: SETTABLE  R4 K39 R5    ; R4["Icon"] := R5
170 [-]: GETGLOBAL R4 K3        ; R4 := mMovie
171 [-]: SELF      R4 R4 K43    ; R5 := R4; R4 := R4["0x26581636"]
172 [-]: LOADK     R6 K16       ; R6 := "Junction.MissionTasks.Rewards.Image"
173 [-]: GETUPVAL  R7 U1        ; R7 := U1
174 [-]: GETUPVAL  R8 U0        ; R8 := U0
175 [-]: GETTABLE  R7 R7 R8     ; R7 := R7[R8]
176 [-]: GETTABLE  R7 R7 K39    ; R7 := R7["Icon"]
177 [-]: CALL      R4 4 1       ; R4(R5,R6,R7)
178 [-]: GETUPVAL  R4 U3        ; R4 := U3
179 [-]: GETTABLE  R4 R4 K36    ; R4 := R4["0xF81722A2"]
180 [-]: GETUPVAL  R5 U1        ; R5 := U1
181 [-]: GETUPVAL  R6 U0        ; R6 := U0
182 [-]: GETTABLE  R5 R5 R6     ; R5 := R5[R6]
183 [-]: GETTABLE  R5 R5 K7     ; R5 := R5["IsMod"]
184 [-]: LOADK     R6 K1        ; R6 := 1
185 [-]: GETGLOBAL R7 K44       ; R7 := 0xF595ADDE
186 [-]: GETGLOBAL R8 K3        ; R8 := mMovie
187 [-]: SELF      R8 R8 K45    ; R9 := R8; R8 := R8["0x6B7B470B"]
188 [-]: LOADK     R10 K5       ; R10 := "Junction.MissionTasks.Rewards.Name"
189 [-]: LOADK     R11 K46      ; R11 := "textLines"
190 [-]: CALL      R8 4 0       ; R8,... := R8(R9,R10,R11)
191 [-]: CALL      R7 0 0       ; R7,... := R7(R8,...)
192 [-]: CALL      R4 0 2       ; R4 := R4(R5,...)
193 [-]: GETGLOBAL R5 K44       ; R5 := 0xF595ADDE
194 [-]: GETGLOBAL R6 K3        ; R6 := mMovie
195 [-]: SELF      R6 R6 K45    ; R7 := R6; R6 := R6["0x6B7B470B"]
196 [-]: LOADK     R8 K16       ; R8 := "Junction.MissionTasks.Rewards.Image"
197 [-]: LOADK     R9 K47       ; R9 := "_height"
198 [-]: CALL      R6 4 0       ; R6,... := R6(R7,R8,R9)
199 [-]: CALL      R5 0 2       ; R5 := R5(R6,...)
200 [-]: GETUPVAL  R6 U5        ; R6 := U5
201 [-]: SUB       R7 R4 K1     ; R7 := R4 - 1
202 [-]: MUL       R7 R7 K48    ; R7 := R7 * 20
203 [-]: ADD       R6 R6 R7     ; R6 := R6 + R7
204 [-]: GETGLOBAL R7 K3        ; R7 := mMovie
205 [-]: SELF      R7 R7 K4     ; R8 := R7; R7 := R7["0x1C19D966"]
206 [-]: LOADK     R9 K49       ; R9 := "Junction.MissionTasks.Rewards.Bg"
207 [-]: LOADK     R10 K47      ; R10 := "_height"
208 [-]: MOVE      R11 R6       ; R11 := R6
209 [-]: CALL      R7 5 1       ; R7(R8,R9,R10,R11)
210 [-]: GETGLOBAL R7 K3        ; R7 := mMovie
211 [-]: SELF      R7 R7 K4     ; R8 := R7; R7 := R7["0x1C19D966"]
212 [-]: LOADK     R9 K50       ; R9 := "Junction.MissionTasks.Rewards.Blurer"
213 [-]: LOADK     R10 K47      ; R10 := "_height"
214 [-]: MOVE      R11 R6       ; R11 := R6
215 [-]: CALL      R7 5 1       ; R7(R8,R9,R10,R11)
216 [-]: GETGLOBAL R7 K3        ; R7 := mMovie
217 [-]: SELF      R7 R7 K4     ; R8 := R7; R7 := R7["0x1C19D966"]
218 [-]: LOADK     R9 K16       ; R9 := "Junction.MissionTasks.Rewards.Image"
219 [-]: LOADK     R10 K51      ; R10 := "_y"
220 [-]: DIV       R11 R5 K38   ; R11 := R5 / 2
221 [-]: SUB       R11 R6 R11   ; R11 := R6 - R11
222 [-]: SUB       R11 R11 K52  ; R11 := R11 - 5
223 [-]: CALL      R7 5 1       ; R7(R8,R9,R10,R11)
224 [-]: GETGLOBAL R7 K3        ; R7 := mMovie
225 [-]: SELF      R7 R7 K4     ; R8 := R7; R7 := R7["0x1C19D966"]
226 [-]: LOADK     R9 K17       ; R9 := "Junction.MissionTasks.Rewards.ImageBg"
227 [-]: LOADK     R10 K51      ; R10 := "_y"
228 [-]: DIV       R11 R5 K38   ; R11 := R5 / 2
229 [-]: SUB       R11 R6 R11   ; R11 := R6 - R11
230 [-]: SUB       R11 R11 K52  ; R11 := R11 - 5
231 [-]: CALL      R7 5 1       ; R7(R8,R9,R10,R11)
232 [-]: GETGLOBAL R7 K3        ; R7 := mMovie
233 [-]: SELF      R7 R7 K4     ; R8 := R7; R7 := R7["0x1C19D966"]
234 [-]: LOADK     R9 K53       ; R9 := "Junction.MissionTasks.Rewards.Right"
235 [-]: LOADK     R10 K51      ; R10 := "_y"
236 [-]: DIV       R11 R6 K38   ; R11 := R6 / 2
237 [-]: CALL      R7 5 1       ; R7(R8,R9,R10,R11)
238 [-]: GETGLOBAL R7 K3        ; R7 := mMovie
239 [-]: SELF      R7 R7 K4     ; R8 := R7; R7 := R7["0x1C19D966"]
240 [-]: LOADK     R9 K54       ; R9 := "Junction.MissionTasks.Rewards.Left"
241 [-]: LOADK     R10 K51      ; R10 := "_y"
242 [-]: DIV       R11 R6 K38   ; R11 := R6 / 2
243 [-]: CALL      R7 5 1       ; R7(R8,R9,R10,R11)
244 [-]: GETUPVAL  R7 U7        ; R7 := U7
245 [-]: MOVE      R7 R6        ; R7 := R6
246 [-]: RETURN    R0 1         ; return 


; Function #5:
;
; Name:            
; Defined at line: 212
; #Upvalues:       9
; #Parameters:     0
; Is_vararg:       0
; Max Stack Size:  57

  1 [-]: NEWTABLE  R1 0 0       ; R1 := {}
  2 [-]: NEWTABLE  R2 0 0       ; R2 := {}
  3 [-]: NEWTABLE  R3 0 0       ; R3 := {}
  4 [-]: LOADK     R4 K0        ; R4 := ""
  5 [-]: LOADK     R5 K1        ; R5 := "/Lotus/Language/Junction/RegionDesc"
  6 [-]: MOVE      R6 R0        ; R6 := R0
  7 [-]: GETGLOBAL R7 K2        ; R7 := _T
  8 [-]: GETTABLE  R7 R7 K3     ; R7 := R7["JunctionTasksUIRadialSector"]
  9 [-]: TEST      R7 0         ; if not R7 then PC := 14
 10 [-]: JMP       14           ; PC := 14
 11 [-]: GETGLOBAL R7 K2        ; R7 := _T
 12 [-]: GETTABLE  R0 R7 K3     ; R0 := R7["JunctionTasksUIRadialSector"]
 13 [-]: JMP       22           ; PC := 22
 14 [-]: GETUPVAL  R7 U0        ; R7 := U0
 15 [-]: SELF      R7 R7 K4     ; R8 := R7; R7 := R7["0xDF213CE1"]
 16 [-]: GETGLOBAL R9 K5        ; R9 := gGameRules
 17 [-]: SELF      R9 R9 K6     ; R10 := R9; R9 := R9["0xB8637349"]
 18 [-]: CALL      R9 2 2       ; R9 := R9(R10)
 19 [-]: GETTABLE  R9 R9 K7     ; R9 := R9["location"]
 20 [-]: CALL      R7 3 2       ; R7 := R7(R8,R9)
 21 [-]: MOVE      R0 R7        ; R0 := R7
 22 [-]: GETGLOBAL R7 K8        ; R7 := 0xE6DC43B0
 23 [-]: GETTABLE  R8 R0 K9     ; R8 := R0["locTag"]
 24 [-]: SELF      R8 R8 K10    ; R9 := R8; R8 := R8["0x5EC7A3D2"]
 25 [-]: CALL      R8 2 2       ; R8 := R8(R9)
 26 [-]: LOADNIL   R9 R9        ; R9 := nil
 27 [-]: CALL      R7 3 2       ; R7 := R7(R8,R9)
 28 [-]: MOVE      R4 R7        ; R4 := R7
 29 [-]: GETTABLE  R7 R0 K11    ; R7 := R0["mission"]
 30 [-]: GETUPVAL  R8 U1        ; R8 := U1
 31 [-]: GETTABLE  R8 R8 K12    ; R8 := R8["0xF030C338"]
 32 [-]: GETGLOBAL R9 K13       ; R9 := mMovie
 33 [-]: GETTABLE  R10 R7 K14   ; R10 := R7["missionReward"]
 34 [-]: MOVE      R11 R1       ; R11 := R1
 35 [-]: CALL      R8 4 2       ; R8 := R8(R9,R10,R11)
 36 [-]: MOVE      R1 R8        ; R1 := R8
 37 [-]: GETUPVAL  R8 U1        ; R8 := U1
 38 [-]: GETTABLE  R8 R8 K15    ; R8 := R8["0xD24950E2"]
 39 [-]: GETTABLE  R9 R7 K14    ; R9 := R7["missionReward"]
 40 [-]: CALL      R8 2 2       ; R8 := R8(R9)
 41 [-]: MOVE      R2 R8        ; R2 := R8
 42 [-]: GETTABLE  R3 R0 K16    ; R3 := R0["challenges"]
 43 [-]: GETGLOBAL R8 K17       ; R8 := 0x400E7765
 44 [-]: MOVE      R9 R3        ; R9 := R3
 45 [-]: CALL      R8 2 2       ; R8 := R8(R9)
 46 [-]: TEST      R8 1         ; if R8 then PC := 54
 47 [-]: JMP       54           ; PC := 54
 48 [-]: GETGLOBAL R8 K17       ; R8 := 0x400E7765
 49 [-]: GETGLOBAL R9 K2        ; R9 := _T
 50 [-]: GETTABLE  R9 R9 K18    ; R9 := R9["JunctionTasksRelayReconstruction"]
 51 [-]: CALL      R8 2 2       ; R8 := R8(R9)
 52 [-]: TEST      R8 1         ; if R8 then PC := 101
 53 [-]: JMP       101          ; PC := 101
 54 [-]: NEWTABLE  R8 0 0       ; R8 := {}
 55 [-]: NEWTABLE  R9 0 0       ; R9 := {}
 56 [-]: MOVE      R3 R9        ; R3 := R9
 57 [-]: GETGLOBAL R9 K17       ; R9 := 0x400E7765
 58 [-]: GETGLOBAL R10 K2       ; R10 := _T
 59 [-]: GETTABLE  R10 R10 K18  ; R10 := R10["JunctionTasksRelayReconstruction"]
 60 [-]: CALL      R9 2 2       ; R9 := R9(R10)
 61 [-]: TEST      R9 1         ; if R9 then PC := 67
 62 [-]: JMP       67           ; PC := 67
 63 [-]: GETGLOBAL R9 K2        ; R9 := _T
 64 [-]: GETTABLE  R9 R9 K18    ; R9 := R9["JunctionTasksRelayReconstruction"]
 65 [-]: GETTABLE  R8 R9 K19    ; R8 := R9["mTasks"]
 66 [-]: JMP       83           ; PC := 83
 67 [-]: GETGLOBAL R9 K2        ; R9 := _T
 68 [-]: GETTABLE  R9 R9 K20    ; R9 := R9["CachedConstructionProjects"]
 69 [-]: LOADK     R10 K21      ; R10 := 1
 70 [-]: LEN       R11 R9       ; R11 := # R9
 71 [-]: LOADK     R12 K21      ; R12 := 1
 72 [-]: FORPREP   R10 82       ; R10 -= R12; PC := 82
 73 [-]: GETTABLE  R14 R9 R13   ; R14 := R9[R13]
 74 [-]: GETTABLE  R14 R14 K22  ; R14 := R14["rebuildNode"]
 75 [-]: GETTABLE  R15 R0 K23   ; R15 := R0["name"]
 76 [-]: EQ        0 R14 R15    ; if R14 ~= R15 then PC := 82
 77 [-]: JMP       82           ; PC := 82
 78 [-]: GETTABLE  R15 R9 R13   ; R15 := R9[R13]
 79 [-]: GETTABLE  R15 R15 K24  ; R15 := R15["info"]
 80 [-]: GETTABLE  R8 R15 K19   ; R8 := R15["mTasks"]
 81 [-]: JMP       83           ; PC := 83
 82 [-]: FORLOOP   R10 73       ; R10 += R12; if R10 <= R11 then begin PC := 73; R13 := R10 end
 83 [-]: LEN       R15 R8       ; R15 := # R8
 84 [-]: LT        0 K25 R15    ; if 0 >= R15 then PC := 88
 85 [-]: JMP       88           ; PC := 88
 86 [-]: MOVE      R6 R1        ; R6 := R1
 87 [-]: LOADK     R5 K26       ; R5 := "/Lotus/Language/Junction/RelayReconDesc"
 88 [-]: GETGLOBAL R15 K27      ; R15 := 0x63B09107
 89 [-]: MOVE      R16 R8       ; R16 := R8
 90 [-]: CALL      R15 2 4      ; R15,R16,R17 := R15(R16)
 91 [-]: JMP       99           ; PC := 99
 92 [-]: GETGLOBAL R20 K28      ; R20 := table
 93 [-]: GETTABLE  R20 R20 K29  ; R20 := R20["0xE6450C9D"]
 94 [-]: MOVE      R21 R3       ; R21 := R3
 95 [-]: GETGLOBAL R22 K30      ; R22 := 0x7C282057
 96 [-]: MOVE      R23 R19      ; R23 := R19
 97 [-]: CALL      R22 2 0      ; R22,... := R22(R23)
 98 [-]: CALL      R20 0 1      ; R20(R21,...)
 99 [-]: TFORLOOP  R15 2        ; R18,R19 :=  R15(R16,R17); if R18 ~= nil then begin PC = 92; R17 := R18 end
100 [-]: JMP       92           ; PC := 92
101 [-]: NEWTABLE  R20 0 0      ; R20 := {}
102 [-]: MOVE      R20 R2       ; R20 := R2
103 [-]: LOADK     R20 K21      ; R20 := 1
104 [-]: LEN       R21 R1       ; R21 := # R1
105 [-]: LOADK     R22 K21      ; R22 := 1
106 [-]: FORPREP   R20 133      ; R20 -= R22; PC := 133
107 [-]: NEWTABLE  R24 0 1      ; R24 := {}
108 [-]: GETTABLE  R25 R1 R23   ; R25 := R1[R23]
109 [-]: SETTABLE  R24 K31 R25  ; R24["Desc"] := R25
110 [-]: GETTABLE  R25 R2 R23   ; R25 := R2[R23]
111 [-]: EQ        1 R25 K32    ; if R25 == nil then PC := 128
112 [-]: JMP       128          ; PC := 128
113 [-]: GETTABLE  R25 R2 R23   ; R25 := R2[R23]
114 [-]: GETTABLE  R25 R25 K33  ; R25 := R25["Icon"]
115 [-]: SETTABLE  R24 K33 R25  ; R24["Icon"] := R25
116 [-]: GETTABLE  R25 R2 R23   ; R25 := R2[R23]
117 [-]: GETTABLE  R25 R25 K34  ; R25 := R25["IsRecipe"]
118 [-]: SETTABLE  R24 K34 R25  ; R24["IsRecipe"] := R25
119 [-]: GETTABLE  R25 R2 R23   ; R25 := R2[R23]
120 [-]: GETTABLE  R25 R25 K35  ; R25 := R25["IsMod"]
121 [-]: SETTABLE  R24 K35 R25  ; R24["IsMod"] := R25
122 [-]: GETTABLE  R25 R24 K35  ; R25 := R24["IsMod"]
123 [-]: TEST      R25 0        ; if not R25 then PC := 128
124 [-]: JMP       128          ; PC := 128
125 [-]: GETTABLE  R25 R2 R23   ; R25 := R2[R23]
126 [-]: GETTABLE  R25 R25 K36  ; R25 := R25["ItemType"]
127 [-]: SETTABLE  R24 K36 R25  ; R24["ItemType"] := R25
128 [-]: GETGLOBAL R25 K28      ; R25 := table
129 [-]: GETTABLE  R25 R25 K29  ; R25 := R25["0xE6450C9D"]
130 [-]: GETUPVAL  R26 U2       ; R26 := U2
131 [-]: MOVE      R27 R24      ; R27 := R24
132 [-]: CALL      R25 3 1      ; R25(R26,R27)
133 [-]: FORLOOP   R20 107      ; R20 += R22; if R20 <= R21 then begin PC := 107; R23 := R20 end
134 [-]: GETGLOBAL R25 K13      ; R25 := mMovie
135 [-]: SELF      R25 R25 K37  ; R26 := R25; R25 := R25["0x1C19D966"]
136 [-]: LOADK     R27 K38      ; R27 := "Junction.MissionTasks.Rewards"
137 [-]: LOADK     R28 K39      ; R28 := "_visible"
138 [-]: TEST      R6 1         ; if R6 then PC := 144
139 [-]: JMP       144          ; PC := 144
140 [-]: GETUPVAL  R29 U2       ; R29 := U2
141 [-]: LEN       R29 R29      ; R29 := # R29
142 [-]: LT        1 K25 R29    ; if 0 < R29 then PC := 145
143 [-]: JMP       145          ; PC := 145
144 [-]: MOVE      R29 R0       ; R29 := R0
145 [-]: MOVE      R29 R1       ; R29 := R1
146 [-]: CALL      R25 5 1      ; R25(R26,R27,R28,R29)
147 [-]: GETGLOBAL R25 K13      ; R25 := mMovie
148 [-]: SELF      R25 R25 K37  ; R26 := R25; R25 := R25["0x1C19D966"]
149 [-]: LOADK     R27 K40      ; R27 := "Junction.MissionTasks.Rewards.NextRewardProgress"
150 [-]: LOADK     R28 K39      ; R28 := "_visible"
151 [-]: GETUPVAL  R29 U2       ; R29 := U2
152 [-]: LEN       R29 R29      ; R29 := # R29
153 [-]: LT        1 K21 R29    ; if 1 < R29 then PC := 156
154 [-]: JMP       156          ; PC := 156
155 [-]: MOVE      R29 R0       ; R29 := R0
156 [-]: MOVE      R29 R1       ; R29 := R1
157 [-]: CALL      R25 5 1      ; R25(R26,R27,R28,R29)
158 [-]: GETGLOBAL R25 K13      ; R25 := mMovie
159 [-]: SELF      R25 R25 K37  ; R26 := R25; R25 := R25["0x1C19D966"]
160 [-]: LOADK     R27 K40      ; R27 := "Junction.MissionTasks.Rewards.NextRewardProgress"
161 [-]: LOADK     R28 K41      ; R28 := "_alpha"
162 [-]: GETUPVAL  R29 U3       ; R29 := U3
163 [-]: GETTABLE  R29 R29 K42  ; R29 := R29["0xF81722A2"]
164 [-]: GETGLOBAL R30 K17      ; R30 := 0x400E7765
165 [-]: GETUPVAL  R31 U4       ; R31 := U4
166 [-]: CALL      R30 2 2      ; R30 := R30(R31)
167 [-]: LOADK     R31 K43      ; R31 := 40
168 [-]: LOADK     R32 K44      ; R32 := 100
169 [-]: CALL      R29 4 0      ; R29,... := R29(R30,R31,R32)
170 [-]: CALL      R25 0 1      ; R25(R26,...)
171 [-]: GETGLOBAL R25 K13      ; R25 := mMovie
172 [-]: SELF      R25 R25 K37  ; R26 := R25; R25 := R25["0x1C19D966"]
173 [-]: LOADK     R27 K45      ; R27 := "Junction.MissionTasks.Rewards.Right"
174 [-]: LOADK     R28 K39      ; R28 := "_visible"
175 [-]: GETUPVAL  R29 U2       ; R29 := U2
176 [-]: LEN       R29 R29      ; R29 := # R29
177 [-]: LT        1 K21 R29    ; if 1 < R29 then PC := 180
178 [-]: JMP       180          ; PC := 180
179 [-]: MOVE      R29 R0       ; R29 := R0
180 [-]: MOVE      R29 R1       ; R29 := R1
181 [-]: CALL      R25 5 1      ; R25(R26,R27,R28,R29)
182 [-]: GETGLOBAL R25 K13      ; R25 := mMovie
183 [-]: SELF      R25 R25 K37  ; R26 := R25; R25 := R25["0x1C19D966"]
184 [-]: LOADK     R27 K46      ; R27 := "Junction.MissionTasks.Rewards.Left"
185 [-]: LOADK     R28 K39      ; R28 := "_visible"
186 [-]: MOVE      R29 R0       ; R29 := R0
187 [-]: CALL      R25 5 1      ; R25(R26,R27,R28,R29)
188 [-]: GETUPVAL  R25 U5       ; R25 := U5
189 [-]: CALL      R25 1 1      ; R25()
190 [-]: GETGLOBAL R25 K13      ; R25 := mMovie
191 [-]: SELF      R25 R25 K37  ; R26 := R25; R25 := R25["0x1C19D966"]
192 [-]: LOADK     R27 K47      ; R27 := "Junction.JunctionName"
193 [-]: LOADK     R28 K48      ; R28 := "verticalAlignment"
194 [-]: LOADK     R29 K49      ; R29 := "center"
195 [-]: CALL      R25 5 1      ; R25(R26,R27,R28,R29)
196 [-]: GETGLOBAL R25 K13      ; R25 := mMovie
197 [-]: SELF      R25 R25 K50  ; R26 := R25; R25 := R25["0x17028E8F"]
198 [-]: LOADK     R27 K51      ; R27 := "Junction.JunctionName.text"
199 [-]: GETGLOBAL R28 K52      ; R28 := string
200 [-]: GETTABLE  R28 R28 K53  ; R28 := R28["0x639C642A"]
201 [-]: MOVE      R29 R4       ; R29 := R4
202 [-]: CALL      R28 2 0      ; R28,... := R28(R29)
203 [-]: CALL      R25 0 1      ; R25(R26,...)
204 [-]: GETGLOBAL R25 K54      ; R25 := 0xF595ADDE
205 [-]: GETGLOBAL R26 K13      ; R26 := mMovie
206 [-]: SELF      R26 R26 K55  ; R27 := R26; R26 := R26["0x6B7B470B"]
207 [-]: LOADK     R28 K47      ; R28 := "Junction.JunctionName"
208 [-]: LOADK     R29 K56      ; R29 := "textWidth"
209 [-]: CALL      R26 4 0      ; R26,... := R26(R27,R28,R29)
210 [-]: CALL      R25 0 2      ; R25 := R25(R26,...)
211 [-]: GETGLOBAL R26 K54      ; R26 := 0xF595ADDE
212 [-]: GETGLOBAL R27 K13      ; R27 := mMovie
213 [-]: SELF      R27 R27 K55  ; R28 := R27; R27 := R27["0x6B7B470B"]
214 [-]: LOADK     R29 K57      ; R29 := "Junction.JunctionIcon"
215 [-]: LOADK     R30 K58      ; R30 := "_width"
216 [-]: CALL      R27 4 0      ; R27,... := R27(R28,R29,R30)
217 [-]: CALL      R26 0 2      ; R26 := R26(R27,...)
218 [-]: SUB       R26 R26 K59  ; R26 := R26 - 10
219 [-]: GETGLOBAL R27 K54      ; R27 := 0xF595ADDE
220 [-]: GETGLOBAL R28 K13      ; R28 := mMovie
221 [-]: SELF      R28 R28 K55  ; R29 := R28; R28 := R28["0x6B7B470B"]
222 [-]: LOADK     R30 K60      ; R30 := "Junction.TitleBg"
223 [-]: LOADK     R31 K61      ; R31 := "_x"
224 [-]: CALL      R28 4 0      ; R28,... := R28(R29,R30,R31)
225 [-]: CALL      R27 0 2      ; R27 := R27(R28,...)
226 [-]: GETGLOBAL R28 K13      ; R28 := mMovie
227 [-]: SELF      R28 R28 K37  ; R29 := R28; R28 := R28["0x1C19D966"]
228 [-]: LOADK     R30 K47      ; R30 := "Junction.JunctionName"
229 [-]: LOADK     R31 K61      ; R31 := "_x"
230 [-]: DIV       R32 R25 K62  ; R32 := R25 / 2
231 [-]: SUB       R32 R27 R32  ; R32 := R27 - R32
232 [-]: DIV       R33 R26 K62  ; R33 := R26 / 2
233 [-]: ADD       R32 R32 R33  ; R32 := R32 + R33
234 [-]: CALL      R28 5 1      ; R28(R29,R30,R31,R32)
235 [-]: GETGLOBAL R28 K13      ; R28 := mMovie
236 [-]: SELF      R28 R28 K37  ; R29 := R28; R28 := R28["0x1C19D966"]
237 [-]: LOADK     R30 K57      ; R30 := "Junction.JunctionIcon"
238 [-]: LOADK     R31 K61      ; R31 := "_x"
239 [-]: DIV       R32 R25 K62  ; R32 := R25 / 2
240 [-]: SUB       R32 R27 R32  ; R32 := R27 - R32
241 [-]: CALL      R28 5 1      ; R28(R29,R30,R31,R32)
242 [-]: GETGLOBAL R28 K13      ; R28 := mMovie
243 [-]: SELF      R28 R28 K37  ; R29 := R28; R28 := R28["0x1C19D966"]
244 [-]: LOADK     R30 K63      ; R30 := "Junction.JunctionDesc"
245 [-]: LOADK     R31 K48      ; R31 := "verticalAlignment"
246 [-]: LOADK     R32 K49      ; R32 := "center"
247 [-]: CALL      R28 5 1      ; R28(R29,R30,R31,R32)
248 [-]: GETGLOBAL R28 K13      ; R28 := mMovie
249 [-]: SELF      R28 R28 K50  ; R29 := R28; R28 := R28["0x17028E8F"]
250 [-]: LOADK     R30 K64      ; R30 := "Junction.JunctionDesc.text"
251 [-]: MOVE      R31 R5       ; R31 := R5
252 [-]: CALL      R28 4 1      ; R28(R29,R30,R31)
253 [-]: GETGLOBAL R28 K13      ; R28 := mMovie
254 [-]: SELF      R28 R28 K65  ; R29 := R28; R28 := R28["0x26581636"]
255 [-]: LOADK     R30 K57      ; R30 := "Junction.JunctionIcon"
256 [-]: GETGLOBAL R31 K66      ; R31 := junctionIcon
257 [-]: CALL      R28 4 1      ; R28(R29,R30,R31)
258 [-]: GETUPVAL  R28 U6       ; R28 := U6
259 [-]: SELF      R28 R28 K67  ; R29 := R28; R28 := R28["0x7CF71D03"]
260 [-]: MOVE      R30 R1       ; R30 := R1
261 [-]: MOVE      R31 R1       ; R31 := R1
262 [-]: CALL      R28 4 1      ; R28(R29,R30,R31)
263 [-]: LOADK     R28 K25      ; R28 := 0
264 [-]: LOADK     R29 K25      ; R29 := 0
265 [-]: LOADK     R30 K21      ; R30 := 1
266 [-]: LEN       R31 R3       ; R31 := # R3
267 [-]: LOADK     R32 K21      ; R32 := 1
268 [-]: FORPREP   R30 380      ; R30 -= R32; PC := 380
269 [-]: GETTABLE  R34 R3 R33   ; R34 := R3[R33]
270 [-]: SELF      R34 R34 K68  ; R35 := R34; R34 := R34["0xA8F86A41"]
271 [-]: CALL      R34 2 2      ; R34 := R34(R35)
272 [-]: LEN       R35 R34      ; R35 := # R34
273 [-]: EQ        0 R35 K25    ; if R35 ~= 0 then PC := 380
274 [-]: JMP       380          ; PC := 380
275 [-]: ADD       R29 R29 K21  ; R29 := R29 + 1
276 [-]: MOVE      R35 R1       ; R35 := R1
277 [-]: GETTABLE  R36 R3 R33   ; R36 := R3[R33]
278 [-]: SELF      R36 R36 K69  ; R37 := R36; R36 := R36["0xE5F1FB5F"]
279 [-]: CALL      R36 2 2      ; R36 := R36(R37)
280 [-]: GETGLOBAL R37 K70      ; R37 := 0xECFDD17
281 [-]: MOVE      R38 R36      ; R38 := R36
282 [-]: CALL      R37 2 4      ; R37,R38,R39 := R37(R38)
283 [-]: JMP       295          ; PC := 295
284 [-]: GETGLOBAL R42 K71      ; R42 := gChallengeMgr
285 [-]: SELF      R42 R42 K72  ; R43 := R42; R42 := R42["0x779154B3"]
286 [-]: SELF      R44 R41 K73  ; R45 := R41; R44 := R41["0x34820572"]
287 [-]: CALL      R44 2 0      ; R44,... := R44(R45)
288 [-]: CALL      R42 0 2      ; R42 := R42(R43,...)
289 [-]: SELF      R43 R41 K74  ; R44 := R41; R43 := R41["0x4330268A"]
290 [-]: CALL      R43 2 2      ; R43 := R43(R44)
291 [-]: LT        0 R42 R43    ; if R42 >= R43 then PC := 295
292 [-]: JMP       295          ; PC := 295
293 [-]: MOVE      R35 R0       ; R35 := R0
294 [-]: JMP       297          ; PC := 297
295 [-]: TFORLOOP  R37 2        ; R40,R41 :=  R37(R38,R39); if R40 ~= nil then begin PC = 284; R39 := R40 end
296 [-]: JMP       284          ; PC := 284
297 [-]: TEST      R35 0        ; if not R35 then PC := 380
298 [-]: JMP       380          ; PC := 380
299 [-]: GETTABLE  R42 R3 R33   ; R42 := R3[R33]
300 [-]: SELF      R42 R42 K73  ; R43 := R42; R42 := R42["0x34820572"]
301 [-]: CALL      R42 2 2      ; R42 := R42(R43)
302 [-]: GETGLOBAL R43 K71      ; R43 := gChallengeMgr
303 [-]: SELF      R43 R43 K72  ; R44 := R43; R43 := R43["0x779154B3"]
304 [-]: MOVE      R45 R42      ; R45 := R42
305 [-]: CALL      R43 3 2      ; R43 := R43(R44,R45)
306 [-]: GETTABLE  R44 R3 R33   ; R44 := R3[R33]
307 [-]: SELF      R44 R44 K74  ; R45 := R44; R44 := R44["0x4330268A"]
308 [-]: CALL      R44 2 2      ; R44 := R44(R45)
309 [-]: LE        1 R44 R43    ; if R44 <= R43 then PC := 312
310 [-]: JMP       312          ; PC := 312
311 [-]: MOVE      R45 R0       ; R45 := R0
312 [-]: MOVE      R45 R1       ; R45 := R1
313 [-]: GETUPVAL  R46 U3       ; R46 := U3
314 [-]: GETTABLE  R46 R46 K42  ; R46 := R46["0xF81722A2"]
315 [-]: MOVE      R47 R45      ; R47 := R45
316 [-]: ADD       R48 R28 K21  ; R48 := R28 + 1
317 [-]: MOVE      R49 R28      ; R49 := R28
318 [-]: CALL      R46 4 2      ; R46 := R46(R47,R48,R49)
319 [-]: MOVE      R28 R46      ; R28 := R46
320 [-]: LOADK     R46 K75      ; R46 := "/Lotus/Language/Challenges/Challenge_"
321 [-]: MOVE      R47 R42      ; R47 := R42
322 [-]: LOADK     R48 K76      ; R48 := "_Hint"
323 [-]: CONCAT    R46 R46 R48  ; R46 := R46 .. R47 .. R48
324 [-]: GETGLOBAL R47 K13      ; R47 := mMovie
325 [-]: SELF      R47 R47 K77  ; R48 := R47; R47 := R47["0x5DB0BD4"]
326 [-]: MOVE      R49 R46      ; R49 := R46
327 [-]: MOVE      R50 R0       ; R50 := R0
328 [-]: CALL      R47 4 2      ; R47 := R47(R48,R49,R50)
329 [-]: LEN       R48 R47      ; R48 := # R47
330 [-]: EQ        1 R48 K25    ; if R48 == 0 then PC := 340
331 [-]: JMP       340          ; PC := 340
332 [-]: GETGLOBAL R48 K52      ; R48 := string
333 [-]: GETTABLE  R48 R48 K78  ; R48 := R48["0x7B782033"]
334 [-]: MOVE      R49 R47      ; R49 := R47
335 [-]: LOADK     R50 K21      ; R50 := 1
336 [-]: LOADK     R51 K21      ; R51 := 1
337 [-]: CALL      R48 4 2      ; R48 := R48(R49,R50,R51)
338 [-]: EQ        0 R48 K79    ; if R48 ~= "/" then PC := 366
339 [-]: JMP       366          ; PC := 366
340 [-]: LOADK     R48 K75      ; R48 := "/Lotus/Language/Challenges/Challenge_"
341 [-]: GETGLOBAL R49 K52      ; R49 := string
342 [-]: GETTABLE  R49 R49 K78  ; R49 := R49["0x7B782033"]
343 [-]: MOVE      R50 R42      ; R50 := R42
344 [-]: LOADK     R51 K80      ; R51 := 3
345 [-]: CALL      R49 3 2      ; R49 := R49(R50,R51)
346 [-]: LOADK     R50 K76      ; R50 := "_Hint"
347 [-]: CONCAT    R48 R48 R50  ; R48 := R48 .. R49 .. R50
348 [-]: GETGLOBAL R49 K13      ; R49 := mMovie
349 [-]: SELF      R49 R49 K77  ; R50 := R49; R49 := R49["0x5DB0BD4"]
350 [-]: MOVE      R51 R48      ; R51 := R48
351 [-]: MOVE      R52 R0       ; R52 := R0
352 [-]: CALL      R49 4 2      ; R49 := R49(R50,R51,R52)
353 [-]: MOVE      R47 R49      ; R47 := R49
354 [-]: LEN       R49 R47      ; R49 := # R47
355 [-]: LT        0 K25 R49    ; if 0 >= R49 then PC := 366
356 [-]: JMP       366          ; PC := 366
357 [-]: GETGLOBAL R49 K52      ; R49 := string
358 [-]: GETTABLE  R49 R49 K78  ; R49 := R49["0x7B782033"]
359 [-]: MOVE      R50 R47      ; R50 := R47
360 [-]: LOADK     R51 K21      ; R51 := 1
361 [-]: LOADK     R52 K21      ; R52 := 1
362 [-]: CALL      R49 4 2      ; R49 := R49(R50,R51,R52)
363 [-]: EQ        1 R49 K79    ; if R49 == "/" then PC := 366
364 [-]: JMP       366          ; PC := 366
365 [-]: MOVE      R46 R48      ; R46 := R48
366 [-]: GETUPVAL  R49 U6       ; R49 := U6
367 [-]: SELF      R49 R49 K81  ; R50 := R49; R49 := R49["0xA77DA8EE"]
368 [-]: NEWTABLE  R51 0 5      ; R51 := {}
369 [-]: LOADK     R52 K75      ; R52 := "/Lotus/Language/Challenges/Challenge_"
370 [-]: MOVE      R53 R42      ; R53 := R42
371 [-]: LOADK     R54 K82      ; R54 := "_Name"
372 [-]: CONCAT    R52 R52 R54  ; R52 := R52 .. R53 .. R54
373 [-]: SETTABLE  R51 K31 R52  ; R51["Desc"] := R52
374 [-]: SETTABLE  R51 K83 R43  ; R51["Progress"] := R43
375 [-]: SETTABLE  R51 K84 R44  ; R51["RequiredCount"] := R44
376 [-]: SETTABLE  R51 K85 R45  ; R51["Completed"] := R45
377 [-]: SETTABLE  R51 K86 R46  ; R51["Hint"] := R46
378 [-]: MOVE      R52 R1       ; R52 := R1
379 [-]: CALL      R49 4 1      ; R49(R50,R51,R52)
380 [-]: FORLOOP   R30 269      ; R30 += R32; if R30 <= R31 then begin PC := 269; R33 := R30 end
381 [-]: LE        1 R29 R28    ; if R29 <= R28 then PC := 389
382 [-]: JMP       389          ; PC := 389
383 [-]: GETGLOBAL R49 K87      ; R49 := gFlashMgr
384 [-]: SELF      R49 R49 K88  ; R50 := R49; R49 := R49["0x1089D053"]
385 [-]: LOADK     R51 K89      ; R51 := "LotusGameRules.MissionDebug"
386 [-]: CALL      R49 3 2      ; R49 := R49(R50,R51)
387 [-]: TEST      R49 0        ; if not R49 then PC := 391
388 [-]: JMP       391          ; PC := 391
389 [-]: MOVE      R49 R1       ; R49 := R1
390 [-]: MOVE      R49 R7       ; R49 := R7
391 [-]: GETUPVAL  R49 U7       ; R49 := U7
392 [-]: TEST      R49 0        ; if not R49 then PC := 408
393 [-]: JMP       408          ; PC := 408
394 [-]: GETGLOBAL R49 K90      ; R49 := gRegion
395 [-]: SELF      R49 R49 K91  ; R50 := R49; R49 := R49["0x90391273"]
396 [-]: GETGLOBAL R51 K92      ; R51 := 0xEC274B1A
397 [-]: LOADK     R52 K93      ; R52 := "JunctionTasksComplete"
398 [-]: CALL      R51 2 0      ; R51,... := R51(R52)
399 [-]: CALL      R49 0 2      ; R49 := R49(R50,...)
400 [-]: GETGLOBAL R50 K17      ; R50 := 0x400E7765
401 [-]: MOVE      R51 R49      ; R51 := R49
402 [-]: CALL      R50 2 2      ; R50 := R50(R51)
403 [-]: TEST      R50 1        ; if R50 then PC := 408
404 [-]: JMP       408          ; PC := 408
405 [-]: SELF      R50 R49 K94  ; R51 := R49; R50 := R49["0x8D5886B7"]
406 [-]: LOADK     R52 K95      ; R52 := "TriggerPort"
407 [-]: CALL      R50 3 1      ; R50(R51,R52)
408 [-]: GETUPVAL  R50 U6       ; R50 := U6
409 [-]: SELF      R50 R50 K96  ; R51 := R50; R50 := R50["0x6470BAF4"]
410 [-]: LOADNIL   R52 R53      ; R52 := R53 := nil
411 [-]: MOVE      R54 R1       ; R54 := R1
412 [-]: CALL      R50 5 1      ; R50(R51,R52,R53,R54)
413 [-]: GETUPVAL  R50 U6       ; R50 := U6
414 [-]: SELF      R50 R50 K97  ; R51 := R50; R50 := R50["0x8BF09FB6"]
415 [-]: CALL      R50 2 2      ; R50 := R50(R51)
416 [-]: GETGLOBAL R51 K13      ; R51 := mMovie
417 [-]: SELF      R51 R51 K37  ; R52 := R51; R51 := R51["0x1C19D966"]
418 [-]: LOADK     R53 K38      ; R53 := "Junction.MissionTasks.Rewards"
419 [-]: LOADK     R54 K98      ; R54 := "_y"
420 [-]: MOVE      R55 R50      ; R55 := R50
421 [-]: CALL      R51 5 1      ; R51(R52,R53,R54,R55)
422 [-]: GETUPVAL  R51 U8       ; R51 := U8
423 [-]: ADD       R51 R50 R51  ; R51 := R50 + R51
424 [-]: GETGLOBAL R52 K54      ; R52 := 0xF595ADDE
425 [-]: GETGLOBAL R53 K13      ; R53 := mMovie
426 [-]: SELF      R53 R53 K55  ; R54 := R53; R53 := R53["0x6B7B470B"]
427 [-]: LOADK     R55 K60      ; R55 := "Junction.TitleBg"
428 [-]: LOADK     R56 K99      ; R56 := "_height"
429 [-]: CALL      R53 4 0      ; R53,... := R53(R54,R55,R56)
430 [-]: CALL      R52 0 2      ; R52 := R52(R53,...)
431 [-]: ADD       R50 R51 R52  ; R50 := R51 + R52
432 [-]: GETGLOBAL R51 K13      ; R51 := mMovie
433 [-]: SELF      R51 R51 K37  ; R52 := R51; R51 := R51["0x1C19D966"]
434 [-]: LOADK     R53 K100     ; R53 := "Junction"
435 [-]: LOADK     R54 K98      ; R54 := "_y"
436 [-]: DIV       R55 R50 K62  ; R55 := R50 / 2
437 [-]: SUB       R55 K101 R55 ; R55 := 345 - R55
438 [-]: ADD       R55 K102 R55 ; R55 := 540 + R55
439 [-]: CALL      R51 5 1      ; R51(R52,R53,R54,R55)
440 [-]: RETURN    R0 1         ; return 


; Function #6:
;
; Name:            
; Defined at line: 371
; #Upvalues:       2
; #Parameters:     0
; Is_vararg:       0
; Max Stack Size:  7

  1 [-]: GETGLOBAL R0 K0        ; R0 := 0xF595ADDE
  2 [-]: GETGLOBAL R1 K1        ; R1 := mMovie
  3 [-]: SELF      R1 R1 K2     ; R2 := R1; R1 := R1["0x6B7B470B"]
  4 [-]: LOADK     R3 K3        ; R3 := "Junction.TitleBg"
  5 [-]: LOADK     R4 K4        ; R4 := "_width"
  6 [-]: CALL      R1 4 0       ; R1,... := R1(R2,R3,R4)
  7 [-]: CALL      R0 0 2       ; R0 := R0(R1,...)
  8 [-]: GETUPVAL  R1 U0        ; R1 := U0
  9 [-]: GETTABLE  R1 R1 K5     ; R1 := R1["0xF81722A2"]
 10 [-]: GETUPVAL  R2 U1        ; R2 := U1
 11 [-]: GETGLOBAL R3 K1        ; R3 := mMovie
 12 [-]: SELF      R3 R3 K6     ; R4 := R3; R3 := R3["0xF3E132E0"]
 13 [-]: CALL      R3 2 2       ; R3 := R3(R4)
 14 [-]: DIV       R4 R0 K7     ; R4 := R0 / 2
 15 [-]: ADD       R4 R4 K8     ; R4 := R4 + 60
 16 [-]: SUB       R3 R3 R4     ; R3 := R3 - R4
 17 [-]: DIV       R4 R0 K7     ; R4 := R0 / 2
 18 [-]: ADD       R4 R4 K9     ; R4 := R4 + 100
 19 [-]: CALL      R1 4 2       ; R1 := R1(R2,R3,R4)
 20 [-]: GETGLOBAL R2 K1        ; R2 := mMovie
 21 [-]: SELF      R2 R2 K10    ; R3 := R2; R2 := R2["0x1C19D966"]
 22 [-]: LOADK     R4 K11       ; R4 := "Junction"
 23 [-]: LOADK     R5 K12       ; R5 := "_x"
 24 [-]: MOVE      R6 R1        ; R6 := R1
 25 [-]: CALL      R2 5 1       ; R2(R3,R4,R5,R6)
 26 [-]: RETURN    R0 1         ; return 


; Function #7:
;
; Name:            
; Defined at line: 378
; #Upvalues:       6
; #Parameters:     0
; Is_vararg:       0
; Max Stack Size:  12

  1 [-]: GETGLOBAL R0 K0        ; R0 := 0x93B1256B
  2 [-]: LOADK     R1 K1        ; R1 := "JunctionTasks initialize"
  3 [-]: CALL      R0 2 1       ; R0(R1)
  4 [-]: GETUPVAL  R0 U1        ; R0 := U1
  5 [-]: GETTABLE  R0 R0 K2     ; R0 := R0["0xBB3AACF2"]
  6 [-]: CALL      R0 1 2       ; R0 := R0()
  7 [-]: MOVE      R0 R0        ; R0 := R0
  8 [-]: GETUPVAL  R0 U1        ; R0 := U1
  9 [-]: GETTABLE  R0 R0 K3     ; R0 := R0["0x84DCC428"]
 10 [-]: CALL      R0 1 2       ; R0 := R0()
 11 [-]: GETGLOBAL R1 K4        ; R1 := _G
 12 [-]: GETTABLE  R1 R1 K5     ; R1 := R1["UIMaterial_DepthTestText"]
 13 [-]: GETUPVAL  R2 U1        ; R2 := U1
 14 [-]: GETTABLE  R2 R2 K6     ; R2 := R2["UI_MODE_IN_SPACE_SHIP"]
 15 [-]: EQ        0 R0 R2      ; if R0 ~= R2 then PC := 19
 16 [-]: JMP       19           ; PC := 19
 17 [-]: GETGLOBAL R2 K4        ; R2 := _G
 18 [-]: GETTABLE  R1 R2 K7     ; R1 := R2["UIMaterial_PlainText"]
 19 [-]: GETGLOBAL R2 K8        ; R2 := mMovie
 20 [-]: SELF      R2 R2 K9     ; R3 := R2; R2 := R2["0xADBA304B"]
 21 [-]: MOVE      R4 R1        ; R4 := R1
 22 [-]: CALL      R2 3 1       ; R2(R3,R4)
 23 [-]: GETGLOBAL R2 K8        ; R2 := mMovie
 24 [-]: SELF      R2 R2 K10    ; R3 := R2; R2 := R2["0xFAA780DF"]
 25 [-]: MOVE      R4 R1        ; R4 := R1
 26 [-]: CALL      R2 3 1       ; R2(R3,R4)
 27 [-]: GETGLOBAL R2 K8        ; R2 := mMovie
 28 [-]: SELF      R2 R2 K11    ; R3 := R2; R2 := R2["0x1C19D966"]
 29 [-]: LOADK     R4 K12       ; R4 := "_root"
 30 [-]: LOADK     R5 K13       ; R5 := "_alpha"
 31 [-]: LOADK     R6 K14       ; R6 := 0
 32 [-]: CALL      R2 5 1       ; R2(R3,R4,R5,R6)
 33 [-]: GETGLOBAL R2 K15       ; R2 := 0x52E17A90
 34 [-]: GETGLOBAL R3 K8        ; R3 := mMovie
 35 [-]: LOADK     R4 K12       ; R4 := "_root"
 36 [-]: GETGLOBAL R5 K16       ; R5 := UISys
 37 [-]: GETTABLE  R5 R5 K17    ; R5 := R5["FlashInstance_SMOOTH_STEP"]
 38 [-]: NEWTABLE  R6 1 0       ; R6 := {}
 39 [-]: LOADK     R7 K13       ; R7 := "_alpha"
 40 [-]: SETLIST   R6 1 1       ; R6[(1-1)*FPF+i] := R(6+i), 1 <= i <= 1
 41 [-]: NEWTABLE  R7 0 0       ; R7 := {}
 42 [-]: GETUPVAL  R8 U2        ; R8 := U2
 43 [-]: GETTABLE  R8 R8 K18    ; R8 := R8["0xF81722A2"]
 44 [-]: GETGLOBAL R9 K19       ; R9 := _T
 45 [-]: GETTABLE  R9 R9 K20    ; R9 := R9["JunctionTasksInstant"]
 46 [-]: LOADK     R10 K21      ; R10 := 100
 47 [-]: LOADK     R11 K14      ; R11 := 0
 48 [-]: CALL      R8 4 0       ; R8,... := R8(R9,R10,R11)
 49 [-]: SETLIST   R7 0 1       ; R7[(1-1)*FPF+i] := R(7+i), 1 <= i <= 0
 50 [-]: LOADK     R8 K22       ; R8 := 0.0099999997764826
 51 [-]: LOADK     R9 K14       ; R9 := 0
 52 [-]: CLOSURE   R10 0        ; R10 := closure(Function #7.1)
 53 [-]: GETUPVAL  R0 U3        ; R0 := U3
 54 [-]: GETUPVAL  R0 U4        ; R0 := U4
 55 [-]: CALL      R2 9 1       ; R2(R3,R4,R5,R6,R7,R8,R9,R10)
 56 [-]: GETUPVAL  R2 U5        ; R2 := U5
 57 [-]: CALL      R2 1 1       ; R2()
 58 [-]: GETGLOBAL R2 K8        ; R2 := mMovie
 59 [-]: SELF      R2 R2 K23    ; R3 := R2; R2 := R2["0x7E1F26D7"]
 60 [-]: LOADK     R4 K24       ; R4 := "Junction.MissionTasks.Rewards.NextRewardProgress.Fill"
 61 [-]: GETGLOBAL R5 K25       ; R5 := progressMaterial
 62 [-]: CALL      R2 4 1       ; R2(R3,R4,R5)
 63 [-]: GETGLOBAL R2 K8        ; R2 := mMovie
 64 [-]: SELF      R2 R2 K26    ; R3 := R2; R2 := R2["0x302AAB2F"]
 65 [-]: LOADK     R4 K24       ; R4 := "Junction.MissionTasks.Rewards.NextRewardProgress.Fill"
 66 [-]: LOADK     R5 K27       ; R5 := "AlphaTestThreshold"
 67 [-]: LOADK     R6 K14       ; R6 := 0
 68 [-]: LOADK     R7 K14       ; R7 := 0
 69 [-]: LOADK     R8 K14       ; R8 := 0
 70 [-]: LOADK     R9 K14       ; R9 := 0
 71 [-]: CALL      R2 8 1       ; R2(R3,R4,R5,R6,R7,R8,R9)
 72 [-]: RETURN    R0 1         ; return 


; Function #7.1:
;
; Name:            
; Defined at line: 393
; #Upvalues:       2
; #Parameters:     0
; Is_vararg:       0
; Max Stack Size:  7

  1 [-]: GETGLOBAL R0 K0        ; R0 := _T
  2 [-]: GETTABLE  R0 R0 K1     ; R0 := R0["JunctionTasksInstant"]
  3 [-]: TEST      R0 1         ; if R0 then PC := 18
  4 [-]: JMP       18           ; PC := 18
  5 [-]: GETGLOBAL R0 K2        ; R0 := 0x52E17A90
  6 [-]: GETGLOBAL R1 K3        ; R1 := mMovie
  7 [-]: LOADK     R2 K4        ; R2 := "_root"
  8 [-]: GETGLOBAL R3 K5        ; R3 := UISys
  9 [-]: GETTABLE  R3 R3 K6     ; R3 := R3["FlashInstance_SMOOTH_STEP"]
 10 [-]: NEWTABLE  R4 1 0       ; R4 := {}
 11 [-]: LOADK     R5 K7        ; R5 := "_alpha"
 12 [-]: SETLIST   R4 1 1       ; R4[(1-1)*FPF+i] := R(4+i), 1 <= i <= 1
 13 [-]: NEWTABLE  R5 1 0       ; R5 := {}
 14 [-]: LOADK     R6 K8        ; R6 := 100
 15 [-]: SETLIST   R5 1 1       ; R5[(1-1)*FPF+i] := R(5+i), 1 <= i <= 1
 16 [-]: LOADK     R6 K9        ; R6 := 0.20000000298023
 17 [-]: CALL      R0 7 1       ; R0(R1,R2,R3,R4,R5,R6)
 18 [-]: GETUPVAL  R0 U0        ; R0 := U0
 19 [-]: CALL      R0 1 1       ; R0()
 20 [-]: GETUPVAL  R0 U1        ; R0 := U1
 21 [-]: CALL      R0 1 1       ; R0()
 22 [-]: RETURN    R0 1         ; return 


; Function #8:
;
; Name:            
; Defined at line: 407
; #Upvalues:       3
; #Parameters:     0
; Is_vararg:       0
; Max Stack Size:  9

  1 [-]: GETGLOBAL R0 K0        ; R0 := mMovie
  2 [-]: SELF      R0 R0 K1     ; R1 := R0; R0 := R0["0x80D6B1A"]
  3 [-]: GETGLOBAL R2 K2        ; R2 := 0x6306558E
  4 [-]: CALL      R2 1 0       ; R2,... := R2()
  5 [-]: CALL      R0 0 1       ; R0(R1,...)
  6 [-]: GETUPVAL  R0 U0        ; R0 := U0
  7 [-]: LT        0 K3 R0      ; if 0 >= R0 then PC := 33
  8 [-]: JMP       33           ; PC := 33
  9 [-]: GETUPVAL  R0 U0        ; R0 := U0
 10 [-]: GETGLOBAL R1 K4        ; R1 := 0x4CDEF9FF
 11 [-]: CALL      R1 1 2       ; R1 := R1()
 12 [-]: SUB       R0 R0 R1     ; R0 := R0 - R1
 13 [-]: MOVE      R0 R0        ; R0 := R0
 14 [-]: GETUPVAL  R0 U0        ; R0 := U0
 15 [-]: GETUPVAL  R1 U1        ; R1 := U1
 16 [-]: DIV       R0 R0 R1     ; R0 := R0 / R1
 17 [-]: SUB       R0 K5 R0     ; R0 := 1 - R0
 18 [-]: GETGLOBAL R1 K0        ; R1 := mMovie
 19 [-]: SELF      R1 R1 K6     ; R2 := R1; R1 := R1["0x302AAB2F"]
 20 [-]: LOADK     R3 K7        ; R3 := "Junction.MissionTasks.Rewards.NextRewardProgress.Fill"
 21 [-]: LOADK     R4 K8        ; R4 := "AlphaTestThreshold"
 22 [-]: MOVE      R5 R0        ; R5 := R0
 23 [-]: LOADK     R6 K3        ; R6 := 0
 24 [-]: LOADK     R7 K3        ; R7 := 0
 25 [-]: LOADK     R8 K3        ; R8 := 0
 26 [-]: CALL      R1 8 1       ; R1(R2,R3,R4,R5,R6,R7,R8)
 27 [-]: GETUPVAL  R1 U0        ; R1 := U0
 28 [-]: LE        0 R1 K3      ; if R1 > 0 then PC := 33
 29 [-]: JMP       33           ; PC := 33
 30 [-]: GETUPVAL  R1 U2        ; R1 := U2
 31 [-]: LOADK     R2 K5        ; R2 := 1
 32 [-]: CALL      R1 2 1       ; R1(R2)
 33 [-]: RETURN    R0 1         ; return 


; Function #9:
;
; Name:            
; Defined at line: 421
; #Upvalues:       2
; #Parameters:     0
; Is_vararg:       0
; Max Stack Size:  2

  1 [-]: MOVE      R0 R1        ; R0 := R1
  2 [-]: MOVE      R0 R0        ; R0 := R0
  3 [-]: GETUPVAL  R0 U1        ; R0 := U1
  4 [-]: CALL      R0 1 1       ; R0()
  5 [-]: RETURN    R0 1         ; return 


; Function #10:
;
; Name:            
; Defined at line: 426
; #Upvalues:       2
; #Parameters:     0
; Is_vararg:       0
; Max Stack Size:  2

  1 [-]: GETUPVAL  R0 U0        ; R0 := U0
  2 [-]: GETTABLE  R0 R0 K0     ; R0 := R0["0x25992394"]
  3 [-]: GETGLOBAL R1 K1        ; R1 := _G
  4 [-]: GETTABLE  R1 R1 K2     ; R1 := R1["UISound_Close"]
  5 [-]: CALL      R0 2 1       ; R0(R1)
  6 [-]: GETUPVAL  R0 U1        ; R0 := U1
  7 [-]: CALL      R0 1 1       ; R0()
  8 [-]: RETURN    R0 1         ; return 


; Function #11:
;
; Name:            
; Defined at line: 431
; #Upvalues:       0
; #Parameters:     0
; Is_vararg:       0
; Max Stack Size:  2

  1 [-]: RETURN    R0 1         ; return 


; Function #12:
;
; Name:            
; Defined at line: 435
; #Upvalues:       0
; #Parameters:     1
; Is_vararg:       0
; Max Stack Size:  7

  1 [-]: GETGLOBAL R1 K0        ; R1 := mMovie
  2 [-]: SELF      R1 R1 K1     ; R2 := R1; R1 := R1["0x880196A7"]
  3 [-]: MOVE      R3 R0        ; R3 := R0
  4 [-]: LOADK     R4 K2        ; R4 := "Label"
  5 [-]: LOADK     R5 K3        ; R5 := "textColor"
  6 [-]: GETGLOBAL R6 K4        ; R6 := _G
  7 [-]: GETTABLE  R6 R6 K5     ; R6 := R6["UIColor_Yellow"]
  8 [-]: CALL      R1 6 1       ; R1(R2,R3,R4,R5,R6)
  9 [-]: RETURN    R0 1         ; return 


; Function #13:
;
; Name:            
; Defined at line: 439
; #Upvalues:       0
; #Parameters:     1
; Is_vararg:       0
; Max Stack Size:  7

  1 [-]: GETGLOBAL R1 K0        ; R1 := mMovie
  2 [-]: SELF      R1 R1 K1     ; R2 := R1; R1 := R1["0x880196A7"]
  3 [-]: MOVE      R3 R0        ; R3 := R0
  4 [-]: LOADK     R4 K2        ; R4 := "Label"
  5 [-]: LOADK     R5 K3        ; R5 := "textColor"
  6 [-]: GETGLOBAL R6 K4        ; R6 := _G
  7 [-]: GETTABLE  R6 R6 K5     ; R6 := R6["UIColor_White"]
  8 [-]: CALL      R1 6 1       ; R1(R2,R3,R4,R5,R6)
  9 [-]: RETURN    R0 1         ; return 


; Function #14:
;
; Name:            
; Defined at line: 443
; #Upvalues:       2
; #Parameters:     0
; Is_vararg:       0
; Max Stack Size:  2

  1 [-]: GETUPVAL  R0 U0        ; R0 := U0
  2 [-]: TEST      R0 1         ; if R0 then PC := 7
  3 [-]: JMP       7            ; PC := 7
  4 [-]: GETUPVAL  R0 U1        ; R0 := U1
  5 [-]: LOADK     R1 K0        ; R1 := 1
  6 [-]: CALL      R0 2 1       ; R0(R1)
  7 [-]: RETURN    R0 1         ; return 


; Function #15:
;
; Name:            
; Defined at line: 449
; #Upvalues:       1
; #Parameters:     0
; Is_vararg:       0
; Max Stack Size:  2

  1 [-]: GETUPVAL  R0 U0        ; R0 := U0
  2 [-]: LOADK     R1 K0        ; R1 := "Junction.MissionTasks.Rewards.Right"
  3 [-]: CALL      R0 2 1       ; R0(R1)
  4 [-]: RETURN    R0 1         ; return 


; Function #16:
;
; Name:            
; Defined at line: 453
; #Upvalues:       1
; #Parameters:     0
; Is_vararg:       0
; Max Stack Size:  2

  1 [-]: GETUPVAL  R0 U0        ; R0 := U0
  2 [-]: LOADK     R1 K0        ; R1 := "Junction.MissionTasks.Rewards.Right"
  3 [-]: CALL      R0 2 1       ; R0(R1)
  4 [-]: RETURN    R0 1         ; return 


; Function #17:
;
; Name:            
; Defined at line: 457
; #Upvalues:       2
; #Parameters:     0
; Is_vararg:       0
; Max Stack Size:  2

  1 [-]: GETUPVAL  R0 U0        ; R0 := U0
  2 [-]: TEST      R0 1         ; if R0 then PC := 7
  3 [-]: JMP       7            ; PC := 7
  4 [-]: GETUPVAL  R0 U1        ; R0 := U1
  5 [-]: LOADK     R1 K0        ; R1 := -1
  6 [-]: CALL      R0 2 1       ; R0(R1)
  7 [-]: RETURN    R0 1         ; return 


; Function #18:
;
; Name:            
; Defined at line: 463
; #Upvalues:       1
; #Parameters:     0
; Is_vararg:       0
; Max Stack Size:  2

  1 [-]: GETUPVAL  R0 U0        ; R0 := U0
  2 [-]: LOADK     R1 K0        ; R1 := "Junction.MissionTasks.Rewards.Left"
  3 [-]: CALL      R0 2 1       ; R0(R1)
  4 [-]: RETURN    R0 1         ; return 


; Function #19:
;
; Name:            
; Defined at line: 467
; #Upvalues:       1
; #Parameters:     0
; Is_vararg:       0
; Max Stack Size:  2

  1 [-]: GETUPVAL  R0 U0        ; R0 := U0
  2 [-]: LOADK     R1 K0        ; R1 := "Junction.MissionTasks.Rewards.Left"
  3 [-]: CALL      R0 2 1       ; R0(R1)
  4 [-]: RETURN    R0 1         ; return 


; Function #20:
;
; Name:            
; Defined at line: 471
; #Upvalues:       2
; #Parameters:     0
; Is_vararg:       0
; Max Stack Size:  2

  1 [-]: GETUPVAL  R0 U0        ; R0 := U0
  2 [-]: TEST      R0 1         ; if R0 then PC := 6
  3 [-]: JMP       6            ; PC := 6
  4 [-]: GETUPVAL  R0 U1        ; R0 := U1
  5 [-]: CALL      R0 1 1       ; R0()
  6 [-]: MOVE      R0 R1        ; R0 := R1
  7 [-]: RETURN    R0 2         ; return R0
  8 [-]: RETURN    R0 1         ; return 


; Function #21:
;
; Name:            
; Defined at line: 479
; #Upvalues:       1
; #Parameters:     1
; Is_vararg:       0
; Max Stack Size:  6

  1 [-]: GETGLOBAL R1 K0        ; R1 := 0x93B1256B
  2 [-]: LOADK     R2 K1        ; R2 := "JunctionTasks:SetTrigger"
  3 [-]: CALL      R1 2 1       ; R1(R2)
  4 [-]: MOVE      R0 R0        ; R0 := R0
  5 [-]: GETGLOBAL R1 K2        ; R1 := mMovie
  6 [-]: SELF      R1 R1 K3     ; R2 := R1; R1 := R1["0x7ED97A84"]
  7 [-]: GETGLOBAL R3 K4        ; R3 := depthTestMaterial
  8 [-]: CALL      R1 3 1       ; R1(R2,R3)
  9 [-]: GETGLOBAL R1 K2        ; R1 := mMovie
 10 [-]: SELF      R1 R1 K5     ; R2 := R1; R1 := R1["0x7E1F26D7"]
 11 [-]: LOADK     R3 K6        ; R3 := "Junction.MissionTasks.Rewards.NextRewardProgress.Fill"
 12 [-]: GETGLOBAL R4 K7        ; R4 := progressMaterialDepthTest
 13 [-]: CALL      R1 4 1       ; R1(R2,R3,R4)
 14 [-]: GETGLOBAL R1 K2        ; R1 := mMovie
 15 [-]: SELF      R1 R1 K8     ; R2 := R1; R1 := R1["0x1C19D966"]
 16 [-]: LOADK     R3 K9        ; R3 := "Junction.Blurer"
 17 [-]: LOADK     R4 K10       ; R4 := "_visible"
 18 [-]: MOVE      R5 R1        ; R5 := R1
 19 [-]: CALL      R1 5 1       ; R1(R2,R3,R4,R5)
 20 [-]: GETGLOBAL R1 K2        ; R1 := mMovie
 21 [-]: SELF      R1 R1 K8     ; R2 := R1; R1 := R1["0x1C19D966"]
 22 [-]: LOADK     R3 K11       ; R3 := "Junction.MissionTasks.Rewards.Blurer"
 23 [-]: LOADK     R4 K10       ; R4 := "_visible"
 24 [-]: MOVE      R5 R1        ; R5 := R1
 25 [-]: CALL      R1 5 1       ; R1(R2,R3,R4,R5)
 26 [-]: MOVE      R1 R1        ; R1 := R1
 27 [-]: RETURN    R1 2         ; return R1
 28 [-]: RETURN    R0 1         ; return 


; Function #22:
;
; Name:            
; Defined at line: 493
; #Upvalues:       2
; #Parameters:     1
; Is_vararg:       0
; Max Stack Size:  2

  1 [-]: EQ        1 R0 K0      ; if R0 == "true" then PC := 4
  2 [-]: JMP       4            ; PC := 4
  3 [-]: MOVE      R1 R0        ; R1 := R0
  4 [-]: MOVE      R1 R1        ; R1 := R1
  5 [-]: MOVE      R1 R0        ; R1 := R0
  6 [-]: GETUPVAL  R1 U1        ; R1 := U1
  7 [-]: CALL      R1 1 1       ; R1()
  8 [-]: RETURN    R0 1         ; return 


; Function #23:
;
; Name:            
; Defined at line: 499
; #Upvalues:       1
; #Parameters:     0
; Is_vararg:       0
; Max Stack Size:  2

  1 [-]: GETUPVAL  R0 U0        ; R0 := U0
  2 [-]: CALL      R0 1 1       ; R0()
  3 [-]: RETURN    R0 1         ; return 


; Function #24:
;
; Name:            
; Defined at line: 503
; #Upvalues:       2
; #Parameters:     0
; Is_vararg:       0
; Max Stack Size:  2

  1 [-]: GETGLOBAL R0 K0        ; R0 := 0x400E7765
  2 [-]: GETUPVAL  R1 U0        ; R1 := U0
  3 [-]: CALL      R0 2 2       ; R0 := R0(R1)
  4 [-]: TEST      R0 1         ; if R0 then PC := 8
  5 [-]: JMP       8            ; PC := 8
  6 [-]: GETUPVAL  R0 U1        ; R0 := U1
  7 [-]: CALL      R0 1 1       ; R0()
  8 [-]: RETURN    R0 1         ; return 


