code size: 16
code size: 915
code size: 12
code size: 12
; This file has been disassembled using luadec 2.0.2 by sztupy (http://winmo.sztupy.hu)
; Command line was: -dis M:\git repos\warframe-lua-disassembled\lua\Lotus\Interface\UICommonResources.luac 

; Name:            
; Defined at line: 0
; #Upvalues:       0
; #Parameters:     0
; Is_vararg:       2
; Max Stack Size:  4

  1 [-]: GETGLOBAL R0 K0        ; R0 := 0x329BDC44
  2 [-]: LOADK     R1 K1        ; R1 := "EE.Interface.Utilities"
  3 [-]: CALL      R0 2 2       ; R0 := R0(R1)
  4 [-]: MOVE      R1 R0        ; R1 := R0
  5 [-]: CLOSURE   R2 0         ; R2 := closure(Function #1)
  6 [-]: MOVE      R0 R0        ; R0 := R0
  7 [-]: CLOSURE   R3 1         ; R3 := closure(Function #2)
  8 [-]: MOVE      R0 R2        ; R0 := R2
  9 [-]: MOVE      R0 R1        ; R0 := R1
 10 [-]: SETGLOBAL R3 K2        ; Initialize := R3
 11 [-]: SETGLOBAL R3 K3        ; 0x62648036 := R3
 12 [-]: CLOSURE   R3 2         ; R3 := closure(Function #3)
 13 [-]: MOVE      R0 R1        ; R0 := R1
 14 [-]: SETGLOBAL R3 K4        ; Update := R3
 15 [-]: SETGLOBAL R3 K5        ; 0x8C7099E9 := R3
 16 [-]: RETURN    R0 1         ; return 


; Function #1:
;
; Name:            
; Defined at line: 179
; #Upvalues:       1
; #Parameters:     1
; Is_vararg:       0
; Max Stack Size:  48

  1 [-]: GETGLOBAL R1 K0        ; R1 := 0x400E7765
  2 [-]: GETTABLE  R2 R0 K1     ; R2 := R0["CommonResourcesType"]
  3 [-]: CALL      R1 2 2       ; R1 := R1(R2)
  4 [-]: TEST      R1 1         ; if R1 then PC := 7
  5 [-]: JMP       7            ; PC := 7
  6 [-]: RETURN    R0 1         ; return 
  7 [-]: GETGLOBAL R1 K2        ; R1 := 0xCAA43ABB
  8 [-]: GETGLOBAL R2 K3        ; R2 := mMovie
  9 [-]: SELF      R2 R2 K4     ; R3 := R2; R2 := R2["0x851AD845"]
 10 [-]: CALL      R2 2 0       ; R2,... := R2(R3)
 11 [-]: CALL      R1 0 2       ; R1 := R1(R2,...)
 12 [-]: SETTABLE  R0 K1 R1     ; R0["CommonResourcesType"] := R1
 13 [-]: GETGLOBAL R1 K6        ; R1 := consolePressFx
 14 [-]: SETTABLE  R0 K5 R1     ; R0["UIFx_ConsolePress"] := R1
 15 [-]: GETGLOBAL R1 K8        ; R1 := pcPressFx
 16 [-]: SETTABLE  R0 K7 R1     ; R0["UIFx_PCPress"] := R1
 17 [-]: GETGLOBAL R1 K10       ; R1 := leftBumperPressFx
 18 [-]: SETTABLE  R0 K9 R1     ; R0["UIFx_LeftBumperPress"] := R1
 19 [-]: GETGLOBAL R1 K12       ; R1 := leftBumperPress3dFx
 20 [-]: SETTABLE  R0 K11 R1    ; R0["UIFx_LeftBumperPress3d"] := R1
 21 [-]: GETGLOBAL R1 K14       ; R1 := rightBumperPressFx
 22 [-]: SETTABLE  R0 K13 R1    ; R0["UIFx_RightBumperPress"] := R1
 23 [-]: GETGLOBAL R1 K16       ; R1 := rightBumperPress3dFx
 24 [-]: SETTABLE  R0 K15 R1    ; R0["UIFx_RightBumperPress3d"] := R1
 25 [-]: GETGLOBAL R1 K18       ; R1 := confirmMovie
 26 [-]: SETTABLE  R0 K17 R1    ; R0["UIMovie_ConfirmMovie"] := R1
 27 [-]: GETGLOBAL R1 K20       ; R1 := transmissionMovie
 28 [-]: SETTABLE  R0 K19 R1    ; R0["UIMovie_TransmissionMovie"] := R1
 29 [-]: GETGLOBAL R1 K22       ; R1 := itemBrowsingMovie
 30 [-]: SETTABLE  R0 K21 R1    ; R0["UIMovie_ItemBrowsingMovie"] := R1
 31 [-]: GETGLOBAL R1 K24       ; R1 := platBrowsingMovie
 32 [-]: SETTABLE  R0 K23 R1    ; R0["UIMovie_PlatBrowsingMovie"] := R1
 33 [-]: GETGLOBAL R1 K26       ; R1 := chatReduxMovie
 34 [-]: SETTABLE  R0 K25 R1    ; R0["UIMovie_ChatReduxMovie"] := R1
 35 [-]: GETGLOBAL R1 K28       ; R1 := inputCountMovie
 36 [-]: SETTABLE  R0 K27 R1    ; R0["UIMovie_InputCountMovie"] := R1
 37 [-]: GETGLOBAL R1 K30       ; R1 := colorPickerMovie
 38 [-]: SETTABLE  R0 K29 R1    ; R0["UIMovie_ColorPicker"] := R1
 39 [-]: GETGLOBAL R1 K32       ; R1 := inputDialogMovie
 40 [-]: SETTABLE  R0 K31 R1    ; R0["UIMovie_InputDialogMovie"] := R1
 41 [-]: GETGLOBAL R1 K34       ; R1 := meleeCombosMovie
 42 [-]: SETTABLE  R0 K33 R1    ; R0["UIMovie_MeleeCombosMovie"] := R1
 43 [-]: GETGLOBAL R1 K36       ; R1 := arcWingHudMovie
 44 [-]: SETTABLE  R0 K35 R1    ; R0["UIMovie_ArcWingHudMovie"] := R1
 45 [-]: GETGLOBAL R1 K38       ; R1 := endOfQuestMovie
 46 [-]: SETTABLE  R0 K37 R1    ; R0["UIMovie_EndOfQuestMovie"] := R1
 47 [-]: GETGLOBAL R1 K40       ; R1 := shipDecoHudMovie
 48 [-]: SETTABLE  R0 K39 R1    ; R0["UIMovie_ShipDecoHUD"] := R1
 49 [-]: GETGLOBAL R1 K42       ; R1 := newDetailedPurchaseDialogMovie
 50 [-]: SETTABLE  R0 K41 R1    ; R0["UIMovie_DetailedPurchaseDialog"] := R1
 51 [-]: GETGLOBAL R1 K44       ; R1 := radialSolarMapMovie
 52 [-]: SETTABLE  R0 K43 R1    ; R0["UIMovie_SolarMap"] := R1
 53 [-]: GETGLOBAL R1 K46       ; R1 := genericMenuMovie
 54 [-]: SETTABLE  R0 K45 R1    ; R0["UIMovie_GenericMenu"] := R1
 55 [-]: GETGLOBAL R1 K48       ; R1 := genericSettingsMovie
 56 [-]: SETTABLE  R0 K47 R1    ; R0["UIMovie_GenericSettings"] := R1
 57 [-]: GETGLOBAL R1 K50       ; R1 := loadoutSelectMovie
 58 [-]: SETTABLE  R0 K49 R1    ; R0["UIMovie_LoadoutSelectMovie"] := R1
 59 [-]: GETGLOBAL R1 K52       ; R1 := nemesisMovie
 60 [-]: SETTABLE  R0 K51 R1    ; R0["UIMovie_NemesisInfoMovie"] := R1
 61 [-]: GETGLOBAL R1 K54       ; R1 := plainMaterial
 62 [-]: SETTABLE  R0 K53 R1    ; R0["UIMaterial_Plain"] := R1
 63 [-]: GETGLOBAL R1 K56       ; R1 := plainTextMaterial
 64 [-]: SETTABLE  R0 K55 R1    ; R0["UIMaterial_PlainText"] := R1
 65 [-]: GETGLOBAL R1 K58       ; R1 := depthTestTextMaterial
 66 [-]: SETTABLE  R0 K57 R1    ; R0["UIMaterial_DepthTestText"] := R1
 67 [-]: GETGLOBAL R1 K60       ; R1 := visibilityRangeMaterial
 68 [-]: SETTABLE  R0 K59 R1    ; R0["UIMaterial_VisibilityRange"] := R1
 69 [-]: GETGLOBAL R1 K62       ; R1 := verticalVisibilityRangeMaterial
 70 [-]: SETTABLE  R0 K61 R1    ; R0["UIMaterial_VerticalVisibilityRange"] := R1
 71 [-]: GETGLOBAL R1 K64       ; R1 := verticalVisibilityRangeTextMaterial
 72 [-]: SETTABLE  R0 K63 R1    ; R0["UIMaterial_VerticalVisibilityRangeText"] := R1
 73 [-]: GETGLOBAL R1 K66       ; R1 := plasmaMaterial
 74 [-]: SETTABLE  R0 K65 R1    ; R0["UIMaterial_Plasma"] := R1
 75 [-]: GETGLOBAL R1 K68       ; R1 := iconMaterial
 76 [-]: SETTABLE  R0 K67 R1    ; R0["UIMaterial_Icon"] := R1
 77 [-]: GETGLOBAL R1 K70       ; R1 := miniMapMaterial
 78 [-]: SETTABLE  R0 K69 R1    ; R0["UIMaterial_MiniMap"] := R1
 79 [-]: GETGLOBAL R1 K72       ; R1 := diegeticMaterial
 80 [-]: SETTABLE  R0 K71 R1    ; R0["UIMaterial_Diegetic"] := R1
 81 [-]: GETGLOBAL R1 K74       ; R1 := smoothEdgeMaterial
 82 [-]: SETTABLE  R0 K73 R1    ; R0["UIMaterial_SmoothEdge"] := R1
 83 [-]: GETGLOBAL R1 K76       ; R1 := smoothEdgeMaterialNoDepthTest
 84 [-]: SETTABLE  R0 K75 R1    ; R0["UIMaterial_SmoothEdgeNoDepthTest"] := R1
 85 [-]: GETGLOBAL R1 K78       ; R1 := rectMaterial
 86 [-]: SETTABLE  R0 K77 R1    ; R0["UIMaterial_Rectangle"] := R1
 87 [-]: GETGLOBAL R1 K80       ; R1 := rectNoDepthMaterial
 88 [-]: SETTABLE  R0 K79 R1    ; R0["UIMaterial_RectangleNoDepth"] := R1
 89 [-]: GETGLOBAL R1 K82       ; R1 := pigmentMaterial
 90 [-]: SETTABLE  R0 K81 R1    ; R0["UIMaterial_Pigment"] := R1
 91 [-]: GETGLOBAL R1 K84       ; R1 := pigmentVisRangeMaterial
 92 [-]: SETTABLE  R0 K83 R1    ; R0["UIMaterial_PigmentVisibilityRange"] := R1
 93 [-]: GETGLOBAL R1 K86       ; R1 := bluerMaterial
 94 [-]: SETTABLE  R0 K85 R1    ; R0["UIMaterial_Bluer"] := R1
 95 [-]: GETGLOBAL R1 K88       ; R1 := buttonMaterial
 96 [-]: SETTABLE  R0 K87 R1    ; R0["UIMaterial_Button"] := R1
 97 [-]: GETGLOBAL R1 K90       ; R1 := vitruvianLinesMaterial
 98 [-]: SETTABLE  R0 K89 R1    ; R0["UIMaterial_VitruvianLines"] := R1
 99 [-]: NEWTABLE  R1 0 0       ; R1 := {}
100 [-]: SETTABLE  R0 K91 R1    ; R0["UIMaterial_Mods"] := R1
101 [-]: GETTABLE  R1 R0 K91    ; R1 := R0["UIMaterial_Mods"]
102 [-]: NEWTABLE  R2 0 17      ; R2 := {}
103 [-]: GETGLOBAL R3 K94       ; R3 := modMaterials
104 [-]: GETTABLE  R3 R3 K92    ; R3 := R3[1]
105 [-]: SETTABLE  R2 K93 R3    ; R2["Icon"] := R3
106 [-]: GETGLOBAL R3 K94       ; R3 := modMaterials
107 [-]: GETTABLE  R3 R3 K96    ; R3 := R3[2]
108 [-]: SETTABLE  R2 K95 R3    ; R2["Background"] := R3
109 [-]: GETGLOBAL R3 K94       ; R3 := modMaterials
110 [-]: GETTABLE  R3 R3 K98    ; R3 := R3[3]
111 [-]: SETTABLE  R2 K97 R3    ; R2["Energy"] := R3
112 [-]: GETGLOBAL R3 K94       ; R3 := modMaterials
113 [-]: GETTABLE  R3 R3 K100   ; R3 := R3[4]
114 [-]: SETTABLE  R2 K99 R3    ; R2["BottomFrame"] := R3
115 [-]: GETGLOBAL R3 K94       ; R3 := modMaterials
116 [-]: GETTABLE  R3 R3 K102   ; R3 := R3[5]
117 [-]: SETTABLE  R2 K101 R3   ; R2["TopFrame"] := R3
118 [-]: GETGLOBAL R3 K94       ; R3 := modMaterials
119 [-]: GETTABLE  R3 R3 K104   ; R3 := R3[6]
120 [-]: SETTABLE  R2 K103 R3   ; R2["Content"] := R3
121 [-]: GETGLOBAL R3 K94       ; R3 := modMaterials
122 [-]: GETTABLE  R3 R3 K106   ; R3 := R3[7]
123 [-]: SETTABLE  R2 K105 R3   ; R2["EmptySlot"] := R3
124 [-]: GETGLOBAL R3 K94       ; R3 := modMaterials
125 [-]: GETTABLE  R3 R3 K108   ; R3 := R3[8]
126 [-]: SETTABLE  R2 K107 R3   ; R2["OmegaIcon"] := R3
127 [-]: GETGLOBAL R3 K94       ; R3 := modMaterials
128 [-]: GETTABLE  R3 R3 K110   ; R3 := R3[9]
129 [-]: SETTABLE  R2 K109 R3   ; R2["Text"] := R3
130 [-]: GETGLOBAL R3 K94       ; R3 := modMaterials
131 [-]: GETTABLE  R3 R3 K112   ; R3 := R3[10]
132 [-]: SETTABLE  R2 K111 R3   ; R2["PeculiarEnergy"] := R3
133 [-]: GETGLOBAL R3 K94       ; R3 := modMaterials
134 [-]: GETTABLE  R3 R3 K114   ; R3 := R3[11]
135 [-]: SETTABLE  R2 K113 R3   ; R2["PeculiarBottomFrame"] := R3
136 [-]: GETGLOBAL R3 K94       ; R3 := modMaterials
137 [-]: GETTABLE  R3 R3 K116   ; R3 := R3[12]
138 [-]: SETTABLE  R2 K115 R3   ; R2["PeculiarTopFrame"] := R3
139 [-]: GETGLOBAL R3 K94       ; R3 := modMaterials
140 [-]: GETTABLE  R3 R3 K118   ; R3 := R3[13]
141 [-]: SETTABLE  R2 K117 R3   ; R2["RailjackBottomFrame"] := R3
142 [-]: GETGLOBAL R3 K94       ; R3 := modMaterials
143 [-]: GETTABLE  R3 R3 K120   ; R3 := R3[14]
144 [-]: SETTABLE  R2 K119 R3   ; R2["RailjackTopFrame"] := R3
145 [-]: GETGLOBAL R3 K94       ; R3 := modMaterials
146 [-]: GETTABLE  R3 R3 K122   ; R3 := R3[15]
147 [-]: SETTABLE  R2 K121 R3   ; R2["ImmortalIcon"] := R3
148 [-]: GETGLOBAL R3 K94       ; R3 := modMaterials
149 [-]: GETTABLE  R3 R3 K124   ; R3 := R3[16]
150 [-]: SETTABLE  R2 K123 R3   ; R2["ImmortalBackground"] := R3
151 [-]: GETGLOBAL R3 K94       ; R3 := modMaterials
152 [-]: GETTABLE  R3 R3 K126   ; R3 := R3[17]
153 [-]: SETTABLE  R2 K125 R3   ; R2["ImmortalBottomFrame"] := R3
154 [-]: GETGLOBAL R3 K94       ; R3 := modMaterials
155 [-]: GETTABLE  R3 R3 K128   ; R3 := R3[18]
156 [-]: SETTABLE  R2 K127 R3   ; R2["ImmortalTopFrame"] := R3
157 [-]: SETTABLE  R1 K92 R2    ; R1[1] := R2
158 [-]: GETTABLE  R1 R0 K91    ; R1 := R0["UIMaterial_Mods"]
159 [-]: NEWTABLE  R2 0 17      ; R2 := {}
160 [-]: GETGLOBAL R3 K129      ; R3 := modMaterialsNoDepthTest
161 [-]: GETTABLE  R3 R3 K92    ; R3 := R3[1]
162 [-]: SETTABLE  R2 K93 R3    ; R2["Icon"] := R3
163 [-]: GETGLOBAL R3 K129      ; R3 := modMaterialsNoDepthTest
164 [-]: GETTABLE  R3 R3 K96    ; R3 := R3[2]
165 [-]: SETTABLE  R2 K95 R3    ; R2["Background"] := R3
166 [-]: GETGLOBAL R3 K129      ; R3 := modMaterialsNoDepthTest
167 [-]: GETTABLE  R3 R3 K98    ; R3 := R3[3]
168 [-]: SETTABLE  R2 K97 R3    ; R2["Energy"] := R3
169 [-]: GETGLOBAL R3 K129      ; R3 := modMaterialsNoDepthTest
170 [-]: GETTABLE  R3 R3 K100   ; R3 := R3[4]
171 [-]: SETTABLE  R2 K99 R3    ; R2["BottomFrame"] := R3
172 [-]: GETGLOBAL R3 K129      ; R3 := modMaterialsNoDepthTest
173 [-]: GETTABLE  R3 R3 K102   ; R3 := R3[5]
174 [-]: SETTABLE  R2 K101 R3   ; R2["TopFrame"] := R3
175 [-]: GETGLOBAL R3 K129      ; R3 := modMaterialsNoDepthTest
176 [-]: GETTABLE  R3 R3 K104   ; R3 := R3[6]
177 [-]: SETTABLE  R2 K103 R3   ; R2["Content"] := R3
178 [-]: GETGLOBAL R3 K129      ; R3 := modMaterialsNoDepthTest
179 [-]: GETTABLE  R3 R3 K106   ; R3 := R3[7]
180 [-]: SETTABLE  R2 K105 R3   ; R2["EmptySlot"] := R3
181 [-]: GETGLOBAL R3 K129      ; R3 := modMaterialsNoDepthTest
182 [-]: GETTABLE  R3 R3 K108   ; R3 := R3[8]
183 [-]: SETTABLE  R2 K107 R3   ; R2["OmegaIcon"] := R3
184 [-]: GETGLOBAL R3 K129      ; R3 := modMaterialsNoDepthTest
185 [-]: GETTABLE  R3 R3 K110   ; R3 := R3[9]
186 [-]: SETTABLE  R2 K109 R3   ; R2["Text"] := R3
187 [-]: GETGLOBAL R3 K129      ; R3 := modMaterialsNoDepthTest
188 [-]: GETTABLE  R3 R3 K112   ; R3 := R3[10]
189 [-]: SETTABLE  R2 K111 R3   ; R2["PeculiarEnergy"] := R3
190 [-]: GETGLOBAL R3 K129      ; R3 := modMaterialsNoDepthTest
191 [-]: GETTABLE  R3 R3 K114   ; R3 := R3[11]
192 [-]: SETTABLE  R2 K113 R3   ; R2["PeculiarBottomFrame"] := R3
193 [-]: GETGLOBAL R3 K129      ; R3 := modMaterialsNoDepthTest
194 [-]: GETTABLE  R3 R3 K116   ; R3 := R3[12]
195 [-]: SETTABLE  R2 K115 R3   ; R2["PeculiarTopFrame"] := R3
196 [-]: GETGLOBAL R3 K129      ; R3 := modMaterialsNoDepthTest
197 [-]: GETTABLE  R3 R3 K118   ; R3 := R3[13]
198 [-]: SETTABLE  R2 K117 R3   ; R2["RailjackBottomFrame"] := R3
199 [-]: GETGLOBAL R3 K129      ; R3 := modMaterialsNoDepthTest
200 [-]: GETTABLE  R3 R3 K120   ; R3 := R3[14]
201 [-]: SETTABLE  R2 K119 R3   ; R2["RailjackTopFrame"] := R3
202 [-]: GETGLOBAL R3 K129      ; R3 := modMaterialsNoDepthTest
203 [-]: GETTABLE  R3 R3 K122   ; R3 := R3[15]
204 [-]: SETTABLE  R2 K121 R3   ; R2["ImmortalIcon"] := R3
205 [-]: GETGLOBAL R3 K129      ; R3 := modMaterialsNoDepthTest
206 [-]: GETTABLE  R3 R3 K124   ; R3 := R3[16]
207 [-]: SETTABLE  R2 K123 R3   ; R2["ImmortalBackground"] := R3
208 [-]: GETGLOBAL R3 K129      ; R3 := modMaterialsNoDepthTest
209 [-]: GETTABLE  R3 R3 K126   ; R3 := R3[17]
210 [-]: SETTABLE  R2 K125 R3   ; R2["ImmortalBottomFrame"] := R3
211 [-]: GETGLOBAL R3 K129      ; R3 := modMaterialsNoDepthTest
212 [-]: GETTABLE  R3 R3 K128   ; R3 := R3[18]
213 [-]: SETTABLE  R2 K127 R3   ; R2["ImmortalTopFrame"] := R3
214 [-]: SETTABLE  R1 K96 R2    ; R1[2] := R2
215 [-]: GETTABLE  R1 R0 K91    ; R1 := R0["UIMaterial_Mods"]
216 [-]: NEWTABLE  R2 0 17      ; R2 := {}
217 [-]: GETGLOBAL R3 K130      ; R3 := modMaterialsHorizontal
218 [-]: GETTABLE  R3 R3 K92    ; R3 := R3[1]
219 [-]: SETTABLE  R2 K93 R3    ; R2["Icon"] := R3
220 [-]: GETGLOBAL R3 K130      ; R3 := modMaterialsHorizontal
221 [-]: GETTABLE  R3 R3 K96    ; R3 := R3[2]
222 [-]: SETTABLE  R2 K95 R3    ; R2["Background"] := R3
223 [-]: GETGLOBAL R3 K130      ; R3 := modMaterialsHorizontal
224 [-]: GETTABLE  R3 R3 K98    ; R3 := R3[3]
225 [-]: SETTABLE  R2 K97 R3    ; R2["Energy"] := R3
226 [-]: GETGLOBAL R3 K130      ; R3 := modMaterialsHorizontal
227 [-]: GETTABLE  R3 R3 K100   ; R3 := R3[4]
228 [-]: SETTABLE  R2 K99 R3    ; R2["BottomFrame"] := R3
229 [-]: GETGLOBAL R3 K130      ; R3 := modMaterialsHorizontal
230 [-]: GETTABLE  R3 R3 K102   ; R3 := R3[5]
231 [-]: SETTABLE  R2 K101 R3   ; R2["TopFrame"] := R3
232 [-]: GETGLOBAL R3 K130      ; R3 := modMaterialsHorizontal
233 [-]: GETTABLE  R3 R3 K104   ; R3 := R3[6]
234 [-]: SETTABLE  R2 K103 R3   ; R2["Content"] := R3
235 [-]: GETGLOBAL R3 K130      ; R3 := modMaterialsHorizontal
236 [-]: GETTABLE  R3 R3 K106   ; R3 := R3[7]
237 [-]: SETTABLE  R2 K105 R3   ; R2["EmptySlot"] := R3
238 [-]: GETGLOBAL R3 K130      ; R3 := modMaterialsHorizontal
239 [-]: GETTABLE  R3 R3 K108   ; R3 := R3[8]
240 [-]: SETTABLE  R2 K107 R3   ; R2["OmegaIcon"] := R3
241 [-]: GETGLOBAL R3 K130      ; R3 := modMaterialsHorizontal
242 [-]: GETTABLE  R3 R3 K110   ; R3 := R3[9]
243 [-]: SETTABLE  R2 K109 R3   ; R2["Text"] := R3
244 [-]: GETGLOBAL R3 K130      ; R3 := modMaterialsHorizontal
245 [-]: GETTABLE  R3 R3 K112   ; R3 := R3[10]
246 [-]: SETTABLE  R2 K111 R3   ; R2["PeculiarEnergy"] := R3
247 [-]: GETGLOBAL R3 K130      ; R3 := modMaterialsHorizontal
248 [-]: GETTABLE  R3 R3 K114   ; R3 := R3[11]
249 [-]: SETTABLE  R2 K113 R3   ; R2["PeculiarBottomFrame"] := R3
250 [-]: GETGLOBAL R3 K130      ; R3 := modMaterialsHorizontal
251 [-]: GETTABLE  R3 R3 K116   ; R3 := R3[12]
252 [-]: SETTABLE  R2 K115 R3   ; R2["PeculiarTopFrame"] := R3
253 [-]: GETGLOBAL R3 K130      ; R3 := modMaterialsHorizontal
254 [-]: GETTABLE  R3 R3 K118   ; R3 := R3[13]
255 [-]: SETTABLE  R2 K117 R3   ; R2["RailjackBottomFrame"] := R3
256 [-]: GETGLOBAL R3 K130      ; R3 := modMaterialsHorizontal
257 [-]: GETTABLE  R3 R3 K120   ; R3 := R3[14]
258 [-]: SETTABLE  R2 K119 R3   ; R2["RailjackTopFrame"] := R3
259 [-]: GETGLOBAL R3 K130      ; R3 := modMaterialsHorizontal
260 [-]: GETTABLE  R3 R3 K122   ; R3 := R3[15]
261 [-]: SETTABLE  R2 K121 R3   ; R2["ImmortalIcon"] := R3
262 [-]: GETGLOBAL R3 K130      ; R3 := modMaterialsHorizontal
263 [-]: GETTABLE  R3 R3 K124   ; R3 := R3[16]
264 [-]: SETTABLE  R2 K123 R3   ; R2["ImmortalBackground"] := R3
265 [-]: GETGLOBAL R3 K130      ; R3 := modMaterialsHorizontal
266 [-]: GETTABLE  R3 R3 K126   ; R3 := R3[17]
267 [-]: SETTABLE  R2 K125 R3   ; R2["ImmortalBottomFrame"] := R3
268 [-]: GETGLOBAL R3 K130      ; R3 := modMaterialsHorizontal
269 [-]: GETTABLE  R3 R3 K128   ; R3 := R3[18]
270 [-]: SETTABLE  R2 K127 R3   ; R2["ImmortalTopFrame"] := R3
271 [-]: SETTABLE  R1 K98 R2    ; R1[3] := R2
272 [-]: GETTABLE  R1 R0 K91    ; R1 := R0["UIMaterial_Mods"]
273 [-]: NEWTABLE  R2 0 17      ; R2 := {}
274 [-]: GETGLOBAL R3 K131      ; R3 := modMaterialsNoDepthTestHorizontal
275 [-]: GETTABLE  R3 R3 K92    ; R3 := R3[1]
276 [-]: SETTABLE  R2 K93 R3    ; R2["Icon"] := R3
277 [-]: GETGLOBAL R3 K131      ; R3 := modMaterialsNoDepthTestHorizontal
278 [-]: GETTABLE  R3 R3 K96    ; R3 := R3[2]
279 [-]: SETTABLE  R2 K95 R3    ; R2["Background"] := R3
280 [-]: GETGLOBAL R3 K131      ; R3 := modMaterialsNoDepthTestHorizontal
281 [-]: GETTABLE  R3 R3 K98    ; R3 := R3[3]
282 [-]: SETTABLE  R2 K97 R3    ; R2["Energy"] := R3
283 [-]: GETGLOBAL R3 K131      ; R3 := modMaterialsNoDepthTestHorizontal
284 [-]: GETTABLE  R3 R3 K100   ; R3 := R3[4]
285 [-]: SETTABLE  R2 K99 R3    ; R2["BottomFrame"] := R3
286 [-]: GETGLOBAL R3 K131      ; R3 := modMaterialsNoDepthTestHorizontal
287 [-]: GETTABLE  R3 R3 K102   ; R3 := R3[5]
288 [-]: SETTABLE  R2 K101 R3   ; R2["TopFrame"] := R3
289 [-]: GETGLOBAL R3 K131      ; R3 := modMaterialsNoDepthTestHorizontal
290 [-]: GETTABLE  R3 R3 K104   ; R3 := R3[6]
291 [-]: SETTABLE  R2 K103 R3   ; R2["Content"] := R3
292 [-]: GETGLOBAL R3 K131      ; R3 := modMaterialsNoDepthTestHorizontal
293 [-]: GETTABLE  R3 R3 K106   ; R3 := R3[7]
294 [-]: SETTABLE  R2 K105 R3   ; R2["EmptySlot"] := R3
295 [-]: GETGLOBAL R3 K131      ; R3 := modMaterialsNoDepthTestHorizontal
296 [-]: GETTABLE  R3 R3 K108   ; R3 := R3[8]
297 [-]: SETTABLE  R2 K107 R3   ; R2["OmegaIcon"] := R3
298 [-]: GETGLOBAL R3 K131      ; R3 := modMaterialsNoDepthTestHorizontal
299 [-]: GETTABLE  R3 R3 K110   ; R3 := R3[9]
300 [-]: SETTABLE  R2 K109 R3   ; R2["Text"] := R3
301 [-]: GETGLOBAL R3 K131      ; R3 := modMaterialsNoDepthTestHorizontal
302 [-]: GETTABLE  R3 R3 K112   ; R3 := R3[10]
303 [-]: SETTABLE  R2 K111 R3   ; R2["PeculiarEnergy"] := R3
304 [-]: GETGLOBAL R3 K131      ; R3 := modMaterialsNoDepthTestHorizontal
305 [-]: GETTABLE  R3 R3 K114   ; R3 := R3[11]
306 [-]: SETTABLE  R2 K113 R3   ; R2["PeculiarBottomFrame"] := R3
307 [-]: GETGLOBAL R3 K131      ; R3 := modMaterialsNoDepthTestHorizontal
308 [-]: GETTABLE  R3 R3 K116   ; R3 := R3[12]
309 [-]: SETTABLE  R2 K115 R3   ; R2["PeculiarTopFrame"] := R3
310 [-]: GETGLOBAL R3 K131      ; R3 := modMaterialsNoDepthTestHorizontal
311 [-]: GETTABLE  R3 R3 K118   ; R3 := R3[13]
312 [-]: SETTABLE  R2 K117 R3   ; R2["RailjackBottomFrame"] := R3
313 [-]: GETGLOBAL R3 K131      ; R3 := modMaterialsNoDepthTestHorizontal
314 [-]: GETTABLE  R3 R3 K120   ; R3 := R3[14]
315 [-]: SETTABLE  R2 K119 R3   ; R2["RailjackTopFrame"] := R3
316 [-]: GETGLOBAL R3 K131      ; R3 := modMaterialsNoDepthTestHorizontal
317 [-]: GETTABLE  R3 R3 K122   ; R3 := R3[15]
318 [-]: SETTABLE  R2 K121 R3   ; R2["ImmortalIcon"] := R3
319 [-]: GETGLOBAL R3 K131      ; R3 := modMaterialsNoDepthTestHorizontal
320 [-]: GETTABLE  R3 R3 K124   ; R3 := R3[16]
321 [-]: SETTABLE  R2 K123 R3   ; R2["ImmortalBackground"] := R3
322 [-]: GETGLOBAL R3 K131      ; R3 := modMaterialsNoDepthTestHorizontal
323 [-]: GETTABLE  R3 R3 K126   ; R3 := R3[17]
324 [-]: SETTABLE  R2 K125 R3   ; R2["ImmortalBottomFrame"] := R3
325 [-]: GETGLOBAL R3 K131      ; R3 := modMaterialsNoDepthTestHorizontal
326 [-]: GETTABLE  R3 R3 K128   ; R3 := R3[18]
327 [-]: SETTABLE  R2 K127 R3   ; R2["ImmortalTopFrame"] := R3
328 [-]: SETTABLE  R1 K100 R2   ; R1[4] := R2
329 [-]: NEWTABLE  R1 0 0       ; R1 := {}
330 [-]: SETTABLE  R0 K132 R1   ; R0["UIMaterial_ModsSyndicateIcons"] := R1
331 [-]: GETTABLE  R1 R0 K132   ; R1 := R0["UIMaterial_ModsSyndicateIcons"]
332 [-]: NEWTABLE  R2 0 6       ; R2 := {}
333 [-]: GETGLOBAL R3 K134      ; R3 := modSyndicateMaterials
334 [-]: GETTABLE  R3 R3 K92    ; R3 := R3[1]
335 [-]: SETTABLE  R2 K133 R3   ; R2["ArbitersSyndicate"] := R3
336 [-]: GETGLOBAL R3 K134      ; R3 := modSyndicateMaterials
337 [-]: GETTABLE  R3 R3 K96    ; R3 := R3[2]
338 [-]: SETTABLE  R2 K135 R3   ; R2["SteelMeridianSyndicate"] := R3
339 [-]: GETGLOBAL R3 K134      ; R3 := modSyndicateMaterials
340 [-]: GETTABLE  R3 R3 K98    ; R3 := R3[3]
341 [-]: SETTABLE  R2 K136 R3   ; R2["PerrinSyndicate"] := R3
342 [-]: GETGLOBAL R3 K134      ; R3 := modSyndicateMaterials
343 [-]: GETTABLE  R3 R3 K100   ; R3 := R3[4]
344 [-]: SETTABLE  R2 K137 R3   ; R2["RedVeilSyndicate"] := R3
345 [-]: GETGLOBAL R3 K134      ; R3 := modSyndicateMaterials
346 [-]: GETTABLE  R3 R3 K102   ; R3 := R3[5]
347 [-]: SETTABLE  R2 K138 R3   ; R2["CephalonSudaSyndicate"] := R3
348 [-]: GETGLOBAL R3 K134      ; R3 := modSyndicateMaterials
349 [-]: GETTABLE  R3 R3 K104   ; R3 := R3[6]
350 [-]: SETTABLE  R2 K139 R3   ; R2["NewLokaSyndicate"] := R3
351 [-]: SETTABLE  R1 K92 R2    ; R1[1] := R2
352 [-]: GETTABLE  R1 R0 K132   ; R1 := R0["UIMaterial_ModsSyndicateIcons"]
353 [-]: NEWTABLE  R2 0 6       ; R2 := {}
354 [-]: GETGLOBAL R3 K140      ; R3 := modSyndicateMaterialsNoDepthTest
355 [-]: GETTABLE  R3 R3 K92    ; R3 := R3[1]
356 [-]: SETTABLE  R2 K133 R3   ; R2["ArbitersSyndicate"] := R3
357 [-]: GETGLOBAL R3 K140      ; R3 := modSyndicateMaterialsNoDepthTest
358 [-]: GETTABLE  R3 R3 K96    ; R3 := R3[2]
359 [-]: SETTABLE  R2 K135 R3   ; R2["SteelMeridianSyndicate"] := R3
360 [-]: GETGLOBAL R3 K140      ; R3 := modSyndicateMaterialsNoDepthTest
361 [-]: GETTABLE  R3 R3 K98    ; R3 := R3[3]
362 [-]: SETTABLE  R2 K136 R3   ; R2["PerrinSyndicate"] := R3
363 [-]: GETGLOBAL R3 K140      ; R3 := modSyndicateMaterialsNoDepthTest
364 [-]: GETTABLE  R3 R3 K100   ; R3 := R3[4]
365 [-]: SETTABLE  R2 K137 R3   ; R2["RedVeilSyndicate"] := R3
366 [-]: GETGLOBAL R3 K140      ; R3 := modSyndicateMaterialsNoDepthTest
367 [-]: GETTABLE  R3 R3 K102   ; R3 := R3[5]
368 [-]: SETTABLE  R2 K138 R3   ; R2["CephalonSudaSyndicate"] := R3
369 [-]: GETGLOBAL R3 K140      ; R3 := modSyndicateMaterialsNoDepthTest
370 [-]: GETTABLE  R3 R3 K104   ; R3 := R3[6]
371 [-]: SETTABLE  R2 K139 R3   ; R2["NewLokaSyndicate"] := R3
372 [-]: SETTABLE  R1 K96 R2    ; R1[2] := R2
373 [-]: GETTABLE  R1 R0 K132   ; R1 := R0["UIMaterial_ModsSyndicateIcons"]
374 [-]: NEWTABLE  R2 0 6       ; R2 := {}
375 [-]: GETGLOBAL R3 K141      ; R3 := modSyndicateMaterialsHorizontal
376 [-]: GETTABLE  R3 R3 K92    ; R3 := R3[1]
377 [-]: SETTABLE  R2 K133 R3   ; R2["ArbitersSyndicate"] := R3
378 [-]: GETGLOBAL R3 K141      ; R3 := modSyndicateMaterialsHorizontal
379 [-]: GETTABLE  R3 R3 K96    ; R3 := R3[2]
380 [-]: SETTABLE  R2 K135 R3   ; R2["SteelMeridianSyndicate"] := R3
381 [-]: GETGLOBAL R3 K141      ; R3 := modSyndicateMaterialsHorizontal
382 [-]: GETTABLE  R3 R3 K98    ; R3 := R3[3]
383 [-]: SETTABLE  R2 K136 R3   ; R2["PerrinSyndicate"] := R3
384 [-]: GETGLOBAL R3 K141      ; R3 := modSyndicateMaterialsHorizontal
385 [-]: GETTABLE  R3 R3 K100   ; R3 := R3[4]
386 [-]: SETTABLE  R2 K137 R3   ; R2["RedVeilSyndicate"] := R3
387 [-]: GETGLOBAL R3 K141      ; R3 := modSyndicateMaterialsHorizontal
388 [-]: GETTABLE  R3 R3 K102   ; R3 := R3[5]
389 [-]: SETTABLE  R2 K138 R3   ; R2["CephalonSudaSyndicate"] := R3
390 [-]: GETGLOBAL R3 K141      ; R3 := modSyndicateMaterialsHorizontal
391 [-]: GETTABLE  R3 R3 K104   ; R3 := R3[6]
392 [-]: SETTABLE  R2 K139 R3   ; R2["NewLokaSyndicate"] := R3
393 [-]: SETTABLE  R1 K98 R2    ; R1[3] := R2
394 [-]: GETTABLE  R1 R0 K132   ; R1 := R0["UIMaterial_ModsSyndicateIcons"]
395 [-]: NEWTABLE  R2 0 6       ; R2 := {}
396 [-]: GETGLOBAL R3 K142      ; R3 := modSyndicateMaterialsNoDepthTestHorizontal
397 [-]: GETTABLE  R3 R3 K92    ; R3 := R3[1]
398 [-]: SETTABLE  R2 K133 R3   ; R2["ArbitersSyndicate"] := R3
399 [-]: GETGLOBAL R3 K142      ; R3 := modSyndicateMaterialsNoDepthTestHorizontal
400 [-]: GETTABLE  R3 R3 K96    ; R3 := R3[2]
401 [-]: SETTABLE  R2 K135 R3   ; R2["SteelMeridianSyndicate"] := R3
402 [-]: GETGLOBAL R3 K142      ; R3 := modSyndicateMaterialsNoDepthTestHorizontal
403 [-]: GETTABLE  R3 R3 K98    ; R3 := R3[3]
404 [-]: SETTABLE  R2 K136 R3   ; R2["PerrinSyndicate"] := R3
405 [-]: GETGLOBAL R3 K142      ; R3 := modSyndicateMaterialsNoDepthTestHorizontal
406 [-]: GETTABLE  R3 R3 K100   ; R3 := R3[4]
407 [-]: SETTABLE  R2 K137 R3   ; R2["RedVeilSyndicate"] := R3
408 [-]: GETGLOBAL R3 K142      ; R3 := modSyndicateMaterialsNoDepthTestHorizontal
409 [-]: GETTABLE  R3 R3 K102   ; R3 := R3[5]
410 [-]: SETTABLE  R2 K138 R3   ; R2["CephalonSudaSyndicate"] := R3
411 [-]: GETGLOBAL R3 K142      ; R3 := modSyndicateMaterialsNoDepthTestHorizontal
412 [-]: GETTABLE  R3 R3 K104   ; R3 := R3[6]
413 [-]: SETTABLE  R2 K139 R3   ; R2["NewLokaSyndicate"] := R3
414 [-]: SETTABLE  R1 K100 R2   ; R1[4] := R2
415 [-]: NEWTABLE  R1 0 0       ; R1 := {}
416 [-]: SETTABLE  R0 K143 R1   ; R0["UIMaterial_FocusLens"] := R1
417 [-]: GETTABLE  R1 R0 K143   ; R1 := R0["UIMaterial_FocusLens"]
418 [-]: GETGLOBAL R2 K144      ; R2 := Lotus_Game
419 [-]: GETTABLE  R2 R2 K145   ; R2 := R2["AP_ATTACK"]
420 [-]: GETGLOBAL R3 K146      ; R3 := focusLensMaterials
421 [-]: GETTABLE  R3 R3 K92    ; R3 := R3[1]
422 [-]: SETTABLE  R1 R2 R3     ; R1[R2] := R3
423 [-]: GETTABLE  R1 R0 K143   ; R1 := R0["UIMaterial_FocusLens"]
424 [-]: GETGLOBAL R2 K144      ; R2 := Lotus_Game
425 [-]: GETTABLE  R2 R2 K147   ; R2 := R2["AP_DEFENSE"]
426 [-]: GETGLOBAL R3 K146      ; R3 := focusLensMaterials
427 [-]: GETTABLE  R3 R3 K96    ; R3 := R3[2]
428 [-]: SETTABLE  R1 R2 R3     ; R1[R2] := R3
429 [-]: GETTABLE  R1 R0 K143   ; R1 := R0["UIMaterial_FocusLens"]
430 [-]: GETGLOBAL R2 K144      ; R2 := Lotus_Game
431 [-]: GETTABLE  R2 R2 K148   ; R2 := R2["AP_TACTIC"]
432 [-]: GETGLOBAL R3 K146      ; R3 := focusLensMaterials
433 [-]: GETTABLE  R3 R3 K98    ; R3 := R3[3]
434 [-]: SETTABLE  R1 R2 R3     ; R1[R2] := R3
435 [-]: GETTABLE  R1 R0 K143   ; R1 := R0["UIMaterial_FocusLens"]
436 [-]: GETGLOBAL R2 K144      ; R2 := Lotus_Game
437 [-]: GETTABLE  R2 R2 K149   ; R2 := R2["AP_POWER"]
438 [-]: GETGLOBAL R3 K146      ; R3 := focusLensMaterials
439 [-]: GETTABLE  R3 R3 K100   ; R3 := R3[4]
440 [-]: SETTABLE  R1 R2 R3     ; R1[R2] := R3
441 [-]: GETTABLE  R1 R0 K143   ; R1 := R0["UIMaterial_FocusLens"]
442 [-]: GETGLOBAL R2 K144      ; R2 := Lotus_Game
443 [-]: GETTABLE  R2 R2 K150   ; R2 := R2["AP_WARD"]
444 [-]: GETGLOBAL R3 K146      ; R3 := focusLensMaterials
445 [-]: GETTABLE  R3 R3 K102   ; R3 := R3[5]
446 [-]: SETTABLE  R1 R2 R3     ; R1[R2] := R3
447 [-]: NEWTABLE  R1 0 0       ; R1 := {}
448 [-]: SETTABLE  R0 K151 R1   ; R0["UIMaterial_FocusLensStore"] := R1
449 [-]: GETTABLE  R1 R0 K151   ; R1 := R0["UIMaterial_FocusLensStore"]
450 [-]: GETGLOBAL R2 K144      ; R2 := Lotus_Game
451 [-]: GETTABLE  R2 R2 K145   ; R2 := R2["AP_ATTACK"]
452 [-]: GETGLOBAL R3 K152      ; R3 := focusLensStoreMaterials
453 [-]: GETTABLE  R3 R3 K92    ; R3 := R3[1]
454 [-]: SETTABLE  R1 R2 R3     ; R1[R2] := R3
455 [-]: GETTABLE  R1 R0 K151   ; R1 := R0["UIMaterial_FocusLensStore"]
456 [-]: GETGLOBAL R2 K144      ; R2 := Lotus_Game
457 [-]: GETTABLE  R2 R2 K147   ; R2 := R2["AP_DEFENSE"]
458 [-]: GETGLOBAL R3 K152      ; R3 := focusLensStoreMaterials
459 [-]: GETTABLE  R3 R3 K96    ; R3 := R3[2]
460 [-]: SETTABLE  R1 R2 R3     ; R1[R2] := R3
461 [-]: GETTABLE  R1 R0 K151   ; R1 := R0["UIMaterial_FocusLensStore"]
462 [-]: GETGLOBAL R2 K144      ; R2 := Lotus_Game
463 [-]: GETTABLE  R2 R2 K148   ; R2 := R2["AP_TACTIC"]
464 [-]: GETGLOBAL R3 K152      ; R3 := focusLensStoreMaterials
465 [-]: GETTABLE  R3 R3 K98    ; R3 := R3[3]
466 [-]: SETTABLE  R1 R2 R3     ; R1[R2] := R3
467 [-]: GETTABLE  R1 R0 K151   ; R1 := R0["UIMaterial_FocusLensStore"]
468 [-]: GETGLOBAL R2 K144      ; R2 := Lotus_Game
469 [-]: GETTABLE  R2 R2 K149   ; R2 := R2["AP_POWER"]
470 [-]: GETGLOBAL R3 K152      ; R3 := focusLensStoreMaterials
471 [-]: GETTABLE  R3 R3 K100   ; R3 := R3[4]
472 [-]: SETTABLE  R1 R2 R3     ; R1[R2] := R3
473 [-]: GETTABLE  R1 R0 K151   ; R1 := R0["UIMaterial_FocusLensStore"]
474 [-]: GETGLOBAL R2 K144      ; R2 := Lotus_Game
475 [-]: GETTABLE  R2 R2 K150   ; R2 := R2["AP_WARD"]
476 [-]: GETGLOBAL R3 K152      ; R3 := focusLensStoreMaterials
477 [-]: GETTABLE  R3 R3 K102   ; R3 := R3[5]
478 [-]: SETTABLE  R1 R2 R3     ; R1[R2] := R3
479 [-]: NEWTABLE  R1 0 0       ; R1 := {}
480 [-]: SETTABLE  R0 K153 R1   ; R0["UIMaterial_FocusLensStoreDepth"] := R1
481 [-]: GETTABLE  R1 R0 K153   ; R1 := R0["UIMaterial_FocusLensStoreDepth"]
482 [-]: GETGLOBAL R2 K144      ; R2 := Lotus_Game
483 [-]: GETTABLE  R2 R2 K145   ; R2 := R2["AP_ATTACK"]
484 [-]: GETGLOBAL R3 K154      ; R3 := focusLensStoreMaterialsWithDepth
485 [-]: GETTABLE  R3 R3 K92    ; R3 := R3[1]
486 [-]: SETTABLE  R1 R2 R3     ; R1[R2] := R3
487 [-]: GETTABLE  R1 R0 K153   ; R1 := R0["UIMaterial_FocusLensStoreDepth"]
488 [-]: GETGLOBAL R2 K144      ; R2 := Lotus_Game
489 [-]: GETTABLE  R2 R2 K147   ; R2 := R2["AP_DEFENSE"]
490 [-]: GETGLOBAL R3 K154      ; R3 := focusLensStoreMaterialsWithDepth
491 [-]: GETTABLE  R3 R3 K96    ; R3 := R3[2]
492 [-]: SETTABLE  R1 R2 R3     ; R1[R2] := R3
493 [-]: GETTABLE  R1 R0 K153   ; R1 := R0["UIMaterial_FocusLensStoreDepth"]
494 [-]: GETGLOBAL R2 K144      ; R2 := Lotus_Game
495 [-]: GETTABLE  R2 R2 K148   ; R2 := R2["AP_TACTIC"]
496 [-]: GETGLOBAL R3 K154      ; R3 := focusLensStoreMaterialsWithDepth
497 [-]: GETTABLE  R3 R3 K98    ; R3 := R3[3]
498 [-]: SETTABLE  R1 R2 R3     ; R1[R2] := R3
499 [-]: GETTABLE  R1 R0 K153   ; R1 := R0["UIMaterial_FocusLensStoreDepth"]
500 [-]: GETGLOBAL R2 K144      ; R2 := Lotus_Game
501 [-]: GETTABLE  R2 R2 K149   ; R2 := R2["AP_POWER"]
502 [-]: GETGLOBAL R3 K154      ; R3 := focusLensStoreMaterialsWithDepth
503 [-]: GETTABLE  R3 R3 K100   ; R3 := R3[4]
504 [-]: SETTABLE  R1 R2 R3     ; R1[R2] := R3
505 [-]: GETTABLE  R1 R0 K153   ; R1 := R0["UIMaterial_FocusLensStoreDepth"]
506 [-]: GETGLOBAL R2 K144      ; R2 := Lotus_Game
507 [-]: GETTABLE  R2 R2 K150   ; R2 := R2["AP_WARD"]
508 [-]: GETGLOBAL R3 K154      ; R3 := focusLensStoreMaterialsWithDepth
509 [-]: GETTABLE  R3 R3 K102   ; R3 := R3[5]
510 [-]: SETTABLE  R1 R2 R3     ; R1[R2] := R3
511 [-]: GETGLOBAL R1 K156      ; R1 := cosmeticEnhancersMaterials
512 [-]: SETTABLE  R0 K155 R1   ; R0["UIMaterial_CosmeticEnhancers"] := R1
513 [-]: GETGLOBAL R1 K158      ; R1 := cosmeticEnhancersStoreMaterials
514 [-]: SETTABLE  R0 K157 R1   ; R0["UIMaterial_CosmeticEnhancersStore"] := R1
515 [-]: GETGLOBAL R1 K160      ; R1 := cosmeticEnhancersStoreMaterialsWithDepth
516 [-]: SETTABLE  R0 K159 R1   ; R0["UIMaterial_CosmeticEnhancersStoreDepth"] := R1
517 [-]: GETGLOBAL R1 K162      ; R1 := cosmeticEnhancersStoreMaterialsHorizontal
518 [-]: SETTABLE  R0 K161 R1   ; R0["UIMaterial_CosmeticEnhancersStoreHorizontal"] := R1
519 [-]: GETGLOBAL R1 K164      ; R1 := cosmeticEnhancersStoreMaterialsWithDepthHorizontal
520 [-]: SETTABLE  R0 K163 R1   ; R0["UIMaterial_CosmeticEnhancersStoreDepthHorizontal"] := R1
521 [-]: GETGLOBAL R1 K166      ; R1 := railjackModMaterials
522 [-]: SETTABLE  R0 K165 R1   ; R0["UIMaterial_RailjackMod"] := R1
523 [-]: GETGLOBAL R1 K168      ; R1 := railjackModStoreMaterials
524 [-]: SETTABLE  R0 K167 R1   ; R0["UIMaterial_RailjackModStore"] := R1
525 [-]: GETGLOBAL R1 K170      ; R1 := railjackModStoreMaterialsWithDepth
526 [-]: SETTABLE  R0 K169 R1   ; R0["UIMaterial_RailjackModStoreDepth"] := R1
527 [-]: GETGLOBAL R1 K172      ; R1 := spaceEnemyMarkerMaterials
528 [-]: SETTABLE  R0 K171 R1   ; R0["UIMaterial_SpaceMarker"] := R1
529 [-]: GETGLOBAL R1 K174      ; R1 := spaceEnemyCrewshipMarkerMaterials
530 [-]: SETTABLE  R0 K173 R1   ; R0["UIMaterial_SpaceMarkerCrewShip"] := R1
531 [-]: GETGLOBAL R1 K176      ; R1 := railjackModStoreMaterialsHorizontal
532 [-]: SETTABLE  R0 K175 R1   ; R0["UIMaterial_RailjackModStoreHorizontal"] := R1
533 [-]: GETGLOBAL R1 K178      ; R1 := railjackModStoreMaterialsWithDepthHorizontal
534 [-]: SETTABLE  R0 K177 R1   ; R0["UIMaterial_RailjackModStoreDepthHorizontal"] := R1
535 [-]: GETGLOBAL R1 K180      ; R1 := squareStoreItemMaterial
536 [-]: SETTABLE  R0 K179 R1   ; R0["UIMaterial_SquareStoreItem"] := R1
537 [-]: GETGLOBAL R1 K182      ; R1 := squareStoreItemVisRangeMaterial
538 [-]: SETTABLE  R0 K181 R1   ; R0["UIMaterial_SquareStoreItemVisRange"] := R1
539 [-]: GETGLOBAL R1 K184      ; R1 := squareStoreItemShadowMaterial
540 [-]: SETTABLE  R0 K183 R1   ; R0["UIMaterial_SquareStoreItemShadow"] := R1
541 [-]: GETGLOBAL R1 K186      ; R1 := squareStoreItemShadowVisRangeMaterial
542 [-]: SETTABLE  R0 K185 R1   ; R0["UIMaterial_SquareStoreItemShadowVisRange"] := R1
543 [-]: GETGLOBAL R1 K188      ; R1 := emojiColorMaterials
544 [-]: SETTABLE  R0 K187 R1   ; R0["UIMaterial_EmojiColors"] := R1
545 [-]: GETGLOBAL R1 K190      ; R1 := masteryEmblemMaterials
546 [-]: SETTABLE  R0 K189 R1   ; R0["UIMaterial_MasteryEmblems"] := R1
547 [-]: GETGLOBAL R1 K192      ; R1 := salvageMaterials
548 [-]: SETTABLE  R0 K191 R1   ; R0["UIMaterial_SalvageMaterials"] := R1
549 [-]: GETGLOBAL R1 K194      ; R1 := creditsIconTexture
550 [-]: SETTABLE  R0 K193 R1   ; R0["UITexture_CreditsIcon"] := R1
551 [-]: GETGLOBAL R1 K196      ; R1 := creditsStoreItemIconTexture
552 [-]: SETTABLE  R0 K195 R1   ; R0["UITexture_CreditsStoreItemIcon"] := R1
553 [-]: GETGLOBAL R1 K198      ; R1 := platinumIconTexture
554 [-]: SETTABLE  R0 K197 R1   ; R0["UITexture_PlatinumIcon"] := R1
555 [-]: GETGLOBAL R1 K200      ; R1 := profilePlaceHolderTexture
556 [-]: SETTABLE  R0 K199 R1   ; R0["UITexture_ProfilePlaceHolder"] := R1
557 [-]: GETGLOBAL R1 K202      ; R1 := blueprintTexture
558 [-]: SETTABLE  R0 K201 R1   ; R0["UITexture_Blueprint"] := R1
559 [-]: GETGLOBAL R1 K204      ; R1 := reusableBlueprintTexture
560 [-]: SETTABLE  R0 K203 R1   ; R0["UITexture_ReusableBlueprint"] := R1
561 [-]: GETGLOBAL R1 K206      ; R1 := searchIcon
562 [-]: SETTABLE  R0 K205 R1   ; R0["UITexture_Search"] := R1
563 [-]: GETGLOBAL R1 K208      ; R1 := clearSearchIcon
564 [-]: SETTABLE  R0 K207 R1   ; R0["UITexture_ClearSearch"] := R1
565 [-]: GETGLOBAL R1 K210      ; R1 := polarityTextures
566 [-]: SETTABLE  R0 K209 R1   ; R0["UITexture_Polarity"] := R1
567 [-]: GETGLOBAL R1 K212      ; R1 := wishlistIconTexture
568 [-]: SETTABLE  R0 K211 R1   ; R0["UITexture_Wishlist"] := R1
569 [-]: GETGLOBAL R1 K214      ; R1 := bundleIconTexture
570 [-]: SETTABLE  R0 K213 R1   ; R0["UITexture_Bundle"] := R1
571 [-]: GETGLOBAL R1 K216      ; R1 := masteryTextures
572 [-]: SETTABLE  R0 K215 R1   ; R0["UITexture_Mastery"] := R1
573 [-]: GETGLOBAL R1 K218      ; R1 := newMasteryInnerTextures
574 [-]: SETTABLE  R0 K217 R1   ; R0["UITexture_NewMasteryInner"] := R1
575 [-]: GETGLOBAL R1 K220      ; R1 := newMasteryTextures
576 [-]: SETTABLE  R0 K219 R1   ; R0["UITexture_NewMastery"] := R1
577 [-]: GETGLOBAL R1 K222      ; R1 := clanClassTextures
578 [-]: SETTABLE  R0 K221 R1   ; R0["UITexture_ClanClass"] := R1
579 [-]: GETGLOBAL R1 K224      ; R1 := emptySlotTexture
580 [-]: SETTABLE  R0 K223 R1   ; R0["UITexture_EmptySlot"] := R1
581 [-]: GETGLOBAL R1 K226      ; R1 := labelIconTextures
582 [-]: SETTABLE  R0 K225 R1   ; R0["UITexture_LabelIcons"] := R1
583 [-]: GETGLOBAL R1 K228      ; R1 := circleGradientBackerTexture
584 [-]: SETTABLE  R0 K227 R1   ; R0["UITexture_CircleGradientBacker"] := R1
585 [-]: GETGLOBAL R1 K230      ; R1 := companionIconTextures
586 [-]: SETTABLE  R0 K229 R1   ; R0["UITexture_CompanionIcons"] := R1
587 [-]: GETGLOBAL R1 K232      ; R1 := genderIconTextures
588 [-]: SETTABLE  R0 K231 R1   ; R0["UITexture_GenderIcons"] := R1
589 [-]: GETGLOBAL R1 K234      ; R1 := salvageTexture
590 [-]: SETTABLE  R0 K233 R1   ; R0["UITexture_Salvage"] := R1
591 [-]: SETTABLE  R0 K235 K236 ; R0["UIColor_Blue"] := 1405683
592 [-]: SETTABLE  R0 K237 K238 ; R0["UIColor_LightBlue"] := 12769497
593 [-]: SETTABLE  R0 K239 K240 ; R0["UIColor_MediumBlue"] := 8100006
594 [-]: SETTABLE  R0 K241 K242 ; R0["UIColor_DarkBlue"] := 4546669
595 [-]: SETTABLE  R0 K243 K244 ; R0["UIColor_MediumGrey"] := 8421504
596 [-]: SETTABLE  R0 K245 K246 ; R0["UIColor_DarkGrey"] := 2368548
597 [-]: SETTABLE  R0 K247 K248 ; R0["UIColor_Yellow"] := 15258973
598 [-]: SETTABLE  R0 K249 K250 ; R0["UIColor_Orange"] := 13466625
599 [-]: SETTABLE  R0 K251 K252 ; R0["UIColor_Gold"] := 16763904
600 [-]: SETTABLE  R0 K253 K254 ; R0["UIColor_Health"] := 13379881
601 [-]: LOADK     R1 K256      ; R1 := 54783
602 [-]: SETTABLE  R0 K255 R1   ; R0["UIColor_Shield"] := R1
603 [-]: LOADK     R1 K257      ; R1 := "UIColor_Overshield"
604 [-]: LOADK     R2 K258      ; R2 := 11731199
605 [-]: SETTABLE  R0 R1 R2     ; R0[R1] := R2
606 [-]: LOADK     R1 K259      ; R1 := "UIColor_Stamina"
607 [-]: LOADK     R2 K260      ; R2 := 4502359
608 [-]: SETTABLE  R0 R1 R2     ; R0[R1] := R2
609 [-]: LOADK     R1 K261      ; R1 := "UIColor_Armor"
610 [-]: LOADK     R2 K262      ; R2 := 14591541
611 [-]: SETTABLE  R0 R1 R2     ; R0[R1] := R2
612 [-]: LOADK     R1 K263      ; R1 := "UIColor_Red"
613 [-]: LOADK     R2 K264      ; R2 := 13108230
614 [-]: SETTABLE  R0 R1 R2     ; R0[R1] := R2
615 [-]: LOADK     R1 K265      ; R1 := "UIColor_Green"
616 [-]: LOADK     R2 K266      ; R2 := 9298982
617 [-]: SETTABLE  R0 R1 R2     ; R0[R1] := R2
618 [-]: LOADK     R1 K267      ; R1 := "UIColor_LightGreen"
619 [-]: LOADK     R2 K268      ; R2 := 12118144
620 [-]: SETTABLE  R0 R1 R2     ; R0[R1] := R2
621 [-]: LOADK     R1 K269      ; R1 := "UIColor_White"
622 [-]: LOADK     R2 K270      ; R2 := 15724527
623 [-]: SETTABLE  R0 R1 R2     ; R0[R1] := R2
624 [-]: LOADK     R1 K271      ; R1 := "UIColor_Black"
625 [-]: LOADK     R2 K272      ; R2 := 0
626 [-]: SETTABLE  R0 R1 R2     ; R0[R1] := R2
627 [-]: LOADK     R1 K273      ; R1 := "UIColor_PositiveReputation"
628 [-]: LOADK     R2 K274      ; R2 := 5030911
629 [-]: SETTABLE  R0 R1 R2     ; R0[R1] := R2
630 [-]: LOADK     R1 K275      ; R1 := "UIColor_NegativeReputation"
631 [-]: LOADK     R2 K276      ; R2 := 16731212
632 [-]: SETTABLE  R0 R1 R2     ; R0[R1] := R2
633 [-]: LOADK     R1 K277      ; R1 := "UIColor_OpposedReputation"
634 [-]: LOADK     R2 K278      ; R2 := 15647744
635 [-]: SETTABLE  R0 R1 R2     ; R0[R1] := R2
636 [-]: LOADK     R1 K279      ; R1 := "UIColor_PvpTeamOne"
637 [-]: LOADK     R2 K280      ; R2 := 15044409
638 [-]: SETTABLE  R0 R1 R2     ; R0[R1] := R2
639 [-]: LOADK     R1 K281      ; R1 := "UIColor_PvpTeamTwo"
640 [-]: LOADK     R2 K282      ; R2 := 3000544
641 [-]: SETTABLE  R0 R1 R2     ; R0[R1] := R2
642 [-]: LOADK     R1 K283      ; R1 := "UIColor_PvpKill"
643 [-]: LOADK     R2 K284      ; R2 := 15945236
644 [-]: SETTABLE  R0 R1 R2     ; R0[R1] := R2
645 [-]: LOADK     R1 K285      ; R1 := "UIColor_Hyperlink"
646 [-]: LOADK     R2 K286      ; R2 := 3394815
647 [-]: SETTABLE  R0 R1 R2     ; R0[R1] := R2
648 [-]: LOADK     R1 K287      ; R1 := "UIColor_UnlimitedUseBP"
649 [-]: LOADK     R2 K288      ; R2 := 15714870
650 [-]: SETTABLE  R0 R1 R2     ; R0[R1] := R2
651 [-]: LOADK     R1 K289      ; R1 := "UIColor_RGB_White"
652 [-]: GETUPVAL  R2 U0        ; R2 := U0
653 [-]: LOADK     R3 K290      ; R3 := "0xBBAE08CF"
654 [-]: GETTABLE  R2 R2 R3     ; R2 := R2[R3]
655 [-]: LOADK     R3 K269      ; R3 := "UIColor_White"
656 [-]: GETTABLE  R3 R0 R3     ; R3 := R0[R3]
657 [-]: CALL      R2 2 2       ; R2 := R2(R3)
658 [-]: SETTABLE  R0 R1 R2     ; R0[R1] := R2
659 [-]: LOADK     R1 K291      ; R1 := "UIColorObject_White"
660 [-]: GETUPVAL  R2 U0        ; R2 := U0
661 [-]: LOADK     R3 K292      ; R3 := "0x97B78441"
662 [-]: GETTABLE  R2 R2 R3     ; R2 := R2[R3]
663 [-]: LOADK     R3 K269      ; R3 := "UIColor_White"
664 [-]: GETTABLE  R3 R0 R3     ; R3 := R0[R3]
665 [-]: CALL      R2 2 2       ; R2 := R2(R3)
666 [-]: SETTABLE  R0 R1 R2     ; R0[R1] := R2
667 [-]: LOADK     R1 K293      ; R1 := "UIColorObject_Black"
668 [-]: GETUPVAL  R2 U0        ; R2 := U0
669 [-]: LOADK     R3 K292      ; R3 := "0x97B78441"
670 [-]: GETTABLE  R2 R2 R3     ; R2 := R2[R3]
671 [-]: LOADK     R3 K271      ; R3 := "UIColor_Black"
672 [-]: GETTABLE  R3 R0 R3     ; R3 := R0[R3]
673 [-]: CALL      R2 2 2       ; R2 := R2(R3)
674 [-]: SETTABLE  R0 R1 R2     ; R0[R1] := R2
675 [-]: LOADK     R1 K294      ; R1 := "UIColorObject_Yellow"
676 [-]: GETUPVAL  R2 U0        ; R2 := U0
677 [-]: LOADK     R3 K292      ; R3 := "0x97B78441"
678 [-]: GETTABLE  R2 R2 R3     ; R2 := R2[R3]
679 [-]: GETTABLE  R3 R0 K247   ; R3 := R0["UIColor_Yellow"]
680 [-]: CALL      R2 2 2       ; R2 := R2(R3)
681 [-]: SETTABLE  R0 R1 R2     ; R0[R1] := R2
682 [-]: LOADK     R1 K295      ; R1 := "UIColorObject_DarkBlue"
683 [-]: GETUPVAL  R2 U0        ; R2 := U0
684 [-]: LOADK     R3 K292      ; R3 := "0x97B78441"
685 [-]: GETTABLE  R2 R2 R3     ; R2 := R2[R3]
686 [-]: GETTABLE  R3 R0 K241   ; R3 := R0["UIColor_DarkBlue"]
687 [-]: CALL      R2 2 2       ; R2 := R2(R3)
688 [-]: SETTABLE  R0 R1 R2     ; R0[R1] := R2
689 [-]: NEWTABLE  R1 28 0      ; R1 := {}
690 [-]: LOADK     R2 K296      ; R2 := "All"
691 [-]: LOADK     R3 K297      ; R3 := "Installed"
692 [-]: LOADK     R4 K298      ; R4 := "Warframe"
693 [-]: LOADK     R5 K299      ; R5 := "Rifle"
694 [-]: LOADK     R6 K300      ; R6 := "HandGun"
695 [-]: LOADK     R7 K301      ; R7 := "Melee"
696 [-]: LOADK     R8 K302      ; R8 := "Stance"
697 [-]: LOADK     R9 K303      ; R9 := "Sentinel"
698 [-]: LOADK     R10 K304     ; R10 := "Kubrow"
699 [-]: LOADK     R11 K305     ; R11 := "Aura"
700 [-]: LOADK     R12 K306     ; R12 := "Misc"
701 [-]: LOADK     R13 K307     ; R13 := "Cores"
702 [-]: LOADK     R14 K308     ; R14 := "Build"
703 [-]: LOADK     R15 K309     ; R15 := "Materials"
704 [-]: LOADK     R16 K310     ; R16 := "Skins"
705 [-]: LOADK     R17 K311     ; R17 := "Corpus"
706 [-]: LOADK     R18 K312     ; R18 := "Grineer"
707 [-]: LOADK     R19 K313     ; R19 := "Infested"
708 [-]: LOADK     R20 K314     ; R20 := "Wild"
709 [-]: LOADK     R21 K315     ; R21 := "Orokin"
710 [-]: LOADK     R22 K316     ; R22 := "Sentient"
711 [-]: LOADK     R23 K317     ; R23 := "Stalker"
712 [-]: LOADK     R24 K318     ; R24 := "Duplicates"
713 [-]: LOADK     R25 K319     ; R25 := "Archwing"
714 [-]: LOADK     R26 K320     ; R26 := "ArchwingPrimary"
715 [-]: LOADK     R27 K321     ; R27 := "ArchwingSecondary"
716 [-]: LOADK     R28 K322     ; R28 := "Mods"
717 [-]: LOADK     R29 K323     ; R29 := "Sigils"
718 [-]: LOADK     R30 K324     ; R30 := "Augment"
719 [-]: LOADK     R31 K325     ; R31 := "Utility"
720 [-]: LOADK     R32 K326     ; R32 := "Omega"
721 [-]: LOADK     R33 K327     ; R33 := "Companions"
722 [-]: LOADK     R34 K328     ; R34 := "Amps"
723 [-]: LOADK     R35 K329     ; R35 := "Cephalon"
724 [-]: LOADK     R36 K330     ; R36 := "Cetus"
725 [-]: LOADK     R37 K331     ; R37 := "Glass"
726 [-]: LOADK     R38 K332     ; R38 := "Ghouls"
727 [-]: LOADK     R39 K333     ; R39 := "Solaris"
728 [-]: LOADK     R40 K334     ; R40 := "FusionTreasures"
729 [-]: LOADK     R41 K335     ; R41 := "Displays"
730 [-]: LOADK     R42 K336     ; R42 := "Noggles"
731 [-]: LOADK     R43 K337     ; R43 := "Vehicles"
732 [-]: LOADK     R44 K338     ; R44 := "Recipes"
733 [-]: LOADK     R45 K339     ; R45 := "Imprints"
734 [-]: LOADK     R46 K340     ; R46 := "Immortal"
735 [-]: LOADK     R47 K341     ; R47 := "DataKnife"
736 [-]: SETLIST   R1 46 1      ; R1[(1-1)*FPF+i] := R(1+i), 1 <= i <= 46
737 [-]: GETGLOBAL R2 K342      ; R2 := 0x63B09107
738 [-]: MOVE      R3 R1        ; R3 := R1
739 [-]: CALL      R2 2 4       ; R2,R3,R4 := R2(R3)
740 [-]: JMP       748          ; PC := 748
741 [-]: LOADK     R7 K343      ; R7 := "UICategoryIcon_"
742 [-]: MOVE      R8 R6        ; R8 := R6
743 [-]: LOADK     R9 K344      ; R9 := "On"
744 [-]: CONCAT    R7 R7 R9     ; R7 := R7 .. R8 .. R9
745 [-]: GETGLOBAL R8 K345      ; R8 := categoryIconsOnTexture
746 [-]: GETTABLE  R8 R8 R5     ; R8 := R8[R5]
747 [-]: SETTABLE  R0 R7 R8     ; R0[R7] := R8
748 [-]: TFORLOOP  R2 2         ; R5,R6 :=  R2(R3,R4); if R5 ~= nil then begin PC = 741; R4 := R5 end
749 [-]: JMP       741          ; PC := 741
750 [-]: LOADK     R7 K346      ; R7 := "UITexture_Portrait"
751 [-]: GETGLOBAL R8 K347      ; R8 := portraitMaterial
752 [-]: SETTABLE  R0 R7 R8     ; R0[R7] := R8
753 [-]: LOADK     R7 K348      ; R7 := "UITexture_Alert"
754 [-]: GETGLOBAL R8 K349      ; R8 := alertTexture
755 [-]: SETTABLE  R0 R7 R8     ; R0[R7] := R8
756 [-]: LOADK     R7 K350      ; R7 := "UITexture_Story"
757 [-]: GETGLOBAL R8 K351      ; R8 := storyTexture
758 [-]: SETTABLE  R0 R7 R8     ; R0[R7] := R8
759 [-]: LOADK     R7 K352      ; R7 := "UITexture_Skull"
760 [-]: GETGLOBAL R8 K353      ; R8 := skullTexture
761 [-]: SETTABLE  R0 R7 R8     ; R0[R7] := R8
762 [-]: LOADK     R7 K354      ; R7 := "UITexture_SkullLarge"
763 [-]: GETGLOBAL R8 K355      ; R8 := skullTextureLarge
764 [-]: SETTABLE  R0 R7 R8     ; R0[R7] := R8
765 [-]: LOADK     R7 K356      ; R7 := "UITexture_VoidTear"
766 [-]: GETGLOBAL R8 K357      ; R8 := voidTearTexture
767 [-]: SETTABLE  R0 R7 R8     ; R0[R7] := R8
768 [-]: LOADK     R7 K358      ; R7 := "UITexture_Locked"
769 [-]: GETGLOBAL R8 K359      ; R8 := lockedTexture
770 [-]: SETTABLE  R0 R7 R8     ; R0[R7] := R8
771 [-]: LOADK     R7 K360      ; R7 := "UITexture_Event"
772 [-]: GETGLOBAL R8 K361      ; R8 := eventTexture
773 [-]: SETTABLE  R0 R7 R8     ; R0[R7] := R8
774 [-]: LOADK     R7 K362      ; R7 := "UITexture_Pvp"
775 [-]: GETGLOBAL R8 K363      ; R8 := pvpTexture
776 [-]: SETTABLE  R0 R7 R8     ; R0[R7] := R8
777 [-]: LOADK     R7 K364      ; R7 := "UITexture_PvpChallenges"
778 [-]: GETGLOBAL R8 K365      ; R8 := pvpChallengesTexture
779 [-]: SETTABLE  R0 R7 R8     ; R0[R7] := R8
780 [-]: LOADK     R7 K366      ; R7 := "UITexture_PvpWeeklyChallenges"
781 [-]: GETGLOBAL R8 K367      ; R8 := pvpWeeklyChallengesTexture
782 [-]: SETTABLE  R0 R7 R8     ; R0[R7] := R8
783 [-]: LOADK     R7 K368      ; R7 := "UITexture_Hub"
784 [-]: GETGLOBAL R8 K369      ; R8 := hubTexture
785 [-]: SETTABLE  R0 R7 R8     ; R0[R7] := R8
786 [-]: LOADK     R7 K370      ; R7 := "UITexture_BossNode"
787 [-]: GETGLOBAL R8 K371      ; R8 := bossNodeTexture
788 [-]: SETTABLE  R0 R7 R8     ; R0[R7] := R8
789 [-]: LOADK     R7 K372      ; R7 := "UITexture_Invasion"
790 [-]: GETGLOBAL R8 K373      ; R8 := invasionTexture
791 [-]: SETTABLE  R0 R7 R8     ; R0[R7] := R8
792 [-]: LOADK     R7 K374      ; R7 := "UITexture_Syndicate"
793 [-]: GETGLOBAL R8 K375      ; R8 := syndicateTexture
794 [-]: SETTABLE  R0 R7 R8     ; R0[R7] := R8
795 [-]: LOADK     R7 K376      ; R7 := "UITexture_Darvo"
796 [-]: GETGLOBAL R8 K377      ; R8 := darvoTexture
797 [-]: SETTABLE  R0 R7 R8     ; R0[R7] := R8
798 [-]: LOADK     R7 K378      ; R7 := "UITexture_DefaultClan"
799 [-]: GETGLOBAL R8 K379      ; R8 := defaultClanIcon
800 [-]: SETTABLE  R0 R7 R8     ; R0[R7] := R8
801 [-]: LOADK     R7 K380      ; R7 := "UITexture_DefaultAlliance"
802 [-]: GETGLOBAL R8 K381      ; R8 := defaultAllianceIcon
803 [-]: SETTABLE  R0 R7 R8     ; R0[R7] := R8
804 [-]: LOADK     R7 K382      ; R7 := "UITexture_BadlandConflict"
805 [-]: GETGLOBAL R8 K383      ; R8 := badlandConflictIcon
806 [-]: SETTABLE  R0 R7 R8     ; R0[R7] := R8
807 [-]: LOADK     R7 K384      ; R7 := "UITexture_Archwing"
808 [-]: GETGLOBAL R8 K385      ; R8 := archwingIcon
809 [-]: SETTABLE  R0 R7 R8     ; R0[R7] := R8
810 [-]: LOADK     R7 K386      ; R7 := "UITexture_SortieEasy"
811 [-]: GETGLOBAL R8 K387      ; R8 := sortieEasyIcon
812 [-]: SETTABLE  R0 R7 R8     ; R0[R7] := R8
813 [-]: LOADK     R7 K388      ; R7 := "UITexture_SortieHard"
814 [-]: GETGLOBAL R8 K389      ; R8 := sortieHardIcon
815 [-]: SETTABLE  R0 R7 R8     ; R0[R7] := R8
816 [-]: LOADK     R7 K390      ; R7 := "UITexture_SortieFinal"
817 [-]: GETGLOBAL R8 K391      ; R8 := sortieFinalIcon
818 [-]: SETTABLE  R0 R7 R8     ; R0[R7] := R8
819 [-]: LOADK     R7 K392      ; R7 := "UITexture_SortieGeneric"
820 [-]: GETGLOBAL R8 K393      ; R8 := sortieGenericIcon
821 [-]: SETTABLE  R0 R7 R8     ; R0[R7] := R8
822 [-]: LOADK     R7 K394      ; R7 := "UITexture_Acolyte"
823 [-]: GETGLOBAL R8 K395      ; R8 := acolyteTexture
824 [-]: SETTABLE  R0 R7 R8     ; R0[R7] := R8
825 [-]: LOADK     R7 K396      ; R7 := "UITexture_Arena"
826 [-]: GETGLOBAL R8 K397      ; R8 := arenaIcon
827 [-]: SETTABLE  R0 R7 R8     ; R0[R7] := R8
828 [-]: LOADK     R7 K398      ; R7 := "UITexture_EliteAlert"
829 [-]: GETGLOBAL R8 K399      ; R8 := eliteAlertIcon
830 [-]: SETTABLE  R0 R7 R8     ; R0[R7] := R8
831 [-]: LOADK     R7 K400      ; R7 := "UITextures_FactionInvasion"
832 [-]: GETGLOBAL R8 K401      ; R8 := factionTexturesInvasion
833 [-]: SETTABLE  R0 R7 R8     ; R0[R7] := R8
834 [-]: LOADK     R7 K402      ; R7 := "UITextures_CorpusShip"
835 [-]: GETGLOBAL R8 K403      ; R8 := corpusShipTextures
836 [-]: SETTABLE  R0 R7 R8     ; R0[R7] := R8
837 [-]: LOADK     R7 K404      ; R7 := "UITextures_GrineerAsteroid"
838 [-]: GETGLOBAL R8 K405      ; R8 := grineerAsteroidTextures
839 [-]: SETTABLE  R0 R7 R8     ; R0[R7] := R8
840 [-]: LOADK     R7 K406      ; R7 := "UITextures_GrineerShip"
841 [-]: GETGLOBAL R8 K407      ; R8 := grineerShipTextures
842 [-]: SETTABLE  R0 R7 R8     ; R0[R7] := R8
843 [-]: LOADK     R7 K408      ; R7 := "UITextures_Outpost"
844 [-]: GETGLOBAL R8 K409      ; R8 := outpostTextures
845 [-]: SETTABLE  R0 R7 R8     ; R0[R7] := R8
846 [-]: LOADK     R7 K410      ; R7 := "UITextures_Settlement"
847 [-]: GETGLOBAL R8 K411      ; R8 := settlementTextures
848 [-]: SETTABLE  R0 R7 R8     ; R0[R7] := R8
849 [-]: LOADK     R7 K412      ; R7 := "UITextures_GasCity"
850 [-]: GETGLOBAL R8 K413      ; R8 := gasCityTextures
851 [-]: SETTABLE  R0 R7 R8     ; R0[R7] := R8
852 [-]: LOADK     R7 K414      ; R7 := "UITextures_GrineerForest"
853 [-]: GETGLOBAL R8 K415      ; R8 := grineerForestTextures
854 [-]: SETTABLE  R0 R7 R8     ; R0[R7] := R8
855 [-]: LOADK     R7 K416      ; R7 := "UITextures_GrineerShipyard"
856 [-]: GETGLOBAL R8 K417      ; R8 := grineerShipyardTextures
857 [-]: SETTABLE  R0 R7 R8     ; R0[R7] := R8
858 [-]: LOADK     R7 K418      ; R7 := "UITextures_InfestedCorpusShip"
859 [-]: GETGLOBAL R8 K419      ; R8 := infestedCorpusTextures
860 [-]: SETTABLE  R0 R7 R8     ; R0[R7] := R8
861 [-]: LOADK     R7 K420      ; R7 := "UITextures_GameModeTextures"
862 [-]: GETGLOBAL R8 K421      ; R8 := gameModeTextures
863 [-]: SETTABLE  R0 R7 R8     ; R0[R7] := R8
864 [-]: LOADK     R7 K422      ; R7 := "UITextures_IcePlanet"
865 [-]: GETGLOBAL R8 K423      ; R8 := icePlanetTextures
866 [-]: SETTABLE  R0 R7 R8     ; R0[R7] := R8
867 [-]: LOADK     R7 K424      ; R7 := "UITextures_ArchwingFreeFlight"
868 [-]: GETGLOBAL R8 K425      ; R8 := archwingFreeFlightTexture
869 [-]: SETTABLE  R0 R7 R8     ; R0[R7] := R8
870 [-]: LOADK     R7 K426      ; R7 := "UITextures_ArchwingTrench"
871 [-]: GETGLOBAL R8 K427      ; R8 := archwingTrenchTexture
872 [-]: SETTABLE  R0 R7 R8     ; R0[R7] := R8
873 [-]: LOADK     R7 K428      ; R7 := "UITextures_GrineerOcean"
874 [-]: GETGLOBAL R8 K429      ; R8 := grineerOceanTexture
875 [-]: SETTABLE  R0 R7 R8     ; R0[R7] := R8
876 [-]: LOADK     R7 K430      ; R7 := "UITextures_OrokinMoon"
877 [-]: GETGLOBAL R8 K431      ; R8 := orokinMoonTexture
878 [-]: SETTABLE  R0 R7 R8     ; R0[R7] := R8
879 [-]: LOADK     R7 K432      ; R7 := "UITextures_OrokinTower"
880 [-]: GETGLOBAL R8 K433      ; R8 := orokinTowerTexture
881 [-]: SETTABLE  R0 R7 R8     ; R0[R7] := R8
882 [-]: LOADK     R7 K434      ; R7 := "UITextures_pvpGameModesTextures"
883 [-]: GETGLOBAL R8 K435      ; R8 := pvpGameModesTextures
884 [-]: SETTABLE  R0 R7 R8     ; R0[R7] := R8
885 [-]: LOADK     R7 K436      ; R7 := "UITextures_ArenaLocation"
886 [-]: GETGLOBAL R8 K437      ; R8 := arenaLocationTexture
887 [-]: SETTABLE  R0 R7 R8     ; R0[R7] := R8
888 [-]: LOADK     R7 K438      ; R7 := "UITextures_GhostTower"
889 [-]: GETGLOBAL R8 K439      ; R8 := ghostTowerTexture
890 [-]: SETTABLE  R0 R7 R8     ; R0[R7] := R8
891 [-]: LOADK     R7 K440      ; R7 := "UITextures_GhostTowerVariant"
892 [-]: GETGLOBAL R8 K441      ; R8 := ghostTowerVariantTexture
893 [-]: SETTABLE  R0 R7 R8     ; R0[R7] := R8
894 [-]: LOADK     R7 K442      ; R7 := "UITextures_GrineerFortress"
895 [-]: GETGLOBAL R8 K443      ; R8 := grineerFortressTexture
896 [-]: SETTABLE  R0 R7 R8     ; R0[R7] := R8
897 [-]: LOADK     R7 K444      ; R7 := "UITextures_JunctionLocation"
898 [-]: GETGLOBAL R8 K445      ; R8 := junctionLocationTexture
899 [-]: SETTABLE  R0 R7 R8     ; R0[R7] := R8
900 [-]: LOADK     R7 K446      ; R7 := "UITextures_EidolonPlains"
901 [-]: GETGLOBAL R8 K447      ; R8 := eidolonPlainsTexture
902 [-]: SETTABLE  R0 R7 R8     ; R0[R7] := R8
903 [-]: LOADK     R7 K448      ; R7 := "UITypes_DojoKeyBlueprint"
904 [-]: GETGLOBAL R8 K449      ; R8 := dojoKeyBlueprintType
905 [-]: SETTABLE  R0 R7 R8     ; R0[R7] := R8
906 [-]: LOADK     R7 K450      ; R7 := "UITypes_UGCKeys"
907 [-]: GETGLOBAL R8 K451      ; R8 := UGCKeys
908 [-]: SETTABLE  R0 R7 R8     ; R0[R7] := R8
909 [-]: LOADK     R7 K452      ; R7 := "UITypes_OwnershipRequiredCapturaTile"
910 [-]: GETGLOBAL R8 K453      ; R8 := ownershipRequiredCapturaTileType
911 [-]: SETTABLE  R0 R7 R8     ; R0[R7] := R8
912 [-]: LOADK     R7 K454      ; R7 := "UITypes_QuestRequiredCapturaTile"
913 [-]: GETGLOBAL R8 K455      ; R8 := questRequiredCapturaTileType
914 [-]: SETTABLE  R0 R7 R8     ; R0[R7] := R8
915 [-]: RETURN    R0 1         ; return 


; Function #2:
;
; Name:            
; Defined at line: 548
; #Upvalues:       2
; #Parameters:     0
; Is_vararg:       0
; Max Stack Size:  5

  1 [-]: GETGLOBAL R0 K0        ; R0 := mMovie
  2 [-]: SELF      R0 R0 K1     ; R1 := R0; R0 := R0["0x1C19D966"]
  3 [-]: LOADK     R2 K2        ; R2 := "_root"
  4 [-]: LOADK     R3 K3        ; R3 := "_alpha"
  5 [-]: LOADK     R4 K4        ; R4 := 0
  6 [-]: CALL      R0 5 1       ; R0(R1,R2,R3,R4)
  7 [-]: GETUPVAL  R0 U0        ; R0 := U0
  8 [-]: GETGLOBAL R1 K5        ; R1 := _G
  9 [-]: CALL      R0 2 1       ; R0(R1)
 10 [-]: MOVE      R0 R1        ; R0 := R1
 11 [-]: MOVE      R0 R1        ; R0 := R1
 12 [-]: RETURN    R0 1         ; return 


; Function #3:
;
; Name:            
; Defined at line: 554
; #Upvalues:       1
; #Parameters:     0
; Is_vararg:       0
; Max Stack Size:  4

  1 [-]: GETUPVAL  R0 U0        ; R0 := U0
  2 [-]: TEST      R0 0         ; if not R0 then PC := 12
  3 [-]: JMP       12           ; PC := 12
  4 [-]: GETGLOBAL R0 K0        ; R0 := gFlashMgr
  5 [-]: SELF      R0 R0 K1     ; R1 := R0; R0 := R0["0xE3A8ABAA"]
  6 [-]: LOADK     R2 K2        ; R2 := "CommonResourcesReady"
  7 [-]: LOADK     R3 K3        ; R3 := ""
  8 [-]: CALL      R0 4 1       ; R0(R1,R2,R3)
  9 [-]: GETGLOBAL R0 K4        ; R0 := mMovie
 10 [-]: SELF      R0 R0 K5     ; R1 := R0; R0 := R0["0xA58BB96C"]
 11 [-]: CALL      R0 2 1       ; R0(R1)
 12 [-]: RETURN    R0 1         ; return 


