code size: 309
code size: 100
; This file has been disassembled using luadec 2.0.2 by sztupy (http://winmo.sztupy.hu)
; Command line was: -dis M:\git repos\warframe-lua-disassembled\B.Font.cache_extracted\Lotus\Scripts\Effects\TC19GrnGalleonListing.luac 

; Name:            
; Defined at line: 0
; #Upvalues:       0
; #Parameters:     0
; Is_vararg:       2
; Max Stack Size:  46

  1 [-]: NEWTABLE  R0 27 0      ; R0 := {}
  2 [-]: GETGLOBAL R1 K0        ; R1 := 0x221C9700
  3 [-]: LOADK     R2 K1        ; R2 := -216.95799255371
  4 [-]: LOADK     R3 K2        ; R3 := -2.23734998703
  5 [-]: LOADK     R4 K3        ; R4 := -1540.2399902344
  6 [-]: CALL      R1 4 2       ; R1 := R1(R2,R3,R4)
  7 [-]: GETGLOBAL R2 K0        ; R2 := 0x221C9700
  8 [-]: LOADK     R3 K4        ; R3 := -224.04100036621
  9 [-]: LOADK     R4 K5        ; R4 := 26.990699768066
 10 [-]: LOADK     R5 K6        ; R5 := -219.33799743652
 11 [-]: CALL      R2 4 2       ; R2 := R2(R3,R4,R5)
 12 [-]: GETGLOBAL R3 K0        ; R3 := 0x221C9700
 13 [-]: LOADK     R4 K7        ; R4 := -481.74301147461
 14 [-]: LOADK     R5 K8        ; R5 := -255.65100097656
 15 [-]: LOADK     R6 K9        ; R6 := 775.98901367188
 16 [-]: CALL      R3 4 2       ; R3 := R3(R4,R5,R6)
 17 [-]: GETGLOBAL R4 K0        ; R4 := 0x221C9700
 18 [-]: LOADK     R5 K10       ; R5 := -115.40799713135
 19 [-]: LOADK     R6 K11       ; R6 := -266.29901123047
 20 [-]: LOADK     R7 K12       ; R7 := 1357.2800292969
 21 [-]: CALL      R4 4 2       ; R4 := R4(R5,R6,R7)
 22 [-]: GETGLOBAL R5 K0        ; R5 := 0x221C9700
 23 [-]: LOADK     R6 K13       ; R6 := -223.13499450684
 24 [-]: LOADK     R7 K14       ; R7 := 57.887798309326
 25 [-]: LOADK     R8 K15       ; R8 := 675.21801757813
 26 [-]: CALL      R5 4 2       ; R5 := R5(R6,R7,R8)
 27 [-]: GETGLOBAL R6 K0        ; R6 := 0x221C9700
 28 [-]: LOADK     R7 K16       ; R7 := -201.87699890137
 29 [-]: LOADK     R8 K17       ; R8 := 337.08599853516
 30 [-]: LOADK     R9 K18       ; R9 := -160.47900390625
 31 [-]: CALL      R6 4 2       ; R6 := R6(R7,R8,R9)
 32 [-]: GETGLOBAL R7 K0        ; R7 := 0x221C9700
 33 [-]: LOADK     R8 K19       ; R8 := -228.72700500488
 34 [-]: LOADK     R9 K20       ; R9 := 53.673301696777
 35 [-]: LOADK     R10 K21      ; R10 := 611.97497558594
 36 [-]: CALL      R7 4 2       ; R7 := R7(R8,R9,R10)
 37 [-]: GETGLOBAL R8 K0        ; R8 := 0x221C9700
 38 [-]: LOADK     R9 K22       ; R9 := -419.86898803711
 39 [-]: LOADK     R10 K23      ; R10 := -151.53799438477
 40 [-]: LOADK     R11 K24      ; R11 := 502.14898681641
 41 [-]: CALL      R8 4 2       ; R8 := R8(R9,R10,R11)
 42 [-]: GETGLOBAL R9 K0        ; R9 := 0x221C9700
 43 [-]: LOADK     R10 K25      ; R10 := 260.42098999023
 44 [-]: LOADK     R11 K26      ; R11 := 344.63101196289
 45 [-]: LOADK     R12 K27      ; R12 := -1029.0100097656
 46 [-]: CALL      R9 4 2       ; R9 := R9(R10,R11,R12)
 47 [-]: GETGLOBAL R10 K0       ; R10 := 0x221C9700
 48 [-]: LOADK     R11 K28      ; R11 := -194.1490020752
 49 [-]: LOADK     R12 K29      ; R12 := -26.167499542236
 50 [-]: LOADK     R13 K30      ; R13 := 880.65698242188
 51 [-]: CALL      R10 4 2      ; R10 := R10(R11,R12,R13)
 52 [-]: GETGLOBAL R11 K0       ; R11 := 0x221C9700
 53 [-]: LOADK     R12 K31      ; R12 := 217.87100219727
 54 [-]: LOADK     R13 K32      ; R13 := 433.5419921875
 55 [-]: LOADK     R14 K33      ; R14 := -407.81100463867
 56 [-]: CALL      R11 4 2      ; R11 := R11(R12,R13,R14)
 57 [-]: GETGLOBAL R12 K0       ; R12 := 0x221C9700
 58 [-]: LOADK     R13 K34      ; R13 := -204.32099914551
 59 [-]: LOADK     R14 K35      ; R14 := 102.15399932861
 60 [-]: LOADK     R15 K36      ; R15 := 1014.450012207
 61 [-]: CALL      R12 4 2      ; R12 := R12(R13,R14,R15)
 62 [-]: GETGLOBAL R13 K0       ; R13 := 0x221C9700
 63 [-]: LOADK     R14 K37      ; R14 := -208.42700195313
 64 [-]: LOADK     R15 K38      ; R15 := -140.67700195313
 65 [-]: LOADK     R16 K39      ; R16 := -1139.9100341797
 66 [-]: CALL      R13 4 2      ; R13 := R13(R14,R15,R16)
 67 [-]: GETGLOBAL R14 K0       ; R14 := 0x221C9700
 68 [-]: LOADK     R15 K40      ; R15 := -293.33200073242
 69 [-]: LOADK     R16 K41      ; R16 := -103.18199920654
 70 [-]: LOADK     R17 K42      ; R17 := -709.76397705078
 71 [-]: CALL      R14 4 2      ; R14 := R14(R15,R16,R17)
 72 [-]: GETGLOBAL R15 K0       ; R15 := 0x221C9700
 73 [-]: LOADK     R16 K43      ; R16 := -142.48899841309
 74 [-]: LOADK     R17 K44      ; R17 := 120.06900024414
 75 [-]: LOADK     R18 K45      ; R18 := -808.88000488281
 76 [-]: CALL      R15 4 2      ; R15 := R15(R16,R17,R18)
 77 [-]: GETGLOBAL R16 K0       ; R16 := 0x221C9700
 78 [-]: LOADK     R17 K46      ; R17 := -140.29800415039
 79 [-]: LOADK     R18 K47      ; R18 := 171.31900024414
 80 [-]: LOADK     R19 K48      ; R19 := -862.64501953125
 81 [-]: CALL      R16 4 2      ; R16 := R16(R17,R18,R19)
 82 [-]: GETGLOBAL R17 K0       ; R17 := 0x221C9700
 83 [-]: LOADK     R18 K49      ; R18 := -130.01899719238
 84 [-]: LOADK     R19 K50      ; R19 := 179.33500671387
 85 [-]: LOADK     R20 K51      ; R20 := -1070
 86 [-]: CALL      R17 4 2      ; R17 := R17(R18,R19,R20)
 87 [-]: GETGLOBAL R18 K0       ; R18 := 0x221C9700
 88 [-]: LOADK     R19 K52      ; R19 := -160.85499572754
 89 [-]: LOADK     R20 K53      ; R20 := -11.405099868774
 90 [-]: LOADK     R21 K54      ; R21 := -895.05297851563
 91 [-]: CALL      R18 4 2      ; R18 := R18(R19,R20,R21)
 92 [-]: GETGLOBAL R19 K0       ; R19 := 0x221C9700
 93 [-]: LOADK     R20 K55      ; R20 := -14.909099578857
 94 [-]: LOADK     R21 K56      ; R21 := 96.913200378418
 95 [-]: LOADK     R22 K57      ; R22 := -1149.2900390625
 96 [-]: CALL      R19 4 2      ; R19 := R19(R20,R21,R22)
 97 [-]: GETGLOBAL R20 K0       ; R20 := 0x221C9700
 98 [-]: LOADK     R21 K58      ; R21 := -243.55400085449
 99 [-]: LOADK     R22 K59      ; R22 := 86.01619720459
100 [-]: LOADK     R23 K60      ; R23 := -556.76898193359
101 [-]: CALL      R20 4 2      ; R20 := R20(R21,R22,R23)
102 [-]: GETGLOBAL R21 K0       ; R21 := 0x221C9700
103 [-]: LOADK     R22 K61      ; R22 := -227.48500061035
104 [-]: LOADK     R23 K62      ; R23 := 82.968299865723
105 [-]: LOADK     R24 K63      ; R24 := -652.39898681641
106 [-]: CALL      R21 4 2      ; R21 := R21(R22,R23,R24)
107 [-]: GETGLOBAL R22 K0       ; R22 := 0x221C9700
108 [-]: LOADK     R23 K64      ; R23 := 179.22200012207
109 [-]: LOADK     R24 K65      ; R24 := 248.71600341797
110 [-]: LOADK     R25 K66      ; R25 := -920.81701660156
111 [-]: CALL      R22 4 2      ; R22 := R22(R23,R24,R25)
112 [-]: GETGLOBAL R23 K0       ; R23 := 0x221C9700
113 [-]: LOADK     R24 K67      ; R24 := 55.369598388672
114 [-]: LOADK     R25 K68      ; R25 := 91.488403320313
115 [-]: LOADK     R26 K69      ; R26 := -1586.5100097656
116 [-]: CALL      R23 4 2      ; R23 := R23(R24,R25,R26)
117 [-]: GETGLOBAL R24 K0       ; R24 := 0x221C9700
118 [-]: LOADK     R25 K70      ; R25 := -110.547996521
119 [-]: LOADK     R26 K71      ; R26 := 36.223999023438
120 [-]: LOADK     R27 K72      ; R27 := -1067.1700439453
121 [-]: CALL      R24 4 2      ; R24 := R24(R25,R26,R27)
122 [-]: GETGLOBAL R25 K0       ; R25 := 0x221C9700
123 [-]: LOADK     R26 K73      ; R26 := -281.98498535156
124 [-]: LOADK     R27 K74      ; R27 := -26.965299606323
125 [-]: LOADK     R28 K75      ; R28 := -727.60900878906
126 [-]: CALL      R25 4 2      ; R25 := R25(R26,R27,R28)
127 [-]: GETGLOBAL R26 K0       ; R26 := 0x221C9700
128 [-]: LOADK     R27 K76      ; R27 := -128.43699645996
129 [-]: LOADK     R28 K77      ; R28 := 131.66900634766
130 [-]: LOADK     R29 K78      ; R29 := -1057.2399902344
131 [-]: CALL      R26 4 2      ; R26 := R26(R27,R28,R29)
132 [-]: GETGLOBAL R27 K0       ; R27 := 0x221C9700
133 [-]: LOADK     R28 K79      ; R28 := 40.65599822998
134 [-]: LOADK     R29 K80      ; R29 := 527.68597412109
135 [-]: LOADK     R30 K81      ; R30 := -410.85000610352
136 [-]: CALL      R27 4 2      ; R27 := R27(R28,R29,R30)
137 [-]: GETGLOBAL R28 K0       ; R28 := 0x221C9700
138 [-]: LOADK     R29 K82      ; R29 := 90.010101318359
139 [-]: LOADK     R30 K83      ; R30 := 258.37100219727
140 [-]: LOADK     R31 K84      ; R31 := 1073.0400390625
141 [-]: CALL      R28 4 2      ; R28 := R28(R29,R30,R31)
142 [-]: GETGLOBAL R29 K0       ; R29 := 0x221C9700
143 [-]: LOADK     R30 K85      ; R30 := -176.65299987793
144 [-]: LOADK     R31 K86      ; R31 := 430.9580078125
145 [-]: LOADK     R32 K87      ; R32 := -487.66299438477
146 [-]: CALL      R29 4 2      ; R29 := R29(R30,R31,R32)
147 [-]: GETGLOBAL R30 K0       ; R30 := 0x221C9700
148 [-]: LOADK     R31 K88      ; R31 := 65.150001525879
149 [-]: LOADK     R32 K89      ; R32 := 492.0530090332
150 [-]: LOADK     R33 K90      ; R33 := -320.60101318359
151 [-]: CALL      R30 4 2      ; R30 := R30(R31,R32,R33)
152 [-]: GETGLOBAL R31 K0       ; R31 := 0x221C9700
153 [-]: LOADK     R32 K91      ; R32 := -144.38900756836
154 [-]: LOADK     R33 K92      ; R33 := -158.08999633789
155 [-]: LOADK     R34 K93      ; R34 := -953.71899414063
156 [-]: CALL      R31 4 2      ; R31 := R31(R32,R33,R34)
157 [-]: GETGLOBAL R32 K0       ; R32 := 0x221C9700
158 [-]: LOADK     R33 K94      ; R33 := -263.64801025391
159 [-]: LOADK     R34 K95      ; R34 := 286.24798583984
160 [-]: LOADK     R35 K96      ; R35 := -264.30700683594
161 [-]: CALL      R32 4 2      ; R32 := R32(R33,R34,R35)
162 [-]: GETGLOBAL R33 K0       ; R33 := 0x221C9700
163 [-]: LOADK     R34 K97      ; R34 := -131.56199645996
164 [-]: LOADK     R35 K98      ; R35 := 137.10800170898
165 [-]: LOADK     R36 K99      ; R36 := -947.36602783203
166 [-]: CALL      R33 4 2      ; R33 := R33(R34,R35,R36)
167 [-]: GETGLOBAL R34 K0       ; R34 := 0x221C9700
168 [-]: LOADK     R35 K100     ; R35 := -569.27001953125
169 [-]: LOADK     R36 K101     ; R36 := -261.99099731445
170 [-]: LOADK     R37 K102     ; R37 := 506.43798828125
171 [-]: CALL      R34 4 2      ; R34 := R34(R35,R36,R37)
172 [-]: GETGLOBAL R35 K0       ; R35 := 0x221C9700
173 [-]: LOADK     R36 K103     ; R36 := -237.10000610352
174 [-]: LOADK     R37 K104     ; R37 := 62.689399719238
175 [-]: LOADK     R38 K105     ; R38 := -385.42498779297
176 [-]: CALL      R35 4 2      ; R35 := R35(R36,R37,R38)
177 [-]: GETGLOBAL R36 K0       ; R36 := 0x221C9700
178 [-]: LOADK     R37 K106     ; R37 := -326.57800292969
179 [-]: LOADK     R38 K107     ; R38 := -127.74900054932
180 [-]: LOADK     R39 K108     ; R39 := -620.31799316406
181 [-]: CALL      R36 4 2      ; R36 := R36(R37,R38,R39)
182 [-]: GETGLOBAL R37 K0       ; R37 := 0x221C9700
183 [-]: LOADK     R38 K109     ; R38 := -91.388298034668
184 [-]: LOADK     R39 K110     ; R39 := 248.51499938965
185 [-]: LOADK     R40 K111     ; R40 := 31.912399291992
186 [-]: CALL      R37 4 2      ; R37 := R37(R38,R39,R40)
187 [-]: GETGLOBAL R38 K0       ; R38 := 0x221C9700
188 [-]: LOADK     R39 K112     ; R39 := -159.3809967041
189 [-]: LOADK     R40 K113     ; R40 := -153.38999938965
190 [-]: LOADK     R41 K114     ; R41 := -1049.6300048828
191 [-]: CALL      R38 4 2      ; R38 := R38(R39,R40,R41)
192 [-]: GETGLOBAL R39 K0       ; R39 := 0x221C9700
193 [-]: LOADK     R40 K115     ; R40 := -140.40400695801
194 [-]: LOADK     R41 K116     ; R41 := 20.955600738525
195 [-]: LOADK     R42 K117     ; R42 := -1141.6300048828
196 [-]: CALL      R39 4 2      ; R39 := R39(R40,R41,R42)
197 [-]: GETGLOBAL R40 K0       ; R40 := 0x221C9700
198 [-]: LOADK     R41 K118     ; R41 := -154.97099304199
199 [-]: LOADK     R42 K119     ; R42 := -112.65899658203
200 [-]: LOADK     R43 K120     ; R43 := 943.916015625
201 [-]: CALL      R40 4 2      ; R40 := R40(R41,R42,R43)
202 [-]: GETGLOBAL R41 K0       ; R41 := 0x221C9700
203 [-]: LOADK     R42 K121     ; R42 := -267.35101318359
204 [-]: LOADK     R43 K122     ; R43 := -60.296798706055
205 [-]: LOADK     R44 K123     ; R44 := -1408.3599853516
206 [-]: CALL      R41 4 2      ; R41 := R41(R42,R43,R44)
207 [-]: GETGLOBAL R42 K0       ; R42 := 0x221C9700
208 [-]: LOADK     R43 K124     ; R43 := -141.72300720215
209 [-]: LOADK     R44 K125     ; R44 := -161.85699462891
210 [-]: LOADK     R45 K126     ; R45 := 1271.0899658203
211 [-]: CALL      R42 4 0      ; R42,... := R42(R43,R44,R45)
212 [-]: SETLIST   R0 0 1       ; R0[(1-1)*FPF+i] := R(0+i), 1 <= i <= 0
213 [-]: NEWTABLE  R1 27 0      ; R1 := {}
214 [-]: LOADK     R2 K127      ; R2 := 60
215 [-]: LOADK     R3 K128      ; R3 := 76
216 [-]: LOADK     R4 K129      ; R4 := 62
217 [-]: LOADK     R5 K130      ; R5 := 38
218 [-]: LOADK     R6 K131      ; R6 := 49
219 [-]: LOADK     R7 K132      ; R7 := 52
220 [-]: LOADK     R8 K133      ; R8 := 33
221 [-]: LOADK     R9 K134      ; R9 := 57
222 [-]: LOADK     R10 K135     ; R10 := 35
223 [-]: LOADK     R11 K136     ; R11 := 73
224 [-]: LOADK     R12 K128     ; R12 := 76
225 [-]: LOADK     R13 K137     ; R13 := 53
226 [-]: LOADK     R14 K138     ; R14 := 91
227 [-]: LOADK     R15 K139     ; R15 := 74
228 [-]: LOADK     R16 K140     ; R16 := 94
229 [-]: LOADK     R17 K137     ; R17 := 53
230 [-]: LOADK     R18 K141     ; R18 := 84
231 [-]: LOADK     R19 K130     ; R19 := 38
232 [-]: LOADK     R20 K142     ; R20 := 28
233 [-]: LOADK     R21 K130     ; R21 := 38
234 [-]: LOADK     R22 K143     ; R22 := 114
235 [-]: LOADK     R23 K144     ; R23 := 125
236 [-]: LOADK     R24 K145     ; R24 := 78
237 [-]: LOADK     R25 K146     ; R25 := 106
238 [-]: LOADK     R26 K147     ; R26 := 93
239 [-]: LOADK     R27 K127     ; R27 := 60
240 [-]: LOADK     R28 K148     ; R28 := 56
241 [-]: LOADK     R29 K149     ; R29 := 55
242 [-]: LOADK     R30 K150     ; R30 := 112
243 [-]: LOADK     R31 K151     ; R31 := 115
244 [-]: LOADK     R32 K135     ; R32 := 35
245 [-]: LOADK     R33 K141     ; R33 := 84
246 [-]: LOADK     R34 K152     ; R34 := 80
247 [-]: LOADK     R35 K131     ; R35 := 49
248 [-]: LOADK     R36 K153     ; R36 := 107
249 [-]: LOADK     R37 K154     ; R37 := 32
250 [-]: LOADK     R38 K155     ; R38 := 92
251 [-]: LOADK     R39 K145     ; R39 := 78
252 [-]: LOADK     R40 K131     ; R40 := 49
253 [-]: LOADK     R41 K151     ; R41 := 115
254 [-]: LOADK     R42 K136     ; R42 := 73
255 [-]: LOADK     R43 K156     ; R43 := 47
256 [-]: SETLIST   R1 42 1      ; R1[(1-1)*FPF+i] := R(1+i), 1 <= i <= 42
257 [-]: NEWTABLE  R2 27 0      ; R2 := {}
258 [-]: LOADK     R3 K157      ; R3 := 1
259 [-]: LOADK     R4 K157      ; R4 := 1
260 [-]: LOADK     R5 K157      ; R5 := 1
261 [-]: LOADK     R6 K158      ; R6 := 2
262 [-]: LOADK     R7 K158      ; R7 := 2
263 [-]: LOADK     R8 K157      ; R8 := 1
264 [-]: LOADK     R9 K158      ; R9 := 2
265 [-]: LOADK     R10 K157     ; R10 := 1
266 [-]: LOADK     R11 K158     ; R11 := 2
267 [-]: LOADK     R12 K158     ; R12 := 2
268 [-]: LOADK     R13 K158     ; R13 := 2
269 [-]: LOADK     R14 K158     ; R14 := 2
270 [-]: LOADK     R15 K157     ; R15 := 1
271 [-]: LOADK     R16 K157     ; R16 := 1
272 [-]: LOADK     R17 K158     ; R17 := 2
273 [-]: LOADK     R18 K157     ; R18 := 1
274 [-]: LOADK     R19 K157     ; R19 := 1
275 [-]: LOADK     R20 K157     ; R20 := 1
276 [-]: LOADK     R21 K157     ; R21 := 1
277 [-]: LOADK     R22 K157     ; R22 := 1
278 [-]: LOADK     R23 K158     ; R23 := 2
279 [-]: LOADK     R24 K157     ; R24 := 1
280 [-]: LOADK     R25 K158     ; R25 := 2
281 [-]: LOADK     R26 K157     ; R26 := 1
282 [-]: LOADK     R27 K158     ; R27 := 2
283 [-]: LOADK     R28 K158     ; R28 := 2
284 [-]: LOADK     R29 K158     ; R29 := 2
285 [-]: LOADK     R30 K157     ; R30 := 1
286 [-]: LOADK     R31 K157     ; R31 := 1
287 [-]: LOADK     R32 K157     ; R32 := 1
288 [-]: LOADK     R33 K157     ; R33 := 1
289 [-]: LOADK     R34 K157     ; R34 := 1
290 [-]: LOADK     R35 K157     ; R35 := 1
291 [-]: LOADK     R36 K157     ; R36 := 1
292 [-]: LOADK     R37 K157     ; R37 := 1
293 [-]: LOADK     R38 K157     ; R38 := 1
294 [-]: LOADK     R39 K157     ; R39 := 1
295 [-]: LOADK     R40 K158     ; R40 := 2
296 [-]: LOADK     R41 K157     ; R41 := 1
297 [-]: LOADK     R42 K157     ; R42 := 1
298 [-]: LOADK     R43 K157     ; R43 := 1
299 [-]: LOADK     R44 K158     ; R44 := 2
300 [-]: SETLIST   R2 42 1      ; R2[(1-1)*FPF+i] := R(2+i), 1 <= i <= 42
301 [-]: LOADK     R3 K157      ; R3 := 1
302 [-]: CLOSURE   R4 0         ; R4 := closure(Function #1)
303 [-]: MOVE      R0 R3        ; R0 := R3
304 [-]: MOVE      R0 R0        ; R0 := R0
305 [-]: MOVE      R0 R2        ; R0 := R2
306 [-]: MOVE      R0 R1        ; R0 := R1
307 [-]: SETGLOBAL R4 K159      ; explodePlease := R4
308 [-]: SETGLOBAL R4 K160      ; 0xE6A23175 := R4
309 [-]: RETURN    R0 1         ; return 


; Function #1:
;
; Name:            
; Defined at line: 56
; #Upvalues:       4
; #Parameters:     1
; Is_vararg:       0
; Max Stack Size:  18

  1 [-]: GETGLOBAL R1 K0        ; R1 := 0x201191EA
  2 [-]: GETGLOBAL R2 K1        ; R2 := delay
  3 [-]: CALL      R1 2 1       ; R1(R2)
  4 [-]: GETGLOBAL R1 K2        ; R1 := 0x400E7765
  5 [-]: MOVE      R2 R0        ; R2 := R0
  6 [-]: CALL      R1 2 2       ; R1 := R1(R2)
  7 [-]: TEST      R1 1         ; if R1 then PC := 100
  8 [-]: JMP       100          ; PC := 100
  9 [-]: SELF      R1 R0 K3     ; R2 := R0; R1 := R0["0xECB5B892"]
 10 [-]: CALL      R1 2 2       ; R1 := R1(R2)
 11 [-]: MOVE      R1 R0        ; R1 := R0
 12 [-]: GETGLOBAL R1 K4        ; R1 := 0x63B09107
 13 [-]: GETUPVAL  R2 U1        ; R2 := U1
 14 [-]: CALL      R1 2 4       ; R1,R2,R3 := R1(R2)
 15 [-]: JMP       98           ; PC := 98
 16 [-]: GETGLOBAL R6 K2        ; R6 := 0x400E7765
 17 [-]: MOVE      R7 R0        ; R7 := R0
 18 [-]: CALL      R6 2 2       ; R6 := R6(R7)
 19 [-]: TEST      R6 1         ; if R6 then PC := 98
 20 [-]: JMP       98           ; PC := 98
 21 [-]: GETGLOBAL R6 K2        ; R6 := 0x400E7765
 22 [-]: GETGLOBAL R7 K5        ; R7 := explosionSpawners
 23 [-]: GETUPVAL  R8 U2        ; R8 := U2
 24 [-]: GETTABLE  R8 R8 R4     ; R8 := R8[R4]
 25 [-]: GETTABLE  R7 R7 R8     ; R7 := R7[R8]
 26 [-]: CALL      R6 2 2       ; R6 := R6(R7)
 27 [-]: TEST      R6 1         ; if R6 then PC := 98
 28 [-]: JMP       98           ; PC := 98
 29 [-]: GETGLOBAL R6 K2        ; R6 := 0x400E7765
 30 [-]: GETUPVAL  R7 U1        ; R7 := U1
 31 [-]: GETTABLE  R7 R7 R4     ; R7 := R7[R4]
 32 [-]: CALL      R6 2 2       ; R6 := R6(R7)
 33 [-]: TEST      R6 1         ; if R6 then PC := 98
 34 [-]: JMP       98           ; PC := 98
 35 [-]: LOADK     R6 K6        ; R6 := 0.0099999997764826
 36 [-]: MOVE      R6 R0        ; R6 := R0
 37 [-]: GETGLOBAL R6 K7        ; R6 := 0x221C9700
 38 [-]: GETUPVAL  R7 U1        ; R7 := U1
 39 [-]: GETTABLE  R7 R7 R4     ; R7 := R7[R4]
 40 [-]: GETTABLE  R7 R7 K8     ; R7 := R7["x"]
 41 [-]: UNM       R7 R7        ; R7 := - R7
 42 [-]: GETUPVAL  R8 U0        ; R8 := U0
 43 [-]: MUL       R7 R7 R8     ; R7 := R7 * R8
 44 [-]: GETUPVAL  R8 U1        ; R8 := U1
 45 [-]: GETTABLE  R8 R8 R4     ; R8 := R8[R4]
 46 [-]: GETTABLE  R8 R8 K9     ; R8 := R8["y"]
 47 [-]: GETUPVAL  R9 U0        ; R9 := U0
 48 [-]: MUL       R8 R8 R9     ; R8 := R8 * R9
 49 [-]: GETUPVAL  R9 U1        ; R9 := U1
 50 [-]: GETTABLE  R9 R9 R4     ; R9 := R9[R4]
 51 [-]: GETTABLE  R9 R9 K10    ; R9 := R9["z"]
 52 [-]: GETUPVAL  R10 U0       ; R10 := U0
 53 [-]: MUL       R9 R9 R10    ; R9 := R9 * R10
 54 [-]: CALL      R6 4 2       ; R6 := R6(R7,R8,R9)
 55 [-]: GETGLOBAL R7 K11       ; R7 := debugPlz
 56 [-]: TEST      R7 0         ; if not R7 then PC := 66
 57 [-]: JMP       66           ; PC := 66
 58 [-]: GETGLOBAL R7 K12       ; R7 := 0x93B1256B
 59 [-]: LOADK     R8 K13       ; R8 := "Point "
 60 [-]: MOVE      R9 R4        ; R9 := R4
 61 [-]: GETUPVAL  R10 U2       ; R10 := U2
 62 [-]: GETTABLE  R10 R10 R4   ; R10 := R10[R4]
 63 [-]: LOADK     R11 K14      ; R11 := "exploded at"
 64 [-]: MOVE      R12 R6       ; R12 := R6
 65 [-]: CALL      R7 6 1       ; R7(R8,R9,R10,R11,R12)
 66 [-]: SELF      R7 R0 K15    ; R8 := R0; R7 := R0["0xAB436EF2"]
 67 [-]: GETGLOBAL R9 K5        ; R9 := explosionSpawners
 68 [-]: GETUPVAL  R10 U2       ; R10 := U2
 69 [-]: GETTABLE  R10 R10 R4   ; R10 := R10[R4]
 70 [-]: GETTABLE  R9 R9 R10    ; R9 := R9[R10]
 71 [-]: GETGLOBAL R10 K16      ; R10 := 0xEC274B1A
 72 [-]: LOADK     R11 K17      ; R11 := "GAME_C1_BOD"
 73 [-]: CALL      R10 2 2      ; R10 := R10(R11)
 74 [-]: MOVE      R11 R6       ; R11 := R6
 75 [-]: GETGLOBAL R12 K18      ; R12 := 0x1E4F6281
 76 [-]: GETGLOBAL R13 K19      ; R13 := math
 77 [-]: GETTABLE  R13 R13 K20  ; R13 := R13["0x865961F7"]
 78 [-]: LOADK     R14 K21      ; R14 := -180
 79 [-]: LOADK     R15 K22      ; R15 := 180
 80 [-]: CALL      R13 3 2      ; R13 := R13(R14,R15)
 81 [-]: GETGLOBAL R14 K19      ; R14 := math
 82 [-]: GETTABLE  R14 R14 K20  ; R14 := R14["0x865961F7"]
 83 [-]: LOADK     R15 K21      ; R15 := -180
 84 [-]: LOADK     R16 K22      ; R16 := 180
 85 [-]: CALL      R14 3 2      ; R14 := R14(R15,R16)
 86 [-]: GETGLOBAL R15 K19      ; R15 := math
 87 [-]: GETTABLE  R15 R15 K20  ; R15 := R15["0x865961F7"]
 88 [-]: LOADK     R16 K21      ; R16 := -180
 89 [-]: LOADK     R17 K22      ; R17 := 180
 90 [-]: CALL      R15 3 0      ; R15,... := R15(R16,R17)
 91 [-]: CALL      R12 0 0      ; R12,... := R12(R13,...)
 92 [-]: CALL      R7 0 1       ; R7(R8,...)
 93 [-]: GETGLOBAL R7 K0        ; R7 := 0x201191EA
 94 [-]: GETUPVAL  R8 U3        ; R8 := U3
 95 [-]: GETTABLE  R8 R8 R4     ; R8 := R8[R4]
 96 [-]: MUL       R8 R8 K6     ; R8 := R8 * 0.0099999997764826
 97 [-]: CALL      R7 2 1       ; R7(R8)
 98 [-]: TFORLOOP  R1 2         ; R4,R5 :=  R1(R2,R3); if R4 ~= nil then begin PC = 16; R3 := R4 end
 99 [-]: JMP       16           ; PC := 16
100 [-]: RETURN    R0 1         ; return 


