code size: 180
code size: 3
code size: 21
code size: 20
code size: 7
code size: 21
code size: 3
code size: 24
code size: 10
code size: 9
code size: 49
code size: 1
code size: 25
code size: 25
code size: 45
code size: 27
code size: 37
code size: 167
code size: 3
code size: 17
code size: 21
code size: 48
code size: 6
code size: 3
code size: 6
code size: 12
code size: 2
code size: 2
code size: 3
code size: 3
code size: 3
code size: 12
code size: 7
code size: 7
code size: 5
code size: 12
code size: 12
code size: 16
code size: 12
code size: 12
code size: 1
code size: 1
code size: 5
code size: 5
code size: 5
code size: 5
code size: 5
code size: 5
code size: 5
code size: 5
code size: 14
code size: 6
code size: 19
; This file has been disassembled using luadec 2.0.2 by sztupy (http://winmo.sztupy.hu)
; Command line was: -dis M:\git repos\warframe-lua-disassembled\B.Font.cache_extracted\Lotus\Interface\HUD\ComponentsList.luac 

; Name:            
; Defined at line: 0
; #Upvalues:       0
; #Parameters:     0
; Is_vararg:       2
; Max Stack Size:  26

  1 [-]: GETGLOBAL R0 K0        ; R0 := 0x329BDC44
  2 [-]: LOADK     R1 K1        ; R1 := "EE.Interface.Utilities"
  3 [-]: CALL      R0 2 2       ; R0 := R0(R1)
  4 [-]: LOADNIL   R1 R1        ; R1 := nil
  5 [-]: MOVE      R2 R0        ; R2 := R0
  6 [-]: MOVE      R3 R1        ; R3 := R1
  7 [-]: LOADNIL   R4 R9        ; R4 := R5 := R6 := R7 := R8 := R9 := nil
  8 [-]: LOADK     R10 K2       ; R10 := 0
  9 [-]: LOADK     R11 K2       ; R11 := 0
 10 [-]: LOADK     R12 K2       ; R12 := 0
 11 [-]: LOADK     R13 K3       ; R13 := 0.44999998807907
 12 [-]: CLOSURE   R14 0        ; R14 := closure(Function #1)
 13 [-]: SETGLOBAL R14 K4       ; Shutdown := R14
 14 [-]: SETGLOBAL R14 K5       ; 0x3C577FA3 := R14
 15 [-]: CLOSURE   R14 1        ; R14 := closure(Function #2)
 16 [-]: MOVE      R0 R3        ; R0 := R3
 17 [-]: MOVE      R0 R13       ; R0 := R13
 18 [-]: MOVE      R0 R8        ; R0 := R8
 19 [-]: MOVE      R0 R9        ; R0 := R9
 20 [-]: CLOSURE   R15 2        ; R15 := closure(Function #3)
 21 [-]: MOVE      R0 R14       ; R0 := R14
 22 [-]: SETGLOBAL R15 K6       ; TransitionOut := R15
 23 [-]: SETGLOBAL R15 K7       ; 0x7097B1B4 := R15
 24 [-]: CLOSURE   R15 3        ; R15 := closure(Function #4)
 25 [-]: MOVE      R0 R0        ; R0 := R0
 26 [-]: MOVE      R0 R14       ; R0 := R14
 27 [-]: CLOSURE   R16 4        ; R16 := closure(Function #5)
 28 [-]: MOVE      R0 R9        ; R0 := R9
 29 [-]: MOVE      R0 R4        ; R0 := R4
 30 [-]: MOVE      R0 R14       ; R0 := R14
 31 [-]: CLOSURE   R17 5        ; R17 := closure(Function #6)
 32 [-]: MOVE      R0 R4        ; R0 := R4
 33 [-]: MOVE      R0 R10       ; R0 := R10
 34 [-]: MOVE      R0 R16       ; R0 := R16
 35 [-]: MOVE      R0 R12       ; R0 := R12
 36 [-]: MOVE      R0 R0        ; R0 := R0
 37 [-]: MOVE      R0 R5        ; R0 := R5
 38 [-]: CLOSURE   R18 6        ; R18 := closure(Function #7)
 39 [-]: MOVE      R0 R2        ; R0 := R2
 40 [-]: MOVE      R0 R1        ; R0 := R1
 41 [-]: MOVE      R0 R4        ; R0 := R4
 42 [-]: SETGLOBAL R18 K8       ; Update := R18
 43 [-]: SETGLOBAL R18 K9       ; 0x8C7099E9 := R18
 44 [-]: CLOSURE   R18 7        ; R18 := closure(Function #8)
 45 [-]: MOVE      R0 R7        ; R0 := R7
 46 [-]: MOVE      R0 R11       ; R0 := R11
 47 [-]: MOVE      R0 R1        ; R0 := R1
 48 [-]: MOVE      R0 R18       ; R0 := R18
 49 [-]: MOVE      R0 R14       ; R0 := R14
 50 [-]: MOVE      R0 R4        ; R0 := R4
 51 [-]: MOVE      R0 R5        ; R0 := R5
 52 [-]: MOVE      R0 R6        ; R0 := R6
 53 [-]: MOVE      R0 R0        ; R0 := R0
 54 [-]: MOVE      R0 R3        ; R0 := R3
 55 [-]: CLOSURE   R19 8        ; R19 := closure(Function #9)
 56 [-]: CLOSURE   R20 9        ; R20 := closure(Function #10)
 57 [-]: CLOSURE   R21 10       ; R21 := closure(Function #11)
 58 [-]: MOVE      R0 R1        ; R0 := R1
 59 [-]: MOVE      R0 R0        ; R0 := R0
 60 [-]: MOVE      R0 R19       ; R0 := R19
 61 [-]: MOVE      R0 R17       ; R0 := R17
 62 [-]: MOVE      R0 R13       ; R0 := R13
 63 [-]: MOVE      R0 R18       ; R0 := R18
 64 [-]: MOVE      R0 R2        ; R0 := R2
 65 [-]: SETGLOBAL R21 K10      ; Initialize := R21
 66 [-]: SETGLOBAL R21 K11      ; 0x62648036 := R21
 67 [-]: CLOSURE   R21 11       ; R21 := closure(Function #12)
 68 [-]: SETGLOBAL R21 K12      ; SetTitle := R21
 69 [-]: SETGLOBAL R21 K13      ; 0x52FAEDE2 := R21
 70 [-]: CLOSURE   R21 12       ; R21 := closure(Function #13)
 71 [-]: SETGLOBAL R21 K14      ; SetNoElementsMessage := R21
 72 [-]: SETGLOBAL R21 K15      ; 0x1657556B := R21
 73 [-]: CLOSURE   R21 13       ; R21 := closure(Function #14)
 74 [-]: MOVE      R0 R7        ; R0 := R7
 75 [-]: SETGLOBAL R21 K16      ; SetElementsFunction := R21
 76 [-]: SETGLOBAL R21 K17      ; 0xF79D8904 := R21
 77 [-]: CLOSURE   R21 14       ; R21 := closure(Function #15)
 78 [-]: MOVE      R0 R8        ; R0 := R8
 79 [-]: SETGLOBAL R21 K18      ; SetCallBack := R21
 80 [-]: SETGLOBAL R21 K19      ; 0x2BF11226 := R21
 81 [-]: CLOSURE   R21 15       ; R21 := closure(Function #16)
 82 [-]: MOVE      R0 R14       ; R0 := R14
 83 [-]: SETGLOBAL R21 K20      ; Close := R21
 84 [-]: SETGLOBAL R21 K21      ; 0xA58BB96C := R21
 85 [-]: CLOSURE   R21 16       ; R21 := closure(Function #17)
 86 [-]: MOVE      R0 R15       ; R0 := R15
 87 [-]: SETGLOBAL R21 K22      ; ExitScreen := R21
 88 [-]: SETGLOBAL R21 K23      ; 0xDFB70305 := R21
 89 [-]: CLOSURE   R21 17       ; R21 := closure(Function #18)
 90 [-]: MOVE      R0 R16       ; R0 := R16
 91 [-]: SETGLOBAL R21 K24      ; FinishSelection := R21
 92 [-]: SETGLOBAL R21 K25      ; 0x4AE52860 := R21
 93 [-]: CLOSURE   R21 18       ; R21 := closure(Function #19)
 94 [-]: MOVE      R0 R3        ; R0 := R3
 95 [-]: MOVE      R0 R4        ; R0 := R4
 96 [-]: SETGLOBAL R21 K26      ; onKeyUp_MENU_SELECT := R21
 97 [-]: SETGLOBAL R21 K27      ; 0x4874089C := R21
 98 [-]: CLOSURE   R21 19       ; R21 := closure(Function #20)
 99 [-]: MOVE      R0 R3        ; R0 := R3
100 [-]: MOVE      R0 R6        ; R0 := R6
101 [-]: SETGLOBAL R21 K28      ; onKeyUp_MENU_CANCEL := R21
102 [-]: SETGLOBAL R21 K29      ; 0xD853E536 := R21
103 [-]: CLOSURE   R21 20       ; R21 := closure(Function #21)
104 [-]: MOVE      R0 R3        ; R0 := R3
105 [-]: MOVE      R0 R5        ; R0 := R5
106 [-]: SETGLOBAL R21 K30      ; onKeyUp_MENU_GENERIC1 := R21
107 [-]: SETGLOBAL R21 K31      ; 0x9C484D9E := R21
108 [-]: CLOSURE   R21 21       ; R21 := closure(Function #22)
109 [-]: MOVE      R0 R19       ; R0 := R19
110 [-]: MOVE      R0 R20       ; R0 := R20
111 [-]: SETGLOBAL R21 K32      ; onViewportSizeChanged := R21
112 [-]: SETGLOBAL R21 K33      ; 0x3A900427 := R21
113 [-]: CLOSURE   R21 22       ; R21 := closure(Function #23)
114 [-]: MOVE      R0 R4        ; R0 := R4
115 [-]: SETGLOBAL R21 K34      ; ComponentFocused := R21
116 [-]: SETGLOBAL R21 K35      ; 0xFE438C75 := R21
117 [-]: CLOSURE   R21 23       ; R21 := closure(Function #24)
118 [-]: MOVE      R0 R4        ; R0 := R4
119 [-]: SETGLOBAL R21 K36      ; ComponentUnfocused := R21
120 [-]: SETGLOBAL R21 K37      ; 0xC431395 := R21
121 [-]: CLOSURE   R21 24       ; R21 := closure(Function #25)
122 [-]: MOVE      R0 R3        ; R0 := R3
123 [-]: MOVE      R0 R4        ; R0 := R4
124 [-]: SETGLOBAL R21 K38      ; ComponentPressed := R21
125 [-]: SETGLOBAL R21 K39      ; 0x5A3E489E := R21
126 [-]: CLOSURE   R21 25       ; R21 := closure(Function #26)
127 [-]: MOVE      R0 R3        ; R0 := R3
128 [-]: MOVE      R0 R4        ; R0 := R4
129 [-]: CLOSURE   R22 26       ; R22 := closure(Function #27)
130 [-]: MOVE      R0 R3        ; R0 := R3
131 [-]: MOVE      R0 R4        ; R0 := R4
132 [-]: CLOSURE   R23 27       ; R23 := closure(Function #28)
133 [-]: CLOSURE   R24 28       ; R24 := closure(Function #29)
134 [-]: CLOSURE   R25 29       ; R25 := closure(Function #30)
135 [-]: MOVE      R0 R21       ; R0 := R21
136 [-]: SETGLOBAL R25 K40      ; onKeyDown_MENU_UP := R25
137 [-]: SETGLOBAL R25 K41      ; 0x396F9C7A := R25
138 [-]: CLOSURE   R25 30       ; R25 := closure(Function #31)
139 [-]: MOVE      R0 R21       ; R0 := R21
140 [-]: SETGLOBAL R25 K42      ; onKeyDown_MENU_UP_FROM_ANALOG := R25
141 [-]: SETGLOBAL R25 K43      ; 0x7EF8360 := R25
142 [-]: CLOSURE   R25 31       ; R25 := closure(Function #32)
143 [-]: MOVE      R0 R22       ; R0 := R22
144 [-]: SETGLOBAL R25 K44      ; onKeyDown_MENU_DOWN := R25
145 [-]: SETGLOBAL R25 K45      ; 0x3C4BCFF3 := R25
146 [-]: CLOSURE   R25 32       ; R25 := closure(Function #33)
147 [-]: MOVE      R0 R22       ; R0 := R22
148 [-]: SETGLOBAL R25 K46      ; onKeyDown_MENU_DOWN_FROM_ANALOG := R25
149 [-]: SETGLOBAL R25 K47      ; 0x42A3C2E3 := R25
150 [-]: CLOSURE   R25 33       ; R25 := closure(Function #34)
151 [-]: MOVE      R0 R23       ; R0 := R23
152 [-]: SETGLOBAL R25 K48      ; onKeyDown_MENU_LEFT := R25
153 [-]: SETGLOBAL R25 K49      ; 0xE7520447 := R25
154 [-]: CLOSURE   R25 34       ; R25 := closure(Function #35)
155 [-]: MOVE      R0 R23       ; R0 := R23
156 [-]: SETGLOBAL R25 K50      ; onKeyDown_MENU_LEFT_FROM_ANALOG := R25
157 [-]: SETGLOBAL R25 K51      ; 0x7EA32551 := R25
158 [-]: CLOSURE   R25 35       ; R25 := closure(Function #36)
159 [-]: MOVE      R0 R24       ; R0 := R24
160 [-]: SETGLOBAL R25 K52      ; onKeyDown_MENU_RIGHT := R25
161 [-]: SETGLOBAL R25 K53      ; 0xD9B90793 := R25
162 [-]: CLOSURE   R25 36       ; R25 := closure(Function #37)
163 [-]: MOVE      R0 R24       ; R0 := R24
164 [-]: SETGLOBAL R25 K54      ; onKeyDown_MENU_RIGHT_FROM_ANALOG := R25
165 [-]: SETGLOBAL R25 K55      ; 0x80AA3206 := R25
166 [-]: CLOSURE   R25 37       ; R25 := closure(Function #38)
167 [-]: MOVE      R0 R3        ; R0 := R3
168 [-]: MOVE      R0 R4        ; R0 := R4
169 [-]: SETGLOBAL R25 K56      ; onKeyDown_MENU_LTRIGGER2 := R25
170 [-]: SETGLOBAL R25 K57      ; 0x9BD896E0 := R25
171 [-]: CLOSURE   R25 38       ; R25 := closure(Function #39)
172 [-]: MOVE      R0 R0        ; R0 := R0
173 [-]: SETGLOBAL R25 K58      ; RollOver := R25
174 [-]: SETGLOBAL R25 K59      ; 0x578AD1BD := R25
175 [-]: CLOSURE   R25 39       ; R25 := closure(Function #40)
176 [-]: MOVE      R0 R3        ; R0 := R3
177 [-]: MOVE      R0 R4        ; R0 := R4
178 [-]: SETGLOBAL R25 K60      ; onKeyDown_MENU_MOUSE_Z := R25
179 [-]: SETGLOBAL R25 K61      ; 0x56EAD3A9 := R25
180 [-]: RETURN    R0 1         ; return 


; Function #1:
;
; Name:            
; Defined at line: 23
; #Upvalues:       0
; #Parameters:     0
; Is_vararg:       0
; Max Stack Size:  2

  1 [-]: GETGLOBAL R0 K0        ; R0 := _T
  2 [-]: SETTABLE  R0 K1 K2     ; R0["gToolTip"] := nil
  3 [-]: RETURN    R0 1         ; return 


; Function #2:
;
; Name:            
; Defined at line: 27
; #Upvalues:       4
; #Parameters:     0
; Is_vararg:       0
; Max Stack Size:  9

  1 [-]: MOVE      R0 R1        ; R0 := R1
  2 [-]: MOVE      R0 R0        ; R0 := R0
  3 [-]: GETGLOBAL R0 K0        ; R0 := 0x52E17A90
  4 [-]: GETGLOBAL R1 K1        ; R1 := mMovie
  5 [-]: LOADK     R2 K2        ; R2 := "_root"
  6 [-]: GETGLOBAL R3 K3        ; R3 := UISys
  7 [-]: GETTABLE  R3 R3 K4     ; R3 := R3["FlashInstance_LINEAR"]
  8 [-]: NEWTABLE  R4 1 0       ; R4 := {}
  9 [-]: LOADK     R5 K5        ; R5 := "_alpha"
 10 [-]: SETLIST   R4 1 1       ; R4[(1-1)*FPF+i] := R(4+i), 1 <= i <= 1
 11 [-]: NEWTABLE  R5 1 0       ; R5 := {}
 12 [-]: LOADK     R6 K6        ; R6 := 0
 13 [-]: SETLIST   R5 1 1       ; R5[(1-1)*FPF+i] := R(5+i), 1 <= i <= 1
 14 [-]: LOADK     R6 K7        ; R6 := 0.20000000298023
 15 [-]: LOADK     R7 K6        ; R7 := 0
 16 [-]: CLOSURE   R8 0         ; R8 := closure(Function #2.1)
 17 [-]: GETUPVAL  R0 U1        ; R0 := U1
 18 [-]: GETUPVAL  R0 U2        ; R0 := U2
 19 [-]: GETUPVAL  R0 U3        ; R0 := U3
 20 [-]: CALL      R0 9 1       ; R0(R1,R2,R3,R4,R5,R6,R7,R8)
 21 [-]: RETURN    R0 1         ; return 


; Function #2.1:
;
; Name:            
; Defined at line: 30
; #Upvalues:       3
; #Parameters:     0
; Is_vararg:       0
; Max Stack Size:  10

  1 [-]: CLOSURE   R0 0         ; R0 := closure(Function #2.1.1)
  2 [-]: GETUPVAL  R0 U0        ; R0 := U0
  3 [-]: GETGLOBAL R1 K0        ; R1 := 0x52E17A90
  4 [-]: GETGLOBAL R2 K1        ; R2 := mMovie
  5 [-]: LOADK     R3 K2        ; R3 := "_root"
  6 [-]: GETGLOBAL R4 K3        ; R4 := UISys
  7 [-]: GETTABLE  R4 R4 K4     ; R4 := R4["FlashInstance_LINEAR"]
  8 [-]: NEWTABLE  R5 1 0       ; R5 := {}
  9 [-]: MOVE      R6 R0        ; R6 := R0
 10 [-]: SETLIST   R5 1 1       ; R5[(1-1)*FPF+i] := R(5+i), 1 <= i <= 1
 11 [-]: NEWTABLE  R6 1 0       ; R6 := {}
 12 [-]: LOADK     R7 K5        ; R7 := 1
 13 [-]: SETLIST   R6 1 1       ; R6[(1-1)*FPF+i] := R(6+i), 1 <= i <= 1
 14 [-]: LOADK     R7 K6        ; R7 := 0.30000001192093
 15 [-]: LOADK     R8 K7        ; R8 := 0
 16 [-]: CLOSURE   R9 1         ; R9 := closure(Function #2.1.2)
 17 [-]: GETUPVAL  R0 U1        ; R0 := U1
 18 [-]: GETUPVAL  R0 U2        ; R0 := U2
 19 [-]: CALL      R1 9 1       ; R1(R2,R3,R4,R5,R6,R7,R8,R9)
 20 [-]: RETURN    R0 1         ; return 


; Function #2.1.1:
;
; Name:            
; Defined at line: 32
; #Upvalues:       1
; #Parameters:     1
; Is_vararg:       0
; Max Stack Size:  5

  1 [-]: GETGLOBAL R1 K0        ; R1 := mMovie
  2 [-]: SELF      R1 R1 K1     ; R2 := R1; R1 := R1["0xE7F490E3"]
  3 [-]: SUB       R3 K2 R0     ; R3 := 1 - R0
  4 [-]: GETUPVAL  R4 U0        ; R4 := U0
  5 [-]: MUL       R3 R3 R4     ; R3 := R3 * R4
  6 [-]: CALL      R1 3 1       ; R1(R2,R3)
  7 [-]: RETURN    R0 1         ; return 


; Function #2.1.2:
;
; Name:            
; Defined at line: 36
; #Upvalues:       2
; #Parameters:     0
; Is_vararg:       0
; Max Stack Size:  3

  1 [-]: GETGLOBAL R0 K0        ; R0 := 0x400E7765
  2 [-]: GETUPVAL  R1 U0        ; R1 := U0
  3 [-]: CALL      R0 2 2       ; R0 := R0(R1)
  4 [-]: TEST      R0 1         ; if R0 then PC := 18
  5 [-]: JMP       18           ; PC := 18
  6 [-]: GETGLOBAL R0 K0        ; R0 := 0x400E7765
  7 [-]: GETGLOBAL R1 K1        ; R1 := _T
  8 [-]: GETUPVAL  R2 U0        ; R2 := U0
  9 [-]: GETTABLE  R1 R1 R2     ; R1 := R1[R2]
 10 [-]: CALL      R0 2 2       ; R0 := R0(R1)
 11 [-]: TEST      R0 1         ; if R0 then PC := 18
 12 [-]: JMP       18           ; PC := 18
 13 [-]: GETGLOBAL R0 K1        ; R0 := _T
 14 [-]: GETUPVAL  R1 U0        ; R1 := U0
 15 [-]: GETTABLE  R0 R0 R1     ; R0 := R0[R1]
 16 [-]: GETUPVAL  R1 U1        ; R1 := U1
 17 [-]: CALL      R0 2 1       ; R0(R1)
 18 [-]: GETGLOBAL R0 K2        ; R0 := mMovie
 19 [-]: SELF      R0 R0 K3     ; R1 := R0; R0 := R0["0xA58BB96C"]
 20 [-]: CALL      R0 2 1       ; R0(R1)
 21 [-]: RETURN    R0 1         ; return 


; Function #3:
;
; Name:            
; Defined at line: 46
; #Upvalues:       1
; #Parameters:     0
; Is_vararg:       0
; Max Stack Size:  2

  1 [-]: GETUPVAL  R0 U0        ; R0 := U0
  2 [-]: CALL      R0 1 1       ; R0()
  3 [-]: RETURN    R0 1         ; return 


; Function #4:
;
; Name:            
; Defined at line: 50
; #Upvalues:       2
; #Parameters:     0
; Is_vararg:       0
; Max Stack Size:  3

  1 [-]: GETUPVAL  R0 U0        ; R0 := U0
  2 [-]: GETTABLE  R0 R0 K0     ; R0 := R0["0x25992394"]
  3 [-]: GETGLOBAL R1 K1        ; R1 := _G
  4 [-]: GETTABLE  R1 R1 K2     ; R1 := R1["UISound_Close"]
  5 [-]: CALL      R0 2 1       ; R0(R1)
  6 [-]: MOVE      R0 R0        ; R0 := R0
  7 [-]: GETGLOBAL R1 K3        ; R1 := _T
  8 [-]: GETTABLE  R1 R1 K4     ; R1 := R1["BackgroundMovie"]
  9 [-]: EQ        1 R1 K5      ; if R1 == nil then PC := 16
 10 [-]: JMP       16           ; PC := 16
 11 [-]: GETGLOBAL R1 K3        ; R1 := _T
 12 [-]: GETTABLE  R1 R1 K6     ; R1 := R1["0x1632CF80"]
 13 [-]: LOADK     R2 K7        ; R2 := "ItemBrowsing"
 14 [-]: CALL      R1 2 2       ; R1 := R1(R2)
 15 [-]: MOVE      R0 R1        ; R0 := R1
 16 [-]: TEST      R0 0         ; if not R0 then PC := 22
 17 [-]: JMP       22           ; PC := 22
 18 [-]: GETGLOBAL R1 K3        ; R1 := _T
 19 [-]: GETTABLE  R1 R1 K8     ; R1 := R1["0xB92B95FB"]
 20 [-]: CALL      R1 1 1       ; R1()
 21 [-]: JMP       24           ; PC := 24
 22 [-]: GETUPVAL  R1 U1        ; R1 := U1
 23 [-]: CALL      R1 1 1       ; R1()
 24 [-]: RETURN    R0 1         ; return 


; Function #5:
;
; Name:            
; Defined at line: 63
; #Upvalues:       3
; #Parameters:     0
; Is_vararg:       0
; Max Stack Size:  3

  1 [-]: NEWTABLE  R0 0 0       ; R0 := {}
  2 [-]: MOVE      R0 R0        ; R0 := R0
  3 [-]: GETUPVAL  R0 U1        ; R0 := U1
  4 [-]: SELF      R0 R0 K0     ; R1 := R0; R0 := R0["0x9D2060CB"]
  5 [-]: CLOSURE   R2 0         ; R2 := closure(Function #5.1)
  6 [-]: GETUPVAL  R0 U0        ; R0 := U0
  7 [-]: CALL      R0 3 1       ; R0(R1,R2)
  8 [-]: GETUPVAL  R0 U2        ; R0 := U2
  9 [-]: CALL      R0 1 1       ; R0()
 10 [-]: RETURN    R0 1         ; return 


; Function #5.1:
;
; Name:            
; Defined at line: 67
; #Upvalues:       1
; #Parameters:     1
; Is_vararg:       0
; Max Stack Size:  4

  1 [-]: GETTABLE  R1 R0 K0     ; R1 := R0["mSelected"]
  2 [-]: TEST      R1 0         ; if not R1 then PC := 9
  3 [-]: JMP       9            ; PC := 9
  4 [-]: GETGLOBAL R1 K1        ; R1 := table
  5 [-]: GETTABLE  R1 R1 K2     ; R1 := R1["0xE6450C9D"]
  6 [-]: GETUPVAL  R2 U0        ; R2 := U0
  7 [-]: MOVE      R3 R0        ; R3 := R0
  8 [-]: CALL      R1 3 1       ; R1(R2,R3)
  9 [-]: RETURN    R0 1         ; return 


; Function #6:
;
; Name:            
; Defined at line: 76
; #Upvalues:       6
; #Parameters:     0
; Is_vararg:       0
; Max Stack Size:  6

  1 [-]: GETGLOBAL R0 K0        ; R0 := 0x93B1256B
  2 [-]: LOADK     R1 K1        ; R1 := "InitializeSettings()"
  3 [-]: CALL      R0 2 1       ; R0(R1)
  4 [-]: GETGLOBAL R0 K2        ; R0 := 0x329BDC44
  5 [-]: LOADK     R1 K3        ; R1 := "EE.Interface.Components.List"
  6 [-]: CALL      R0 2 2       ; R0 := R0(R1)
  7 [-]: GETTABLE  R1 R0 K4     ; R1 := R0["0xB40DEC3F"]
  8 [-]: GETGLOBAL R2 K5        ; R2 := mMovie
  9 [-]: LOADK     R3 K6        ; R3 := "Container.Component1"
 10 [-]: CALL      R1 3 2       ; R1 := R1(R2,R3)
 11 [-]: MOVE      R1 R0        ; R1 := R0
 12 [-]: GETUPVAL  R1 U0        ; R1 := U0
 13 [-]: SELF      R1 R1 K7     ; R2 := R1; R1 := R1["0xE13A565"]
 14 [-]: LOADK     R3 K8        ; R3 := "ComponentPressed"
 15 [-]: LOADK     R4 K9        ; R4 := "ComponentFocused"
 16 [-]: LOADK     R5 K10       ; R5 := "ComponentUnfocused"
 17 [-]: CALL      R1 5 1       ; R1(R2,R3,R4,R5)
 18 [-]: GETUPVAL  R1 U0        ; R1 := U0
 19 [-]: SETTABLE  R1 K11 K12   ; R1["mForcedVerticalSeparation"] := 26
 20 [-]: GETUPVAL  R1 U0        ; R1 := U0
 21 [-]: SETTABLE  R1 K13 K14   ; R1["mVisibleElements"] := 10
 22 [-]: GETUPVAL  R1 U0        ; R1 := U0
 23 [-]: SELF      R1 R1 K15    ; R2 := R1; R1 := R1["0x3DB61F37"]
 24 [-]: LOADK     R3 K16       ; R3 := "Container.ScrollBar"
 25 [-]: LOADK     R4 K17       ; R4 := -18
 26 [-]: CALL      R1 4 1       ; R1(R2,R3,R4)
 27 [-]: GETUPVAL  R1 U0        ; R1 := U0
 28 [-]: CLOSURE   R2 0         ; R2 := closure(Function #6.1)
 29 [-]: SETTABLE  R1 K18 R2    ; R1["Print"] := R2
 30 [-]: GETUPVAL  R1 U0        ; R1 := U0
 31 [-]: CLOSURE   R2 1         ; R2 := closure(Function #6.2)
 32 [-]: SETTABLE  R1 K19 R2    ; R1["mOnFocusedCallback"] := R2
 33 [-]: GETUPVAL  R1 U0        ; R1 := U0
 34 [-]: CLOSURE   R2 2         ; R2 := closure(Function #6.3)
 35 [-]: SETTABLE  R1 K20 R2    ; R1["mOnUnfocusedCallback"] := R2
 36 [-]: GETUPVAL  R1 U0        ; R1 := U0
 37 [-]: CLOSURE   R2 3         ; R2 := closure(Function #6.4)
 38 [-]: GETUPVAL  R0 U1        ; R0 := U1
 39 [-]: GETUPVAL  R0 U2        ; R0 := U2
 40 [-]: GETUPVAL  R0 U0        ; R0 := U0
 41 [-]: GETUPVAL  R0 U3        ; R0 := U3
 42 [-]: GETUPVAL  R0 U4        ; R0 := U4
 43 [-]: GETUPVAL  R0 U5        ; R0 := U5
 44 [-]: SETTABLE  R1 K21 R2    ; R1["mOnSelectedCallback"] := R2
 45 [-]: GETUPVAL  R1 U0        ; R1 := U0
 46 [-]: CLOSURE   R2 4         ; R2 := closure(Function #6.5)
 47 [-]: GETUPVAL  R0 U0        ; R0 := U0
 48 [-]: SETTABLE  R1 K22 R2    ; R1["mElementDrawCallback"] := R2
 49 [-]: RETURN    R0 1         ; return 


; Function #6.1:
;
; Name:            
; Defined at line: 85
; #Upvalues:       0
; #Parameters:     2
; Is_vararg:       0
; Max Stack Size:  2

  1 [-]: RETURN    R0 1         ; return 


; Function #6.2:
;
; Name:            
; Defined at line: 89
; #Upvalues:       0
; #Parameters:     1
; Is_vararg:       0
; Max Stack Size:  7

  1 [-]: SETTABLE  R0 K0 K1     ; R0["mFocused"] := "0x1"
  2 [-]: GETGLOBAL R1 K2        ; R1 := mMovie
  3 [-]: SELF      R1 R1 K3     ; R2 := R1; R1 := R1["0x880196A7"]
  4 [-]: GETTABLE  R3 R0 K4     ; R3 := R0["mClipName"]
  5 [-]: LOADK     R4 K5        ; R4 := "Label"
  6 [-]: LOADK     R5 K6        ; R5 := "textColor"
  7 [-]: GETGLOBAL R6 K7        ; R6 := _G
  8 [-]: GETTABLE  R6 R6 K8     ; R6 := R6["UIColor_Black"]
  9 [-]: CALL      R1 6 1       ; R1(R2,R3,R4,R5,R6)
 10 [-]: GETGLOBAL R1 K2        ; R1 := mMovie
 11 [-]: SELF      R1 R1 K3     ; R2 := R1; R1 := R1["0x880196A7"]
 12 [-]: GETTABLE  R3 R0 K4     ; R3 := R0["mClipName"]
 13 [-]: LOADK     R4 K9        ; R4 := "Bg"
 14 [-]: LOADK     R5 K10       ; R5 := "_alpha"
 15 [-]: LOADK     R6 K11       ; R6 := 100
 16 [-]: CALL      R1 6 1       ; R1(R2,R3,R4,R5,R6)
 17 [-]: GETGLOBAL R1 K2        ; R1 := mMovie
 18 [-]: SELF      R1 R1 K3     ; R2 := R1; R1 := R1["0x880196A7"]
 19 [-]: GETTABLE  R3 R0 K4     ; R3 := R0["mClipName"]
 20 [-]: LOADK     R4 K9        ; R4 := "Bg"
 21 [-]: LOADK     R5 K12       ; R5 := "_color"
 22 [-]: GETGLOBAL R6 K7        ; R6 := _G
 23 [-]: GETTABLE  R6 R6 K13    ; R6 := R6["UIColor_LightBlue"]
 24 [-]: CALL      R1 6 1       ; R1(R2,R3,R4,R5,R6)
 25 [-]: RETURN    R0 1         ; return 


; Function #6.3:
;
; Name:            
; Defined at line: 96
; #Upvalues:       0
; #Parameters:     1
; Is_vararg:       0
; Max Stack Size:  7

  1 [-]: SETTABLE  R0 K0 K1     ; R0["mFocused"] := "0x0"
  2 [-]: GETGLOBAL R1 K2        ; R1 := mMovie
  3 [-]: SELF      R1 R1 K3     ; R2 := R1; R1 := R1["0x880196A7"]
  4 [-]: GETTABLE  R3 R0 K4     ; R3 := R0["mClipName"]
  5 [-]: LOADK     R4 K5        ; R4 := "Label"
  6 [-]: LOADK     R5 K6        ; R5 := "textColor"
  7 [-]: GETGLOBAL R6 K7        ; R6 := _G
  8 [-]: GETTABLE  R6 R6 K8     ; R6 := R6["UIColor_LightBlue"]
  9 [-]: CALL      R1 6 1       ; R1(R2,R3,R4,R5,R6)
 10 [-]: GETGLOBAL R1 K2        ; R1 := mMovie
 11 [-]: SELF      R1 R1 K3     ; R2 := R1; R1 := R1["0x880196A7"]
 12 [-]: GETTABLE  R3 R0 K4     ; R3 := R0["mClipName"]
 13 [-]: LOADK     R4 K9        ; R4 := "Bg"
 14 [-]: LOADK     R5 K10       ; R5 := "_alpha"
 15 [-]: LOADK     R6 K11       ; R6 := 40
 16 [-]: CALL      R1 6 1       ; R1(R2,R3,R4,R5,R6)
 17 [-]: GETGLOBAL R1 K2        ; R1 := mMovie
 18 [-]: SELF      R1 R1 K3     ; R2 := R1; R1 := R1["0x880196A7"]
 19 [-]: GETTABLE  R3 R0 K4     ; R3 := R0["mClipName"]
 20 [-]: LOADK     R4 K9        ; R4 := "Bg"
 21 [-]: LOADK     R5 K12       ; R5 := "_color"
 22 [-]: GETGLOBAL R6 K7        ; R6 := _G
 23 [-]: GETTABLE  R6 R6 K13    ; R6 := R6["UIColor_DarkGrey"]
 24 [-]: CALL      R1 6 1       ; R1(R2,R3,R4,R5,R6)
 25 [-]: RETURN    R0 1         ; return 


; Function #6.4:
;
; Name:            
; Defined at line: 103
; #Upvalues:       6
; #Parameters:     1
; Is_vararg:       0
; Max Stack Size:  6

  1 [-]: GETGLOBAL R1 K0        ; R1 := Engine
  2 [-]: GETTABLE  R1 R1 K1     ; R1 := R1["0x9490FE70"]
  3 [-]: CALL      R1 1 2       ; R1 := R1()
  4 [-]: TEST      R1 1         ; if R1 then PC := 21
  5 [-]: JMP       21           ; PC := 21
  6 [-]: GETTABLE  R1 R0 K2     ; R1 := R0["mSelected"]
  7 [-]: TEST      R1 0         ; if not R1 then PC := 18
  8 [-]: JMP       18           ; PC := 18
  9 [-]: GETGLOBAL R1 K3        ; R1 := 0x58E5C2DB
 10 [-]: CALL      R1 1 2       ; R1 := R1()
 11 [-]: GETUPVAL  R2 U0        ; R2 := U0
 12 [-]: SUB       R1 R1 R2     ; R1 := R1 - R2
 13 [-]: LT        0 R1 K4      ; if R1 >= 0.5 then PC := 18
 14 [-]: JMP       18           ; PC := 18
 15 [-]: GETUPVAL  R1 U1        ; R1 := U1
 16 [-]: CALL      R1 1 1       ; R1()
 17 [-]: RETURN    R0 1         ; return 
 18 [-]: GETGLOBAL R1 K3        ; R1 := 0x58E5C2DB
 19 [-]: CALL      R1 1 2       ; R1 := R1()
 20 [-]: MOVE      R1 R0        ; R1 := R0
 21 [-]: GETTABLE  R1 R0 K2     ; R1 := R0["mSelected"]
 22 [-]: MOVE      R1 R1        ; R1 := R1
 23 [-]: SETTABLE  R0 K2 R1     ; R0["mSelected"] := R1
 24 [-]: GETUPVAL  R1 U2        ; R1 := U2
 25 [-]: GETTABLE  R1 R1 K5     ; R1 := R1["0xA372F64A"]
 26 [-]: MOVE      R2 R0        ; R2 := R0
 27 [-]: CALL      R1 2 1       ; R1(R2)
 28 [-]: GETUPVAL  R1 U3        ; R1 := U3
 29 [-]: GETUPVAL  R2 U4        ; R2 := U4
 30 [-]: GETTABLE  R2 R2 K6     ; R2 := R2["0xF81722A2"]
 31 [-]: GETTABLE  R3 R0 K2     ; R3 := R0["mSelected"]
 32 [-]: LOADK     R4 K7        ; R4 := 1
 33 [-]: LOADK     R5 K8        ; R5 := -1
 34 [-]: CALL      R2 4 2       ; R2 := R2(R3,R4,R5)
 35 [-]: ADD       R1 R1 R2     ; R1 := R1 + R2
 36 [-]: MOVE      R1 R3        ; R1 := R3
 37 [-]: GETUPVAL  R1 U5        ; R1 := U5
 38 [-]: SELF      R1 R1 K9     ; R2 := R1; R1 := R1["0xE2A2E3AC"]
 39 [-]: GETUPVAL  R3 U3        ; R3 := U3
 40 [-]: LT        1 K10 R3     ; if 0 < R3 then PC := 43
 41 [-]: JMP       43           ; PC := 43
 42 [-]: MOVE      R3 R0        ; R3 := R0
 43 [-]: MOVE      R3 R1        ; R3 := R1
 44 [-]: CALL      R1 3 1       ; R1(R2,R3)
 45 [-]: RETURN    R0 1         ; return 


; Function #6.5:
;
; Name:            
; Defined at line: 119
; #Upvalues:       1
; #Parameters:     1
; Is_vararg:       0
; Max Stack Size:  7

  1 [-]: GETGLOBAL R1 K0        ; R1 := mMovie
  2 [-]: SELF      R1 R1 K1     ; R2 := R1; R1 := R1["0x880196A7"]
  3 [-]: GETTABLE  R3 R0 K2     ; R3 := R0["mClipName"]
  4 [-]: LOADK     R4 K3        ; R4 := "CheckMark"
  5 [-]: LOADK     R5 K4        ; R5 := "_visible"
  6 [-]: GETTABLE  R6 R0 K5     ; R6 := R0["mSelected"]
  7 [-]: CALL      R1 6 1       ; R1(R2,R3,R4,R5,R6)
  8 [-]: GETGLOBAL R1 K0        ; R1 := mMovie
  9 [-]: SELF      R1 R1 K6     ; R2 := R1; R1 := R1["0x17028E8F"]
 10 [-]: GETTABLE  R3 R0 K2     ; R3 := R0["mClipName"]
 11 [-]: LOADK     R4 K7        ; R4 := ".Label.text"
 12 [-]: CONCAT    R3 R3 R4     ; R3 := R3 .. R4
 13 [-]: GETTABLE  R4 R0 K8     ; R4 := R0["mName"]
 14 [-]: CALL      R1 4 1       ; R1(R2,R3,R4)
 15 [-]: GETTABLE  R1 R0 K9     ; R1 := R0["mFocused"]
 16 [-]: TEST      R1 1         ; if R1 then PC := 23
 17 [-]: JMP       23           ; PC := 23
 18 [-]: GETUPVAL  R1 U0        ; R1 := U0
 19 [-]: GETTABLE  R1 R1 K10    ; R1 := R1["0x490928C6"]
 20 [-]: MOVE      R2 R0        ; R2 := R0
 21 [-]: CALL      R1 2 1       ; R1(R2)
 22 [-]: JMP       27           ; PC := 27
 23 [-]: GETUPVAL  R1 U0        ; R1 := U0
 24 [-]: GETTABLE  R1 R1 K11    ; R1 := R1["0xCAB0A8A1"]
 25 [-]: MOVE      R2 R0        ; R2 := R0
 26 [-]: CALL      R1 2 1       ; R1(R2)
 27 [-]: RETURN    R0 1         ; return 


; Function #7:
;
; Name:            
; Defined at line: 130
; #Upvalues:       3
; #Parameters:     0
; Is_vararg:       0
; Max Stack Size:  3

  1 [-]: GETUPVAL  R0 U0        ; R0 := U0
  2 [-]: TEST      R0 0         ; if not R0 then PC := 9
  3 [-]: JMP       9            ; PC := 9
  4 [-]: GETGLOBAL R0 K0        ; R0 := 0x400E7765
  5 [-]: GETGLOBAL R1 K1        ; R1 := mMovie
  6 [-]: CALL      R0 2 2       ; R0 := R0(R1)
  7 [-]: TEST      R0 0         ; if not R0 then PC := 10
  8 [-]: JMP       10           ; PC := 10
  9 [-]: RETURN    R0 1         ; return 
 10 [-]: GETGLOBAL R0 K1        ; R0 := mMovie
 11 [-]: SELF      R0 R0 K2     ; R1 := R0; R0 := R0["0x80D6B1A"]
 12 [-]: GETGLOBAL R2 K3        ; R2 := 0x4CDEF9FF
 13 [-]: CALL      R2 1 0       ; R2,... := R2()
 14 [-]: CALL      R0 0 1       ; R0(R1,...)
 15 [-]: GETGLOBAL R0 K0        ; R0 := 0x400E7765
 16 [-]: GETUPVAL  R1 U1        ; R1 := U1
 17 [-]: CALL      R0 2 2       ; R0 := R0(R1)
 18 [-]: TEST      R0 1         ; if R0 then PC := 25
 19 [-]: JMP       25           ; PC := 25
 20 [-]: GETUPVAL  R0 U1        ; R0 := U1
 21 [-]: SELF      R0 R0 K4     ; R1 := R0; R0 := R0["0x8C7099E9"]
 22 [-]: GETGLOBAL R2 K3        ; R2 := 0x4CDEF9FF
 23 [-]: CALL      R2 1 0       ; R2,... := R2()
 24 [-]: CALL      R0 0 1       ; R0(R1,...)
 25 [-]: GETGLOBAL R0 K0        ; R0 := 0x400E7765
 26 [-]: GETUPVAL  R1 U2        ; R1 := U2
 27 [-]: GETTABLE  R1 R1 K5     ; R1 := R1["mScrollBar"]
 28 [-]: CALL      R0 2 2       ; R0 := R0(R1)
 29 [-]: TEST      R0 1         ; if R0 then PC := 37
 30 [-]: JMP       37           ; PC := 37
 31 [-]: GETUPVAL  R0 U2        ; R0 := U2
 32 [-]: GETTABLE  R0 R0 K5     ; R0 := R0["mScrollBar"]
 33 [-]: SELF      R0 R0 K4     ; R1 := R0; R0 := R0["0x8C7099E9"]
 34 [-]: GETGLOBAL R2 K3        ; R2 := 0x4CDEF9FF
 35 [-]: CALL      R2 1 0       ; R2,... := R2()
 36 [-]: CALL      R0 0 1       ; R0(R1,...)
 37 [-]: RETURN    R0 1         ; return 


; Function #8:
;
; Name:            
; Defined at line: 146
; #Upvalues:       10
; #Parameters:     0
; Is_vararg:       0
; Max Stack Size:  17

  1 [-]: GETUPVAL  R0 U0        ; R0 := U0
  2 [-]: EQ        0 R0 K0      ; if R0 ~= nil then PC := 19
  3 [-]: JMP       19           ; PC := 19
  4 [-]: GETUPVAL  R0 U1        ; R0 := U1
  5 [-]: ADD       R0 R0 K1     ; R0 := R0 + 1
  6 [-]: MOVE      R0 R1        ; R0 := R1
  7 [-]: GETUPVAL  R0 U1        ; R0 := U1
  8 [-]: LT        0 R0 K2      ; if R0 >= 10 then PC := 16
  9 [-]: JMP       16           ; PC := 16
 10 [-]: GETUPVAL  R0 U2        ; R0 := U2
 11 [-]: SELF      R0 R0 K3     ; R1 := R0; R0 := R0["0x61494587"]
 12 [-]: LOADK     R2 K4        ; R2 := 0.10000000149012
 13 [-]: GETUPVAL  R3 U3        ; R3 := U3
 14 [-]: CALL      R0 4 1       ; R0(R1,R2,R3)
 15 [-]: JMP       18           ; PC := 18
 16 [-]: GETUPVAL  R0 U4        ; R0 := U4
 17 [-]: CALL      R0 1 1       ; R0()
 18 [-]: RETURN    R0 1         ; return 
 19 [-]: GETGLOBAL R0 K5        ; R0 := 0x400E7765
 20 [-]: GETGLOBAL R1 K6        ; R1 := _T
 21 [-]: GETUPVAL  R2 U0        ; R2 := U0
 22 [-]: GETTABLE  R1 R1 R2     ; R1 := R1[R2]
 23 [-]: CALL      R0 2 2       ; R0 := R0(R1)
 24 [-]: TEST      R0 1         ; if R0 then PC := 45
 25 [-]: JMP       45           ; PC := 45
 26 [-]: GETGLOBAL R0 K6        ; R0 := _T
 27 [-]: GETUPVAL  R1 U0        ; R1 := U0
 28 [-]: GETTABLE  R0 R0 R1     ; R0 := R0[R1]
 29 [-]: CALL      R0 1 2       ; R0 := R0()
 30 [-]: LOADK     R1 K1        ; R1 := 1
 31 [-]: LEN       R2 R0        ; R2 := # R0
 32 [-]: LOADK     R3 K1        ; R3 := 1
 33 [-]: FORPREP   R1 44        ; R1 -= R3; PC := 44
 34 [-]: GETGLOBAL R5 K7        ; R5 := 0x1BF588C6
 35 [-]: LOADK     R6 K8        ; R6 := 0
 36 [-]: CALL      R5 2 1       ; R5(R6)
 37 [-]: GETTABLE  R5 R0 R4     ; R5 := R0[R4]
 38 [-]: SETTABLE  R5 K9 R4     ; R5["Id"] := R4
 39 [-]: GETUPVAL  R5 U5        ; R5 := U5
 40 [-]: SELF      R5 R5 K10    ; R6 := R5; R5 := R5["0xA77DA8EE"]
 41 [-]: GETTABLE  R7 R0 R4     ; R7 := R0[R4]
 42 [-]: MOVE      R8 R1        ; R8 := R1
 43 [-]: CALL      R5 4 1       ; R5(R6,R7,R8)
 44 [-]: FORLOOP   R1 34        ; R1 += R3; if R1 <= R2 then begin PC := 34; R4 := R1 end
 45 [-]: GETGLOBAL R5 K11       ; R5 := 0x329BDC44
 46 [-]: LOADK     R6 K12       ; R6 := "Lotus.Interface.Components.Button"
 47 [-]: CALL      R5 2 2       ; R5 := R5(R6)
 48 [-]: GETTABLE  R6 R5 K13    ; R6 := R5["0xF232C660"]
 49 [-]: GETGLOBAL R7 K14       ; R7 := mMovie
 50 [-]: LOADK     R8 K15       ; R8 := "Container.ConfirmBtn"
 51 [-]: LOADK     R9 K16       ; R9 := "/Lotus/Language/Menu/Global_Confirm"
 52 [-]: LOADK     R10 K17      ; R10 := "FinishSelection"
 53 [-]: LOADK     R11 K18      ; R11 := "<MENU_GEENRIC1>"
 54 [-]: CALL      R6 6 2       ; R6 := R6(R7,R8,R9,R10,R11)
 55 [-]: MOVE      R6 R6        ; R6 := R6
 56 [-]: GETUPVAL  R6 U6        ; R6 := U6
 57 [-]: SELF      R6 R6 K19    ; R7 := R6; R6 := R6["0xE2A2E3AC"]
 58 [-]: MOVE      R8 R0        ; R8 := R0
 59 [-]: CALL      R6 3 1       ; R6(R7,R8)
 60 [-]: GETUPVAL  R6 U6        ; R6 := U6
 61 [-]: SELF      R6 R6 K20    ; R7 := R6; R6 := R6["0x6470BAF4"]
 62 [-]: CALL      R6 2 1       ; R6(R7)
 63 [-]: GETTABLE  R6 R5 K13    ; R6 := R5["0xF232C660"]
 64 [-]: GETGLOBAL R7 K14       ; R7 := mMovie
 65 [-]: LOADK     R8 K21       ; R8 := "Container.CancelBtn"
 66 [-]: LOADK     R9 K22       ; R9 := "/Menu/Confirm_Item_Cancel"
 67 [-]: LOADK     R10 K23      ; R10 := "ExitScreen"
 68 [-]: LOADK     R11 K24      ; R11 := "<MENU_CANCEL>"
 69 [-]: CALL      R6 6 2       ; R6 := R6(R7,R8,R9,R10,R11)
 70 [-]: MOVE      R6 R7        ; R6 := R7
 71 [-]: GETUPVAL  R6 U7        ; R6 := U7
 72 [-]: SELF      R6 R6 K20    ; R7 := R6; R6 := R6["0x6470BAF4"]
 73 [-]: CALL      R6 2 1       ; R6(R7)
 74 [-]: GETUPVAL  R6 U5        ; R6 := U5
 75 [-]: SELF      R6 R6 K20    ; R7 := R6; R6 := R6["0x6470BAF4"]
 76 [-]: CALL      R6 2 1       ; R6(R7)
 77 [-]: GETGLOBAL R6 K25       ; R6 := math
 78 [-]: GETTABLE  R6 R6 K26    ; R6 := R6["0x8B011038"]
 79 [-]: GETGLOBAL R7 K25       ; R7 := math
 80 [-]: GETTABLE  R7 R7 K27    ; R7 := R7["0x65F9712A"]
 81 [-]: GETUPVAL  R8 U5        ; R8 := U5
 82 [-]: SELF      R8 R8 K28    ; R9 := R8; R8 := R8["0xC51A5C9D"]
 83 [-]: CALL      R8 2 2       ; R8 := R8(R9)
 84 [-]: GETUPVAL  R9 U5        ; R9 := U5
 85 [-]: GETTABLE  R9 R9 K29    ; R9 := R9["mVisibleElements"]
 86 [-]: CALL      R7 3 2       ; R7 := R7(R8,R9)
 87 [-]: GETUPVAL  R8 U5        ; R8 := U5
 88 [-]: GETTABLE  R8 R8 K30    ; R8 := R8["mForcedVerticalSeparation"]
 89 [-]: MUL       R7 R7 R8     ; R7 := R7 * R8
 90 [-]: ADD       R7 K31 R7    ; R7 := 100 + R7
 91 [-]: LOADK     R8 K32       ; R8 := 200
 92 [-]: CALL      R6 3 2       ; R6 := R6(R7,R8)
 93 [-]: GETGLOBAL R7 K14       ; R7 := mMovie
 94 [-]: SELF      R7 R7 K33    ; R8 := R7; R7 := R7["0x1C19D966"]
 95 [-]: LOADK     R9 K15       ; R9 := "Container.ConfirmBtn"
 96 [-]: LOADK     R10 K34      ; R10 := "_y"
 97 [-]: SUB       R11 R6 K35   ; R11 := R6 - 15
 98 [-]: CALL      R7 5 1       ; R7(R8,R9,R10,R11)
 99 [-]: GETGLOBAL R7 K14       ; R7 := mMovie
100 [-]: SELF      R7 R7 K33    ; R8 := R7; R7 := R7["0x1C19D966"]
101 [-]: LOADK     R9 K21       ; R9 := "Container.CancelBtn"
102 [-]: LOADK     R10 K34      ; R10 := "_y"
103 [-]: SUB       R11 R6 K35   ; R11 := R6 - 15
104 [-]: CALL      R7 5 1       ; R7(R8,R9,R10,R11)
105 [-]: GETUPVAL  R7 U8        ; R7 := U8
106 [-]: GETTABLE  R7 R7 K36    ; R7 := R7["0xB57E56DF"]
107 [-]: GETGLOBAL R8 K14       ; R8 := mMovie
108 [-]: SELF      R8 R8 K37    ; R9 := R8; R8 := R8["0x68998E7D"]
109 [-]: CALL      R8 2 2       ; R8 := R8(R9)
110 [-]: SUB       R8 R8 R6     ; R8 := R8 - R6
111 [-]: DIV       R8 R8 K38    ; R8 := R8 / 2
112 [-]: CALL      R7 2 2       ; R7 := R7(R8)
113 [-]: GETGLOBAL R8 K14       ; R8 := mMovie
114 [-]: SELF      R8 R8 K33    ; R9 := R8; R8 := R8["0x1C19D966"]
115 [-]: LOADK     R10 K39      ; R10 := "BgFill"
116 [-]: LOADK     R11 K34      ; R11 := "_y"
117 [-]: MOVE      R12 R7       ; R12 := R7
118 [-]: CALL      R8 5 1       ; R8(R9,R10,R11,R12)
119 [-]: GETGLOBAL R8 K14       ; R8 := mMovie
120 [-]: SELF      R8 R8 K33    ; R9 := R8; R8 := R8["0x1C19D966"]
121 [-]: LOADK     R10 K40      ; R10 := "Container"
122 [-]: LOADK     R11 K34      ; R11 := "_y"
123 [-]: MOVE      R12 R7       ; R12 := R7
124 [-]: CALL      R8 5 1       ; R8(R9,R10,R11,R12)
125 [-]: GETGLOBAL R8 K14       ; R8 := mMovie
126 [-]: SELF      R8 R8 K33    ; R9 := R8; R8 := R8["0x1C19D966"]
127 [-]: LOADK     R10 K41      ; R10 := "BgUpperLine"
128 [-]: LOADK     R11 K34      ; R11 := "_y"
129 [-]: MOVE      R12 R7       ; R12 := R7
130 [-]: CALL      R8 5 1       ; R8(R9,R10,R11,R12)
131 [-]: GETGLOBAL R8 K14       ; R8 := mMovie
132 [-]: SELF      R8 R8 K33    ; R9 := R8; R8 := R8["0x1C19D966"]
133 [-]: LOADK     R10 K42      ; R10 := "BgLowerLine"
134 [-]: LOADK     R11 K34      ; R11 := "_y"
135 [-]: ADD       R12 R7 R6    ; R12 := R7 + R6
136 [-]: CALL      R8 5 1       ; R8(R9,R10,R11,R12)
137 [-]: GETGLOBAL R8 K14       ; R8 := mMovie
138 [-]: SELF      R8 R8 K33    ; R9 := R8; R8 := R8["0x1C19D966"]
139 [-]: LOADK     R10 K43      ; R10 := "Container.Message"
140 [-]: LOADK     R11 K44      ; R11 := "_visible"
141 [-]: GETUPVAL  R12 U5       ; R12 := U5
142 [-]: SELF      R12 R12 K28  ; R13 := R12; R12 := R12["0xC51A5C9D"]
143 [-]: CALL      R12 2 2      ; R12 := R12(R13)
144 [-]: EQ        1 R12 K8     ; if R12 == 0 then PC := 147
145 [-]: JMP       147          ; PC := 147
146 [-]: MOVE      R12 R0       ; R12 := R0
147 [-]: MOVE      R12 R1       ; R12 := R1
148 [-]: CALL      R8 5 1       ; R8(R9,R10,R11,R12)
149 [-]: GETGLOBAL R8 K45       ; R8 := 0x52E17A90
150 [-]: GETGLOBAL R9 K14       ; R9 := mMovie
151 [-]: LOADK     R10 K46      ; R10 := "_root"
152 [-]: GETGLOBAL R11 K47      ; R11 := UISys
153 [-]: GETTABLE  R11 R11 K48  ; R11 := R11["FlashInstance_EASE_OUT_ELASTIC"]
154 [-]: NEWTABLE  R12 2 0      ; R12 := {}
155 [-]: LOADK     R13 K49      ; R13 := "_alpha"
156 [-]: LOADK     R14 K50      ; R14 := "_z"
157 [-]: SETLIST   R12 2 1      ; R12[(1-1)*FPF+i] := R(12+i), 1 <= i <= 2
158 [-]: NEWTABLE  R13 2 0      ; R13 := {}
159 [-]: LOADK     R14 K31      ; R14 := 100
160 [-]: LOADK     R15 K8       ; R15 := 0
161 [-]: SETLIST   R13 2 1      ; R13[(1-1)*FPF+i] := R(13+i), 1 <= i <= 2
162 [-]: LOADK     R14 K51      ; R14 := 0.44999998807907
163 [-]: LOADK     R15 K8       ; R15 := 0
164 [-]: CLOSURE   R16 0        ; R16 := closure(Function #8.1)
165 [-]: GETUPVAL  R0 U9        ; R0 := U9
166 [-]: CALL      R8 9 1       ; R8(R9,R10,R11,R12,R13,R14,R15,R16)
167 [-]: RETURN    R0 1         ; return 


; Function #8.1:
;
; Name:            
; Defined at line: 189
; #Upvalues:       1
; #Parameters:     0
; Is_vararg:       0
; Max Stack Size:  2

  1 [-]: MOVE      R0 R0        ; R0 := R0
  2 [-]: MOVE      R0 R0        ; R0 := R0
  3 [-]: RETURN    R0 1         ; return 


; Function #9:
;
; Name:            
; Defined at line: 194
; #Upvalues:       0
; #Parameters:     0
; Is_vararg:       0
; Max Stack Size:  6

  1 [-]: GETGLOBAL R0 K0        ; R0 := mMovie
  2 [-]: SELF      R0 R0 K1     ; R1 := R0; R0 := R0["0x1C19D966"]
  3 [-]: LOADK     R2 K2        ; R2 := "MouseCatcherBtn"
  4 [-]: LOADK     R3 K3        ; R3 := "_width"
  5 [-]: GETGLOBAL R4 K0        ; R4 := mMovie
  6 [-]: SELF      R4 R4 K4     ; R5 := R4; R4 := R4["0xF595D5E1"]
  7 [-]: CALL      R4 2 0       ; R4,... := R4(R5)
  8 [-]: CALL      R0 0 1       ; R0(R1,...)
  9 [-]: GETGLOBAL R0 K0        ; R0 := mMovie
 10 [-]: SELF      R0 R0 K1     ; R1 := R0; R0 := R0["0x1C19D966"]
 11 [-]: LOADK     R2 K2        ; R2 := "MouseCatcherBtn"
 12 [-]: LOADK     R3 K5        ; R3 := "_height"
 13 [-]: GETGLOBAL R4 K0        ; R4 := mMovie
 14 [-]: SELF      R4 R4 K6     ; R5 := R4; R4 := R4["0xEE069D65"]
 15 [-]: CALL      R4 2 0       ; R4,... := R4(R5)
 16 [-]: CALL      R0 0 1       ; R0(R1,...)
 17 [-]: RETURN    R0 1         ; return 


; Function #10:
;
; Name:            
; Defined at line: 199
; #Upvalues:       0
; #Parameters:     0
; Is_vararg:       0
; Max Stack Size:  12

  1 [-]: NEWTABLE  R0 3 0       ; R0 := {}
  2 [-]: LOADK     R1 K0        ; R1 := "BgFill"
  3 [-]: LOADK     R2 K1        ; R2 := "BgUpperLine"
  4 [-]: LOADK     R3 K2        ; R3 := "BgLowerLine"
  5 [-]: SETLIST   R0 3 1       ; R0[(1-1)*FPF+i] := R(0+i), 1 <= i <= 3
  6 [-]: GETGLOBAL R1 K3        ; R1 := 0x63B09107
  7 [-]: MOVE      R2 R0        ; R2 := R0
  8 [-]: CALL      R1 2 4       ; R1,R2,R3 := R1(R2)
  9 [-]: JMP       19           ; PC := 19
 10 [-]: GETGLOBAL R6 K4        ; R6 := mMovie
 11 [-]: SELF      R6 R6 K5     ; R7 := R6; R6 := R6["0x1C19D966"]
 12 [-]: MOVE      R8 R5        ; R8 := R5
 13 [-]: LOADK     R9 K6        ; R9 := "_width"
 14 [-]: GETGLOBAL R10 K4       ; R10 := mMovie
 15 [-]: SELF      R10 R10 K7   ; R11 := R10; R10 := R10["0xF595D5E1"]
 16 [-]: CALL      R10 2 2      ; R10 := R10(R11)
 17 [-]: ADD       R10 R10 K8   ; R10 := R10 + 200
 18 [-]: CALL      R6 5 1       ; R6(R7,R8,R9,R10)
 19 [-]: TFORLOOP  R1 2         ; R4,R5 :=  R1(R2,R3); if R4 ~= nil then begin PC = 10; R3 := R4 end
 20 [-]: JMP       10           ; PC := 10
 21 [-]: RETURN    R0 1         ; return 


; Function #11:
;
; Name:            
; Defined at line: 206
; #Upvalues:       7
; #Parameters:     0
; Is_vararg:       0
; Max Stack Size:  11

  1 [-]: GETGLOBAL R0 K0        ; R0 := 0x329BDC44
  2 [-]: LOADK     R1 K1        ; R1 := "Lotus.Interface.Libs.TimerMgr"
  3 [-]: CALL      R0 2 2       ; R0 := R0(R1)
  4 [-]: GETTABLE  R1 R0 K2     ; R1 := R0["0xC2A7FAC0"]
  5 [-]: CALL      R1 1 2       ; R1 := R1()
  6 [-]: MOVE      R1 R0        ; R1 := R0
  7 [-]: GETUPVAL  R1 U1        ; R1 := U1
  8 [-]: GETTABLE  R1 R1 K3     ; R1 := R1["0x25992394"]
  9 [-]: GETGLOBAL R2 K4        ; R2 := _G
 10 [-]: GETTABLE  R2 R2 K5     ; R2 := R2["UISound_Open"]
 11 [-]: CALL      R1 2 1       ; R1(R2)
 12 [-]: GETUPVAL  R1 U2        ; R1 := U2
 13 [-]: CALL      R1 1 1       ; R1()
 14 [-]: GETUPVAL  R1 U3        ; R1 := U3
 15 [-]: CALL      R1 1 1       ; R1()
 16 [-]: GETGLOBAL R1 K6        ; R1 := mMovie
 17 [-]: SELF      R1 R1 K7     ; R2 := R1; R1 := R1["0x1C19D966"]
 18 [-]: LOADK     R3 K8        ; R3 := "_root"
 19 [-]: LOADK     R4 K9        ; R4 := "_alpha"
 20 [-]: LOADK     R5 K10       ; R5 := 0
 21 [-]: CALL      R1 5 1       ; R1(R2,R3,R4,R5)
 22 [-]: GETGLOBAL R1 K6        ; R1 := mMovie
 23 [-]: SELF      R1 R1 K7     ; R2 := R1; R1 := R1["0x1C19D966"]
 24 [-]: LOADK     R3 K8        ; R3 := "_root"
 25 [-]: LOADK     R4 K11       ; R4 := "_z"
 26 [-]: LOADK     R5 K12       ; R5 := -15000
 27 [-]: CALL      R1 5 1       ; R1(R2,R3,R4,R5)
 28 [-]: CLOSURE   R1 0         ; R1 := closure(Function #11.1)
 29 [-]: GETUPVAL  R0 U4        ; R0 := U4
 30 [-]: GETGLOBAL R2 K13       ; R2 := 0x52E17A90
 31 [-]: GETGLOBAL R3 K6        ; R3 := mMovie
 32 [-]: LOADK     R4 K8        ; R4 := "_root"
 33 [-]: GETGLOBAL R5 K14       ; R5 := UISys
 34 [-]: GETTABLE  R5 R5 K15    ; R5 := R5["FlashInstance_LINEAR"]
 35 [-]: NEWTABLE  R6 1 0       ; R6 := {}
 36 [-]: MOVE      R7 R1        ; R7 := R1
 37 [-]: SETLIST   R6 1 1       ; R6[(1-1)*FPF+i] := R(6+i), 1 <= i <= 1
 38 [-]: NEWTABLE  R7 1 0       ; R7 := {}
 39 [-]: LOADK     R8 K16       ; R8 := 1
 40 [-]: SETLIST   R7 1 1       ; R7[(1-1)*FPF+i] := R(7+i), 1 <= i <= 1
 41 [-]: LOADK     R8 K17       ; R8 := 0.15000000596046
 42 [-]: LOADK     R9 K10       ; R9 := 0
 43 [-]: CLOSURE   R10 1        ; R10 := closure(Function #11.2)
 44 [-]: GETUPVAL  R0 U5        ; R0 := U5
 45 [-]: CALL      R2 9 1       ; R2(R3,R4,R5,R6,R7,R8,R9,R10)
 46 [-]: MOVE      R2 R1        ; R2 := R1
 47 [-]: MOVE      R2 R6        ; R2 := R6
 48 [-]: RETURN    R0 1         ; return 


; Function #11.1:
;
; Name:            
; Defined at line: 219
; #Upvalues:       1
; #Parameters:     1
; Is_vararg:       0
; Max Stack Size:  4

  1 [-]: GETGLOBAL R1 K0        ; R1 := mMovie
  2 [-]: SELF      R1 R1 K1     ; R2 := R1; R1 := R1["0xE7F490E3"]
  3 [-]: GETUPVAL  R3 U0        ; R3 := U0
  4 [-]: MUL       R3 R0 R3     ; R3 := R0 * R3
  5 [-]: CALL      R1 3 1       ; R1(R2,R3)
  6 [-]: RETURN    R0 1         ; return 


; Function #11.2:
;
; Name:            
; Defined at line: 223
; #Upvalues:       1
; #Parameters:     0
; Is_vararg:       0
; Max Stack Size:  2

  1 [-]: GETUPVAL  R0 U0        ; R0 := U0
  2 [-]: CALL      R0 1 1       ; R0()
  3 [-]: RETURN    R0 1         ; return 


; Function #12:
;
; Name:            
; Defined at line: 230
; #Upvalues:       0
; #Parameters:     1
; Is_vararg:       0
; Max Stack Size:  5

  1 [-]: GETGLOBAL R1 K0        ; R1 := mMovie
  2 [-]: SELF      R1 R1 K1     ; R2 := R1; R1 := R1["0x17028E8F"]
  3 [-]: LOADK     R3 K2        ; R3 := "Container.Title.text"
  4 [-]: MOVE      R4 R0        ; R4 := R0
  5 [-]: CALL      R1 4 1       ; R1(R2,R3,R4)
  6 [-]: RETURN    R0 1         ; return 


; Function #13:
;
; Name:            
; Defined at line: 234
; #Upvalues:       0
; #Parameters:     1
; Is_vararg:       0
; Max Stack Size:  6

  1 [-]: GETGLOBAL R1 K0        ; R1 := mMovie
  2 [-]: SELF      R1 R1 K1     ; R2 := R1; R1 := R1["0x1C19D966"]
  3 [-]: LOADK     R3 K2        ; R3 := "Container.Message"
  4 [-]: LOADK     R4 K3        ; R4 := "verticalAlignment"
  5 [-]: LOADK     R5 K4        ; R5 := "center"
  6 [-]: CALL      R1 5 1       ; R1(R2,R3,R4,R5)
  7 [-]: GETGLOBAL R1 K0        ; R1 := mMovie
  8 [-]: SELF      R1 R1 K5     ; R2 := R1; R1 := R1["0x17028E8F"]
  9 [-]: LOADK     R3 K6        ; R3 := "Container.Message.text"
 10 [-]: MOVE      R4 R0        ; R4 := R0
 11 [-]: CALL      R1 4 1       ; R1(R2,R3,R4)
 12 [-]: RETURN    R0 1         ; return 


; Function #14:
;
; Name:            
; Defined at line: 239
; #Upvalues:       1
; #Parameters:     1
; Is_vararg:       0
; Max Stack Size:  2

  1 [-]: MOVE      R0 R0        ; R0 := R0
  2 [-]: RETURN    R0 1         ; return 


; Function #15:
;
; Name:            
; Defined at line: 243
; #Upvalues:       1
; #Parameters:     1
; Is_vararg:       0
; Max Stack Size:  2

  1 [-]: MOVE      R0 R0        ; R0 := R0
  2 [-]: RETURN    R0 1         ; return 


; Function #16:
;
; Name:            
; Defined at line: 247
; #Upvalues:       1
; #Parameters:     0
; Is_vararg:       0
; Max Stack Size:  2

  1 [-]: GETUPVAL  R0 U0        ; R0 := U0
  2 [-]: CALL      R0 1 1       ; R0()
  3 [-]: RETURN    R0 1         ; return 


; Function #17:
;
; Name:            
; Defined at line: 251
; #Upvalues:       1
; #Parameters:     0
; Is_vararg:       0
; Max Stack Size:  2

  1 [-]: GETUPVAL  R0 U0        ; R0 := U0
  2 [-]: CALL      R0 1 1       ; R0()
  3 [-]: RETURN    R0 1         ; return 


; Function #18:
;
; Name:            
; Defined at line: 255
; #Upvalues:       1
; #Parameters:     0
; Is_vararg:       0
; Max Stack Size:  2

  1 [-]: GETUPVAL  R0 U0        ; R0 := U0
  2 [-]: CALL      R0 1 1       ; R0()
  3 [-]: RETURN    R0 1         ; return 


; Function #19:
;
; Name:            
; Defined at line: 259
; #Upvalues:       2
; #Parameters:     0
; Is_vararg:       0
; Max Stack Size:  2

  1 [-]: GETUPVAL  R0 U0        ; R0 := U0
  2 [-]: TEST      R0 1         ; if R0 then PC := 12
  3 [-]: JMP       12           ; PC := 12
  4 [-]: GETGLOBAL R0 K0        ; R0 := 0x400E7765
  5 [-]: GETUPVAL  R1 U1        ; R1 := U1
  6 [-]: CALL      R0 2 2       ; R0 := R0(R1)
  7 [-]: TEST      R0 0         ; if not R0 then PC := 12
  8 [-]: JMP       12           ; PC := 12
  9 [-]: GETUPVAL  R0 U1        ; R0 := U1
 10 [-]: SELF      R0 R0 K1     ; R1 := R0; R0 := R0["0xF41D5FCC"]
 11 [-]: CALL      R0 2 1       ; R0(R1)
 12 [-]: RETURN    R0 1         ; return 


; Function #20:
;
; Name:            
; Defined at line: 267
; #Upvalues:       2
; #Parameters:     0
; Is_vararg:       0
; Max Stack Size:  2

  1 [-]: GETUPVAL  R0 U0        ; R0 := U0
  2 [-]: TEST      R0 1         ; if R0 then PC := 7
  3 [-]: JMP       7            ; PC := 7
  4 [-]: GETUPVAL  R0 U1        ; R0 := U1
  5 [-]: SELF      R0 R0 K0     ; R1 := R0; R0 := R0["0xAA737F39"]
  6 [-]: CALL      R0 2 1       ; R0(R1)
  7 [-]: RETURN    R0 1         ; return 


; Function #21:
;
; Name:            
; Defined at line: 273
; #Upvalues:       2
; #Parameters:     0
; Is_vararg:       0
; Max Stack Size:  2

  1 [-]: GETUPVAL  R0 U0        ; R0 := U0
  2 [-]: TEST      R0 1         ; if R0 then PC := 7
  3 [-]: JMP       7            ; PC := 7
  4 [-]: GETUPVAL  R0 U1        ; R0 := U1
  5 [-]: SELF      R0 R0 K0     ; R1 := R0; R0 := R0["0xAA737F39"]
  6 [-]: CALL      R0 2 1       ; R0(R1)
  7 [-]: RETURN    R0 1         ; return 


; Function #22:
;
; Name:            
; Defined at line: 279
; #Upvalues:       2
; #Parameters:     2
; Is_vararg:       0
; Max Stack Size:  3

  1 [-]: GETUPVAL  R2 U0        ; R2 := U0
  2 [-]: CALL      R2 1 1       ; R2()
  3 [-]: GETUPVAL  R2 U1        ; R2 := U1
  4 [-]: CALL      R2 1 1       ; R2()
  5 [-]: RETURN    R0 1         ; return 


; Function #23:
;
; Name:            
; Defined at line: 286
; #Upvalues:       1
; #Parameters:     1
; Is_vararg:       0
; Max Stack Size:  5

  1 [-]: GETGLOBAL R1 K0        ; R1 := 0x400E7765
  2 [-]: GETUPVAL  R2 U0        ; R2 := U0
  3 [-]: CALL      R1 2 2       ; R1 := R1(R2)
  4 [-]: TEST      R1 1         ; if R1 then PC := 12
  5 [-]: JMP       12           ; PC := 12
  6 [-]: GETUPVAL  R1 U0        ; R1 := U0
  7 [-]: SELF      R1 R1 K1     ; R2 := R1; R1 := R1["0x8ABD6CC8"]
  8 [-]: GETGLOBAL R3 K2        ; R3 := 0xF595ADDE
  9 [-]: MOVE      R4 R0        ; R4 := R0
 10 [-]: CALL      R3 2 0       ; R3,... := R3(R4)
 11 [-]: CALL      R1 0 1       ; R1(R2,...)
 12 [-]: RETURN    R0 1         ; return 


; Function #24:
;
; Name:            
; Defined at line: 292
; #Upvalues:       1
; #Parameters:     1
; Is_vararg:       0
; Max Stack Size:  5

  1 [-]: GETGLOBAL R1 K0        ; R1 := 0x400E7765
  2 [-]: GETUPVAL  R2 U0        ; R2 := U0
  3 [-]: CALL      R1 2 2       ; R1 := R1(R2)
  4 [-]: TEST      R1 1         ; if R1 then PC := 12
  5 [-]: JMP       12           ; PC := 12
  6 [-]: GETUPVAL  R1 U0        ; R1 := U0
  7 [-]: SELF      R1 R1 K1     ; R2 := R1; R1 := R1["0x2176B11E"]
  8 [-]: GETGLOBAL R3 K2        ; R3 := 0xF595ADDE
  9 [-]: MOVE      R4 R0        ; R4 := R0
 10 [-]: CALL      R3 2 0       ; R3,... := R3(R4)
 11 [-]: CALL      R1 0 1       ; R1(R2,...)
 12 [-]: RETURN    R0 1         ; return 


; Function #25:
;
; Name:            
; Defined at line: 298
; #Upvalues:       2
; #Parameters:     1
; Is_vararg:       0
; Max Stack Size:  5

  1 [-]: GETUPVAL  R1 U0        ; R1 := U0
  2 [-]: TEST      R1 1         ; if R1 then PC := 16
  3 [-]: JMP       16           ; PC := 16
  4 [-]: GETGLOBAL R1 K0        ; R1 := 0x400E7765
  5 [-]: GETUPVAL  R2 U1        ; R2 := U1
  6 [-]: CALL      R1 2 2       ; R1 := R1(R2)
  7 [-]: TEST      R1 1         ; if R1 then PC := 16
  8 [-]: JMP       16           ; PC := 16
  9 [-]: GETUPVAL  R1 U1        ; R1 := U1
 10 [-]: SELF      R1 R1 K1     ; R2 := R1; R1 := R1["0x3BC31182"]
 11 [-]: GETGLOBAL R3 K2        ; R3 := 0xF595ADDE
 12 [-]: MOVE      R4 R0        ; R4 := R0
 13 [-]: CALL      R3 2 2       ; R3 := R3(R4)
 14 [-]: MOVE      R4 R1        ; R4 := R1
 15 [-]: CALL      R1 4 1       ; R1(R2,R3,R4)
 16 [-]: RETURN    R0 1         ; return 


; Function #26:
;
; Name:            
; Defined at line: 305
; #Upvalues:       2
; #Parameters:     0
; Is_vararg:       0
; Max Stack Size:  2

  1 [-]: GETUPVAL  R0 U0        ; R0 := U0
  2 [-]: TEST      R0 1         ; if R0 then PC := 12
  3 [-]: JMP       12           ; PC := 12
  4 [-]: GETGLOBAL R0 K0        ; R0 := 0x400E7765
  5 [-]: GETUPVAL  R1 U1        ; R1 := U1
  6 [-]: CALL      R0 2 2       ; R0 := R0(R1)
  7 [-]: TEST      R0 1         ; if R0 then PC := 12
  8 [-]: JMP       12           ; PC := 12
  9 [-]: GETUPVAL  R0 U1        ; R0 := U1
 10 [-]: SELF      R0 R0 K1     ; R1 := R0; R0 := R0["0x9F72DD91"]
 11 [-]: CALL      R0 2 1       ; R0(R1)
 12 [-]: RETURN    R0 1         ; return 


; Function #27:
;
; Name:            
; Defined at line: 311
; #Upvalues:       2
; #Parameters:     0
; Is_vararg:       0
; Max Stack Size:  2

  1 [-]: GETUPVAL  R0 U0        ; R0 := U0
  2 [-]: TEST      R0 1         ; if R0 then PC := 12
  3 [-]: JMP       12           ; PC := 12
  4 [-]: GETGLOBAL R0 K0        ; R0 := 0x400E7765
  5 [-]: GETUPVAL  R1 U1        ; R1 := U1
  6 [-]: CALL      R0 2 2       ; R0 := R0(R1)
  7 [-]: TEST      R0 1         ; if R0 then PC := 12
  8 [-]: JMP       12           ; PC := 12
  9 [-]: GETUPVAL  R0 U1        ; R0 := U1
 10 [-]: SELF      R0 R0 K1     ; R1 := R0; R0 := R0["0x5AE77CF9"]
 11 [-]: CALL      R0 2 1       ; R0(R1)
 12 [-]: RETURN    R0 1         ; return 


; Function #28:
;
; Name:            
; Defined at line: 317
; #Upvalues:       0
; #Parameters:     0
; Is_vararg:       0
; Max Stack Size:  2

  1 [-]: RETURN    R0 1         ; return 


; Function #29:
;
; Name:            
; Defined at line: 320
; #Upvalues:       0
; #Parameters:     0
; Is_vararg:       0
; Max Stack Size:  2

  1 [-]: RETURN    R0 1         ; return 


; Function #30:
;
; Name:            
; Defined at line: 323
; #Upvalues:       1
; #Parameters:     0
; Is_vararg:       0
; Max Stack Size:  2

  1 [-]: GETUPVAL  R0 U0        ; R0 := U0
  2 [-]: CALL      R0 1 1       ; R0()
  3 [-]: MOVE      R0 R1        ; R0 := R1
  4 [-]: RETURN    R0 2         ; return R0
  5 [-]: RETURN    R0 1         ; return 


; Function #31:
;
; Name:            
; Defined at line: 328
; #Upvalues:       1
; #Parameters:     0
; Is_vararg:       0
; Max Stack Size:  2

  1 [-]: GETUPVAL  R0 U0        ; R0 := U0
  2 [-]: CALL      R0 1 1       ; R0()
  3 [-]: MOVE      R0 R1        ; R0 := R1
  4 [-]: RETURN    R0 2         ; return R0
  5 [-]: RETURN    R0 1         ; return 


; Function #32:
;
; Name:            
; Defined at line: 333
; #Upvalues:       1
; #Parameters:     0
; Is_vararg:       0
; Max Stack Size:  2

  1 [-]: GETUPVAL  R0 U0        ; R0 := U0
  2 [-]: CALL      R0 1 1       ; R0()
  3 [-]: MOVE      R0 R1        ; R0 := R1
  4 [-]: RETURN    R0 2         ; return R0
  5 [-]: RETURN    R0 1         ; return 


; Function #33:
;
; Name:            
; Defined at line: 338
; #Upvalues:       1
; #Parameters:     0
; Is_vararg:       0
; Max Stack Size:  2

  1 [-]: GETUPVAL  R0 U0        ; R0 := U0
  2 [-]: CALL      R0 1 1       ; R0()
  3 [-]: MOVE      R0 R1        ; R0 := R1
  4 [-]: RETURN    R0 2         ; return R0
  5 [-]: RETURN    R0 1         ; return 


; Function #34:
;
; Name:            
; Defined at line: 343
; #Upvalues:       1
; #Parameters:     0
; Is_vararg:       0
; Max Stack Size:  2

  1 [-]: GETUPVAL  R0 U0        ; R0 := U0
  2 [-]: CALL      R0 1 1       ; R0()
  3 [-]: MOVE      R0 R1        ; R0 := R1
  4 [-]: RETURN    R0 2         ; return R0
  5 [-]: RETURN    R0 1         ; return 


; Function #35:
;
; Name:            
; Defined at line: 348
; #Upvalues:       1
; #Parameters:     0
; Is_vararg:       0
; Max Stack Size:  2

  1 [-]: GETUPVAL  R0 U0        ; R0 := U0
  2 [-]: CALL      R0 1 1       ; R0()
  3 [-]: MOVE      R0 R1        ; R0 := R1
  4 [-]: RETURN    R0 2         ; return R0
  5 [-]: RETURN    R0 1         ; return 


; Function #36:
;
; Name:            
; Defined at line: 353
; #Upvalues:       1
; #Parameters:     0
; Is_vararg:       0
; Max Stack Size:  2

  1 [-]: GETUPVAL  R0 U0        ; R0 := U0
  2 [-]: CALL      R0 1 1       ; R0()
  3 [-]: MOVE      R0 R1        ; R0 := R1
  4 [-]: RETURN    R0 2         ; return R0
  5 [-]: RETURN    R0 1         ; return 


; Function #37:
;
; Name:            
; Defined at line: 358
; #Upvalues:       1
; #Parameters:     0
; Is_vararg:       0
; Max Stack Size:  2

  1 [-]: GETUPVAL  R0 U0        ; R0 := U0
  2 [-]: CALL      R0 1 1       ; R0()
  3 [-]: MOVE      R0 R1        ; R0 := R1
  4 [-]: RETURN    R0 2         ; return R0
  5 [-]: RETURN    R0 1         ; return 


; Function #38:
;
; Name:            
; Defined at line: 363
; #Upvalues:       2
; #Parameters:     0
; Is_vararg:       0
; Max Stack Size:  2

  1 [-]: GETUPVAL  R0 U0        ; R0 := U0
  2 [-]: TEST      R0 1         ; if R0 then PC := 12
  3 [-]: JMP       12           ; PC := 12
  4 [-]: GETGLOBAL R0 K0        ; R0 := 0x400E7765
  5 [-]: GETUPVAL  R1 U1        ; R1 := U1
  6 [-]: CALL      R0 2 2       ; R0 := R0(R1)
  7 [-]: TEST      R0 1         ; if R0 then PC := 12
  8 [-]: JMP       12           ; PC := 12
  9 [-]: GETUPVAL  R0 U1        ; R0 := U1
 10 [-]: SELF      R0 R0 K1     ; R1 := R0; R0 := R0["0x26D94321"]
 11 [-]: CALL      R0 2 1       ; R0(R1)
 12 [-]: MOVE      R0 R1        ; R0 := R1
 13 [-]: RETURN    R0 2         ; return R0
 14 [-]: RETURN    R0 1         ; return 


; Function #39:
;
; Name:            
; Defined at line: 370
; #Upvalues:       1
; #Parameters:     0
; Is_vararg:       0
; Max Stack Size:  2

  1 [-]: GETUPVAL  R0 U0        ; R0 := U0
  2 [-]: GETTABLE  R0 R0 K0     ; R0 := R0["0x25992394"]
  3 [-]: GETGLOBAL R1 K1        ; R1 := _G
  4 [-]: GETTABLE  R1 R1 K2     ; R1 := R1["UISound_Focus"]
  5 [-]: CALL      R0 2 1       ; R0(R1)
  6 [-]: RETURN    R0 1         ; return 


; Function #40:
;
; Name:            
; Defined at line: 374
; #Upvalues:       2
; #Parameters:     2
; Is_vararg:       0
; Max Stack Size:  6

  1 [-]: GETUPVAL  R2 U0        ; R2 := U0
  2 [-]: TEST      R2 1         ; if R2 then PC := 19
  3 [-]: JMP       19           ; PC := 19
  4 [-]: GETGLOBAL R2 K0        ; R2 := 0x400E7765
  5 [-]: GETUPVAL  R3 U1        ; R3 := U1
  6 [-]: GETTABLE  R3 R3 K1     ; R3 := R3["mScrollBar"]
  7 [-]: CALL      R2 2 2       ; R2 := R2(R3)
  8 [-]: TEST      R2 1         ; if R2 then PC := 19
  9 [-]: JMP       19           ; PC := 19
 10 [-]: GETUPVAL  R2 U1        ; R2 := U1
 11 [-]: GETTABLE  R2 R2 K1     ; R2 := R2["mScrollBar"]
 12 [-]: SELF      R2 R2 K2     ; R3 := R2; R2 := R2["0x9F50FF89"]
 13 [-]: GETGLOBAL R4 K3        ; R4 := 0xF595ADDE
 14 [-]: MOVE      R5 R1        ; R5 := R1
 15 [-]: CALL      R4 2 2       ; R4 := R4(R5)
 16 [-]: GETGLOBAL R5 K4        ; R5 := _G
 17 [-]: GETTABLE  R5 R5 K5     ; R5 := R5["UISound_Scroll"]
 18 [-]: CALL      R2 4 1       ; R2(R3,R4,R5)
 19 [-]: RETURN    R0 1         ; return 


