code size: 163
code size: 16
code size: 6
code size: 17
code size: 12
code size: 53
code size: 11
code size: 16
code size: 19
code size: 4
code size: 52
code size: 35
code size: 53
code size: 25
code size: 81
code size: 49
code size: 5
code size: 53
code size: 53
code size: 51
code size: 50
code size: 83
code size: 20
code size: 4
code size: 25
code size: 4
code size: 4
code size: 11
code size: 11
code size: 5
code size: 5
code size: 5
code size: 5
code size: 5
code size: 5
code size: 5
code size: 5
code size: 6
code size: 6
code size: 38
code size: 13
code size: 4
code size: 79
; This file has been disassembled using luadec 2.0.2 by sztupy (http://winmo.sztupy.hu)
; Command line was: -dis M:\git repos\warframe-lua-disassembled\B.Font.cache_extracted\EE\Menus\Secrets.luac 

; Name:            
; Defined at line: 0
; #Upvalues:       0
; #Parameters:     0
; Is_vararg:       2
; Max Stack Size:  32

  1 [-]: LOADK     R0 K0        ; R0 := 1
  2 [-]: LOADK     R1 K1        ; R1 := 2
  3 [-]: LOADK     R2 K2        ; R2 := 3
  4 [-]: LOADNIL   R3 R3        ; R3 := nil
  5 [-]: LOADK     R4 K3        ; R4 := 0
  6 [-]: CLOSURE   R5 0         ; R5 := closure(Function #1)
  7 [-]: CLOSURE   R6 1         ; R6 := closure(Function #2)
  8 [-]: MOVE      R0 R0        ; R0 := R0
  9 [-]: MOVE      R0 R2        ; R0 := R2
 10 [-]: CLOSURE   R7 2         ; R7 := closure(Function #3)
 11 [-]: MOVE      R0 R6        ; R0 := R6
 12 [-]: CLOSURE   R8 3         ; R8 := closure(Function #4)
 13 [-]: CLOSURE   R9 4         ; R9 := closure(Function #5)
 14 [-]: CLOSURE   R10 5        ; R10 := closure(Function #6)
 15 [-]: CLOSURE   R11 6        ; R11 := closure(Function #7)
 16 [-]: CLOSURE   R12 7        ; R12 := closure(Function #8)
 17 [-]: CLOSURE   R13 8        ; R13 := closure(Function #9)
 18 [-]: MOVE      R0 R5        ; R0 := R5
 19 [-]: MOVE      R0 R7        ; R0 := R7
 20 [-]: MOVE      R0 R1        ; R0 := R1
 21 [-]: MOVE      R0 R9        ; R0 := R9
 22 [-]: MOVE      R0 R2        ; R0 := R2
 23 [-]: MOVE      R0 R11       ; R0 := R11
 24 [-]: MOVE      R0 R3        ; R0 := R3
 25 [-]: MOVE      R0 R0        ; R0 := R0
 26 [-]: CLOSURE   R14 9        ; R14 := closure(Function #10)
 27 [-]: MOVE      R0 R5        ; R0 := R5
 28 [-]: MOVE      R0 R7        ; R0 := R7
 29 [-]: MOVE      R0 R0        ; R0 := R0
 30 [-]: MOVE      R0 R12       ; R0 := R12
 31 [-]: MOVE      R0 R3        ; R0 := R3
 32 [-]: CLOSURE   R15 10       ; R15 := closure(Function #11)
 33 [-]: MOVE      R0 R8        ; R0 := R8
 34 [-]: MOVE      R0 R5        ; R0 := R5
 35 [-]: MOVE      R0 R7        ; R0 := R7
 36 [-]: MOVE      R0 R1        ; R0 := R1
 37 [-]: MOVE      R0 R9        ; R0 := R9
 38 [-]: CLOSURE   R16 11       ; R16 := closure(Function #12)
 39 [-]: CLOSURE   R17 12       ; R17 := closure(Function #13)
 40 [-]: MOVE      R0 R16       ; R0 := R16
 41 [-]: MOVE      R0 R17       ; R0 := R17
 42 [-]: MOVE      R0 R6        ; R0 := R6
 43 [-]: MOVE      R0 R2        ; R0 := R2
 44 [-]: MOVE      R0 R1        ; R0 := R1
 45 [-]: MOVE      R0 R10       ; R0 := R10
 46 [-]: CLOSURE   R18 13       ; R18 := closure(Function #14)
 47 [-]: MOVE      R0 R5        ; R0 := R5
 48 [-]: MOVE      R0 R7        ; R0 := R7
 49 [-]: MOVE      R0 R1        ; R0 := R1
 50 [-]: MOVE      R0 R9        ; R0 := R9
 51 [-]: MOVE      R0 R17       ; R0 := R17
 52 [-]: MOVE      R0 R3        ; R0 := R3
 53 [-]: MOVE      R0 R0        ; R0 := R0
 54 [-]: CLOSURE   R19 14       ; R19 := closure(Function #15)
 55 [-]: CLOSURE   R20 15       ; R20 := closure(Function #16)
 56 [-]: CLOSURE   R21 16       ; R21 := closure(Function #17)
 57 [-]: MOVE      R0 R4        ; R0 := R4
 58 [-]: MOVE      R0 R19       ; R0 := R19
 59 [-]: MOVE      R0 R3        ; R0 := R3
 60 [-]: CLOSURE   R22 17       ; R22 := closure(Function #18)
 61 [-]: CLOSURE   R23 18       ; R23 := closure(Function #19)
 62 [-]: MOVE      R0 R22       ; R0 := R22
 63 [-]: MOVE      R0 R20       ; R0 := R20
 64 [-]: MOVE      R0 R4        ; R0 := R4
 65 [-]: MOVE      R0 R19       ; R0 := R19
 66 [-]: MOVE      R0 R3        ; R0 := R3
 67 [-]: CLOSURE   R24 19       ; R24 := closure(Function #20)
 68 [-]: MOVE      R0 R4        ; R0 := R4
 69 [-]: MOVE      R0 R3        ; R0 := R3
 70 [-]: MOVE      R0 R23       ; R0 := R23
 71 [-]: CLOSURE   R25 20       ; R25 := closure(Function #21)
 72 [-]: MOVE      R0 R19       ; R0 := R19
 73 [-]: MOVE      R0 R23       ; R0 := R23
 74 [-]: CLOSURE   R26 21       ; R26 := closure(Function #22)
 75 [-]: MOVE      R0 R21       ; R0 := R21
 76 [-]: CLOSURE   R27 22       ; R27 := closure(Function #23)
 77 [-]: MOVE      R0 R3        ; R0 := R3
 78 [-]: MOVE      R0 R4        ; R0 := R4
 79 [-]: MOVE      R0 R21       ; R0 := R21
 80 [-]: SETGLOBAL R27 K4       ; onItemClick := R27
 81 [-]: SETGLOBAL R27 K5       ; 0xB70862C := R27
 82 [-]: CLOSURE   R27 23       ; R27 := closure(Function #24)
 83 [-]: MOVE      R0 R24       ; R0 := R24
 84 [-]: CLOSURE   R28 24       ; R28 := closure(Function #25)
 85 [-]: MOVE      R0 R24       ; R0 := R24
 86 [-]: CLOSURE   R29 25       ; R29 := closure(Function #26)
 87 [-]: MOVE      R0 R4        ; R0 := R4
 88 [-]: MOVE      R0 R21       ; R0 := R21
 89 [-]: CLOSURE   R30 26       ; R30 := closure(Function #27)
 90 [-]: MOVE      R0 R4        ; R0 := R4
 91 [-]: MOVE      R0 R21       ; R0 := R21
 92 [-]: CLOSURE   R31 27       ; R31 := closure(Function #28)
 93 [-]: MOVE      R0 R27       ; R0 := R27
 94 [-]: SETGLOBAL R31 K6       ; onKeyDown_MENU_DOWN := R31
 95 [-]: SETGLOBAL R31 K7       ; 0x3C4BCFF3 := R31
 96 [-]: CLOSURE   R31 28       ; R31 := closure(Function #29)
 97 [-]: MOVE      R0 R28       ; R0 := R28
 98 [-]: SETGLOBAL R31 K8       ; onKeyDown_MENU_UP := R31
 99 [-]: SETGLOBAL R31 K9       ; 0x396F9C7A := R31
100 [-]: CLOSURE   R31 29       ; R31 := closure(Function #30)
101 [-]: MOVE      R0 R29       ; R0 := R29
102 [-]: SETGLOBAL R31 K10      ; onKeyDown_MENU_LEFT := R31
103 [-]: SETGLOBAL R31 K11      ; 0xE7520447 := R31
104 [-]: CLOSURE   R31 30       ; R31 := closure(Function #31)
105 [-]: MOVE      R0 R30       ; R0 := R30
106 [-]: SETGLOBAL R31 K12      ; onKeyDown_MENU_RIGHT := R31
107 [-]: SETGLOBAL R31 K13      ; 0xD9B90793 := R31
108 [-]: CLOSURE   R31 31       ; R31 := closure(Function #32)
109 [-]: MOVE      R0 R27       ; R0 := R27
110 [-]: SETGLOBAL R31 K14      ; onKeyDown_MENU_DOWN_FROM_ANALOG := R31
111 [-]: SETGLOBAL R31 K15      ; 0x42A3C2E3 := R31
112 [-]: CLOSURE   R31 32       ; R31 := closure(Function #33)
113 [-]: MOVE      R0 R28       ; R0 := R28
114 [-]: SETGLOBAL R31 K16      ; onKeyDown_MENU_UP_FROM_ANALOG := R31
115 [-]: SETGLOBAL R31 K17      ; 0x7EF8360 := R31
116 [-]: CLOSURE   R31 33       ; R31 := closure(Function #34)
117 [-]: MOVE      R0 R29       ; R0 := R29
118 [-]: SETGLOBAL R31 K18      ; onKeyDown_MENU_LEFT_FROM_ANALOG := R31
119 [-]: SETGLOBAL R31 K19      ; 0x7EA32551 := R31
120 [-]: CLOSURE   R31 34       ; R31 := closure(Function #35)
121 [-]: MOVE      R0 R30       ; R0 := R30
122 [-]: SETGLOBAL R31 K20      ; onKeyDown_MENU_RIGHT_FROM_ANALOG := R31
123 [-]: SETGLOBAL R31 K21      ; 0x80AA3206 := R31
124 [-]: CLOSURE   R31 35       ; R31 := closure(Function #36)
125 [-]: MOVE      R0 R24       ; R0 := R24
126 [-]: SETGLOBAL R31 K22      ; onKeyDown_MENU_LTRIGGER2 := R31
127 [-]: SETGLOBAL R31 K23      ; 0x9BD896E0 := R31
128 [-]: CLOSURE   R31 36       ; R31 := closure(Function #37)
129 [-]: MOVE      R0 R24       ; R0 := R24
130 [-]: SETGLOBAL R31 K24      ; onKeyDown_MENU_RTRIGGER2 := R31
131 [-]: SETGLOBAL R31 K25      ; 0xFE4FF8B := R31
132 [-]: CLOSURE   R31 37       ; R31 := closure(Function #38)
133 [-]: MOVE      R0 R4        ; R0 := R4
134 [-]: MOVE      R0 R3        ; R0 := R3
135 [-]: MOVE      R0 R23       ; R0 := R23
136 [-]: SETGLOBAL R31 K26      ; onKeyDown_MENU_SELECT := R31
137 [-]: SETGLOBAL R31 K27      ; 0xEEDD1ACF := R31
138 [-]: CLOSURE   R31 38       ; R31 := closure(Function #39)
139 [-]: MOVE      R0 R4        ; R0 := R4
140 [-]: MOVE      R0 R21       ; R0 := R21
141 [-]: SETGLOBAL R31 K28      ; onKeyDown_MENU_CANCEL := R31
142 [-]: SETGLOBAL R31 K29      ; 0x5B2C0B28 := R31
143 [-]: CLOSURE   R31 39       ; R31 := closure(Function #40)
144 [-]: SETGLOBAL R31 K30      ; onKeyUp_HIDE_PAUSE_MENU := R31
145 [-]: SETGLOBAL R31 K31      ; 0xFBCEB10C := R31
146 [-]: CLOSURE   R31 40       ; R31 := closure(Function #41)
147 [-]: MOVE      R0 R3        ; R0 := R3
148 [-]: MOVE      R0 R5        ; R0 := R5
149 [-]: MOVE      R0 R25       ; R0 := R25
150 [-]: MOVE      R0 R26       ; R0 := R26
151 [-]: MOVE      R0 R18       ; R0 := R18
152 [-]: MOVE      R0 R13       ; R0 := R13
153 [-]: MOVE      R0 R17       ; R0 := R17
154 [-]: MOVE      R0 R7        ; R0 := R7
155 [-]: MOVE      R0 R0        ; R0 := R0
156 [-]: MOVE      R0 R14       ; R0 := R14
157 [-]: MOVE      R0 R2        ; R0 := R2
158 [-]: MOVE      R0 R15       ; R0 := R15
159 [-]: MOVE      R0 R21       ; R0 := R21
160 [-]: MOVE      R0 R23       ; R0 := R23
161 [-]: SETGLOBAL R31 K32      ; Initialize := R31
162 [-]: SETGLOBAL R31 K33      ; 0x62648036 := R31
163 [-]: RETURN    R0 1         ; return 


; Function #1:
;
; Name:            
; Defined at line: 19
; #Upvalues:       0
; #Parameters:     2
; Is_vararg:       0
; Max Stack Size:  5

  1 [-]: CLOSURE   R2 0         ; R2 := closure(Function #1.1)
  2 [-]: NEWTABLE  R3 0 11      ; R3 := {}
  3 [-]: SETTABLE  R3 K0 R0     ; R3["name"] := R0
  4 [-]: SETTABLE  R3 K1 R1     ; R3["flashListName"] := R1
  5 [-]: SETTABLE  R3 K2 K3     ; R3["visibleItems"] := 12
  6 [-]: SETTABLE  R3 K4 K5     ; R3["scrollPos"] := 0
  7 [-]: SETTABLE  R3 K6 K7     ; R3["selected"] := 1
  8 [-]: NEWTABLE  R4 0 0       ; R4 := {}
  9 [-]: SETTABLE  R3 K8 R4     ; R3["items"] := R4
 10 [-]: SETTABLE  R3 K9 R2     ; R3["count"] := R2
 11 [-]: SETTABLE  R3 K10 K11   ; R3["onValidate"] := nil
 12 [-]: SETTABLE  R3 K12 K11   ; R3["onScroll"] := nil
 13 [-]: SETTABLE  R3 K13 K11   ; R3["onFocused"] := nil
 14 [-]: SETTABLE  R3 K14 K11   ; R3["onPress"] := nil
 15 [-]: RETURN    R3 2         ; return R3
 16 [-]: RETURN    R0 1         ; return 


; Function #1.1:
;
; Name:            
; Defined at line: 21
; #Upvalues:       0
; #Parameters:     1
; Is_vararg:       0
; Max Stack Size:  3

  1 [-]: GETGLOBAL R1 K0        ; R1 := table
  2 [-]: GETTABLE  R1 R1 K1     ; R1 := R1["0xBEA3A82E"]
  3 [-]: GETTABLE  R2 R0 K2     ; R2 := R0["items"]
  4 [-]: TAILCALL  R1 2 0       ; R1,... := R1(R2)
  5 [-]: RETURN    R1 0         ; return R1,...
  6 [-]: RETURN    R0 1         ; return 


; Function #2:
;
; Name:            
; Defined at line: 50
; #Upvalues:       2
; #Parameters:     5
; Is_vararg:       0
; Max Stack Size:  7

  1 [-]: EQ        0 R2 K0      ; if R2 ~= nil then PC := 4
  2 [-]: JMP       4            ; PC := 4
  3 [-]: GETUPVAL  R2 U0        ; R2 := U0
  4 [-]: MOVE      R5 R1        ; R5 := R1
  5 [-]: GETUPVAL  R6 U1        ; R6 := U1
  6 [-]: EQ        0 R2 R6      ; if R2 ~= R6 then PC := 9
  7 [-]: JMP       9            ; PC := 9
  8 [-]: MOVE      R5 R0        ; R5 := R0
  9 [-]: NEWTABLE  R6 0 6       ; R6 := {}
 10 [-]: SETTABLE  R6 K1 R0     ; R6["name"] := R0
 11 [-]: SETTABLE  R6 K2 R1     ; R6["value"] := R1
 12 [-]: SETTABLE  R6 K3 R2     ; R6["type"] := R2
 13 [-]: SETTABLE  R6 K4 R3     ; R6["callback"] := R3
 14 [-]: SETTABLE  R6 K5 R4     ; R6["usrData"] := R4
 15 [-]: SETTABLE  R6 K6 R5     ; R6["selectable"] := R5
 16 [-]: RETURN    R6 2         ; return R6
 17 [-]: RETURN    R0 1         ; return 


; Function #3:
;
; Name:            
; Defined at line: 75
; #Upvalues:       1
; #Parameters:     6
; Is_vararg:       0
; Max Stack Size:  14

  1 [-]: GETGLOBAL R6 K0        ; R6 := table
  2 [-]: GETTABLE  R6 R6 K1     ; R6 := R6["0xE6450C9D"]
  3 [-]: GETTABLE  R7 R0 K2     ; R7 := R0["items"]
  4 [-]: GETUPVAL  R8 U0        ; R8 := U0
  5 [-]: MOVE      R9 R1        ; R9 := R1
  6 [-]: MOVE      R10 R2       ; R10 := R2
  7 [-]: MOVE      R11 R3       ; R11 := R3
  8 [-]: MOVE      R12 R4       ; R12 := R4
  9 [-]: MOVE      R13 R5       ; R13 := R5
 10 [-]: CALL      R8 6 0       ; R8,... := R8(R9,R10,R11,R12,R13)
 11 [-]: CALL      R6 0 1       ; R6(R7,...)
 12 [-]: RETURN    R0 1         ; return 


; Function #4:
;
; Name:            
; Defined at line: 84
; #Upvalues:       0
; #Parameters:     2
; Is_vararg:       0
; Max Stack Size:  13

  1 [-]: NEWTABLE  R2 0 0       ; R2 := {}
  2 [-]: LOADK     R3 K0        ; R3 := 1
  3 [-]: GETGLOBAL R4 K1        ; R4 := string
  4 [-]: GETTABLE  R4 R4 K2     ; R4 := R4["0xDE44F664"]
  5 [-]: LOADK     R5 K3        ; R5 := ""
  6 [-]: MOVE      R6 R1        ; R6 := R1
  7 [-]: LOADK     R7 K0        ; R7 := 1
  8 [-]: MOVE      R8 R1        ; R8 := R1
  9 [-]: CALL      R4 5 2       ; R4 := R4(R5,R6,R7,R8)
 10 [-]: TEST      R4 0         ; if not R4 then PC := 19
 11 [-]: JMP       19           ; PC := 19
 12 [-]: GETGLOBAL R4 K4        ; R4 := table
 13 [-]: GETTABLE  R4 R4 K5     ; R4 := R4["0xE6450C9D"]
 14 [-]: MOVE      R5 R2        ; R5 := R2
 15 [-]: LOADK     R6 K0        ; R6 := 1
 16 [-]: MOVE      R7 R0        ; R7 := R0
 17 [-]: CALL      R4 4 1       ; R4(R5,R6,R7)
 18 [-]: RETURN    R2 2         ; return R2
 19 [-]: GETGLOBAL R4 K1        ; R4 := string
 20 [-]: GETTABLE  R4 R4 K2     ; R4 := R4["0xDE44F664"]
 21 [-]: MOVE      R5 R0        ; R5 := R0
 22 [-]: MOVE      R6 R1        ; R6 := R1
 23 [-]: MOVE      R7 R3        ; R7 := R3
 24 [-]: MOVE      R8 R1        ; R8 := R1
 25 [-]: CALL      R4 5 3       ; R4,R5 := R4(R5,R6,R7,R8)
 26 [-]: TEST      R4 0         ; if not R4 then PC := 41
 27 [-]: JMP       41           ; PC := 41
 28 [-]: GETGLOBAL R6 K4        ; R6 := table
 29 [-]: GETTABLE  R6 R6 K5     ; R6 := R6["0xE6450C9D"]
 30 [-]: MOVE      R7 R2        ; R7 := R2
 31 [-]: GETGLOBAL R8 K1        ; R8 := string
 32 [-]: GETTABLE  R8 R8 K6     ; R8 := R8["0x7B782033"]
 33 [-]: MOVE      R9 R0        ; R9 := R0
 34 [-]: MOVE      R10 R3       ; R10 := R3
 35 [-]: SUB       R11 R4 K0    ; R11 := R4 - 1
 36 [-]: MOVE      R12 R1       ; R12 := R1
 37 [-]: CALL      R8 5 0       ; R8,... := R8(R9,R10,R11,R12)
 38 [-]: CALL      R6 0 1       ; R6(R7,...)
 39 [-]: ADD       R3 R5 K0     ; R3 := R5 + 1
 40 [-]: JMP       19           ; PC := 19
 41 [-]: GETGLOBAL R6 K4        ; R6 := table
 42 [-]: GETTABLE  R6 R6 K5     ; R6 := R6["0xE6450C9D"]
 43 [-]: MOVE      R7 R2        ; R7 := R2
 44 [-]: GETGLOBAL R8 K1        ; R8 := string
 45 [-]: GETTABLE  R8 R8 K6     ; R8 := R8["0x7B782033"]
 46 [-]: MOVE      R9 R0        ; R9 := R0
 47 [-]: MOVE      R10 R3       ; R10 := R3
 48 [-]: CALL      R8 3 0       ; R8,... := R8(R9,R10)
 49 [-]: CALL      R6 0 1       ; R6(R7,...)
 50 [-]: JMP       52           ; PC := 52
 51 [-]: JMP       19           ; PC := 19
 52 [-]: RETURN    R2 2         ; return R2
 53 [-]: RETURN    R0 1         ; return 


; Function #5:
;
; Name:            
; Defined at line: 111
; #Upvalues:       0
; #Parameters:     3
; Is_vararg:       0
; Max Stack Size:  9

  1 [-]: GETTABLE  R3 R0 K0     ; R3 := R0["value"]
  2 [-]: MOVE      R3 R3        ; R3 := R3
  3 [-]: SETTABLE  R0 K0 R3     ; R0["value"] := R3
  4 [-]: GETTABLE  R3 R0 K1     ; R3 := R0["usrData"]
  5 [-]: GETTABLE  R4 R0 K0     ; R4 := R0["value"]
  6 [-]: GETGLOBAL R5 K2        ; R5 := gFlashMgr
  7 [-]: SELF      R5 R5 K3     ; R6 := R5; R5 := R5["0x8F6FC47E"]
  8 [-]: MOVE      R7 R3        ; R7 := R3
  9 [-]: MOVE      R8 R4        ; R8 := R4
 10 [-]: CALL      R5 4 1       ; R5(R6,R7,R8)
 11 [-]: RETURN    R0 1         ; return 


; Function #6:
;
; Name:            
; Defined at line: 125
; #Upvalues:       0
; #Parameters:     3
; Is_vararg:       0
; Max Stack Size:  8

  1 [-]: GETTABLE  R3 R0 K0     ; R3 := R0["usrData"]
  2 [-]: GETGLOBAL R4 K1        ; R4 := gFlashMgr
  3 [-]: SELF      R4 R4 K2     ; R5 := R4; R4 := R4["0xE7F47B4C"]
  4 [-]: MOVE      R6 R3        ; R6 := R3
  5 [-]: CALL      R4 3 2       ; R4 := R4(R5,R6)
  6 [-]: GETGLOBAL R5 K1        ; R5 := gFlashMgr
  7 [-]: SELF      R5 R5 K3     ; R6 := R5; R5 := R5["0x1041EAD3"]
  8 [-]: MOVE      R7 R3        ; R7 := R3
  9 [-]: CALL      R5 3 1       ; R5(R6,R7)
 10 [-]: GETGLOBAL R5 K1        ; R5 := gFlashMgr
 11 [-]: SELF      R5 R5 K2     ; R6 := R5; R5 := R5["0xE7F47B4C"]
 12 [-]: MOVE      R7 R3        ; R7 := R3
 13 [-]: CALL      R5 3 2       ; R5 := R5(R6,R7)
 14 [-]: MOVE      R4 R5        ; R4 := R5
 15 [-]: SETTABLE  R0 K4 R4     ; R0["value"] := R4
 16 [-]: RETURN    R0 1         ; return 


; Function #7:
;
; Name:            
; Defined at line: 144
; #Upvalues:       0
; #Parameters:     3
; Is_vararg:       0
; Max Stack Size:  12

  1 [-]: GETTABLE  R3 R0 K0     ; R3 := R0["usrData"]
  2 [-]: GETGLOBAL R4 K1        ; R4 := Script
  3 [-]: GETTABLE  R4 R4 K2     ; R4 := R4["0x918F04D3"]
  4 [-]: CALL      R4 1 2       ; R4 := R4()
  5 [-]: SELF      R5 R4 K3     ; R6 := R4; R5 := R4["0xE139A98D"]
  6 [-]: CALL      R5 2 2       ; R5 := R5(R6)
  7 [-]: GETTABLE  R6 R5 R3     ; R6 := R5[R3]
  8 [-]: SELF      R6 R6 K4     ; R7 := R6; R6 := R6["0x34820572"]
  9 [-]: CALL      R6 2 2       ; R6 := R6(R7)
 10 [-]: GETTABLE  R7 R5 R3     ; R7 := R5[R3]
 11 [-]: SELF      R7 R7 K5     ; R8 := R7; R7 := R7["0x8C1ACCEF"]
 12 [-]: CALL      R7 2 2       ; R7 := R7(R8)
 13 [-]: MOVE      R7 R7        ; R7 := R7
 14 [-]: SELF      R8 R4 K6     ; R9 := R4; R8 := R4["0xF0D07921"]
 15 [-]: MOVE      R10 R6       ; R10 := R6
 16 [-]: MOVE      R11 R7       ; R11 := R7
 17 [-]: CALL      R8 4 1       ; R8(R9,R10,R11)
 18 [-]: SETTABLE  R0 K7 R7     ; R0["value"] := R7
 19 [-]: RETURN    R0 1         ; return 


; Function #8:
;
; Name:            
; Defined at line: 160
; #Upvalues:       0
; #Parameters:     3
; Is_vararg:       0
; Max Stack Size:  6

  1 [-]: GETTABLE  R3 R0 K0     ; R3 := R0["usrData"]
  2 [-]: SELF      R4 R3 K1     ; R5 := R3; R4 := R3["0xA35B422"]
  3 [-]: CALL      R4 2 1       ; R4(R5)
  4 [-]: RETURN    R0 1         ; return 


; Function #9:
;
; Name:            
; Defined at line: 171
; #Upvalues:       8
; #Parameters:     0
; Is_vararg:       0
; Max Stack Size:  16

  1 [-]: GETGLOBAL R0 K0        ; R0 := Script
  2 [-]: GETTABLE  R0 R0 K1     ; R0 := R0["0x918F04D3"]
  3 [-]: CALL      R0 1 2       ; R0 := R0()
  4 [-]: SELF      R1 R0 K2     ; R2 := R0; R1 := R0["0xE139A98D"]
  5 [-]: CALL      R1 2 2       ; R1 := R1(R2)
  6 [-]: GETUPVAL  R2 U0        ; R2 := U0
  7 [-]: LOADK     R3 K3        ; R3 := "Stat Groups"
  8 [-]: LOADK     R4 K4        ; R4 := "subList"
  9 [-]: CALL      R2 3 2       ; R2 := R2(R3,R4)
 10 [-]: GETUPVAL  R3 U1        ; R3 := U1
 11 [-]: MOVE      R4 R2        ; R4 := R2
 12 [-]: LOADK     R5 K5        ; R5 := "ShowStats"
 13 [-]: GETGLOBAL R6 K6        ; R6 := gFlashMgr
 14 [-]: SELF      R6 R6 K7     ; R7 := R6; R6 := R6["0x1089D053"]
 15 [-]: LOADK     R8 K8        ; R8 := "Stats.ShowStats"
 16 [-]: CALL      R6 3 2       ; R6 := R6(R7,R8)
 17 [-]: GETUPVAL  R7 U2        ; R7 := U2
 18 [-]: GETUPVAL  R8 U3        ; R8 := U3
 19 [-]: LOADK     R9 K8        ; R9 := "Stats.ShowStats"
 20 [-]: CALL      R3 7 1       ; R3(R4,R5,R6,R7,R8,R9)
 21 [-]: GETUPVAL  R3 U1        ; R3 := U1
 22 [-]: MOVE      R4 R2        ; R4 := R2
 23 [-]: LOADK     R5 K9        ; R5 := "-"
 24 [-]: MOVE      R6 R0        ; R6 := R0
 25 [-]: GETUPVAL  R7 U4        ; R7 := U4
 26 [-]: CALL      R3 5 1       ; R3(R4,R5,R6,R7)
 27 [-]: LOADK     R3 K10       ; R3 := 1
 28 [-]: LEN       R4 R1        ; R4 := # R1
 29 [-]: LOADK     R5 K10       ; R5 := 1
 30 [-]: FORPREP   R3 45        ; R3 -= R5; PC := 45
 31 [-]: GETTABLE  R7 R1 R6     ; R7 := R1[R6]
 32 [-]: SELF      R7 R7 K11    ; R8 := R7; R7 := R7["0x34820572"]
 33 [-]: CALL      R7 2 2       ; R7 := R7(R8)
 34 [-]: GETTABLE  R8 R1 R6     ; R8 := R1[R6]
 35 [-]: SELF      R8 R8 K12    ; R9 := R8; R8 := R8["0x8C1ACCEF"]
 36 [-]: CALL      R8 2 2       ; R8 := R8(R9)
 37 [-]: GETUPVAL  R9 U1        ; R9 := U1
 38 [-]: MOVE      R10 R2       ; R10 := R2
 39 [-]: MOVE      R11 R7       ; R11 := R7
 40 [-]: MOVE      R12 R8       ; R12 := R8
 41 [-]: GETUPVAL  R13 U2       ; R13 := U2
 42 [-]: GETUPVAL  R14 U5       ; R14 := U5
 43 [-]: MOVE      R15 R6       ; R15 := R6
 44 [-]: CALL      R9 7 1       ; R9(R10,R11,R12,R13,R14,R15)
 45 [-]: FORLOOP   R3 31        ; R3 += R5; if R3 <= R4 then begin PC := 31; R6 := R3 end
 46 [-]: GETUPVAL  R9 U1        ; R9 := U1
 47 [-]: GETUPVAL  R10 U6       ; R10 := U6
 48 [-]: GETTABLE  R11 R2 K13   ; R11 := R2["name"]
 49 [-]: MOVE      R12 R2       ; R12 := R2
 50 [-]: GETUPVAL  R13 U7       ; R13 := U7
 51 [-]: CALL      R9 5 1       ; R9(R10,R11,R12,R13)
 52 [-]: RETURN    R0 1         ; return 


; Function #10:
;
; Name:            
; Defined at line: 198
; #Upvalues:       5
; #Parameters:     0
; Is_vararg:       0
; Max Stack Size:  15

  1 [-]: GETGLOBAL R0 K0        ; R0 := gGameRules
  2 [-]: SELF      R1 R0 K1     ; R2 := R0; R1 := R0["0x1B46A189"]
  3 [-]: CALL      R1 2 2       ; R1 := R1(R2)
  4 [-]: EQ        1 R1 K2      ; if R1 == nil then PC := 35
  5 [-]: JMP       35           ; PC := 35
  6 [-]: LEN       R2 R1        ; R2 := # R1
  7 [-]: LT        0 K3 R2      ; if 0 >= R2 then PC := 35
  8 [-]: JMP       35           ; PC := 35
  9 [-]: GETUPVAL  R2 U0        ; R2 := U0
 10 [-]: LOADK     R3 K4        ; R3 := "CheckPoints"
 11 [-]: LOADK     R4 K5        ; R4 := "subList"
 12 [-]: CALL      R2 3 2       ; R2 := R2(R3,R4)
 13 [-]: LOADK     R3 K6        ; R3 := 1
 14 [-]: LEN       R4 R1        ; R4 := # R1
 15 [-]: LOADK     R5 K6        ; R5 := 1
 16 [-]: FORPREP   R3 28        ; R3 -= R5; PC := 28
 17 [-]: GETTABLE  R7 R1 R6     ; R7 := R1[R6]
 18 [-]: SELF      R7 R7 K7     ; R8 := R7; R7 := R7["0x34820572"]
 19 [-]: CALL      R7 2 2       ; R7 := R7(R8)
 20 [-]: GETUPVAL  R8 U1        ; R8 := U1
 21 [-]: MOVE      R9 R2        ; R9 := R2
 22 [-]: MOVE      R10 R7       ; R10 := R7
 23 [-]: MOVE      R11 R0       ; R11 := R0
 24 [-]: GETUPVAL  R12 U2       ; R12 := U2
 25 [-]: GETUPVAL  R13 U3       ; R13 := U3
 26 [-]: GETTABLE  R14 R1 R6    ; R14 := R1[R6]
 27 [-]: CALL      R8 7 1       ; R8(R9,R10,R11,R12,R13,R14)
 28 [-]: FORLOOP   R3 17        ; R3 += R5; if R3 <= R4 then begin PC := 17; R6 := R3 end
 29 [-]: GETUPVAL  R8 U1        ; R8 := U1
 30 [-]: GETUPVAL  R9 U4        ; R9 := U4
 31 [-]: GETTABLE  R10 R2 K8    ; R10 := R2["name"]
 32 [-]: MOVE      R11 R2       ; R11 := R2
 33 [-]: GETUPVAL  R12 U2       ; R12 := U2
 34 [-]: CALL      R8 5 1       ; R8(R9,R10,R11,R12)
 35 [-]: RETURN    R0 1         ; return 


; Function #11:
;
; Name:            
; Defined at line: 220
; #Upvalues:       5
; #Parameters:     0
; Is_vararg:       0
; Max Stack Size:  23

  1 [-]: NEWTABLE  R0 0 0       ; R0 := {}
  2 [-]: GETGLOBAL R1 K0        ; R1 := gFlashMgr
  3 [-]: SELF      R1 R1 K1     ; R2 := R1; R1 := R1["0x86CEBD96"]
  4 [-]: CALL      R1 2 2       ; R1 := R1(R2)
  5 [-]: LOADK     R2 K2        ; R2 := ""
  6 [-]: LOADK     R3 K3        ; R3 := 0
  7 [-]: LOADK     R4 K4        ; R4 := 1
  8 [-]: MOVE      R5 R1        ; R5 := R1
  9 [-]: LOADK     R6 K4        ; R6 := 1
 10 [-]: FORPREP   R4 51        ; R4 -= R6; PC := 51
 11 [-]: GETGLOBAL R8 K0        ; R8 := gFlashMgr
 12 [-]: SELF      R8 R8 K5     ; R9 := R8; R8 := R8["0xDCB1D2E4"]
 13 [-]: MOVE      R10 R7       ; R10 := R7
 14 [-]: CALL      R8 3 2       ; R8 := R8(R9,R10)
 15 [-]: GETGLOBAL R9 K0        ; R9 := gFlashMgr
 16 [-]: SELF      R9 R9 K6     ; R10 := R9; R9 := R9["0x1089D053"]
 17 [-]: MOVE      R11 R8       ; R11 := R8
 18 [-]: CALL      R9 3 2       ; R9 := R9(R10,R11)
 19 [-]: GETUPVAL  R10 U0       ; R10 := U0
 20 [-]: MOVE      R11 R8       ; R11 := R8
 21 [-]: LOADK     R12 K7       ; R12 := "."
 22 [-]: CALL      R10 3 2      ; R10 := R10(R11,R12)
 23 [-]: GETTABLE  R11 R10 K8   ; R11 := R10[2]
 24 [-]: EQ        1 R11 K9     ; if R11 == nil then PC := 51
 25 [-]: JMP       51           ; PC := 51
 26 [-]: GETTABLE  R11 R10 K4   ; R11 := R10[1]
 27 [-]: GETTABLE  R12 R10 K8   ; R12 := R10[2]
 28 [-]: EQ        1 R2 R11     ; if R2 == R11 then PC := 39
 29 [-]: JMP       39           ; PC := 39
 30 [-]: GETGLOBAL R13 K10      ; R13 := table
 31 [-]: GETTABLE  R13 R13 K11  ; R13 := R13["0xE6450C9D"]
 32 [-]: MOVE      R14 R0       ; R14 := R0
 33 [-]: GETUPVAL  R15 U1       ; R15 := U1
 34 [-]: MOVE      R16 R11      ; R16 := R11
 35 [-]: CALL      R15 2 0      ; R15,... := R15(R16)
 36 [-]: CALL      R13 0 1      ; R13(R14,...)
 37 [-]: MOVE      R2 R11       ; R2 := R11
 38 [-]: ADD       R3 R3 K4     ; R3 := R3 + 1
 39 [-]: GETTABLE  R13 R0 R3    ; R13 := R0[R3]
 40 [-]: GETUPVAL  R14 U2       ; R14 := U2
 41 [-]: MOVE      R15 R13      ; R15 := R13
 42 [-]: MOVE      R16 R12      ; R16 := R12
 43 [-]: MOVE      R17 R9       ; R17 := R9
 44 [-]: GETUPVAL  R18 U3       ; R18 := U3
 45 [-]: GETUPVAL  R19 U4       ; R19 := U4
 46 [-]: MOVE      R20 R11      ; R20 := R11
 47 [-]: LOADK     R21 K7       ; R21 := "."
 48 [-]: MOVE      R22 R12      ; R22 := R12
 49 [-]: CONCAT    R20 R20 R22  ; R20 := R20 .. R21 .. R22
 50 [-]: CALL      R14 7 1      ; R14(R15,R16,R17,R18,R19,R20)
 51 [-]: FORLOOP   R4 11        ; R4 += R6; if R4 <= R5 then begin PC := 11; R7 := R4 end
 52 [-]: RETURN    R0 2         ; return R0
 53 [-]: RETURN    R0 1         ; return 


; Function #12:
;
; Name:            
; Defined at line: 261
; #Upvalues:       0
; #Parameters:     1
; Is_vararg:       0
; Max Stack Size:  11

  1 [-]: GETGLOBAL R1 K0        ; R1 := gFlashMgr
  2 [-]: SELF      R1 R1 K1     ; R2 := R1; R1 := R1["0x6E16AA60"]
  3 [-]: MOVE      R3 R0        ; R3 := R0
  4 [-]: CALL      R1 3 2       ; R1 := R1(R2,R3)
  5 [-]: NEWTABLE  R2 0 0       ; R2 := {}
  6 [-]: LOADK     R3 K2        ; R3 := 0
  7 [-]: SUB       R4 R1 K3     ; R4 := R1 - 1
  8 [-]: LOADK     R5 K3        ; R5 := 1
  9 [-]: FORPREP   R3 23        ; R3 -= R5; PC := 23
 10 [-]: GETGLOBAL R7 K0        ; R7 := gFlashMgr
 11 [-]: SELF      R7 R7 K4     ; R8 := R7; R7 := R7["0x6B56F127"]
 12 [-]: MOVE      R9 R0        ; R9 := R0
 13 [-]: MOVE      R10 R6       ; R10 := R6
 14 [-]: CALL      R7 4 2       ; R7 := R7(R8,R9,R10)
 15 [-]: EQ        0 R7 K5      ; if R7 ~= nil then PC := 18
 16 [-]: JMP       18           ; PC := 18
 17 [-]: LOADK     R7 K6        ; R7 := "-"
 18 [-]: GETGLOBAL R8 K7        ; R8 := table
 19 [-]: GETTABLE  R8 R8 K8     ; R8 := R8["0xE6450C9D"]
 20 [-]: MOVE      R9 R2        ; R9 := R2
 21 [-]: MOVE      R10 R7       ; R10 := R7
 22 [-]: CALL      R8 3 1       ; R8(R9,R10)
 23 [-]: FORLOOP   R3 10        ; R3 += R5; if R3 <= R4 then begin PC := 10; R6 := R3 end
 24 [-]: RETURN    R2 2         ; return R2
 25 [-]: RETURN    R0 1         ; return 


; Function #13:
;
; Name:            
; Defined at line: 285
; #Upvalues:       6
; #Parameters:     1
; Is_vararg:       0
; Max Stack Size:  25

  1 [-]: GETGLOBAL R1 K0        ; R1 := gFlashMgr
  2 [-]: SELF      R1 R1 K1     ; R2 := R1; R1 := R1["0xE8FE9496"]
  3 [-]: MOVE      R3 R0        ; R3 := R0
  4 [-]: CALL      R1 3 2       ; R1 := R1(R2,R3)
  5 [-]: GETUPVAL  R2 U0        ; R2 := U0
  6 [-]: MOVE      R3 R0        ; R3 := R0
  7 [-]: CALL      R2 2 2       ; R2 := R2(R3)
  8 [-]: GETGLOBAL R3 K2        ; R3 := table
  9 [-]: GETTABLE  R3 R3 K3     ; R3 := R3["0xBEA3A82E"]
 10 [-]: MOVE      R4 R2        ; R4 := R2
 11 [-]: CALL      R3 2 2       ; R3 := R3(R4)
 12 [-]: NEWTABLE  R4 0 0       ; R4 := {}
 13 [-]: LOADK     R5 K4        ; R5 := 1
 14 [-]: MOVE      R6 R3        ; R6 := R3
 15 [-]: LOADK     R7 K4        ; R7 := 1
 16 [-]: FORPREP   R5 79        ; R5 -= R7; PC := 79
 17 [-]: GETTABLE  R9 R2 R8     ; R9 := R2[R8]
 18 [-]: LOADNIL   R10 R10      ; R10 := nil
 19 [-]: EQ        0 R9 K5      ; if R9 ~= "-" then PC := 23
 20 [-]: JMP       23           ; PC := 23
 21 [-]: MOVE      R10 R0       ; R10 := R0
 22 [-]: JMP       28           ; PC := 28
 23 [-]: GETGLOBAL R11 K0       ; R11 := gFlashMgr
 24 [-]: SELF      R11 R11 K6   ; R12 := R11; R11 := R11["0x82E67295"]
 25 [-]: MOVE      R13 R9       ; R13 := R9
 26 [-]: CALL      R11 3 2      ; R11 := R11(R12,R13)
 27 [-]: MOVE      R10 R11      ; R10 := R11
 28 [-]: TEST      R10 0        ; if not R10 then PC := 44
 29 [-]: JMP       44           ; PC := 44
 30 [-]: GETUPVAL  R11 U1       ; R11 := U1
 31 [-]: MOVE      R12 R9       ; R12 := R9
 32 [-]: CALL      R11 2 2      ; R11 := R11(R12)
 33 [-]: LOADK     R12 K4       ; R12 := 1
 34 [-]: LEN       R13 R11      ; R13 := # R11
 35 [-]: LOADK     R14 K4       ; R14 := 1
 36 [-]: FORPREP   R12 42       ; R12 -= R14; PC := 42
 37 [-]: GETGLOBAL R16 K2       ; R16 := table
 38 [-]: GETTABLE  R16 R16 K7   ; R16 := R16["0xE6450C9D"]
 39 [-]: MOVE      R17 R4       ; R17 := R4
 40 [-]: GETTABLE  R18 R11 R15  ; R18 := R11[R15]
 41 [-]: CALL      R16 3 1      ; R16(R17,R18)
 42 [-]: FORLOOP   R12 37       ; R12 += R14; if R12 <= R13 then begin PC := 37; R15 := R12 end
 43 [-]: JMP       79           ; PC := 79
 44 [-]: LOADNIL   R16 R16      ; R16 := nil
 45 [-]: EQ        0 R9 K5      ; if R9 ~= "-" then PC := 54
 46 [-]: JMP       54           ; PC := 54
 47 [-]: GETUPVAL  R17 U2       ; R17 := U2
 48 [-]: LOADK     R18 K5       ; R18 := "-"
 49 [-]: MOVE      R19 R0       ; R19 := R0
 50 [-]: GETUPVAL  R20 U3       ; R20 := U3
 51 [-]: CALL      R17 4 2      ; R17 := R17(R18,R19,R20)
 52 [-]: MOVE      R16 R17      ; R16 := R17
 53 [-]: JMP       74           ; PC := 74
 54 [-]: GETGLOBAL R17 K0       ; R17 := gFlashMgr
 55 [-]: SELF      R17 R17 K1   ; R18 := R17; R17 := R17["0xE8FE9496"]
 56 [-]: MOVE      R19 R9       ; R19 := R9
 57 [-]: CALL      R17 3 2      ; R17 := R17(R18,R19)
 58 [-]: MOVE      R18 R0       ; R18 := R0
 59 [-]: GETGLOBAL R19 K0       ; R19 := gFlashMgr
 60 [-]: SELF      R19 R19 K8   ; R20 := R19; R19 := R19["0xE7F47B4C"]
 61 [-]: MOVE      R21 R9       ; R21 := R9
 62 [-]: CALL      R19 3 2      ; R19 := R19(R20,R21)
 63 [-]: TEST      R19 0        ; if not R19 then PC := 66
 64 [-]: JMP       66           ; PC := 66
 65 [-]: MOVE      R18 R1       ; R18 := R1
 66 [-]: GETUPVAL  R19 U2       ; R19 := U2
 67 [-]: MOVE      R20 R17      ; R20 := R17
 68 [-]: MOVE      R21 R18      ; R21 := R18
 69 [-]: GETUPVAL  R22 U4       ; R22 := U4
 70 [-]: GETUPVAL  R23 U5       ; R23 := U5
 71 [-]: MOVE      R24 R9       ; R24 := R9
 72 [-]: CALL      R19 6 2      ; R19 := R19(R20,R21,R22,R23,R24)
 73 [-]: MOVE      R16 R19      ; R16 := R19
 74 [-]: GETGLOBAL R19 K2       ; R19 := table
 75 [-]: GETTABLE  R19 R19 K7   ; R19 := R19["0xE6450C9D"]
 76 [-]: MOVE      R20 R4       ; R20 := R4
 77 [-]: MOVE      R21 R16      ; R21 := R16
 78 [-]: CALL      R19 3 1      ; R19(R20,R21)
 79 [-]: FORLOOP   R5 17        ; R5 += R7; if R5 <= R6 then begin PC := 17; R8 := R5 end
 80 [-]: RETURN    R4 2         ; return R4
 81 [-]: RETURN    R0 1         ; return 


; Function #14:
;
; Name:            
; Defined at line: 349
; #Upvalues:       7
; #Parameters:     0
; Is_vararg:       0
; Max Stack Size:  19

  1 [-]: NEWTABLE  R0 4 0       ; R0 := {}
  2 [-]: LOADK     R1 K0        ; R1 := "AI.ShowDebug"
  3 [-]: LOADK     R2 K1        ; R2 := "App.ShowDebugInfo"
  4 [-]: LOADK     R3 K2        ; R3 := "Client.InfiniteAmmo"
  5 [-]: LOADK     R4 K3        ; R4 := "Client.GodMode"
  6 [-]: SETLIST   R0 4 1       ; R0[(1-1)*FPF+i] := R(0+i), 1 <= i <= 4
  7 [-]: GETUPVAL  R1 U0        ; R1 := U0
  8 [-]: LOADK     R2 K4        ; R2 := "QA Fav"
  9 [-]: LOADK     R3 K5        ; R3 := "subList"
 10 [-]: CALL      R1 3 2       ; R1 := R1(R2,R3)
 11 [-]: LEN       R2 R0        ; R2 := # R0
 12 [-]: LOADK     R3 K6        ; R3 := 1
 13 [-]: MOVE      R4 R2        ; R4 := R2
 14 [-]: LOADK     R5 K6        ; R5 := 1
 15 [-]: FORPREP   R3 29        ; R3 -= R5; PC := 29
 16 [-]: GETTABLE  R7 R0 R6     ; R7 := R0[R6]
 17 [-]: GETGLOBAL R8 K7        ; R8 := gFlashMgr
 18 [-]: SELF      R8 R8 K8     ; R9 := R8; R8 := R8["0x1089D053"]
 19 [-]: MOVE      R10 R7       ; R10 := R7
 20 [-]: CALL      R8 3 2       ; R8 := R8(R9,R10)
 21 [-]: GETUPVAL  R9 U1        ; R9 := U1
 22 [-]: MOVE      R10 R1       ; R10 := R1
 23 [-]: MOVE      R11 R7       ; R11 := R7
 24 [-]: MOVE      R12 R8       ; R12 := R8
 25 [-]: GETUPVAL  R13 U2       ; R13 := U2
 26 [-]: GETUPVAL  R14 U3       ; R14 := U3
 27 [-]: MOVE      R15 R7       ; R15 := R7
 28 [-]: CALL      R9 7 1       ; R9(R10,R11,R12,R13,R14,R15)
 29 [-]: FORLOOP   R3 16        ; R3 += R5; if R3 <= R4 then begin PC := 16; R6 := R3 end
 30 [-]: GETUPVAL  R9 U4        ; R9 := U4
 31 [-]: GETGLOBAL R10 K9       ; R10 := qaMenu
 32 [-]: CALL      R9 2 2       ; R9 := R9(R10)
 33 [-]: LOADK     R10 K6       ; R10 := 1
 34 [-]: LEN       R11 R9       ; R11 := # R9
 35 [-]: LOADK     R12 K6       ; R12 := 1
 36 [-]: FORPREP   R10 42       ; R10 -= R12; PC := 42
 37 [-]: GETGLOBAL R14 K10      ; R14 := table
 38 [-]: GETTABLE  R14 R14 K11  ; R14 := R14["0xE6450C9D"]
 39 [-]: GETTABLE  R15 R1 K12   ; R15 := R1["items"]
 40 [-]: GETTABLE  R16 R9 R13   ; R16 := R9[R13]
 41 [-]: CALL      R14 3 1      ; R14(R15,R16)
 42 [-]: FORLOOP   R10 37       ; R10 += R12; if R10 <= R11 then begin PC := 37; R13 := R10 end
 43 [-]: GETUPVAL  R14 U1       ; R14 := U1
 44 [-]: GETUPVAL  R15 U5       ; R15 := U5
 45 [-]: GETTABLE  R16 R1 K13   ; R16 := R1["name"]
 46 [-]: MOVE      R17 R1       ; R17 := R1
 47 [-]: GETUPVAL  R18 U6       ; R18 := U6
 48 [-]: CALL      R14 5 1      ; R14(R15,R16,R17,R18)
 49 [-]: RETURN    R0 1         ; return 


; Function #15:
;
; Name:            
; Defined at line: 388
; #Upvalues:       0
; #Parameters:     1
; Is_vararg:       0
; Max Stack Size:  3

  1 [-]: GETTABLE  R1 R0 K0     ; R1 := R0["selected"]
  2 [-]: GETTABLE  R2 R0 K1     ; R2 := R0["scrollPos"]
  3 [-]: SUB       R1 R1 R2     ; R1 := R1 - R2
  4 [-]: RETURN    R1 2         ; return R1
  5 [-]: RETURN    R0 1         ; return 


; Function #16:
;
; Name:            
; Defined at line: 397
; #Upvalues:       0
; #Parameters:     1
; Is_vararg:       0
; Max Stack Size:  19

  1 [-]: GETTABLE  R1 R0 K0     ; R1 := R0["flashListName"]
  2 [-]: GETGLOBAL R2 K1        ; R2 := math
  3 [-]: GETTABLE  R2 R2 K2     ; R2 := R2["0x65F9712A"]
  4 [-]: GETTABLE  R3 R0 K3     ; R3 := R0["visibleItems"]
  5 [-]: GETGLOBAL R4 K4        ; R4 := table
  6 [-]: GETTABLE  R4 R4 K5     ; R4 := R4["0xBEA3A82E"]
  7 [-]: GETTABLE  R5 R0 K6     ; R5 := R0["items"]
  8 [-]: CALL      R4 2 0       ; R4,... := R4(R5)
  9 [-]: CALL      R2 0 2       ; R2 := R2(R3,...)
 10 [-]: GETTABLE  R3 R0 K7     ; R3 := R0["scrollPos"]
 11 [-]: ADD       R3 R3 K8     ; R3 := R3 + 1
 12 [-]: LOADK     R4 K9        ; R4 := 0
 13 [-]: LOADK     R5 K10       ; R5 := "_root."
 14 [-]: MOVE      R6 R1        ; R6 := R1
 15 [-]: CONCAT    R5 R5 R6     ; R5 := R5 .. R6
 16 [-]: MOVE      R6 R5        ; R6 := R5
 17 [-]: LOADK     R7 K11       ; R7 := "."
 18 [-]: LOADK     R8 K12       ; R8 := "clearList"
 19 [-]: CONCAT    R6 R6 R8     ; R6 := R6 .. R7 .. R8
 20 [-]: GETGLOBAL R7 K13       ; R7 := 0x8C64AFA9
 21 [-]: GETGLOBAL R8 K14       ; R8 := mMovie
 22 [-]: MOVE      R9 R6        ; R9 := R6
 23 [-]: CALL      R7 3 1       ; R7(R8,R9)
 24 [-]: MOVE      R7 R5        ; R7 := R5
 25 [-]: LOADK     R8 K11       ; R8 := "."
 26 [-]: LOADK     R9 K15       ; R9 := "setItem"
 27 [-]: CONCAT    R6 R7 R9     ; R6 := R7 .. R8 .. R9
 28 [-]: MOVE      R7 R3        ; R7 := R3
 29 [-]: ADD       R8 R2 R3     ; R8 := R2 + R3
 30 [-]: SUB       R8 R8 K8     ; R8 := R8 - 1
 31 [-]: LOADK     R9 K8        ; R9 := 1
 32 [-]: FORPREP   R7 44        ; R7 -= R9; PC := 44
 33 [-]: GETTABLE  R11 R0 K6    ; R11 := R0["items"]
 34 [-]: GETTABLE  R11 R11 R10  ; R11 := R11[R10]
 35 [-]: GETGLOBAL R12 K13      ; R12 := 0x8C64AFA9
 36 [-]: GETGLOBAL R13 K14      ; R13 := mMovie
 37 [-]: MOVE      R14 R6       ; R14 := R6
 38 [-]: GETTABLE  R15 R11 K16  ; R15 := R11["name"]
 39 [-]: MOVE      R16 R4       ; R16 := R4
 40 [-]: GETTABLE  R17 R11 K17  ; R17 := R11["type"]
 41 [-]: GETTABLE  R18 R11 K18  ; R18 := R11["value"]
 42 [-]: CALL      R12 7 1      ; R12(R13,R14,R15,R16,R17,R18)
 43 [-]: ADD       R4 R4 K8     ; R4 := R4 + 1
 44 [-]: FORLOOP   R7 33        ; R7 += R9; if R7 <= R8 then begin PC := 33; R10 := R7 end
 45 [-]: MOVE      R12 R5       ; R12 := R5
 46 [-]: LOADK     R13 K11      ; R13 := "."
 47 [-]: LOADK     R14 K19      ; R14 := "invalidate"
 48 [-]: CONCAT    R6 R12 R14   ; R6 := R12 .. R13 .. R14
 49 [-]: GETGLOBAL R12 K13      ; R12 := 0x8C64AFA9
 50 [-]: GETGLOBAL R13 K14      ; R13 := mMovie
 51 [-]: MOVE      R14 R6       ; R14 := R6
 52 [-]: CALL      R12 3 1      ; R12(R13,R14)
 53 [-]: RETURN    R0 1         ; return 


; Function #17:
;
; Name:            
; Defined at line: 426
; #Upvalues:       3
; #Parameters:     1
; Is_vararg:       0
; Max Stack Size:  9

  1 [-]: EQ        0 R0 K0      ; if R0 ~= 0 then PC := 24
  2 [-]: JMP       24           ; PC := 24
  3 [-]: LOADK     R1 K0        ; R1 := 0
  4 [-]: MOVE      R1 R0        ; R1 := R0
  5 [-]: GETGLOBAL R1 K1        ; R1 := 0x8C64AFA9
  6 [-]: GETGLOBAL R2 K2        ; R2 := mMovie
  7 [-]: LOADK     R3 K3        ; R3 := "_root.showHighlighter"
  8 [-]: MOVE      R4 R0        ; R4 := R0
  9 [-]: CALL      R1 4 1       ; R1(R2,R3,R4)
 10 [-]: GETUPVAL  R1 U1        ; R1 := U1
 11 [-]: GETUPVAL  R2 U2        ; R2 := U2
 12 [-]: CALL      R1 2 2       ; R1 := R1(R2)
 13 [-]: GETGLOBAL R2 K1        ; R2 := 0x8C64AFA9
 14 [-]: GETGLOBAL R3 K2        ; R3 := mMovie
 15 [-]: LOADK     R4 K4        ; R4 := "_root.setSelectorFocus"
 16 [-]: LOADK     R5 K5        ; R5 := "categories"
 17 [-]: SUB       R6 R1 K6     ; R6 := R1 - 1
 18 [-]: CALL      R2 5 1       ; R2(R3,R4,R5,R6)
 19 [-]: GETGLOBAL R2 K1        ; R2 := 0x8C64AFA9
 20 [-]: GETGLOBAL R3 K2        ; R3 := mMovie
 21 [-]: LOADK     R4 K7        ; R4 := "_root.clearSubListFocus"
 22 [-]: CALL      R2 3 1       ; R2(R3,R4)
 23 [-]: JMP       53           ; PC := 53
 24 [-]: EQ        0 R0 K6      ; if R0 ~= 1 then PC := 53
 25 [-]: JMP       53           ; PC := 53
 26 [-]: LOADK     R2 K6        ; R2 := 1
 27 [-]: MOVE      R2 R0        ; R2 := R0
 28 [-]: GETUPVAL  R2 U2        ; R2 := U2
 29 [-]: GETTABLE  R2 R2 K8     ; R2 := R2["items"]
 30 [-]: GETUPVAL  R3 U2        ; R3 := U2
 31 [-]: GETTABLE  R3 R3 K9     ; R3 := R3["selected"]
 32 [-]: GETTABLE  R2 R2 R3     ; R2 := R2[R3]
 33 [-]: GETTABLE  R2 R2 K10    ; R2 := R2["value"]
 34 [-]: GETUPVAL  R3 U1        ; R3 := U1
 35 [-]: MOVE      R4 R2        ; R4 := R2
 36 [-]: CALL      R3 2 2       ; R3 := R3(R4)
 37 [-]: GETGLOBAL R4 K1        ; R4 := 0x8C64AFA9
 38 [-]: GETGLOBAL R5 K2        ; R5 := mMovie
 39 [-]: LOADK     R6 K3        ; R6 := "_root.showHighlighter"
 40 [-]: MOVE      R7 R1        ; R7 := R1
 41 [-]: CALL      R4 4 1       ; R4(R5,R6,R7)
 42 [-]: GETGLOBAL R4 K1        ; R4 := 0x8C64AFA9
 43 [-]: GETGLOBAL R5 K2        ; R5 := mMovie
 44 [-]: LOADK     R6 K11       ; R6 := "_root.setItemFocus"
 45 [-]: SUB       R7 R3 K6     ; R7 := R3 - 1
 46 [-]: CALL      R4 4 1       ; R4(R5,R6,R7)
 47 [-]: GETGLOBAL R4 K1        ; R4 := 0x8C64AFA9
 48 [-]: GETGLOBAL R5 K2        ; R5 := mMovie
 49 [-]: LOADK     R6 K4        ; R6 := "_root.setSelectorFocus"
 50 [-]: LOADK     R7 K12       ; R7 := "subList"
 51 [-]: SUB       R8 R3 K6     ; R8 := R3 - 1
 52 [-]: CALL      R4 5 1       ; R4(R5,R6,R7,R8)
 53 [-]: RETURN    R0 1         ; return 


; Function #18:
;
; Name:            
; Defined at line: 459
; #Upvalues:       0
; #Parameters:     1
; Is_vararg:       0
; Max Stack Size:  8

  1 [-]: GETTABLE  R1 R0 K0     ; R1 := R0["selected"]
  2 [-]: GETTABLE  R2 R0 K1     ; R2 := R0["scrollPos"]
  3 [-]: GETTABLE  R3 R0 K2     ; R3 := R0["visibleItems"]
  4 [-]: ADD       R2 R2 R3     ; R2 := R2 + R3
  5 [-]: LT        0 R2 R1      ; if R2 >= R1 then PC := 12
  6 [-]: JMP       12           ; PC := 12
  7 [-]: GETTABLE  R1 R0 K0     ; R1 := R0["selected"]
  8 [-]: GETTABLE  R2 R0 K2     ; R2 := R0["visibleItems"]
  9 [-]: SUB       R1 R1 R2     ; R1 := R1 - R2
 10 [-]: SETTABLE  R0 K1 R1     ; R0["scrollPos"] := R1
 11 [-]: JMP       19           ; PC := 19
 12 [-]: GETTABLE  R1 R0 K0     ; R1 := R0["selected"]
 13 [-]: GETTABLE  R2 R0 K1     ; R2 := R0["scrollPos"]
 14 [-]: LE        0 R1 R2      ; if R1 > R2 then PC := 19
 15 [-]: JMP       19           ; PC := 19
 16 [-]: GETTABLE  R1 R0 K0     ; R1 := R0["selected"]
 17 [-]: SUB       R1 R1 K3     ; R1 := R1 - 1
 18 [-]: SETTABLE  R0 K1 R1     ; R0["scrollPos"] := R1
 19 [-]: MOVE      R1 R0        ; R1 := R0
 20 [-]: MOVE      R2 R0        ; R2 := R0
 21 [-]: GETTABLE  R3 R0 K1     ; R3 := R0["scrollPos"]
 22 [-]: LT        0 K4 R3      ; if 0 >= R3 then PC := 25
 23 [-]: JMP       25           ; PC := 25
 24 [-]: MOVE      R1 R1        ; R1 := R1
 25 [-]: GETTABLE  R3 R0 K1     ; R3 := R0["scrollPos"]
 26 [-]: GETTABLE  R4 R0 K2     ; R4 := R0["visibleItems"]
 27 [-]: ADD       R3 R3 R4     ; R3 := R3 + R4
 28 [-]: GETTABLE  R4 R0 K5     ; R4 := R0["items"]
 29 [-]: LEN       R4 R4        ; R4 := # R4
 30 [-]: LT        0 R3 R4      ; if R3 >= R4 then PC := 33
 31 [-]: JMP       33           ; PC := 33
 32 [-]: MOVE      R2 R1        ; R2 := R1
 33 [-]: GETGLOBAL R3 K6        ; R3 := 0x8C64AFA9
 34 [-]: GETGLOBAL R4 K7        ; R4 := mMovie
 35 [-]: LOADK     R5 K8        ; R5 := "_root."
 36 [-]: GETTABLE  R6 R0 K9     ; R6 := R0["flashListName"]
 37 [-]: LOADK     R7 K10       ; R7 := ".setArrowVisible"
 38 [-]: CONCAT    R5 R5 R7     ; R5 := R5 .. R6 .. R7
 39 [-]: LOADK     R6 K4        ; R6 := 0
 40 [-]: MOVE      R7 R1        ; R7 := R1
 41 [-]: CALL      R3 5 1       ; R3(R4,R5,R6,R7)
 42 [-]: GETGLOBAL R3 K6        ; R3 := 0x8C64AFA9
 43 [-]: GETGLOBAL R4 K7        ; R4 := mMovie
 44 [-]: LOADK     R5 K8        ; R5 := "_root."
 45 [-]: GETTABLE  R6 R0 K9     ; R6 := R0["flashListName"]
 46 [-]: LOADK     R7 K10       ; R7 := ".setArrowVisible"
 47 [-]: CONCAT    R5 R5 R7     ; R5 := R5 .. R6 .. R7
 48 [-]: LOADK     R6 K3        ; R6 := 1
 49 [-]: MOVE      R7 R2        ; R7 := R2
 50 [-]: CALL      R3 5 1       ; R3(R4,R5,R6,R7)
 51 [-]: RETURN    R0 1         ; return 


; Function #19:
;
; Name:            
; Defined at line: 488
; #Upvalues:       5
; #Parameters:     1
; Is_vararg:       0
; Max Stack Size:  9

  1 [-]: GETUPVAL  R1 U0        ; R1 := U0
  2 [-]: MOVE      R2 R0        ; R2 := R0
  3 [-]: CALL      R1 2 1       ; R1(R2)
  4 [-]: GETUPVAL  R1 U1        ; R1 := U1
  5 [-]: MOVE      R2 R0        ; R2 := R0
  6 [-]: CALL      R1 2 1       ; R1(R2)
  7 [-]: GETTABLE  R1 R0 K0     ; R1 := R0["onValidate"]
  8 [-]: EQ        1 R1 K1      ; if R1 == nil then PC := 12
  9 [-]: JMP       12           ; PC := 12
 10 [-]: SELF      R1 R0 K2     ; R2 := R0; R1 := R0["0x417EDD03"]
 11 [-]: CALL      R1 2 1       ; R1(R2)
 12 [-]: GETUPVAL  R1 U2        ; R1 := U2
 13 [-]: EQ        0 R1 K3      ; if R1 ~= 0 then PC := 26
 14 [-]: JMP       26           ; PC := 26
 15 [-]: GETUPVAL  R1 U3        ; R1 := U3
 16 [-]: GETUPVAL  R2 U4        ; R2 := U4
 17 [-]: CALL      R1 2 2       ; R1 := R1(R2)
 18 [-]: SUB       R1 R1 K4     ; R1 := R1 - 1
 19 [-]: GETGLOBAL R2 K5        ; R2 := 0x8C64AFA9
 20 [-]: GETGLOBAL R3 K6        ; R3 := mMovie
 21 [-]: LOADK     R4 K7        ; R4 := "_root.setSelectorFocus"
 22 [-]: LOADK     R5 K8        ; R5 := "categories"
 23 [-]: MOVE      R6 R1        ; R6 := R1
 24 [-]: CALL      R2 5 1       ; R2(R3,R4,R5,R6)
 25 [-]: JMP       50           ; PC := 50
 26 [-]: GETUPVAL  R2 U2        ; R2 := U2
 27 [-]: EQ        0 R2 K4      ; if R2 ~= 1 then PC := 50
 28 [-]: JMP       50           ; PC := 50
 29 [-]: GETUPVAL  R2 U4        ; R2 := U4
 30 [-]: GETTABLE  R2 R2 K9     ; R2 := R2["items"]
 31 [-]: GETUPVAL  R3 U4        ; R3 := U4
 32 [-]: GETTABLE  R3 R3 K10    ; R3 := R3["selected"]
 33 [-]: GETTABLE  R2 R2 R3     ; R2 := R2[R3]
 34 [-]: GETTABLE  R2 R2 K11    ; R2 := R2["value"]
 35 [-]: GETUPVAL  R3 U3        ; R3 := U3
 36 [-]: MOVE      R4 R2        ; R4 := R2
 37 [-]: CALL      R3 2 2       ; R3 := R3(R4)
 38 [-]: SUB       R3 R3 K4     ; R3 := R3 - 1
 39 [-]: GETGLOBAL R4 K5        ; R4 := 0x8C64AFA9
 40 [-]: GETGLOBAL R5 K6        ; R5 := mMovie
 41 [-]: LOADK     R6 K12       ; R6 := "_root.setItemFocus"
 42 [-]: MOVE      R7 R3        ; R7 := R3
 43 [-]: CALL      R4 4 1       ; R4(R5,R6,R7)
 44 [-]: GETGLOBAL R4 K5        ; R4 := 0x8C64AFA9
 45 [-]: GETGLOBAL R5 K6        ; R5 := mMovie
 46 [-]: LOADK     R6 K7        ; R6 := "_root.setSelectorFocus"
 47 [-]: LOADK     R7 K13       ; R7 := "subList"
 48 [-]: MOVE      R8 R3        ; R8 := R3
 49 [-]: CALL      R4 5 1       ; R4(R5,R6,R7,R8)
 50 [-]: RETURN    R0 1         ; return 


; Function #20:
;
; Name:            
; Defined at line: 520
; #Upvalues:       3
; #Parameters:     1
; Is_vararg:       0
; Max Stack Size:  13

  1 [-]: EQ        1 R0 K0      ; if R0 == nil then PC := 5
  2 [-]: JMP       5            ; PC := 5
  3 [-]: EQ        0 R0 K1      ; if R0 ~= 0 then PC := 7
  4 [-]: JMP       7            ; PC := 7
  5 [-]: LOADNIL   R1 R1        ; R1 := nil
  6 [-]: RETURN    R1 2         ; return R1
  7 [-]: LOADNIL   R1 R2        ; R1 := R2 := nil
  8 [-]: GETUPVAL  R3 U0        ; R3 := U0
  9 [-]: EQ        0 R3 K1      ; if R3 ~= 0 then PC := 14
 10 [-]: JMP       14           ; PC := 14
 11 [-]: GETUPVAL  R1 U1        ; R1 := U1
 12 [-]: LOADK     R2 K2        ; R2 := "categories"
 13 [-]: JMP       21           ; PC := 21
 14 [-]: GETUPVAL  R3 U1        ; R3 := U1
 15 [-]: GETTABLE  R3 R3 K3     ; R3 := R3["items"]
 16 [-]: GETUPVAL  R4 U1        ; R4 := U1
 17 [-]: GETTABLE  R4 R4 K4     ; R4 := R4["selected"]
 18 [-]: GETTABLE  R3 R3 R4     ; R3 := R3[R4]
 19 [-]: GETTABLE  R1 R3 K5     ; R1 := R3["value"]
 20 [-]: LOADK     R2 K6        ; R2 := "subList"
 21 [-]: GETGLOBAL R3 K7        ; R3 := table
 22 [-]: GETTABLE  R3 R3 K8     ; R3 := R3["0xBEA3A82E"]
 23 [-]: GETTABLE  R4 R1 K3     ; R4 := R1["items"]
 24 [-]: CALL      R3 2 2       ; R3 := R3(R4)
 25 [-]: LOADNIL   R4 R4        ; R4 := nil
 26 [-]: GETGLOBAL R5 K9        ; R5 := math
 27 [-]: GETTABLE  R5 R5 K10    ; R5 := R5["0xF93F7CC8"]
 28 [-]: GETTABLE  R6 R1 K4     ; R6 := R1["selected"]
 29 [-]: ADD       R6 R6 R3     ; R6 := R6 + R3
 30 [-]: ADD       R6 R6 R0     ; R6 := R6 + R0
 31 [-]: CALL      R5 2 2       ; R5 := R5(R6)
 32 [-]: SUB       R4 R5 K11    ; R4 := R5 - 1
 33 [-]: GETGLOBAL R5 K9        ; R5 := math
 34 [-]: GETTABLE  R5 R5 K12    ; R5 := R5["0x32396E6F"]
 35 [-]: MOVE      R6 R4        ; R6 := R4
 36 [-]: MOVE      R7 R3        ; R7 := R3
 37 [-]: CALL      R5 3 2       ; R5 := R5(R6,R7)
 38 [-]: ADD       R5 R5 K11    ; R5 := R5 + 1
 39 [-]: SETTABLE  R1 K4 R5     ; R1["selected"] := R5
 40 [-]: LOADK     R5 K1        ; R5 := 0
 41 [-]: GETTABLE  R6 R1 K4     ; R6 := R1["selected"]
 42 [-]: GETTABLE  R7 R1 K4     ; R7 := R1["selected"]
 43 [-]: MOVE      R8 R3        ; R8 := R3
 44 [-]: LOADK     R9 K11       ; R9 := 1
 45 [-]: FORPREP   R7 74        ; R7 -= R9; PC := 74
 46 [-]: LT        0 R3 R6      ; if R3 >= R6 then PC := 50
 47 [-]: JMP       50           ; PC := 50
 48 [-]: LOADK     R6 K11       ; R6 := 1
 49 [-]: JMP       53           ; PC := 53
 50 [-]: LT        0 R6 K11     ; if R6 >= 1 then PC := 53
 51 [-]: JMP       53           ; PC := 53
 52 [-]: MOVE      R6 R3        ; R6 := R3
 53 [-]: ADD       R5 R5 K11    ; R5 := R5 + 1
 54 [-]: GETTABLE  R11 R1 K3    ; R11 := R1["items"]
 55 [-]: GETTABLE  R11 R11 R6   ; R11 := R11[R6]
 56 [-]: GETTABLE  R11 R11 K13  ; R11 := R11["selectable"]
 57 [-]: EQ        0 R11 K14    ; if R11 ~= "0x1" then PC := 62
 58 [-]: JMP       62           ; PC := 62
 59 [-]: SETTABLE  R1 K4 R6     ; R1["selected"] := R6
 60 [-]: JMP       75           ; PC := 75
 61 [-]: JMP       69           ; PC := 69
 62 [-]: EQ        0 R5 R3      ; if R5 ~= R3 then PC := 69
 63 [-]: JMP       69           ; PC := 69
 64 [-]: GETGLOBAL R11 K15      ; R11 := 0x3BAEBAA3
 65 [-]: LOADK     R12 K16      ; R12 := "This list contains all non-selectable items. Invalid."
 66 [-]: CALL      R11 2 1      ; R11(R12)
 67 [-]: SETTABLE  R1 K4 K0     ; R1["selected"] := nil
 68 [-]: JMP       75           ; PC := 75
 69 [-]: LT        0 K1 R0      ; if 0 >= R0 then PC := 73
 70 [-]: JMP       73           ; PC := 73
 71 [-]: ADD       R6 R6 K11    ; R6 := R6 + 1
 72 [-]: JMP       74           ; PC := 74
 73 [-]: SUB       R6 R6 K11    ; R6 := R6 - 1
 74 [-]: FORLOOP   R7 46        ; R7 += R9; if R7 <= R8 then begin PC := 46; R10 := R7 end
 75 [-]: GETUPVAL  R11 U2       ; R11 := U2
 76 [-]: MOVE      R12 R1       ; R12 := R1
 77 [-]: CALL      R11 2 1      ; R11(R12)
 78 [-]: GETTABLE  R11 R1 K17   ; R11 := R1["onScroll"]
 79 [-]: TEST      R11 0        ; if not R11 then PC := 83
 80 [-]: JMP       83           ; PC := 83
 81 [-]: SELF      R11 R1 K18   ; R12 := R1; R11 := R1["0x16828058"]
 82 [-]: CALL      R11 2 1      ; R11(R12)
 83 [-]: RETURN    R0 1         ; return 


; Function #21:
;
; Name:            
; Defined at line: 586
; #Upvalues:       2
; #Parameters:     2
; Is_vararg:       0
; Max Stack Size:  7

  1 [-]: GETUPVAL  R2 U0        ; R2 := U0
  2 [-]: MOVE      R3 R0        ; R3 := R0
  3 [-]: CALL      R2 2 2       ; R2 := R2(R3)
  4 [-]: GETGLOBAL R3 K0        ; R3 := 0x8C64AFA9
  5 [-]: GETGLOBAL R4 K1        ; R4 := mMovie
  6 [-]: LOADK     R5 K2        ; R5 := "_root.setSelectedCategory"
  7 [-]: SUB       R6 R2 K3     ; R6 := R2 - 1
  8 [-]: CALL      R3 4 1       ; R3(R4,R5,R6)
  9 [-]: GETTABLE  R3 R0 K4     ; R3 := R0["items"]
 10 [-]: GETTABLE  R4 R0 K5     ; R4 := R0["selected"]
 11 [-]: GETTABLE  R3 R3 R4     ; R3 := R3[R4]
 12 [-]: GETTABLE  R3 R3 K6     ; R3 := R3["value"]
 13 [-]: GETUPVAL  R4 U0        ; R4 := U0
 14 [-]: MOVE      R5 R3        ; R5 := R3
 15 [-]: CALL      R4 2 2       ; R4 := R4(R5)
 16 [-]: SUB       R4 R4 K3     ; R4 := R4 - 1
 17 [-]: GETUPVAL  R5 U1        ; R5 := U1
 18 [-]: MOVE      R6 R3        ; R6 := R3
 19 [-]: CALL      R5 2 1       ; R5(R6)
 20 [-]: RETURN    R0 1         ; return 


; Function #22:
;
; Name:            
; Defined at line: 602
; #Upvalues:       1
; #Parameters:     2
; Is_vararg:       0
; Max Stack Size:  4

  1 [-]: GETUPVAL  R2 U0        ; R2 := U0
  2 [-]: LOADK     R3 K0        ; R3 := 1
  3 [-]: CALL      R2 2 1       ; R2(R3)
  4 [-]: RETURN    R0 1         ; return 


; Function #23:
;
; Name:            
; Defined at line: 611
; #Upvalues:       3
; #Parameters:     1
; Is_vararg:       0
; Max Stack Size:  6

  1 [-]: GETUPVAL  R1 U0        ; R1 := U0
  2 [-]: GETTABLE  R1 R1 K0     ; R1 := R1["items"]
  3 [-]: GETUPVAL  R2 U0        ; R2 := U0
  4 [-]: GETTABLE  R2 R2 K1     ; R2 := R2["selected"]
  5 [-]: GETTABLE  R1 R1 R2     ; R1 := R1[R2]
  6 [-]: GETTABLE  R1 R1 K2     ; R1 := R1["value"]
  7 [-]: GETTABLE  R2 R1 K3     ; R2 := R1["scrollPos"]
  8 [-]: ADD       R2 R2 R0     ; R2 := R2 + R0
  9 [-]: ADD       R0 R2 K4     ; R0 := R2 + 1
 10 [-]: GETTABLE  R2 R1 K0     ; R2 := R1["items"]
 11 [-]: GETTABLE  R2 R2 R0     ; R2 := R2[R0]
 12 [-]: GETUPVAL  R3 U1        ; R3 := U1
 13 [-]: EQ        1 R3 K4      ; if R3 == 1 then PC := 19
 14 [-]: JMP       19           ; PC := 19
 15 [-]: SETTABLE  R1 K1 R0     ; R1["selected"] := R0
 16 [-]: GETUPVAL  R3 U2        ; R3 := U2
 17 [-]: LOADK     R4 K4        ; R4 := 1
 18 [-]: CALL      R3 2 1       ; R3(R4)
 19 [-]: GETTABLE  R3 R2 K5     ; R3 := R2["callback"]
 20 [-]: EQ        1 R3 K6      ; if R3 == nil then PC := 25
 21 [-]: JMP       25           ; PC := 25
 22 [-]: SELF      R3 R2 K7     ; R4 := R2; R3 := R2["0xB775F1C7"]
 23 [-]: MOVE      R5 R1        ; R5 := R1
 24 [-]: CALL      R3 3 1       ; R3(R4,R5)
 25 [-]: RETURN    R0 1         ; return 


; Function #24:
;
; Name:            
; Defined at line: 662
; #Upvalues:       1
; #Parameters:     0
; Is_vararg:       0
; Max Stack Size:  2

  1 [-]: GETUPVAL  R0 U0        ; R0 := U0
  2 [-]: LOADK     R1 K0        ; R1 := 1
  3 [-]: CALL      R0 2 1       ; R0(R1)
  4 [-]: RETURN    R0 1         ; return 


; Function #25:
;
; Name:            
; Defined at line: 669
; #Upvalues:       1
; #Parameters:     0
; Is_vararg:       0
; Max Stack Size:  2

  1 [-]: GETUPVAL  R0 U0        ; R0 := U0
  2 [-]: LOADK     R1 K0        ; R1 := -1
  3 [-]: CALL      R0 2 1       ; R0(R1)
  4 [-]: RETURN    R0 1         ; return 


; Function #26:
;
; Name:            
; Defined at line: 676
; #Upvalues:       2
; #Parameters:     0
; Is_vararg:       0
; Max Stack Size:  2

  1 [-]: GETUPVAL  R0 U0        ; R0 := U0
  2 [-]: EQ        0 R0 K0      ; if R0 ~= 0 then PC := 8
  3 [-]: JMP       8            ; PC := 8
  4 [-]: GETUPVAL  R0 U1        ; R0 := U1
  5 [-]: LOADK     R1 K1        ; R1 := 1
  6 [-]: CALL      R0 2 1       ; R0(R1)
  7 [-]: JMP       11           ; PC := 11
  8 [-]: GETUPVAL  R0 U1        ; R0 := U1
  9 [-]: LOADK     R1 K0        ; R1 := 0
 10 [-]: CALL      R0 2 1       ; R0(R1)
 11 [-]: RETURN    R0 1         ; return 


; Function #27:
;
; Name:            
; Defined at line: 686
; #Upvalues:       2
; #Parameters:     0
; Is_vararg:       0
; Max Stack Size:  2

  1 [-]: GETUPVAL  R0 U0        ; R0 := U0
  2 [-]: EQ        0 R0 K0      ; if R0 ~= 0 then PC := 8
  3 [-]: JMP       8            ; PC := 8
  4 [-]: GETUPVAL  R0 U1        ; R0 := U1
  5 [-]: LOADK     R1 K1        ; R1 := 1
  6 [-]: CALL      R0 2 1       ; R0(R1)
  7 [-]: JMP       11           ; PC := 11
  8 [-]: GETUPVAL  R0 U1        ; R0 := U1
  9 [-]: LOADK     R1 K0        ; R1 := 0
 10 [-]: CALL      R0 2 1       ; R0(R1)
 11 [-]: RETURN    R0 1         ; return 


; Function #28:
;
; Name:            
; Defined at line: 699
; #Upvalues:       1
; #Parameters:     0
; Is_vararg:       0
; Max Stack Size:  2

  1 [-]: GETUPVAL  R0 U0        ; R0 := U0
  2 [-]: CALL      R0 1 1       ; R0()
  3 [-]: MOVE      R0 R1        ; R0 := R1
  4 [-]: RETURN    R0 2         ; return R0
  5 [-]: RETURN    R0 1         ; return 


; Function #29:
;
; Name:            
; Defined at line: 705
; #Upvalues:       1
; #Parameters:     0
; Is_vararg:       0
; Max Stack Size:  2

  1 [-]: GETUPVAL  R0 U0        ; R0 := U0
  2 [-]: CALL      R0 1 1       ; R0()
  3 [-]: MOVE      R0 R1        ; R0 := R1
  4 [-]: RETURN    R0 2         ; return R0
  5 [-]: RETURN    R0 1         ; return 


; Function #30:
;
; Name:            
; Defined at line: 711
; #Upvalues:       1
; #Parameters:     0
; Is_vararg:       0
; Max Stack Size:  2

  1 [-]: GETUPVAL  R0 U0        ; R0 := U0
  2 [-]: CALL      R0 1 1       ; R0()
  3 [-]: MOVE      R0 R1        ; R0 := R1
  4 [-]: RETURN    R0 2         ; return R0
  5 [-]: RETURN    R0 1         ; return 


; Function #31:
;
; Name:            
; Defined at line: 717
; #Upvalues:       1
; #Parameters:     0
; Is_vararg:       0
; Max Stack Size:  2

  1 [-]: GETUPVAL  R0 U0        ; R0 := U0
  2 [-]: CALL      R0 1 1       ; R0()
  3 [-]: MOVE      R0 R1        ; R0 := R1
  4 [-]: RETURN    R0 2         ; return R0
  5 [-]: RETURN    R0 1         ; return 


; Function #32:
;
; Name:            
; Defined at line: 725
; #Upvalues:       1
; #Parameters:     0
; Is_vararg:       0
; Max Stack Size:  2

  1 [-]: GETUPVAL  R0 U0        ; R0 := U0
  2 [-]: CALL      R0 1 1       ; R0()
  3 [-]: MOVE      R0 R1        ; R0 := R1
  4 [-]: RETURN    R0 2         ; return R0
  5 [-]: RETURN    R0 1         ; return 


; Function #33:
;
; Name:            
; Defined at line: 730
; #Upvalues:       1
; #Parameters:     0
; Is_vararg:       0
; Max Stack Size:  2

  1 [-]: GETUPVAL  R0 U0        ; R0 := U0
  2 [-]: CALL      R0 1 1       ; R0()
  3 [-]: MOVE      R0 R1        ; R0 := R1
  4 [-]: RETURN    R0 2         ; return R0
  5 [-]: RETURN    R0 1         ; return 


; Function #34:
;
; Name:            
; Defined at line: 735
; #Upvalues:       1
; #Parameters:     0
; Is_vararg:       0
; Max Stack Size:  2

  1 [-]: GETUPVAL  R0 U0        ; R0 := U0
  2 [-]: CALL      R0 1 1       ; R0()
  3 [-]: MOVE      R0 R1        ; R0 := R1
  4 [-]: RETURN    R0 2         ; return R0
  5 [-]: RETURN    R0 1         ; return 


; Function #35:
;
; Name:            
; Defined at line: 740
; #Upvalues:       1
; #Parameters:     0
; Is_vararg:       0
; Max Stack Size:  2

  1 [-]: GETUPVAL  R0 U0        ; R0 := U0
  2 [-]: CALL      R0 1 1       ; R0()
  3 [-]: MOVE      R0 R1        ; R0 := R1
  4 [-]: RETURN    R0 2         ; return R0
  5 [-]: RETURN    R0 1         ; return 


; Function #36:
;
; Name:            
; Defined at line: 746
; #Upvalues:       1
; #Parameters:     0
; Is_vararg:       0
; Max Stack Size:  2

  1 [-]: GETUPVAL  R0 U0        ; R0 := U0
  2 [-]: LOADK     R1 K0        ; R1 := -3
  3 [-]: CALL      R0 2 1       ; R0(R1)
  4 [-]: MOVE      R0 R1        ; R0 := R1
  5 [-]: RETURN    R0 2         ; return R0
  6 [-]: RETURN    R0 1         ; return 


; Function #37:
;
; Name:            
; Defined at line: 753
; #Upvalues:       1
; #Parameters:     0
; Is_vararg:       0
; Max Stack Size:  2

  1 [-]: GETUPVAL  R0 U0        ; R0 := U0
  2 [-]: LOADK     R1 K0        ; R1 := 3
  3 [-]: CALL      R0 2 1       ; R0(R1)
  4 [-]: MOVE      R0 R1        ; R0 := R1
  5 [-]: RETURN    R0 2         ; return R0
  6 [-]: RETURN    R0 1         ; return 


; Function #38:
;
; Name:            
; Defined at line: 764
; #Upvalues:       3
; #Parameters:     0
; Is_vararg:       0
; Max Stack Size:  5

  1 [-]: GETGLOBAL R0 K0        ; R0 := 0x93B1256B
  2 [-]: LOADK     R1 K1        ; R1 := "SELECT"
  3 [-]: CALL      R0 2 1       ; R0(R1)
  4 [-]: LOADNIL   R0 R0        ; R0 := nil
  5 [-]: GETUPVAL  R1 U0        ; R1 := U0
  6 [-]: EQ        0 R1 K2      ; if R1 ~= 0 then PC := 10
  7 [-]: JMP       10           ; PC := 10
  8 [-]: GETUPVAL  R0 U1        ; R0 := U1
  9 [-]: JMP       19           ; PC := 19
 10 [-]: GETUPVAL  R1 U0        ; R1 := U0
 11 [-]: EQ        0 R1 K3      ; if R1 ~= 1 then PC := 19
 12 [-]: JMP       19           ; PC := 19
 13 [-]: GETUPVAL  R1 U1        ; R1 := U1
 14 [-]: GETTABLE  R1 R1 K4     ; R1 := R1["items"]
 15 [-]: GETUPVAL  R2 U1        ; R2 := U1
 16 [-]: GETTABLE  R2 R2 K5     ; R2 := R2["selected"]
 17 [-]: GETTABLE  R1 R1 R2     ; R1 := R1[R2]
 18 [-]: GETTABLE  R0 R1 K6     ; R0 := R1["value"]
 19 [-]: GETTABLE  R1 R0 K7     ; R1 := R0["onPress"]
 20 [-]: EQ        1 R1 K8      ; if R1 == nil then PC := 24
 21 [-]: JMP       24           ; PC := 24
 22 [-]: SELF      R1 R0 K9     ; R2 := R0; R1 := R0["0x6530DD2C"]
 23 [-]: CALL      R1 2 1       ; R1(R2)
 24 [-]: GETTABLE  R1 R0 K4     ; R1 := R0["items"]
 25 [-]: GETTABLE  R2 R0 K5     ; R2 := R0["selected"]
 26 [-]: GETTABLE  R1 R1 R2     ; R1 := R1[R2]
 27 [-]: GETTABLE  R2 R1 K10    ; R2 := R1["callback"]
 28 [-]: EQ        1 R2 K8      ; if R2 == nil then PC := 33
 29 [-]: JMP       33           ; PC := 33
 30 [-]: SELF      R2 R1 K11    ; R3 := R1; R2 := R1["0xB775F1C7"]
 31 [-]: MOVE      R4 R0        ; R4 := R0
 32 [-]: CALL      R2 3 1       ; R2(R3,R4)
 33 [-]: GETUPVAL  R2 U2        ; R2 := U2
 34 [-]: MOVE      R3 R0        ; R3 := R0
 35 [-]: CALL      R2 2 1       ; R2(R3)
 36 [-]: MOVE      R2 R1        ; R2 := R1
 37 [-]: RETURN    R2 2         ; return R2
 38 [-]: RETURN    R0 1         ; return 


; Function #39:
;
; Name:            
; Defined at line: 795
; #Upvalues:       2
; #Parameters:     0
; Is_vararg:       0
; Max Stack Size:  2

  1 [-]: GETUPVAL  R0 U0        ; R0 := U0
  2 [-]: EQ        0 R0 K0      ; if R0 ~= 0 then PC := 8
  3 [-]: JMP       8            ; PC := 8
  4 [-]: GETGLOBAL R0 K1        ; R0 := mMovie
  5 [-]: SELF      R0 R0 K2     ; R1 := R0; R0 := R0["0xA58BB96C"]
  6 [-]: CALL      R0 2 1       ; R0(R1)
  7 [-]: JMP       11           ; PC := 11
  8 [-]: GETUPVAL  R0 U1        ; R0 := U1
  9 [-]: LOADK     R1 K0        ; R1 := 0
 10 [-]: CALL      R0 2 1       ; R0(R1)
 11 [-]: MOVE      R0 R1        ; R0 := R1
 12 [-]: RETURN    R0 2         ; return R0
 13 [-]: RETURN    R0 1         ; return 


; Function #40:
;
; Name:            
; Defined at line: 810
; #Upvalues:       0
; #Parameters:     0
; Is_vararg:       0
; Max Stack Size:  2

  1 [-]: GETGLOBAL R0 K0        ; R0 := mMovie
  2 [-]: SELF      R0 R0 K1     ; R1 := R0; R0 := R0["0xA58BB96C"]
  3 [-]: CALL      R0 2 1       ; R0(R1)
  4 [-]: RETURN    R0 1         ; return 


; Function #41:
;
; Name:            
; Defined at line: 817
; #Upvalues:       14
; #Parameters:     0
; Is_vararg:       0
; Max Stack Size:  16

  1 [-]: GETUPVAL  R0 U1        ; R0 := U1
  2 [-]: LOADK     R1 K0        ; R1 := "categories"
  3 [-]: LOADK     R2 K0        ; R2 := "categories"
  4 [-]: CALL      R0 3 2       ; R0 := R0(R1,R2)
  5 [-]: MOVE      R0 R0        ; R0 := R0
  6 [-]: GETUPVAL  R0 U0        ; R0 := U0
  7 [-]: GETUPVAL  R1 U2        ; R1 := U2
  8 [-]: SETTABLE  R0 K1 R1     ; R0["onScroll"] := R1
  9 [-]: GETUPVAL  R0 U0        ; R0 := U0
 10 [-]: GETUPVAL  R1 U3        ; R1 := U3
 11 [-]: SETTABLE  R0 K2 R1     ; R0["onPress"] := R1
 12 [-]: GETUPVAL  R0 U4        ; R0 := U4
 13 [-]: CALL      R0 1 1       ; R0()
 14 [-]: GETUPVAL  R0 U5        ; R0 := U5
 15 [-]: CALL      R0 1 1       ; R0()
 16 [-]: GETUPVAL  R0 U6        ; R0 := U6
 17 [-]: GETGLOBAL R1 K3        ; R1 := visModesMenu
 18 [-]: CALL      R0 2 2       ; R0 := R0(R1)
 19 [-]: GETUPVAL  R1 U1        ; R1 := U1
 20 [-]: LOADK     R2 K4        ; R2 := "Vis Modes"
 21 [-]: LOADK     R3 K5        ; R3 := "subList"
 22 [-]: CALL      R1 3 2       ; R1 := R1(R2,R3)
 23 [-]: LOADK     R2 K6        ; R2 := 1
 24 [-]: LEN       R3 R0        ; R3 := # R0
 25 [-]: LOADK     R4 K6        ; R4 := 1
 26 [-]: FORPREP   R2 32        ; R2 -= R4; PC := 32
 27 [-]: GETGLOBAL R6 K7        ; R6 := table
 28 [-]: GETTABLE  R6 R6 K8     ; R6 := R6["0xE6450C9D"]
 29 [-]: GETTABLE  R7 R1 K9     ; R7 := R1["items"]
 30 [-]: GETTABLE  R8 R0 R5     ; R8 := R0[R5]
 31 [-]: CALL      R6 3 1       ; R6(R7,R8)
 32 [-]: FORLOOP   R2 27        ; R2 += R4; if R2 <= R3 then begin PC := 27; R5 := R2 end
 33 [-]: GETUPVAL  R6 U7        ; R6 := U7
 34 [-]: GETUPVAL  R7 U0        ; R7 := U0
 35 [-]: LOADK     R8 K4        ; R8 := "Vis Modes"
 36 [-]: MOVE      R9 R1        ; R9 := R1
 37 [-]: GETUPVAL  R10 U8       ; R10 := U8
 38 [-]: CALL      R6 5 1       ; R6(R7,R8,R9,R10)
 39 [-]: GETUPVAL  R6 U9        ; R6 := U9
 40 [-]: CALL      R6 1 1       ; R6()
 41 [-]: GETUPVAL  R6 U7        ; R6 := U7
 42 [-]: GETUPVAL  R7 U0        ; R7 := U0
 43 [-]: LOADK     R8 K10       ; R8 := "-"
 44 [-]: MOVE      R9 R0        ; R9 := R0
 45 [-]: GETUPVAL  R10 U10      ; R10 := U10
 46 [-]: CALL      R6 5 1       ; R6(R7,R8,R9,R10)
 47 [-]: GETUPVAL  R6 U11       ; R6 := U11
 48 [-]: CALL      R6 1 2       ; R6 := R6()
 49 [-]: LOADK     R7 K6        ; R7 := 1
 50 [-]: GETGLOBAL R8 K7        ; R8 := table
 51 [-]: GETTABLE  R8 R8 K11    ; R8 := R8["0xBEA3A82E"]
 52 [-]: MOVE      R9 R6        ; R9 := R6
 53 [-]: CALL      R8 2 2       ; R8 := R8(R9)
 54 [-]: LOADK     R9 K6        ; R9 := 1
 55 [-]: FORPREP   R7 65        ; R7 -= R9; PC := 65
 56 [-]: GETTABLE  R11 R6 R10   ; R11 := R6[R10]
 57 [-]: SETTABLE  R11 K12 K5   ; R11["flashListName"] := "subList"
 58 [-]: GETUPVAL  R11 U7       ; R11 := U7
 59 [-]: GETUPVAL  R12 U0       ; R12 := U0
 60 [-]: GETTABLE  R13 R6 R10   ; R13 := R6[R10]
 61 [-]: GETTABLE  R13 R13 K13  ; R13 := R13["name"]
 62 [-]: GETTABLE  R14 R6 R10   ; R14 := R6[R10]
 63 [-]: GETUPVAL  R15 U8       ; R15 := U8
 64 [-]: CALL      R11 5 1      ; R11(R12,R13,R14,R15)
 65 [-]: FORLOOP   R7 56        ; R7 += R9; if R7 <= R8 then begin PC := 56; R10 := R7 end
 66 [-]: GETGLOBAL R11 K14      ; R11 := 0x8C64AFA9
 67 [-]: GETGLOBAL R12 K15      ; R12 := mMovie
 68 [-]: LOADK     R13 K16      ; R13 := "init"
 69 [-]: CALL      R11 3 1      ; R11(R12,R13)
 70 [-]: GETUPVAL  R11 U12      ; R11 := U12
 71 [-]: LOADK     R12 K17      ; R12 := 0
 72 [-]: CALL      R11 2 1      ; R11(R12)
 73 [-]: GETUPVAL  R11 U13      ; R11 := U13
 74 [-]: GETUPVAL  R12 U0       ; R12 := U0
 75 [-]: CALL      R11 2 1      ; R11(R12)
 76 [-]: GETUPVAL  R11 U0       ; R11 := U0
 77 [-]: SELF      R11 R11 K18  ; R12 := R11; R11 := R11["0x16828058"]
 78 [-]: CALL      R11 2 1      ; R11(R12)
 79 [-]: RETURN    R0 1         ; return 


