code size: 23
code size: 3
code size: 21
code size: 5
code size: 5
code size: 5
code size: 5
code size: 5
; This file has been disassembled using luadec 2.0.2 by sztupy (http://winmo.sztupy.hu)
; Command line was: -dis M:\git repos\warframe-lua-disassembled\B.Font.cache_extracted\Lotus\Scripts\Restoratives\CorruptedKey.luac 

; Name:            
; Defined at line: 0
; #Upvalues:       0
; #Parameters:     0
; Is_vararg:       2
; Max Stack Size:  3

  1 [-]: CLOSURE   R0 0         ; R0 := closure(Function #1)
  2 [-]: SETGLOBAL R0 K0        ; EvaluateUseKey := R0
  3 [-]: SETGLOBAL R0 K1        ; 0xB0AB3D6 := R0
  4 [-]: CLOSURE   R0 1         ; R0 := closure(Function #2)
  5 [-]: CLOSURE   R1 2         ; R1 := closure(Function #3)
  6 [-]: MOVE      R0 R0        ; R0 := R0
  7 [-]: CLOSURE   R2 3         ; R2 := closure(Function #4)
  8 [-]: MOVE      R0 R1        ; R0 := R1
  9 [-]: SETGLOBAL R2 K2        ; HealthKeyOnUse := R2
 10 [-]: SETGLOBAL R2 K3        ; 0x13B73CC8 := R2
 11 [-]: CLOSURE   R2 4         ; R2 := closure(Function #5)
 12 [-]: MOVE      R0 R1        ; R0 := R1
 13 [-]: SETGLOBAL R2 K4        ; ShieldKeyOnUse := R2
 14 [-]: SETGLOBAL R2 K5        ; 0x70375D6B := R2
 15 [-]: CLOSURE   R2 5         ; R2 := closure(Function #6)
 16 [-]: MOVE      R0 R1        ; R0 := R1
 17 [-]: SETGLOBAL R2 K6        ; DamageKeyOnUse := R2
 18 [-]: SETGLOBAL R2 K7        ; 0x8CA8E463 := R2
 19 [-]: CLOSURE   R2 6         ; R2 := closure(Function #7)
 20 [-]: MOVE      R0 R1        ; R0 := R1
 21 [-]: SETGLOBAL R2 K8        ; SpeedKeyOnUse := R2
 22 [-]: SETGLOBAL R2 K9        ; 0x60A4D4F0 := R2
 23 [-]: RETURN    R0 1         ; return 


; Function #1:
;
; Name:            
; Defined at line: 3
; #Upvalues:       0
; #Parameters:     2
; Is_vararg:       0
; Max Stack Size:  3

  1 [-]: MOVE      R2 R0        ; R2 := R0
  2 [-]: RETURN    R2 2         ; return R2
  3 [-]: RETURN    R0 1         ; return 


; Function #2:
;
; Name:            
; Defined at line: 7
; #Upvalues:       0
; #Parameters:     2
; Is_vararg:       0
; Max Stack Size:  6

  1 [-]: GETGLOBAL R2 K0        ; R2 := 0x400E7765
  2 [-]: MOVE      R3 R0        ; R3 := R0
  3 [-]: CALL      R2 2 2       ; R2 := R2(R3)
  4 [-]: TEST      R2 1         ; if R2 then PC := 11
  5 [-]: JMP       11           ; PC := 11
  6 [-]: GETGLOBAL R2 K0        ; R2 := 0x400E7765
  7 [-]: MOVE      R3 R1        ; R3 := R1
  8 [-]: CALL      R2 2 2       ; R2 := R2(R3)
  9 [-]: TEST      R2 0         ; if not R2 then PC := 12
 10 [-]: JMP       12           ; PC := 12
 11 [-]: RETURN    R0 1         ; return 
 12 [-]: GETGLOBAL R2 K0        ; R2 := 0x400E7765
 13 [-]: GETGLOBAL R3 K1        ; R3 := onUseEffect
 14 [-]: CALL      R2 2 2       ; R2 := R2(R3)
 15 [-]: TEST      R2 1         ; if R2 then PC := 21
 16 [-]: JMP       21           ; PC := 21
 17 [-]: SELF      R2 R0 K2     ; R3 := R0; R2 := R0["0xAB436EF2"]
 18 [-]: GETGLOBAL R4 K1        ; R4 := onUseEffect
 19 [-]: GETGLOBAL R5 K3        ; R5 := EMPTY_SYMBOL
 20 [-]: CALL      R2 4 1       ; R2(R3,R4,R5)
 21 [-]: RETURN    R0 1         ; return 


; Function #3:
;
; Name:            
; Defined at line: 17
; #Upvalues:       1
; #Parameters:     2
; Is_vararg:       0
; Max Stack Size:  5

  1 [-]: GETUPVAL  R2 U0        ; R2 := U0
  2 [-]: MOVE      R3 R0        ; R3 := R0
  3 [-]: MOVE      R4 R1        ; R4 := R1
  4 [-]: CALL      R2 3 1       ; R2(R3,R4)
  5 [-]: RETURN    R0 1         ; return 


; Function #4:
;
; Name:            
; Defined at line: 22
; #Upvalues:       1
; #Parameters:     2
; Is_vararg:       0
; Max Stack Size:  5

  1 [-]: GETUPVAL  R2 U0        ; R2 := U0
  2 [-]: MOVE      R3 R0        ; R3 := R0
  3 [-]: MOVE      R4 R1        ; R4 := R1
  4 [-]: CALL      R2 3 1       ; R2(R3,R4)
  5 [-]: RETURN    R0 1         ; return 


; Function #5:
;
; Name:            
; Defined at line: 26
; #Upvalues:       1
; #Parameters:     2
; Is_vararg:       0
; Max Stack Size:  5

  1 [-]: GETUPVAL  R2 U0        ; R2 := U0
  2 [-]: MOVE      R3 R0        ; R3 := R0
  3 [-]: MOVE      R4 R1        ; R4 := R1
  4 [-]: CALL      R2 3 1       ; R2(R3,R4)
  5 [-]: RETURN    R0 1         ; return 


; Function #6:
;
; Name:            
; Defined at line: 30
; #Upvalues:       1
; #Parameters:     2
; Is_vararg:       0
; Max Stack Size:  5

  1 [-]: GETUPVAL  R2 U0        ; R2 := U0
  2 [-]: MOVE      R3 R0        ; R3 := R0
  3 [-]: MOVE      R4 R1        ; R4 := R1
  4 [-]: CALL      R2 3 1       ; R2(R3,R4)
  5 [-]: RETURN    R0 1         ; return 


; Function #7:
;
; Name:            
; Defined at line: 34
; #Upvalues:       1
; #Parameters:     2
; Is_vararg:       0
; Max Stack Size:  5

  1 [-]: GETUPVAL  R2 U0        ; R2 := U0
  2 [-]: MOVE      R3 R0        ; R3 := R0
  3 [-]: MOVE      R4 R1        ; R4 := R1
  4 [-]: CALL      R2 3 1       ; R2(R3,R4)
  5 [-]: RETURN    R0 1         ; return 


