code size: 192
code size: 37
code size: 22
code size: 34
code size: 19
code size: 57
code size: 41
code size: 36
code size: 112
code size: 3
code size: 7
code size: 5
code size: 42
code size: 4
code size: 42
code size: 5
code size: 18
code size: 22
code size: 11
code size: 95
code size: 23
code size: 19
code size: 27
code size: 38
code size: 67
code size: 416
code size: 43
; This file has been disassembled using luadec 2.0.2 by sztupy (http://winmo.sztupy.hu)
; Command line was: -dis M:\git repos\warframe-lua-disassembled\B.Font.cache_extracted\Lotus\Interface\SpecialReticles\RailjackMultiToolReticle.luac 

; Name:            
; Defined at line: 0
; #Upvalues:       0
; #Parameters:     0
; Is_vararg:       2
; Max Stack Size:  53

  1 [-]: GETGLOBAL R1 K0        ; R1 := 0x221C9700
  2 [-]: LOADK     R2 K1        ; R2 := 0
  3 [-]: LOADK     R3 K2        ; R3 := 0.11999999731779
  4 [-]: LOADK     R4 K3        ; R4 := 4
  5 [-]: CALL      R1 4 2       ; R1 := R1(R2,R3,R4)
  6 [-]: GETGLOBAL R2 K4        ; R2 := 0x1E4F6281
  7 [-]: LOADK     R3 K1        ; R3 := 0
  8 [-]: LOADK     R4 K5        ; R4 := -90
  9 [-]: LOADK     R5 K1        ; R5 := 0
 10 [-]: CALL      R2 4 2       ; R2 := R2(R3,R4,R5)
 11 [-]: LOADK     R3 K6        ; R3 := 1
 12 [-]: GETGLOBAL R4 K7        ; R4 := 0x329BDC44
 13 [-]: LOADK     R5 K8        ; R5 := "Lotus.Interface.LotusUtilities"
 14 [-]: CALL      R4 2 2       ; R4 := R4(R5)
 15 [-]: GETGLOBAL R5 K7        ; R5 := 0x329BDC44
 16 [-]: LOADK     R6 K9        ; R6 := "EE.Interface.Utilities"
 17 [-]: CALL      R5 2 2       ; R5 := R5(R6)
 18 [-]: MOVE      R6 R0        ; R6 := R0
 19 [-]: LOADK     R7 K1        ; R7 := 0
 20 [-]: LOADK     R8 K1        ; R8 := 0
 21 [-]: MOVE      R9 R1        ; R9 := R1
 22 [-]: MOVE      R10 R1       ; R10 := R1
 23 [-]: MOVE      R11 R0       ; R11 := R0
 24 [-]: MOVE      R12 R0       ; R12 := R0
 25 [-]: MOVE      R13 R0       ; R13 := R0
 26 [-]: LOADNIL   R14 R14      ; R14 := nil
 27 [-]: GETGLOBAL R15 K10      ; R15 := 0xEC274B1A
 28 [-]: LOADK     R16 K11      ; R16 := "Scope"
 29 [-]: CALL      R15 2 2      ; R15 := R15(R16)
 30 [-]: LOADNIL   R16 R21      ; R16 := R17 := R18 := R19 := R20 := R21 := nil
 31 [-]: MOVE      R22 R0       ; R22 := R0
 32 [-]: MOVE      R23 R0       ; R23 := R0
 33 [-]: MOVE      R24 R0       ; R24 := R0
 34 [-]: GETGLOBAL R25 K10      ; R25 := 0xEC274B1A
 35 [-]: LOADK     R26 K12      ; R26 := "MiningLaser"
 36 [-]: CALL      R25 2 2      ; R25 := R25(R26)
 37 [-]: LOADNIL   R26 R28      ; R26 := R27 := R28 := nil
 38 [-]: MOVE      R29 R1       ; R29 := R1
 39 [-]: LOADNIL   R30 R31      ; R30 := R31 := nil
 40 [-]: LOADK     R32 K1       ; R32 := 0
 41 [-]: GETGLOBAL R33 K13      ; R33 := 0x70D42C02
 42 [-]: LOADK     R34 K14      ; R34 := 100
 43 [-]: LOADK     R35 K15      ; R35 := 0.20000000298023
 44 [-]: CALL      R33 3 2      ; R33 := R33(R34,R35)
 45 [-]: MOVE      R34 R0       ; R34 := R0
 46 [-]: LOADNIL   R35 R35      ; R35 := nil
 47 [-]: CLOSURE   R36 0        ; R36 := closure(Function #1)
 48 [-]: CLOSURE   R37 1        ; R37 := closure(Function #2)
 49 [-]: MOVE      R0 R27       ; R0 := R27
 50 [-]: CLOSURE   R38 2        ; R38 := closure(Function #3)
 51 [-]: CLOSURE   R39 3        ; R39 := closure(Function #4)
 52 [-]: MOVE      R0 R27       ; R0 := R27
 53 [-]: MOVE      R0 R28       ; R0 := R28
 54 [-]: CLOSURE   R40 4        ; R40 := closure(Function #5)
 55 [-]: MOVE      R0 R38       ; R0 := R38
 56 [-]: MOVE      R0 R24       ; R0 := R24
 57 [-]: MOVE      R0 R14       ; R0 := R14
 58 [-]: CLOSURE   R41 5        ; R41 := closure(Function #6)
 59 [-]: MOVE      R0 R5        ; R0 := R5
 60 [-]: MOVE      R0 R7        ; R0 := R7
 61 [-]: CLOSURE   R42 6        ; R42 := closure(Function #7)
 62 [-]: MOVE      R0 R6        ; R0 := R6
 63 [-]: MOVE      R0 R17       ; R0 := R17
 64 [-]: MOVE      R0 R18       ; R0 := R18
 65 [-]: MOVE      R0 R19       ; R0 := R19
 66 [-]: MOVE      R0 R28       ; R0 := R28
 67 [-]: MOVE      R0 R5        ; R0 := R5
 68 [-]: MOVE      R0 R29       ; R0 := R29
 69 [-]: MOVE      R0 R36       ; R0 := R36
 70 [-]: MOVE      R0 R41       ; R0 := R41
 71 [-]: CLOSURE   R43 7        ; R43 := closure(Function #8)
 72 [-]: MOVE      R0 R16       ; R0 := R16
 73 [-]: MOVE      R0 R7        ; R0 := R7
 74 [-]: MOVE      R0 R5        ; R0 := R5
 75 [-]: MOVE      R0 R8        ; R0 := R8
 76 [-]: MOVE      R0 R42       ; R0 := R42
 77 [-]: SETGLOBAL R43 K16      ; Initialize := R43
 78 [-]: SETGLOBAL R43 K17      ; 0x62648036 := R43
 79 [-]: CLOSURE   R43 8        ; R43 := closure(Function #9)
 80 [-]: MOVE      R0 R41       ; R0 := R41
 81 [-]: SETGLOBAL R43 K18      ; onViewportSizeChanged := R43
 82 [-]: SETGLOBAL R43 K19      ; 0x3A900427 := R43
 83 [-]: CLOSURE   R43 9        ; R43 := closure(Function #10)
 84 [-]: MOVE      R0 R19       ; R0 := R19
 85 [-]: SETGLOBAL R43 K20      ; SetWeapon := R43
 86 [-]: SETGLOBAL R43 K21      ; 0x7C377721 := R43
 87 [-]: CLOSURE   R43 10       ; R43 := closure(Function #11)
 88 [-]: MOVE      R0 R10       ; R0 := R10
 89 [-]: CLOSURE   R44 11       ; R44 := closure(Function #12)
 90 [-]: MOVE      R0 R11       ; R0 := R11
 91 [-]: MOVE      R0 R43       ; R0 := R43
 92 [-]: MOVE      R0 R17       ; R0 := R17
 93 [-]: MOVE      R0 R20       ; R0 := R20
 94 [-]: MOVE      R0 R15       ; R0 := R15
 95 [-]: CLOSURE   R45 12       ; R45 := closure(Function #13)
 96 [-]: MOVE      R0 R44       ; R0 := R44
 97 [-]: SETGLOBAL R45 K22      ; SetAiming := R45
 98 [-]: SETGLOBAL R45 K23      ; 0xD51D3E81 := R45
 99 [-]: CLOSURE   R45 13       ; R45 := closure(Function #14)
100 [-]: MOVE      R0 R10       ; R0 := R10
101 [-]: MOVE      R0 R14       ; R0 := R14
102 [-]: MOVE      R0 R43       ; R0 := R43
103 [-]: MOVE      R0 R44       ; R0 := R44
104 [-]: CLOSURE   R46 14       ; R46 := closure(Function #15)
105 [-]: MOVE      R0 R45       ; R0 := R45
106 [-]: SETGLOBAL R46 K24      ; SetEnabled := R46
107 [-]: SETGLOBAL R46 K25      ; 0x91791A08 := R46
108 [-]: CLOSURE   R46 15       ; R46 := closure(Function #16)
109 [-]: MOVE      R0 R15       ; R0 := R15
110 [-]: SETGLOBAL R46 K26      ; ClearCustomReticleAiming := R46
111 [-]: SETGLOBAL R46 K27      ; 0x568C9EE := R46
112 [-]: CLOSURE   R46 16       ; R46 := closure(Function #17)
113 [-]: MOVE      R0 R24       ; R0 := R24
114 [-]: MOVE      R0 R14       ; R0 := R14
115 [-]: CLOSURE   R47 17       ; R47 := closure(Function #18)
116 [-]: MOVE      R0 R28       ; R0 := R28
117 [-]: MOVE      R0 R22       ; R0 := R22
118 [-]: MOVE      R0 R24       ; R0 := R24
119 [-]: MOVE      R0 R29       ; R0 := R29
120 [-]: MOVE      R0 R5        ; R0 := R5
121 [-]: CLOSURE   R48 18       ; R48 := closure(Function #19)
122 [-]: MOVE      R0 R40       ; R0 := R40
123 [-]: MOVE      R0 R47       ; R0 := R47
124 [-]: CLOSURE   R49 19       ; R49 := closure(Function #20)
125 [-]: MOVE      R0 R12       ; R0 := R12
126 [-]: MOVE      R0 R5        ; R0 := R5
127 [-]: MOVE      R0 R11       ; R0 := R11
128 [-]: MOVE      R0 R45       ; R0 := R45
129 [-]: CLOSURE   R50 20       ; R50 := closure(Function #21)
130 [-]: MOVE      R0 R31       ; R0 := R31
131 [-]: MOVE      R0 R37       ; R0 := R37
132 [-]: MOVE      R0 R39       ; R0 := R39
133 [-]: CLOSURE   R35 21       ; R35 := closure(Function #22)
134 [-]: MOVE      R0 R5        ; R0 := R5
135 [-]: MOVE      R0 R22       ; R0 := R22
136 [-]: MOVE      R0 R37       ; R0 := R37
137 [-]: MOVE      R0 R39       ; R0 := R39
138 [-]: MOVE      R0 R46       ; R0 := R46
139 [-]: CLOSURE   R51 22       ; R51 := closure(Function #23)
140 [-]: MOVE      R0 R19       ; R0 := R19
141 [-]: MOVE      R0 R22       ; R0 := R22
142 [-]: MOVE      R0 R23       ; R0 := R23
143 [-]: MOVE      R0 R0        ; R0 := R0
144 [-]: MOVE      R0 R1        ; R0 := R1
145 [-]: MOVE      R0 R2        ; R0 := R2
146 [-]: MOVE      R0 R3        ; R0 := R3
147 [-]: CLOSURE   R52 23       ; R52 := closure(Function #24)
148 [-]: MOVE      R0 R14       ; R0 := R14
149 [-]: MOVE      R0 R6        ; R0 := R6
150 [-]: MOVE      R0 R42       ; R0 := R42
151 [-]: MOVE      R0 R16       ; R0 := R16
152 [-]: MOVE      R0 R17       ; R0 := R17
153 [-]: MOVE      R0 R12       ; R0 := R12
154 [-]: MOVE      R0 R49       ; R0 := R49
155 [-]: MOVE      R0 R10       ; R0 := R10
156 [-]: MOVE      R0 R39       ; R0 := R39
157 [-]: MOVE      R0 R18       ; R0 := R18
158 [-]: MOVE      R0 R19       ; R0 := R19
159 [-]: MOVE      R0 R20       ; R0 := R20
160 [-]: MOVE      R0 R21       ; R0 := R21
161 [-]: MOVE      R0 R9        ; R0 := R9
162 [-]: MOVE      R0 R30       ; R0 := R30
163 [-]: MOVE      R0 R11       ; R0 := R11
164 [-]: MOVE      R0 R13       ; R0 := R13
165 [-]: MOVE      R0 R25       ; R0 := R25
166 [-]: MOVE      R0 R26       ; R0 := R26
167 [-]: MOVE      R0 R31       ; R0 := R31
168 [-]: MOVE      R0 R35       ; R0 := R35
169 [-]: MOVE      R0 R22       ; R0 := R22
170 [-]: MOVE      R0 R50       ; R0 := R50
171 [-]: MOVE      R0 R23       ; R0 := R23
172 [-]: MOVE      R0 R32       ; R0 := R32
173 [-]: MOVE      R0 R34       ; R0 := R34
174 [-]: MOVE      R0 R33       ; R0 := R33
175 [-]: MOVE      R0 R5        ; R0 := R5
176 [-]: MOVE      R0 R46       ; R0 := R46
177 [-]: MOVE      R0 R48       ; R0 := R48
178 [-]: MOVE      R0 R51       ; R0 := R51
179 [-]: SETGLOBAL R52 K28      ; Update := R52
180 [-]: SETGLOBAL R52 K29      ; 0x8C7099E9 := R52
181 [-]: CLOSURE   R52 24       ; R52 := closure(Function #25)
182 [-]: MOVE      R0 R39       ; R0 := R39
183 [-]: MOVE      R0 R4        ; R0 := R4
184 [-]: MOVE      R0 R14       ; R0 := R14
185 [-]: MOVE      R0 R21       ; R0 := R21
186 [-]: MOVE      R0 R13       ; R0 := R13
187 [-]: MOVE      R0 R25       ; R0 := R25
188 [-]: MOVE      R0 R26       ; R0 := R26
189 [-]: MOVE      R0 R46       ; R0 := R46
190 [-]: SETGLOBAL R52 K30      ; Shutdown := R52
191 [-]: SETGLOBAL R52 K31      ; 0x3C577FA3 := R52
192 [-]: RETURN    R0 1         ; return 


; Function #1:
;
; Name:            
; Defined at line: 83
; #Upvalues:       0
; #Parameters:     0
; Is_vararg:       0
; Max Stack Size:  5

  1 [-]: GETGLOBAL R0 K0        ; R0 := mMovie
  2 [-]: SELF      R0 R0 K1     ; R1 := R0; R0 := R0["0x1C19D966"]
  3 [-]: LOADK     R2 K2        ; R2 := "Scope"
  4 [-]: LOADK     R3 K3        ; R3 := "_visible"
  5 [-]: MOVE      R4 R0        ; R4 := R0
  6 [-]: CALL      R0 5 1       ; R0(R1,R2,R3,R4)
  7 [-]: GETGLOBAL R0 K0        ; R0 := mMovie
  8 [-]: SELF      R0 R0 K1     ; R1 := R0; R0 := R0["0x1C19D966"]
  9 [-]: LOADK     R2 K4        ; R2 := "Info.Hint"
 10 [-]: LOADK     R3 K3        ; R3 := "_visible"
 11 [-]: MOVE      R4 R0        ; R4 := R0
 12 [-]: CALL      R0 5 1       ; R0(R1,R2,R3,R4)
 13 [-]: GETGLOBAL R0 K0        ; R0 := mMovie
 14 [-]: SELF      R0 R0 K1     ; R1 := R0; R0 := R0["0x1C19D966"]
 15 [-]: LOADK     R2 K5        ; R2 := "Info.OreList"
 16 [-]: LOADK     R3 K3        ; R3 := "_visible"
 17 [-]: MOVE      R4 R0        ; R4 := R0
 18 [-]: CALL      R0 5 1       ; R0(R1,R2,R3,R4)
 19 [-]: GETGLOBAL R0 K0        ; R0 := mMovie
 20 [-]: SELF      R0 R0 K1     ; R1 := R0; R0 := R0["0x1C19D966"]
 21 [-]: LOADK     R2 K6        ; R2 := "Info.Rating"
 22 [-]: LOADK     R3 K3        ; R3 := "_visible"
 23 [-]: MOVE      R4 R0        ; R4 := R0
 24 [-]: CALL      R0 5 1       ; R0(R1,R2,R3,R4)
 25 [-]: GETGLOBAL R0 K0        ; R0 := mMovie
 26 [-]: SELF      R0 R0 K1     ; R1 := R0; R0 := R0["0x1C19D966"]
 27 [-]: LOADK     R2 K7        ; R2 := "Info.Progress"
 28 [-]: LOADK     R3 K3        ; R3 := "_visible"
 29 [-]: MOVE      R4 R0        ; R4 := R0
 30 [-]: CALL      R0 5 1       ; R0(R1,R2,R3,R4)
 31 [-]: GETGLOBAL R0 K0        ; R0 := mMovie
 32 [-]: SELF      R0 R0 K1     ; R1 := R0; R0 := R0["0x1C19D966"]
 33 [-]: LOADK     R2 K8        ; R2 := "Info.Success"
 34 [-]: LOADK     R3 K3        ; R3 := "_visible"
 35 [-]: MOVE      R4 R0        ; R4 := R0
 36 [-]: CALL      R0 5 1       ; R0(R1,R2,R3,R4)
 37 [-]: RETURN    R0 1         ; return 


; Function #2:
;
; Name:            
; Defined at line: 93
; #Upvalues:       1
; #Parameters:     1
; Is_vararg:       0
; Max Stack Size:  6

  1 [-]: GETGLOBAL R1 K0        ; R1 := 0x400E7765
  2 [-]: GETUPVAL  R2 U0        ; R2 := U0
  3 [-]: CALL      R1 2 2       ; R1 := R1(R2)
  4 [-]: TEST      R1 1         ; if R1 then PC := 10
  5 [-]: JMP       10           ; PC := 10
  6 [-]: GETUPVAL  R1 U0        ; R1 := U0
  7 [-]: SELF      R1 R1 K1     ; R2 := R1; R1 := R1["0x2842784A"]
  8 [-]: MOVE      R3 R1        ; R3 := R1
  9 [-]: CALL      R1 3 1       ; R1(R2,R3)
 10 [-]: GETGLOBAL R1 K0        ; R1 := 0x400E7765
 11 [-]: GETGLOBAL R2 K2        ; R2 := heatingNodeSoundLoop
 12 [-]: CALL      R1 2 2       ; R1 := R1(R2)
 13 [-]: TEST      R1 1         ; if R1 then PC := 22
 14 [-]: JMP       22           ; PC := 22
 15 [-]: GETGLOBAL R1 K3        ; R1 := gRegion
 16 [-]: SELF      R1 R1 K4     ; R2 := R1; R1 := R1["0x25992394"]
 17 [-]: GETGLOBAL R3 K2        ; R3 := heatingNodeSoundLoop
 18 [-]: MOVE      R4 R0        ; R4 := R0
 19 [-]: MOVE      R5 R0        ; R5 := R0
 20 [-]: CALL      R1 5 2       ; R1 := R1(R2,R3,R4,R5)
 21 [-]: MOVE      R1 R0        ; R1 := R0
 22 [-]: RETURN    R0 1         ; return 


; Function #3:
;
; Name:            
; Defined at line: 103
; #Upvalues:       0
; #Parameters:     3
; Is_vararg:       0
; Max Stack Size:  11

  1 [-]: MUL       R3 R0 K0     ; R3 := R0 * 360
  2 [-]: MUL       R4 R1 K0     ; R4 := R1 * 360
  3 [-]: GETGLOBAL R5 K1        ; R5 := mMovie
  4 [-]: SELF      R5 R5 K2     ; R6 := R5; R5 := R5["0x1C19D966"]
  5 [-]: LOADK     R7 K3        ; R7 := "Gauge.BracketStart"
  6 [-]: LOADK     R8 K4        ; R8 := "_rotation"
  7 [-]: MOVE      R9 R3        ; R9 := R3
  8 [-]: CALL      R5 5 1       ; R5(R6,R7,R8,R9)
  9 [-]: GETGLOBAL R5 K1        ; R5 := mMovie
 10 [-]: SELF      R5 R5 K2     ; R6 := R5; R5 := R5["0x1C19D966"]
 11 [-]: LOADK     R7 K5        ; R7 := "Gauge.BracketEnd"
 12 [-]: LOADK     R8 K4        ; R8 := "_rotation"
 13 [-]: MOVE      R9 R4        ; R9 := R4
 14 [-]: CALL      R5 5 1       ; R5(R6,R7,R8,R9)
 15 [-]: GETGLOBAL R5 K1        ; R5 := mMovie
 16 [-]: SELF      R5 R5 K2     ; R6 := R5; R5 := R5["0x1C19D966"]
 17 [-]: LOADK     R7 K6        ; R7 := "Gauge.RangeRing"
 18 [-]: LOADK     R8 K4        ; R8 := "_rotation"
 19 [-]: MOVE      R9 R3        ; R9 := R3
 20 [-]: CALL      R5 5 1       ; R5(R6,R7,R8,R9)
 21 [-]: GETGLOBAL R5 K1        ; R5 := mMovie
 22 [-]: SELF      R5 R5 K2     ; R6 := R5; R5 := R5["0x1C19D966"]
 23 [-]: LOADK     R7 K7        ; R7 := "Gauge.EndMask"
 24 [-]: LOADK     R8 K4        ; R8 := "_rotation"
 25 [-]: MOVE      R9 R4        ; R9 := R4
 26 [-]: CALL      R5 5 1       ; R5(R6,R7,R8,R9)
 27 [-]: MUL       R5 R2 K0     ; R5 := R2 * 360
 28 [-]: GETGLOBAL R6 K1        ; R6 := mMovie
 29 [-]: SELF      R6 R6 K2     ; R7 := R6; R6 := R6["0x1C19D966"]
 30 [-]: LOADK     R8 K8        ; R8 := "Gauge.GemIndicator"
 31 [-]: LOADK     R9 K4        ; R9 := "_rotation"
 32 [-]: MOVE      R10 R5       ; R10 := R5
 33 [-]: CALL      R6 5 1       ; R6(R7,R8,R9,R10)
 34 [-]: RETURN    R0 1         ; return 


; Function #4:
;
; Name:            
; Defined at line: 115
; #Upvalues:       2
; #Parameters:     0
; Is_vararg:       0
; Max Stack Size:  3

  1 [-]: GETGLOBAL R0 K0        ; R0 := 0x400E7765
  2 [-]: GETUPVAL  R1 U0        ; R1 := U0
  3 [-]: CALL      R0 2 2       ; R0 := R0(R1)
  4 [-]: TEST      R0 1         ; if R0 then PC := 10
  5 [-]: JMP       10           ; PC := 10
  6 [-]: GETUPVAL  R0 U0        ; R0 := U0
  7 [-]: SELF      R0 R0 K1     ; R1 := R0; R0 := R0["0x2842784A"]
  8 [-]: MOVE      R2 R0        ; R2 := R0
  9 [-]: CALL      R0 3 1       ; R0(R1,R2)
 10 [-]: GETGLOBAL R0 K0        ; R0 := 0x400E7765
 11 [-]: GETUPVAL  R1 U1        ; R1 := U1
 12 [-]: CALL      R0 2 2       ; R0 := R0(R1)
 13 [-]: TEST      R0 1         ; if R0 then PC := 19
 14 [-]: JMP       19           ; PC := 19
 15 [-]: GETUPVAL  R0 U1        ; R0 := U1
 16 [-]: SELF      R0 R0 K1     ; R1 := R0; R0 := R0["0x2842784A"]
 17 [-]: MOVE      R2 R0        ; R2 := R0
 18 [-]: CALL      R0 3 1       ; R0(R1,R2)
 19 [-]: RETURN    R0 1         ; return 


; Function #5:
;
; Name:            
; Defined at line: 125
; #Upvalues:       3
; #Parameters:     5
; Is_vararg:       0
; Max Stack Size:  13

  1 [-]: GETUPVAL  R5 U0        ; R5 := U0
  2 [-]: MOVE      R6 R1        ; R6 := R1
  3 [-]: MOVE      R7 R2        ; R7 := R2
  4 [-]: MOVE      R8 R3        ; R8 := R3
  5 [-]: CALL      R5 4 1       ; R5(R6,R7,R8)
  6 [-]: GETGLOBAL R5 K0        ; R5 := mMovie
  7 [-]: SELF      R5 R5 K1     ; R6 := R5; R5 := R5["0x302AAB2F"]
  8 [-]: LOADK     R7 K2        ; R7 := "Gauge.Fill"
  9 [-]: LOADK     R8 K3        ; R8 := "AlphaTestThreshold"
 10 [-]: MOVE      R9 R0        ; R9 := R0
 11 [-]: LOADK     R10 K4       ; R10 := 0
 12 [-]: LOADK     R11 K4       ; R11 := 0
 13 [-]: LOADK     R12 K4       ; R12 := 0
 14 [-]: CALL      R5 8 1       ; R5(R6,R7,R8,R9,R10,R11,R12)
 15 [-]: GETGLOBAL R5 K0        ; R5 := mMovie
 16 [-]: SELF      R5 R5 K5     ; R6 := R5; R5 := R5["0x1C19D966"]
 17 [-]: LOADK     R7 K6        ; R7 := "Gauge.GemIndicator"
 18 [-]: LOADK     R8 K7        ; R8 := "_visible"
 19 [-]: GETUPVAL  R9 U1        ; R9 := U1
 20 [-]: TEST      R9 0         ; if not R9 then PC := 26
 21 [-]: JMP       26           ; PC := 26
 22 [-]: LT        1 K4 R3      ; if 0 < R3 then PC := 25
 23 [-]: JMP       25           ; PC := 25
 24 [-]: MOVE      R9 R0        ; R9 := R0
 25 [-]: MOVE      R9 R1        ; R9 := R1
 26 [-]: CALL      R5 5 1       ; R5(R6,R7,R8,R9)
 27 [-]: GETUPVAL  R5 U1        ; R5 := U1
 28 [-]: TEST      R5 1         ; if R5 then PC := 57
 29 [-]: JMP       57           ; PC := 57
 30 [-]: TEST      R4 0         ; if not R4 then PC := 57
 31 [-]: JMP       57           ; PC := 57
 32 [-]: MOVE      R5 R1        ; R5 := R1
 33 [-]: MOVE      R5 R1        ; R5 := R1
 34 [-]: GETGLOBAL R5 K8        ; R5 := 0x400E7765
 35 [-]: GETUPVAL  R6 U2        ; R6 := U2
 36 [-]: CALL      R5 2 2       ; R5 := R5(R6)
 37 [-]: TEST      R5 1         ; if R5 then PC := 44
 38 [-]: JMP       44           ; PC := 44
 39 [-]: GETUPVAL  R5 U2        ; R5 := U2
 40 [-]: SELF      R5 R5 K9     ; R6 := R5; R5 := R5["0x458F27A9"]
 41 [-]: LOADK     R7 K10       ; R7 := "HideAbilityDots"
 42 [-]: LOADK     R8 K11       ; R8 := ""
 43 [-]: CALL      R5 4 1       ; R5(R6,R7,R8)
 44 [-]: GETGLOBAL R5 K12       ; R5 := 0x52E17A90
 45 [-]: GETGLOBAL R6 K0        ; R6 := mMovie
 46 [-]: LOADK     R7 K13       ; R7 := "Gauge"
 47 [-]: GETGLOBAL R8 K14       ; R8 := UISys
 48 [-]: GETTABLE  R8 R8 K15    ; R8 := R8["FlashInstance_EASE_OUT"]
 49 [-]: NEWTABLE  R9 1 0       ; R9 := {}
 50 [-]: LOADK     R10 K16      ; R10 := "_alpha"
 51 [-]: SETLIST   R9 1 1       ; R9[(1-1)*FPF+i] := R(9+i), 1 <= i <= 1
 52 [-]: NEWTABLE  R10 1 0      ; R10 := {}
 53 [-]: LOADK     R11 K17      ; R11 := 100
 54 [-]: SETLIST   R10 1 1      ; R10[(1-1)*FPF+i] := R(10+i), 1 <= i <= 1
 55 [-]: LOADK     R11 K18      ; R11 := 0.15000000596046
 56 [-]: CALL      R5 7 1       ; R5(R6,R7,R8,R9,R10,R11)
 57 [-]: RETURN    R0 1         ; return 


; Function #6:
;
; Name:            
; Defined at line: 140
; #Upvalues:       2
; #Parameters:     0
; Is_vararg:       0
; Max Stack Size:  7

  1 [-]: GETGLOBAL R0 K0        ; R0 := Engine
  2 [-]: GETTABLE  R0 R0 K1     ; R0 := R0["0x9490FE70"]
  3 [-]: CALL      R0 1 2       ; R0 := R0()
  4 [-]: TEST      R0 0         ; if not R0 then PC := 7
  5 [-]: JMP       7            ; PC := 7
  6 [-]: RETURN    R0 1         ; return 
  7 [-]: GETUPVAL  R0 U0        ; R0 := U0
  8 [-]: GETTABLE  R0 R0 K2     ; R0 := R0["0xEA569929"]
  9 [-]: GETGLOBAL R1 K3        ; R1 := mMovie
 10 [-]: CALL      R0 2 3       ; R0,R1 := R0(R1)
 11 [-]: GETGLOBAL R2 K3        ; R2 := mMovie
 12 [-]: SELF      R2 R2 K4     ; R3 := R2; R2 := R2["0x1C19D966"]
 13 [-]: LOADK     R4 K5        ; R4 := "Scope.Vignette"
 14 [-]: LOADK     R5 K6        ; R5 := "_width"
 15 [-]: MOVE      R6 R0        ; R6 := R0
 16 [-]: CALL      R2 5 1       ; R2(R3,R4,R5,R6)
 17 [-]: GETGLOBAL R2 K3        ; R2 := mMovie
 18 [-]: SELF      R2 R2 K4     ; R3 := R2; R2 := R2["0x1C19D966"]
 19 [-]: LOADK     R4 K5        ; R4 := "Scope.Vignette"
 20 [-]: LOADK     R5 K7        ; R5 := "_height"
 21 [-]: MOVE      R6 R1        ; R6 := R1
 22 [-]: CALL      R2 5 1       ; R2(R3,R4,R5,R6)
 23 [-]: GETGLOBAL R2 K8        ; R2 := reticleVisRange
 24 [-]: SELF      R2 R2 K9     ; R3 := R2; R2 := R2["0x94FB2E1A"]
 25 [-]: GETGLOBAL R4 K10       ; R4 := Lotus_Game
 26 [-]: GETTABLE  R4 R4 K11    ; R4 := R4["VISIBILITY_CENTER"]
 27 [-]: LOADK     R5 K12       ; R5 := 0.5
 28 [-]: CALL      R2 4 1       ; R2(R3,R4,R5)
 29 [-]: GETGLOBAL R2 K8        ; R2 := reticleVisRange
 30 [-]: SELF      R2 R2 K9     ; R3 := R2; R2 := R2["0x94FB2E1A"]
 31 [-]: GETGLOBAL R4 K10       ; R4 := Lotus_Game
 32 [-]: GETTABLE  R4 R4 K13    ; R4 := R4["VISIBILITY_SIZE"]
 33 [-]: GETUPVAL  R5 U1        ; R5 := U1
 34 [-]: CALL      R2 4 1       ; R2(R3,R4,R5)
 35 [-]: GETGLOBAL R2 K8        ; R2 := reticleVisRange
 36 [-]: SELF      R2 R2 K9     ; R3 := R2; R2 := R2["0x94FB2E1A"]
 37 [-]: GETGLOBAL R4 K10       ; R4 := Lotus_Game
 38 [-]: GETTABLE  R4 R4 K14    ; R4 := R4["VISIBILITY_FADE_SIZE"]
 39 [-]: LOADK     R5 K15       ; R5 := 0.20000000298023
 40 [-]: CALL      R2 4 1       ; R2(R3,R4,R5)
 41 [-]: RETURN    R0 1         ; return 


; Function #7:
;
; Name:            
; Defined at line: 155
; #Upvalues:       9
; #Parameters:     0
; Is_vararg:       0
; Max Stack Size:  3

  1 [-]: MOVE      R0 R1        ; R0 := R1
  2 [-]: MOVE      R0 R0        ; R0 := R0
  3 [-]: GETGLOBAL R0 K0        ; R0 := gRegion
  4 [-]: SELF      R0 R0 K1     ; R1 := R0; R0 := R0["0x3E2F6BF"]
  5 [-]: CALL      R0 2 2       ; R0 := R0(R1)
  6 [-]: MOVE      R0 R1        ; R0 := R1
  7 [-]: GETUPVAL  R0 U1        ; R0 := U1
  8 [-]: SELF      R0 R0 K2     ; R1 := R0; R0 := R0["0x8DB5D01F"]
  9 [-]: CALL      R0 2 2       ; R0 := R0(R1)
 10 [-]: MOVE      R0 R2        ; R0 := R2
 11 [-]: GETUPVAL  R0 U2        ; R0 := U2
 12 [-]: SELF      R0 R0 K3     ; R1 := R0; R0 := R0["0x63D63C30"]
 13 [-]: GETGLOBAL R2 K4        ; R2 := Engine
 14 [-]: GETTABLE  R2 R2 K5     ; R2 := R2["SLOT_3"]
 15 [-]: CALL      R0 3 2       ; R0 := R0(R1,R2)
 16 [-]: MOVE      R0 R3        ; R0 := R3
 17 [-]: GETGLOBAL R0 K6        ; R0 := 0x400E7765
 18 [-]: GETUPVAL  R1 U4        ; R1 := U4
 19 [-]: CALL      R0 2 2       ; R0 := R0(R1)
 20 [-]: TEST      R0 0         ; if not R0 then PC := 32
 21 [-]: JMP       32           ; PC := 32
 22 [-]: GETUPVAL  R0 U5        ; R0 := U5
 23 [-]: GETTABLE  R0 R0 K7     ; R0 := R0["0x25992394"]
 24 [-]: GETGLOBAL R1 K8        ; R1 := proximityToSweetSpotSound
 25 [-]: CALL      R0 2 2       ; R0 := R0(R1)
 26 [-]: MOVE      R0 R4        ; R0 := R4
 27 [-]: MOVE      R0 R1        ; R0 := R1
 28 [-]: MOVE      R0 R6        ; R0 := R6
 29 [-]: GETUPVAL  R0 U4        ; R0 := U4
 30 [-]: SELF      R0 R0 K9     ; R1 := R0; R0 := R0["0x6EEAD185"]
 31 [-]: CALL      R0 2 1       ; R0(R1)
 32 [-]: GETUPVAL  R0 U7        ; R0 := U7
 33 [-]: CALL      R0 1 1       ; R0()
 34 [-]: GETUPVAL  R0 U8        ; R0 := U8
 35 [-]: CALL      R0 1 1       ; R0()
 36 [-]: RETURN    R0 1         ; return 


; Function #8:
;
; Name:            
; Defined at line: 172
; #Upvalues:       5
; #Parameters:     0
; Is_vararg:       0
; Max Stack Size:  6

  1 [-]: GETGLOBAL R0 K0        ; R0 := 0x329BDC44
  2 [-]: LOADK     R1 K1        ; R1 := "Lotus.Interface.Libs.TimerMgr"
  3 [-]: CALL      R0 2 2       ; R0 := R0(R1)
  4 [-]: GETTABLE  R1 R0 K2     ; R1 := R0["0xC2A7FAC0"]
  5 [-]: CALL      R1 1 2       ; R1 := R1()
  6 [-]: MOVE      R1 R0        ; R1 := R0
  7 [-]: GETGLOBAL R1 K3        ; R1 := mMovie
  8 [-]: SELF      R1 R1 K4     ; R2 := R1; R1 := R1["0x1C19D966"]
  9 [-]: LOADK     R3 K5        ; R3 := "Scope"
 10 [-]: LOADK     R4 K6        ; R4 := "_alpha"
 11 [-]: LOADK     R5 K7        ; R5 := 0
 12 [-]: CALL      R1 5 1       ; R1(R2,R3,R4,R5)
 13 [-]: GETGLOBAL R1 K3        ; R1 := mMovie
 14 [-]: SELF      R1 R1 K4     ; R2 := R1; R1 := R1["0x1C19D966"]
 15 [-]: LOADK     R3 K8        ; R3 := "Scope.Reticle"
 16 [-]: LOADK     R4 K6        ; R4 := "_alpha"
 17 [-]: LOADK     R5 K9        ; R5 := 60
 18 [-]: CALL      R1 5 1       ; R1(R2,R3,R4,R5)
 19 [-]: GETGLOBAL R1 K3        ; R1 := mMovie
 20 [-]: SELF      R1 R1 K4     ; R2 := R1; R1 := R1["0x1C19D966"]
 21 [-]: LOADK     R3 K10       ; R3 := "Info.UnzoomedReticle"
 22 [-]: LOADK     R4 K6        ; R4 := "_alpha"
 23 [-]: LOADK     R5 K11       ; R5 := 80
 24 [-]: CALL      R1 5 1       ; R1(R2,R3,R4,R5)
 25 [-]: GETGLOBAL R1 K3        ; R1 := mMovie
 26 [-]: SELF      R1 R1 K12    ; R2 := R1; R1 := R1["0x7E1F26D7"]
 27 [-]: LOADK     R3 K10       ; R3 := "Info.UnzoomedReticle"
 28 [-]: GETGLOBAL R4 K13       ; R4 := reticleVisRange
 29 [-]: CALL      R1 4 1       ; R1(R2,R3,R4)
 30 [-]: GETGLOBAL R1 K3        ; R1 := mMovie
 31 [-]: SELF      R1 R1 K4     ; R2 := R1; R1 := R1["0x1C19D966"]
 32 [-]: LOADK     R3 K14       ; R3 := "Info.Hint"
 33 [-]: LOADK     R4 K15       ; R4 := "text"
 34 [-]: LOADK     R5 K16       ; R5 := ""
 35 [-]: CALL      R1 5 1       ; R1(R2,R3,R4,R5)
 36 [-]: GETGLOBAL R1 K3        ; R1 := mMovie
 37 [-]: SELF      R1 R1 K4     ; R2 := R1; R1 := R1["0x1C19D966"]
 38 [-]: LOADK     R3 K17       ; R3 := "Gauge"
 39 [-]: LOADK     R4 K6        ; R4 := "_alpha"
 40 [-]: LOADK     R5 K18       ; R5 := 0.0099999997764826
 41 [-]: CALL      R1 5 1       ; R1(R2,R3,R4,R5)
 42 [-]: GETGLOBAL R1 K3        ; R1 := mMovie
 43 [-]: SELF      R1 R1 K19    ; R2 := R1; R1 := R1["0x26581636"]
 44 [-]: LOADK     R3 K20       ; R3 := "Gauge.Backer"
 45 [-]: GETGLOBAL R4 K21       ; R4 := gaugeBackerTexture
 46 [-]: CALL      R1 4 1       ; R1(R2,R3,R4)
 47 [-]: GETGLOBAL R1 K3        ; R1 := mMovie
 48 [-]: SELF      R1 R1 K19    ; R2 := R1; R1 := R1["0x26581636"]
 49 [-]: LOADK     R3 K22       ; R3 := "Gauge.FillBg"
 50 [-]: GETGLOBAL R4 K23       ; R4 := gaugeFillBgTexture
 51 [-]: CALL      R1 4 1       ; R1(R2,R3,R4)
 52 [-]: GETGLOBAL R1 K3        ; R1 := mMovie
 53 [-]: SELF      R1 R1 K19    ; R2 := R1; R1 := R1["0x26581636"]
 54 [-]: LOADK     R3 K24       ; R3 := "Gauge.Fill"
 55 [-]: GETGLOBAL R4 K25       ; R4 := gaugeFillTexture
 56 [-]: CALL      R1 4 1       ; R1(R2,R3,R4)
 57 [-]: GETGLOBAL R1 K3        ; R1 := mMovie
 58 [-]: SELF      R1 R1 K12    ; R2 := R1; R1 := R1["0x7E1F26D7"]
 59 [-]: LOADK     R3 K24       ; R3 := "Gauge.Fill"
 60 [-]: GETGLOBAL R4 K26       ; R4 := gaugeFillMaterial
 61 [-]: CALL      R1 4 1       ; R1(R2,R3,R4)
 62 [-]: GETGLOBAL R1 K27       ; R1 := 0x8C64AFA9
 63 [-]: GETGLOBAL R2 K3        ; R2 := mMovie
 64 [-]: LOADK     R3 K28       ; R3 := "Info.UnzoomedReticle.gotoAndStop"
 65 [-]: LOADK     R4 K29       ; R4 := "Closed"
 66 [-]: CALL      R1 4 1       ; R1(R2,R3,R4)
 67 [-]: GETGLOBAL R1 K3        ; R1 := mMovie
 68 [-]: SELF      R1 R1 K12    ; R2 := R1; R1 := R1["0x7E1F26D7"]
 69 [-]: LOADK     R3 K30       ; R3 := "Info.Success.Highlight"
 70 [-]: GETGLOBAL R4 K31       ; R4 := lightRaysMaterial
 71 [-]: CALL      R1 4 1       ; R1(R2,R3,R4)
 72 [-]: GETGLOBAL R1 K27       ; R1 := 0x8C64AFA9
 73 [-]: GETGLOBAL R2 K3        ; R2 := mMovie
 74 [-]: LOADK     R3 K32       ; R3 := "Info.Success.Highlight.Sparkles.gotoAndStop"
 75 [-]: LOADK     R4 K33       ; R4 := 1
 76 [-]: CALL      R1 4 1       ; R1(R2,R3,R4)
 77 [-]: GETGLOBAL R1 K3        ; R1 := mMovie
 78 [-]: SELF      R1 R1 K4     ; R2 := R1; R1 := R1["0x1C19D966"]
 79 [-]: LOADK     R3 K34       ; R3 := "Ammo.Warning"
 80 [-]: LOADK     R4 K35       ; R4 := "textColor"
 81 [-]: GETGLOBAL R5 K36       ; R5 := _G
 82 [-]: GETTABLE  R5 R5 K37    ; R5 := R5["UIColor_Red"]
 83 [-]: CALL      R1 5 1       ; R1(R2,R3,R4,R5)
 84 [-]: GETGLOBAL R1 K3        ; R1 := mMovie
 85 [-]: SELF      R1 R1 K4     ; R2 := R1; R1 := R1["0x1C19D966"]
 86 [-]: LOADK     R3 K34       ; R3 := "Ammo.Warning"
 87 [-]: LOADK     R4 K6        ; R4 := "_alpha"
 88 [-]: LOADK     R5 K7        ; R5 := 0
 89 [-]: CALL      R1 5 1       ; R1(R2,R3,R4,R5)
 90 [-]: GETGLOBAL R1 K3        ; R1 := mMovie
 91 [-]: SELF      R1 R1 K38    ; R2 := R1; R1 := R1["0x17028E8F"]
 92 [-]: LOADK     R3 K39       ; R3 := "Ammo.Warning.text"
 93 [-]: LOADK     R4 K40       ; R4 := "/Lotus/Language/Railjack/Warning_NotEnoughRepairAmmo"
 94 [-]: CALL      R1 4 1       ; R1(R2,R3,R4)
 95 [-]: GETGLOBAL R1 K41       ; R1 := 0xF595ADDE
 96 [-]: GETGLOBAL R2 K3        ; R2 := mMovie
 97 [-]: SELF      R2 R2 K42    ; R3 := R2; R2 := R2["0x6B7B470B"]
 98 [-]: LOADK     R4 K10       ; R4 := "Info.UnzoomedReticle"
 99 [-]: LOADK     R5 K43       ; R5 := "_height"
100 [-]: CALL      R2 4 0       ; R2,... := R2(R3,R4,R5)
101 [-]: CALL      R1 0 2       ; R1 := R1(R2,...)
102 [-]: GETUPVAL  R2 U2        ; R2 := U2
103 [-]: GETTABLE  R2 R2 K44    ; R2 := R2["0x9884F87F"]
104 [-]: GETGLOBAL R3 K3        ; R3 := mMovie
105 [-]: MUL       R4 R1 K45    ; R4 := R1 * 0.44999998807907
106 [-]: CALL      R2 3 2       ; R2 := R2(R3,R4)
107 [-]: MOVE      R2 R1        ; R2 := R1
108 [-]: GETUPVAL  R2 U1        ; R2 := U1
109 [-]: MOVE      R2 R3        ; R2 := R3
110 [-]: GETUPVAL  R2 U4        ; R2 := U4
111 [-]: CALL      R2 1 1       ; R2()
112 [-]: RETURN    R0 1         ; return 


; Function #9:
;
; Name:            
; Defined at line: 202
; #Upvalues:       1
; #Parameters:     4
; Is_vararg:       0
; Max Stack Size:  5

  1 [-]: GETUPVAL  R4 U0        ; R4 := U0
  2 [-]: CALL      R4 1 1       ; R4()
  3 [-]: RETURN    R0 1         ; return 


; Function #10:
;
; Name:            
; Defined at line: 206
; #Upvalues:       1
; #Parameters:     1
; Is_vararg:       0
; Max Stack Size:  3

  1 [-]: MOVE      R0 R0        ; R0 := R0
  2 [-]: GETGLOBAL R1 K0        ; R1 := 0x400E7765
  3 [-]: MOVE      R2 R0        ; R2 := R0
  4 [-]: CALL      R1 2 2       ; R1 := R1(R2)
  5 [-]: MOVE      R1 R1        ; R1 := R1
  6 [-]: RETURN    R1 2         ; return R1
  7 [-]: RETURN    R0 1         ; return 


; Function #11:
;
; Name:            
; Defined at line: 211
; #Upvalues:       1
; #Parameters:     0
; Is_vararg:       0
; Max Stack Size:  3

  1 [-]: GETGLOBAL R0 K0        ; R0 := mMovie
  2 [-]: SELF      R0 R0 K1     ; R1 := R0; R0 := R0["0x625791A8"]
  3 [-]: GETUPVAL  R2 U0        ; R2 := U0
  4 [-]: CALL      R0 3 1       ; R0(R1,R2)
  5 [-]: RETURN    R0 1         ; return 


; Function #12:
;
; Name:            
; Defined at line: 215
; #Upvalues:       5
; #Parameters:     2
; Is_vararg:       0
; Max Stack Size:  9

  1 [-]: EQ        1 R0 K0      ; if R0 == "true" then PC := 4
  2 [-]: JMP       4            ; PC := 4
  3 [-]: MOVE      R2 R0        ; R2 := R0
  4 [-]: MOVE      R2 R1        ; R2 := R1
  5 [-]: MOVE      R2 R0        ; R2 := R0
  6 [-]: GETUPVAL  R2 U1        ; R2 := U1
  7 [-]: CALL      R2 1 1       ; R2()
  8 [-]: GETGLOBAL R2 K1        ; R2 := 0x400E7765
  9 [-]: GETUPVAL  R3 U2        ; R3 := U2
 10 [-]: CALL      R2 2 2       ; R2 := R2(R3)
 11 [-]: TEST      R2 1         ; if R2 then PC := 42
 12 [-]: JMP       42           ; PC := 42
 13 [-]: GETGLOBAL R2 K2        ; R2 := radialBlurStrength
 14 [-]: LT        0 K3 R2      ; if 0 >= R2 then PC := 42
 15 [-]: JMP       42           ; PC := 42
 16 [-]: GETGLOBAL R2 K1        ; R2 := 0x400E7765
 17 [-]: GETUPVAL  R3 U3        ; R3 := U3
 18 [-]: CALL      R2 2 2       ; R2 := R2(R3)
 19 [-]: TEST      R2 1         ; if R2 then PC := 42
 20 [-]: JMP       42           ; PC := 42
 21 [-]: GETUPVAL  R2 U0        ; R2 := U0
 22 [-]: TEST      R2 0         ; if not R2 then PC := 33
 23 [-]: JMP       33           ; PC := 33
 24 [-]: GETUPVAL  R2 U3        ; R2 := U3
 25 [-]: SELF      R2 R2 K4     ; R3 := R2; R2 := R2["0x9FD36BA"]
 26 [-]: GETGLOBAL R4 K2        ; R4 := radialBlurStrength
 27 [-]: LOADK     R5 K5        ; R5 := 10
 28 [-]: LOADK     R6 K5        ; R6 := 10
 29 [-]: GETGLOBAL R7 K6        ; R7 := radialBlurDuration
 30 [-]: GETUPVAL  R8 U4        ; R8 := U4
 31 [-]: CALL      R2 7 1       ; R2(R3,R4,R5,R6,R7,R8)
 32 [-]: JMP       42           ; PC := 42
 33 [-]: GETUPVAL  R2 U3        ; R2 := U3
 34 [-]: SELF      R2 R2 K7     ; R3 := R2; R2 := R2["0x3EAD0003"]
 35 [-]: GETUPVAL  R4 U4        ; R4 := U4
 36 [-]: CALL      R2 3 1       ; R2(R3,R4)
 37 [-]: GETUPVAL  R2 U3        ; R2 := U3
 38 [-]: SELF      R2 R2 K8     ; R3 := R2; R2 := R2["0x29E3D5B1"]
 39 [-]: GETGLOBAL R4 K9        ; R4 := colorCorrectionTexture
 40 [-]: LOADK     R5 K3        ; R5 := 0
 41 [-]: CALL      R2 4 1       ; R2(R3,R4,R5)
 42 [-]: RETURN    R0 1         ; return 


; Function #13:
;
; Name:            
; Defined at line: 233
; #Upvalues:       1
; #Parameters:     1
; Is_vararg:       0
; Max Stack Size:  3

  1 [-]: GETUPVAL  R1 U0        ; R1 := U0
  2 [-]: MOVE      R2 R0        ; R2 := R0
  3 [-]: CALL      R1 2 1       ; R1(R2)
  4 [-]: RETURN    R0 1         ; return 


; Function #14:
;
; Name:            
; Defined at line: 237
; #Upvalues:       4
; #Parameters:     2
; Is_vararg:       0
; Max Stack Size:  6

  1 [-]: EQ        1 R0 K0      ; if R0 == "true" then PC := 4
  2 [-]: JMP       4            ; PC := 4
  3 [-]: MOVE      R2 R0        ; R2 := R0
  4 [-]: MOVE      R2 R1        ; R2 := R1
  5 [-]: MOVE      R2 R0        ; R2 := R0
  6 [-]: GETUPVAL  R2 U0        ; R2 := U0
  7 [-]: TEST      R2 1         ; if R2 then PC := 23
  8 [-]: JMP       23           ; PC := 23
  9 [-]: GETGLOBAL R2 K1        ; R2 := 0x400E7765
 10 [-]: GETUPVAL  R3 U1        ; R3 := U1
 11 [-]: CALL      R2 2 2       ; R2 := R2(R3)
 12 [-]: TEST      R2 1         ; if R2 then PC := 36
 13 [-]: JMP       36           ; PC := 36
 14 [-]: GETGLOBAL R2 K2        ; R2 := 0x93B1256B
 15 [-]: LOADK     R3 K3        ; R3 := "ScopeDebug: Show from MiningLaserReticle:_SetEnabled"
 16 [-]: CALL      R2 2 1       ; R2(R3)
 17 [-]: GETUPVAL  R2 U1        ; R2 := U1
 18 [-]: SELF      R2 R2 K4     ; R3 := R2; R2 := R2["0x458F27A9"]
 19 [-]: LOADK     R4 K5        ; R4 := "ShowReticle"
 20 [-]: LOADK     R5 K6        ; R5 := ""
 21 [-]: CALL      R2 4 1       ; R2(R3,R4,R5)
 22 [-]: JMP       36           ; PC := 36
 23 [-]: GETGLOBAL R2 K1        ; R2 := 0x400E7765
 24 [-]: GETUPVAL  R3 U1        ; R3 := U1
 25 [-]: CALL      R2 2 2       ; R2 := R2(R3)
 26 [-]: TEST      R2 1         ; if R2 then PC := 36
 27 [-]: JMP       36           ; PC := 36
 28 [-]: GETGLOBAL R2 K2        ; R2 := 0x93B1256B
 29 [-]: LOADK     R3 K7        ; R3 := "ScopeDebug: Hide from MiningLaserReticle:_SetEnabled"
 30 [-]: CALL      R2 2 1       ; R2(R3)
 31 [-]: GETUPVAL  R2 U1        ; R2 := U1
 32 [-]: SELF      R2 R2 K4     ; R3 := R2; R2 := R2["0x458F27A9"]
 33 [-]: LOADK     R4 K8        ; R4 := "HideReticle"
 34 [-]: LOADK     R5 K6        ; R5 := ""
 35 [-]: CALL      R2 4 1       ; R2(R3,R4,R5)
 36 [-]: GETUPVAL  R2 U2        ; R2 := U2
 37 [-]: CALL      R2 1 1       ; R2()
 38 [-]: GETUPVAL  R2 U3        ; R2 := U3
 39 [-]: MOVE      R3 R1        ; R3 := R1
 40 [-]: GETUPVAL  R4 U0        ; R4 := U0
 41 [-]: CALL      R2 3 1       ; R2(R3,R4)
 42 [-]: RETURN    R0 1         ; return 


; Function #15:
;
; Name:            
; Defined at line: 256
; #Upvalues:       1
; #Parameters:     2
; Is_vararg:       0
; Max Stack Size:  5

  1 [-]: GETUPVAL  R2 U0        ; R2 := U0
  2 [-]: MOVE      R3 R0        ; R3 := R0
  3 [-]: MOVE      R4 R1        ; R4 := R1
  4 [-]: CALL      R2 3 1       ; R2(R3,R4)
  5 [-]: RETURN    R0 1         ; return 


; Function #16:
;
; Name:            
; Defined at line: 260
; #Upvalues:       1
; #Parameters:     0
; Is_vararg:       0
; Max Stack Size:  6

  1 [-]: GETGLOBAL R0 K0        ; R0 := gRegion
  2 [-]: SELF      R0 R0 K1     ; R1 := R0; R0 := R0["0x3E2F6BF"]
  3 [-]: CALL      R0 2 2       ; R0 := R0(R1)
  4 [-]: SELF      R1 R0 K2     ; R2 := R0; R1 := R0["0x5AF30A19"]
  5 [-]: CALL      R1 2 2       ; R1 := R1(R2)
  6 [-]: GETGLOBAL R2 K3        ; R2 := 0x400E7765
  7 [-]: MOVE      R3 R1        ; R3 := R1
  8 [-]: CALL      R2 2 2       ; R2 := R2(R3)
  9 [-]: TEST      R2 1         ; if R2 then PC := 18
 10 [-]: JMP       18           ; PC := 18
 11 [-]: SELF      R2 R1 K4     ; R3 := R1; R2 := R1["0x3EAD0003"]
 12 [-]: GETUPVAL  R4 U0        ; R4 := U0
 13 [-]: CALL      R2 3 1       ; R2(R3,R4)
 14 [-]: SELF      R2 R1 K5     ; R3 := R1; R2 := R1["0x29E3D5B1"]
 15 [-]: GETGLOBAL R4 K6        ; R4 := colorCorrectionTexture
 16 [-]: LOADK     R5 K7        ; R5 := 0
 17 [-]: CALL      R2 4 1       ; R2(R3,R4,R5)
 18 [-]: RETURN    R0 1         ; return 


; Function #17:
;
; Name:            
; Defined at line: 269
; #Upvalues:       2
; #Parameters:     0
; Is_vararg:       0
; Max Stack Size:  9

  1 [-]: GETUPVAL  R0 U0        ; R0 := U0
  2 [-]: TEST      R0 0         ; if not R0 then PC := 22
  3 [-]: JMP       22           ; PC := 22
  4 [-]: MOVE      R0 R0        ; R0 := R0
  5 [-]: MOVE      R0 R0        ; R0 := R0
  6 [-]: GETGLOBAL R0 K0        ; R0 := 0x52E17A90
  7 [-]: GETGLOBAL R1 K1        ; R1 := mMovie
  8 [-]: LOADK     R2 K2        ; R2 := "Gauge"
  9 [-]: GETGLOBAL R3 K3        ; R3 := UISys
 10 [-]: GETTABLE  R3 R3 K4     ; R3 := R3["FlashInstance_EASE_OUT"]
 11 [-]: NEWTABLE  R4 1 0       ; R4 := {}
 12 [-]: LOADK     R5 K5        ; R5 := "_alpha"
 13 [-]: SETLIST   R4 1 1       ; R4[(1-1)*FPF+i] := R(4+i), 1 <= i <= 1
 14 [-]: NEWTABLE  R5 1 0       ; R5 := {}
 15 [-]: LOADK     R6 K6        ; R6 := 0
 16 [-]: SETLIST   R5 1 1       ; R5[(1-1)*FPF+i] := R(5+i), 1 <= i <= 1
 17 [-]: LOADK     R6 K7        ; R6 := 0.10000000149012
 18 [-]: LOADK     R7 K8        ; R7 := 0.40000000596046
 19 [-]: CLOSURE   R8 0         ; R8 := closure(Function #17.1)
 20 [-]: GETUPVAL  R0 U1        ; R0 := U1
 21 [-]: CALL      R0 9 1       ; R0(R1,R2,R3,R4,R5,R6,R7,R8)
 22 [-]: RETURN    R0 1         ; return 


; Function #17.1:
;
; Name:            
; Defined at line: 273
; #Upvalues:       1
; #Parameters:     0
; Is_vararg:       0
; Max Stack Size:  4

  1 [-]: GETGLOBAL R0 K0        ; R0 := 0x400E7765
  2 [-]: GETUPVAL  R1 U0        ; R1 := U0
  3 [-]: CALL      R0 2 2       ; R0 := R0(R1)
  4 [-]: TEST      R0 1         ; if R0 then PC := 11
  5 [-]: JMP       11           ; PC := 11
  6 [-]: GETUPVAL  R0 U0        ; R0 := U0
  7 [-]: SELF      R0 R0 K1     ; R1 := R0; R0 := R0["0x458F27A9"]
  8 [-]: LOADK     R2 K2        ; R2 := "ShowAbilityDots"
  9 [-]: LOADK     R3 K3        ; R3 := ""
 10 [-]: CALL      R0 4 1       ; R0(R1,R2,R3)
 11 [-]: RETURN    R0 1         ; return 


; Function #18:
;
; Name:            
; Defined at line: 281
; #Upvalues:       5
; #Parameters:     4
; Is_vararg:       0
; Max Stack Size:  15

  1 [-]: GETGLOBAL R4 K0        ; R4 := 0x400E7765
  2 [-]: GETUPVAL  R5 U0        ; R5 := U0
  3 [-]: CALL      R4 2 2       ; R4 := R4(R5)
  4 [-]: TEST      R4 1         ; if R4 then PC := 89
  5 [-]: JMP       89           ; PC := 89
  6 [-]: LOADK     R4 K1        ; R4 := 0
  7 [-]: LT        1 R0 R1      ; if R0 < R1 then PC := 11
  8 [-]: JMP       11           ; PC := 11
  9 [-]: LT        0 R2 R0      ; if R2 >= R0 then PC := 23
 10 [-]: JMP       23           ; PC := 23
 11 [-]: GETGLOBAL R5 K2        ; R5 := math
 12 [-]: GETTABLE  R5 R5 K3     ; R5 := R5["0x65F9712A"]
 13 [-]: GETGLOBAL R6 K2        ; R6 := math
 14 [-]: GETTABLE  R6 R6 K4     ; R6 := R6["0xF93F7CC8"]
 15 [-]: SUB       R7 R0 R1     ; R7 := R0 - R1
 16 [-]: CALL      R6 2 2       ; R6 := R6(R7)
 17 [-]: GETGLOBAL R7 K2        ; R7 := math
 18 [-]: GETTABLE  R7 R7 K4     ; R7 := R7["0xF93F7CC8"]
 19 [-]: SUB       R8 R0 R2     ; R8 := R0 - R2
 20 [-]: CALL      R7 2 0       ; R7,... := R7(R8)
 21 [-]: CALL      R5 0 2       ; R5 := R5(R6,...)
 22 [-]: MOVE      R4 R5        ; R4 := R5
 23 [-]: GETUPVAL  R5 U1        ; R5 := U1
 24 [-]: TEST      R5 0         ; if not R5 then PC := 81
 25 [-]: JMP       81           ; PC := 81
 26 [-]: GETUPVAL  R5 U2        ; R5 := U2
 27 [-]: TEST      R5 0         ; if not R5 then PC := 81
 28 [-]: JMP       81           ; PC := 81
 29 [-]: GETGLOBAL R5 K5        ; R5 := minProximityForSweetSpotCue
 30 [-]: LE        0 R4 R5      ; if R4 > R5 then PC := 81
 31 [-]: JMP       81           ; PC := 81
 32 [-]: GETGLOBAL R5 K2        ; R5 := math
 33 [-]: GETTABLE  R5 R5 K4     ; R5 := R5["0xF93F7CC8"]
 34 [-]: SUB       R6 R2 R1     ; R6 := R2 - R1
 35 [-]: CALL      R5 2 2       ; R5 := R5(R6)
 36 [-]: DIV       R5 R5 K6     ; R5 := R5 / 2
 37 [-]: ADD       R6 R1 R5     ; R6 := R1 + R5
 38 [-]: GETGLOBAL R7 K2        ; R7 := math
 39 [-]: GETTABLE  R7 R7 K4     ; R7 := R7["0xF93F7CC8"]
 40 [-]: SUB       R8 R0 R6     ; R8 := R0 - R6
 41 [-]: CALL      R7 2 2       ; R7 := R7(R8)
 42 [-]: GETGLOBAL R8 K5        ; R8 := minProximityForSweetSpotCue
 43 [-]: ADD       R8 R8 R5     ; R8 := R8 + R5
 44 [-]: DIV       R9 R7 R8     ; R9 := R7 / R8
 45 [-]: SUB       R9 K7 R9     ; R9 := 1 - R9
 46 [-]: GETUPVAL  R10 U3       ; R10 := U3
 47 [-]: TEST      R10 0        ; if not R10 then PC := 64
 48 [-]: JMP       64           ; PC := 64
 49 [-]: MOVE      R10 R0       ; R10 := R0
 50 [-]: MOVE      R10 R3       ; R10 := R3
 51 [-]: GETUPVAL  R10 U0       ; R10 := U0
 52 [-]: SELF      R10 R10 K8   ; R11 := R10; R10 := R10["0x880F0700"]
 53 [-]: GETGLOBAL R12 K9       ; R12 := proximityGainRange
 54 [-]: GETTABLE  R12 R12 K10  ; R12 := R12["minValue"]
 55 [-]: CALL      R10 3 1      ; R10(R11,R12)
 56 [-]: GETUPVAL  R10 U0       ; R10 := U0
 57 [-]: SELF      R10 R10 K11  ; R11 := R10; R10 := R10["0x683C0132"]
 58 [-]: GETGLOBAL R12 K12      ; R12 := proximityPitchRange
 59 [-]: GETTABLE  R12 R12 K10  ; R12 := R12["minValue"]
 60 [-]: CALL      R10 3 1      ; R10(R11,R12)
 61 [-]: GETUPVAL  R10 U0       ; R10 := U0
 62 [-]: SELF      R10 R10 K13  ; R11 := R10; R10 := R10["0x472F5C1C"]
 63 [-]: CALL      R10 2 1      ; R10(R11)
 64 [-]: GETGLOBAL R10 K9       ; R10 := proximityGainRange
 65 [-]: SELF      R10 R10 K14  ; R11 := R10; R10 := R10["0xA27950B2"]
 66 [-]: MOVE      R12 R9       ; R12 := R9
 67 [-]: CALL      R10 3 2      ; R10 := R10(R11,R12)
 68 [-]: GETUPVAL  R11 U0       ; R11 := U0
 69 [-]: SELF      R11 R11 K8   ; R12 := R11; R11 := R11["0x880F0700"]
 70 [-]: MOVE      R13 R10      ; R13 := R10
 71 [-]: CALL      R11 3 1      ; R11(R12,R13)
 72 [-]: GETGLOBAL R11 K12      ; R11 := proximityPitchRange
 73 [-]: SELF      R11 R11 K14  ; R12 := R11; R11 := R11["0xA27950B2"]
 74 [-]: MOVE      R13 R9       ; R13 := R9
 75 [-]: CALL      R11 3 2      ; R11 := R11(R12,R13)
 76 [-]: GETUPVAL  R12 U0       ; R12 := U0
 77 [-]: SELF      R12 R12 K11  ; R13 := R12; R12 := R12["0x683C0132"]
 78 [-]: MOVE      R14 R11      ; R14 := R11
 79 [-]: CALL      R12 3 1      ; R12(R13,R14)
 80 [-]: JMP       89           ; PC := 89
 81 [-]: GETUPVAL  R12 U3       ; R12 := U3
 82 [-]: TEST      R12 1        ; if R12 then PC := 89
 83 [-]: JMP       89           ; PC := 89
 84 [-]: GETUPVAL  R12 U0       ; R12 := U0
 85 [-]: SELF      R12 R12 K15  ; R13 := R12; R12 := R12["0x6EEAD185"]
 86 [-]: CALL      R12 2 1      ; R12(R13)
 87 [-]: MOVE      R12 R1       ; R12 := R1
 88 [-]: MOVE      R12 R3       ; R12 := R3
 89 [-]: TEST      R3 0         ; if not R3 then PC := 95
 90 [-]: JMP       95           ; PC := 95
 91 [-]: GETUPVAL  R12 U4       ; R12 := U4
 92 [-]: GETTABLE  R12 R12 K16  ; R12 := R12["0x25992394"]
 93 [-]: GETGLOBAL R13 K17      ; R13 := enteredSweetSpotSound
 94 [-]: CALL      R12 2 1      ; R12(R13)
 95 [-]: RETURN    R0 1         ; return 


; Function #19:
;
; Name:            
; Defined at line: 320
; #Upvalues:       2
; #Parameters:     2
; Is_vararg:       0
; Max Stack Size:  8

  1 [-]: GETGLOBAL R2 K0        ; R2 := 0x400E7765
  2 [-]: MOVE      R3 R0        ; R3 := R0
  3 [-]: CALL      R2 2 2       ; R2 := R2(R3)
  4 [-]: TEST      R2 1         ; if R2 then PC := 23
  5 [-]: JMP       23           ; PC := 23
  6 [-]: GETUPVAL  R2 U0        ; R2 := U0
  7 [-]: GETTABLE  R3 R0 K1     ; R3 := R0["progression"]
  8 [-]: GETTABLE  R4 R0 K2     ; R4 := R0["sweetSpot"]
  9 [-]: GETTABLE  R4 R4 K3     ; R4 := R4["START"]
 10 [-]: GETTABLE  R5 R0 K2     ; R5 := R0["sweetSpot"]
 11 [-]: GETTABLE  R5 R5 K4     ; R5 := R5["END"]
 12 [-]: GETTABLE  R6 R0 K5     ; R6 := R0["gemSpot"]
 13 [-]: MOVE      R7 R1        ; R7 := R1
 14 [-]: CALL      R2 6 1       ; R2(R3,R4,R5,R6,R7)
 15 [-]: GETUPVAL  R2 U1        ; R2 := U1
 16 [-]: GETTABLE  R3 R0 K1     ; R3 := R0["progression"]
 17 [-]: GETTABLE  R4 R0 K2     ; R4 := R0["sweetSpot"]
 18 [-]: GETTABLE  R4 R4 K3     ; R4 := R4["START"]
 19 [-]: GETTABLE  R5 R0 K2     ; R5 := R0["sweetSpot"]
 20 [-]: GETTABLE  R5 R5 K4     ; R5 := R5["END"]
 21 [-]: GETTABLE  R6 R0 K6     ; R6 := R0["enteredSweetSpot"]
 22 [-]: CALL      R2 5 1       ; R2(R3,R4,R5,R6)
 23 [-]: RETURN    R0 1         ; return 


; Function #20:
;
; Name:            
; Defined at line: 327
; #Upvalues:       4
; #Parameters:     1
; Is_vararg:       0
; Max Stack Size:  6

  1 [-]: MOVE      R0 R0        ; R0 := R0
  2 [-]: GETUPVAL  R1 U1        ; R1 := U1
  3 [-]: GETTABLE  R1 R1 K0     ; R1 := R1["0xF81722A2"]
  4 [-]: GETUPVAL  R2 U0        ; R2 := U0
  5 [-]: MOVE      R2 R2        ; R2 := R2
  6 [-]: LOADK     R3 K1        ; R3 := "true"
  7 [-]: LOADK     R4 K2        ; R4 := "false"
  8 [-]: CALL      R1 4 2       ; R1 := R1(R2,R3,R4)
  9 [-]: GETUPVAL  R2 U1        ; R2 := U1
 10 [-]: GETTABLE  R2 R2 K0     ; R2 := R2["0xF81722A2"]
 11 [-]: GETUPVAL  R3 U2        ; R3 := U2
 12 [-]: LOADK     R4 K1        ; R4 := "true"
 13 [-]: LOADK     R5 K2        ; R5 := "false"
 14 [-]: CALL      R2 4 2       ; R2 := R2(R3,R4,R5)
 15 [-]: GETUPVAL  R3 U3        ; R3 := U3
 16 [-]: MOVE      R4 R1        ; R4 := R1
 17 [-]: MOVE      R5 R2        ; R5 := R2
 18 [-]: CALL      R3 3 1       ; R3(R4,R5)
 19 [-]: RETURN    R0 1         ; return 


; Function #21:
;
; Name:            
; Defined at line: 334
; #Upvalues:       3
; #Parameters:     1
; Is_vararg:       0
; Max Stack Size:  5

  1 [-]: TEST      R0 0         ; if not R0 then PC := 25
  2 [-]: JMP       25           ; PC := 25
  3 [-]: GETGLOBAL R1 K0        ; R1 := 0x400E7765
  4 [-]: GETUPVAL  R2 U0        ; R2 := U0
  5 [-]: CALL      R1 2 2       ; R1 := R1(R2)
  6 [-]: TEST      R1 1         ; if R1 then PC := 14
  7 [-]: JMP       14           ; PC := 14
  8 [-]: GETGLOBAL R1 K0        ; R1 := 0x400E7765
  9 [-]: GETUPVAL  R2 U0        ; R2 := U0
 10 [-]: GETTABLE  R2 R2 K1     ; R2 := R2["target"]
 11 [-]: CALL      R1 2 2       ; R1 := R1(R2)
 12 [-]: MOVE      R1 R1        ; R1 := R1
 13 [-]: JMP       16           ; PC := 16
 14 [-]: MOVE      R1 R0        ; R1 := R0
 15 [-]: MOVE      R1 R1        ; R1 := R1
 16 [-]: TEST      R1 0         ; if not R1 then PC := 27
 17 [-]: JMP       27           ; PC := 27
 18 [-]: GETUPVAL  R2 U1        ; R2 := U1
 19 [-]: GETUPVAL  R3 U0        ; R3 := U0
 20 [-]: GETTABLE  R3 R3 K1     ; R3 := R3["target"]
 21 [-]: SELF      R3 R3 K2     ; R4 := R3; R3 := R3["0x6DA72501"]
 22 [-]: CALL      R3 2 0       ; R3,... := R3(R4)
 23 [-]: CALL      R2 0 1       ; R2(R3,...)
 24 [-]: JMP       27           ; PC := 27
 25 [-]: GETUPVAL  R2 U2        ; R2 := U2
 26 [-]: CALL      R2 1 1       ; R2()
 27 [-]: RETURN    R0 1         ; return 


; Function #22:
;
; Name:            
; Defined at line: 345
; #Upvalues:       5
; #Parameters:     1
; Is_vararg:       0
; Max Stack Size:  9

  1 [-]: GETGLOBAL R1 K0        ; R1 := 0x400E7765
  2 [-]: MOVE      R2 R0        ; R2 := R0
  3 [-]: CALL      R1 2 2       ; R1 := R1(R2)
  4 [-]: TEST      R1 1         ; if R1 then PC := 11
  5 [-]: JMP       11           ; PC := 11
  6 [-]: GETGLOBAL R1 K0        ; R1 := 0x400E7765
  7 [-]: GETTABLE  R2 R0 K1     ; R2 := R0["target"]
  8 [-]: CALL      R1 2 2       ; R1 := R1(R2)
  9 [-]: MOVE      R1 R1        ; R1 := R1
 10 [-]: JMP       13           ; PC := 13
 11 [-]: MOVE      R1 R0        ; R1 := R0
 12 [-]: MOVE      R1 R1        ; R1 := R1
 13 [-]: GETGLOBAL R2 K2        ; R2 := 0x8C64AFA9
 14 [-]: GETGLOBAL R3 K3        ; R3 := mMovie
 15 [-]: LOADK     R4 K4        ; R4 := "Info.UnzoomedReticle.gotoAndStop"
 16 [-]: GETUPVAL  R5 U0        ; R5 := U0
 17 [-]: GETTABLE  R5 R5 K5     ; R5 := R5["0xF81722A2"]
 18 [-]: MOVE      R6 R1        ; R6 := R1
 19 [-]: LOADK     R7 K6        ; R7 := "Closed"
 20 [-]: LOADK     R8 K7        ; R8 := "Open"
 21 [-]: CALL      R5 4 0       ; R5,... := R5(R6,R7,R8)
 22 [-]: CALL      R2 0 1       ; R2(R3,...)
 23 [-]: TEST      R1 0         ; if not R1 then PC := 34
 24 [-]: JMP       34           ; PC := 34
 25 [-]: GETUPVAL  R2 U1        ; R2 := U1
 26 [-]: TEST      R2 0         ; if not R2 then PC := 38
 27 [-]: JMP       38           ; PC := 38
 28 [-]: GETUPVAL  R2 U2        ; R2 := U2
 29 [-]: GETTABLE  R3 R0 K1     ; R3 := R0["target"]
 30 [-]: SELF      R3 R3 K8     ; R4 := R3; R3 := R3["0x6DA72501"]
 31 [-]: CALL      R3 2 0       ; R3,... := R3(R4)
 32 [-]: CALL      R2 0 1       ; R2(R3,...)
 33 [-]: JMP       38           ; PC := 38
 34 [-]: GETUPVAL  R2 U3        ; R2 := U3
 35 [-]: CALL      R2 1 1       ; R2()
 36 [-]: GETUPVAL  R2 U4        ; R2 := U4
 37 [-]: CALL      R2 1 1       ; R2()
 38 [-]: RETURN    R0 1         ; return 


; Function #23:
;
; Name:            
; Defined at line: 359
; #Upvalues:       7
; #Parameters:     0
; Is_vararg:       0
; Max Stack Size:  9

  1 [-]: GETUPVAL  R0 U0        ; R0 := U0
  2 [-]: SELF      R0 R0 K0     ; R1 := R0; R0 := R0["0x726C32B7"]
  3 [-]: CALL      R0 2 2       ; R0 := R0(R1)
  4 [-]: GETUPVAL  R1 U1        ; R1 := U1
  5 [-]: TEST      R1 1         ; if R1 then PC := 10
  6 [-]: JMP       10           ; PC := 10
  7 [-]: GETUPVAL  R1 U2        ; R1 := U2
  8 [-]: TEST      R1 0         ; if not R1 then PC := 57
  9 [-]: JMP       57           ; PC := 57
 10 [-]: GETUPVAL  R1 U0        ; R1 := U0
 11 [-]: SELF      R1 R1 K1     ; R2 := R1; R1 := R1["0x578740F0"]
 12 [-]: CALL      R1 2 2       ; R1 := R1(R2)
 13 [-]: TEST      R1 0         ; if not R1 then PC := 57
 14 [-]: JMP       57           ; PC := 57
 15 [-]: GETGLOBAL R1 K2        ; R1 := 0x400E7765
 16 [-]: GETUPVAL  R2 U3        ; R2 := U3
 17 [-]: CALL      R1 2 2       ; R1 := R1(R2)
 18 [-]: TEST      R1 0         ; if not R1 then PC := 40
 19 [-]: JMP       40           ; PC := 40
 20 [-]: GETGLOBAL R1 K3        ; R1 := gRegion
 21 [-]: SELF      R1 R1 K4     ; R2 := R1; R1 := R1["0xF7C1BE25"]
 22 [-]: CALL      R1 2 2       ; R1 := R1(R2)
 23 [-]: SELF      R2 R1 K5     ; R3 := R1; R2 := R1["0x9F1DC568"]
 24 [-]: GETGLOBAL R4 K6        ; R4 := imagingDecoType
 25 [-]: CALL      R2 3 2       ; R2 := R2(R3,R4)
 26 [-]: MOVE      R2 R3        ; R2 := R3
 27 [-]: GETGLOBAL R2 K2        ; R2 := 0x400E7765
 28 [-]: GETUPVAL  R3 U3        ; R3 := U3
 29 [-]: CALL      R2 2 2       ; R2 := R2(R3)
 30 [-]: TEST      R2 0         ; if not R2 then PC := 40
 31 [-]: JMP       40           ; PC := 40
 32 [-]: SELF      R2 R1 K7     ; R3 := R1; R2 := R1["0xAB436EF2"]
 33 [-]: GETGLOBAL R4 K6        ; R4 := imagingDecoType
 34 [-]: GETGLOBAL R5 K8        ; R5 := EMPTY_SYMBOL
 35 [-]: GETUPVAL  R6 U4        ; R6 := U4
 36 [-]: GETUPVAL  R7 U5        ; R7 := U5
 37 [-]: GETUPVAL  R8 U0        ; R8 := U0
 38 [-]: CALL      R2 7 2       ; R2 := R2(R3,R4,R5,R6,R7,R8)
 39 [-]: MOVE      R2 R3        ; R2 := R3
 40 [-]: GETGLOBAL R2 K2        ; R2 := 0x400E7765
 41 [-]: GETUPVAL  R3 U3        ; R3 := U3
 42 [-]: CALL      R2 2 2       ; R2 := R2(R3)
 43 [-]: TEST      R2 1         ; if R2 then PC := 67
 44 [-]: JMP       67           ; PC := 67
 45 [-]: GETGLOBAL R2 K9        ; R2 := 0x93034B55
 46 [-]: GETUPVAL  R3 U6        ; R3 := U6
 47 [-]: MOVE      R4 R0        ; R4 := R0
 48 [-]: LOADK     R5 K10       ; R5 := 0.050000000745058
 49 [-]: CALL      R2 4 2       ; R2 := R2(R3,R4,R5)
 50 [-]: MOVE      R2 R6        ; R2 := R6
 51 [-]: GETUPVAL  R2 U3        ; R2 := U3
 52 [-]: SELF      R2 R2 K11    ; R3 := R2; R2 := R2["0x6A7E5F92"]
 53 [-]: GETUPVAL  R4 U6        ; R4 := U6
 54 [-]: MUL       R4 K12 R4    ; R4 := 4 * R4
 55 [-]: CALL      R2 3 1       ; R2(R3,R4)
 56 [-]: JMP       67           ; PC := 67
 57 [-]: GETGLOBAL R2 K2        ; R2 := 0x400E7765
 58 [-]: GETUPVAL  R3 U3        ; R3 := U3
 59 [-]: CALL      R2 2 2       ; R2 := R2(R3)
 60 [-]: TEST      R2 1         ; if R2 then PC := 67
 61 [-]: JMP       67           ; PC := 67
 62 [-]: GETUPVAL  R2 U3        ; R2 := U3
 63 [-]: SELF      R2 R2 K13    ; R3 := R2; R2 := R2["0x5AB2AAEF"]
 64 [-]: CALL      R2 2 1       ; R2(R3)
 65 [-]: LOADNIL   R2 R2        ; R2 := nil
 66 [-]: MOVE      R2 R3        ; R2 := R3
 67 [-]: RETURN    R0 1         ; return 


; Function #24:
;
; Name:            
; Defined at line: 381
; #Upvalues:       31
; #Parameters:     0
; Is_vararg:       0
; Max Stack Size:  21

  1 [-]: GETGLOBAL R0 K0        ; R0 := 0x400E7765
  2 [-]: GETUPVAL  R1 U0        ; R1 := U0
  3 [-]: CALL      R0 2 2       ; R0 := R0(R1)
  4 [-]: TEST      R0 0         ; if not R0 then PC := 10
  5 [-]: JMP       10           ; PC := 10
  6 [-]: GETGLOBAL R0 K1        ; R0 := gGameRules
  7 [-]: SELF      R0 R0 K2     ; R1 := R0; R0 := R0["0x8709CE86"]
  8 [-]: CALL      R0 2 2       ; R0 := R0(R1)
  9 [-]: MOVE      R0 R0        ; R0 := R0
 10 [-]: GETGLOBAL R0 K0        ; R0 := 0x400E7765
 11 [-]: GETUPVAL  R1 U0        ; R1 := U0
 12 [-]: CALL      R0 2 2       ; R0 := R0(R1)
 13 [-]: TEST      R0 1         ; if R0 then PC := 27
 14 [-]: JMP       27           ; PC := 27
 15 [-]: GETGLOBAL R0 K3        ; R0 := _T
 16 [-]: GETTABLE  R0 R0 K4     ; R0 := R0["reticleState"]
 17 [-]: TEST      R0 0         ; if not R0 then PC := 27
 18 [-]: JMP       27           ; PC := 27
 19 [-]: GETGLOBAL R0 K5        ; R0 := 0x93B1256B
 20 [-]: LOADK     R1 K6        ; R1 := "ScopeDebug: Hide from MiningLaserReticle:Update"
 21 [-]: CALL      R0 2 1       ; R0(R1)
 22 [-]: GETUPVAL  R0 U0        ; R0 := U0
 23 [-]: SELF      R0 R0 K7     ; R1 := R0; R0 := R0["0x458F27A9"]
 24 [-]: LOADK     R2 K8        ; R2 := "HideReticle"
 25 [-]: LOADK     R3 K9        ; R3 := ""
 26 [-]: CALL      R0 4 1       ; R0(R1,R2,R3)
 27 [-]: GETUPVAL  R0 U1        ; R0 := U1
 28 [-]: TEST      R0 1         ; if R0 then PC := 32
 29 [-]: JMP       32           ; PC := 32
 30 [-]: GETUPVAL  R0 U2        ; R0 := U2
 31 [-]: CALL      R0 1 1       ; R0()
 32 [-]: GETUPVAL  R0 U1        ; R0 := U1
 33 [-]: TEST      R0 1         ; if R0 then PC := 36
 34 [-]: JMP       36           ; PC := 36
 35 [-]: RETURN    R0 1         ; return 
 36 [-]: GETGLOBAL R0 K0        ; R0 := 0x400E7765
 37 [-]: GETUPVAL  R1 U3        ; R1 := U3
 38 [-]: CALL      R0 2 2       ; R0 := R0(R1)
 39 [-]: TEST      R0 1         ; if R0 then PC := 46
 40 [-]: JMP       46           ; PC := 46
 41 [-]: GETUPVAL  R0 U3        ; R0 := U3
 42 [-]: SELF      R0 R0 K10    ; R1 := R0; R0 := R0["0x8C7099E9"]
 43 [-]: GETGLOBAL R2 K11       ; R2 := 0x4CDEF9FF
 44 [-]: CALL      R2 1 0       ; R2,... := R2()
 45 [-]: CALL      R0 0 1       ; R0(R1,...)
 46 [-]: GETGLOBAL R0 K12       ; R0 := mMovie
 47 [-]: SELF      R0 R0 K13    ; R1 := R0; R0 := R0["0x80D6B1A"]
 48 [-]: GETGLOBAL R2 K14       ; R2 := 0x6306558E
 49 [-]: CALL      R2 1 0       ; R2,... := R2()
 50 [-]: CALL      R0 0 1       ; R0(R1,...)
 51 [-]: GETGLOBAL R0 K0        ; R0 := 0x400E7765
 52 [-]: GETUPVAL  R1 U4        ; R1 := U4
 53 [-]: CALL      R0 2 2       ; R0 := R0(R1)
 54 [-]: TEST      R0 1         ; if R0 then PC := 65
 55 [-]: JMP       65           ; PC := 65
 56 [-]: GETUPVAL  R0 U4        ; R0 := U4
 57 [-]: SELF      R0 R0 K15    ; R1 := R0; R0 := R0["0x2D1EF09A"]
 58 [-]: CALL      R0 2 2       ; R0 := R0(R1)
 59 [-]: GETUPVAL  R1 U5        ; R1 := U5
 60 [-]: EQ        1 R0 R1      ; if R0 == R1 then PC := 65
 61 [-]: JMP       65           ; PC := 65
 62 [-]: GETUPVAL  R1 U6        ; R1 := U6
 63 [-]: MOVE      R2 R0        ; R2 := R0
 64 [-]: CALL      R1 2 1       ; R1(R2)
 65 [-]: GETGLOBAL R1 K0        ; R1 := 0x400E7765
 66 [-]: GETGLOBAL R2 K12       ; R2 := mMovie
 67 [-]: CALL      R1 2 2       ; R1 := R1(R2)
 68 [-]: TEST      R1 1         ; if R1 then PC := 76
 69 [-]: JMP       76           ; PC := 76
 70 [-]: GETUPVAL  R1 U1        ; R1 := U1
 71 [-]: TEST      R1 0         ; if not R1 then PC := 76
 72 [-]: JMP       76           ; PC := 76
 73 [-]: GETUPVAL  R1 U7        ; R1 := U7
 74 [-]: TEST      R1 1         ; if R1 then PC := 77
 75 [-]: JMP       77           ; PC := 77
 76 [-]: RETURN    R0 1         ; return 
 77 [-]: GETGLOBAL R1 K0        ; R1 := 0x400E7765
 78 [-]: GETUPVAL  R2 U4        ; R2 := U4
 79 [-]: CALL      R1 2 2       ; R1 := R1(R2)
 80 [-]: TEST      R1 0         ; if not R1 then PC := 86
 81 [-]: JMP       86           ; PC := 86
 82 [-]: GETGLOBAL R1 K16       ; R1 := gRegion
 83 [-]: SELF      R1 R1 K17    ; R2 := R1; R1 := R1["0x3E2F6BF"]
 84 [-]: CALL      R1 2 2       ; R1 := R1(R2)
 85 [-]: MOVE      R1 R4        ; R1 := R4
 86 [-]: GETGLOBAL R1 K0        ; R1 := 0x400E7765
 87 [-]: GETUPVAL  R2 U4        ; R2 := U4
 88 [-]: CALL      R1 2 2       ; R1 := R1(R2)
 89 [-]: TEST      R1 1         ; if R1 then PC := 98
 90 [-]: JMP       98           ; PC := 98
 91 [-]: GETUPVAL  R1 U4        ; R1 := U4
 92 [-]: SELF      R1 R1 K18    ; R2 := R1; R1 := R1["0x5A115A02"]
 93 [-]: CALL      R1 2 2       ; R1 := R1(R2)
 94 [-]: TEST      R1 0         ; if not R1 then PC := 98
 95 [-]: JMP       98           ; PC := 98
 96 [-]: GETUPVAL  R1 U8        ; R1 := U8
 97 [-]: CALL      R1 1 1       ; R1()
 98 [-]: GETGLOBAL R1 K0        ; R1 := 0x400E7765
 99 [-]: GETUPVAL  R2 U9        ; R2 := U9
100 [-]: CALL      R1 2 2       ; R1 := R1(R2)
101 [-]: TEST      R1 0         ; if not R1 then PC := 112
102 [-]: JMP       112          ; PC := 112
103 [-]: GETGLOBAL R1 K0        ; R1 := 0x400E7765
104 [-]: GETUPVAL  R2 U4        ; R2 := U4
105 [-]: CALL      R1 2 2       ; R1 := R1(R2)
106 [-]: TEST      R1 1         ; if R1 then PC := 112
107 [-]: JMP       112          ; PC := 112
108 [-]: GETUPVAL  R1 U4        ; R1 := U4
109 [-]: SELF      R1 R1 K19    ; R2 := R1; R1 := R1["0x8DB5D01F"]
110 [-]: CALL      R1 2 2       ; R1 := R1(R2)
111 [-]: MOVE      R1 R9        ; R1 := R9
112 [-]: GETGLOBAL R1 K0        ; R1 := 0x400E7765
113 [-]: GETUPVAL  R2 U10       ; R2 := U10
114 [-]: CALL      R1 2 2       ; R1 := R1(R2)
115 [-]: TEST      R1 0         ; if not R1 then PC := 128
116 [-]: JMP       128          ; PC := 128
117 [-]: GETGLOBAL R1 K0        ; R1 := 0x400E7765
118 [-]: GETUPVAL  R2 U9        ; R2 := U9
119 [-]: CALL      R1 2 2       ; R1 := R1(R2)
120 [-]: TEST      R1 1         ; if R1 then PC := 128
121 [-]: JMP       128          ; PC := 128
122 [-]: GETUPVAL  R1 U9        ; R1 := U9
123 [-]: SELF      R1 R1 K20    ; R2 := R1; R1 := R1["0x63D63C30"]
124 [-]: GETGLOBAL R3 K21       ; R3 := Engine
125 [-]: GETTABLE  R3 R3 K22    ; R3 := R3["SLOT_3"]
126 [-]: CALL      R1 3 2       ; R1 := R1(R2,R3)
127 [-]: MOVE      R1 R10       ; R1 := R10
128 [-]: GETGLOBAL R1 K0        ; R1 := 0x400E7765
129 [-]: GETUPVAL  R2 U11       ; R2 := U11
130 [-]: CALL      R1 2 2       ; R1 := R1(R2)
131 [-]: TEST      R1 0         ; if not R1 then PC := 142
132 [-]: JMP       142          ; PC := 142
133 [-]: GETGLOBAL R1 K0        ; R1 := 0x400E7765
134 [-]: GETUPVAL  R2 U4        ; R2 := U4
135 [-]: CALL      R1 2 2       ; R1 := R1(R2)
136 [-]: TEST      R1 1         ; if R1 then PC := 142
137 [-]: JMP       142          ; PC := 142
138 [-]: GETUPVAL  R1 U4        ; R1 := U4
139 [-]: SELF      R1 R1 K23    ; R2 := R1; R1 := R1["0x5AF30A19"]
140 [-]: CALL      R1 2 2       ; R1 := R1(R2)
141 [-]: MOVE      R1 R11       ; R1 := R11
142 [-]: GETGLOBAL R1 K0        ; R1 := 0x400E7765
143 [-]: GETUPVAL  R2 U12       ; R2 := U12
144 [-]: CALL      R1 2 2       ; R1 := R1(R2)
145 [-]: TEST      R1 0         ; if not R1 then PC := 156
146 [-]: JMP       156          ; PC := 156
147 [-]: GETGLOBAL R1 K0        ; R1 := 0x400E7765
148 [-]: GETUPVAL  R2 U4        ; R2 := U4
149 [-]: CALL      R1 2 2       ; R1 := R1(R2)
150 [-]: TEST      R1 1         ; if R1 then PC := 156
151 [-]: JMP       156          ; PC := 156
152 [-]: GETUPVAL  R1 U4        ; R1 := U4
153 [-]: SELF      R1 R1 K24    ; R2 := R1; R1 := R1["0x53F87356"]
154 [-]: CALL      R1 2 2       ; R1 := R1(R2)
155 [-]: MOVE      R1 R12       ; R1 := R12
156 [-]: GETGLOBAL R1 K0        ; R1 := 0x400E7765
157 [-]: GETUPVAL  R2 U4        ; R2 := U4
158 [-]: CALL      R1 2 2       ; R1 := R1(R2)
159 [-]: TEST      R1 1         ; if R1 then PC := 177
160 [-]: JMP       177          ; PC := 177
161 [-]: GETGLOBAL R1 K0        ; R1 := 0x400E7765
162 [-]: GETUPVAL  R2 U10       ; R2 := U10
163 [-]: CALL      R1 2 2       ; R1 := R1(R2)
164 [-]: TEST      R1 1         ; if R1 then PC := 177
165 [-]: JMP       177          ; PC := 177
166 [-]: GETGLOBAL R1 K0        ; R1 := 0x400E7765
167 [-]: GETUPVAL  R2 U11       ; R2 := U11
168 [-]: CALL      R1 2 2       ; R1 := R1(R2)
169 [-]: TEST      R1 1         ; if R1 then PC := 177
170 [-]: JMP       177          ; PC := 177
171 [-]: GETUPVAL  R1 U10       ; R1 := U10
172 [-]: SELF      R1 R1 K25    ; R2 := R1; R1 := R1["0x8B598ED4"]
173 [-]: GETGLOBAL R3 K26       ; R3 := multiToolWeaponType
174 [-]: CALL      R1 3 2       ; R1 := R1(R2,R3)
175 [-]: TEST      R1 1         ; if R1 then PC := 182
176 [-]: JMP       182          ; PC := 182
177 [-]: GETGLOBAL R1 K12       ; R1 := mMovie
178 [-]: SELF      R1 R1 K27    ; R2 := R1; R1 := R1["0x625791A8"]
179 [-]: MOVE      R3 R0        ; R3 := R0
180 [-]: CALL      R1 3 1       ; R1(R2,R3)
181 [-]: RETURN    R0 1         ; return 
182 [-]: GETGLOBAL R1 K3        ; R1 := _T
183 [-]: GETTABLE  R1 R1 K28    ; R1 := R1["TopMenuOpen"]
184 [-]: TEST      R1 1         ; if R1 then PC := 195
185 [-]: JMP       195          ; PC := 195
186 [-]: GETGLOBAL R1 K3        ; R1 := _T
187 [-]: GETTABLE  R1 R1 K29    ; R1 := R1["freeCamActive"]
188 [-]: TEST      R1 1         ; if R1 then PC := 195
189 [-]: JMP       195          ; PC := 195
190 [-]: GETGLOBAL R1 K16       ; R1 := gRegion
191 [-]: SELF      R1 R1 K30    ; R2 := R1; R1 := R1["0x7B2F8B2F"]
192 [-]: CALL      R1 2 2       ; R1 := R1(R2)
193 [-]: MOVE      R1 R1        ; R1 := R1
194 [-]: JMP       197          ; PC := 197
195 [-]: MOVE      R1 R0        ; R1 := R0
196 [-]: MOVE      R1 R1        ; R1 := R1
197 [-]: GETUPVAL  R2 U13       ; R2 := U13
198 [-]: EQ        1 R2 R1      ; if R2 == R1 then PC := 205
199 [-]: JMP       205          ; PC := 205
200 [-]: MOVE      R1 R13       ; R1 := R13
201 [-]: GETGLOBAL R2 K12       ; R2 := mMovie
202 [-]: SELF      R2 R2 K27    ; R3 := R2; R2 := R2["0x625791A8"]
203 [-]: GETUPVAL  R4 U13       ; R4 := U13
204 [-]: CALL      R2 3 1       ; R2(R3,R4)
205 [-]: GETGLOBAL R2 K0        ; R2 := 0x400E7765
206 [-]: GETUPVAL  R3 U14       ; R3 := U14
207 [-]: CALL      R2 2 2       ; R2 := R2(R3)
208 [-]: TEST      R2 1         ; if R2 then PC := 223
209 [-]: JMP       223          ; PC := 223
210 [-]: GETGLOBAL R2 K0        ; R2 := 0x400E7765
211 [-]: GETUPVAL  R3 U14       ; R3 := U14
212 [-]: GETTABLE  R3 R3 K31    ; R3 := R3["mInstance"]
213 [-]: CALL      R2 2 2       ; R2 := R2(R3)
214 [-]: TEST      R2 0         ; if not R2 then PC := 219
215 [-]: JMP       219          ; PC := 219
216 [-]: LOADNIL   R2 R2        ; R2 := nil
217 [-]: MOVE      R2 R14       ; R2 := R14
218 [-]: JMP       223          ; PC := 223
219 [-]: GETUPVAL  R2 U14       ; R2 := U14
220 [-]: SELF      R2 R2 K10    ; R3 := R2; R2 := R2["0x8C7099E9"]
221 [-]: LOADK     R4 K32       ; R4 := 0
222 [-]: CALL      R2 3 1       ; R2(R3,R4)
223 [-]: GETUPVAL  R2 U12       ; R2 := U12
224 [-]: GETUPVAL  R3 U15       ; R3 := U15
225 [-]: TEST      R3 0         ; if not R3 then PC := 234
226 [-]: JMP       234          ; PC := 234
227 [-]: GETGLOBAL R3 K21       ; R3 := Engine
228 [-]: GETTABLE  R3 R3 K33    ; R3 := R3["0x9490FE70"]
229 [-]: CALL      R3 1 2       ; R3 := R3()
230 [-]: TEST      R3 1         ; if R3 then PC := 234
231 [-]: JMP       234          ; PC := 234
232 [-]: SELF      R3 R2 K34    ; R4 := R2; R3 := R2["0x25C786F4"]
233 [-]: CALL      R3 2 2       ; R3 := R3(R4)
234 [-]: GETUPVAL  R4 U16       ; R4 := U16
235 [-]: EQ        1 R3 R4      ; if R3 == R4 then PC := 267
236 [-]: JMP       267          ; PC := 267
237 [-]: TEST      R3 0         ; if not R3 then PC := 254
238 [-]: JMP       254          ; PC := 254
239 [-]: SELF      R4 R2 K35    ; R5 := R2; R4 := R2["0xC84CB5A6"]
240 [-]: GETUPVAL  R6 U17       ; R6 := U17
241 [-]: GETGLOBAL R7 K36       ; R7 := controllerSensitivityMultiplier
242 [-]: CALL      R4 4 1       ; R4(R5,R6,R7)
243 [-]: SELF      R4 R2 K37    ; R5 := R2; R4 := R2["0x4D82027F"]
244 [-]: CALL      R4 2 2       ; R4 := R4(R5)
245 [-]: MOVE      R4 R18       ; R4 := R18
246 [-]: SELF      R4 R2 K38    ; R5 := R2; R4 := R2["0x4A544194"]
247 [-]: SELF      R6 R2 K39    ; R7 := R2; R6 := R2["0x174AA97"]
248 [-]: CALL      R6 2 0       ; R6,... := R6(R7)
249 [-]: CALL      R4 0 1       ; R4(R5,...)
250 [-]: SELF      R4 R2 K40    ; R5 := R2; R4 := R2["0x6CF615C8"]
251 [-]: MOVE      R6 R0        ; R6 := R0
252 [-]: CALL      R4 3 1       ; R4(R5,R6)
253 [-]: JMP       266          ; PC := 266
254 [-]: SELF      R4 R2 K41    ; R5 := R2; R4 := R2["0x30B2C2A1"]
255 [-]: GETUPVAL  R6 U17       ; R6 := U17
256 [-]: CALL      R4 3 1       ; R4(R5,R6)
257 [-]: SELF      R4 R2 K40    ; R5 := R2; R4 := R2["0x6CF615C8"]
258 [-]: MOVE      R6 R1        ; R6 := R1
259 [-]: CALL      R4 3 1       ; R4(R5,R6)
260 [-]: GETUPVAL  R4 U18       ; R4 := U18
261 [-]: TEST      R4 0         ; if not R4 then PC := 266
262 [-]: JMP       266          ; PC := 266
263 [-]: SELF      R4 R2 K38    ; R5 := R2; R4 := R2["0x4A544194"]
264 [-]: GETUPVAL  R6 U18       ; R6 := U18
265 [-]: CALL      R4 3 1       ; R4(R5,R6)
266 [-]: MOVE      R3 R16       ; R3 := R16
267 [-]: GETUPVAL  R4 U19       ; R4 := U19
268 [-]: GETGLOBAL R5 K3        ; R5 := _T
269 [-]: GETTABLE  R5 R5 K42    ; R5 := R5["MultiTool"]
270 [-]: GETTABLE  R5 R5 K43    ; R5 := R5["CurrentTargetRepairInfo"]
271 [-]: MOVE      R5 R19       ; R5 := R19
272 [-]: GETUPVAL  R5 U19       ; R5 := U19
273 [-]: EQ        1 R5 R4      ; if R5 == R4 then PC := 278
274 [-]: JMP       278          ; PC := 278
275 [-]: GETUPVAL  R5 U20       ; R5 := U20
276 [-]: GETUPVAL  R6 U19       ; R6 := U19
277 [-]: CALL      R5 2 1       ; R5(R6)
278 [-]: GETUPVAL  R5 U21       ; R5 := U21
279 [-]: GETUPVAL  R6 U10       ; R6 := U10
280 [-]: SELF      R6 R6 K44    ; R7 := R6; R6 := R6["0xCEF5AD37"]
281 [-]: CALL      R6 2 2       ; R6 := R6(R7)
282 [-]: MOVE      R6 R21       ; R6 := R21
283 [-]: GETUPVAL  R6 U21       ; R6 := U21
284 [-]: EQ        1 R6 R5      ; if R6 == R5 then PC := 289
285 [-]: JMP       289          ; PC := 289
286 [-]: GETUPVAL  R6 U22       ; R6 := U22
287 [-]: GETUPVAL  R7 U21       ; R7 := U21
288 [-]: CALL      R6 2 1       ; R6(R7)
289 [-]: GETUPVAL  R6 U4        ; R6 := U4
290 [-]: SELF      R6 R6 K45    ; R7 := R6; R6 := R6["0xF3340665"]
291 [-]: GETGLOBAL R8 K21       ; R8 := Engine
292 [-]: GETTABLE  R8 R8 K46    ; R8 := R8["PM_AIM"]
293 [-]: CALL      R6 3 2       ; R6 := R6(R7,R8)
294 [-]: MOVE      R6 R23       ; R6 := R23
295 [-]: GETGLOBAL R6 K3        ; R6 := _T
296 [-]: GETTABLE  R6 R6 K42    ; R6 := R6["MultiTool"]
297 [-]: GETTABLE  R6 R6 K47    ; R6 := R6["Revolite"]
298 [-]: MOVE      R6 R24       ; R6 := R24
299 [-]: GETUPVAL  R6 U25       ; R6 := U25
300 [-]: TEST      R6 1         ; if R6 then PC := 309
301 [-]: JMP       309          ; PC := 309
302 [-]: MOVE      R6 R1        ; R6 := R1
303 [-]: MOVE      R6 R25       ; R6 := R25
304 [-]: GETUPVAL  R6 U26       ; R6 := U26
305 [-]: SELF      R6 R6 K48    ; R7 := R6; R6 := R6["0x5A7A6B1"]
306 [-]: GETUPVAL  R8 U24       ; R8 := U24
307 [-]: CALL      R6 3 1       ; R6(R7,R8)
308 [-]: JMP       313          ; PC := 313
309 [-]: GETUPVAL  R6 U26       ; R6 := U26
310 [-]: SELF      R6 R6 K49    ; R7 := R6; R6 := R6["0xDB349344"]
311 [-]: GETUPVAL  R8 U24       ; R8 := U24
312 [-]: CALL      R6 3 1       ; R6(R7,R8)
313 [-]: GETUPVAL  R6 U26       ; R6 := U26
314 [-]: SELF      R6 R6 K10    ; R7 := R6; R6 := R6["0x8C7099E9"]
315 [-]: GETGLOBAL R8 K11       ; R8 := 0x4CDEF9FF
316 [-]: CALL      R8 1 0       ; R8,... := R8()
317 [-]: CALL      R6 0 1       ; R6(R7,...)
318 [-]: GETGLOBAL R6 K50       ; R6 := 0x9FAED6BC
319 [-]: GETUPVAL  R7 U27       ; R7 := U27
320 [-]: GETTABLE  R7 R7 K51    ; R7 := R7["0xB57E56DF"]
321 [-]: GETUPVAL  R8 U26       ; R8 := U26
322 [-]: SELF      R8 R8 K52    ; R9 := R8; R8 := R8["0xC4E503B0"]
323 [-]: CALL      R8 2 0       ; R8,... := R8(R9)
324 [-]: CALL      R7 0 0       ; R7,... := R7(R8,...)
325 [-]: CALL      R6 0 2       ; R6 := R6(R7,...)
326 [-]: LOADK     R7 K53       ; R7 := 1
327 [-]: LOADK     R8 K54       ; R8 := 3
328 [-]: LOADK     R9 K53       ; R9 := 1
329 [-]: FORPREP   R7 374       ; R7 -= R9; PC := 374
330 [-]: LOADK     R11 K55      ; R11 := "0"
331 [-]: LOADK     R12 K56      ; R12 := 30
332 [-]: GETGLOBAL R13 K57      ; R13 := string
333 [-]: GETTABLE  R13 R13 K58  ; R13 := R13["0xC6772A8A"]
334 [-]: MOVE      R14 R6       ; R14 := R6
335 [-]: CALL      R13 2 2      ; R13 := R13(R14)
336 [-]: LT        0 K32 R13    ; if 0 >= R13 then PC := 356
337 [-]: JMP       356          ; PC := 356
338 [-]: GETGLOBAL R13 K57      ; R13 := string
339 [-]: GETTABLE  R13 R13 K59  ; R13 := R13["0x7B782033"]
340 [-]: MOVE      R14 R6       ; R14 := R6
341 [-]: LOADK     R15 K60      ; R15 := -1
342 [-]: CALL      R13 3 2      ; R13 := R13(R14,R15)
343 [-]: MOVE      R11 R13      ; R11 := R13
344 [-]: GETGLOBAL R13 K57      ; R13 := string
345 [-]: GETTABLE  R13 R13 K59  ; R13 := R13["0x7B782033"]
346 [-]: MOVE      R14 R6       ; R14 := R6
347 [-]: LOADK     R15 K53      ; R15 := 1
348 [-]: GETGLOBAL R16 K57      ; R16 := string
349 [-]: GETTABLE  R16 R16 K58  ; R16 := R16["0xC6772A8A"]
350 [-]: MOVE      R17 R6       ; R17 := R6
351 [-]: CALL      R16 2 2      ; R16 := R16(R17)
352 [-]: SUB       R16 R16 K53  ; R16 := R16 - 1
353 [-]: CALL      R13 4 2      ; R13 := R13(R14,R15,R16)
354 [-]: MOVE      R6 R13       ; R6 := R13
355 [-]: LOADK     R12 K61      ; R12 := 100
356 [-]: GETGLOBAL R13 K12      ; R13 := mMovie
357 [-]: SELF      R13 R13 K62  ; R14 := R13; R13 := R13["0x880196A7"]
358 [-]: LOADK     R15 K63      ; R15 := "Ammo"
359 [-]: LOADK     R16 K64      ; R16 := "Digit"
360 [-]: MOVE      R17 R10      ; R17 := R10
361 [-]: CONCAT    R16 R16 R17  ; R16 := R16 .. R17
362 [-]: LOADK     R17 K65      ; R17 := "text"
363 [-]: MOVE      R18 R11      ; R18 := R11
364 [-]: CALL      R13 6 1      ; R13(R14,R15,R16,R17,R18)
365 [-]: GETGLOBAL R13 K12      ; R13 := mMovie
366 [-]: SELF      R13 R13 K62  ; R14 := R13; R13 := R13["0x880196A7"]
367 [-]: LOADK     R15 K63      ; R15 := "Ammo"
368 [-]: LOADK     R16 K64      ; R16 := "Digit"
369 [-]: MOVE      R17 R10      ; R17 := R10
370 [-]: CONCAT    R16 R16 R17  ; R16 := R16 .. R17
371 [-]: LOADK     R17 K66      ; R17 := "_alpha"
372 [-]: MOVE      R18 R12      ; R18 := R12
373 [-]: CALL      R13 6 1      ; R13(R14,R15,R16,R17,R18)
374 [-]: FORLOOP   R7 330       ; R7 += R9; if R7 <= R8 then begin PC := 330; R10 := R7 end
375 [-]: GETGLOBAL R13 K3       ; R13 := _T
376 [-]: GETTABLE  R13 R13 K42  ; R13 := R13["MultiTool"]
377 [-]: GETTABLE  R13 R13 K67  ; R13 := R13["HasEnoughRevolite"]
378 [-]: GETGLOBAL R14 K0       ; R14 := 0x400E7765
379 [-]: GETUPVAL  R15 U19      ; R15 := U19
380 [-]: CALL      R14 2 2      ; R14 := R14(R15)
381 [-]: TEST      R14 1        ; if R14 then PC := 404
382 [-]: JMP       404          ; PC := 404
383 [-]: TEST      R13 1        ; if R13 then PC := 404
384 [-]: JMP       404          ; PC := 404
385 [-]: GETUPVAL  R14 U28      ; R14 := U28
386 [-]: CALL      R14 1 1      ; R14()
387 [-]: GETGLOBAL R14 K12      ; R14 := mMovie
388 [-]: SELF      R14 R14 K68  ; R15 := R14; R14 := R14["0x1C19D966"]
389 [-]: LOADK     R16 K69      ; R16 := "Ammo.Warning"
390 [-]: LOADK     R17 K66      ; R17 := "_alpha"
391 [-]: GETGLOBAL R18 K70      ; R18 := math
392 [-]: GETTABLE  R18 R18 K71  ; R18 := R18["0xF93F7CC8"]
393 [-]: GETGLOBAL R19 K70      ; R19 := math
394 [-]: GETTABLE  R19 R19 K72  ; R19 := R19["0xBB3F1476"]
395 [-]: GETGLOBAL R20 K73      ; R20 := 0x58E5C2DB
396 [-]: CALL      R20 1 2      ; R20 := R20()
397 [-]: MUL       R20 R20 K74  ; R20 := R20 * 5
398 [-]: CALL      R19 2 0      ; R19,... := R19(R20)
399 [-]: CALL      R18 0 2      ; R18 := R18(R19,...)
400 [-]: MUL       R18 R18 K75  ; R18 := R18 * 70
401 [-]: ADD       R18 K56 R18  ; R18 := 30 + R18
402 [-]: CALL      R14 5 1      ; R14(R15,R16,R17,R18)
403 [-]: JMP       410          ; PC := 410
404 [-]: GETGLOBAL R14 K12      ; R14 := mMovie
405 [-]: SELF      R14 R14 K68  ; R15 := R14; R14 := R14["0x1C19D966"]
406 [-]: LOADK     R16 K69      ; R16 := "Ammo.Warning"
407 [-]: LOADK     R17 K66      ; R17 := "_alpha"
408 [-]: LOADK     R18 K32      ; R18 := 0
409 [-]: CALL      R14 5 1      ; R14(R15,R16,R17,R18)
410 [-]: GETUPVAL  R14 U29      ; R14 := U29
411 [-]: GETUPVAL  R15 U19      ; R15 := U19
412 [-]: MOVE      R16 R13      ; R16 := R13
413 [-]: CALL      R14 3 1      ; R14(R15,R16)
414 [-]: GETUPVAL  R14 U30      ; R14 := U30
415 [-]: CALL      R14 1 1      ; R14()
416 [-]: RETURN    R0 1         ; return 


; Function #25:
;
; Name:            
; Defined at line: 532
; #Upvalues:       8
; #Parameters:     0
; Is_vararg:       0
; Max Stack Size:  4

  1 [-]: GETUPVAL  R0 U0        ; R0 := U0
  2 [-]: CALL      R0 1 1       ; R0()
  3 [-]: GETUPVAL  R0 U1        ; R0 := U1
  4 [-]: GETTABLE  R0 R0 K0     ; R0 := R0["0xC3F8AC06"]
  5 [-]: GETGLOBAL R1 K1        ; R1 := gRegion
  6 [-]: SELF      R1 R1 K2     ; R2 := R1; R1 := R1["0x3E2F6BF"]
  7 [-]: CALL      R1 2 2       ; R1 := R1(R2)
  8 [-]: LOADK     R2 K3        ; R2 := 0
  9 [-]: CALL      R0 3 1       ; R0(R1,R2)
 10 [-]: GETGLOBAL R0 K4        ; R0 := 0x400E7765
 11 [-]: GETUPVAL  R1 U2        ; R1 := U2
 12 [-]: CALL      R0 2 2       ; R0 := R0(R1)
 13 [-]: TEST      R0 1         ; if R0 then PC := 23
 14 [-]: JMP       23           ; PC := 23
 15 [-]: GETGLOBAL R0 K5        ; R0 := 0x93B1256B
 16 [-]: LOADK     R1 K6        ; R1 := "ScopeDebug: Show from MiningLaserReticle:Shutdown"
 17 [-]: CALL      R0 2 1       ; R0(R1)
 18 [-]: GETUPVAL  R0 U2        ; R0 := U2
 19 [-]: SELF      R0 R0 K7     ; R1 := R0; R0 := R0["0x458F27A9"]
 20 [-]: LOADK     R2 K8        ; R2 := "ShowReticle"
 21 [-]: LOADK     R3 K9        ; R3 := ""
 22 [-]: CALL      R0 4 1       ; R0(R1,R2,R3)
 23 [-]: GETUPVAL  R0 U3        ; R0 := U3
 24 [-]: GETUPVAL  R1 U4        ; R1 := U4
 25 [-]: TEST      R1 0         ; if not R1 then PC := 39
 26 [-]: JMP       39           ; PC := 39
 27 [-]: SELF      R1 R0 K10    ; R2 := R0; R1 := R0["0x30B2C2A1"]
 28 [-]: GETUPVAL  R3 U5        ; R3 := U5
 29 [-]: CALL      R1 3 1       ; R1(R2,R3)
 30 [-]: SELF      R1 R0 K11    ; R2 := R0; R1 := R0["0x6CF615C8"]
 31 [-]: MOVE      R3 R1        ; R3 := R1
 32 [-]: CALL      R1 3 1       ; R1(R2,R3)
 33 [-]: GETUPVAL  R1 U6        ; R1 := U6
 34 [-]: TEST      R1 0         ; if not R1 then PC := 39
 35 [-]: JMP       39           ; PC := 39
 36 [-]: SELF      R1 R0 K12    ; R2 := R0; R1 := R0["0x4A544194"]
 37 [-]: GETUPVAL  R3 U6        ; R3 := U6
 38 [-]: CALL      R1 3 1       ; R1(R2,R3)
 39 [-]: GETUPVAL  R1 U0        ; R1 := U0
 40 [-]: CALL      R1 1 1       ; R1()
 41 [-]: GETUPVAL  R1 U7        ; R1 := U7
 42 [-]: CALL      R1 1 1       ; R1()
 43 [-]: RETURN    R0 1         ; return 


