code size: 132
code size: 27
code size: 3
code size: 6
code size: 14
code size: 33
code size: 17
code size: 17
code size: 14
code size: 14
code size: 41
code size: 26
code size: 1
code size: 15
code size: 5
code size: 6
code size: 37
code size: 13
code size: 51
code size: 26
code size: 26
code size: 35
code size: 8
code size: 127
code size: 64
code size: 77
code size: 41
code size: 1
code size: 117
code size: 86
code size: 118
code size: 65
code size: 11
code size: 47
code size: 230
code size: 12
code size: 61
code size: 88
code size: 1
; This file has been disassembled using luadec 2.0.2 by sztupy (http://winmo.sztupy.hu)
; Command line was: -dis M:\git repos\warframe-lua-disassembled\B.Font.cache_extracted\Lotus\Scripts\LotusObstacleCourseObject.luac 

; Name:            
; Defined at line: 0
; #Upvalues:       0
; #Parameters:     0
; Is_vararg:       2
; Max Stack Size:  31

  1 [-]: GETGLOBAL R0 K0        ; R0 := 0x7C282057
  2 [-]: LOADK     R1 K1        ; R1 := "/Lotus/Music/ObstacleCourse/ObstacleCourseMusic"
  3 [-]: CALL      R0 2 2       ; R0 := R0(R1)
  4 [-]: LOADK     R1 K2        ; R1 := "/Lotus/Language/Dojo/RaceIncreaseSeconds"
  5 [-]: LOADK     R2 K3        ; R2 := "/Lotus/Language/Menu/AlertPopup_Time"
  6 [-]: GETGLOBAL R3 K4        ; R3 := 0x329BDC44
  7 [-]: LOADK     R4 K5        ; R4 := "EE.Interface.Utilities"
  8 [-]: CALL      R3 2 2       ; R3 := R3(R4)
  9 [-]: GETGLOBAL R4 K6        ; R4 := 0xEC274B1A
 10 [-]: LOADK     R5 K7        ; R5 := "ObstacleCourseTimer"
 11 [-]: CALL      R4 2 2       ; R4 := R4(R5)
 12 [-]: GETGLOBAL R5 K6        ; R5 := 0xEC274B1A
 13 [-]: LOADK     R6 K8        ; R6 := "UnlitAtten"
 14 [-]: CALL      R5 2 2       ; R5 := R5(R6)
 15 [-]: CLOSURE   R6 0         ; R6 := closure(Function #1)
 16 [-]: CLOSURE   R7 1         ; R7 := closure(Function #2)
 17 [-]: CLOSURE   R8 2         ; R8 := closure(Function #3)
 18 [-]: MOVE      R0 R7        ; R0 := R7
 19 [-]: CLOSURE   R9 3         ; R9 := closure(Function #4)
 20 [-]: CLOSURE   R10 4        ; R10 := closure(Function #5)
 21 [-]: CLOSURE   R11 5        ; R11 := closure(Function #6)
 22 [-]: CLOSURE   R12 6        ; R12 := closure(Function #7)
 23 [-]: CLOSURE   R13 7        ; R13 := closure(Function #8)
 24 [-]: MOVE      R0 R11       ; R0 := R11
 25 [-]: CLOSURE   R14 8        ; R14 := closure(Function #9)
 26 [-]: MOVE      R0 R12       ; R0 := R12
 27 [-]: CLOSURE   R15 9        ; R15 := closure(Function #10)
 28 [-]: MOVE      R0 R0        ; R0 := R0
 29 [-]: CLOSURE   R16 10       ; R16 := closure(Function #11)
 30 [-]: MOVE      R0 R0        ; R0 := R0
 31 [-]: CLOSURE   R17 11       ; R17 := closure(Function #12)
 32 [-]: SETGLOBAL R17 K9       ; Initialize := R17
 33 [-]: SETGLOBAL R17 K10      ; 0x62648036 := R17
 34 [-]: CLOSURE   R17 12       ; R17 := closure(Function #13)
 35 [-]: SETGLOBAL R17 K11      ; SetActionText := R17
 36 [-]: SETGLOBAL R17 K12      ; 0x20F4CA9F := R17
 37 [-]: CLOSURE   R17 13       ; R17 := closure(Function #14)
 38 [-]: MOVE      R0 R7        ; R0 := R7
 39 [-]: CLOSURE   R18 14       ; R18 := closure(Function #15)
 40 [-]: MOVE      R0 R4        ; R0 := R4
 41 [-]: CLOSURE   R19 15       ; R19 := closure(Function #16)
 42 [-]: SETGLOBAL R19 K13      ; OnLocalPlayerSpawned := R19
 43 [-]: SETGLOBAL R19 K14      ; 0x884E69B3 := R19
 44 [-]: CLOSURE   R19 16       ; R19 := closure(Function #17)
 45 [-]: MOVE      R0 R4        ; R0 := R4
 46 [-]: SETGLOBAL R19 K15      ; OnPlayersChanged := R19
 47 [-]: SETGLOBAL R19 K16      ; 0x1AC2CE51 := R19
 48 [-]: CLOSURE   R19 17       ; R19 := closure(Function #18)
 49 [-]: CLOSURE   R20 18       ; R20 := closure(Function #19)
 50 [-]: CLOSURE   R21 19       ; R21 := closure(Function #20)
 51 [-]: CLOSURE   R22 20       ; R22 := closure(Function #21)
 52 [-]: CLOSURE   R23 21       ; R23 := closure(Function #22)
 53 [-]: MOVE      R0 R16       ; R0 := R16
 54 [-]: CLOSURE   R24 22       ; R24 := closure(Function #23)
 55 [-]: MOVE      R0 R16       ; R0 := R16
 56 [-]: MOVE      R0 R7        ; R0 := R7
 57 [-]: MOVE      R0 R2        ; R0 := R2
 58 [-]: MOVE      R0 R14       ; R0 := R14
 59 [-]: MOVE      R0 R21       ; R0 := R21
 60 [-]: MOVE      R0 R22       ; R0 := R22
 61 [-]: MOVE      R0 R18       ; R0 := R18
 62 [-]: MOVE      R0 R10       ; R0 := R10
 63 [-]: CLOSURE   R25 23       ; R25 := closure(Function #24)
 64 [-]: MOVE      R0 R16       ; R0 := R16
 65 [-]: MOVE      R0 R7        ; R0 := R7
 66 [-]: MOVE      R0 R14       ; R0 := R14
 67 [-]: MOVE      R0 R21       ; R0 := R21
 68 [-]: MOVE      R0 R18       ; R0 := R18
 69 [-]: MOVE      R0 R10       ; R0 := R10
 70 [-]: CLOSURE   R26 24       ; R26 := closure(Function #25)
 71 [-]: CLOSURE   R27 25       ; R27 := closure(Function #26)
 72 [-]: MOVE      R0 R8        ; R0 := R8
 73 [-]: MOVE      R0 R7        ; R0 := R7
 74 [-]: MOVE      R0 R26       ; R0 := R26
 75 [-]: MOVE      R0 R24       ; R0 := R24
 76 [-]: MOVE      R0 R23       ; R0 := R23
 77 [-]: MOVE      R0 R25       ; R0 := R25
 78 [-]: MOVE      R0 R19       ; R0 := R19
 79 [-]: SETGLOBAL R27 K17      ; OnStateUpdated := R27
 80 [-]: SETGLOBAL R27 K18      ; 0x3416E1D4 := R27
 81 [-]: CLOSURE   R27 26       ; R27 := closure(Function #27)
 82 [-]: SETGLOBAL R27 K19      ; Update := R27
 83 [-]: SETGLOBAL R27 K20      ; 0x8C7099E9 := R27
 84 [-]: CLOSURE   R27 27       ; R27 := closure(Function #28)
 85 [-]: CLOSURE   R28 28       ; R28 := closure(Function #29)
 86 [-]: MOVE      R0 R8        ; R0 := R8
 87 [-]: MOVE      R0 R4        ; R0 := R4
 88 [-]: MOVE      R0 R1        ; R0 := R1
 89 [-]: SETGLOBAL R28 K21      ; OnDestroyed := R28
 90 [-]: SETGLOBAL R28 K22      ; 0x49A9EC8E := R28
 91 [-]: CLOSURE   R28 29       ; R28 := closure(Function #30)
 92 [-]: MOVE      R0 R5        ; R0 := R5
 93 [-]: MOVE      R0 R20       ; R0 := R20
 94 [-]: MOVE      R0 R13       ; R0 := R13
 95 [-]: CLOSURE   R29 30       ; R29 := closure(Function #31)
 96 [-]: MOVE      R0 R8        ; R0 := R8
 97 [-]: MOVE      R0 R7        ; R0 := R7
 98 [-]: MOVE      R0 R15       ; R0 := R15
 99 [-]: MOVE      R0 R28       ; R0 := R28
100 [-]: MOVE      R0 R4        ; R0 := R4
101 [-]: SETGLOBAL R29 K23      ; StartObstacleCourse := R29
102 [-]: SETGLOBAL R29 K24      ; 0x187EF3AC := R29
103 [-]: CLOSURE   R29 31       ; R29 := closure(Function #32)
104 [-]: CLOSURE   R30 32       ; R30 := closure(Function #33)
105 [-]: MOVE      R0 R8        ; R0 := R8
106 [-]: MOVE      R0 R27       ; R0 := R27
107 [-]: MOVE      R0 R17       ; R0 := R17
108 [-]: MOVE      R0 R29       ; R0 := R29
109 [-]: SETGLOBAL R30 K25      ; ObstacleGateTriggered := R30
110 [-]: SETGLOBAL R30 K26      ; 0x2A553A91 := R30
111 [-]: CLOSURE   R30 33       ; R30 := closure(Function #34)
112 [-]: MOVE      R0 R3        ; R0 := R3
113 [-]: MOVE      R0 R22       ; R0 := R22
114 [-]: MOVE      R0 R6        ; R0 := R6
115 [-]: SETGLOBAL R30 K27      ; StartInstancing := R30
116 [-]: SETGLOBAL R30 K28      ; 0x75F69C90 := R30
117 [-]: CLOSURE   R30 34       ; R30 := closure(Function #35)
118 [-]: SETGLOBAL R30 K29      ; MainMenuConfirm := R30
119 [-]: SETGLOBAL R30 K30      ; 0xAA561337 := R30
120 [-]: CLOSURE   R30 35       ; R30 := closure(Function #36)
121 [-]: MOVE      R0 R8        ; R0 := R8
122 [-]: MOVE      R0 R7        ; R0 := R7
123 [-]: SETGLOBAL R30 K31      ; ValidateVanishTriggerEntity := R30
124 [-]: SETGLOBAL R30 K32      ; 0x9CDCB982 := R30
125 [-]: CLOSURE   R30 36       ; R30 := closure(Function #37)
126 [-]: MOVE      R0 R5        ; R0 := R5
127 [-]: SETGLOBAL R30 K33      ; HitDissapearingTrigger := R30
128 [-]: SETGLOBAL R30 K34      ; 0xE13573B8 := R30
129 [-]: CLOSURE   R30 37       ; R30 := closure(Function #38)
130 [-]: SETGLOBAL R30 K35      ; SubmitScoreResult := R30
131 [-]: SETGLOBAL R30 K36      ; 0x8CEAB4FB := R30
132 [-]: RETURN    R0 1         ; return 


; Function #1:
;
; Name:            
; Defined at line: 29
; #Upvalues:       0
; #Parameters:     2
; Is_vararg:       0
; Max Stack Size:  7

  1 [-]: SELF      R2 R0 K0     ; R3 := R0; R2 := R0["0x4CC9B24B"]
  2 [-]: CALL      R2 2 2       ; R2 := R2(R3)
  3 [-]: LOADNIL   R3 R3        ; R3 := nil
  4 [-]: GETGLOBAL R4 K1        ; R4 := 0x400E7765
  5 [-]: GETGLOBAL R5 K2        ; R5 := _T
  6 [-]: GETTABLE  R5 R5 K3     ; R5 := R5["DojoMgr"]
  7 [-]: GETTABLE  R5 R5 K4     ; R5 := R5["mIdToPlacedDecos"]
  8 [-]: GETTABLE  R5 R5 R1     ; R5 := R5[R1]
  9 [-]: CALL      R4 2 2       ; R4 := R4(R5)
 10 [-]: TEST      R4 1         ; if R4 then PC := 26
 11 [-]: JMP       26           ; PC := 26
 12 [-]: GETGLOBAL R4 K2        ; R4 := _T
 13 [-]: GETTABLE  R4 R4 K3     ; R4 := R4["DojoMgr"]
 14 [-]: GETTABLE  R4 R4 K5     ; R4 := R4["mDojo"]
 15 [-]: SELF      R4 R4 K6     ; R5 := R4; R4 := R4["0x20612AEC"]
 16 [-]: MOVE      R6 R1        ; R6 := R1
 17 [-]: CALL      R4 3 2       ; R4 := R4(R5,R6)
 18 [-]: SELF      R4 R4 K7     ; R5 := R4; R4 := R4["0xE5170280"]
 19 [-]: MOVE      R6 R2        ; R6 := R2
 20 [-]: CALL      R4 3 2       ; R4 := R4(R5,R6)
 21 [-]: SELF      R5 R4 K8     ; R6 := R4; R5 := R4["0x315E860F"]
 22 [-]: CALL      R5 2 2       ; R5 := R5(R6)
 23 [-]: TEST      R5 0         ; if not R5 then PC := 26
 24 [-]: JMP       26           ; PC := 26
 25 [-]: MOVE      R3 R4        ; R3 := R4
 26 [-]: RETURN    R3 2         ; return R3
 27 [-]: RETURN    R0 1         ; return 


; Function #2:
;
; Name:            
; Defined at line: 43
; #Upvalues:       0
; #Parameters:     0
; Is_vararg:       0
; Max Stack Size:  2

  1 [-]: GETGLOBAL R0 K0        ; R0 := gGameRules
  2 [-]: RETURN    R0 2         ; return R0
  3 [-]: RETURN    R0 1         ; return 


; Function #3:
;
; Name:            
; Defined at line: 47
; #Upvalues:       1
; #Parameters:     0
; Is_vararg:       0
; Max Stack Size:  2

  1 [-]: GETUPVAL  R0 U0        ; R0 := U0
  2 [-]: CALL      R0 1 2       ; R0 := R0()
  3 [-]: SELF      R0 R0 K0     ; R1 := R0; R0 := R0["0xD01F29AC"]
  4 [-]: TAILCALL  R0 2 0       ; R0,... := R0(R1)
  5 [-]: RETURN    R0 0         ; return R0,...
  6 [-]: RETURN    R0 1         ; return 


; Function #4:
;
; Name:            
; Defined at line: 51
; #Upvalues:       0
; #Parameters:     2
; Is_vararg:       0
; Max Stack Size:  9

  1 [-]: GETGLOBAL R2 K0        ; R2 := gRegion
  2 [-]: SELF      R2 R2 K1     ; R3 := R2; R2 := R2["0x3E2F6BF"]
  3 [-]: CALL      R2 2 2       ; R2 := R2(R3)
  4 [-]: EQ        0 R0 R2      ; if R0 ~= R2 then PC := 14
  5 [-]: JMP       14           ; PC := 14
  6 [-]: GETGLOBAL R3 K2        ; R3 := _T
  7 [-]: GETTABLE  R3 R3 K3     ; R3 := R3["0xA3639E71"]
  8 [-]: MOVE      R4 R1        ; R4 := R1
  9 [-]: LOADK     R5 K4        ; R5 := 5
 10 [-]: MOVE      R6 R1        ; R6 := R1
 11 [-]: LOADNIL   R7 R7        ; R7 := nil
 12 [-]: MOVE      R8 R0        ; R8 := R0
 13 [-]: CALL      R3 6 1       ; R3(R4,R5,R6,R7,R8)
 14 [-]: RETURN    R0 1         ; return 


; Function #5:
;
; Name:            
; Defined at line: 58
; #Upvalues:       0
; #Parameters:     1
; Is_vararg:       0
; Max Stack Size:  11

  1 [-]: GETGLOBAL R1 K0        ; R1 := gRegion
  2 [-]: SELF      R1 R1 K1     ; R2 := R1; R1 := R1["0xA76F0612"]
  3 [-]: GETGLOBAL R3 K2        ; R3 := 0xEC274B1A
  4 [-]: LOADK     R4 K3        ; R4 := "CustomObstacleCourseSpawn"
  5 [-]: CALL      R3 2 0       ; R3,... := R3(R4)
  6 [-]: CALL      R1 0 2       ; R1 := R1(R2,...)
  7 [-]: GETGLOBAL R2 K4        ; R2 := _T
  8 [-]: GETTABLE  R2 R2 K5     ; R2 := R2["DojoMgr"]
  9 [-]: SELF      R2 R2 K6     ; R3 := R2; R2 := R2["0xBF9A2C88"]
 10 [-]: SELF      R4 R0 K7     ; R5 := R0; R4 := R0["0x72E5DB62"]
 11 [-]: CALL      R4 2 2       ; R4 := R4(R5)
 12 [-]: SELF      R4 R4 K8     ; R5 := R4; R4 := R4["0x61FDC81"]
 13 [-]: CALL      R4 2 0       ; R4,... := R4(R5)
 14 [-]: CALL      R2 0 2       ; R2 := R2(R3,...)
 15 [-]: LOADK     R3 K9        ; R3 := 1
 16 [-]: LEN       R4 R1        ; R4 := # R1
 17 [-]: LOADK     R5 K9        ; R5 := 1
 18 [-]: FORPREP   R3 30        ; R3 -= R5; PC := 30
 19 [-]: GETTABLE  R7 R1 R6     ; R7 := R1[R6]
 20 [-]: GETGLOBAL R8 K4        ; R8 := _T
 21 [-]: GETTABLE  R8 R8 K5     ; R8 := R8["DojoMgr"]
 22 [-]: SELF      R8 R8 K6     ; R9 := R8; R8 := R8["0xBF9A2C88"]
 23 [-]: MOVE      R10 R7       ; R10 := R7
 24 [-]: CALL      R8 3 2       ; R8 := R8(R9,R10)
 25 [-]: GETTABLE  R9 R2 K10    ; R9 := R2["id"]
 26 [-]: GETTABLE  R10 R8 K10   ; R10 := R8["id"]
 27 [-]: EQ        0 R9 R10     ; if R9 ~= R10 then PC := 30
 28 [-]: JMP       30           ; PC := 30
 29 [-]: RETURN    R7 2         ; return R7
 30 [-]: FORLOOP   R3 19        ; R3 += R5; if R3 <= R4 then begin PC := 19; R6 := R3 end
 31 [-]: LOADNIL   R9 R9        ; R9 := nil
 32 [-]: RETURN    R9 2         ; return R9
 33 [-]: RETURN    R0 1         ; return 


; Function #6:
;
; Name:            
; Defined at line: 73
; #Upvalues:       0
; #Parameters:     1
; Is_vararg:       0
; Max Stack Size:  8

  1 [-]: GETGLOBAL R1 K0        ; R1 := 0x400E7765
  2 [-]: GETGLOBAL R2 K1        ; R2 := laserType
  3 [-]: CALL      R1 2 2       ; R1 := R1(R2)
  4 [-]: TEST      R1 1         ; if R1 then PC := 17
  5 [-]: JMP       17           ; PC := 17
  6 [-]: SELF      R1 R0 K2     ; R2 := R0; R1 := R0["0x15D4DAEE"]
  7 [-]: GETGLOBAL R3 K1        ; R3 := laserType
  8 [-]: CALL      R1 3 2       ; R1 := R1(R2,R3)
  9 [-]: LOADK     R2 K3        ; R2 := 1
 10 [-]: LEN       R3 R1        ; R3 := # R1
 11 [-]: LOADK     R4 K3        ; R4 := 1
 12 [-]: FORPREP   R2 16        ; R2 -= R4; PC := 16
 13 [-]: GETTABLE  R6 R1 R5     ; R6 := R1[R5]
 14 [-]: SELF      R6 R6 K4     ; R7 := R6; R6 := R6["0xC5E91BA6"]
 15 [-]: CALL      R6 2 1       ; R6(R7)
 16 [-]: FORLOOP   R2 13        ; R2 += R4; if R2 <= R3 then begin PC := 13; R5 := R2 end
 17 [-]: RETURN    R0 1         ; return 


; Function #7:
;
; Name:            
; Defined at line: 82
; #Upvalues:       0
; #Parameters:     1
; Is_vararg:       0
; Max Stack Size:  8

  1 [-]: GETGLOBAL R1 K0        ; R1 := 0x400E7765
  2 [-]: GETGLOBAL R2 K1        ; R2 := laserType
  3 [-]: CALL      R1 2 2       ; R1 := R1(R2)
  4 [-]: TEST      R1 1         ; if R1 then PC := 17
  5 [-]: JMP       17           ; PC := 17
  6 [-]: SELF      R1 R0 K2     ; R2 := R0; R1 := R0["0x15D4DAEE"]
  7 [-]: GETGLOBAL R3 K1        ; R3 := laserType
  8 [-]: CALL      R1 3 2       ; R1 := R1(R2,R3)
  9 [-]: LOADK     R2 K3        ; R2 := 1
 10 [-]: LEN       R3 R1        ; R3 := # R1
 11 [-]: LOADK     R4 K3        ; R4 := 1
 12 [-]: FORPREP   R2 16        ; R2 -= R4; PC := 16
 13 [-]: GETTABLE  R6 R1 R5     ; R6 := R1[R5]
 14 [-]: SELF      R6 R6 K4     ; R7 := R6; R6 := R6["0x2DB1272F"]
 15 [-]: CALL      R6 2 1       ; R6(R7)
 16 [-]: FORLOOP   R2 13        ; R2 += R4; if R2 <= R3 then begin PC := 13; R5 := R2 end
 17 [-]: RETURN    R0 1         ; return 


; Function #8:
;
; Name:            
; Defined at line: 91
; #Upvalues:       1
; #Parameters:     0
; Is_vararg:       0
; Max Stack Size:  8

  1 [-]: GETGLOBAL R0 K0        ; R0 := gRegion
  2 [-]: SELF      R0 R0 K1     ; R1 := R0; R0 := R0["0x9139A00"]
  3 [-]: GETGLOBAL R2 K2        ; R2 := dojoLaserTrapType
  4 [-]: CALL      R0 3 2       ; R0 := R0(R1,R2)
  5 [-]: LOADK     R1 K3        ; R1 := 1
  6 [-]: LEN       R2 R0        ; R2 := # R0
  7 [-]: LOADK     R3 K3        ; R3 := 1
  8 [-]: FORPREP   R1 13        ; R1 -= R3; PC := 13
  9 [-]: GETTABLE  R5 R0 R4     ; R5 := R0[R4]
 10 [-]: GETUPVAL  R6 U0        ; R6 := U0
 11 [-]: MOVE      R7 R5        ; R7 := R5
 12 [-]: CALL      R6 2 1       ; R6(R7)
 13 [-]: FORLOOP   R1 9         ; R1 += R3; if R1 <= R2 then begin PC := 9; R4 := R1 end
 14 [-]: RETURN    R0 1         ; return 


; Function #9:
;
; Name:            
; Defined at line: 99
; #Upvalues:       1
; #Parameters:     0
; Is_vararg:       0
; Max Stack Size:  8

  1 [-]: GETGLOBAL R0 K0        ; R0 := gRegion
  2 [-]: SELF      R0 R0 K1     ; R1 := R0; R0 := R0["0x9139A00"]
  3 [-]: GETGLOBAL R2 K2        ; R2 := dojoLaserTrapType
  4 [-]: CALL      R0 3 2       ; R0 := R0(R1,R2)
  5 [-]: LOADK     R1 K3        ; R1 := 1
  6 [-]: LEN       R2 R0        ; R2 := # R0
  7 [-]: LOADK     R3 K3        ; R3 := 1
  8 [-]: FORPREP   R1 13        ; R1 -= R3; PC := 13
  9 [-]: GETTABLE  R5 R0 R4     ; R5 := R0[R4]
 10 [-]: GETUPVAL  R6 U0        ; R6 := U0
 11 [-]: MOVE      R7 R5        ; R7 := R5
 12 [-]: CALL      R6 2 1       ; R6(R7)
 13 [-]: FORLOOP   R1 9         ; R1 += R3; if R1 <= R2 then begin PC := 9; R4 := R1 end
 14 [-]: RETURN    R0 1         ; return 


; Function #10:
;
; Name:            
; Defined at line: 107
; #Upvalues:       1
; #Parameters:     0
; Is_vararg:       0
; Max Stack Size:  7

  1 [-]: GETGLOBAL R0 K0        ; R0 := 0x400E7765
  2 [-]: GETUPVAL  R1 U0        ; R1 := U0
  3 [-]: CALL      R0 2 2       ; R0 := R0(R1)
  4 [-]: TEST      R0 1         ; if R0 then PC := 41
  5 [-]: JMP       41           ; PC := 41
  6 [-]: GETGLOBAL R0 K1        ; R0 := gRegion
  7 [-]: SELF      R0 R0 K2     ; R1 := R0; R0 := R0["0x9139A00"]
  8 [-]: GETUPVAL  R2 U0        ; R2 := U0
  9 [-]: CALL      R0 3 2       ; R0 := R0(R1,R2)
 10 [-]: LEN       R1 R0        ; R1 := # R0
 11 [-]: LT        0 K3 R1      ; if 0 >= R1 then PC := 27
 12 [-]: JMP       27           ; PC := 27
 13 [-]: GETTABLE  R1 R0 K4     ; R1 := R0[1]
 14 [-]: GETGLOBAL R2 K0        ; R2 := 0x400E7765
 15 [-]: MOVE      R3 R1        ; R3 := R1
 16 [-]: CALL      R2 2 2       ; R2 := R2(R3)
 17 [-]: TEST      R2 1         ; if R2 then PC := 41
 18 [-]: JMP       41           ; PC := 41
 19 [-]: SELF      R2 R1 K5     ; R3 := R1; R2 := R1["0x8B598ED4"]
 20 [-]: GETUPVAL  R4 U0        ; R4 := U0
 21 [-]: CALL      R2 3 2       ; R2 := R2(R3,R4)
 22 [-]: TEST      R2 0         ; if not R2 then PC := 41
 23 [-]: JMP       41           ; PC := 41
 24 [-]: SELF      R2 R1 K6     ; R3 := R1; R2 := R1["0xC5E91BA6"]
 25 [-]: CALL      R2 2 1       ; R2(R3)
 26 [-]: JMP       41           ; PC := 41
 27 [-]: GETGLOBAL R2 K1        ; R2 := gRegion
 28 [-]: SELF      R2 R2 K7     ; R3 := R2; R2 := R2["0xBDD34CC6"]
 29 [-]: GETUPVAL  R4 U0        ; R4 := U0
 30 [-]: GETGLOBAL R5 K8        ; R5 := ZERO_VECTOR
 31 [-]: GETGLOBAL R6 K9        ; R6 := ZERO_ROTATION
 32 [-]: CALL      R2 5 2       ; R2 := R2(R3,R4,R5,R6)
 33 [-]: MOVE      R0 R2        ; R0 := R2
 34 [-]: GETGLOBAL R2 K0        ; R2 := 0x400E7765
 35 [-]: MOVE      R3 R0        ; R3 := R0
 36 [-]: CALL      R2 2 2       ; R2 := R2(R3)
 37 [-]: TEST      R2 1         ; if R2 then PC := 41
 38 [-]: JMP       41           ; PC := 41
 39 [-]: SELF      R2 R0 K6     ; R3 := R0; R2 := R0["0xC5E91BA6"]
 40 [-]: CALL      R2 2 1       ; R2(R3)
 41 [-]: RETURN    R0 1         ; return 


; Function #11:
;
; Name:            
; Defined at line: 124
; #Upvalues:       1
; #Parameters:     0
; Is_vararg:       0
; Max Stack Size:  8

  1 [-]: GETGLOBAL R0 K0        ; R0 := 0x400E7765
  2 [-]: GETUPVAL  R1 U0        ; R1 := U0
  3 [-]: CALL      R0 2 2       ; R0 := R0(R1)
  4 [-]: TEST      R0 1         ; if R0 then PC := 26
  5 [-]: JMP       26           ; PC := 26
  6 [-]: GETGLOBAL R0 K1        ; R0 := gRegion
  7 [-]: SELF      R0 R0 K2     ; R1 := R0; R0 := R0["0x9139A00"]
  8 [-]: GETUPVAL  R2 U0        ; R2 := U0
  9 [-]: CALL      R0 3 2       ; R0 := R0(R1,R2)
 10 [-]: LEN       R1 R0        ; R1 := # R0
 11 [-]: LT        0 K3 R1      ; if 0 >= R1 then PC := 26
 12 [-]: JMP       26           ; PC := 26
 13 [-]: LOADK     R1 K4        ; R1 := 1
 14 [-]: LEN       R2 R0        ; R2 := # R0
 15 [-]: LOADK     R3 K4        ; R3 := 1
 16 [-]: FORPREP   R1 25        ; R1 -= R3; PC := 25
 17 [-]: GETTABLE  R5 R0 R4     ; R5 := R0[R4]
 18 [-]: GETGLOBAL R6 K0        ; R6 := 0x400E7765
 19 [-]: MOVE      R7 R5        ; R7 := R5
 20 [-]: CALL      R6 2 2       ; R6 := R6(R7)
 21 [-]: TEST      R6 1         ; if R6 then PC := 25
 22 [-]: JMP       25           ; PC := 25
 23 [-]: SELF      R6 R5 K5     ; R7 := R5; R6 := R5["0x2DB1272F"]
 24 [-]: CALL      R6 2 1       ; R6(R7)
 25 [-]: FORLOOP   R1 17        ; R1 += R3; if R1 <= R2 then begin PC := 17; R4 := R1 end
 26 [-]: RETURN    R0 1         ; return 


; Function #12:
;
; Name:            
; Defined at line: 139
; #Upvalues:       0
; #Parameters:     0
; Is_vararg:       0
; Max Stack Size:  2

  1 [-]: RETURN    R0 1         ; return 


; Function #13:
;
; Name:            
; Defined at line: 142
; #Upvalues:       0
; #Parameters:     1
; Is_vararg:       0
; Max Stack Size:  4

  1 [-]: GETGLOBAL R1 K0        ; R1 := 0x400E7765
  2 [-]: GETGLOBAL R2 K1        ; R2 := gGameRules
  3 [-]: CALL      R1 2 2       ; R1 := R1(R2)
  4 [-]: TEST      R1 1         ; if R1 then PC := 15
  5 [-]: JMP       15           ; PC := 15
  6 [-]: GETGLOBAL R1 K1        ; R1 := gGameRules
  7 [-]: SELF      R1 R1 K2     ; R2 := R1; R1 := R1["0x8B598ED4"]
  8 [-]: GETGLOBAL R3 K3        ; R3 := dojoCustomObstacleCourseGameRules
  9 [-]: CALL      R1 3 2       ; R1 := R1(R2,R3)
 10 [-]: TEST      R1 0         ; if not R1 then PC := 15
 11 [-]: JMP       15           ; PC := 15
 12 [-]: SELF      R1 R0 K4     ; R2 := R0; R1 := R0["0x20F4CA9F"]
 13 [-]: LOADK     R3 K5        ; R3 := "/Lotus/Language/Dojo/CustomObstacleCourseLeave"
 14 [-]: CALL      R1 3 1       ; R1(R2,R3)
 15 [-]: RETURN    R0 1         ; return 


; Function #14:
;
; Name:            
; Defined at line: 148
; #Upvalues:       1
; #Parameters:     0
; Is_vararg:       0
; Max Stack Size:  2

  1 [-]: GETUPVAL  R0 U0        ; R0 := U0
  2 [-]: CALL      R0 1 2       ; R0 := R0()
  3 [-]: SELF      R0 R0 K0     ; R1 := R0; R0 := R0["0xB4E66650"]
  4 [-]: CALL      R0 2 1       ; R0(R1)
  5 [-]: RETURN    R0 1         ; return 


; Function #15:
;
; Name:            
; Defined at line: 152
; #Upvalues:       1
; #Parameters:     1
; Is_vararg:       0
; Max Stack Size:  4

  1 [-]: SELF      R1 R0 K0     ; R2 := R0; R1 := R0["0xDE5882DD"]
  2 [-]: CALL      R1 2 2       ; R1 := R1(R2)
  3 [-]: SELF      R1 R1 K1     ; R2 := R1; R1 := R1["0x36A5750D"]
  4 [-]: GETUPVAL  R3 U0        ; R3 := U0
  5 [-]: CALL      R1 3 1       ; R1(R2,R3)
  6 [-]: RETURN    R0 1         ; return 


; Function #16:
;
; Name:            
; Defined at line: 156
; #Upvalues:       0
; #Parameters:     0
; Is_vararg:       0
; Max Stack Size:  8

  1 [-]: GETGLOBAL R0 K0        ; R0 := gRegion
  2 [-]: SELF      R0 R0 K1     ; R1 := R0; R0 := R0["0x3E2F6BF"]
  3 [-]: CALL      R0 2 2       ; R0 := R0(R1)
  4 [-]: GETGLOBAL R1 K2        ; R1 := 0x400E7765
  5 [-]: MOVE      R2 R0        ; R2 := R0
  6 [-]: CALL      R1 2 2       ; R1 := R1(R2)
  7 [-]: TEST      R1 1         ; if R1 then PC := 37
  8 [-]: JMP       37           ; PC := 37
  9 [-]: GETGLOBAL R1 K3        ; R1 := gGameRules
 10 [-]: SELF      R1 R1 K4     ; R2 := R1; R1 := R1["0x8B598ED4"]
 11 [-]: GETGLOBAL R3 K5        ; R3 := dojoCustomObstacleCourseGameRules
 12 [-]: CALL      R1 3 2       ; R1 := R1(R2,R3)
 13 [-]: TEST      R1 0         ; if not R1 then PC := 37
 14 [-]: JMP       37           ; PC := 37
 15 [-]: GETGLOBAL R1 K3        ; R1 := gGameRules
 16 [-]: SELF      R1 R1 K6     ; R2 := R1; R1 := R1["0xB5A958D4"]
 17 [-]: CALL      R1 2 2       ; R1 := R1(R2)
 18 [-]: GETGLOBAL R2 K7        ; R2 := Lotus_Game
 19 [-]: GETTABLE  R2 R2 K8     ; R2 := R2["LotusObstacleCourseGameRules_CM_WarframeOnly"]
 20 [-]: EQ        0 R1 R2      ; if R1 ~= R2 then PC := 37
 21 [-]: JMP       37           ; PC := 37
 22 [-]: SELF      R2 R0 K9     ; R3 := R0; R2 := R0["0x8DB5D01F"]
 23 [-]: CALL      R2 2 2       ; R2 := R2(R3)
 24 [-]: SELF      R2 R2 K10    ; R3 := R2; R2 := R2["0x6978AC59"]
 25 [-]: CALL      R2 2 2       ; R2 := R2(R3)
 26 [-]: GETGLOBAL R3 K2        ; R3 := 0x400E7765
 27 [-]: MOVE      R4 R2        ; R4 := R2
 28 [-]: CALL      R3 2 2       ; R3 := R3(R4)
 29 [-]: TEST      R3 1         ; if R3 then PC := 37
 30 [-]: JMP       37           ; PC := 37
 31 [-]: SELF      R3 R2 K11    ; R4 := R2; R3 := R2["0xB279F0AF"]
 32 [-]: MOVE      R5 R1        ; R5 := R1
 33 [-]: GETGLOBAL R6 K12       ; R6 := 0xEC274B1A
 34 [-]: LOADK     R7 K13       ; R7 := "OPERATOR_TRANSFERENCE"
 35 [-]: CALL      R6 2 0       ; R6,... := R6(R7)
 36 [-]: CALL      R3 0 1       ; R3(R4,...)
 37 [-]: RETURN    R0 1         ; return 


; Function #17:
;
; Name:            
; Defined at line: 169
; #Upvalues:       1
; #Parameters:     0
; Is_vararg:       0
; Max Stack Size:  8

  1 [-]: GETGLOBAL R0 K0        ; R0 := gRegion
  2 [-]: SELF      R0 R0 K1     ; R1 := R0; R0 := R0["0x48FBE19F"]
  3 [-]: CALL      R0 2 2       ; R0 := R0(R1)
  4 [-]: LOADK     R1 K2        ; R1 := 1
  5 [-]: LEN       R2 R0        ; R2 := # R0
  6 [-]: LOADK     R3 K2        ; R3 := 1
  7 [-]: FORPREP   R1 12        ; R1 -= R3; PC := 12
  8 [-]: GETTABLE  R5 R0 R4     ; R5 := R0[R4]
  9 [-]: SELF      R5 R5 K3     ; R6 := R5; R5 := R5["0xCE0170C"]
 10 [-]: GETUPVAL  R7 U0        ; R7 := U0
 11 [-]: CALL      R5 3 1       ; R5(R6,R7)
 12 [-]: FORLOOP   R1 8         ; R1 += R3; if R1 <= R2 then begin PC := 8; R4 := R1 end
 13 [-]: RETURN    R0 1         ; return 


; Function #18:
;
; Name:            
; Defined at line: 176
; #Upvalues:       0
; #Parameters:     0
; Is_vararg:       0
; Max Stack Size:  20

  1 [-]: GETGLOBAL R0 K0        ; R0 := gRegion
  2 [-]: SELF      R0 R0 K1     ; R1 := R0; R0 := R0["0xA559F558"]
  3 [-]: CALL      R0 2 2       ; R0 := R0(R1)
  4 [-]: TEST      R0 0         ; if not R0 then PC := 18
  5 [-]: JMP       18           ; PC := 18
  6 [-]: GETGLOBAL R0 K0        ; R0 := gRegion
  7 [-]: SELF      R0 R0 K2     ; R1 := R0; R0 := R0["0x9139A00"]
  8 [-]: GETGLOBAL R2 K3        ; R2 := dojoStartTriggerType
  9 [-]: CALL      R0 3 2       ; R0 := R0(R1,R2)
 10 [-]: LOADK     R1 K4        ; R1 := 1
 11 [-]: LEN       R2 R0        ; R2 := # R0
 12 [-]: LOADK     R3 K4        ; R3 := 1
 13 [-]: FORPREP   R1 17        ; R1 -= R3; PC := 17
 14 [-]: GETTABLE  R5 R0 R4     ; R5 := R0[R4]
 15 [-]: SELF      R6 R5 K5     ; R7 := R5; R6 := R5["0xC5E91BA6"]
 16 [-]: CALL      R6 2 1       ; R6(R7)
 17 [-]: FORLOOP   R1 14        ; R1 += R3; if R1 <= R2 then begin PC := 14; R4 := R1 end
 18 [-]: GETGLOBAL R6 K0        ; R6 := gRegion
 19 [-]: SELF      R6 R6 K2     ; R7 := R6; R6 := R6["0x9139A00"]
 20 [-]: GETGLOBAL R8 K6        ; R8 := dojoStartDecoType
 21 [-]: CALL      R6 3 2       ; R6 := R6(R7,R8)
 22 [-]: LOADK     R7 K4        ; R7 := 1
 23 [-]: LEN       R8 R6        ; R8 := # R6
 24 [-]: LOADK     R9 K4        ; R9 := 1
 25 [-]: FORPREP   R7 50        ; R7 -= R9; PC := 50
 26 [-]: GETTABLE  R11 R6 R10   ; R11 := R6[R10]
 27 [-]: GETGLOBAL R12 K7       ; R12 := 0x400E7765
 28 [-]: MOVE      R13 R11      ; R13 := R11
 29 [-]: CALL      R12 2 2      ; R12 := R12(R13)
 30 [-]: TEST      R12 1        ; if R12 then PC := 50
 31 [-]: JMP       50           ; PC := 50
 32 [-]: SELF      R12 R11 K8   ; R13 := R11; R12 := R11["0xB3733382"]
 33 [-]: CALL      R12 2 2      ; R12 := R12(R13)
 34 [-]: LOADK     R13 K4       ; R13 := 1
 35 [-]: LEN       R14 R12      ; R14 := # R12
 36 [-]: LOADK     R15 K4       ; R15 := 1
 37 [-]: FORPREP   R13 49       ; R13 -= R15; PC := 49
 38 [-]: GETTABLE  R17 R12 R16  ; R17 := R12[R16]
 39 [-]: SELF      R17 R17 K9   ; R18 := R17; R17 := R17["0x8B598ED4"]
 40 [-]: GETGLOBAL R19 K10      ; R19 := dojoStartGateEffectType
 41 [-]: CALL      R17 3 2      ; R17 := R17(R18,R19)
 42 [-]: TEST      R17 0        ; if not R17 then PC := 49
 43 [-]: JMP       49           ; PC := 49
 44 [-]: GETTABLE  R17 R12 R16  ; R17 := R12[R16]
 45 [-]: SELF      R17 R17 K11  ; R18 := R17; R17 := R17["0xBF1BDD58"]
 46 [-]: GETGLOBAL R19 K12      ; R19 := Lotus_Game
 47 [-]: GETTABLE  R19 R19 K13  ; R19 := R19["TINT_COLOR"]
 48 [-]: CALL      R17 3 1      ; R17(R18,R19)
 49 [-]: FORLOOP   R13 38       ; R13 += R15; if R13 <= R14 then begin PC := 38; R16 := R13 end
 50 [-]: FORLOOP   R7 26        ; R7 += R9; if R7 <= R8 then begin PC := 26; R10 := R7 end
 51 [-]: RETURN    R0 1         ; return 


; Function #19:
;
; Name:            
; Defined at line: 199
; #Upvalues:       0
; #Parameters:     0
; Is_vararg:       0
; Max Stack Size:  13

  1 [-]: GETGLOBAL R0 K0        ; R0 := gRegion
  2 [-]: SELF      R0 R0 K1     ; R1 := R0; R0 := R0["0x9139A00"]
  3 [-]: GETGLOBAL R2 K2        ; R2 := gDamageTriggerType
  4 [-]: CALL      R0 3 2       ; R0 := R0(R1,R2)
  5 [-]: LOADK     R1 K3        ; R1 := 1
  6 [-]: LEN       R2 R0        ; R2 := # R0
  7 [-]: LOADK     R3 K3        ; R3 := 1
  8 [-]: FORPREP   R1 12        ; R1 -= R3; PC := 12
  9 [-]: GETTABLE  R5 R0 R4     ; R5 := R0[R4]
 10 [-]: SELF      R6 R5 K4     ; R7 := R5; R6 := R5["0xC5E91BA6"]
 11 [-]: CALL      R6 2 1       ; R6(R7)
 12 [-]: FORLOOP   R1 9         ; R1 += R3; if R1 <= R2 then begin PC := 9; R4 := R1 end
 13 [-]: GETGLOBAL R6 K0        ; R6 := gRegion
 14 [-]: SELF      R6 R6 K1     ; R7 := R6; R6 := R6["0x9139A00"]
 15 [-]: GETGLOBAL R8 K5        ; R8 := gElementType
 16 [-]: CALL      R6 3 2       ; R6 := R6(R7,R8)
 17 [-]: MOVE      R0 R6        ; R0 := R6
 18 [-]: LOADK     R6 K3        ; R6 := 1
 19 [-]: LEN       R7 R0        ; R7 := # R0
 20 [-]: LOADK     R8 K3        ; R8 := 1
 21 [-]: FORPREP   R6 25        ; R6 -= R8; PC := 25
 22 [-]: GETTABLE  R10 R0 R9    ; R10 := R0[R9]
 23 [-]: SELF      R11 R10 K4   ; R12 := R10; R11 := R10["0xC5E91BA6"]
 24 [-]: CALL      R11 2 1      ; R11(R12)
 25 [-]: FORLOOP   R6 22        ; R6 += R8; if R6 <= R7 then begin PC := 22; R9 := R6 end
 26 [-]: RETURN    R0 1         ; return 


; Function #20:
;
; Name:            
; Defined at line: 213
; #Upvalues:       0
; #Parameters:     0
; Is_vararg:       0
; Max Stack Size:  13

  1 [-]: GETGLOBAL R0 K0        ; R0 := gRegion
  2 [-]: SELF      R0 R0 K1     ; R1 := R0; R0 := R0["0x9139A00"]
  3 [-]: GETGLOBAL R2 K2        ; R2 := gDamageTriggerType
  4 [-]: CALL      R0 3 2       ; R0 := R0(R1,R2)
  5 [-]: LOADK     R1 K3        ; R1 := 1
  6 [-]: LEN       R2 R0        ; R2 := # R0
  7 [-]: LOADK     R3 K3        ; R3 := 1
  8 [-]: FORPREP   R1 12        ; R1 -= R3; PC := 12
  9 [-]: GETTABLE  R5 R0 R4     ; R5 := R0[R4]
 10 [-]: SELF      R6 R5 K4     ; R7 := R5; R6 := R5["0x2DB1272F"]
 11 [-]: CALL      R6 2 1       ; R6(R7)
 12 [-]: FORLOOP   R1 9         ; R1 += R3; if R1 <= R2 then begin PC := 9; R4 := R1 end
 13 [-]: GETGLOBAL R6 K0        ; R6 := gRegion
 14 [-]: SELF      R6 R6 K1     ; R7 := R6; R6 := R6["0x9139A00"]
 15 [-]: GETGLOBAL R8 K5        ; R8 := gElementType
 16 [-]: CALL      R6 3 2       ; R6 := R6(R7,R8)
 17 [-]: MOVE      R0 R6        ; R0 := R6
 18 [-]: LOADK     R6 K3        ; R6 := 1
 19 [-]: LEN       R7 R0        ; R7 := # R0
 20 [-]: LOADK     R8 K3        ; R8 := 1
 21 [-]: FORPREP   R6 25        ; R6 -= R8; PC := 25
 22 [-]: GETTABLE  R10 R0 R9    ; R10 := R0[R9]
 23 [-]: SELF      R11 R10 K4   ; R12 := R10; R11 := R10["0x2DB1272F"]
 24 [-]: CALL      R11 2 1      ; R11(R12)
 25 [-]: FORLOOP   R6 22        ; R6 += R8; if R6 <= R7 then begin PC := 22; R9 := R6 end
 26 [-]: RETURN    R0 1         ; return 


; Function #21:
;
; Name:            
; Defined at line: 228
; #Upvalues:       0
; #Parameters:     1
; Is_vararg:       0
; Max Stack Size:  7

  1 [-]: GETGLOBAL R2 K0        ; R2 := 0x400E7765
  2 [-]: MOVE      R3 R0        ; R3 := R0
  3 [-]: CALL      R2 2 2       ; R2 := R2(R3)
  4 [-]: TEST      R2 1         ; if R2 then PC := 16
  5 [-]: JMP       16           ; PC := 16
  6 [-]: SELF      R2 R0 K1     ; R3 := R0; R2 := R0["0x72E5DB62"]
  7 [-]: CALL      R2 2 2       ; R2 := R2(R3)
  8 [-]: SELF      R2 R2 K2     ; R3 := R2; R2 := R2["0x61FDC81"]
  9 [-]: CALL      R2 2 2       ; R2 := R2(R3)
 10 [-]: GETGLOBAL R3 K3        ; R3 := _T
 11 [-]: GETTABLE  R3 R3 K4     ; R3 := R3["DojoMgr"]
 12 [-]: SELF      R3 R3 K5     ; R4 := R3; R3 := R3["0xBF9A2C88"]
 13 [-]: MOVE      R5 R2        ; R5 := R2
 14 [-]: CALL      R3 3 2       ; R3 := R3(R4,R5)
 15 [-]: GETTABLE  R1 R3 K6     ; R1 := R3["id"]
 16 [-]: EQ        1 R1 K7      ; if R1 == nil then PC := 20
 17 [-]: JMP       20           ; PC := 20
 18 [-]: EQ        0 R1 K8      ; if R1 ~= "" then PC := 34
 19 [-]: JMP       34           ; PC := 34
 20 [-]: GETGLOBAL R4 K9        ; R4 := gGameRules
 21 [-]: SELF      R4 R4 K10    ; R5 := R4; R4 := R4["0x8B598ED4"]
 22 [-]: GETGLOBAL R6 K11       ; R6 := dojoCustomObstacleCourseGameRules
 23 [-]: CALL      R4 3 2       ; R4 := R4(R5,R6)
 24 [-]: TEST      R4 0         ; if not R4 then PC := 34
 25 [-]: JMP       34           ; PC := 34
 26 [-]: GETGLOBAL R4 K12       ; R4 := gRegion
 27 [-]: SELF      R4 R4 K13    ; R5 := R4; R4 := R4["0xD2075696"]
 28 [-]: CALL      R4 2 2       ; R4 := R4(R5)
 29 [-]: GETTABLE  R4 R4 K14    ; R4 := R4["contextTags"]
 30 [-]: LEN       R5 R4        ; R5 := # R4
 31 [-]: LE        0 K15 R5     ; if 5 > R5 then PC := 34
 32 [-]: JMP       34           ; PC := 34
 33 [-]: GETTABLE  R1 R4 K15    ; R1 := R4[5]
 34 [-]: RETURN    R1 2         ; return R1
 35 [-]: RETURN    R0 1         ; return 


; Function #22:
;
; Name:            
; Defined at line: 245
; #Upvalues:       1
; #Parameters:     0
; Is_vararg:       0
; Max Stack Size:  2

  1 [-]: GETGLOBAL R0 K0        ; R0 := gRegion
  2 [-]: SELF      R0 R0 K1     ; R1 := R0; R0 := R0["0xA559F558"]
  3 [-]: CALL      R0 2 2       ; R0 := R0(R1)
  4 [-]: TEST      R0 1         ; if R0 then PC := 8
  5 [-]: JMP       8            ; PC := 8
  6 [-]: GETUPVAL  R0 U0        ; R0 := U0
  7 [-]: CALL      R0 1 1       ; R0()
  8 [-]: RETURN    R0 1         ; return 


; Function #23:
;
; Name:            
; Defined at line: 251
; #Upvalues:       8
; #Parameters:     0
; Is_vararg:       0
; Max Stack Size:  17

  1 [-]: GETUPVAL  R0 U0        ; R0 := U0
  2 [-]: CALL      R0 1 1       ; R0()
  3 [-]: GETUPVAL  R0 U1        ; R0 := U1
  4 [-]: CALL      R0 1 2       ; R0 := R0()
  5 [-]: SELF      R1 R0 K0     ; R2 := R0; R1 := R0["0x762CE56E"]
  6 [-]: CALL      R1 2 2       ; R1 := R1(R2)
  7 [-]: GETGLOBAL R2 K1        ; R2 := 0x400E7765
  8 [-]: MOVE      R3 R1        ; R3 := R1
  9 [-]: CALL      R2 2 2       ; R2 := R2(R3)
 10 [-]: TEST      R2 0         ; if not R2 then PC := 13
 11 [-]: JMP       13           ; PC := 13
 12 [-]: RETURN    R0 1         ; return 
 13 [-]: GETGLOBAL R2 K2        ; R2 := gRegion
 14 [-]: SELF      R2 R2 K3     ; R3 := R2; R2 := R2["0xA559F558"]
 15 [-]: CALL      R2 2 2       ; R2 := R2(R3)
 16 [-]: TEST      R2 1         ; if R2 then PC := 19
 17 [-]: JMP       19           ; PC := 19
 18 [-]: RETURN    R0 1         ; return 
 19 [-]: SELF      R2 R0 K4     ; R3 := R0; R2 := R0["0xEAA8244E"]
 20 [-]: CALL      R2 2 2       ; R2 := R2(R3)
 21 [-]: GETGLOBAL R3 K5        ; R3 := math
 22 [-]: GETTABLE  R3 R3 K6     ; R3 := R3["0xF7005A7B"]
 23 [-]: DIV       R4 R2 K7     ; R4 := R2 / 60
 24 [-]: CALL      R3 2 2       ; R3 := R3(R4)
 25 [-]: MUL       R4 K7 R3     ; R4 := 60 * R3
 26 [-]: SUB       R4 R2 R4     ; R4 := R2 - R4
 27 [-]: GETGLOBAL R5 K8        ; R5 := string
 28 [-]: GETTABLE  R5 R5 K9     ; R5 := R5["0x4B1F4F58"]
 29 [-]: LOADK     R6 K10       ; R6 := "%.2f"
 30 [-]: MOVE      R7 R4        ; R7 := R4
 31 [-]: CALL      R5 3 2       ; R5 := R5(R6,R7)
 32 [-]: MOVE      R4 R5        ; R4 := R5
 33 [-]: GETGLOBAL R5 K8        ; R5 := string
 34 [-]: GETTABLE  R5 R5 K9     ; R5 := R5["0x4B1F4F58"]
 35 [-]: LOADK     R6 K11       ; R6 := "%02d"
 36 [-]: MOVE      R7 R3        ; R7 := R3
 37 [-]: CALL      R5 3 2       ; R5 := R5(R6,R7)
 38 [-]: MOVE      R3 R5        ; R3 := R5
 39 [-]: GETGLOBAL R5 K12       ; R5 := 0xE6DC43B0
 40 [-]: GETUPVAL  R6 U2        ; R6 := U2
 41 [-]: MOVE      R7 R0        ; R7 := R0
 42 [-]: CALL      R5 3 2       ; R5 := R5(R6,R7)
 43 [-]: GETUPVAL  R6 U3        ; R6 := U3
 44 [-]: CALL      R6 1 1       ; R6()
 45 [-]: GETUPVAL  R6 U4        ; R6 := U4
 46 [-]: CALL      R6 1 1       ; R6()
 47 [-]: SELF      R6 R1 K13    ; R7 := R1; R6 := R1["0xDE5882DD"]
 48 [-]: CALL      R6 2 2       ; R6 := R6(R7)
 49 [-]: GETGLOBAL R7 K1        ; R7 := 0x400E7765
 50 [-]: MOVE      R8 R6        ; R8 := R6
 51 [-]: CALL      R7 2 2       ; R7 := R7(R8)
 52 [-]: TEST      R7 0         ; if not R7 then PC := 55
 53 [-]: JMP       55           ; PC := 55
 54 [-]: RETURN    R0 1         ; return 
 55 [-]: GETGLOBAL R7 K14       ; R7 := gGameRules
 56 [-]: SELF      R7 R7 K15    ; R8 := R7; R7 := R7["0x362A2E36"]
 57 [-]: MOVE      R9 R6        ; R9 := R6
 58 [-]: MOVE      R10 R5       ; R10 := R5
 59 [-]: LOADK     R11 K16      ; R11 := " "
 60 [-]: MOVE      R12 R3       ; R12 := R3
 61 [-]: LOADK     R13 K17      ; R13 := ":"
 62 [-]: MOVE      R14 R4       ; R14 := R4
 63 [-]: CONCAT    R10 R10 R14  ; R10 := R10 .. R11 .. R12 .. R13 .. R14
 64 [-]: LOADK     R11 K18      ; R11 := ""
 65 [-]: LOADK     R12 K19      ; R12 := 0
 66 [-]: LOADK     R13 K20      ; R13 := 2
 67 [-]: MOVE      R14 R1       ; R14 := R1
 68 [-]: CALL      R7 8 1       ; R7(R8,R9,R10,R11,R12,R13,R14)
 69 [-]: GETGLOBAL R7 K21       ; R7 := gPlayerProfileMgr
 70 [-]: SELF      R7 R7 K22    ; R8 := R7; R7 := R7["0x21EF7B1A"]
 71 [-]: LOADK     R9 K19       ; R9 := 0
 72 [-]: CALL      R7 3 2       ; R7 := R7(R8,R9)
 73 [-]: GETGLOBAL R8 K1        ; R8 := 0x400E7765
 74 [-]: MOVE      R9 R7        ; R9 := R7
 75 [-]: CALL      R8 2 2       ; R8 := R8(R9)
 76 [-]: TEST      R8 1         ; if R8 then PC := 105
 77 [-]: JMP       105          ; PC := 105
 78 [-]: SELF      R8 R7 K23    ; R9 := R7; R8 := R7["0x654F1092"]
 79 [-]: CALL      R8 2 2       ; R8 := R8(R9)
 80 [-]: GETGLOBAL R9 K1        ; R9 := 0x400E7765
 81 [-]: MOVE      R10 R8       ; R10 := R8
 82 [-]: CALL      R9 2 2       ; R9 := R9(R10)
 83 [-]: TEST      R9 1         ; if R9 then PC := 105
 84 [-]: JMP       105          ; PC := 105
 85 [-]: GETUPVAL  R9 U5        ; R9 := U5
 86 [-]: MOVE      R10 R1       ; R10 := R1
 87 [-]: CALL      R9 2 2       ; R9 := R9(R10)
 88 [-]: GETGLOBAL R10 K1       ; R10 := 0x400E7765
 89 [-]: MOVE      R11 R9       ; R11 := R9
 90 [-]: CALL      R10 2 2      ; R10 := R10(R11)
 91 [-]: TEST      R10 1        ; if R10 then PC := 105
 92 [-]: JMP       105          ; PC := 105
 93 [-]: EQ        1 R9 K18     ; if R9 == "" then PC := 105
 94 [-]: JMP       105          ; PC := 105
 95 [-]: SELF      R10 R8 K24   ; R11 := R8; R10 := R8["0x2B0810E4"]
 96 [-]: SELF      R12 R6 K25   ; R13 := R6; R12 := R6["0x8F535238"]
 97 [-]: CALL      R12 2 2      ; R12 := R12(R13)
 98 [-]: GETGLOBAL R13 K14      ; R13 := gGameRules
 99 [-]: SELF      R13 R13 K26  ; R14 := R13; R13 := R13["0x15793965"]
100 [-]: CALL      R13 2 2      ; R13 := R13(R14)
101 [-]: MOVE      R14 R9       ; R14 := R9
102 [-]: MUL       R15 R2 K27   ; R15 := R2 * 1000
103 [-]: LOADK     R16 K28      ; R16 := "SubmitScoreResult"
104 [-]: CALL      R10 7 1      ; R10(R11,R12,R13,R14,R15,R16)
105 [-]: GETUPVAL  R10 U6       ; R10 := U6
106 [-]: MOVE      R11 R1       ; R11 := R1
107 [-]: CALL      R10 2 1      ; R10(R11)
108 [-]: GETUPVAL  R10 U7       ; R10 := U7
109 [-]: MOVE      R11 R1       ; R11 := R1
110 [-]: CALL      R10 2 2      ; R10 := R10(R11)
111 [-]: GETGLOBAL R11 K1       ; R11 := 0x400E7765
112 [-]: MOVE      R12 R10      ; R12 := R10
113 [-]: CALL      R11 2 2      ; R11 := R11(R12)
114 [-]: TEST      R11 1        ; if R11 then PC := 124
115 [-]: JMP       124          ; PC := 124
116 [-]: SELF      R11 R10 K29  ; R12 := R10; R11 := R10["0x6DA72501"]
117 [-]: CALL      R11 2 2      ; R11 := R11(R12)
118 [-]: SELF      R12 R10 K30  ; R13 := R10; R12 := R10["0xF23A7849"]
119 [-]: CALL      R12 2 2      ; R12 := R12(R13)
120 [-]: SELF      R13 R1 K31   ; R14 := R1; R13 := R1["0x39D7F449"]
121 [-]: MOVE      R15 R11      ; R15 := R11
122 [-]: MOVE      R16 R12      ; R16 := R12
123 [-]: CALL      R13 4 1      ; R13(R14,R15,R16)
124 [-]: SELF      R13 R0 K32   ; R14 := R0; R13 := R0["0xB4E66650"]
125 [-]: LOADK     R15 K20      ; R15 := 2
126 [-]: CALL      R13 3 1      ; R13(R14,R15)
127 [-]: RETURN    R0 1         ; return 


; Function #24:
;
; Name:            
; Defined at line: 303
; #Upvalues:       6
; #Parameters:     0
; Is_vararg:       0
; Max Stack Size:  12

  1 [-]: GETUPVAL  R0 U0        ; R0 := U0
  2 [-]: CALL      R0 1 1       ; R0()
  3 [-]: GETGLOBAL R0 K0        ; R0 := gRegion
  4 [-]: SELF      R0 R0 K1     ; R1 := R0; R0 := R0["0xA559F558"]
  5 [-]: CALL      R0 2 2       ; R0 := R0(R1)
  6 [-]: TEST      R0 1         ; if R0 then PC := 9
  7 [-]: JMP       9            ; PC := 9
  8 [-]: RETURN    R0 1         ; return 
  9 [-]: GETUPVAL  R0 U1        ; R0 := U1
 10 [-]: CALL      R0 1 2       ; R0 := R0()
 11 [-]: SELF      R1 R0 K2     ; R2 := R0; R1 := R0["0x762CE56E"]
 12 [-]: CALL      R1 2 2       ; R1 := R1(R2)
 13 [-]: GETGLOBAL R2 K3        ; R2 := 0x400E7765
 14 [-]: MOVE      R3 R1        ; R3 := R1
 15 [-]: CALL      R2 2 2       ; R2 := R2(R3)
 16 [-]: TEST      R2 0         ; if not R2 then PC := 19
 17 [-]: JMP       19           ; PC := 19
 18 [-]: RETURN    R0 1         ; return 
 19 [-]: GETGLOBAL R2 K4        ; R2 := 0x201191EA
 20 [-]: GETGLOBAL R3 K5        ; R3 := triggerDelay
 21 [-]: CALL      R2 2 1       ; R2(R3)
 22 [-]: GETUPVAL  R2 U2        ; R2 := U2
 23 [-]: CALL      R2 1 1       ; R2()
 24 [-]: GETUPVAL  R2 U3        ; R2 := U3
 25 [-]: CALL      R2 1 1       ; R2()
 26 [-]: GETUPVAL  R2 U4        ; R2 := U4
 27 [-]: MOVE      R3 R1        ; R3 := R1
 28 [-]: CALL      R2 2 1       ; R2(R3)
 29 [-]: GETUPVAL  R2 U5        ; R2 := U5
 30 [-]: MOVE      R3 R1        ; R3 := R1
 31 [-]: CALL      R2 2 2       ; R2 := R2(R3)
 32 [-]: GETGLOBAL R3 K3        ; R3 := 0x400E7765
 33 [-]: MOVE      R4 R2        ; R4 := R2
 34 [-]: CALL      R3 2 2       ; R3 := R3(R4)
 35 [-]: TEST      R3 1         ; if R3 then PC := 62
 36 [-]: JMP       62           ; PC := 62
 37 [-]: SELF      R3 R1 K6     ; R4 := R1; R3 := R1["0xDE5882DD"]
 38 [-]: CALL      R3 2 2       ; R3 := R3(R4)
 39 [-]: GETGLOBAL R4 K7        ; R4 := gGameRules
 40 [-]: SELF      R4 R4 K8     ; R5 := R4; R4 := R4["0x362A2E36"]
 41 [-]: SELF      R6 R1 K6     ; R7 := R1; R6 := R1["0xDE5882DD"]
 42 [-]: CALL      R6 2 2       ; R6 := R6(R7)
 43 [-]: LOADK     R7 K9        ; R7 := "/Lotus/Language/Dojo/CustomObstacleCourseFailed"
 44 [-]: LOADK     R8 K10       ; R8 := ""
 45 [-]: LOADK     R9 K11       ; R9 := 0
 46 [-]: LOADK     R10 K12      ; R10 := 2
 47 [-]: MOVE      R11 R0       ; R11 := R0
 48 [-]: CALL      R4 8 1       ; R4(R5,R6,R7,R8,R9,R10,R11)
 49 [-]: SELF      R4 R3 K13    ; R5 := R3; R4 := R3["0xA9BB1F2"]
 50 [-]: MOVE      R6 R2        ; R6 := R2
 51 [-]: CALL      R4 3 1       ; R4(R5,R6)
 52 [-]: SELF      R4 R1 K14    ; R5 := R1; R4 := R1["0x3B1E0FE1"]
 53 [-]: CALL      R4 2 1       ; R4(R5)
 54 [-]: SELF      R4 R2 K15    ; R5 := R2; R4 := R2["0x6DA72501"]
 55 [-]: CALL      R4 2 2       ; R4 := R4(R5)
 56 [-]: SELF      R5 R2 K16    ; R6 := R2; R5 := R2["0xF23A7849"]
 57 [-]: CALL      R5 2 2       ; R5 := R5(R6)
 58 [-]: SELF      R6 R1 K17    ; R7 := R1; R6 := R1["0x39D7F449"]
 59 [-]: MOVE      R8 R4        ; R8 := R4
 60 [-]: MOVE      R9 R5        ; R9 := R5
 61 [-]: CALL      R6 4 1       ; R6(R7,R8,R9)
 62 [-]: SELF      R6 R0 K18    ; R7 := R0; R6 := R0["0xF65EB71C"]
 63 [-]: CALL      R6 2 1       ; R6(R7)
 64 [-]: RETURN    R0 1         ; return 


; Function #25:
;
; Name:            
; Defined at line: 331
; #Upvalues:       0
; #Parameters:     0
; Is_vararg:       0
; Max Stack Size:  25

  1 [-]: GETGLOBAL R0 K0        ; R0 := gRegion
  2 [-]: SELF      R0 R0 K1     ; R1 := R0; R0 := R0["0xA559F558"]
  3 [-]: CALL      R0 2 2       ; R0 := R0(R1)
  4 [-]: TEST      R0 0         ; if not R0 then PC := 32
  5 [-]: JMP       32           ; PC := 32
  6 [-]: GETGLOBAL R0 K0        ; R0 := gRegion
  7 [-]: SELF      R0 R0 K2     ; R1 := R0; R0 := R0["0x9139A00"]
  8 [-]: GETGLOBAL R2 K3        ; R2 := dojoStartTriggerType
  9 [-]: CALL      R0 3 2       ; R0 := R0(R1,R2)
 10 [-]: LOADK     R1 K4        ; R1 := 1
 11 [-]: LEN       R2 R0        ; R2 := # R0
 12 [-]: LOADK     R3 K4        ; R3 := 1
 13 [-]: FORPREP   R1 31        ; R1 -= R3; PC := 31
 14 [-]: GETTABLE  R5 R0 R4     ; R5 := R0[R4]
 15 [-]: SELF      R6 R5 K5     ; R7 := R5; R6 := R5["0x2DB1272F"]
 16 [-]: CALL      R6 2 1       ; R6(R7)
 17 [-]: SELF      R6 R5 K6     ; R7 := R5; R6 := R5["0xD5FAF012"]
 18 [-]: CALL      R6 2 2       ; R6 := R6(R7)
 19 [-]: GETGLOBAL R7 K7        ; R7 := 0x400E7765
 20 [-]: MOVE      R8 R5        ; R8 := R5
 21 [-]: CALL      R7 2 2       ; R7 := R7(R8)
 22 [-]: TEST      R7 1         ; if R7 then PC := 31
 23 [-]: JMP       31           ; PC := 31
 24 [-]: GETGLOBAL R7 K7        ; R7 := 0x400E7765
 25 [-]: MOVE      R8 R6        ; R8 := R6
 26 [-]: CALL      R7 2 2       ; R7 := R7(R8)
 27 [-]: TEST      R7 1         ; if R7 then PC := 31
 28 [-]: JMP       31           ; PC := 31
 29 [-]: SELF      R7 R5 K5     ; R8 := R5; R7 := R5["0x2DB1272F"]
 30 [-]: CALL      R7 2 1       ; R7(R8)
 31 [-]: FORLOOP   R1 14        ; R1 += R3; if R1 <= R2 then begin PC := 14; R4 := R1 end
 32 [-]: GETGLOBAL R7 K0        ; R7 := gRegion
 33 [-]: SELF      R7 R7 K2     ; R8 := R7; R7 := R7["0x9139A00"]
 34 [-]: GETGLOBAL R9 K8        ; R9 := dojoStartDecoType
 35 [-]: CALL      R7 3 2       ; R7 := R7(R8,R9)
 36 [-]: LOADK     R8 K4        ; R8 := 1
 37 [-]: LEN       R9 R7        ; R9 := # R7
 38 [-]: LOADK     R10 K4       ; R10 := 1
 39 [-]: FORPREP   R8 76        ; R8 -= R10; PC := 76
 40 [-]: GETTABLE  R12 R7 R11   ; R12 := R7[R11]
 41 [-]: GETGLOBAL R13 K7       ; R13 := 0x400E7765
 42 [-]: MOVE      R14 R12      ; R14 := R12
 43 [-]: CALL      R13 2 2      ; R13 := R13(R14)
 44 [-]: TEST      R13 1        ; if R13 then PC := 76
 45 [-]: JMP       76           ; PC := 76
 46 [-]: SELF      R13 R12 K9   ; R14 := R12; R13 := R12["0xB3733382"]
 47 [-]: CALL      R13 2 2      ; R13 := R13(R14)
 48 [-]: LOADK     R14 K4       ; R14 := 1
 49 [-]: LEN       R15 R13      ; R15 := # R13
 50 [-]: LOADK     R16 K4       ; R16 := 1
 51 [-]: FORPREP   R14 75       ; R14 -= R16; PC := 75
 52 [-]: GETTABLE  R18 R13 R17  ; R18 := R13[R17]
 53 [-]: SELF      R18 R18 K10  ; R19 := R18; R18 := R18["0x8B598ED4"]
 54 [-]: GETGLOBAL R20 K11      ; R20 := dojoStartGateEffectType
 55 [-]: CALL      R18 3 2      ; R18 := R18(R19,R20)
 56 [-]: TEST      R18 0        ; if not R18 then PC := 75
 57 [-]: JMP       75           ; PC := 75
 58 [-]: GETTABLE  R18 R13 R17  ; R18 := R13[R17]
 59 [-]: SELF      R18 R18 K12  ; R19 := R18; R18 := R18["0xD124E361"]
 60 [-]: GETGLOBAL R20 K13      ; R20 := Lotus_Game
 61 [-]: GETTABLE  R20 R20 K14  ; R20 := R20["TINT_COLOR"]
 62 [-]: GETGLOBAL R21 K15      ; R21 := startGateInactiveColor
 63 [-]: GETTABLE  R21 R21 K16  ; R21 := R21["red"]
 64 [-]: DIV       R21 R21 K17  ; R21 := R21 / 255
 65 [-]: GETGLOBAL R22 K15      ; R22 := startGateInactiveColor
 66 [-]: GETTABLE  R22 R22 K18  ; R22 := R22["green"]
 67 [-]: DIV       R22 R22 K17  ; R22 := R22 / 255
 68 [-]: GETGLOBAL R23 K15      ; R23 := startGateInactiveColor
 69 [-]: GETTABLE  R23 R23 K19  ; R23 := R23["blue"]
 70 [-]: DIV       R23 R23 K17  ; R23 := R23 / 255
 71 [-]: GETGLOBAL R24 K15      ; R24 := startGateInactiveColor
 72 [-]: GETTABLE  R24 R24 K20  ; R24 := R24["alpha"]
 73 [-]: DIV       R24 R24 K17  ; R24 := R24 / 255
 74 [-]: CALL      R18 7 1      ; R18(R19,R20,R21,R22,R23,R24)
 75 [-]: FORLOOP   R14 52       ; R14 += R16; if R14 <= R15 then begin PC := 52; R17 := R14 end
 76 [-]: FORLOOP   R8 40        ; R8 += R10; if R8 <= R9 then begin PC := 40; R11 := R8 end
 77 [-]: RETURN    R0 1         ; return 


; Function #26:
;
; Name:            
; Defined at line: 358
; #Upvalues:       7
; #Parameters:     0
; Is_vararg:       0
; Max Stack Size:  4

  1 [-]: GETUPVAL  R0 U0        ; R0 := U0
  2 [-]: CALL      R0 1 2       ; R0 := R0()
  3 [-]: GETUPVAL  R1 U1        ; R1 := U1
  4 [-]: CALL      R1 1 2       ; R1 := R1()
  5 [-]: SELF      R2 R1 K0     ; R3 := R1; R2 := R1["0xD01F29AC"]
  6 [-]: CALL      R2 2 2       ; R2 := R2(R3)
  7 [-]: GETGLOBAL R3 K1        ; R3 := Lotus_Game
  8 [-]: GETTABLE  R3 R3 K2     ; R3 := R3["LotusObstacleCourseGameRules_RS_RUNNING"]
  9 [-]: EQ        0 R2 R3      ; if R2 ~= R3 then PC := 14
 10 [-]: JMP       14           ; PC := 14
 11 [-]: GETUPVAL  R3 U2        ; R3 := U2
 12 [-]: CALL      R3 1 1       ; R3()
 13 [-]: JMP       41           ; PC := 41
 14 [-]: GETGLOBAL R3 K1        ; R3 := Lotus_Game
 15 [-]: GETTABLE  R3 R3 K3     ; R3 := R3["LotusObstacleCourseGameRules_RS_VICTORY"]
 16 [-]: EQ        0 R2 R3      ; if R2 ~= R3 then PC := 21
 17 [-]: JMP       21           ; PC := 21
 18 [-]: GETUPVAL  R3 U3        ; R3 := U3
 19 [-]: CALL      R3 1 1       ; R3()
 20 [-]: JMP       41           ; PC := 41
 21 [-]: GETGLOBAL R3 K1        ; R3 := Lotus_Game
 22 [-]: GETTABLE  R3 R3 K4     ; R3 := R3["LotusObstacleCourseGameRules_RS_RESET"]
 23 [-]: EQ        0 R2 R3      ; if R2 ~= R3 then PC := 28
 24 [-]: JMP       28           ; PC := 28
 25 [-]: GETUPVAL  R3 U4        ; R3 := U4
 26 [-]: CALL      R3 1 1       ; R3()
 27 [-]: JMP       41           ; PC := 41
 28 [-]: GETGLOBAL R3 K1        ; R3 := Lotus_Game
 29 [-]: GETTABLE  R3 R3 K5     ; R3 := R3["LotusObstacleCourseGameRules_RS_FAILURE"]
 30 [-]: EQ        0 R2 R3      ; if R2 ~= R3 then PC := 35
 31 [-]: JMP       35           ; PC := 35
 32 [-]: GETUPVAL  R3 U5        ; R3 := U5
 33 [-]: CALL      R3 1 1       ; R3()
 34 [-]: JMP       41           ; PC := 41
 35 [-]: GETGLOBAL R3 K1        ; R3 := Lotus_Game
 36 [-]: GETTABLE  R3 R3 K6     ; R3 := R3["LotusObstacleCourseGameRules_RS_IDLE"]
 37 [-]: EQ        0 R2 R3      ; if R2 ~= R3 then PC := 41
 38 [-]: JMP       41           ; PC := 41
 39 [-]: GETUPVAL  R3 U6        ; R3 := U6
 40 [-]: CALL      R3 1 1       ; R3()
 41 [-]: RETURN    R0 1         ; return 


; Function #27:
;
; Name:            
; Defined at line: 376
; #Upvalues:       0
; #Parameters:     0
; Is_vararg:       0
; Max Stack Size:  2

  1 [-]: RETURN    R0 1         ; return 


; Function #28:
;
; Name:            
; Defined at line: 379
; #Upvalues:       0
; #Parameters:     1
; Is_vararg:       0
; Max Stack Size:  32

  1 [-]: GETGLOBAL R1 K0        ; R1 := 0x400E7765
  2 [-]: MOVE      R2 R0        ; R2 := R0
  3 [-]: CALL      R1 2 2       ; R1 := R1(R2)
  4 [-]: TEST      R1 0         ; if not R1 then PC := 7
  5 [-]: JMP       7            ; PC := 7
  6 [-]: RETURN    R0 1         ; return 
  7 [-]: LOADK     R1 K1        ; R1 := 0
  8 [-]: GETGLOBAL R2 K2        ; R2 := gRegion
  9 [-]: SELF      R2 R2 K3     ; R3 := R2; R2 := R2["0x9139A00"]
 10 [-]: GETGLOBAL R4 K4        ; R4 := dojoCheckpointTriggerType
 11 [-]: CALL      R2 3 2       ; R2 := R2(R3,R4)
 12 [-]: LOADK     R3 K5        ; R3 := 1
 13 [-]: LEN       R4 R2        ; R4 := # R2
 14 [-]: LOADK     R5 K5        ; R5 := 1
 15 [-]: FORPREP   R3 29        ; R3 -= R5; PC := 29
 16 [-]: GETTABLE  R7 R2 R6     ; R7 := R2[R6]
 17 [-]: SELF      R8 R7 K6     ; R9 := R7; R8 := R7["0xD5FAF012"]
 18 [-]: CALL      R8 2 2       ; R8 := R8(R9)
 19 [-]: GETGLOBAL R9 K0        ; R9 := 0x400E7765
 20 [-]: MOVE      R10 R8       ; R10 := R8
 21 [-]: CALL      R9 2 2       ; R9 := R9(R10)
 22 [-]: TEST      R9 1         ; if R9 then PC := 29
 23 [-]: JMP       29           ; PC := 29
 24 [-]: SELF      R9 R7 K7     ; R10 := R7; R9 := R7["0xB1627322"]
 25 [-]: CALL      R9 2 2       ; R9 := R9(R10)
 26 [-]: TEST      R9 0         ; if not R9 then PC := 29
 27 [-]: JMP       29           ; PC := 29
 28 [-]: ADD       R1 R1 K5     ; R1 := R1 + 1
 29 [-]: FORLOOP   R3 16        ; R3 += R5; if R3 <= R4 then begin PC := 16; R6 := R3 end
 30 [-]: LOADK     R9 K1        ; R9 := 0
 31 [-]: GETGLOBAL R10 K2       ; R10 := gRegion
 32 [-]: SELF      R10 R10 K3   ; R11 := R10; R10 := R10["0x9139A00"]
 33 [-]: GETGLOBAL R12 K8       ; R12 := destructibleDummyType
 34 [-]: CALL      R10 3 2      ; R10 := R10(R11,R12)
 35 [-]: LOADK     R11 K5       ; R11 := 1
 36 [-]: LEN       R12 R10      ; R12 := # R10
 37 [-]: LOADK     R13 K5       ; R13 := 1
 38 [-]: FORPREP   R11 45       ; R11 -= R13; PC := 45
 39 [-]: GETTABLE  R15 R10 R14  ; R15 := R10[R14]
 40 [-]: SELF      R15 R15 K9   ; R16 := R15; R15 := R15["0x2F79FBD3"]
 41 [-]: CALL      R15 2 2      ; R15 := R15(R16)
 42 [-]: LT        0 K1 R15     ; if 0 >= R15 then PC := 45
 43 [-]: JMP       45           ; PC := 45
 44 [-]: ADD       R9 R9 K5     ; R9 := R9 + 1
 45 [-]: FORLOOP   R11 39       ; R11 += R13; if R11 <= R12 then begin PC := 39; R14 := R11 end
 46 [-]: GETGLOBAL R16 K2       ; R16 := gRegion
 47 [-]: SELF      R16 R16 K3   ; R17 := R16; R16 := R16["0x9139A00"]
 48 [-]: GETGLOBAL R18 K10      ; R18 := dojoEndTriggerType
 49 [-]: CALL      R16 3 2      ; R16 := R16(R17,R18)
 50 [-]: LOADK     R17 K5       ; R17 := 1
 51 [-]: LEN       R18 R16      ; R18 := # R16
 52 [-]: LOADK     R19 K5       ; R19 := 1
 53 [-]: FORPREP   R17 114      ; R17 -= R19; PC := 114
 54 [-]: GETTABLE  R21 R16 R20  ; R21 := R16[R20]
 55 [-]: SELF      R22 R21 K6   ; R23 := R21; R22 := R21["0xD5FAF012"]
 56 [-]: CALL      R22 2 2      ; R22 := R22(R23)
 57 [-]: GETGLOBAL R23 K0       ; R23 := 0x400E7765
 58 [-]: MOVE      R24 R22      ; R24 := R22
 59 [-]: CALL      R23 2 2      ; R23 := R23(R24)
 60 [-]: TEST      R23 1        ; if R23 then PC := 114
 61 [-]: JMP       114          ; PC := 114
 62 [-]: LT        1 K1 R1      ; if 0 < R1 then PC := 66
 63 [-]: JMP       66           ; PC := 66
 64 [-]: LT        0 K1 R9      ; if 0 >= R9 then PC := 112
 65 [-]: JMP       112          ; PC := 112
 66 [-]: LOADK     R23 K11      ; R23 := ""
 67 [-]: LT        0 K1 R1      ; if 0 >= R1 then PC := 84
 68 [-]: JMP       84           ; PC := 84
 69 [-]: LT        0 K1 R9      ; if 0 >= R9 then PC := 84
 70 [-]: JMP       84           ; PC := 84
 71 [-]: GETGLOBAL R24 K12      ; R24 := 0xE6DC43B0
 72 [-]: LOADK     R25 K13      ; R25 := "/Lotus/Language/Dojo/CustomObstacleCourseCheckpointRemaning"
 73 [-]: NEWTABLE  R26 0 1      ; R26 := {}
 74 [-]: SETTABLE  R26 K14 R1   ; R26["CHECKPOINTS"] := R1
 75 [-]: CALL      R24 3 2      ; R24 := R24(R25,R26)
 76 [-]: LOADK     R25 K15      ; R25 := "\r"
 77 [-]: GETGLOBAL R26 K12      ; R26 := 0xE6DC43B0
 78 [-]: LOADK     R27 K16      ; R27 := "/Lotus/Language/Dojo/CustomObstacleCourseTargetDummyRemaning"
 79 [-]: NEWTABLE  R28 0 1      ; R28 := {}
 80 [-]: SETTABLE  R28 K17 R9   ; R28["DUMMIES"] := R9
 81 [-]: CALL      R26 3 2      ; R26 := R26(R27,R28)
 82 [-]: CONCAT    R23 R24 R26  ; R23 := R24 .. R25 .. R26
 83 [-]: JMP       99           ; PC := 99
 84 [-]: LT        0 K1 R1      ; if 0 >= R1 then PC := 93
 85 [-]: JMP       93           ; PC := 93
 86 [-]: GETGLOBAL R24 K12      ; R24 := 0xE6DC43B0
 87 [-]: LOADK     R25 K13      ; R25 := "/Lotus/Language/Dojo/CustomObstacleCourseCheckpointRemaning"
 88 [-]: NEWTABLE  R26 0 1      ; R26 := {}
 89 [-]: SETTABLE  R26 K14 R1   ; R26["CHECKPOINTS"] := R1
 90 [-]: CALL      R24 3 2      ; R24 := R24(R25,R26)
 91 [-]: MOVE      R23 R24      ; R23 := R24
 92 [-]: JMP       99           ; PC := 99
 93 [-]: GETGLOBAL R24 K12      ; R24 := 0xE6DC43B0
 94 [-]: LOADK     R25 K16      ; R25 := "/Lotus/Language/Dojo/CustomObstacleCourseTargetDummyRemaning"
 95 [-]: NEWTABLE  R26 0 1      ; R26 := {}
 96 [-]: SETTABLE  R26 K17 R9   ; R26["DUMMIES"] := R9
 97 [-]: CALL      R24 3 2      ; R24 := R24(R25,R26)
 98 [-]: MOVE      R23 R24      ; R23 := R24
 99 [-]: GETGLOBAL R24 K18      ; R24 := gGameRules
100 [-]: SELF      R24 R24 K19  ; R25 := R24; R24 := R24["0x362A2E36"]
101 [-]: SELF      R26 R0 K20   ; R27 := R0; R26 := R0["0xDE5882DD"]
102 [-]: CALL      R26 2 2      ; R26 := R26(R27)
103 [-]: MOVE      R27 R23      ; R27 := R23
104 [-]: LOADK     R28 K11      ; R28 := ""
105 [-]: LOADK     R29 K1       ; R29 := 0
106 [-]: LOADK     R30 K21      ; R30 := 3
107 [-]: MOVE      R31 R0       ; R31 := R0
108 [-]: CALL      R24 8 1      ; R24(R25,R26,R27,R28,R29,R30,R31)
109 [-]: MOVE      R24 R0       ; R24 := R0
110 [-]: RETURN    R24 2        ; return R24
111 [-]: JMP       114          ; PC := 114
112 [-]: SELF      R24 R21 K22  ; R25 := R21; R24 := R21["0x2DB1272F"]
113 [-]: CALL      R24 2 1      ; R24(R25)
114 [-]: FORLOOP   R17 54       ; R17 += R19; if R17 <= R18 then begin PC := 54; R20 := R17 end
115 [-]: MOVE      R24 R1       ; R24 := R1
116 [-]: RETURN    R24 2        ; return R24
117 [-]: RETURN    R0 1         ; return 


; Function #29:
;
; Name:            
; Defined at line: 430
; #Upvalues:       3
; #Parameters:     1
; Is_vararg:       0
; Max Stack Size:  13

  1 [-]: GETGLOBAL R1 K0        ; R1 := gRegion
  2 [-]: SELF      R1 R1 K1     ; R2 := R1; R1 := R1["0xA559F558"]
  3 [-]: CALL      R1 2 2       ; R1 := R1(R2)
  4 [-]: TEST      R1 1         ; if R1 then PC := 7
  5 [-]: JMP       7            ; PC := 7
  6 [-]: RETURN    R0 1         ; return 
  7 [-]: GETGLOBAL R1 K2        ; R1 := gGameRules
  8 [-]: TEST      R1 0         ; if not R1 then PC := 16
  9 [-]: JMP       16           ; PC := 16
 10 [-]: GETGLOBAL R1 K2        ; R1 := gGameRules
 11 [-]: SELF      R1 R1 K3     ; R2 := R1; R1 := R1["0x8B598ED4"]
 12 [-]: GETGLOBAL R3 K4        ; R3 := dojoCustomObstacleCourseGameRules
 13 [-]: CALL      R1 3 2       ; R1 := R1(R2,R3)
 14 [-]: TEST      R1 1         ; if R1 then PC := 17
 15 [-]: JMP       17           ; PC := 17
 16 [-]: RETURN    R0 1         ; return 
 17 [-]: GETUPVAL  R1 U0        ; R1 := U0
 18 [-]: CALL      R1 1 2       ; R1 := R1()
 19 [-]: GETGLOBAL R2 K5        ; R2 := Lotus_Game
 20 [-]: GETTABLE  R2 R2 K6     ; R2 := R2["LotusObstacleCourseGameRules_RS_RUNNING"]
 21 [-]: EQ        1 R1 R2      ; if R1 == R2 then PC := 24
 22 [-]: JMP       24           ; PC := 24
 23 [-]: RETURN    R0 1         ; return 
 24 [-]: SELF      R1 R0 K7     ; R2 := R0; R1 := R0["0xB002826D"]
 25 [-]: CALL      R1 2 2       ; R1 := R1(R2)
 26 [-]: GETGLOBAL R2 K8        ; R2 := 0x400E7765
 27 [-]: MOVE      R3 R1        ; R3 := R1
 28 [-]: CALL      R2 2 2       ; R2 := R2(R3)
 29 [-]: TEST      R2 1         ; if R2 then PC := 33
 30 [-]: JMP       33           ; PC := 33
 31 [-]: EQ        0 R0 R1      ; if R0 ~= R1 then PC := 34
 32 [-]: JMP       34           ; PC := 34
 33 [-]: RETURN    R0 1         ; return 
 34 [-]: SELF      R2 R0 K9     ; R3 := R0; R2 := R0["0xE2B32C65"]
 35 [-]: CALL      R2 2 2       ; R2 := R2(R3)
 36 [-]: GETGLOBAL R3 K10       ; R3 := dojoTargetType
 37 [-]: EQ        0 R2 R3      ; if R2 ~= R3 then PC := 71
 38 [-]: JMP       71           ; PC := 71
 39 [-]: GETGLOBAL R2 K11       ; R2 := math
 40 [-]: GETTABLE  R2 R2 K12    ; R2 := R2["0x8B011038"]
 41 [-]: LOADK     R3 K13       ; R3 := 0
 42 [-]: GETGLOBAL R4 K2        ; R4 := gGameRules
 43 [-]: SELF      R4 R4 K14    ; R5 := R4; R4 := R4["0x4503D699"]
 44 [-]: GETUPVAL  R6 U1        ; R6 := U1
 45 [-]: CALL      R4 3 2       ; R4 := R4(R5,R6)
 46 [-]: GETGLOBAL R5 K15       ; R5 := targetTimeIncrease
 47 [-]: SUB       R4 R4 R5     ; R4 := R4 - R5
 48 [-]: CALL      R2 3 2       ; R2 := R2(R3,R4)
 49 [-]: GETGLOBAL R3 K2        ; R3 := gGameRules
 50 [-]: SELF      R3 R3 K16    ; R4 := R3; R3 := R3["0xF1349880"]
 51 [-]: GETUPVAL  R5 U1        ; R5 := U1
 52 [-]: MOVE      R6 R2        ; R6 := R2
 53 [-]: CALL      R3 4 1       ; R3(R4,R5,R6)
 54 [-]: GETGLOBAL R3 K2        ; R3 := gGameRules
 55 [-]: SELF      R3 R3 K17    ; R4 := R3; R3 := R3["0xAF43EF6E"]
 56 [-]: MOVE      R5 R2        ; R5 := R2
 57 [-]: CALL      R3 3 1       ; R3(R4,R5)
 58 [-]: GETGLOBAL R3 K2        ; R3 := gGameRules
 59 [-]: SELF      R3 R3 K18    ; R4 := R3; R3 := R3["0x362A2E36"]
 60 [-]: SELF      R5 R1 K19    ; R6 := R1; R5 := R1["0xDE5882DD"]
 61 [-]: CALL      R5 2 2       ; R5 := R5(R6)
 62 [-]: GETUPVAL  R6 U2        ; R6 := U2
 63 [-]: LOADK     R7 K20       ; R7 := ""
 64 [-]: LOADK     R8 K13       ; R8 := 0
 65 [-]: LOADK     R9 K21       ; R9 := 2
 66 [-]: MOVE      R10 R1       ; R10 := R1
 67 [-]: LOADK     R11 K22      ; R11 := "SECONDS"
 68 [-]: GETGLOBAL R12 K15      ; R12 := targetTimeIncrease
 69 [-]: CALL      R3 10 1      ; R3(R4,R5,R6,R7,R8,R9,R10,R11,R12)
 70 [-]: JMP       86           ; PC := 86
 71 [-]: SELF      R3 R0 K9     ; R4 := R0; R3 := R0["0xE2B32C65"]
 72 [-]: CALL      R3 2 2       ; R3 := R3(R4)
 73 [-]: GETGLOBAL R4 K23       ; R4 := destructibleDummyType
 74 [-]: EQ        0 R3 R4      ; if R3 ~= R4 then PC := 86
 75 [-]: JMP       86           ; PC := 86
 76 [-]: GETGLOBAL R3 K2        ; R3 := gGameRules
 77 [-]: SELF      R3 R3 K18    ; R4 := R3; R3 := R3["0x362A2E36"]
 78 [-]: SELF      R5 R1 K19    ; R6 := R1; R5 := R1["0xDE5882DD"]
 79 [-]: CALL      R5 2 2       ; R5 := R5(R6)
 80 [-]: LOADK     R6 K24       ; R6 := "/Lotus/Language/Dojo/CustomObstacleDummyDestroyed"
 81 [-]: LOADK     R7 K20       ; R7 := ""
 82 [-]: LOADK     R8 K13       ; R8 := 0
 83 [-]: LOADK     R9 K21       ; R9 := 2
 84 [-]: MOVE      R10 R1       ; R10 := R1
 85 [-]: CALL      R3 8 1       ; R3(R4,R5,R6,R7,R8,R9,R10)
 86 [-]: RETURN    R0 1         ; return 


; Function #30:
;
; Name:            
; Defined at line: 459
; #Upvalues:       3
; #Parameters:     0
; Is_vararg:       0
; Max Stack Size:  35

  1 [-]: GETGLOBAL R0 K0        ; R0 := gRegion
  2 [-]: SELF      R0 R0 K1     ; R1 := R0; R0 := R0["0x9139A00"]
  3 [-]: GETGLOBAL R2 K2        ; R2 := dojoVanishingPlatformType
  4 [-]: CALL      R0 3 2       ; R0 := R0(R1,R2)
  5 [-]: LOADK     R1 K3        ; R1 := 1
  6 [-]: LEN       R2 R0        ; R2 := # R0
  7 [-]: LOADK     R3 K3        ; R3 := 1
  8 [-]: FORPREP   R1 55        ; R1 -= R3; PC := 55
  9 [-]: GETTABLE  R5 R0 R4     ; R5 := R0[R4]
 10 [-]: SELF      R6 R5 K4     ; R7 := R5; R6 := R5["0xD610586B"]
 11 [-]: LOADK     R8 K5        ; R8 := 0
 12 [-]: CALL      R6 3 1       ; R6(R7,R8)
 13 [-]: SELF      R6 R5 K6     ; R7 := R5; R6 := R5["0x7DBDDA0B"]
 14 [-]: MOVE      R8 R1        ; R8 := R1
 15 [-]: MOVE      R9 R1        ; R9 := R1
 16 [-]: CALL      R6 4 1       ; R6(R7,R8,R9)
 17 [-]: SELF      R6 R5 K7     ; R7 := R5; R6 := R5["0x15D4DAEE"]
 18 [-]: GETGLOBAL R8 K8        ; R8 := gLotusEffectDecorationType
 19 [-]: CALL      R6 3 2       ; R6 := R6(R7,R8)
 20 [-]: LOADK     R7 K3        ; R7 := 1
 21 [-]: LEN       R8 R6        ; R8 := # R6
 22 [-]: LOADK     R9 K3        ; R9 := 1
 23 [-]: FORPREP   R7 34        ; R7 -= R9; PC := 34
 24 [-]: GETGLOBAL R11 K9       ; R11 := 0x400E7765
 25 [-]: GETTABLE  R12 R6 R10   ; R12 := R6[R10]
 26 [-]: CALL      R11 2 2      ; R11 := R11(R12)
 27 [-]: TEST      R11 1        ; if R11 then PC := 34
 28 [-]: JMP       34           ; PC := 34
 29 [-]: GETTABLE  R11 R6 R10   ; R11 := R6[R10]
 30 [-]: SELF      R11 R11 K10  ; R12 := R11; R11 := R11["0xD124E361"]
 31 [-]: GETUPVAL  R13 U0       ; R13 := U0
 32 [-]: LOADK     R14 K3       ; R14 := 1
 33 [-]: CALL      R11 4 1      ; R11(R12,R13,R14)
 34 [-]: FORLOOP   R7 24        ; R7 += R9; if R7 <= R8 then begin PC := 24; R10 := R7 end
 35 [-]: SELF      R11 R5 K7    ; R12 := R5; R11 := R5["0x15D4DAEE"]
 36 [-]: GETGLOBAL R13 K11      ; R13 := gScriptTriggerType
 37 [-]: CALL      R11 3 2      ; R11 := R11(R12,R13)
 38 [-]: MOVE      R6 R11       ; R6 := R11
 39 [-]: LOADK     R11 K3       ; R11 := 1
 40 [-]: LEN       R12 R6       ; R12 := # R6
 41 [-]: LOADK     R13 K3       ; R13 := 1
 42 [-]: FORPREP   R11 54       ; R11 -= R13; PC := 54
 43 [-]: GETGLOBAL R15 K9       ; R15 := 0x400E7765
 44 [-]: GETTABLE  R16 R6 R14   ; R16 := R6[R14]
 45 [-]: CALL      R15 2 2      ; R15 := R15(R16)
 46 [-]: TEST      R15 1        ; if R15 then PC := 54
 47 [-]: JMP       54           ; PC := 54
 48 [-]: GETTABLE  R15 R6 R14   ; R15 := R6[R14]
 49 [-]: SELF      R15 R15 K12  ; R16 := R15; R15 := R15["0xC5E91BA6"]
 50 [-]: CALL      R15 2 1      ; R15(R16)
 51 [-]: GETTABLE  R15 R6 R14   ; R15 := R6[R14]
 52 [-]: SELF      R15 R15 K13  ; R16 := R15; R15 := R15["0xC2A0432E"]
 53 [-]: CALL      R15 2 1      ; R15(R16)
 54 [-]: FORLOOP   R11 43       ; R11 += R13; if R11 <= R12 then begin PC := 43; R14 := R11 end
 55 [-]: FORLOOP   R1 9         ; R1 += R3; if R1 <= R2 then begin PC := 9; R4 := R1 end
 56 [-]: GETGLOBAL R15 K0       ; R15 := gRegion
 57 [-]: SELF      R15 R15 K1   ; R16 := R15; R15 := R15["0x9139A00"]
 58 [-]: GETGLOBAL R17 K14      ; R17 := dojoEndTriggerType
 59 [-]: CALL      R15 3 2      ; R15 := R15(R16,R17)
 60 [-]: LOADK     R16 K3       ; R16 := 1
 61 [-]: LEN       R17 R15      ; R17 := # R15
 62 [-]: LOADK     R18 K3       ; R18 := 1
 63 [-]: FORPREP   R16 67       ; R16 -= R18; PC := 67
 64 [-]: GETTABLE  R20 R15 R19  ; R20 := R15[R19]
 65 [-]: SELF      R21 R20 K12  ; R22 := R20; R21 := R20["0xC5E91BA6"]
 66 [-]: CALL      R21 2 1      ; R21(R22)
 67 [-]: FORLOOP   R16 64       ; R16 += R18; if R16 <= R17 then begin PC := 64; R19 := R16 end
 68 [-]: GETGLOBAL R21 K0       ; R21 := gRegion
 69 [-]: SELF      R21 R21 K1   ; R22 := R21; R21 := R21["0x9139A00"]
 70 [-]: GETGLOBAL R23 K15      ; R23 := dojoCheckpointTriggerType
 71 [-]: CALL      R21 3 2      ; R21 := R21(R22,R23)
 72 [-]: LOADK     R22 K3       ; R22 := 1
 73 [-]: LEN       R23 R21      ; R23 := # R21
 74 [-]: LOADK     R24 K3       ; R24 := 1
 75 [-]: FORPREP   R22 79       ; R22 -= R24; PC := 79
 76 [-]: GETTABLE  R26 R21 R25  ; R26 := R21[R25]
 77 [-]: SELF      R27 R26 K12  ; R28 := R26; R27 := R26["0xC5E91BA6"]
 78 [-]: CALL      R27 2 1      ; R27(R28)
 79 [-]: FORLOOP   R22 76       ; R22 += R24; if R22 <= R23 then begin PC := 76; R25 := R22 end
 80 [-]: GETGLOBAL R27 K9       ; R27 := 0x400E7765
 81 [-]: GETGLOBAL R28 K16      ; R28 := _T
 82 [-]: GETTABLE  R28 R28 K17  ; R28 := R28["DojoMgr"]
 83 [-]: CALL      R27 2 2      ; R27 := R27(R28)
 84 [-]: TEST      R27 1        ; if R27 then PC := 111
 85 [-]: JMP       111          ; PC := 111
 86 [-]: GETGLOBAL R27 K9       ; R27 := 0x400E7765
 87 [-]: GETGLOBAL R28 K16      ; R28 := _T
 88 [-]: GETTABLE  R28 R28 K17  ; R28 := R28["DojoMgr"]
 89 [-]: GETTABLE  R28 R28 K18  ; R28 := R28["mDojo"]
 90 [-]: CALL      R27 2 2      ; R27 := R27(R28)
 91 [-]: TEST      R27 1        ; if R27 then PC := 111
 92 [-]: JMP       111          ; PC := 111
 93 [-]: GETGLOBAL R27 K0       ; R27 := gRegion
 94 [-]: SELF      R27 R27 K1   ; R28 := R27; R27 := R27["0x9139A00"]
 95 [-]: GETGLOBAL R29 K19      ; R29 := dojoDummyType
 96 [-]: CALL      R27 3 2      ; R27 := R27(R28,R29)
 97 [-]: LOADK     R28 K3       ; R28 := 1
 98 [-]: LEN       R29 R27      ; R29 := # R27
 99 [-]: LOADK     R30 K3       ; R30 := 1
100 [-]: FORPREP   R28 109      ; R28 -= R30; PC := 109
101 [-]: GETTABLE  R32 R27 R31  ; R32 := R27[R31]
102 [-]: GETGLOBAL R33 K9       ; R33 := 0x400E7765
103 [-]: MOVE      R34 R32      ; R34 := R32
104 [-]: CALL      R33 2 2      ; R33 := R33(R34)
105 [-]: TEST      R33 1        ; if R33 then PC := 109
106 [-]: JMP       109          ; PC := 109
107 [-]: SELF      R33 R32 K20  ; R34 := R32; R33 := R32["0x97382E1"]
108 [-]: CALL      R33 2 1      ; R33(R34)
109 [-]: FORLOOP   R28 101      ; R28 += R30; if R28 <= R29 then begin PC := 101; R31 := R28 end
110 [-]: JMP       114          ; PC := 114
111 [-]: GETGLOBAL R33 K21      ; R33 := 0x93B1256B
112 [-]: LOADK     R34 K22      ; R34 := "[Obstacle Course] Error, DojoMgr was null when attempting to reload destructible decos?"
113 [-]: CALL      R33 2 1      ; R33(R34)
114 [-]: GETUPVAL  R33 U1       ; R33 := U1
115 [-]: CALL      R33 1 1      ; R33()
116 [-]: GETUPVAL  R33 U2       ; R33 := U2
117 [-]: CALL      R33 1 1      ; R33()
118 [-]: RETURN    R0 1         ; return 


; Function #31:
;
; Name:            
; Defined at line: 511
; #Upvalues:       5
; #Parameters:     2
; Is_vararg:       0
; Max Stack Size:  12

  1 [-]: GETGLOBAL R2 K0        ; R2 := gGameRules
  2 [-]: TEST      R2 0         ; if not R2 then PC := 10
  3 [-]: JMP       10           ; PC := 10
  4 [-]: GETGLOBAL R2 K0        ; R2 := gGameRules
  5 [-]: SELF      R2 R2 K1     ; R3 := R2; R2 := R2["0x8B598ED4"]
  6 [-]: GETGLOBAL R4 K2        ; R4 := dojoCustomObstacleCourseGameRules
  7 [-]: CALL      R2 3 2       ; R2 := R2(R3,R4)
  8 [-]: TEST      R2 1         ; if R2 then PC := 11
  9 [-]: JMP       11           ; PC := 11
 10 [-]: RETURN    R0 1         ; return 
 11 [-]: GETUPVAL  R2 U0        ; R2 := U0
 12 [-]: CALL      R2 1 2       ; R2 := R2()
 13 [-]: GETUPVAL  R3 U0        ; R3 := U0
 14 [-]: CALL      R3 1 2       ; R3 := R3()
 15 [-]: GETGLOBAL R4 K3        ; R4 := Lotus_Game
 16 [-]: GETTABLE  R4 R4 K4     ; R4 := R4["LotusObstacleCourseGameRules_RS_IDLE"]
 17 [-]: EQ        1 R3 R4      ; if R3 == R4 then PC := 20
 18 [-]: JMP       20           ; PC := 20
 19 [-]: RETURN    R0 1         ; return 
 20 [-]: GETUPVAL  R3 U1        ; R3 := U1
 21 [-]: CALL      R3 1 2       ; R3 := R3()
 22 [-]: GETUPVAL  R4 U2        ; R4 := U2
 23 [-]: CALL      R4 1 1       ; R4()
 24 [-]: GETGLOBAL R4 K5        ; R4 := gRegion
 25 [-]: SELF      R4 R4 K6     ; R5 := R4; R4 := R4["0xA559F558"]
 26 [-]: CALL      R4 2 2       ; R4 := R4(R5)
 27 [-]: TEST      R4 1         ; if R4 then PC := 30
 28 [-]: JMP       30           ; PC := 30
 29 [-]: RETURN    R0 1         ; return 
 30 [-]: GETUPVAL  R4 U3        ; R4 := U3
 31 [-]: CALL      R4 1 1       ; R4()
 32 [-]: GETGLOBAL R4 K0        ; R4 := gGameRules
 33 [-]: SELF      R4 R4 K7     ; R5 := R4; R4 := R4["0x362A2E36"]
 34 [-]: SELF      R6 R1 K8     ; R7 := R1; R6 := R1["0xDE5882DD"]
 35 [-]: CALL      R6 2 2       ; R6 := R6(R7)
 36 [-]: LOADK     R7 K9        ; R7 := "/Lotus/Language/Game/BeginObstacleCourse"
 37 [-]: LOADK     R8 K10       ; R8 := ""
 38 [-]: LOADK     R9 K11       ; R9 := 0
 39 [-]: LOADK     R10 K12      ; R10 := 2
 40 [-]: MOVE      R11 R1       ; R11 := R1
 41 [-]: CALL      R4 8 1       ; R4(R5,R6,R7,R8,R9,R10,R11)
 42 [-]: GETGLOBAL R4 K0        ; R4 := gGameRules
 43 [-]: SELF      R4 R4 K13    ; R5 := R4; R4 := R4["0xF11B6ABD"]
 44 [-]: GETUPVAL  R6 U4        ; R6 := U4
 45 [-]: GETGLOBAL R7 K14       ; R7 := 0xEC274B1A
 46 [-]: CALL      R7 1 2       ; R7 := R7()
 47 [-]: LOADK     R8 K11       ; R8 := 0
 48 [-]: MOVE      R9 R0        ; R9 := R0
 49 [-]: MOVE      R10 R1       ; R10 := R1
 50 [-]: MOVE      R11 R1       ; R11 := R1
 51 [-]: CALL      R4 8 1       ; R4(R5,R6,R7,R8,R9,R10,R11)
 52 [-]: GETGLOBAL R4 K0        ; R4 := gGameRules
 53 [-]: SELF      R4 R4 K15    ; R5 := R4; R4 := R4["0xFD9FB6BF"]
 54 [-]: GETUPVAL  R6 U4        ; R6 := U4
 55 [-]: MOVE      R7 R1        ; R7 := R1
 56 [-]: CALL      R4 4 1       ; R4(R5,R6,R7)
 57 [-]: SELF      R4 R1 K8     ; R5 := R1; R4 := R1["0xDE5882DD"]
 58 [-]: CALL      R4 2 2       ; R4 := R4(R5)
 59 [-]: SELF      R4 R4 K16    ; R5 := R4; R4 := R4["0xCE0170C"]
 60 [-]: GETUPVAL  R6 U4        ; R6 := U4
 61 [-]: CALL      R4 3 1       ; R4(R5,R6)
 62 [-]: SELF      R4 R3 K17    ; R5 := R3; R4 := R3["0x9FB2FA54"]
 63 [-]: MOVE      R6 R1        ; R6 := R1
 64 [-]: CALL      R4 3 1       ; R4(R5,R6)
 65 [-]: RETURN    R0 1         ; return 


; Function #32:
;
; Name:            
; Defined at line: 539
; #Upvalues:       0
; #Parameters:     1
; Is_vararg:       0
; Max Stack Size:  9

  1 [-]: GETGLOBAL R1 K0        ; R1 := gGameRules
  2 [-]: SELF      R1 R1 K1     ; R2 := R1; R1 := R1["0x362A2E36"]
  3 [-]: SELF      R3 R0 K2     ; R4 := R0; R3 := R0["0xDE5882DD"]
  4 [-]: CALL      R3 2 2       ; R3 := R3(R4)
  5 [-]: LOADK     R4 K3        ; R4 := "/Lotus/Language/Dojo/CustomObstacleCheckpointReached"
  6 [-]: LOADK     R5 K4        ; R5 := ""
  7 [-]: LOADK     R6 K5        ; R6 := 0
  8 [-]: LOADK     R7 K6        ; R7 := 2
  9 [-]: MOVE      R8 R1        ; R8 := R1
 10 [-]: CALL      R1 8 1       ; R1(R2,R3,R4,R5,R6,R7,R8)
 11 [-]: RETURN    R0 1         ; return 


; Function #33:
;
; Name:            
; Defined at line: 544
; #Upvalues:       4
; #Parameters:     2
; Is_vararg:       0
; Max Stack Size:  6

  1 [-]: GETGLOBAL R2 K0        ; R2 := gRegion
  2 [-]: SELF      R2 R2 K1     ; R3 := R2; R2 := R2["0xA559F558"]
  3 [-]: CALL      R2 2 2       ; R2 := R2(R3)
  4 [-]: TEST      R2 1         ; if R2 then PC := 7
  5 [-]: JMP       7            ; PC := 7
  6 [-]: RETURN    R0 1         ; return 
  7 [-]: GETGLOBAL R2 K2        ; R2 := gGameRules
  8 [-]: TEST      R2 0         ; if not R2 then PC := 16
  9 [-]: JMP       16           ; PC := 16
 10 [-]: GETGLOBAL R2 K2        ; R2 := gGameRules
 11 [-]: SELF      R2 R2 K3     ; R3 := R2; R2 := R2["0x8B598ED4"]
 12 [-]: GETGLOBAL R4 K4        ; R4 := dojoCustomObstacleCourseGameRules
 13 [-]: CALL      R2 3 2       ; R2 := R2(R3,R4)
 14 [-]: TEST      R2 1         ; if R2 then PC := 17
 15 [-]: JMP       17           ; PC := 17
 16 [-]: RETURN    R0 1         ; return 
 17 [-]: GETUPVAL  R2 U0        ; R2 := U0
 18 [-]: CALL      R2 1 2       ; R2 := R2()
 19 [-]: GETGLOBAL R3 K5        ; R3 := Lotus_Game
 20 [-]: GETTABLE  R3 R3 K6     ; R3 := R3["LotusObstacleCourseGameRules_RS_RUNNING"]
 21 [-]: EQ        1 R2 R3      ; if R2 == R3 then PC := 24
 22 [-]: JMP       24           ; PC := 24
 23 [-]: RETURN    R0 1         ; return 
 24 [-]: SELF      R2 R0 K7     ; R3 := R0; R2 := R0["0xB1627322"]
 25 [-]: CALL      R2 2 2       ; R2 := R2(R3)
 26 [-]: SELF      R3 R0 K3     ; R4 := R0; R3 := R0["0x8B598ED4"]
 27 [-]: GETGLOBAL R5 K8        ; R5 := dojoEndTriggerType
 28 [-]: CALL      R3 3 2       ; R3 := R3(R4,R5)
 29 [-]: TEST      R3 0         ; if not R3 then PC := 40
 30 [-]: JMP       40           ; PC := 40
 31 [-]: GETUPVAL  R3 U1        ; R3 := U1
 32 [-]: MOVE      R4 R1        ; R4 := R1
 33 [-]: CALL      R3 2 2       ; R3 := R3(R4)
 34 [-]: TEST      R3 0         ; if not R3 then PC := 47
 35 [-]: JMP       47           ; PC := 47
 36 [-]: GETUPVAL  R3 U2        ; R3 := U2
 37 [-]: MOVE      R4 R1        ; R4 := R1
 38 [-]: CALL      R3 2 1       ; R3(R4)
 39 [-]: JMP       47           ; PC := 47
 40 [-]: TEST      R2 0         ; if not R2 then PC := 47
 41 [-]: JMP       47           ; PC := 47
 42 [-]: SELF      R3 R0 K9     ; R4 := R0; R3 := R0["0x2DB1272F"]
 43 [-]: CALL      R3 2 1       ; R3(R4)
 44 [-]: GETUPVAL  R3 U3        ; R3 := U3
 45 [-]: MOVE      R4 R1        ; R4 := R1
 46 [-]: CALL      R3 2 1       ; R3(R4)
 47 [-]: RETURN    R0 1         ; return 


; Function #34:
;
; Name:            
; Defined at line: 570
; #Upvalues:       3
; #Parameters:     2
; Is_vararg:       0
; Max Stack Size:  26

  1 [-]: GETGLOBAL R2 K0        ; R2 := 0x400E7765
  2 [-]: MOVE      R3 R1        ; R3 := R1
  3 [-]: CALL      R2 2 2       ; R2 := R2(R3)
  4 [-]: TEST      R2 0         ; if not R2 then PC := 7
  5 [-]: JMP       7            ; PC := 7
  6 [-]: RETURN    R0 1         ; return 
  7 [-]: MOVE      R2 R1        ; R2 := R1
  8 [-]: GETGLOBAL R3 K1        ; R3 := gRegion
  9 [-]: SELF      R3 R3 K2     ; R4 := R3; R3 := R3["0x3E2F6BF"]
 10 [-]: CALL      R3 2 2       ; R3 := R3(R4)
 11 [-]: EQ        0 R2 R3      ; if R2 ~= R3 then PC := 14
 12 [-]: JMP       14           ; PC := 14
 13 [-]: RETURN    R0 1         ; return 
 14 [-]: GETGLOBAL R2 K3        ; R2 := gGameRules
 15 [-]: SELF      R2 R2 K4     ; R3 := R2; R2 := R2["0x8B598ED4"]
 16 [-]: GETGLOBAL R4 K5        ; R4 := dojoCustomObstacleCourseGameRules
 17 [-]: CALL      R2 3 2       ; R2 := R2(R3,R4)
 18 [-]: TEST      R2 1         ; if R2 then PC := 225
 19 [-]: JMP       225          ; PC := 225
 20 [-]: GETGLOBAL R2 K6        ; R2 := gMatchingService
 21 [-]: SELF      R2 R2 K7     ; R3 := R2; R2 := R2["0x8E578E9"]
 22 [-]: CALL      R2 2 2       ; R2 := R2(R3)
 23 [-]: TEST      R2 0         ; if not R2 then PC := 30
 24 [-]: JMP       30           ; PC := 30
 25 [-]: GETUPVAL  R2 U0        ; R2 := U0
 26 [-]: GETTABLE  R2 R2 K8     ; R2 := R2["0xB11F032"]
 27 [-]: LOADK     R3 K9        ; R3 := "/Lotus/Language/Dojo/CustomObstacleCourseLoading"
 28 [-]: CALL      R2 2 1       ; R2(R3)
 29 [-]: RETURN    R0 1         ; return 
 30 [-]: GETUPVAL  R2 U1        ; R2 := U1
 31 [-]: MOVE      R3 R1        ; R3 := R1
 32 [-]: CALL      R2 2 2       ; R2 := R2(R3)
 33 [-]: GETGLOBAL R3 K1        ; R3 := gRegion
 34 [-]: SELF      R3 R3 K10    ; R4 := R3; R3 := R3["0x9139A00"]
 35 [-]: GETGLOBAL R5 K11       ; R5 := dojoStartDecoType
 36 [-]: CALL      R3 3 2       ; R3 := R3(R4,R5)
 37 [-]: GETGLOBAL R4 K1        ; R4 := gRegion
 38 [-]: SELF      R4 R4 K10    ; R5 := R4; R4 := R4["0x9139A00"]
 39 [-]: GETGLOBAL R6 K12       ; R6 := dojoEndDecoType
 40 [-]: CALL      R4 3 2       ; R4 := R4(R5,R6)
 41 [-]: LOADNIL   R5 R5        ; R5 := nil
 42 [-]: GETGLOBAL R6 K0        ; R6 := 0x400E7765
 43 [-]: MOVE      R7 R2        ; R7 := R2
 44 [-]: CALL      R6 2 2       ; R6 := R6(R7)
 45 [-]: TEST      R6 1         ; if R6 then PC := 136
 46 [-]: JMP       136          ; PC := 136
 47 [-]: EQ        1 R2 K13     ; if R2 == "" then PC := 136
 48 [-]: JMP       136          ; PC := 136
 49 [-]: LOADK     R6 K14       ; R6 := 1
 50 [-]: LEN       R7 R3        ; R7 := # R3
 51 [-]: LOADK     R8 K14       ; R8 := 1
 52 [-]: FORPREP   R6 83        ; R6 -= R8; PC := 83
 53 [-]: GETGLOBAL R10 K15      ; R10 := _T
 54 [-]: GETTABLE  R10 R10 K16  ; R10 := R10["DojoMgr"]
 55 [-]: SELF      R10 R10 K17  ; R11 := R10; R10 := R10["0xBF9A2C88"]
 56 [-]: GETTABLE  R12 R3 R9    ; R12 := R3[R9]
 57 [-]: SELF      R12 R12 K18  ; R13 := R12; R12 := R12["0x72E5DB62"]
 58 [-]: CALL      R12 2 2      ; R12 := R12(R13)
 59 [-]: SELF      R12 R12 K19  ; R13 := R12; R12 := R12["0x61FDC81"]
 60 [-]: CALL      R12 2 0      ; R12,... := R12(R13)
 61 [-]: CALL      R10 0 2      ; R10 := R10(R11,...)
 62 [-]: GETUPVAL  R11 U2       ; R11 := U2
 63 [-]: GETTABLE  R12 R3 R9    ; R12 := R3[R9]
 64 [-]: GETTABLE  R13 R10 K20  ; R13 := R10["id"]
 65 [-]: CALL      R11 3 2      ; R11 := R11(R12,R13)
 66 [-]: GETTABLE  R12 R10 K20  ; R12 := R10["id"]
 67 [-]: EQ        0 R12 R2     ; if R12 ~= R2 then PC := 83
 68 [-]: JMP       83           ; PC := 83
 69 [-]: GETGLOBAL R12 K0       ; R12 := 0x400E7765
 70 [-]: MOVE      R13 R11      ; R13 := R11
 71 [-]: CALL      R12 2 2      ; R12 := R12(R13)
 72 [-]: TEST      R12 1        ; if R12 then PC := 83
 73 [-]: JMP       83           ; PC := 83
 74 [-]: SELF      R12 R11 K21  ; R13 := R11; R12 := R11["0xEA470E3C"]
 75 [-]: CALL      R12 2 2      ; R12 := R12(R13)
 76 [-]: TEST      R12 1        ; if R12 then PC := 83
 77 [-]: JMP       83           ; PC := 83
 78 [-]: SELF      R12 R11 K22  ; R13 := R11; R12 := R11["0x89C671D6"]
 79 [-]: CALL      R12 2 2      ; R12 := R12(R13)
 80 [-]: TEST      R12 1        ; if R12 then PC := 83
 81 [-]: JMP       83           ; PC := 83
 82 [-]: GETTABLE  R5 R3 R9     ; R5 := R3[R9]
 83 [-]: FORLOOP   R6 53        ; R6 += R8; if R6 <= R7 then begin PC := 53; R9 := R6 end
 84 [-]: GETGLOBAL R12 K15      ; R12 := _T
 85 [-]: NEWTABLE  R13 0 0      ; R13 := {}
 86 [-]: SETTABLE  R12 K23 R13  ; R12["EndTriggers"] := R13
 87 [-]: GETGLOBAL R12 K15      ; R12 := _T
 88 [-]: NEWTABLE  R13 0 0      ; R13 := {}
 89 [-]: SETTABLE  R12 K24 R13  ; R12["TriggerCompletion"] := R13
 90 [-]: LOADK     R12 K14      ; R12 := 1
 91 [-]: LEN       R13 R4       ; R13 := # R4
 92 [-]: LOADK     R14 K14      ; R14 := 1
 93 [-]: FORPREP   R12 135      ; R12 -= R14; PC := 135
 94 [-]: GETGLOBAL R16 K15      ; R16 := _T
 95 [-]: GETTABLE  R16 R16 K16  ; R16 := R16["DojoMgr"]
 96 [-]: SELF      R16 R16 K17  ; R17 := R16; R16 := R16["0xBF9A2C88"]
 97 [-]: GETTABLE  R18 R4 R15   ; R18 := R4[R15]
 98 [-]: SELF      R18 R18 K18  ; R19 := R18; R18 := R18["0x72E5DB62"]
 99 [-]: CALL      R18 2 2      ; R18 := R18(R19)
100 [-]: SELF      R18 R18 K19  ; R19 := R18; R18 := R18["0x61FDC81"]
101 [-]: CALL      R18 2 0      ; R18,... := R18(R19)
102 [-]: CALL      R16 0 2      ; R16 := R16(R17,...)
103 [-]: GETUPVAL  R17 U2       ; R17 := U2
104 [-]: GETTABLE  R18 R4 R15   ; R18 := R4[R15]
105 [-]: GETTABLE  R19 R16 K20  ; R19 := R16["id"]
106 [-]: CALL      R17 3 2      ; R17 := R17(R18,R19)
107 [-]: GETTABLE  R18 R16 K20  ; R18 := R16["id"]
108 [-]: EQ        0 R18 R2     ; if R18 ~= R2 then PC := 135
109 [-]: JMP       135          ; PC := 135
110 [-]: GETGLOBAL R18 K0       ; R18 := 0x400E7765
111 [-]: MOVE      R19 R17      ; R19 := R17
112 [-]: CALL      R18 2 2      ; R18 := R18(R19)
113 [-]: TEST      R18 1        ; if R18 then PC := 135
114 [-]: JMP       135          ; PC := 135
115 [-]: SELF      R18 R17 K21  ; R19 := R17; R18 := R17["0xEA470E3C"]
116 [-]: CALL      R18 2 2      ; R18 := R18(R19)
117 [-]: TEST      R18 1        ; if R18 then PC := 135
118 [-]: JMP       135          ; PC := 135
119 [-]: SELF      R18 R17 K22  ; R19 := R17; R18 := R17["0x89C671D6"]
120 [-]: CALL      R18 2 2      ; R18 := R18(R19)
121 [-]: TEST      R18 1        ; if R18 then PC := 135
122 [-]: JMP       135          ; PC := 135
123 [-]: GETGLOBAL R18 K25      ; R18 := table
124 [-]: GETTABLE  R18 R18 K26  ; R18 := R18["0xE6450C9D"]
125 [-]: GETGLOBAL R19 K15      ; R19 := _T
126 [-]: GETTABLE  R19 R19 K23  ; R19 := R19["EndTriggers"]
127 [-]: GETTABLE  R20 R4 R15   ; R20 := R4[R15]
128 [-]: CALL      R18 3 1      ; R18(R19,R20)
129 [-]: GETGLOBAL R18 K25      ; R18 := table
130 [-]: GETTABLE  R18 R18 K26  ; R18 := R18["0xE6450C9D"]
131 [-]: GETGLOBAL R19 K15      ; R19 := _T
132 [-]: GETTABLE  R19 R19 K24  ; R19 := R19["TriggerCompletion"]
133 [-]: MOVE      R20 R0       ; R20 := R0
134 [-]: CALL      R18 3 1      ; R18(R19,R20)
135 [-]: FORLOOP   R12 94       ; R12 += R14; if R12 <= R13 then begin PC := 94; R15 := R12 end
136 [-]: GETGLOBAL R18 K0       ; R18 := 0x400E7765
137 [-]: MOVE      R19 R5       ; R19 := R5
138 [-]: CALL      R18 2 2      ; R18 := R18(R19)
139 [-]: TEST      R18 1        ; if R18 then PC := 177
140 [-]: JMP       177          ; PC := 177
141 [-]: GETGLOBAL R18 K15      ; R18 := _T
142 [-]: GETTABLE  R18 R18 K23  ; R18 := R18["EndTriggers"]
143 [-]: LEN       R18 R18      ; R18 := # R18
144 [-]: LT        0 K27 R18    ; if 0 >= R18 then PC := 177
145 [-]: JMP       177          ; PC := 177
146 [-]: GETGLOBAL R18 K15      ; R18 := _T
147 [-]: NEWTABLE  R19 0 2      ; R19 := {}
148 [-]: SETTABLE  R19 K29 R2   ; R19["RoomID"] := R2
149 [-]: GETGLOBAL R20 K31      ; R20 := Lotus_Game
150 [-]: GETTABLE  R20 R20 K32  ; R20 := R20["LotusObstacleCourseGameRules_CM_WarframeOnly"]
151 [-]: SETTABLE  R19 K30 R20  ; R19["courseMode"] := R20
152 [-]: SETTABLE  R18 K28 R19  ; R18["ActivatedObstacleCourse"] := R19
153 [-]: GETGLOBAL R18 K15      ; R18 := _T
154 [-]: GETTABLE  R18 R18 K33  ; R18 := R18["ObstacleCourseMode"]
155 [-]: EQ        1 R18 K34    ; if R18 == nil then PC := 170
156 [-]: JMP       170          ; PC := 170
157 [-]: GETGLOBAL R18 K15      ; R18 := _T
158 [-]: GETTABLE  R18 R18 K33  ; R18 := R18["ObstacleCourseMode"]
159 [-]: GETTABLE  R18 R18 R2   ; R18 := R18[R2]
160 [-]: EQ        1 R18 K34    ; if R18 == nil then PC := 168
161 [-]: JMP       168          ; PC := 168
162 [-]: GETGLOBAL R18 K15      ; R18 := _T
163 [-]: GETTABLE  R18 R18 K28  ; R18 := R18["ActivatedObstacleCourse"]
164 [-]: GETGLOBAL R19 K15      ; R19 := _T
165 [-]: GETTABLE  R19 R19 K33  ; R19 := R19["ObstacleCourseMode"]
166 [-]: GETTABLE  R19 R19 R2   ; R19 := R19[R2]
167 [-]: SETTABLE  R18 K30 R19  ; R18["courseMode"] := R19
168 [-]: GETGLOBAL R18 K15      ; R18 := _T
169 [-]: SETTABLE  R18 K33 K34  ; R18["ObstacleCourseMode"] := nil
170 [-]: GETGLOBAL R18 K15      ; R18 := _T
171 [-]: GETTABLE  R18 R18 K35  ; R18 := R18["SquadOverlay"]
172 [-]: SELF      R18 R18 K36  ; R19 := R18; R18 := R18["0x458F27A9"]
173 [-]: LOADK     R20 K37      ; R20 := "OnHostObstacleCourseComplete"
174 [-]: LOADK     R21 K13      ; R21 := ""
175 [-]: CALL      R18 4 1      ; R18(R19,R20,R21)
176 [-]: JMP       230          ; PC := 230
177 [-]: GETGLOBAL R18 K0       ; R18 := 0x400E7765
178 [-]: MOVE      R19 R5       ; R19 := R5
179 [-]: CALL      R18 2 2      ; R18 := R18(R19)
180 [-]: TEST      R18 0        ; if not R18 then PC := 198
181 [-]: JMP       198          ; PC := 198
182 [-]: GETGLOBAL R18 K15      ; R18 := _T
183 [-]: GETTABLE  R18 R18 K23  ; R18 := R18["EndTriggers"]
184 [-]: LEN       R18 R18      ; R18 := # R18
185 [-]: EQ        0 R18 K27    ; if R18 ~= 0 then PC := 198
186 [-]: JMP       198          ; PC := 198
187 [-]: GETGLOBAL R18 K3       ; R18 := gGameRules
188 [-]: SELF      R18 R18 K38  ; R19 := R18; R18 := R18["0x362A2E36"]
189 [-]: SELF      R20 R1 K39   ; R21 := R1; R20 := R1["0xDE5882DD"]
190 [-]: CALL      R20 2 2      ; R20 := R20(R21)
191 [-]: LOADK     R21 K40      ; R21 := "/Lotus/Language/Dojo/CustomObstacleCourseMissingBoth"
192 [-]: LOADK     R22 K13      ; R22 := ""
193 [-]: LOADK     R23 K27      ; R23 := 0
194 [-]: LOADK     R24 K41      ; R24 := 2
195 [-]: MOVE      R25 R0       ; R25 := R0
196 [-]: CALL      R18 8 1      ; R18(R19,R20,R21,R22,R23,R24,R25)
197 [-]: JMP       230          ; PC := 230
198 [-]: GETGLOBAL R18 K0       ; R18 := 0x400E7765
199 [-]: MOVE      R19 R5       ; R19 := R5
200 [-]: CALL      R18 2 2      ; R18 := R18(R19)
201 [-]: TEST      R18 0        ; if not R18 then PC := 214
202 [-]: JMP       214          ; PC := 214
203 [-]: GETGLOBAL R18 K3       ; R18 := gGameRules
204 [-]: SELF      R18 R18 K38  ; R19 := R18; R18 := R18["0x362A2E36"]
205 [-]: SELF      R20 R1 K39   ; R21 := R1; R20 := R1["0xDE5882DD"]
206 [-]: CALL      R20 2 2      ; R20 := R20(R21)
207 [-]: LOADK     R21 K42      ; R21 := "/Lotus/Language/Dojo/CustomObstacleCourseMissingStart"
208 [-]: LOADK     R22 K13      ; R22 := ""
209 [-]: LOADK     R23 K27      ; R23 := 0
210 [-]: LOADK     R24 K41      ; R24 := 2
211 [-]: MOVE      R25 R0       ; R25 := R0
212 [-]: CALL      R18 8 1      ; R18(R19,R20,R21,R22,R23,R24,R25)
213 [-]: JMP       230          ; PC := 230
214 [-]: GETGLOBAL R18 K3       ; R18 := gGameRules
215 [-]: SELF      R18 R18 K38  ; R19 := R18; R18 := R18["0x362A2E36"]
216 [-]: SELF      R20 R1 K39   ; R21 := R1; R20 := R1["0xDE5882DD"]
217 [-]: CALL      R20 2 2      ; R20 := R20(R21)
218 [-]: LOADK     R21 K43      ; R21 := "/Lotus/Language/Dojo/CustomObstacleCourseMissingEnd"
219 [-]: LOADK     R22 K13      ; R22 := ""
220 [-]: LOADK     R23 K27      ; R23 := 0
221 [-]: LOADK     R24 K41      ; R24 := 2
222 [-]: MOVE      R25 R0       ; R25 := R0
223 [-]: CALL      R18 8 1      ; R18(R19,R20,R21,R22,R23,R24,R25)
224 [-]: JMP       230          ; PC := 230
225 [-]: GETUPVAL  R18 U0       ; R18 := U0
226 [-]: GETTABLE  R18 R18 K44  ; R18 := R18["0x1C988750"]
227 [-]: LOADK     R19 K45      ; R19 := "/Lotus/Language/Dojo/CustomObstacleCourseLeave"
228 [-]: LOADK     R20 K46      ; R20 := "MainMenuConfirm"
229 [-]: CALL      R18 3 1      ; R18(R19,R20)
230 [-]: RETURN    R0 1         ; return 


; Function #35:
;
; Name:            
; Defined at line: 646
; #Upvalues:       0
; #Parameters:     1
; Is_vararg:       0
; Max Stack Size:  3

  1 [-]: GETGLOBAL R1 K0        ; R1 := 0xF595ADDE
  2 [-]: MOVE      R2 R0        ; R2 := R0
  3 [-]: CALL      R1 2 2       ; R1 := R1(R2)
  4 [-]: GETGLOBAL R2 K1        ; R2 := Engine
  5 [-]: GETTABLE  R2 R2 K2     ; R2 := R2["CI_SELECT"]
  6 [-]: EQ        0 R1 R2      ; if R1 ~= R2 then PC := 12
  7 [-]: JMP       12           ; PC := 12
  8 [-]: GETGLOBAL R1 K1        ; R1 := Engine
  9 [-]: GETTABLE  R1 R1 K3     ; R1 := R1["0xC53FF352"]
 10 [-]: MOVE      R2 R1        ; R2 := R1
 11 [-]: CALL      R1 2 1       ; R1(R2)
 12 [-]: RETURN    R0 1         ; return 


; Function #36:
;
; Name:            
; Defined at line: 652
; #Upvalues:       2
; #Parameters:     2
; Is_vararg:       0
; Max Stack Size:  7

  1 [-]: GETGLOBAL R2 K0        ; R2 := gRegion
  2 [-]: SELF      R2 R2 K1     ; R3 := R2; R2 := R2["0xA559F558"]
  3 [-]: CALL      R2 2 2       ; R2 := R2(R3)
  4 [-]: TEST      R2 1         ; if R2 then PC := 8
  5 [-]: JMP       8            ; PC := 8
  6 [-]: MOVE      R2 R0        ; R2 := R0
  7 [-]: RETURN    R2 2         ; return R2
  8 [-]: GETGLOBAL R2 K2        ; R2 := gGameRules
  9 [-]: TEST      R2 0         ; if not R2 then PC := 17
 10 [-]: JMP       17           ; PC := 17
 11 [-]: GETGLOBAL R2 K2        ; R2 := gGameRules
 12 [-]: SELF      R2 R2 K3     ; R3 := R2; R2 := R2["0x8B598ED4"]
 13 [-]: GETGLOBAL R4 K4        ; R4 := dojoCustomObstacleCourseGameRules
 14 [-]: CALL      R2 3 2       ; R2 := R2(R3,R4)
 15 [-]: TEST      R2 1         ; if R2 then PC := 19
 16 [-]: JMP       19           ; PC := 19
 17 [-]: MOVE      R2 R0        ; R2 := R0
 18 [-]: RETURN    R2 2         ; return R2
 19 [-]: GETGLOBAL R2 K5        ; R2 := 0x400E7765
 20 [-]: MOVE      R3 R0        ; R3 := R0
 21 [-]: CALL      R2 2 2       ; R2 := R2(R3)
 22 [-]: TEST      R2 1         ; if R2 then PC := 28
 23 [-]: JMP       28           ; PC := 28
 24 [-]: SELF      R2 R0 K6     ; R3 := R0; R2 := R0["0x1F3021FA"]
 25 [-]: CALL      R2 2 2       ; R2 := R2(R3)
 26 [-]: TEST      R2 0         ; if not R2 then PC := 30
 27 [-]: JMP       30           ; PC := 30
 28 [-]: MOVE      R2 R0        ; R2 := R0
 29 [-]: RETURN    R2 2         ; return R2
 30 [-]: GETUPVAL  R2 U0        ; R2 := U0
 31 [-]: MOVE      R3 R1        ; R3 := R1
 32 [-]: CALL      R2 2 2       ; R2 := R2(R3)
 33 [-]: GETUPVAL  R3 U0        ; R3 := U0
 34 [-]: CALL      R3 1 2       ; R3 := R3()
 35 [-]: GETGLOBAL R4 K7        ; R4 := Lotus_Game
 36 [-]: GETTABLE  R4 R4 K8     ; R4 := R4["LotusObstacleCourseGameRules_RS_RUNNING"]
 37 [-]: EQ        1 R3 R4      ; if R3 == R4 then PC := 41
 38 [-]: JMP       41           ; PC := 41
 39 [-]: MOVE      R3 R0        ; R3 := R0
 40 [-]: RETURN    R3 2         ; return R3
 41 [-]: GETUPVAL  R3 U1        ; R3 := U1
 42 [-]: CALL      R3 1 2       ; R3 := R3()
 43 [-]: GETGLOBAL R4 K5        ; R4 := 0x400E7765
 44 [-]: MOVE      R5 R3        ; R5 := R3
 45 [-]: CALL      R4 2 2       ; R4 := R4(R5)
 46 [-]: TEST      R4 1         ; if R4 then PC := 59
 47 [-]: JMP       59           ; PC := 59
 48 [-]: SELF      R4 R3 K9     ; R5 := R3; R4 := R3["0x762CE56E"]
 49 [-]: CALL      R4 2 2       ; R4 := R4(R5)
 50 [-]: GETGLOBAL R5 K5        ; R5 := 0x400E7765
 51 [-]: MOVE      R6 R4        ; R6 := R4
 52 [-]: CALL      R5 2 2       ; R5 := R5(R6)
 53 [-]: TEST      R5 1         ; if R5 then PC := 57
 54 [-]: JMP       57           ; PC := 57
 55 [-]: EQ        1 R1 R4      ; if R1 == R4 then PC := 59
 56 [-]: JMP       59           ; PC := 59
 57 [-]: MOVE      R5 R0        ; R5 := R0
 58 [-]: RETURN    R5 2         ; return R5
 59 [-]: MOVE      R5 R1        ; R5 := R1
 60 [-]: RETURN    R5 2         ; return R5
 61 [-]: RETURN    R0 1         ; return 


; Function #37:
;
; Name:            
; Defined at line: 681
; #Upvalues:       1
; #Parameters:     2
; Is_vararg:       0
; Max Stack Size:  18

  1 [-]: GETGLOBAL R2 K0        ; R2 := 0x400E7765
  2 [-]: MOVE      R3 R0        ; R3 := R0
  3 [-]: CALL      R2 2 2       ; R2 := R2(R3)
  4 [-]: TEST      R2 1         ; if R2 then PC := 88
  5 [-]: JMP       88           ; PC := 88
  6 [-]: SELF      R2 R0 K1     ; R3 := R0; R2 := R0["0x1F0EF534"]
  7 [-]: CALL      R2 2 1       ; R2(R3)
  8 [-]: SELF      R2 R0 K2     ; R3 := R0; R2 := R0["0x907C463B"]
  9 [-]: CALL      R2 2 2       ; R2 := R2(R3)
 10 [-]: SELF      R3 R2 K3     ; R4 := R2; R3 := R2["0xBDF6AF22"]
 11 [-]: CALL      R3 2 2       ; R3 := R3(R4)
 12 [-]: GETGLOBAL R4 K0        ; R4 := 0x400E7765
 13 [-]: GETGLOBAL R5 K4        ; R5 := vanishDecoSound
 14 [-]: CALL      R4 2 2       ; R4 := R4(R5)
 15 [-]: TEST      R4 1         ; if R4 then PC := 21
 16 [-]: JMP       21           ; PC := 21
 17 [-]: SELF      R4 R0 K5     ; R5 := R0; R4 := R0["0x25992394"]
 18 [-]: GETGLOBAL R6 K4        ; R6 := vanishDecoSound
 19 [-]: MOVE      R7 R0        ; R7 := R0
 20 [-]: CALL      R4 4 1       ; R4(R5,R6,R7)
 21 [-]: GETGLOBAL R4 K0        ; R4 := 0x400E7765
 22 [-]: MOVE      R5 R2        ; R5 := R2
 23 [-]: CALL      R4 2 2       ; R4 := R4(R5)
 24 [-]: TEST      R4 1         ; if R4 then PC := 88
 25 [-]: JMP       88           ; PC := 88
 26 [-]: LT        0 R3 K6      ; if R3 >= 1 then PC := 88
 27 [-]: JMP       88           ; PC := 88
 28 [-]: SELF      R4 R2 K7     ; R5 := R2; R4 := R2["0x15D4DAEE"]
 29 [-]: GETGLOBAL R6 K8        ; R6 := gLotusEffectDecorationType
 30 [-]: CALL      R4 3 2       ; R4 := R4(R5,R6)
 31 [-]: LOADK     R5 K9        ; R5 := 0
 32 [-]: LOADK     R6 K9        ; R6 := 0
 33 [-]: GETGLOBAL R7 K10       ; R7 := platformVanishDelay
 34 [-]: LT        0 R5 R7      ; if R5 >= R7 then PC := 76
 35 [-]: JMP       76           ; PC := 76
 36 [-]: LOADK     R7 K6        ; R7 := 1
 37 [-]: LEN       R8 R4        ; R8 := # R4
 38 [-]: LOADK     R9 K6        ; R9 := 1
 39 [-]: FORPREP   R7 58        ; R7 -= R9; PC := 58
 40 [-]: GETGLOBAL R11 K0       ; R11 := 0x400E7765
 41 [-]: GETTABLE  R12 R4 R10   ; R12 := R4[R10]
 42 [-]: CALL      R11 2 2      ; R11 := R11(R12)
 43 [-]: TEST      R11 1        ; if R11 then PC := 58
 44 [-]: JMP       58           ; PC := 58
 45 [-]: GETTABLE  R11 R4 R10   ; R11 := R4[R10]
 46 [-]: SELF      R11 R11 K11  ; R12 := R11; R11 := R11["0xD124E361"]
 47 [-]: GETUPVAL  R13 U0       ; R13 := U0
 48 [-]: GETGLOBAL R14 K12      ; R14 := 0x93034B55
 49 [-]: LOADK     R15 K13      ; R15 := 2
 50 [-]: LOADK     R16 K14      ; R16 := 0.20000000298023
 51 [-]: GETGLOBAL R17 K10      ; R17 := platformVanishDelay
 52 [-]: DIV       R17 R5 R17   ; R17 := R5 / R17
 53 [-]: CALL      R14 4 0      ; R14,... := R14(R15,R16,R17)
 54 [-]: CALL      R11 0 1      ; R11(R12,...)
 55 [-]: GETGLOBAL R11 K15      ; R11 := 0x201191EA
 56 [-]: LOADK     R12 K9       ; R12 := 0
 57 [-]: CALL      R11 2 1      ; R11(R12)
 58 [-]: FORLOOP   R7 40        ; R7 += R9; if R7 <= R8 then begin PC := 40; R10 := R7 end
 59 [-]: GETGLOBAL R11 K12      ; R11 := 0x93034B55
 60 [-]: LOADK     R12 K9       ; R12 := 0
 61 [-]: LOADK     R13 K6       ; R13 := 1
 62 [-]: GETGLOBAL R14 K10      ; R14 := platformVanishDelay
 63 [-]: DIV       R14 R5 R14   ; R14 := R5 / R14
 64 [-]: CALL      R11 4 2      ; R11 := R11(R12,R13,R14)
 65 [-]: MOVE      R6 R11       ; R6 := R11
 66 [-]: SELF      R11 R2 K16   ; R12 := R2; R11 := R2["0xD610586B"]
 67 [-]: MOVE      R13 R6       ; R13 := R6
 68 [-]: CALL      R11 3 1      ; R11(R12,R13)
 69 [-]: GETGLOBAL R11 K17      ; R11 := 0x4CDEF9FF
 70 [-]: CALL      R11 1 2      ; R11 := R11()
 71 [-]: ADD       R5 R5 R11    ; R5 := R5 + R11
 72 [-]: GETGLOBAL R11 K15      ; R11 := 0x201191EA
 73 [-]: LOADK     R12 K9       ; R12 := 0
 74 [-]: CALL      R11 2 1      ; R11(R12)
 75 [-]: JMP       33           ; PC := 33
 76 [-]: GETGLOBAL R11 K0       ; R11 := 0x400E7765
 77 [-]: MOVE      R12 R2       ; R12 := R2
 78 [-]: CALL      R11 2 2      ; R11 := R11(R12)
 79 [-]: TEST      R11 1        ; if R11 then PC := 88
 80 [-]: JMP       88           ; PC := 88
 81 [-]: SELF      R11 R2 K16   ; R12 := R2; R11 := R2["0xD610586B"]
 82 [-]: LOADK     R13 K6       ; R13 := 1
 83 [-]: CALL      R11 3 1      ; R11(R12,R13)
 84 [-]: SELF      R11 R2 K18   ; R12 := R2; R11 := R2["0x7DBDDA0B"]
 85 [-]: MOVE      R13 R0       ; R13 := R0
 86 [-]: MOVE      R14 R1       ; R14 := R1
 87 [-]: CALL      R11 4 1      ; R11(R12,R13,R14)
 88 [-]: RETURN    R0 1         ; return 


; Function #38:
;
; Name:            
; Defined at line: 712
; #Upvalues:       0
; #Parameters:     2
; Is_vararg:       0
; Max Stack Size:  2

  1 [-]: RETURN    R0 1         ; return 


