code size: 101
code size: 17
code size: 29
code size: 18
code size: 24
code size: 33
code size: 6
code size: 26
code size: 88
code size: 58
code size: 13
code size: 57
code size: 13
code size: 25
code size: 15
code size: 92
code size: 7
code size: 10
code size: 16
code size: 67
code size: 51
code size: 102
code size: 13
code size: 15
code size: 92
code size: 31
code size: 5
code size: 28
code size: 5
code size: 87
code size: 89
code size: 198
code size: 12
code size: 12
code size: 15
; This file has been disassembled using luadec 2.0.2 by sztupy (http://winmo.sztupy.hu)
; Command line was: -dis M:\git repos\warframe-lua-disassembled\lua\Lotus\Interface\Quests\VitruvianPassword.luac 

; Name:            
; Defined at line: 0
; #Upvalues:       0
; #Parameters:     0
; Is_vararg:       2
; Max Stack Size:  24

  1 [-]: GETGLOBAL R0 K0        ; R0 := 0x329BDC44
  2 [-]: LOADK     R1 K1        ; R1 := "EE.Interface.Utilities"
  3 [-]: CALL      R0 2 2       ; R0 := R0(R1)
  4 [-]: GETGLOBAL R1 K0        ; R1 := 0x329BDC44
  5 [-]: LOADK     R2 K2        ; R2 := "Lotus.Interface.UIStyleUtilities"
  6 [-]: CALL      R1 2 2       ; R1 := R1(R2)
  7 [-]: MOVE      R2 R1        ; R2 := R1
  8 [-]: LOADNIL   R3 R3        ; R3 := nil
  9 [-]: GETGLOBAL R4 K3        ; R4 := 0x70D42C02
 10 [-]: LOADK     R5 K4        ; R5 := 0
 11 [-]: LOADK     R6 K5        ; R6 := 0.15000000596046
 12 [-]: CALL      R4 3 2       ; R4 := R4(R5,R6)
 13 [-]: GETGLOBAL R5 K3        ; R5 := 0x70D42C02
 14 [-]: LOADK     R6 K4        ; R6 := 0
 15 [-]: LOADK     R7 K5        ; R7 := 0.15000000596046
 16 [-]: CALL      R5 3 2       ; R5 := R5(R6,R7)
 17 [-]: LOADK     R6 K6        ; R6 := 1
 18 [-]: MOVE      R7 R1        ; R7 := R1
 19 [-]: LOADK     R8 K6        ; R8 := 1
 20 [-]: LOADK     R9 K4        ; R9 := 0
 21 [-]: MOVE      R10 R0       ; R10 := R0
 22 [-]: LOADNIL   R11 R11      ; R11 := nil
 23 [-]: LOADK     R12 K7       ; R12 := 40
 24 [-]: LOADK     R13 K8       ; R13 := 300
 25 [-]: LOADK     R14 K9       ; R14 := 180
 26 [-]: CLOSURE   R15 0        ; R15 := closure(Function #1)
 27 [-]: SETGLOBAL R15 K10      ; Shutdown := R15
 28 [-]: SETGLOBAL R15 K11      ; 0x3C577FA3 := R15
 29 [-]: CLOSURE   R15 1        ; R15 := closure(Function #2)
 30 [-]: CLOSURE   R16 2        ; R16 := closure(Function #3)
 31 [-]: CLOSURE   R17 3        ; R17 := closure(Function #4)
 32 [-]: MOVE      R0 R11       ; R0 := R11
 33 [-]: MOVE      R0 R0        ; R0 := R0
 34 [-]: CLOSURE   R18 4        ; R18 := closure(Function #5)
 35 [-]: MOVE      R0 R2        ; R0 := R2
 36 [-]: MOVE      R0 R10       ; R0 := R10
 37 [-]: MOVE      R0 R3        ; R0 := R3
 38 [-]: MOVE      R0 R0        ; R0 := R0
 39 [-]: MOVE      R0 R9        ; R0 := R9
 40 [-]: MOVE      R0 R7        ; R0 := R7
 41 [-]: MOVE      R0 R16       ; R0 := R16
 42 [-]: CLOSURE   R19 5        ; R19 := closure(Function #6)
 43 [-]: MOVE      R0 R3        ; R0 := R3
 44 [-]: MOVE      R0 R0        ; R0 := R0
 45 [-]: MOVE      R0 R17       ; R0 := R17
 46 [-]: MOVE      R0 R7        ; R0 := R7
 47 [-]: MOVE      R0 R18       ; R0 := R18
 48 [-]: MOVE      R0 R9        ; R0 := R9
 49 [-]: MOVE      R0 R4        ; R0 := R4
 50 [-]: MOVE      R0 R13       ; R0 := R13
 51 [-]: MOVE      R0 R5        ; R0 := R5
 52 [-]: MOVE      R0 R14       ; R0 := R14
 53 [-]: MOVE      R0 R10       ; R0 := R10
 54 [-]: CLOSURE   R20 6        ; R20 := closure(Function #7)
 55 [-]: MOVE      R0 R3        ; R0 := R3
 56 [-]: MOVE      R0 R6        ; R0 := R6
 57 [-]: MOVE      R0 R12       ; R0 := R12
 58 [-]: MOVE      R0 R8        ; R0 := R8
 59 [-]: MOVE      R0 R0        ; R0 := R0
 60 [-]: MOVE      R0 R9        ; R0 := R9
 61 [-]: MOVE      R0 R2        ; R0 := R2
 62 [-]: CLOSURE   R21 7        ; R21 := closure(Function #8)
 63 [-]: MOVE      R0 R0        ; R0 := R0
 64 [-]: CLOSURE   R22 8        ; R22 := closure(Function #9)
 65 [-]: MOVE      R0 R17       ; R0 := R17
 66 [-]: MOVE      R0 R6        ; R0 := R6
 67 [-]: MOVE      R0 R1        ; R0 := R1
 68 [-]: MOVE      R0 R0        ; R0 := R0
 69 [-]: CLOSURE   R23 9        ; R23 := closure(Function #10)
 70 [-]: MOVE      R0 R6        ; R0 := R6
 71 [-]: MOVE      R0 R7        ; R0 := R7
 72 [-]: MOVE      R0 R22       ; R0 := R22
 73 [-]: MOVE      R0 R21       ; R0 := R21
 74 [-]: MOVE      R0 R19       ; R0 := R19
 75 [-]: MOVE      R0 R20       ; R0 := R20
 76 [-]: SETGLOBAL R23 K12      ; Initialize := R23
 77 [-]: SETGLOBAL R23 K13      ; 0x62648036 := R23
 78 [-]: CLOSURE   R23 10       ; R23 := closure(Function #11)
 79 [-]: MOVE      R0 R3        ; R0 := R3
 80 [-]: MOVE      R0 R2        ; R0 := R2
 81 [-]: MOVE      R0 R4        ; R0 := R4
 82 [-]: MOVE      R0 R5        ; R0 := R5
 83 [-]: MOVE      R0 R13       ; R0 := R13
 84 [-]: MOVE      R0 R14       ; R0 := R14
 85 [-]: MOVE      R0 R0        ; R0 := R0
 86 [-]: SETGLOBAL R23 K14      ; Update := R23
 87 [-]: SETGLOBAL R23 K15      ; 0x8C7099E9 := R23
 88 [-]: CLOSURE   R23 11       ; R23 := closure(Function #12)
 89 [-]: MOVE      R0 R3        ; R0 := R3
 90 [-]: SETGLOBAL R23 K16      ; WordFocused := R23
 91 [-]: SETGLOBAL R23 K17      ; 0x3F1B0B52 := R23
 92 [-]: CLOSURE   R23 12       ; R23 := closure(Function #13)
 93 [-]: MOVE      R0 R3        ; R0 := R3
 94 [-]: SETGLOBAL R23 K18      ; WordUnfocused := R23
 95 [-]: SETGLOBAL R23 K19      ; 0x345F5E43 := R23
 96 [-]: CLOSURE   R23 13       ; R23 := closure(Function #14)
 97 [-]: MOVE      R0 R2        ; R0 := R2
 98 [-]: MOVE      R0 R3        ; R0 := R3
 99 [-]: SETGLOBAL R23 K20      ; WordPressed := R23
100 [-]: SETGLOBAL R23 K21      ; 0x56DFFC1D := R23
101 [-]: RETURN    R0 1         ; return 


; Function #1:
;
; Name:            
; Defined at line: 37
; #Upvalues:       0
; #Parameters:     0
; Is_vararg:       0
; Max Stack Size:  3

  1 [-]: GETGLOBAL R0 K0        ; R0 := 0x400E7765
  2 [-]: GETGLOBAL R1 K1        ; R1 := mMovie
  3 [-]: SELF      R1 R1 K2     ; R2 := R1; R1 := R1["0x4C52612B"]
  4 [-]: CALL      R1 2 0       ; R1,... := R1(R2)
  5 [-]: CALL      R0 0 2       ; R0 := R0(R1,...)
  6 [-]: TEST      R0 0         ; if not R0 then PC := 17
  7 [-]: JMP       17           ; PC := 17
  8 [-]: GETGLOBAL R0 K0        ; R0 := 0x400E7765
  9 [-]: GETGLOBAL R1 K3        ; R1 := _T
 10 [-]: GETTABLE  R1 R1 K4     ; R1 := R1["HideBackground"]
 11 [-]: CALL      R0 2 2       ; R0 := R0(R1)
 12 [-]: TEST      R0 1         ; if R0 then PC := 17
 13 [-]: JMP       17           ; PC := 17
 14 [-]: GETGLOBAL R0 K3        ; R0 := _T
 15 [-]: GETTABLE  R0 R0 K5     ; R0 := R0["0x90516A99"]
 16 [-]: CALL      R0 1 1       ; R0()
 17 [-]: RETURN    R0 1         ; return 


; Function #2:
;
; Name:            
; Defined at line: 45
; #Upvalues:       0
; #Parameters:     2
; Is_vararg:       0
; Max Stack Size:  5

  1 [-]: GETTABLE  R2 R0 K0     ; R2 := R0["X"]
  2 [-]: GETTABLE  R3 R1 K0     ; R3 := R1["X"]
  3 [-]: GETTABLE  R4 R1 K1     ; R4 := R1["Width"]
  4 [-]: ADD       R3 R3 R4     ; R3 := R3 + R4
  5 [-]: LT        0 R2 R3      ; if R2 >= R3 then PC := 27
  6 [-]: JMP       27           ; PC := 27
  7 [-]: GETTABLE  R2 R0 K0     ; R2 := R0["X"]
  8 [-]: GETTABLE  R3 R0 K1     ; R3 := R0["Width"]
  9 [-]: ADD       R2 R2 R3     ; R2 := R2 + R3
 10 [-]: GETTABLE  R3 R1 K0     ; R3 := R1["X"]
 11 [-]: LT        0 R3 R2      ; if R3 >= R2 then PC := 27
 12 [-]: JMP       27           ; PC := 27
 13 [-]: GETTABLE  R2 R0 K2     ; R2 := R0["Y"]
 14 [-]: GETTABLE  R3 R1 K2     ; R3 := R1["Y"]
 15 [-]: GETTABLE  R4 R1 K3     ; R4 := R1["Height"]
 16 [-]: ADD       R3 R3 R4     ; R3 := R3 + R4
 17 [-]: LT        0 R2 R3      ; if R2 >= R3 then PC := 27
 18 [-]: JMP       27           ; PC := 27
 19 [-]: GETTABLE  R2 R0 K2     ; R2 := R0["Y"]
 20 [-]: GETTABLE  R3 R0 K3     ; R3 := R0["Height"]
 21 [-]: ADD       R2 R2 R3     ; R2 := R2 + R3
 22 [-]: GETTABLE  R3 R1 K2     ; R3 := R1["Y"]
 23 [-]: LT        0 R3 R2      ; if R3 >= R2 then PC := 27
 24 [-]: JMP       27           ; PC := 27
 25 [-]: MOVE      R2 R1        ; R2 := R1
 26 [-]: RETURN    R2 2         ; return R2
 27 [-]: MOVE      R2 R0        ; R2 := R0
 28 [-]: RETURN    R2 2         ; return R2
 29 [-]: RETURN    R0 1         ; return 


; Function #3:
;
; Name:            
; Defined at line: 55
; #Upvalues:       0
; #Parameters:     0
; Is_vararg:       0
; Max Stack Size:  4

  1 [-]: GETGLOBAL R0 K0        ; R0 := 0x400E7765
  2 [-]: GETGLOBAL R1 K1        ; R1 := mMovie
  3 [-]: SELF      R1 R1 K2     ; R2 := R1; R1 := R1["0x4C52612B"]
  4 [-]: CALL      R1 2 0       ; R1,... := R1(R2)
  5 [-]: CALL      R0 0 2       ; R0 := R0(R1,...)
  6 [-]: TEST      R0 1         ; if R0 then PC := 15
  7 [-]: JMP       15           ; PC := 15
  8 [-]: GETGLOBAL R0 K1        ; R0 := mMovie
  9 [-]: SELF      R0 R0 K2     ; R1 := R0; R0 := R0["0x4C52612B"]
 10 [-]: CALL      R0 2 2       ; R0 := R0(R1)
 11 [-]: SELF      R0 R0 K3     ; R1 := R0; R0 := R0["0x458F27A9"]
 12 [-]: LOADK     R2 K4        ; R2 := "Next"
 13 [-]: LOADK     R3 K5        ; R3 := ""
 14 [-]: CALL      R0 4 1       ; R0(R1,R2,R3)
 15 [-]: GETGLOBAL R0 K1        ; R0 := mMovie
 16 [-]: SELF      R0 R0 K6     ; R1 := R0; R0 := R0["0xA58BB96C"]
 17 [-]: CALL      R0 2 1       ; R0(R1)
 18 [-]: RETURN    R0 1         ; return 


; Function #4:
;
; Name:            
; Defined at line: 62
; #Upvalues:       2
; #Parameters:     2
; Is_vararg:       0
; Max Stack Size:  13

  1 [-]: LOADK     R2 K0        ; R2 := 0.25
  2 [-]: TEST      R1 0         ; if not R1 then PC := 5
  3 [-]: JMP       5            ; PC := 5
  4 [-]: LOADK     R2 K1        ; R2 := 0
  5 [-]: MOVE      R0 R0        ; R0 := R0
  6 [-]: GETGLOBAL R3 K2        ; R3 := 0x52E17A90
  7 [-]: GETGLOBAL R4 K3        ; R4 := mMovie
  8 [-]: LOADK     R5 K4        ; R5 := "Info"
  9 [-]: GETGLOBAL R6 K5        ; R6 := UISys
 10 [-]: GETTABLE  R6 R6 K6     ; R6 := R6["FlashInstance_SMOOTH_STEP"]
 11 [-]: NEWTABLE  R7 1 0       ; R7 := {}
 12 [-]: LOADK     R8 K7        ; R8 := "_alpha"
 13 [-]: SETLIST   R7 1 1       ; R7[(1-1)*FPF+i] := R(7+i), 1 <= i <= 1
 14 [-]: NEWTABLE  R8 0 0       ; R8 := {}
 15 [-]: GETUPVAL  R9 U1        ; R9 := U1
 16 [-]: GETTABLE  R9 R9 K8     ; R9 := R9["0xF81722A2"]
 17 [-]: GETUPVAL  R10 U0       ; R10 := U0
 18 [-]: LOADK     R11 K9       ; R11 := 100
 19 [-]: LOADK     R12 K1       ; R12 := 0
 20 [-]: CALL      R9 4 0       ; R9,... := R9(R10,R11,R12)
 21 [-]: SETLIST   R8 0 1       ; R8[(1-1)*FPF+i] := R(8+i), 1 <= i <= 0
 22 [-]: MOVE      R9 R2        ; R9 := R2
 23 [-]: CALL      R3 7 1       ; R3(R4,R5,R6,R7,R8,R9)
 24 [-]: RETURN    R0 1         ; return 


; Function #5:
;
; Name:            
; Defined at line: 71
; #Upvalues:       7
; #Parameters:     0
; Is_vararg:       0
; Max Stack Size:  9

  1 [-]: MOVE      R0 R1        ; R0 := R1
  2 [-]: MOVE      R0 R0        ; R0 := R0
  3 [-]: MOVE      R0 R1        ; R0 := R1
  4 [-]: MOVE      R0 R1        ; R0 := R1
  5 [-]: GETUPVAL  R0 U2        ; R0 := U2
  6 [-]: SELF      R0 R0 K0     ; R1 := R0; R0 := R0["0x501F0A32"]
  7 [-]: MOVE      R2 R0        ; R2 := R0
  8 [-]: CALL      R0 3 1       ; R0(R1,R2)
  9 [-]: GETUPVAL  R0 U3        ; R0 := U3
 10 [-]: GETTABLE  R0 R0 K1     ; R0 := R0["0x25992394"]
 11 [-]: GETGLOBAL R1 K2        ; R1 := transitionOutSound
 12 [-]: CALL      R0 2 1       ; R0(R1)
 13 [-]: GETGLOBAL R0 K3        ; R0 := 0x52E17A90
 14 [-]: GETGLOBAL R1 K4        ; R1 := mMovie
 15 [-]: LOADK     R2 K5        ; R2 := "_root"
 16 [-]: GETGLOBAL R3 K6        ; R3 := UISys
 17 [-]: GETTABLE  R3 R3 K7     ; R3 := R3["FlashInstance_SMOOTH_STEP"]
 18 [-]: NEWTABLE  R4 1 0       ; R4 := {}
 19 [-]: CLOSURE   R5 0         ; R5 := closure(Function #5.1)
 20 [-]: GETUPVAL  R0 U4        ; R0 := U4
 21 [-]: GETUPVAL  R0 U2        ; R0 := U2
 22 [-]: SETLIST   R4 1 1       ; R4[(1-1)*FPF+i] := R(4+i), 1 <= i <= 1
 23 [-]: NEWTABLE  R5 1 0       ; R5 := {}
 24 [-]: LOADK     R6 K8        ; R6 := 1
 25 [-]: SETLIST   R5 1 1       ; R5[(1-1)*FPF+i] := R(5+i), 1 <= i <= 1
 26 [-]: LOADK     R6 K9        ; R6 := 0.64999997615814
 27 [-]: LOADK     R7 K10       ; R7 := 0.15000000596046
 28 [-]: CLOSURE   R8 1         ; R8 := closure(Function #5.2)
 29 [-]: GETUPVAL  R0 U5        ; R0 := U5
 30 [-]: GETUPVAL  R0 U3        ; R0 := U3
 31 [-]: GETUPVAL  R0 U6        ; R0 := U6
 32 [-]: CALL      R0 9 1       ; R0(R1,R2,R3,R4,R5,R6,R7,R8)
 33 [-]: RETURN    R0 1         ; return 


; Function #5.1:
;
; Name:            
; Defined at line: 78
; #Upvalues:       2
; #Parameters:     1
; Is_vararg:       0
; Max Stack Size:  3

  1 [-]: SUB       R1 K0 R0     ; R1 := 1 - R0
  2 [-]: MOVE      R1 R0        ; R1 := R0
  3 [-]: GETUPVAL  R1 U1        ; R1 := U1
  4 [-]: SELF      R1 R1 K1     ; R2 := R1; R1 := R1["0xD28673BC"]
  5 [-]: CALL      R1 2 1       ; R1(R2)
  6 [-]: RETURN    R0 1         ; return 


; Function #5.2:
;
; Name:            
; Defined at line: 83
; #Upvalues:       3
; #Parameters:     0
; Is_vararg:       0
; Max Stack Size:  9

  1 [-]: GETUPVAL  R0 U0        ; R0 := U0
  2 [-]: TEST      R0 0         ; if not R0 then PC := 24
  3 [-]: JMP       24           ; PC := 24
  4 [-]: GETUPVAL  R0 U1        ; R0 := U1
  5 [-]: GETTABLE  R0 R0 K0     ; R0 := R0["0x25992394"]
  6 [-]: GETGLOBAL R1 K1        ; R1 := glyphFadeSound
  7 [-]: CALL      R0 2 1       ; R0(R1)
  8 [-]: GETGLOBAL R0 K2        ; R0 := 0x52E17A90
  9 [-]: GETGLOBAL R1 K3        ; R1 := mMovie
 10 [-]: LOADK     R2 K4        ; R2 := "_root"
 11 [-]: GETGLOBAL R3 K5        ; R3 := UISys
 12 [-]: GETTABLE  R3 R3 K6     ; R3 := R3["FlashInstance_SMOOTH_STEP"]
 13 [-]: NEWTABLE  R4 1 0       ; R4 := {}
 14 [-]: LOADK     R5 K7        ; R5 := "_alpha"
 15 [-]: SETLIST   R4 1 1       ; R4[(1-1)*FPF+i] := R(4+i), 1 <= i <= 1
 16 [-]: NEWTABLE  R5 1 0       ; R5 := {}
 17 [-]: LOADK     R6 K8        ; R6 := 0
 18 [-]: SETLIST   R5 1 1       ; R5[(1-1)*FPF+i] := R(5+i), 1 <= i <= 1
 19 [-]: LOADK     R6 K9        ; R6 := 0.55000001192093
 20 [-]: LOADK     R7 K10       ; R7 := 1.5
 21 [-]: GETUPVAL  R8 U2        ; R8 := U2
 22 [-]: CALL      R0 9 1       ; R0(R1,R2,R3,R4,R5,R6,R7,R8)
 23 [-]: JMP       26           ; PC := 26
 24 [-]: GETUPVAL  R0 U2        ; R0 := U2
 25 [-]: CALL      R0 1 1       ; R0()
 26 [-]: RETURN    R0 1         ; return 


; Function #6:
;
; Name:            
; Defined at line: 93
; #Upvalues:       11
; #Parameters:     0
; Is_vararg:       0
; Max Stack Size:  6

  1 [-]: GETGLOBAL R0 K0        ; R0 := 0x329BDC44
  2 [-]: LOADK     R1 K1        ; R1 := "EE.Interface.Components.List"
  3 [-]: CALL      R0 2 2       ; R0 := R0(R1)
  4 [-]: GETTABLE  R1 R0 K2     ; R1 := R0["0xB40DEC3F"]
  5 [-]: GETGLOBAL R2 K3        ; R2 := mMovie
  6 [-]: LOADK     R3 K4        ; R3 := "Entry1"
  7 [-]: CALL      R1 3 2       ; R1 := R1(R2,R3)
  8 [-]: MOVE      R1 R0        ; R1 := R0
  9 [-]: GETUPVAL  R1 U0        ; R1 := U0
 10 [-]: SELF      R1 R1 K5     ; R2 := R1; R1 := R1["0xE13A565"]
 11 [-]: LOADK     R3 K6        ; R3 := "WordPressed"
 12 [-]: LOADK     R4 K7        ; R4 := "WordFocused"
 13 [-]: LOADK     R5 K8        ; R5 := "WordUnfocused"
 14 [-]: CALL      R1 5 1       ; R1(R2,R3,R4,R5)
 15 [-]: GETUPVAL  R1 U0        ; R1 := U0
 16 [-]: SETTABLE  R1 K9 K10    ; R1["mForcedVerticalSeparation"] := 12
 17 [-]: GETUPVAL  R1 U0        ; R1 := U0
 18 [-]: SETTABLE  R1 K11 K12   ; R1["mElementTransitionTime"] := 0
 19 [-]: GETUPVAL  R1 U0        ; R1 := U0
 20 [-]: SETTABLE  R1 K13 K12   ; R1["mElementDelayTime"] := 0
 21 [-]: GETUPVAL  R1 U0        ; R1 := U0
 22 [-]: SETTABLE  R1 K14 K12   ; R1["mTransitionInDeltaY"] := 0
 23 [-]: GETUPVAL  R1 U0        ; R1 := U0
 24 [-]: SETTABLE  R1 K15 K12   ; R1["mTransitionOutDeltaY"] := 0
 25 [-]: GETUPVAL  R1 U0        ; R1 := U0
 26 [-]: CLOSURE   R2 0         ; R2 := closure(Function #6.1)
 27 [-]: GETUPVAL  R0 U1        ; R0 := U1
 28 [-]: GETUPVAL  R0 U2        ; R0 := U2
 29 [-]: SETTABLE  R1 K16 R2    ; R1["mOnFocusedCallback"] := R2
 30 [-]: GETUPVAL  R1 U0        ; R1 := U0
 31 [-]: CLOSURE   R2 1         ; R2 := closure(Function #6.2)
 32 [-]: GETUPVAL  R0 U0        ; R0 := U0
 33 [-]: GETUPVAL  R0 U2        ; R0 := U2
 34 [-]: SETTABLE  R1 K17 R2    ; R1["mOnUnfocusedCallback"] := R2
 35 [-]: GETUPVAL  R1 U0        ; R1 := U0
 36 [-]: CLOSURE   R2 2         ; R2 := closure(Function #6.3)
 37 [-]: GETUPVAL  R0 U3        ; R0 := U3
 38 [-]: GETUPVAL  R0 U1        ; R0 := U1
 39 [-]: GETUPVAL  R0 U4        ; R0 := U4
 40 [-]: SETTABLE  R1 K18 R2    ; R1["mOnSelectedCallback"] := R2
 41 [-]: GETUPVAL  R1 U0        ; R1 := U0
 42 [-]: CLOSURE   R2 3         ; R2 := closure(Function #6.4)
 43 [-]: GETUPVAL  R0 U3        ; R0 := U3
 44 [-]: SETTABLE  R1 K19 R2    ; R1["CalculateAlpha"] := R2
 45 [-]: GETUPVAL  R1 U0        ; R1 := U0
 46 [-]: CLOSURE   R2 4         ; R2 := closure(Function #6.5)
 47 [-]: GETUPVAL  R0 U0        ; R0 := U0
 48 [-]: GETUPVAL  R0 U1        ; R0 := U1
 49 [-]: GETUPVAL  R0 U3        ; R0 := U3
 50 [-]: SETTABLE  R1 K20 R2    ; R1["mElementDrawCallback"] := R2
 51 [-]: GETUPVAL  R1 U0        ; R1 := U0
 52 [-]: CLOSURE   R2 5         ; R2 := closure(Function #6.6)
 53 [-]: SETTABLE  R1 K21 R2    ; R1["SetupPreInterpolationValues"] := R2
 54 [-]: GETUPVAL  R1 U0        ; R1 := U0
 55 [-]: CLOSURE   R2 6         ; R2 := closure(Function #6.7)
 56 [-]: SETTABLE  R1 K22 R2    ; R1["GetInterpolationProperties"] := R2
 57 [-]: GETUPVAL  R1 U0        ; R1 := U0
 58 [-]: CLOSURE   R2 7         ; R2 := closure(Function #6.8)
 59 [-]: GETUPVAL  R0 U5        ; R0 := U5
 60 [-]: SETTABLE  R1 K23 R2    ; R1["GetScale"] := R2
 61 [-]: GETUPVAL  R1 U0        ; R1 := U0
 62 [-]: CLOSURE   R2 8         ; R2 := closure(Function #6.9)
 63 [-]: GETUPVAL  R0 U0        ; R0 := U0
 64 [-]: GETUPVAL  R0 U1        ; R0 := U1
 65 [-]: SETTABLE  R1 K24 R2    ; R1["GetRectangle"] := R2
 66 [-]: GETUPVAL  R1 U0        ; R1 := U0
 67 [-]: CLOSURE   R2 9         ; R2 := closure(Function #6.10)
 68 [-]: GETUPVAL  R0 U5        ; R0 := U5
 69 [-]: GETUPVAL  R0 U6        ; R0 := U6
 70 [-]: GETUPVAL  R0 U7        ; R0 := U7
 71 [-]: GETUPVAL  R0 U8        ; R0 := U8
 72 [-]: GETUPVAL  R0 U9        ; R0 := U9
 73 [-]: SETTABLE  R1 K25 R2    ; R1["Reposition"] := R2
 74 [-]: GETUPVAL  R1 U0        ; R1 := U0
 75 [-]: CLOSURE   R2 10        ; R2 := closure(Function #6.11)
 76 [-]: GETUPVAL  R0 U5        ; R0 := U5
 77 [-]: GETUPVAL  R0 U0        ; R0 := U0
 78 [-]: GETUPVAL  R0 U10       ; R0 := U10
 79 [-]: GETUPVAL  R0 U3        ; R0 := U3
 80 [-]: SETTABLE  R1 K26 R2    ; R1["Transform"] := R2
 81 [-]: GETUPVAL  R1 U0        ; R1 := U0
 82 [-]: CLOSURE   R2 11        ; R2 := closure(Function #6.12)
 83 [-]: GETUPVAL  R0 U0        ; R0 := U0
 84 [-]: SETTABLE  R1 K27 R2    ; R1["ArrangeGlpyhs"] := R2
 85 [-]: GETUPVAL  R1 U0        ; R1 := U0
 86 [-]: CLOSURE   R2 12        ; R2 := closure(Function #6.13)
 87 [-]: SETTABLE  R1 K28 R2    ; R1["SetButtonsEnabled"] := R2
 88 [-]: RETURN    R0 1         ; return 


; Function #6.1:
;
; Name:            
; Defined at line: 103
; #Upvalues:       2
; #Parameters:     1
; Is_vararg:       0
; Max Stack Size:  9

  1 [-]: GETUPVAL  R1 U0        ; R1 := U0
  2 [-]: GETTABLE  R1 R1 K0     ; R1 := R1["0x25992394"]
  3 [-]: GETGLOBAL R2 K1        ; R2 := glyphHoverSound
  4 [-]: CALL      R1 2 1       ; R1(R2)
  5 [-]: GETGLOBAL R1 K2        ; R1 := 0x52E17A90
  6 [-]: GETGLOBAL R2 K3        ; R2 := mMovie
  7 [-]: GETTABLE  R3 R0 K4     ; R3 := R0["mClipName"]
  8 [-]: LOADK     R4 K5        ; R4 := ".HiddenIcon"
  9 [-]: CONCAT    R3 R3 R4     ; R3 := R3 .. R4
 10 [-]: GETGLOBAL R4 K6        ; R4 := UISys
 11 [-]: GETTABLE  R4 R4 K7     ; R4 := R4["FlashInstance_EASE_IN"]
 12 [-]: NEWTABLE  R5 1 0       ; R5 := {}
 13 [-]: CLOSURE   R6 0         ; R6 := closure(Function #6.1.1)
 14 [-]: MOVE      R0 R0        ; R0 := R0
 15 [-]: SETLIST   R5 1 1       ; R5[(1-1)*FPF+i] := R(5+i), 1 <= i <= 1
 16 [-]: NEWTABLE  R6 1 0       ; R6 := {}
 17 [-]: LOADK     R7 K8        ; R7 := 1
 18 [-]: SETLIST   R6 1 1       ; R6[(1-1)*FPF+i] := R(6+i), 1 <= i <= 1
 19 [-]: LOADK     R7 K9        ; R7 := 0.85000002384186
 20 [-]: LOADK     R8 K10       ; R8 := 0
 21 [-]: CALL      R1 8 1       ; R1(R2,R3,R4,R5,R6,R7,R8)
 22 [-]: GETGLOBAL R1 K2        ; R1 := 0x52E17A90
 23 [-]: GETGLOBAL R2 K3        ; R2 := mMovie
 24 [-]: GETTABLE  R3 R0 K4     ; R3 := R0["mClipName"]
 25 [-]: LOADK     R4 K11       ; R4 := ".Icon"
 26 [-]: CONCAT    R3 R3 R4     ; R3 := R3 .. R4
 27 [-]: GETGLOBAL R4 K6        ; R4 := UISys
 28 [-]: GETTABLE  R4 R4 K12    ; R4 := R4["FlashInstance_SMOOTH_STEP"]
 29 [-]: NEWTABLE  R5 1 0       ; R5 := {}
 30 [-]: LOADK     R6 K13       ; R6 := "_alpha"
 31 [-]: SETLIST   R5 1 1       ; R5[(1-1)*FPF+i] := R(5+i), 1 <= i <= 1
 32 [-]: NEWTABLE  R6 1 0       ; R6 := {}
 33 [-]: LOADK     R7 K14       ; R7 := 100
 34 [-]: SETLIST   R6 1 1       ; R6[(1-1)*FPF+i] := R(6+i), 1 <= i <= 1
 35 [-]: LOADK     R7 K15       ; R7 := 0.20000000298023
 36 [-]: CALL      R1 7 1       ; R1(R2,R3,R4,R5,R6,R7)
 37 [-]: GETGLOBAL R1 K2        ; R1 := 0x52E17A90
 38 [-]: GETGLOBAL R2 K3        ; R2 := mMovie
 39 [-]: GETTABLE  R3 R0 K4     ; R3 := R0["mClipName"]
 40 [-]: LOADK     R4 K16       ; R4 := ".BackerIcon"
 41 [-]: CONCAT    R3 R3 R4     ; R3 := R3 .. R4
 42 [-]: GETGLOBAL R4 K6        ; R4 := UISys
 43 [-]: GETTABLE  R4 R4 K12    ; R4 := R4["FlashInstance_SMOOTH_STEP"]
 44 [-]: NEWTABLE  R5 1 0       ; R5 := {}
 45 [-]: LOADK     R6 K13       ; R6 := "_alpha"
 46 [-]: SETLIST   R5 1 1       ; R5[(1-1)*FPF+i] := R(5+i), 1 <= i <= 1
 47 [-]: NEWTABLE  R6 1 0       ; R6 := {}
 48 [-]: LOADK     R7 K17       ; R7 := 20
 49 [-]: SETLIST   R6 1 1       ; R6[(1-1)*FPF+i] := R(6+i), 1 <= i <= 1
 50 [-]: LOADK     R7 K15       ; R7 := 0.20000000298023
 51 [-]: CALL      R1 7 1       ; R1(R2,R3,R4,R5,R6,R7)
 52 [-]: GETTABLE  R1 R0 K18    ; R1 := R0["mIsCorrectOne"]
 53 [-]: TEST      R1 0         ; if not R1 then PC := 58
 54 [-]: JMP       58           ; PC := 58
 55 [-]: GETUPVAL  R1 U1        ; R1 := U1
 56 [-]: MOVE      R2 R1        ; R2 := R1
 57 [-]: CALL      R1 2 1       ; R1(R2)
 58 [-]: RETURN    R0 1         ; return 


; Function #6.1.1:
;
; Name:            
; Defined at line: 108
; #Upvalues:       1
; #Parameters:     1
; Is_vararg:       0
; Max Stack Size:  9

  1 [-]: GETGLOBAL R1 K0        ; R1 := mMovie
  2 [-]: SELF      R1 R1 K1     ; R2 := R1; R1 := R1["0x302AAB2F"]
  3 [-]: GETUPVAL  R3 U0        ; R3 := U0
  4 [-]: GETTABLE  R3 R3 K2     ; R3 := R3["mClipName"]
  5 [-]: LOADK     R4 K3        ; R4 := ".HiddenIcon"
  6 [-]: CONCAT    R3 R3 R4     ; R3 := R3 .. R4
  7 [-]: LOADK     R4 K4        ; R4 := "AlphaTestThreshold"
  8 [-]: MOVE      R5 R0        ; R5 := R0
  9 [-]: LOADK     R6 K5        ; R6 := 0
 10 [-]: LOADK     R7 K6        ; R7 := 1
 11 [-]: LOADK     R8 K6        ; R8 := 1
 12 [-]: CALL      R1 8 1       ; R1(R2,R3,R4,R5,R6,R7,R8)
 13 [-]: RETURN    R0 1         ; return 


; Function #6.2:
;
; Name:            
; Defined at line: 121
; #Upvalues:       2
; #Parameters:     2
; Is_vararg:       0
; Max Stack Size:  11

  1 [-]: GETGLOBAL R2 K0        ; R2 := 0x52E17A90
  2 [-]: GETGLOBAL R3 K1        ; R3 := mMovie
  3 [-]: GETTABLE  R4 R0 K2     ; R4 := R0["mClipName"]
  4 [-]: LOADK     R5 K3        ; R5 := ".HiddenIcon"
  5 [-]: CONCAT    R4 R4 R5     ; R4 := R4 .. R5
  6 [-]: GETGLOBAL R5 K4        ; R5 := UISys
  7 [-]: GETTABLE  R5 R5 K5     ; R5 := R5["FlashInstance_EASE_OUT"]
  8 [-]: NEWTABLE  R6 1 0       ; R6 := {}
  9 [-]: CLOSURE   R7 0         ; R7 := closure(Function #6.2.1)
 10 [-]: MOVE      R0 R0        ; R0 := R0
 11 [-]: SETLIST   R6 1 1       ; R6[(1-1)*FPF+i] := R(6+i), 1 <= i <= 1
 12 [-]: NEWTABLE  R7 1 0       ; R7 := {}
 13 [-]: LOADK     R8 K6        ; R8 := 1
 14 [-]: SETLIST   R7 1 1       ; R7[(1-1)*FPF+i] := R(7+i), 1 <= i <= 1
 15 [-]: LOADK     R8 K7        ; R8 := 0.85000002384186
 16 [-]: MOVE      R9 R1        ; R9 := R1
 17 [-]: CALL      R2 8 1       ; R2(R3,R4,R5,R6,R7,R8,R9)
 18 [-]: GETGLOBAL R2 K0        ; R2 := 0x52E17A90
 19 [-]: GETGLOBAL R3 K1        ; R3 := mMovie
 20 [-]: GETTABLE  R4 R0 K2     ; R4 := R0["mClipName"]
 21 [-]: LOADK     R5 K8        ; R5 := ".Icon"
 22 [-]: CONCAT    R4 R4 R5     ; R4 := R4 .. R5
 23 [-]: GETGLOBAL R5 K4        ; R5 := UISys
 24 [-]: GETTABLE  R5 R5 K9     ; R5 := R5["FlashInstance_SMOOTH_STEP"]
 25 [-]: NEWTABLE  R6 1 0       ; R6 := {}
 26 [-]: LOADK     R7 K10       ; R7 := "_alpha"
 27 [-]: SETLIST   R6 1 1       ; R6[(1-1)*FPF+i] := R(6+i), 1 <= i <= 1
 28 [-]: NEWTABLE  R7 0 0       ; R7 := {}
 29 [-]: GETUPVAL  R8 U0        ; R8 := U0
 30 [-]: SELF      R8 R8 K11    ; R9 := R8; R8 := R8["0xF3EC2EB3"]
 31 [-]: MOVE      R10 R0       ; R10 := R0
 32 [-]: CALL      R8 3 0       ; R8,... := R8(R9,R10)
 33 [-]: SETLIST   R7 0 1       ; R7[(1-1)*FPF+i] := R(7+i), 1 <= i <= 0
 34 [-]: LOADK     R8 K12       ; R8 := 0.20000000298023
 35 [-]: CALL      R2 7 1       ; R2(R3,R4,R5,R6,R7,R8)
 36 [-]: GETGLOBAL R2 K0        ; R2 := 0x52E17A90
 37 [-]: GETGLOBAL R3 K1        ; R3 := mMovie
 38 [-]: GETTABLE  R4 R0 K2     ; R4 := R0["mClipName"]
 39 [-]: LOADK     R5 K13       ; R5 := ".BackerIcon"
 40 [-]: CONCAT    R4 R4 R5     ; R4 := R4 .. R5
 41 [-]: GETGLOBAL R5 K4        ; R5 := UISys
 42 [-]: GETTABLE  R5 R5 K9     ; R5 := R5["FlashInstance_SMOOTH_STEP"]
 43 [-]: NEWTABLE  R6 1 0       ; R6 := {}
 44 [-]: LOADK     R7 K10       ; R7 := "_alpha"
 45 [-]: SETLIST   R6 1 1       ; R6[(1-1)*FPF+i] := R(6+i), 1 <= i <= 1
 46 [-]: NEWTABLE  R7 1 0       ; R7 := {}
 47 [-]: LOADK     R8 K14       ; R8 := 4
 48 [-]: SETLIST   R7 1 1       ; R7[(1-1)*FPF+i] := R(7+i), 1 <= i <= 1
 49 [-]: LOADK     R8 K12       ; R8 := 0.20000000298023
 50 [-]: CALL      R2 7 1       ; R2(R3,R4,R5,R6,R7,R8)
 51 [-]: GETTABLE  R2 R0 K15    ; R2 := R0["mIsCorrectOne"]
 52 [-]: TEST      R2 0         ; if not R2 then PC := 57
 53 [-]: JMP       57           ; PC := 57
 54 [-]: GETUPVAL  R2 U1        ; R2 := U1
 55 [-]: MOVE      R3 R0        ; R3 := R0
 56 [-]: CALL      R2 2 1       ; R2(R3)
 57 [-]: RETURN    R0 1         ; return 


; Function #6.2.1:
;
; Name:            
; Defined at line: 124
; #Upvalues:       1
; #Parameters:     1
; Is_vararg:       0
; Max Stack Size:  9

  1 [-]: GETGLOBAL R1 K0        ; R1 := mMovie
  2 [-]: SELF      R1 R1 K1     ; R2 := R1; R1 := R1["0x302AAB2F"]
  3 [-]: GETUPVAL  R3 U0        ; R3 := U0
  4 [-]: GETTABLE  R3 R3 K2     ; R3 := R3["mClipName"]
  5 [-]: LOADK     R4 K3        ; R4 := ".HiddenIcon"
  6 [-]: CONCAT    R3 R3 R4     ; R3 := R3 .. R4
  7 [-]: LOADK     R4 K4        ; R4 := "AlphaTestThreshold"
  8 [-]: SUB       R5 K5 R0     ; R5 := 1 - R0
  9 [-]: LOADK     R6 K6        ; R6 := 0
 10 [-]: LOADK     R7 K5        ; R7 := 1
 11 [-]: LOADK     R8 K5        ; R8 := 1
 12 [-]: CALL      R1 8 1       ; R1(R2,R3,R4,R5,R6,R7,R8)
 13 [-]: RETURN    R0 1         ; return 


; Function #6.3:
;
; Name:            
; Defined at line: 137
; #Upvalues:       3
; #Parameters:     1
; Is_vararg:       0
; Max Stack Size:  3

  1 [-]: GETUPVAL  R1 U0        ; R1 := U0
  2 [-]: TEST      R1 0         ; if not R1 then PC := 19
  3 [-]: JMP       19           ; PC := 19
  4 [-]: GETTABLE  R1 R0 K0     ; R1 := R0["mIsCorrectOne"]
  5 [-]: TEST      R1 0         ; if not R1 then PC := 14
  6 [-]: JMP       14           ; PC := 14
  7 [-]: GETUPVAL  R1 U1        ; R1 := U1
  8 [-]: GETTABLE  R1 R1 K1     ; R1 := R1["0x25992394"]
  9 [-]: GETGLOBAL R2 K2        ; R2 := glyphSelectSound
 10 [-]: CALL      R1 2 1       ; R1(R2)
 11 [-]: GETUPVAL  R1 U2        ; R1 := U2
 12 [-]: CALL      R1 1 1       ; R1()
 13 [-]: JMP       25           ; PC := 25
 14 [-]: GETUPVAL  R1 U1        ; R1 := U1
 15 [-]: GETTABLE  R1 R1 K1     ; R1 := R1["0x25992394"]
 16 [-]: GETGLOBAL R2 K3        ; R2 := glyphWrongSelectSound
 17 [-]: CALL      R1 2 1       ; R1(R2)
 18 [-]: JMP       25           ; PC := 25
 19 [-]: GETUPVAL  R1 U1        ; R1 := U1
 20 [-]: GETTABLE  R1 R1 K1     ; R1 := R1["0x25992394"]
 21 [-]: GETGLOBAL R2 K3        ; R2 := glyphWrongSelectSound
 22 [-]: CALL      R1 2 1       ; R1(R2)
 23 [-]: GETUPVAL  R1 U2        ; R1 := U2
 24 [-]: CALL      R1 1 1       ; R1()
 25 [-]: RETURN    R0 1         ; return 


; Function #6.4:
;
; Name:            
; Defined at line: 151
; #Upvalues:       1
; #Parameters:     2
; Is_vararg:       0
; Max Stack Size:  6

  1 [-]: GETTABLE  R2 R1 K0     ; R2 := R1["mIsCorrectOne"]
  2 [-]: TEST      R2 0         ; if not R2 then PC := 9
  3 [-]: JMP       9            ; PC := 9
  4 [-]: GETUPVAL  R2 U0        ; R2 := U0
  5 [-]: TEST      R2 0         ; if not R2 then PC := 9
  6 [-]: JMP       9            ; PC := 9
  7 [-]: LOADK     R2 K1        ; R2 := 60
  8 [-]: RETURN    R2 2         ; return R2
  9 [-]: GETGLOBAL R2 K2        ; R2 := 0x93034B55
 10 [-]: LOADK     R3 K3        ; R3 := 70
 11 [-]: LOADK     R4 K4        ; R4 := 15
 12 [-]: GETTABLE  R5 R1 K5     ; R5 := R1["mDepth"]
 13 [-]: CALL      R2 4 2       ; R2 := R2(R3,R4,R5)
 14 [-]: RETURN    R2 2         ; return R2
 15 [-]: RETURN    R0 1         ; return 


; Function #6.5:
;
; Name:            
; Defined at line: 158
; #Upvalues:       3
; #Parameters:     2
; Is_vararg:       0
; Max Stack Size:  12

  1 [-]: GETUPVAL  R2 U0        ; R2 := U0
  2 [-]: SELF      R2 R2 K0     ; R3 := R2; R2 := R2["0xF3EC2EB3"]
  3 [-]: MOVE      R4 R0        ; R4 := R0
  4 [-]: CALL      R2 3 2       ; R2 := R2(R3,R4)
  5 [-]: GETGLOBAL R3 K1        ; R3 := mMovie
  6 [-]: SELF      R3 R3 K2     ; R4 := R3; R3 := R3["0x880196A7"]
  7 [-]: GETTABLE  R5 R0 K3     ; R5 := R0["mClipName"]
  8 [-]: LOADK     R6 K4        ; R6 := "Icon"
  9 [-]: LOADK     R7 K5        ; R7 := "_alpha"
 10 [-]: MOVE      R8 R2        ; R8 := R2
 11 [-]: CALL      R3 6 1       ; R3(R4,R5,R6,R7,R8)
 12 [-]: GETGLOBAL R3 K1        ; R3 := mMovie
 13 [-]: SELF      R3 R3 K2     ; R4 := R3; R3 := R3["0x880196A7"]
 14 [-]: GETTABLE  R5 R0 K3     ; R5 := R0["mClipName"]
 15 [-]: LOADK     R6 K4        ; R6 := "Icon"
 16 [-]: LOADK     R7 K6        ; R7 := "_color"
 17 [-]: GETUPVAL  R8 U1        ; R8 := U1
 18 [-]: GETTABLE  R8 R8 K7     ; R8 := R8["0xF81722A2"]
 19 [-]: GETTABLE  R9 R0 K8     ; R9 := R0["mIsCorrectOne"]
 20 [-]: TEST      R9 0         ; if not R9 then PC := 23
 21 [-]: JMP       23           ; PC := 23
 22 [-]: GETUPVAL  R9 U2        ; R9 := U2
 23 [-]: LOADK     R10 K9       ; R10 := 5695743
 24 [-]: LOADK     R11 K10      ; R11 := 15125356
 25 [-]: CALL      R8 4 0       ; R8,... := R8(R9,R10,R11)
 26 [-]: CALL      R3 0 1       ; R3(R4,...)
 27 [-]: GETGLOBAL R3 K1        ; R3 := mMovie
 28 [-]: SELF      R3 R3 K2     ; R4 := R3; R3 := R3["0x880196A7"]
 29 [-]: GETTABLE  R5 R0 K3     ; R5 := R0["mClipName"]
 30 [-]: LOADK     R6 K11       ; R6 := "BackerIcon"
 31 [-]: LOADK     R7 K5        ; R7 := "_alpha"
 32 [-]: LOADK     R8 K12       ; R8 := 4
 33 [-]: CALL      R3 6 1       ; R3(R4,R5,R6,R7,R8)
 34 [-]: GETGLOBAL R3 K1        ; R3 := mMovie
 35 [-]: SELF      R3 R3 K2     ; R4 := R3; R3 := R3["0x880196A7"]
 36 [-]: GETTABLE  R5 R0 K3     ; R5 := R0["mClipName"]
 37 [-]: LOADK     R6 K11       ; R6 := "BackerIcon"
 38 [-]: LOADK     R7 K13       ; R7 := "_z"
 39 [-]: LOADK     R8 K14       ; R8 := -2000
 40 [-]: CALL      R3 6 1       ; R3(R4,R5,R6,R7,R8)
 41 [-]: GETGLOBAL R3 K1        ; R3 := mMovie
 42 [-]: SELF      R3 R3 K2     ; R4 := R3; R3 := R3["0x880196A7"]
 43 [-]: GETTABLE  R5 R0 K3     ; R5 := R0["mClipName"]
 44 [-]: LOADK     R6 K15       ; R6 := "HiddenIcon"
 45 [-]: LOADK     R7 K6        ; R7 := "_color"
 46 [-]: GETGLOBAL R8 K16       ; R8 := _G
 47 [-]: GETTABLE  R8 R8 K17    ; R8 := R8["UIColor_White"]
 48 [-]: CALL      R3 6 1       ; R3(R4,R5,R6,R7,R8)
 49 [-]: GETGLOBAL R3 K1        ; R3 := mMovie
 50 [-]: SELF      R3 R3 K18    ; R4 := R3; R3 := R3["0x4443A5E7"]
 51 [-]: GETTABLE  R5 R0 K3     ; R5 := R0["mClipName"]
 52 [-]: LOADK     R6 K19       ; R6 := ".BackerIcon"
 53 [-]: CONCAT    R5 R5 R6     ; R5 := R5 .. R6
 54 [-]: GETTABLE  R6 R0 K20    ; R6 := R0["mIcon"]
 55 [-]: GETGLOBAL R7 K21       ; R7 := glyphBackerMaterial
 56 [-]: CALL      R3 5 1       ; R3(R4,R5,R6,R7)
 57 [-]: GETGLOBAL R3 K1        ; R3 := mMovie
 58 [-]: SELF      R3 R3 K18    ; R4 := R3; R3 := R3["0x4443A5E7"]
 59 [-]: GETTABLE  R5 R0 K3     ; R5 := R0["mClipName"]
 60 [-]: LOADK     R6 K22       ; R6 := ".Icon"
 61 [-]: CONCAT    R5 R5 R6     ; R5 := R5 .. R6
 62 [-]: GETTABLE  R6 R0 K20    ; R6 := R0["mIcon"]
 63 [-]: GETGLOBAL R7 K23       ; R7 := glyphMaterial
 64 [-]: CALL      R3 5 1       ; R3(R4,R5,R6,R7)
 65 [-]: GETGLOBAL R3 K1        ; R3 := mMovie
 66 [-]: SELF      R3 R3 K18    ; R4 := R3; R3 := R3["0x4443A5E7"]
 67 [-]: GETTABLE  R5 R0 K3     ; R5 := R0["mClipName"]
 68 [-]: LOADK     R6 K24       ; R6 := ".HiddenIcon"
 69 [-]: CONCAT    R5 R5 R6     ; R5 := R5 .. R6
 70 [-]: GETTABLE  R6 R0 K20    ; R6 := R0["mIcon"]
 71 [-]: GETGLOBAL R7 K25       ; R7 := glyphHoverMaterial
 72 [-]: CALL      R3 5 1       ; R3(R4,R5,R6,R7)
 73 [-]: GETGLOBAL R3 K1        ; R3 := mMovie
 74 [-]: SELF      R3 R3 K26    ; R4 := R3; R3 := R3["0x302AAB2F"]
 75 [-]: GETTABLE  R5 R0 K3     ; R5 := R0["mClipName"]
 76 [-]: LOADK     R6 K24       ; R6 := ".HiddenIcon"
 77 [-]: CONCAT    R5 R5 R6     ; R5 := R5 .. R6
 78 [-]: LOADK     R6 K27       ; R6 := "AlphaTestThreshold"
 79 [-]: LOADK     R7 K28       ; R7 := 1
 80 [-]: LOADK     R8 K29       ; R8 := 0
 81 [-]: LOADK     R9 K28       ; R9 := 1
 82 [-]: LOADK     R10 K28      ; R10 := 1
 83 [-]: CALL      R3 8 1       ; R3(R4,R5,R6,R7,R8,R9,R10)
 84 [-]: GETUPVAL  R3 U0        ; R3 := U0
 85 [-]: GETTABLE  R3 R3 K30    ; R3 := R3["0x490928C6"]
 86 [-]: MOVE      R4 R0        ; R4 := R0
 87 [-]: GETGLOBAL R5 K31       ; R5 := 0x8C4A6742
 88 [-]: LOADK     R6 K32       ; R6 := 0.64999997615814
 89 [-]: LOADK     R7 K33       ; R7 := 1.5
 90 [-]: CALL      R5 3 0       ; R5,... := R5(R6,R7)
 91 [-]: CALL      R3 0 1       ; R3(R4,...)
 92 [-]: RETURN    R0 1         ; return 


; Function #6.6:
;
; Name:            
; Defined at line: 174
; #Upvalues:       0
; #Parameters:     2
; Is_vararg:       0
; Max Stack Size:  7

  1 [-]: GETTABLE  R2 R0 K0     ; R2 := R0["mMovie"]
  2 [-]: SELF      R2 R2 K1     ; R3 := R2; R2 := R2["0x1C19D966"]
  3 [-]: GETTABLE  R4 R1 K2     ; R4 := R1["mClipName"]
  4 [-]: LOADK     R5 K3        ; R5 := "_z"
  5 [-]: LOADK     R6 K4        ; R6 := -5000
  6 [-]: CALL      R2 5 1       ; R2(R3,R4,R5,R6)
  7 [-]: RETURN    R0 1         ; return 


; Function #6.7:
;
; Name:            
; Defined at line: 178
; #Upvalues:       0
; #Parameters:     2
; Is_vararg:       0
; Max Stack Size:  6

  1 [-]: NEWTABLE  R2 2 0       ; R2 := {}
  2 [-]: LOADK     R3 K0        ; R3 := "_alpha"
  3 [-]: LOADK     R4 K1        ; R4 := "_z"
  4 [-]: SETLIST   R2 2 1       ; R2[(1-1)*FPF+i] := R(2+i), 1 <= i <= 2
  5 [-]: NEWTABLE  R3 2 0       ; R3 := {}
  6 [-]: LOADK     R4 K2        ; R4 := 100
  7 [-]: LOADK     R5 K3        ; R5 := 0
  8 [-]: SETLIST   R3 2 1       ; R3[(1-1)*FPF+i] := R(3+i), 1 <= i <= 2
  9 [-]: RETURN    R2 3         ; return R2,R3
 10 [-]: RETURN    R0 1         ; return 


; Function #6.8:
;
; Name:            
; Defined at line: 182
; #Upvalues:       1
; #Parameters:     3
; Is_vararg:       0
; Max Stack Size:  10

  1 [-]: GETTABLE  R3 R1 K0     ; R3 := R1["mDepth"]
  2 [-]: TEST      R2 1         ; if R2 then PC := 6
  3 [-]: JMP       6            ; PC := 6
  4 [-]: GETUPVAL  R4 U0        ; R4 := U0
  5 [-]: MUL       R3 R3 R4     ; R3 := R3 * R4
  6 [-]: GETGLOBAL R4 K1        ; R4 := 0x93034B55
  7 [-]: LOADK     R5 K2        ; R5 := 0.25
  8 [-]: LOADK     R6 K3        ; R6 := 1
  9 [-]: GETGLOBAL R7 K4        ; R7 := math
 10 [-]: GETTABLE  R7 R7 K5     ; R7 := R7["0xD6F2D811"]
 11 [-]: MOVE      R8 R3        ; R8 := R3
 12 [-]: LOADK     R9 K6        ; R9 := 0.5
 13 [-]: CALL      R7 3 0       ; R7,... := R7(R8,R9)
 14 [-]: CALL      R4 0 2       ; R4 := R4(R5,...)
 15 [-]: RETURN    R4 2         ; return R4
 16 [-]: RETURN    R0 1         ; return 


; Function #6.9:
;
; Name:            
; Defined at line: 190
; #Upvalues:       2
; #Parameters:     2
; Is_vararg:       0
; Max Stack Size:  11

  1 [-]: GETTABLE  R2 R1 K0     ; R2 := R1["mRectangle"]
  2 [-]: EQ        0 R2 K1      ; if R2 ~= nil then PC := 65
  3 [-]: JMP       65           ; PC := 65
  4 [-]: GETUPVAL  R2 U0        ; R2 := U0
  5 [-]: SELF      R2 R2 K2     ; R3 := R2; R2 := R2["0xF7BBD9F5"]
  6 [-]: MOVE      R4 R1        ; R4 := R1
  7 [-]: CALL      R2 3 2       ; R2 := R2(R3,R4)
  8 [-]: GETUPVAL  R3 U1        ; R3 := U1
  9 [-]: GETTABLE  R3 R3 K3     ; R3 := R3["0xF81722A2"]
 10 [-]: GETTABLE  R4 R1 K4     ; R4 := R1["ScreenX"]
 11 [-]: EQ        0 R4 K1      ; if R4 ~= nil then PC := 14
 12 [-]: JMP       14           ; PC := 14
 13 [-]: MOVE      R4 R0        ; R4 := R0
 14 [-]: MOVE      R4 R1        ; R4 := R1
 15 [-]: GETTABLE  R5 R1 K4     ; R5 := R1["ScreenX"]
 16 [-]: LOADK     R6 K5        ; R6 := 0
 17 [-]: CALL      R3 4 2       ; R3 := R3(R4,R5,R6)
 18 [-]: GETUPVAL  R4 U1        ; R4 := U1
 19 [-]: GETTABLE  R4 R4 K3     ; R4 := R4["0xF81722A2"]
 20 [-]: GETTABLE  R5 R1 K6     ; R5 := R1["ScreenY"]
 21 [-]: EQ        0 R5 K1      ; if R5 ~= nil then PC := 24
 22 [-]: JMP       24           ; PC := 24
 23 [-]: MOVE      R5 R0        ; R5 := R0
 24 [-]: MOVE      R5 R1        ; R5 := R1
 25 [-]: GETTABLE  R6 R1 K6     ; R6 := R1["ScreenY"]
 26 [-]: LOADK     R7 K5        ; R7 := 0
 27 [-]: CALL      R4 4 2       ; R4 := R4(R5,R6,R7)
 28 [-]: GETGLOBAL R5 K7        ; R5 := 0xF595ADDE
 29 [-]: GETGLOBAL R6 K8        ; R6 := mMovie
 30 [-]: SELF      R6 R6 K9     ; R7 := R6; R6 := R6["0x6B7B470B"]
 31 [-]: GETTABLE  R8 R1 K10    ; R8 := R1["mClipName"]
 32 [-]: LOADK     R9 K11       ; R9 := ".Icon"
 33 [-]: CONCAT    R8 R8 R9     ; R8 := R8 .. R9
 34 [-]: LOADK     R9 K12       ; R9 := "_width"
 35 [-]: CALL      R6 4 0       ; R6,... := R6(R7,R8,R9)
 36 [-]: CALL      R5 0 2       ; R5 := R5(R6,...)
 37 [-]: MUL       R5 R5 R2     ; R5 := R5 * R2
 38 [-]: GETGLOBAL R6 K7        ; R6 := 0xF595ADDE
 39 [-]: GETGLOBAL R7 K8        ; R7 := mMovie
 40 [-]: SELF      R7 R7 K9     ; R8 := R7; R7 := R7["0x6B7B470B"]
 41 [-]: GETTABLE  R9 R1 K10    ; R9 := R1["mClipName"]
 42 [-]: LOADK     R10 K11      ; R10 := ".Icon"
 43 [-]: CONCAT    R9 R9 R10    ; R9 := R9 .. R10
 44 [-]: LOADK     R10 K13      ; R10 := "_height"
 45 [-]: CALL      R7 4 0       ; R7,... := R7(R8,R9,R10)
 46 [-]: CALL      R6 0 2       ; R6 := R6(R7,...)
 47 [-]: MUL       R6 R6 R2     ; R6 := R6 * R2
 48 [-]: LOADK     R7 K5        ; R7 := 0
 49 [-]: NEWTABLE  R8 0 4       ; R8 := {}
 50 [-]: MUL       R9 R5 K15    ; R9 := R5 * 0.5
 51 [-]: SUB       R9 R3 R9     ; R9 := R3 - R9
 52 [-]: SUB       R9 R9 R7     ; R9 := R9 - R7
 53 [-]: SETTABLE  R8 K14 R9    ; R8["X"] := R9
 54 [-]: MUL       R9 R6 K15    ; R9 := R6 * 0.5
 55 [-]: SUB       R9 R4 R9     ; R9 := R4 - R9
 56 [-]: SUB       R9 R9 R7     ; R9 := R9 - R7
 57 [-]: SETTABLE  R8 K16 R9    ; R8["Y"] := R9
 58 [-]: MUL       R9 R7 K18    ; R9 := R7 * 2
 59 [-]: ADD       R9 R5 R9     ; R9 := R5 + R9
 60 [-]: SETTABLE  R8 K17 R9    ; R8["Width"] := R9
 61 [-]: MUL       R9 R7 K18    ; R9 := R7 * 2
 62 [-]: ADD       R9 R6 R9     ; R9 := R6 + R9
 63 [-]: SETTABLE  R8 K19 R9    ; R8["Height"] := R9
 64 [-]: SETTABLE  R1 K0 R8     ; R1["mRectangle"] := R8
 65 [-]: GETTABLE  R8 R1 K0     ; R8 := R1["mRectangle"]
 66 [-]: RETURN    R8 2         ; return R8
 67 [-]: RETURN    R0 1         ; return 


; Function #6.10:
;
; Name:            
; Defined at line: 205
; #Upvalues:       5
; #Parameters:     2
; Is_vararg:       0
; Max Stack Size:  11

  1 [-]: GETTABLE  R2 R1 K0     ; R2 := R1["mDepth"]
  2 [-]: GETUPVAL  R3 U0        ; R3 := U0
  3 [-]: MUL       R2 R2 R3     ; R2 := R2 * R3
  4 [-]: GETTABLE  R3 R1 K1     ; R3 := R1["ScreenX"]
  5 [-]: GETUPVAL  R4 U1        ; R4 := U1
  6 [-]: SELF      R4 R4 K2     ; R5 := R4; R4 := R4["0xC4E503B0"]
  7 [-]: CALL      R4 2 2       ; R4 := R4(R5)
  8 [-]: GETUPVAL  R5 U2        ; R5 := U2
  9 [-]: UNM       R5 R5        ; R5 := - R5
 10 [-]: MUL       R4 R4 R5     ; R4 := R4 * R5
 11 [-]: MUL       R4 R4 R2     ; R4 := R4 * R2
 12 [-]: ADD       R3 R3 R4     ; R3 := R3 + R4
 13 [-]: GETTABLE  R4 R1 K3     ; R4 := R1["ScreenY"]
 14 [-]: GETUPVAL  R5 U3        ; R5 := U3
 15 [-]: SELF      R5 R5 K2     ; R6 := R5; R5 := R5["0xC4E503B0"]
 16 [-]: CALL      R5 2 2       ; R5 := R5(R6)
 17 [-]: GETUPVAL  R6 U4        ; R6 := U4
 18 [-]: UNM       R6 R6        ; R6 := - R6
 19 [-]: MUL       R5 R5 R6     ; R5 := R5 * R6
 20 [-]: MUL       R5 R5 R2     ; R5 := R5 * R2
 21 [-]: ADD       R4 R4 R5     ; R4 := R4 + R5
 22 [-]: GETGLOBAL R5 K4        ; R5 := mMovie
 23 [-]: SELF      R5 R5 K5     ; R6 := R5; R5 := R5["0x1C19D966"]
 24 [-]: GETTABLE  R7 R1 K6     ; R7 := R1["mClipName"]
 25 [-]: LOADK     R8 K7        ; R8 := "_x"
 26 [-]: MOVE      R9 R3        ; R9 := R3
 27 [-]: CALL      R5 5 1       ; R5(R6,R7,R8,R9)
 28 [-]: GETGLOBAL R5 K4        ; R5 := mMovie
 29 [-]: SELF      R5 R5 K5     ; R6 := R5; R5 := R5["0x1C19D966"]
 30 [-]: GETTABLE  R7 R1 K6     ; R7 := R1["mClipName"]
 31 [-]: LOADK     R8 K8        ; R8 := "_y"
 32 [-]: MOVE      R9 R4        ; R9 := R4
 33 [-]: CALL      R5 5 1       ; R5(R6,R7,R8,R9)
 34 [-]: GETTABLE  R5 R1 K9     ; R5 := R1["mIsCorrectOne"]
 35 [-]: TEST      R5 0         ; if not R5 then PC := 51
 36 [-]: JMP       51           ; PC := 51
 37 [-]: GETGLOBAL R5 K4        ; R5 := mMovie
 38 [-]: SELF      R5 R5 K5     ; R6 := R5; R5 := R5["0x1C19D966"]
 39 [-]: LOADK     R7 K10       ; R7 := "Info"
 40 [-]: LOADK     R8 K7        ; R8 := "_x"
 41 [-]: ADD       R9 R3 K11    ; R9 := R3 + 30
 42 [-]: MUL       R10 K12 R2   ; R10 := 60 * R2
 43 [-]: ADD       R9 R9 R10    ; R9 := R9 + R10
 44 [-]: CALL      R5 5 1       ; R5(R6,R7,R8,R9)
 45 [-]: GETGLOBAL R5 K4        ; R5 := mMovie
 46 [-]: SELF      R5 R5 K5     ; R6 := R5; R5 := R5["0x1C19D966"]
 47 [-]: LOADK     R7 K10       ; R7 := "Info"
 48 [-]: LOADK     R8 K8        ; R8 := "_y"
 49 [-]: MOVE      R9 R4        ; R9 := R4
 50 [-]: CALL      R5 5 1       ; R5(R6,R7,R8,R9)
 51 [-]: RETURN    R0 1         ; return 


; Function #6.11:
;
; Name:            
; Defined at line: 219
; #Upvalues:       4
; #Parameters:     2
; Is_vararg:       0
; Max Stack Size:  14

  1 [-]: GETGLOBAL R2 K0        ; R2 := mMovie
  2 [-]: SELF      R2 R2 K1     ; R3 := R2; R2 := R2["0xF3E132E0"]
  3 [-]: CALL      R2 2 2       ; R2 := R2(R3)
  4 [-]: GETGLOBAL R3 K0        ; R3 := mMovie
  5 [-]: SELF      R3 R3 K2     ; R4 := R3; R3 := R3["0x68998E7D"]
  6 [-]: CALL      R3 2 2       ; R3 := R3(R4)
  7 [-]: MUL       R4 R2 K3     ; R4 := R2 * 0.5
  8 [-]: MUL       R5 R3 K3     ; R5 := R3 * 0.5
  9 [-]: MUL       R2 R2 K4     ; R2 := R2 * 0.30000001192093
 10 [-]: MUL       R3 R3 K5     ; R3 := R3 * 0.40000000596046
 11 [-]: GETTABLE  R6 R1 K6     ; R6 := R1["mDepth"]
 12 [-]: GETUPVAL  R7 U0        ; R7 := U0
 13 [-]: MUL       R6 R6 R7     ; R6 := R6 * R7
 14 [-]: GETUPVAL  R7 U1        ; R7 := U1
 15 [-]: SELF      R7 R7 K7     ; R8 := R7; R7 := R7["0xF7BBD9F5"]
 16 [-]: MOVE      R9 R1        ; R9 := R1
 17 [-]: CALL      R7 3 2       ; R7 := R7(R8,R9)
 18 [-]: MUL       R7 R7 K8     ; R7 := R7 * 100
 19 [-]: LOADK     R8 K8        ; R8 := 100
 20 [-]: GETUPVAL  R9 U2        ; R9 := U2
 21 [-]: TEST      R9 0         ; if not R9 then PC := 43
 22 [-]: JMP       43           ; PC := 43
 23 [-]: GETTABLE  R9 R1 K9     ; R9 := R1["mIsCorrectOne"]
 24 [-]: TEST      R9 0         ; if not R9 then PC := 41
 25 [-]: JMP       41           ; PC := 41
 26 [-]: GETUPVAL  R9 U3        ; R9 := U3
 27 [-]: TEST      R9 0         ; if not R9 then PC := 41
 28 [-]: JMP       41           ; PC := 41
 29 [-]: GETUPVAL  R9 U1        ; R9 := U1
 30 [-]: SELF      R9 R9 K7     ; R10 := R9; R9 := R9["0xF7BBD9F5"]
 31 [-]: MOVE      R11 R1       ; R11 := R1
 32 [-]: MOVE      R12 R1       ; R12 := R1
 33 [-]: CALL      R9 4 2       ; R9 := R9(R10,R11,R12)
 34 [-]: GETUPVAL  R10 U0       ; R10 := U0
 35 [-]: SUB       R10 K10 R10  ; R10 := 1 - R10
 36 [-]: MUL       R10 K11 R10  ; R10 := 1.5 * R10
 37 [-]: ADD       R9 R9 R10    ; R9 := R9 + R10
 38 [-]: MUL       R7 R9 K8     ; R7 := R9 * 100
 39 [-]: LOADK     R8 K8        ; R8 := 100
 40 [-]: JMP       43           ; PC := 43
 41 [-]: GETUPVAL  R9 U0        ; R9 := U0
 42 [-]: MUL       R8 K8 R9     ; R8 := 100 * R9
 43 [-]: GETGLOBAL R9 K0        ; R9 := mMovie
 44 [-]: SELF      R9 R9 K12    ; R10 := R9; R9 := R9["0x1C19D966"]
 45 [-]: GETTABLE  R11 R1 K13   ; R11 := R1["mClipName"]
 46 [-]: LOADK     R12 K14      ; R12 := "_xscale"
 47 [-]: MOVE      R13 R7       ; R13 := R7
 48 [-]: CALL      R9 5 1       ; R9(R10,R11,R12,R13)
 49 [-]: GETGLOBAL R9 K0        ; R9 := mMovie
 50 [-]: SELF      R9 R9 K12    ; R10 := R9; R9 := R9["0x1C19D966"]
 51 [-]: GETTABLE  R11 R1 K13   ; R11 := R1["mClipName"]
 52 [-]: LOADK     R12 K15      ; R12 := "_yscale"
 53 [-]: MOVE      R13 R7       ; R13 := R7
 54 [-]: CALL      R9 5 1       ; R9(R10,R11,R12,R13)
 55 [-]: GETGLOBAL R9 K0        ; R9 := mMovie
 56 [-]: SELF      R9 R9 K12    ; R10 := R9; R9 := R9["0x1C19D966"]
 57 [-]: GETTABLE  R11 R1 K13   ; R11 := R1["mClipName"]
 58 [-]: LOADK     R12 K16      ; R12 := "_alpha"
 59 [-]: MOVE      R13 R8       ; R13 := R8
 60 [-]: CALL      R9 5 1       ; R9(R10,R11,R12,R13)
 61 [-]: GETGLOBAL R9 K17       ; R9 := math
 62 [-]: GETTABLE  R9 R9 K18    ; R9 := R9["pi"]
 63 [-]: MUL       R9 R9 K19    ; R9 := R9 * 0
 64 [-]: GETGLOBAL R10 K17      ; R10 := math
 65 [-]: GETTABLE  R10 R10 K18  ; R10 := R10["pi"]
 66 [-]: MUL       R10 R10 K20  ; R10 := R10 * 6
 67 [-]: GETGLOBAL R11 K17      ; R11 := math
 68 [-]: GETTABLE  R11 R11 K21  ; R11 := R11["0xD6F2D811"]
 69 [-]: GETTABLE  R12 R1 K6    ; R12 := R1["mDepth"]
 70 [-]: LOADK     R13 K3       ; R13 := 0.5
 71 [-]: CALL      R11 3 2      ; R11 := R11(R12,R13)
 72 [-]: MUL       R10 R10 R11  ; R10 := R10 * R11
 73 [-]: ADD       R9 R9 R10    ; R9 := R9 + R10
 74 [-]: GETGLOBAL R10 K17      ; R10 := math
 75 [-]: GETTABLE  R10 R10 K21  ; R10 := R10["0xD6F2D811"]
 76 [-]: MOVE      R11 R6       ; R11 := R6
 77 [-]: LOADK     R12 K22      ; R12 := 0.64999997615814
 78 [-]: CALL      R10 3 2      ; R10 := R10(R11,R12)
 79 [-]: MUL       R10 R10 K10  ; R10 := R10 * 1
 80 [-]: ADD       R10 K19 R10  ; R10 := 0 + R10
 81 [-]: GETGLOBAL R11 K17      ; R11 := math
 82 [-]: GETTABLE  R11 R11 K24  ; R11 := R11["0x96330A01"]
 83 [-]: MOVE      R12 R9       ; R12 := R9
 84 [-]: CALL      R11 2 2      ; R11 := R11(R12)
 85 [-]: MUL       R11 R11 R10  ; R11 := R11 * R10
 86 [-]: MUL       R11 R11 R2   ; R11 := R11 * R2
 87 [-]: ADD       R11 R4 R11   ; R11 := R4 + R11
 88 [-]: SETTABLE  R1 K23 R11   ; R1["ScreenX"] := R11
 89 [-]: GETGLOBAL R11 K17      ; R11 := math
 90 [-]: GETTABLE  R11 R11 K26  ; R11 := R11["0xBB3F1476"]
 91 [-]: MOVE      R12 R9       ; R12 := R9
 92 [-]: CALL      R11 2 2      ; R11 := R11(R12)
 93 [-]: MUL       R11 R11 R10  ; R11 := R11 * R10
 94 [-]: MUL       R11 R11 R3   ; R11 := R11 * R3
 95 [-]: ADD       R11 R5 R11   ; R11 := R5 + R11
 96 [-]: SETTABLE  R1 K25 R11   ; R1["ScreenY"] := R11
 97 [-]: SETTABLE  R1 K27 K28   ; R1["mRectangle"] := nil
 98 [-]: GETUPVAL  R11 U1       ; R11 := U1
 99 [-]: SELF      R11 R11 K29  ; R12 := R11; R11 := R11["0xA07092B3"]
100 [-]: MOVE      R13 R1       ; R13 := R1
101 [-]: CALL      R11 3 1      ; R11(R12,R13)
102 [-]: RETURN    R0 1         ; return 


; Function #6.12:
;
; Name:            
; Defined at line: 253
; #Upvalues:       1
; #Parameters:     1
; Is_vararg:       0
; Max Stack Size:  8

  1 [-]: LOADK     R1 K0        ; R1 := 1
  2 [-]: GETTABLE  R2 R0 K1     ; R2 := R0["mElements"]
  3 [-]: LEN       R2 R2        ; R2 := # R2
  4 [-]: LOADK     R3 K0        ; R3 := 1
  5 [-]: FORPREP   R1 11        ; R1 -= R3; PC := 11
  6 [-]: GETUPVAL  R5 U0        ; R5 := U0
  7 [-]: SELF      R5 R5 K2     ; R6 := R5; R5 := R5["0x72E53A4A"]
  8 [-]: GETTABLE  R7 R0 K1     ; R7 := R0["mElements"]
  9 [-]: GETTABLE  R7 R7 R4     ; R7 := R7[R4]
 10 [-]: CALL      R5 3 1       ; R5(R6,R7)
 11 [-]: FORLOOP   R1 6         ; R1 += R3; if R1 <= R2 then begin PC := 6; R4 := R1 end
 12 [-]: SETTABLE  R0 K3 K4     ; R0["mGlyphspread"] := "0x1"
 13 [-]: RETURN    R0 1         ; return 


; Function #6.13:
;
; Name:            
; Defined at line: 260
; #Upvalues:       0
; #Parameters:     2
; Is_vararg:       0
; Max Stack Size:  11

  1 [-]: LOADK     R2 K0        ; R2 := 1
  2 [-]: GETTABLE  R3 R0 K1     ; R3 := R0["mElements"]
  3 [-]: LEN       R3 R3        ; R3 := # R3
  4 [-]: LOADK     R4 K0        ; R4 := 1
  5 [-]: FORPREP   R2 14        ; R2 -= R4; PC := 14
  6 [-]: GETGLOBAL R6 K2        ; R6 := mMovie
  7 [-]: SELF      R6 R6 K3     ; R7 := R6; R6 := R6["0x1C19D966"]
  8 [-]: GETTABLE  R8 R0 K1     ; R8 := R0["mElements"]
  9 [-]: GETTABLE  R8 R8 R5     ; R8 := R8[R5]
 10 [-]: GETTABLE  R8 R8 K4     ; R8 := R8["mClipName"]
 11 [-]: LOADK     R9 K5        ; R9 := "enabled"
 12 [-]: MOVE      R10 R1       ; R10 := R1
 13 [-]: CALL      R6 5 1       ; R6(R7,R8,R9,R10)
 14 [-]: FORLOOP   R2 6         ; R2 += R4; if R2 <= R3 then begin PC := 6; R5 := R2 end
 15 [-]: RETURN    R0 1         ; return 


; Function #7:
;
; Name:            
; Defined at line: 267
; #Upvalues:       7
; #Parameters:     0
; Is_vararg:       0
; Max Stack Size:  15

  1 [-]: GETUPVAL  R0 U0        ; R0 := U0
  2 [-]: SELF      R0 R0 K0     ; R1 := R0; R0 := R0["0xC51A5C9D"]
  3 [-]: CALL      R0 2 2       ; R0 := R0(R1)
  4 [-]: LT        0 K1 R0      ; if 0 >= R0 then PC := 11
  5 [-]: JMP       11           ; PC := 11
  6 [-]: GETUPVAL  R0 U0        ; R0 := U0
  7 [-]: SELF      R0 R0 K2     ; R1 := R0; R0 := R0["0x7CF71D03"]
  8 [-]: MOVE      R2 R1        ; R2 := R1
  9 [-]: MOVE      R3 R1        ; R3 := R1
 10 [-]: CALL      R0 4 1       ; R0(R1,R2,R3)
 11 [-]: LOADK     R0 K1        ; R0 := 0
 12 [-]: GETUPVAL  R1 U1        ; R1 := U1
 13 [-]: EQ        0 R1 K3      ; if R1 ~= 1 then PC := 17
 14 [-]: JMP       17           ; PC := 17
 15 [-]: LOADK     R0 K4        ; R0 := 10234567
 16 [-]: JMP       26           ; PC := 26
 17 [-]: GETUPVAL  R1 U1        ; R1 := U1
 18 [-]: EQ        0 R1 K5      ; if R1 ~= 2 then PC := 22
 19 [-]: JMP       22           ; PC := 22
 20 [-]: LOADK     R0 K6        ; R0 := 123567
 21 [-]: JMP       26           ; PC := 26
 22 [-]: GETUPVAL  R1 U1        ; R1 := U1
 23 [-]: EQ        0 R1 K7      ; if R1 ~= 3 then PC := 26
 24 [-]: JMP       26           ; PC := 26
 25 [-]: LOADK     R0 K8        ; R0 := 102367
 26 [-]: GETGLOBAL R1 K9        ; R1 := 0x9B21739C
 27 [-]: GETGLOBAL R2 K10       ; R2 := 0xCD597D99
 28 [-]: MOVE      R3 R0        ; R3 := R0
 29 [-]: CALL      R2 2 0       ; R2,... := R2(R3)
 30 [-]: CALL      R1 0 1       ; R1(R2,...)
 31 [-]: NEWTABLE  R1 0 0       ; R1 := {}
 32 [-]: LOADK     R2 K3        ; R2 := 1
 33 [-]: GETUPVAL  R3 U2        ; R3 := U2
 34 [-]: SUB       R3 R3 K3     ; R3 := R3 - 1
 35 [-]: LOADK     R4 K3        ; R4 := 1
 36 [-]: FORPREP   R2 48        ; R2 -= R4; PC := 48
 37 [-]: GETGLOBAL R6 K11       ; R6 := table
 38 [-]: GETTABLE  R6 R6 K12    ; R6 := R6["0xE6450C9D"]
 39 [-]: MOVE      R7 R1        ; R7 := R1
 40 [-]: GETGLOBAL R8 K13       ; R8 := assortedGlyphs
 41 [-]: GETGLOBAL R9 K14       ; R9 := 0x290116D3
 42 [-]: LOADK     R10 K3       ; R10 := 1
 43 [-]: GETGLOBAL R11 K13      ; R11 := assortedGlyphs
 44 [-]: LEN       R11 R11      ; R11 := # R11
 45 [-]: CALL      R9 3 2       ; R9 := R9(R10,R11)
 46 [-]: GETTABLE  R8 R8 R9     ; R8 := R8[R9]
 47 [-]: CALL      R6 3 1       ; R6(R7,R8)
 48 [-]: FORLOOP   R2 37        ; R2 += R4; if R2 <= R3 then begin PC := 37; R5 := R2 end
 49 [-]: GETGLOBAL R6 K14       ; R6 := 0x290116D3
 50 [-]: LOADK     R7 K3        ; R7 := 1
 51 [-]: GETUPVAL  R8 U2        ; R8 := U2
 52 [-]: CALL      R6 3 2       ; R6 := R6(R7,R8)
 53 [-]: MOVE      R6 R3        ; R6 := R3
 54 [-]: GETGLOBAL R6 K11       ; R6 := table
 55 [-]: GETTABLE  R6 R6 K12    ; R6 := R6["0xE6450C9D"]
 56 [-]: MOVE      R7 R1        ; R7 := R1
 57 [-]: GETUPVAL  R8 U3        ; R8 := U3
 58 [-]: GETGLOBAL R9 K15       ; R9 := correctGlpyhs
 59 [-]: GETUPVAL  R10 U1       ; R10 := U1
 60 [-]: GETTABLE  R9 R9 R10    ; R9 := R9[R10]
 61 [-]: CALL      R6 4 1       ; R6(R7,R8,R9)
 62 [-]: LOADK     R6 K3        ; R6 := 1
 63 [-]: LEN       R7 R1        ; R7 := # R1
 64 [-]: LOADK     R8 K3        ; R8 := 1
 65 [-]: FORPREP   R6 83        ; R6 -= R8; PC := 83
 66 [-]: GETUPVAL  R10 U0       ; R10 := U0
 67 [-]: SELF      R10 R10 K16  ; R11 := R10; R10 := R10["0xA77DA8EE"]
 68 [-]: NEWTABLE  R12 0 3      ; R12 := {}
 69 [-]: GETTABLE  R13 R1 R9    ; R13 := R1[R9]
 70 [-]: SETTABLE  R12 K17 R13  ; R12["mIcon"] := R13
 71 [-]: SUB       R13 R9 K3    ; R13 := R9 - 1
 72 [-]: LEN       R14 R1       ; R14 := # R1
 73 [-]: DIV       R13 R13 R14  ; R13 := R13 / R14
 74 [-]: SETTABLE  R12 K18 R13  ; R12["mDepth"] := R13
 75 [-]: GETUPVAL  R13 U3       ; R13 := U3
 76 [-]: EQ        1 R9 R13     ; if R9 == R13 then PC := 79
 77 [-]: JMP       79           ; PC := 79
 78 [-]: MOVE      R13 R0       ; R13 := R0
 79 [-]: MOVE      R13 R1       ; R13 := R1
 80 [-]: SETTABLE  R12 K19 R13  ; R12["mIsCorrectOne"] := R13
 81 [-]: MOVE      R13 R1       ; R13 := R1
 82 [-]: CALL      R10 4 1      ; R10(R11,R12,R13)
 83 [-]: FORLOOP   R6 66        ; R6 += R8; if R6 <= R7 then begin PC := 66; R9 := R6 end
 84 [-]: GETUPVAL  R10 U0       ; R10 := U0
 85 [-]: SELF      R10 R10 K20  ; R11 := R10; R10 := R10["0x6470BAF4"]
 86 [-]: CLOSURE   R12 0        ; R12 := closure(Function #7.1)
 87 [-]: GETUPVAL  R0 U0        ; R0 := U0
 88 [-]: GETUPVAL  R0 U4        ; R0 := U4
 89 [-]: GETUPVAL  R0 U5        ; R0 := U5
 90 [-]: GETUPVAL  R0 U6        ; R0 := U6
 91 [-]: CALL      R10 3 1      ; R10(R11,R12)
 92 [-]: RETURN    R0 1         ; return 


; Function #7.1:
;
; Name:            
; Defined at line: 296
; #Upvalues:       4
; #Parameters:     0
; Is_vararg:       0
; Max Stack Size:  9

  1 [-]: GETUPVAL  R0 U0        ; R0 := U0
  2 [-]: SELF      R0 R0 K0     ; R1 := R0; R0 := R0["0x501F0A32"]
  3 [-]: MOVE      R2 R0        ; R2 := R0
  4 [-]: CALL      R0 3 1       ; R0(R1,R2)
  5 [-]: GETUPVAL  R0 U0        ; R0 := U0
  6 [-]: SELF      R0 R0 K1     ; R1 := R0; R0 := R0["0xD28673BC"]
  7 [-]: CALL      R0 2 1       ; R0(R1)
  8 [-]: GETUPVAL  R0 U1        ; R0 := U1
  9 [-]: GETTABLE  R0 R0 K2     ; R0 := R0["0x25992394"]
 10 [-]: GETGLOBAL R1 K3        ; R1 := transitionInSound
 11 [-]: CALL      R0 2 1       ; R0(R1)
 12 [-]: GETGLOBAL R0 K4        ; R0 := 0x52E17A90
 13 [-]: GETGLOBAL R1 K5        ; R1 := mMovie
 14 [-]: LOADK     R2 K6        ; R2 := "_root"
 15 [-]: GETGLOBAL R3 K7        ; R3 := UISys
 16 [-]: GETTABLE  R3 R3 K8     ; R3 := R3["FlashInstance_SMOOTH_STEP"]
 17 [-]: NEWTABLE  R4 1 0       ; R4 := {}
 18 [-]: CLOSURE   R5 0         ; R5 := closure(Function #7.1.1)
 19 [-]: GETUPVAL  R0 U2        ; R0 := U2
 20 [-]: GETUPVAL  R0 U0        ; R0 := U0
 21 [-]: SETLIST   R4 1 1       ; R4[(1-1)*FPF+i] := R(4+i), 1 <= i <= 1
 22 [-]: NEWTABLE  R5 1 0       ; R5 := {}
 23 [-]: LOADK     R6 K9        ; R6 := 1
 24 [-]: SETLIST   R5 1 1       ; R5[(1-1)*FPF+i] := R(5+i), 1 <= i <= 1
 25 [-]: LOADK     R6 K10       ; R6 := 0.85000002384186
 26 [-]: LOADK     R7 K11       ; R7 := 0
 27 [-]: CLOSURE   R8 1         ; R8 := closure(Function #7.1.2)
 28 [-]: GETUPVAL  R0 U0        ; R0 := U0
 29 [-]: GETUPVAL  R0 U3        ; R0 := U3
 30 [-]: CALL      R0 9 1       ; R0(R1,R2,R3,R4,R5,R6,R7,R8)
 31 [-]: RETURN    R0 1         ; return 


; Function #7.1.1:
;
; Name:            
; Defined at line: 304
; #Upvalues:       2
; #Parameters:     1
; Is_vararg:       0
; Max Stack Size:  3

  1 [-]: MOVE      R0 R0        ; R0 := R0
  2 [-]: GETUPVAL  R1 U1        ; R1 := U1
  3 [-]: SELF      R1 R1 K0     ; R2 := R1; R1 := R1["0xD28673BC"]
  4 [-]: CALL      R1 2 1       ; R1(R2)
  5 [-]: RETURN    R0 1         ; return 


; Function #7.1.2:
;
; Name:            
; Defined at line: 309
; #Upvalues:       2
; #Parameters:     0
; Is_vararg:       0
; Max Stack Size:  11

  1 [-]: GETUPVAL  R0 U0        ; R0 := U0
  2 [-]: SELF      R0 R0 K0     ; R1 := R0; R0 := R0["0x501F0A32"]
  3 [-]: MOVE      R2 R1        ; R2 := R1
  4 [-]: CALL      R0 3 1       ; R0(R1,R2)
  5 [-]: MOVE      R0 R0        ; R0 := R0
  6 [-]: MOVE      R0 R1        ; R0 := R1
  7 [-]: LOADK     R0 K1        ; R0 := 1
  8 [-]: LOADK     R1 K2        ; R1 := 8
  9 [-]: LOADK     R2 K1        ; R2 := 1
 10 [-]: FORPREP   R0 27        ; R0 -= R2; PC := 27
 11 [-]: GETGLOBAL R4 K3        ; R4 := 0x52E17A90
 12 [-]: GETGLOBAL R5 K4        ; R5 := mMovie
 13 [-]: LOADK     R6 K5        ; R6 := "Line"
 14 [-]: MOVE      R7 R3        ; R7 := R3
 15 [-]: LOADK     R8 K6        ; R8 := ".Inner"
 16 [-]: CONCAT    R6 R6 R8     ; R6 := R6 .. R7 .. R8
 17 [-]: GETGLOBAL R7 K7        ; R7 := UISys
 18 [-]: GETTABLE  R7 R7 K8     ; R7 := R7["FlashInstance_SMOOTH_STEP"]
 19 [-]: NEWTABLE  R8 1 0       ; R8 := {}
 20 [-]: LOADK     R9 K9        ; R9 := "_alpha"
 21 [-]: SETLIST   R8 1 1       ; R8[(1-1)*FPF+i] := R(8+i), 1 <= i <= 1
 22 [-]: NEWTABLE  R9 1 0       ; R9 := {}
 23 [-]: LOADK     R10 K10      ; R10 := 30
 24 [-]: SETLIST   R9 1 1       ; R9[(1-1)*FPF+i] := R(9+i), 1 <= i <= 1
 25 [-]: LOADK     R10 K11      ; R10 := 0.20000000298023
 26 [-]: CALL      R4 7 1       ; R4(R5,R6,R7,R8,R9,R10)
 27 [-]: FORLOOP   R0 11        ; R0 += R2; if R0 <= R1 then begin PC := 11; R3 := R0 end
 28 [-]: RETURN    R0 1         ; return 


; Function #8:
;
; Name:            
; Defined at line: 319
; #Upvalues:       1
; #Parameters:     0
; Is_vararg:       0
; Max Stack Size:  2

  1 [-]: GETUPVAL  R0 U0        ; R0 := U0
  2 [-]: GETTABLE  R0 R0 K0     ; R0 := R0["0xEA569929"]
  3 [-]: GETGLOBAL R1 K1        ; R1 := mMovie
  4 [-]: CALL      R0 2 3       ; R0,R1 := R0(R1)
  5 [-]: RETURN    R0 1         ; return 


; Function #9:
;
; Name:            
; Defined at line: 326
; #Upvalues:       4
; #Parameters:     0
; Is_vararg:       0
; Max Stack Size:  14

  1 [-]: GETUPVAL  R0 U0        ; R0 := U0
  2 [-]: MOVE      R1 R0        ; R1 := R0
  3 [-]: MOVE      R2 R1        ; R2 := R1
  4 [-]: CALL      R0 3 1       ; R0(R1,R2)
  5 [-]: LOADK     R0 K0        ; R0 := "/Lotus/Language/Sacrifice/VitruvianPassword_Glyph"
  6 [-]: GETUPVAL  R1 U1        ; R1 := U1
  7 [-]: CONCAT    R0 R0 R1     ; R0 := R0 .. R1
  8 [-]: GETGLOBAL R1 K1        ; R1 := mMovie
  9 [-]: SELF      R1 R1 K2     ; R2 := R1; R1 := R1["0x7E1F26D7"]
 10 [-]: LOADK     R3 K3        ; R3 := "Info.Bg"
 11 [-]: GETGLOBAL R4 K4        ; R4 := _G
 12 [-]: GETTABLE  R4 R4 K5     ; R4 := R4["UIMaterial_RectangleNoDepth"]
 13 [-]: CALL      R1 4 1       ; R1(R2,R3,R4)
 14 [-]: GETUPVAL  R1 U2        ; R1 := U2
 15 [-]: GETTABLE  R1 R1 K6     ; R1 := R1["0xDDA3917C"]
 16 [-]: GETGLOBAL R2 K7        ; R2 := Lotus_Game
 17 [-]: GETTABLE  R2 R2 K8     ; R2 := R2["UIStyle_FloatingContent"]
 18 [-]: MOVE      R3 R1        ; R3 := R1
 19 [-]: CALL      R1 3 2       ; R1 := R1(R2,R3)
 20 [-]: GETUPVAL  R2 U2        ; R2 := U2
 21 [-]: GETTABLE  R2 R2 K6     ; R2 := R2["0xDDA3917C"]
 22 [-]: GETGLOBAL R3 K7        ; R3 := Lotus_Game
 23 [-]: GETTABLE  R3 R3 K9     ; R3 := R3["UIStyle_Background1"]
 24 [-]: MOVE      R4 R1        ; R4 := R1
 25 [-]: CALL      R2 3 2       ; R2 := R2(R3,R4)
 26 [-]: GETUPVAL  R3 U3        ; R3 := U3
 27 [-]: GETTABLE  R3 R3 K10    ; R3 := R3["0x97B78441"]
 28 [-]: MOVE      R4 R2        ; R4 := R2
 29 [-]: CALL      R3 2 2       ; R3 := R3(R4)
 30 [-]: GETUPVAL  R4 U2        ; R4 := U2
 31 [-]: GETTABLE  R4 R4 K6     ; R4 := R4["0xDDA3917C"]
 32 [-]: GETGLOBAL R5 K7        ; R5 := Lotus_Game
 33 [-]: GETTABLE  R5 R5 K11    ; R5 := R5["UIStyle_Background2"]
 34 [-]: MOVE      R6 R1        ; R6 := R1
 35 [-]: CALL      R4 3 2       ; R4 := R4(R5,R6)
 36 [-]: GETUPVAL  R5 U3        ; R5 := U3
 37 [-]: GETTABLE  R5 R5 K10    ; R5 := R5["0x97B78441"]
 38 [-]: MOVE      R6 R4        ; R6 := R4
 39 [-]: CALL      R5 2 2       ; R5 := R5(R6)
 40 [-]: GETGLOBAL R6 K12       ; R6 := 0x8C64AFA9
 41 [-]: GETGLOBAL R7 K1        ; R7 := mMovie
 42 [-]: LOADK     R8 K13       ; R8 := "Info.swapDepths"
 43 [-]: LOADK     R9 K14       ; R9 := 5000
 44 [-]: CALL      R6 4 1       ; R6(R7,R8,R9)
 45 [-]: GETGLOBAL R6 K1        ; R6 := mMovie
 46 [-]: SELF      R6 R6 K15    ; R7 := R6; R6 := R6["0x302AAB2F"]
 47 [-]: LOADK     R8 K3        ; R8 := "Info.Bg"
 48 [-]: LOADK     R9 K16       ; R9 := "RectInnerColor"
 49 [-]: GETTABLE  R10 R3 K17   ; R10 := R3["r"]
 50 [-]: GETTABLE  R11 R3 K18   ; R11 := R3["g"]
 51 [-]: GETTABLE  R12 R3 K19   ; R12 := R3["b"]
 52 [-]: LOADK     R13 K20      ; R13 := 0.89999997615814
 53 [-]: CALL      R6 8 1       ; R6(R7,R8,R9,R10,R11,R12,R13)
 54 [-]: GETGLOBAL R6 K1        ; R6 := mMovie
 55 [-]: SELF      R6 R6 K15    ; R7 := R6; R6 := R6["0x302AAB2F"]
 56 [-]: LOADK     R8 K3        ; R8 := "Info.Bg"
 57 [-]: LOADK     R9 K21       ; R9 := "RectEdgeColor"
 58 [-]: GETTABLE  R10 R5 K17   ; R10 := R5["r"]
 59 [-]: GETTABLE  R11 R5 K18   ; R11 := R5["g"]
 60 [-]: GETTABLE  R12 R5 K19   ; R12 := R5["b"]
 61 [-]: LOADK     R13 K22      ; R13 := 1
 62 [-]: CALL      R6 8 1       ; R6(R7,R8,R9,R10,R11,R12,R13)
 63 [-]: GETGLOBAL R6 K1        ; R6 := mMovie
 64 [-]: SELF      R6 R6 K23    ; R7 := R6; R6 := R6["0x1C19D966"]
 65 [-]: LOADK     R8 K24       ; R8 := "Info.Label"
 66 [-]: LOADK     R9 K25       ; R9 := "textColor"
 67 [-]: MOVE      R10 R1       ; R10 := R1
 68 [-]: CALL      R6 5 1       ; R6(R7,R8,R9,R10)
 69 [-]: GETGLOBAL R6 K1        ; R6 := mMovie
 70 [-]: SELF      R6 R6 K26    ; R7 := R6; R6 := R6["0x17028E8F"]
 71 [-]: LOADK     R8 K27       ; R8 := "Info.Label.text"
 72 [-]: MOVE      R9 R0        ; R9 := R0
 73 [-]: CALL      R6 4 1       ; R6(R7,R8,R9)
 74 [-]: GETGLOBAL R6 K28       ; R6 := 0xF595ADDE
 75 [-]: GETGLOBAL R7 K1        ; R7 := mMovie
 76 [-]: SELF      R7 R7 K29    ; R8 := R7; R7 := R7["0x6B7B470B"]
 77 [-]: LOADK     R9 K24       ; R9 := "Info.Label"
 78 [-]: LOADK     R10 K30      ; R10 := "textWidth"
 79 [-]: CALL      R7 4 0       ; R7,... := R7(R8,R9,R10)
 80 [-]: CALL      R6 0 2       ; R6 := R6(R7,...)
 81 [-]: GETGLOBAL R7 K1        ; R7 := mMovie
 82 [-]: SELF      R7 R7 K23    ; R8 := R7; R7 := R7["0x1C19D966"]
 83 [-]: LOADK     R9 K3        ; R9 := "Info.Bg"
 84 [-]: LOADK     R10 K31      ; R10 := "_width"
 85 [-]: ADD       R11 R6 K32   ; R11 := R6 + 12
 86 [-]: CALL      R7 5 1       ; R7(R8,R9,R10,R11)
 87 [-]: RETURN    R0 1         ; return 


; Function #10:
;
; Name:            
; Defined at line: 349
; #Upvalues:       6
; #Parameters:     0
; Is_vararg:       0
; Max Stack Size:  10

  1 [-]: GETGLOBAL R0 K0        ; R0 := _T
  2 [-]: GETTABLE  R0 R0 K1     ; R0 := R0["0xEFDFBF7E"]
  3 [-]: GETGLOBAL R1 K2        ; R1 := mMovie
  4 [-]: LOADNIL   R2 R2        ; R2 := nil
  5 [-]: GETGLOBAL R3 K3        ; R3 := 0x6B695579
  6 [-]: LOADK     R4 K4        ; R4 := 1
  7 [-]: CALL      R3 2 0       ; R3,... := R3(R4)
  8 [-]: CALL      R0 0 1       ; R0(R1,...)
  9 [-]: GETGLOBAL R0 K0        ; R0 := _T
 10 [-]: GETTABLE  R0 R0 K5     ; R0 := R0["VitruvianPasswordStage"]
 11 [-]: EQ        1 R0 K6      ; if R0 == nil then PC := 16
 12 [-]: JMP       16           ; PC := 16
 13 [-]: GETGLOBAL R0 K0        ; R0 := _T
 14 [-]: GETTABLE  R0 R0 K5     ; R0 := R0["VitruvianPasswordStage"]
 15 [-]: MOVE      R0 R0        ; R0 := R0
 16 [-]: GETGLOBAL R0 K0        ; R0 := _T
 17 [-]: GETTABLE  R0 R0 K7     ; R0 := R0["VitruvianPasswordLocked"]
 18 [-]: EQ        1 R0 K6      ; if R0 == nil then PC := 24
 19 [-]: JMP       24           ; PC := 24
 20 [-]: GETGLOBAL R0 K0        ; R0 := _T
 21 [-]: GETTABLE  R0 R0 K7     ; R0 := R0["VitruvianPasswordLocked"]
 22 [-]: MOVE      R0 R0        ; R0 := R0
 23 [-]: MOVE      R0 R1        ; R0 := R1
 24 [-]: GETUPVAL  R0 U2        ; R0 := U2
 25 [-]: CALL      R0 1 1       ; R0()
 26 [-]: GETGLOBAL R0 K8        ; R0 := 0x400E7765
 27 [-]: GETGLOBAL R1 K2        ; R1 := mMovie
 28 [-]: SELF      R1 R1 K9     ; R2 := R1; R1 := R1["0x4C52612B"]
 29 [-]: CALL      R1 2 0       ; R1,... := R1(R2)
 30 [-]: CALL      R0 0 2       ; R0 := R0(R1,...)
 31 [-]: TEST      R0 0         ; if not R0 then PC := 45
 32 [-]: JMP       45           ; PC := 45
 33 [-]: GETGLOBAL R0 K8        ; R0 := 0x400E7765
 34 [-]: GETGLOBAL R1 K0        ; R1 := _T
 35 [-]: GETTABLE  R1 R1 K10    ; R1 := R1["ShowBackground"]
 36 [-]: CALL      R0 2 2       ; R0 := R0(R1)
 37 [-]: TEST      R0 1         ; if R0 then PC := 45
 38 [-]: JMP       45           ; PC := 45
 39 [-]: GETGLOBAL R0 K0        ; R0 := _T
 40 [-]: GETTABLE  R0 R0 K11    ; R0 := R0["0x17BDDC36"]
 41 [-]: LOADK     R1 K12       ; R1 := 0.25
 42 [-]: LOADNIL   R2 R2        ; R2 := nil
 43 [-]: MOVE      R3 R0        ; R3 := R0
 44 [-]: CALL      R0 4 1       ; R0(R1,R2,R3)
 45 [-]: GETUPVAL  R0 U3        ; R0 := U3
 46 [-]: CALL      R0 1 1       ; R0()
 47 [-]: LOADK     R0 K4        ; R0 := 1
 48 [-]: LOADK     R1 K13       ; R1 := 8
 49 [-]: LOADK     R2 K4        ; R2 := 1
 50 [-]: FORPREP   R0 84        ; R0 -= R2; PC := 84
 51 [-]: LOADK     R4 K14       ; R4 := "Line"
 52 [-]: MOVE      R5 R3        ; R5 := R3
 53 [-]: LOADK     R6 K15       ; R6 := ".Inner"
 54 [-]: CONCAT    R4 R4 R6     ; R4 := R4 .. R5 .. R6
 55 [-]: GETGLOBAL R5 K2        ; R5 := mMovie
 56 [-]: SELF      R5 R5 K16    ; R6 := R5; R5 := R5["0x7E1F26D7"]
 57 [-]: MOVE      R7 R4        ; R7 := R4
 58 [-]: GETGLOBAL R8 K17       ; R8 := lineMaterial
 59 [-]: CALL      R5 4 1       ; R5(R6,R7,R8)
 60 [-]: GETGLOBAL R5 K2        ; R5 := mMovie
 61 [-]: SELF      R5 R5 K18    ; R6 := R5; R5 := R5["0x1C19D966"]
 62 [-]: MOVE      R7 R4        ; R7 := R4
 63 [-]: LOADK     R8 K19       ; R8 := "_width"
 64 [-]: LOADK     R9 K20       ; R9 := 1200
 65 [-]: CALL      R5 5 1       ; R5(R6,R7,R8,R9)
 66 [-]: GETGLOBAL R5 K2        ; R5 := mMovie
 67 [-]: SELF      R5 R5 K18    ; R6 := R5; R5 := R5["0x1C19D966"]
 68 [-]: MOVE      R7 R4        ; R7 := R4
 69 [-]: LOADK     R8 K21       ; R8 := "_height"
 70 [-]: LOADK     R9 K22       ; R9 := 3
 71 [-]: CALL      R5 5 1       ; R5(R6,R7,R8,R9)
 72 [-]: GETGLOBAL R5 K2        ; R5 := mMovie
 73 [-]: SELF      R5 R5 K18    ; R6 := R5; R5 := R5["0x1C19D966"]
 74 [-]: MOVE      R7 R4        ; R7 := R4
 75 [-]: LOADK     R8 K23       ; R8 := "_color"
 76 [-]: LOADK     R9 K24       ; R9 := 16436789
 77 [-]: CALL      R5 5 1       ; R5(R6,R7,R8,R9)
 78 [-]: GETGLOBAL R5 K2        ; R5 := mMovie
 79 [-]: SELF      R5 R5 K18    ; R6 := R5; R5 := R5["0x1C19D966"]
 80 [-]: MOVE      R7 R4        ; R7 := R4
 81 [-]: LOADK     R8 K25       ; R8 := "_alpha"
 82 [-]: LOADK     R9 K26       ; R9 := 0
 83 [-]: CALL      R5 5 1       ; R5(R6,R7,R8,R9)
 84 [-]: FORLOOP   R0 51        ; R0 += R2; if R0 <= R1 then begin PC := 51; R3 := R0 end
 85 [-]: GETUPVAL  R5 U4        ; R5 := U4
 86 [-]: CALL      R5 1 1       ; R5()
 87 [-]: GETUPVAL  R5 U5        ; R5 := U5
 88 [-]: CALL      R5 1 1       ; R5()
 89 [-]: RETURN    R0 1         ; return 


; Function #11:
;
; Name:            
; Defined at line: 381
; #Upvalues:       7
; #Parameters:     0
; Is_vararg:       0
; Max Stack Size:  26

  1 [-]: GETGLOBAL R0 K0        ; R0 := mMovie
  2 [-]: SELF      R0 R0 K1     ; R1 := R0; R0 := R0["0x80D6B1A"]
  3 [-]: GETGLOBAL R2 K2        ; R2 := 0x6306558E
  4 [-]: CALL      R2 1 0       ; R2,... := R2()
  5 [-]: CALL      R0 0 1       ; R0(R1,...)
  6 [-]: GETUPVAL  R0 U0        ; R0 := U0
  7 [-]: EQ        1 R0 K3      ; if R0 == nil then PC := 198
  8 [-]: JMP       198          ; PC := 198
  9 [-]: GETUPVAL  R0 U0        ; R0 := U0
 10 [-]: GETTABLE  R0 R0 K4     ; R0 := R0["mGlyphspread"]
 11 [-]: TEST      R0 0         ; if not R0 then PC := 198
 12 [-]: JMP       198          ; PC := 198
 13 [-]: GETUPVAL  R0 U1        ; R0 := U1
 14 [-]: TEST      R0 1         ; if R0 then PC := 198
 15 [-]: JMP       198          ; PC := 198
 16 [-]: GETGLOBAL R0 K5        ; R0 := 0xF595ADDE
 17 [-]: GETGLOBAL R1 K0        ; R1 := mMovie
 18 [-]: SELF      R1 R1 K6     ; R2 := R1; R1 := R1["0x6B7B470B"]
 19 [-]: LOADK     R3 K7        ; R3 := "_root"
 20 [-]: LOADK     R4 K8        ; R4 := "_xmouse"
 21 [-]: CALL      R1 4 0       ; R1,... := R1(R2,R3,R4)
 22 [-]: CALL      R0 0 2       ; R0 := R0(R1,...)
 23 [-]: GETGLOBAL R1 K5        ; R1 := 0xF595ADDE
 24 [-]: GETGLOBAL R2 K0        ; R2 := mMovie
 25 [-]: SELF      R2 R2 K6     ; R3 := R2; R2 := R2["0x6B7B470B"]
 26 [-]: LOADK     R4 K7        ; R4 := "_root"
 27 [-]: LOADK     R5 K9        ; R5 := "_ymouse"
 28 [-]: CALL      R2 4 0       ; R2,... := R2(R3,R4,R5)
 29 [-]: CALL      R1 0 2       ; R1 := R1(R2,...)
 30 [-]: GETGLOBAL R2 K0        ; R2 := mMovie
 31 [-]: SELF      R2 R2 K10    ; R3 := R2; R2 := R2["0xF3E132E0"]
 32 [-]: CALL      R2 2 2       ; R2 := R2(R3)
 33 [-]: GETGLOBAL R3 K0        ; R3 := mMovie
 34 [-]: SELF      R3 R3 K11    ; R4 := R3; R3 := R3["0x68998E7D"]
 35 [-]: CALL      R3 2 2       ; R3 := R3(R4)
 36 [-]: MUL       R4 R2 K12    ; R4 := R2 * 0.5
 37 [-]: MUL       R5 R3 K12    ; R5 := R3 * 0.5
 38 [-]: LT        0 K13 R0     ; if -1000 >= R0 then PC := 54
 39 [-]: JMP       54           ; PC := 54
 40 [-]: LT        0 K13 R1     ; if -1000 >= R1 then PC := 54
 41 [-]: JMP       54           ; PC := 54
 42 [-]: SUB       R6 R0 R4     ; R6 := R0 - R4
 43 [-]: DIV       R0 R6 R4     ; R0 := R6 / R4
 44 [-]: SUB       R6 R1 R5     ; R6 := R1 - R5
 45 [-]: DIV       R1 R6 R5     ; R1 := R6 / R5
 46 [-]: GETUPVAL  R6 U2        ; R6 := U2
 47 [-]: SELF      R6 R6 K14    ; R7 := R6; R6 := R6["0xDB349344"]
 48 [-]: MOVE      R8 R0        ; R8 := R0
 49 [-]: CALL      R6 3 1       ; R6(R7,R8)
 50 [-]: GETUPVAL  R6 U3        ; R6 := U3
 51 [-]: SELF      R6 R6 K14    ; R7 := R6; R6 := R6["0xDB349344"]
 52 [-]: MOVE      R8 R1        ; R8 := R1
 53 [-]: CALL      R6 3 1       ; R6(R7,R8)
 54 [-]: GETUPVAL  R6 U2        ; R6 := U2
 55 [-]: SELF      R6 R6 K15    ; R7 := R6; R6 := R6["0x8C7099E9"]
 56 [-]: GETGLOBAL R8 K2        ; R8 := 0x6306558E
 57 [-]: CALL      R8 1 0       ; R8,... := R8()
 58 [-]: CALL      R6 0 1       ; R6(R7,...)
 59 [-]: GETUPVAL  R6 U3        ; R6 := U3
 60 [-]: SELF      R6 R6 K15    ; R7 := R6; R6 := R6["0x8C7099E9"]
 61 [-]: GETGLOBAL R8 K2        ; R8 := 0x6306558E
 62 [-]: CALL      R8 1 0       ; R8,... := R8()
 63 [-]: CALL      R6 0 1       ; R6(R7,...)
 64 [-]: GETUPVAL  R6 U2        ; R6 := U2
 65 [-]: SELF      R6 R6 K16    ; R7 := R6; R6 := R6["0xC4E503B0"]
 66 [-]: CALL      R6 2 2       ; R6 := R6(R7)
 67 [-]: MOVE      R0 R6        ; R0 := R6
 68 [-]: GETUPVAL  R6 U3        ; R6 := U3
 69 [-]: SELF      R6 R6 K16    ; R7 := R6; R6 := R6["0xC4E503B0"]
 70 [-]: CALL      R6 2 2       ; R6 := R6(R7)
 71 [-]: MOVE      R1 R6        ; R1 := R6
 72 [-]: LOADK     R6 K17       ; R6 := 1
 73 [-]: GETUPVAL  R7 U0        ; R7 := U0
 74 [-]: GETTABLE  R7 R7 K18    ; R7 := R7["mElements"]
 75 [-]: LEN       R7 R7        ; R7 := # R7
 76 [-]: LOADK     R8 K17       ; R8 := 1
 77 [-]: FORPREP   R6 84        ; R6 -= R8; PC := 84
 78 [-]: GETUPVAL  R10 U0       ; R10 := U0
 79 [-]: SELF      R10 R10 K19  ; R11 := R10; R10 := R10["0xA07092B3"]
 80 [-]: GETUPVAL  R12 U0       ; R12 := U0
 81 [-]: GETTABLE  R12 R12 K18  ; R12 := R12["mElements"]
 82 [-]: GETTABLE  R12 R12 R9   ; R12 := R12[R9]
 83 [-]: CALL      R10 3 1      ; R10(R11,R12)
 84 [-]: FORLOOP   R6 78        ; R6 += R8; if R6 <= R7 then begin PC := 78; R9 := R6 end
 85 [-]: NEWTABLE  R10 0 0      ; R10 := {}
 86 [-]: NEWTABLE  R11 0 2      ; R11 := {}
 87 [-]: GETUPVAL  R12 U4       ; R12 := U4
 88 [-]: MUL       R12 R0 R12   ; R12 := R0 * R12
 89 [-]: SETTABLE  R11 K20 R12  ; R11["X"] := R12
 90 [-]: GETUPVAL  R12 U5       ; R12 := U5
 91 [-]: UNM       R12 R12      ; R12 := - R12
 92 [-]: MUL       R12 R1 R12   ; R12 := R1 * R12
 93 [-]: SETTABLE  R11 K21 R12  ; R11["Y"] := R12
 94 [-]: SETTABLE  R10 K17 R11  ; R10[1] := R11
 95 [-]: NEWTABLE  R11 0 2      ; R11 := {}
 96 [-]: MUL       R12 R2 K12   ; R12 := R2 * 0.5
 97 [-]: GETUPVAL  R13 U4       ; R13 := U4
 98 [-]: MUL       R13 R0 R13   ; R13 := R0 * R13
 99 [-]: ADD       R12 R12 R13  ; R12 := R12 + R13
100 [-]: SETTABLE  R11 K20 R12  ; R11["X"] := R12
101 [-]: GETUPVAL  R12 U5       ; R12 := U5
102 [-]: UNM       R12 R12      ; R12 := - R12
103 [-]: MUL       R12 R1 R12   ; R12 := R1 * R12
104 [-]: SETTABLE  R11 K21 R12  ; R11["Y"] := R12
105 [-]: SETTABLE  R10 K22 R11  ; R10[2] := R11
106 [-]: NEWTABLE  R11 0 2      ; R11 := {}
107 [-]: GETUPVAL  R12 U4       ; R12 := U4
108 [-]: MUL       R12 R0 R12   ; R12 := R0 * R12
109 [-]: ADD       R12 R2 R12   ; R12 := R2 + R12
110 [-]: SETTABLE  R11 K20 R12  ; R11["X"] := R12
111 [-]: GETUPVAL  R12 U5       ; R12 := U5
112 [-]: UNM       R12 R12      ; R12 := - R12
113 [-]: MUL       R12 R1 R12   ; R12 := R1 * R12
114 [-]: SETTABLE  R11 K21 R12  ; R11["Y"] := R12
115 [-]: SETTABLE  R10 K23 R11  ; R10[3] := R11
116 [-]: NEWTABLE  R11 0 2      ; R11 := {}
117 [-]: GETUPVAL  R12 U4       ; R12 := U4
118 [-]: MUL       R12 R0 R12   ; R12 := R0 * R12
119 [-]: ADD       R12 R2 R12   ; R12 := R2 + R12
120 [-]: SETTABLE  R11 K20 R12  ; R11["X"] := R12
121 [-]: MUL       R12 R3 K12   ; R12 := R3 * 0.5
122 [-]: GETUPVAL  R13 U5       ; R13 := U5
123 [-]: UNM       R13 R13      ; R13 := - R13
124 [-]: MUL       R13 R1 R13   ; R13 := R1 * R13
125 [-]: ADD       R12 R12 R13  ; R12 := R12 + R13
126 [-]: SETTABLE  R11 K21 R12  ; R11["Y"] := R12
127 [-]: SETTABLE  R10 K24 R11  ; R10[4] := R11
128 [-]: NEWTABLE  R11 0 2      ; R11 := {}
129 [-]: GETUPVAL  R12 U4       ; R12 := U4
130 [-]: MUL       R12 R0 R12   ; R12 := R0 * R12
131 [-]: ADD       R12 R2 R12   ; R12 := R2 + R12
132 [-]: SETTABLE  R11 K20 R12  ; R11["X"] := R12
133 [-]: GETUPVAL  R12 U5       ; R12 := U5
134 [-]: UNM       R12 R12      ; R12 := - R12
135 [-]: MUL       R12 R1 R12   ; R12 := R1 * R12
136 [-]: ADD       R12 R3 R12   ; R12 := R3 + R12
137 [-]: SETTABLE  R11 K21 R12  ; R11["Y"] := R12
138 [-]: SETTABLE  R10 K25 R11  ; R10[5] := R11
139 [-]: NEWTABLE  R11 0 2      ; R11 := {}
140 [-]: MUL       R12 R2 K12   ; R12 := R2 * 0.5
141 [-]: GETUPVAL  R13 U4       ; R13 := U4
142 [-]: MUL       R13 R0 R13   ; R13 := R0 * R13
143 [-]: ADD       R12 R12 R13  ; R12 := R12 + R13
144 [-]: SETTABLE  R11 K20 R12  ; R11["X"] := R12
145 [-]: GETUPVAL  R12 U5       ; R12 := U5
146 [-]: UNM       R12 R12      ; R12 := - R12
147 [-]: MUL       R12 R1 R12   ; R12 := R1 * R12
148 [-]: ADD       R12 R3 R12   ; R12 := R3 + R12
149 [-]: SETTABLE  R11 K21 R12  ; R11["Y"] := R12
150 [-]: SETTABLE  R10 K26 R11  ; R10[6] := R11
151 [-]: NEWTABLE  R11 0 2      ; R11 := {}
152 [-]: GETUPVAL  R12 U4       ; R12 := U4
153 [-]: MUL       R12 R0 R12   ; R12 := R0 * R12
154 [-]: SETTABLE  R11 K20 R12  ; R11["X"] := R12
155 [-]: GETUPVAL  R12 U5       ; R12 := U5
156 [-]: UNM       R12 R12      ; R12 := - R12
157 [-]: MUL       R12 R1 R12   ; R12 := R1 * R12
158 [-]: ADD       R12 R3 R12   ; R12 := R3 + R12
159 [-]: SETTABLE  R11 K21 R12  ; R11["Y"] := R12
160 [-]: SETTABLE  R10 K27 R11  ; R10[7] := R11
161 [-]: NEWTABLE  R11 0 2      ; R11 := {}
162 [-]: GETUPVAL  R12 U4       ; R12 := U4
163 [-]: MUL       R12 R0 R12   ; R12 := R0 * R12
164 [-]: SETTABLE  R11 K20 R12  ; R11["X"] := R12
165 [-]: MUL       R12 R3 K12   ; R12 := R3 * 0.5
166 [-]: GETUPVAL  R13 U5       ; R13 := U5
167 [-]: UNM       R13 R13      ; R13 := - R13
168 [-]: MUL       R13 R1 R13   ; R13 := R1 * R13
169 [-]: ADD       R12 R12 R13  ; R12 := R12 + R13
170 [-]: SETTABLE  R11 K21 R12  ; R11["Y"] := R12
171 [-]: SETTABLE  R10 K28 R11  ; R10[8] := R11
172 [-]: LOADK     R11 K17      ; R11 := 1
173 [-]: LOADK     R12 K28      ; R12 := 8
174 [-]: LOADK     R13 K17      ; R13 := 1
175 [-]: FORPREP   R11 197      ; R11 -= R13; PC := 197
176 [-]: LOADK     R15 K29      ; R15 := "Line"
177 [-]: MOVE      R16 R14      ; R16 := R14
178 [-]: CONCAT    R15 R15 R16  ; R15 := R15 .. R16
179 [-]: GETGLOBAL R16 K0       ; R16 := mMovie
180 [-]: SELF      R16 R16 K30  ; R17 := R16; R16 := R16["0x1C19D966"]
181 [-]: MOVE      R18 R15      ; R18 := R15
182 [-]: LOADK     R19 K31      ; R19 := "_rotation"
183 [-]: GETUPVAL  R20 U6       ; R20 := U6
184 [-]: GETTABLE  R20 R20 K32  ; R20 := R20["0xBFE096C9"]
185 [-]: GETUPVAL  R21 U6       ; R21 := U6
186 [-]: GETTABLE  R21 R21 K33  ; R21 := R21["0xABA21F2F"]
187 [-]: GETTABLE  R22 R10 R14  ; R22 := R10[R14]
188 [-]: GETTABLE  R22 R22 K20  ; R22 := R22["X"]
189 [-]: GETTABLE  R23 R10 R14  ; R23 := R10[R14]
190 [-]: GETTABLE  R23 R23 K21  ; R23 := R23["Y"]
191 [-]: MOVE      R24 R4       ; R24 := R4
192 [-]: MOVE      R25 R5       ; R25 := R5
193 [-]: CALL      R21 5 0      ; R21,... := R21(R22,R23,R24,R25)
194 [-]: CALL      R20 0 2      ; R20 := R20(R21,...)
195 [-]: ADD       R20 K34 R20  ; R20 := -90 + R20
196 [-]: CALL      R16 5 1      ; R16(R17,R18,R19,R20)
197 [-]: FORLOOP   R11 176      ; R11 += R13; if R11 <= R12 then begin PC := 176; R14 := R11 end
198 [-]: RETURN    R0 1         ; return 


; Function #12:
;
; Name:            
; Defined at line: 424
; #Upvalues:       1
; #Parameters:     1
; Is_vararg:       0
; Max Stack Size:  5

  1 [-]: GETGLOBAL R1 K0        ; R1 := 0x400E7765
  2 [-]: GETUPVAL  R2 U0        ; R2 := U0
  3 [-]: CALL      R1 2 2       ; R1 := R1(R2)
  4 [-]: TEST      R1 1         ; if R1 then PC := 12
  5 [-]: JMP       12           ; PC := 12
  6 [-]: GETUPVAL  R1 U0        ; R1 := U0
  7 [-]: SELF      R1 R1 K1     ; R2 := R1; R1 := R1["0x8ABD6CC8"]
  8 [-]: GETGLOBAL R3 K2        ; R3 := 0xF595ADDE
  9 [-]: MOVE      R4 R0        ; R4 := R0
 10 [-]: CALL      R3 2 0       ; R3,... := R3(R4)
 11 [-]: CALL      R1 0 1       ; R1(R2,...)
 12 [-]: RETURN    R0 1         ; return 


; Function #13:
;
; Name:            
; Defined at line: 430
; #Upvalues:       1
; #Parameters:     1
; Is_vararg:       0
; Max Stack Size:  5

  1 [-]: GETGLOBAL R1 K0        ; R1 := 0x400E7765
  2 [-]: GETUPVAL  R2 U0        ; R2 := U0
  3 [-]: CALL      R1 2 2       ; R1 := R1(R2)
  4 [-]: TEST      R1 1         ; if R1 then PC := 12
  5 [-]: JMP       12           ; PC := 12
  6 [-]: GETUPVAL  R1 U0        ; R1 := U0
  7 [-]: SELF      R1 R1 K1     ; R2 := R1; R1 := R1["0x2176B11E"]
  8 [-]: GETGLOBAL R3 K2        ; R3 := 0xF595ADDE
  9 [-]: MOVE      R4 R0        ; R4 := R0
 10 [-]: CALL      R3 2 0       ; R3,... := R3(R4)
 11 [-]: CALL      R1 0 1       ; R1(R2,...)
 12 [-]: RETURN    R0 1         ; return 


; Function #14:
;
; Name:            
; Defined at line: 436
; #Upvalues:       2
; #Parameters:     1
; Is_vararg:       0
; Max Stack Size:  5

  1 [-]: GETUPVAL  R1 U0        ; R1 := U0
  2 [-]: TEST      R1 1         ; if R1 then PC := 15
  3 [-]: JMP       15           ; PC := 15
  4 [-]: GETGLOBAL R1 K0        ; R1 := 0x400E7765
  5 [-]: GETUPVAL  R2 U1        ; R2 := U1
  6 [-]: CALL      R1 2 2       ; R1 := R1(R2)
  7 [-]: TEST      R1 1         ; if R1 then PC := 15
  8 [-]: JMP       15           ; PC := 15
  9 [-]: GETUPVAL  R1 U1        ; R1 := U1
 10 [-]: SELF      R1 R1 K1     ; R2 := R1; R1 := R1["0x3BC31182"]
 11 [-]: GETGLOBAL R3 K2        ; R3 := 0xF595ADDE
 12 [-]: MOVE      R4 R0        ; R4 := R0
 13 [-]: CALL      R3 2 0       ; R3,... := R3(R4)
 14 [-]: CALL      R1 0 1       ; R1(R2,...)
 15 [-]: RETURN    R0 1         ; return 


